Workbook
Name All_Days: #REF!
Name ARGUS_DAYS_PRICED: #REF!
Name ARGUS_PRICING_DAYS: #REF!
Name BRENT_DAYS_PRICED: #REF!
Name Calendar: #REF!
Name CargoSize: #REF!
Name CMA_Argus_Trading_Days: #REF!
Name CMA_Brent_Trading_Days: #REF!
Name CMA_DAYS_PRICED: #REF!
Name CMA_NYMEX_Trading_Days: #REF!
Name CMA_Platts_Dubai: #REF!
Name CMA_Platts_Euro_Brent_Trading_Days: #REF!
Name CMA_Platts_US_Trading_Days: #REF!
Name CMA_PRICING_DAYS: #REF!
Name Cons_Date: #REF!
Name CostDemK: 'Cargo Data'!$AE$2:$AE$21
Name CostFlag: 'Cost Dashboard'!$C$6
Name CostFreightK: 'Cargo Data'!$AC$2:$AC$21
Name CostInclFlag: 'Cargo Data'!$AJ$2:$AJ$21
Name CostMonth: 'Cost Dashboard'!$C$4
Name CostOtherK: 'Cargo Data'!$AH$2:$AH$21
Name CostSTSK: 'Cargo Data'!$AF$2:$AF$21
Name CostTD7K: 'Cargo Data'!$AD$2:$AD$21
Name CostTotalK: 'Cargo Data'!$AI$2:$AI$21
Name CostTVMK: 'Cargo Data'!$AG$2:$AG$21
Name CostVessel: 'Cost Dashboard'!$C$5
Name Crude: #REF!
Name Crude: #REF!
Name CrudeBenchmarks: #REF!
Name CrudeBenchmarks: #REF!
Name Crudes: #REF!
Name Current_Day: #REF!
Name DateRange: OFFSET(#REF!,0,0,MATCH(TODAY(),#REF!,0),1)
Name DaysInMonth: #REF!
Name DischargePort: #REF!
Name Disports: #REF!
Name EV__LASTREFTIME__: 40738.6979398148
Name FilterFlag: Dashboard!$C$6
Name FilterMonth: Dashboard!$C$4
Name FilterVessel: Dashboard!$C$5
Name FregithTable: #REF!
Name Holidays: #REF!
Name IBrentCurve: '[1]Calendar Management'!#REF!
Name IBrentCurve: '[1]Calendar Management'!#REF!
Name Ledgerdd: Ledger[[#All],[Cargo Name]]
Name Ledgerdd: Ledger[[#All],[Cargo Name]]
Name Ledgerdd: Ledger[[#All],[Cargo Name]]
Name Ledgerdd: Ledger[[#All],[Cargo Name]]
Name Ledgerdd: Ledger[[#All],[Cargo Name]]
Name LIM_START_DATE: #REF!
Name LIM_START_DATE: #REF!
Name LoadPort: #REF!
Name LoadPorts: #REF!
Name MinTonnage: #REF!
Name Mo_Avg_Pricing: #REF!
Name Months: '[1]Calendar Management'!#REF!
Name Months: '[1]Calendar Management'!#REF!
Name MorningStar_As_Of_Date: #REF!
Name MTDRange: OFFSET(#REF!,0,0,MATCH(TODAY(),#REF!,0),1)
Name No_Holiday: #REF!

Sheet Dashboard
B2: CARGO ECONOMICS DASHBOARD — 2026
B3: FILTERS ▼ (use dropdowns)
B4: Load Month | C4: All | E4: Cargoes shown | F4: =SUM(CargoData[Incl]) -> 19
B5: Vessel Class | C5: All
B6: Exclude flagged | C6: Yes
B8: Total Volume (kbbl) | C8: Total Day-1 P&L ($k) | D8: Wtd Avg P&L ($/bbl) | E8: Total Costs ($k) | F8: Avg Cost ($/bbl) | G8: Win Rate
B9: =SUMPRODUCT(CargoData[Incl],CargoData[Volume (kbbl)]) -> 24996 | C9: =SUMPRODUCT(CargoData[Incl],CargoData[Day 1 P&L ($k)]) -> 10767.648 | D9: =IFERROR(C9/B9,0) -> 0.43077483 | E9: =SUMPRODUCT(CargoData[Incl],CargoData[Total Costs ($k)]) -> 164120.47 | F9: =IFERROR(SUMPRODUCT(CargoData[Incl],CargoData[Volume (kbbl)],CargoData[Total Cost ($/bbl)])/B9,0) -> 6.2509164 | G9: {=IFERROR(SUMPRODUCT(CargoData[Incl],--(CargoData[P&L ($/bbl)]>0))/F4,0)} -> 0.84210526
B12: P&L BY LOAD MONTH | H12: P&L BY VESSEL CLASS | AA12: Chart helper: Month | AD12: Chart helper: Vessel
B13: Load Month | C13: Cargoes | D13: Volume (kbbl) | E13: Day-1 P&L ($k) | F13: $/bbl | H13: Vessel Class | I13: Cargoes | J13: Volume (kbbl) | K13: Day-1 P&L ($k) | L13: $/bbl | AA13: Load Month | AB13: Day-1 P&L ($k) | AD13: Vessel Class | AE13: Volume (kbbl)
B14: {=IFERROR(TEXT(_xlfn._xlws.SORT(_xlfn.UNIQUE(_xlfn._xlws.FILTER(CargoData[Load Month],CargoData[Incl]=1))),"mmm-yy"),"")} -> Feb-26 | C14: {=IF($B14="","",SUMPRODUCT((CargoData[Load Mo]=$B14)*CargoData[Incl]))} -> 5 | D14: {=IF($B14="","",SUMPRODUCT((CargoData[Load Mo]=$B14)*CargoData[Incl]*CargoData[Volume (kbbl)]))} -> 4872 | E14: {=IF($B14="","",SUMPRODUCT((CargoData[Load Mo]=$B14)*CargoData[Incl]*CargoData[Day 1 P&L ($k)]))} -> 495.64474 | F14: =IF($B14="","",IFERROR(E14/D14,"")) -> 0.10173332 | H14: {=IFERROR(_xlfn._xlws.SORT(_xlfn.UNIQUE(_xlfn._xlws.FILTER(CargoData[Vessel Class],CargoData[Incl]=1))),"")} -> Aframax | I14: {=IF($H14="","",SUMPRODUCT((CargoData[Vessel Class]=$H14)*CargoData[Incl]))} -> 7 | J14: {=IF($H14="","",SUMPRODUCT((CargoData[Vessel Class]=$H14)*CargoData[Incl]*CargoData[Volume (kbbl)]))} -> 4900 | K14: {=IF($H14="","",SUMPRODUCT((CargoData[Vessel Class]=$H14)*CargoData[Incl]*CargoData[Day 1 P&L ($k)]))} -> 436.10499 | L14: =IF($H14="","",IFERROR(K14/J14,"")) -> 0.089001018 | AA14: =IF($B14="","",$B14) -> Feb-26 | AB14: =IF($B14="",NA(),$E14) -> 495.64474 | AD14: =IF($H14="","",$H14) -> Aframax | AE14: =IF($H14="",NA(),$J14) -> 4900
B15: Mar-26 | C15: {=IF($B15="","",SUMPRODUCT((CargoData[Load Mo]=$B15)*CargoData[Incl]))} -> 3 | D15: {=IF($B15="","",SUMPRODUCT((CargoData[Load Mo]=$B15)*CargoData[Incl]*CargoData[Volume (kbbl)]))} -> 3530 | E15: {=IF($B15="","",SUMPRODUCT((CargoData[Load Mo]=$B15)*CargoData[Incl]*CargoData[Day 1 P&L ($k)]))} -> 873.08655 | F15: =IF($B15="","",IFERROR(E15/D15,"")) -> 0.2473333 | H15: FOB | I15: {=IF($H15="","",SUMPRODUCT((CargoData[Vessel Class]=$H15)*CargoData[Incl]))} -> 4 | J15: {=IF($H15="","",SUMPRODUCT((CargoData[Vessel Class]=$H15)*CargoData[Incl]*CargoData[Volume (kbbl)]))} -> 4000 | K15: {=IF($H15="","",SUMPRODUCT((CargoData[Vessel Class]=$H15)*CargoData[Incl]*CargoData[Day 1 P&L ($k)]))} -> 1122.575 | L15: =IF($H15="","",IFERROR(K15/J15,"")) -> 0.28064375 | AA15: =IF($B15="","",$B15) -> Mar-26 | AB15: =IF($B15="",NA(),$E15) -> 873.08655 | AD15: =IF($H15="","",$H15) -> FOB | AE15: =IF($H15="",NA(),$J15) -> 4000
B16: Apr-26 | C16: {=IF($B16="","",SUMPRODUCT((CargoData[Load Mo]=$B16)*CargoData[Incl]))} -> 4 | D16: {=IF($B16="","",SUMPRODUCT((CargoData[Load Mo]=$B16)*CargoData[Incl]*CargoData[Volume (kbbl)]))} -> 6744 | E16: {=IF($B16="","",SUMPRODUCT((CargoData[Load Mo]=$B16)*CargoData[Incl]*CargoData[Day 1 P&L ($k)]))} -> 886.48 | F16: =IF($B16="","",IFERROR(E16/D16,"")) -> 0.13144721 | H16: VLCC | I16: {=IF($H16="","",SUMPRODUCT((CargoData[Vessel Class]=$H16)*CargoData[Incl]))} -> 8 | J16: {=IF($H16="","",SUMPRODUCT((CargoData[Vessel Class]=$H16)*CargoData[Incl]*CargoData[Volume (kbbl)]))} -> 16096 | K16: {=IF($H16="","",SUMPRODUCT((CargoData[Vessel Class]=$H16)*CargoData[Incl]*CargoData[Day 1 P&L ($k)]))} -> 9208.9677 | L16: =IF($H16="","",IFERROR(K16/J16,"")) -> 0.57212771 | AA16: =IF($B16="","",$B16) -> Apr-26 | AB16: =IF($B16="",NA(),$E16) -> 886.48 | AD16: =IF($H16="","",$H16) -> VLCC | AE16: =IF($H16="",NA(),$J16) -> 16096
B17: May-26 | C17: {=IF($B17="","",SUMPRODUCT((CargoData[Load Mo]=$B17)*CargoData[Incl]))} -> 2 | D17: {=IF($B17="","",SUMPRODUCT((CargoData[Load Mo]=$B17)*CargoData[Incl]*CargoData[Volume (kbbl)]))} -> 4204 | E17: {=IF($B17="","",SUMPRODUCT((CargoData[Load Mo]=$B17)*CargoData[Incl]*CargoData[Day 1 P&L ($k)]))} -> 6396.71 | F17: =IF($B17="","",IFERROR(E17/D17,"")) -> 1.5215771 | I17: {=IF($H17="","",SUMPRODUCT((CargoData[Vessel Class]=$H17)*CargoData[Incl]))} | J17: {=IF($H17="","",SUMPRODUCT((CargoData[Vessel Class]=$H17)*CargoData[Incl]*CargoData[Volume (kbbl)]))} | K17: {=IF($H17="","",SUMPRODUCT((CargoData[Vessel Class]=$H17)*CargoData[Incl]*CargoData[Day 1 P&L ($k)]))} | L17: =IF($H17="","",IFERROR(K17/J17,"")) | AA17: =IF($B17="","",$B17) -> May-26 | AB17: =IF($B17="",NA(),$E17) -> 6396.71 | AD17: =IF($H17="","",$H17) | AE17: =IF($H17="",NA(),$J17) -> #N/A
B18: Jun-26 | C18: {=IF($B18="","",SUMPRODUCT((CargoData[Load Mo]=$B18)*CargoData[Incl]))} -> 5 | D18: {=IF($B18="","",SUMPRODUCT((CargoData[Load Mo]=$B18)*CargoData[Incl]*CargoData[Volume (kbbl)]))} -> 5646 | E18: {=IF($B18="","",SUMPRODUCT((CargoData[Load Mo]=$B18)*CargoData[Incl]*CargoData[Day 1 P&L ($k)]))} -> 2115.7264 | F18: =IF($B18="","",IFERROR(E18/D18,"")) -> 0.37473014 | I18: {=IF($H18="","",SUMPRODUCT((CargoData[Vessel Class]=$H18)*CargoData[Incl]))} | J18: {=IF($H18="","",SUMPRODUCT((CargoData[Vessel Class]=$H18)*CargoData[Incl]*CargoData[Volume (kbbl)]))} | K18: {=IF($H18="","",SUMPRODUCT((CargoData[Vessel Class]=$H18)*CargoData[Incl]*CargoData[Day 1 P&L ($k)]))} | L18: =IF($H18="","",IFERROR(K18/J18,"")) | AA18: =IF($B18="","",$B18) -> Jun-26 | AB18: =IF($B18="",NA(),$E18) -> 2115.7264 | AD18: =IF($H18="","",$H18) | AE18: =IF($H18="",NA(),$J18) -> #N/A
C19: {=IF($B19="","",SUMPRODUCT((CargoData[Load Mo]=$B19)*CargoData[Incl]))} | D19: {=IF($B19="","",SUMPRODUCT((CargoData[Load Mo]=$B19)*CargoData[Incl]*CargoData[Volume (kbbl)]))} | E19: {=IF($B19="","",SUMPRODUCT((CargoData[Load Mo]=$B19)*CargoData[Incl]*CargoData[Day 1 P&L ($k)]))} | F19: =IF($B19="","",IFERROR(E19/D19,"")) | H19: Total | I19: =SUM(I14:I18) -> 19 | J19: =SUM(J14:J18) -> 24996 | K19: =SUM(K14:K18) -> 10767.648 | L19: =IFERROR(K19/J19,"") -> 0.43077483 | AA19: =IF($B19="","",$B19) | AB19: =IF($B19="",NA(),$E19) -> #N/A
B20: Total | C20: =SUM(C14:C19) -> 19 | D20: =SUM(D14:D19) -> 24996 | E20: =SUM(E14:E19) -> 10767.648 | F20: =IFERROR(E20/D20,"") -> 0.43077483
B23: COST BUILD-UP ($/bbl, volume-weighted)
B24: Component | C24: $/bbl
B25: Freight | C25: =IFERROR(SUMPRODUCT(CargoData[Incl],CargoData[Volume (kbbl)],CargoData[Freight])/$B$9,0) -> 5.8558489
B26: TD7 Freight | C26: =IFERROR(SUMPRODUCT(CargoData[Incl],CargoData[Volume (kbbl)],CargoData[TD7 Freight])/$B$9,0) -> -0.17505693
B27: Demurrage | C27: =IFERROR(SUMPRODUCT(CargoData[Incl],CargoData[Volume (kbbl)],CargoData[Demurrage])/$B$9,0) -> 0.090736478
B28: STS | C28: =IFERROR(SUMPRODUCT(CargoData[Incl],CargoData[Volume (kbbl)],CargoData[STS])/$B$9,0) -> 0.17503046
B29: TVM | C29: =IFERROR(SUMPRODUCT(CargoData[Incl],CargoData[Volume (kbbl)],CargoData[TVM])/$B$9,0) -> 0.062050476
B30: Other | C30: =IFERROR(SUMPRODUCT(CargoData[Incl],CargoData[Volume (kbbl)],CargoData[Other])/$B$9,0) -> 0.24230706
B31: Total | C31: =SUM(C25:C30) -> 6.2509164
B34: CARGO DETAIL (filtered)
B35: Load Month | C35: Cargo Name | D35: Deal Number | E35: Vessel | F35: Volume (kbbl) | G35: FOB Corpus (ICE Brent) | H35: Landed | I35: Sold | J35: P&L ($/bbl) | K35: Day-1 P&L ($k) | L35: Flag
B36: {=IFERROR(_xlfn._xlws.SORT(_xlfn._xlws.FILTER(_xlfn.CHOOSECOLS(CargoData[#Data],3,4,5,6,7,12,20,21,22,23,25),CargoData[Incl]=1),10,-1),"No cargoes match the current filters")} -> May-26 | C36: HDO July26 10-20 | D36: ARA26HS00053 | E36: VLCC | F36: 2065 | G36: 5.92 | H36: 22.373438 | I36: 23.98 | J36: 1.6065617 | K36: 3317.55 | L36: OK
B37: May-26 | C37: ENEOS July 20-30 | D37: ENE26HS00007 | E37: VLCC | F37: 2139 | G37: 17.89 | H37: 26.890468 | I37: 28.33 | J37: 1.4395325 | K37: 3079.16 | L37: OK
B38: Apr-26 | C38: HDO FOB APR 7-12 | D38: HDH26HS00001 | E38: FOB | F38: 1900 | G38: -3.6273684 | H38: -1.488 | I38: -0.94875 | J38: 0.53925 | K38: 1024.575 | L38: OK
B39: Jun-26 | C39: HDO Aug26 22-31 DAP | D39: ARA26HS00078 | E39: VLCC | F39: 1422 | G39: -0.34 | H39: 13.755495 | I39: 14.34 | J39: 0.58450518 | K39: 831.16637 | L39: OK
B40: Mar-26 | C40: HDO May 1-10 WTI+WTL | D40: ARA26HS00032 | E40: VLCC | F40: 2130 | G40: -1.85 | H40: 6.3077999 | I40: 6.68 | J40: 0.37220014 | K40: 792.7863 | L40: OK
B41: Jun-26 | C41: GS Caltex Korea Aug 16-22 | D41: ARA26HS00075 | E41: VLCC | F41: 2124 | G41: 0.17 | H41: 15.352335 | I41: 15.67 | J41: 0.31766478 | K41: 674.72 | L41: OK
B42: Feb-26 | C42: Dangote VLCC March 15-25 | D42: ARA26HS00023 | E42: VLCC | F42: 2072 | G42: -2.31 | H42: 0.83305019 | I42: 1.08 | J42: 0.24694981 | K42: 511.68 | L42: OK
B43: Jun-26 | C43: Jun26 EFP 1 | D43: ARA26HS00069-1 | E43: Aframax | F43: 700 | G43: -6.73 | H43: -0.2806 | I43: 0.03 | J43: 0.3106 | K43: 217.42 | L43: OK
B44: Jun-26 | C44: Jun26 EFP 2 | D44: ARA26HS00069-2 | E44: Aframax | F44: 700 | G44: -6.73 | H44: -0.2806 | I44: 0.03 | J44: 0.3106 | K44: 217.42 | L44: OK
B45: Jun-26 | C45: BP FOB June26 10-15 | D45: BPO26HS00009 | E45: Aframax | F45: 700 | G45: 1.3 | H45: 1.3 | I45: 1.55 | J45: 0.25 | K45: 175 | L45: OK
B46: Mar-26 | C46: April26 EFP 1 | D46: ARA26HS000036 | E46: Aframax | F46: 700 | G46: -4.5 | H46: -0.11471464 | I46: -0.02 | J46: 0.094714643 | K46: 66.30025 | L46: OK
B47: Feb-26 | C47: Gunvor FOB Feb28-01 | D47: GUN26HS00014 | E47: FOB | F47: 700 | G47: -2.61 | H47: -2.61 | I47: -2.55 | J47: 0.06 | K47: 42 | L47: OK
B48: Feb-26 | C48: Gunvor FOB Feb 27-28 STG | D48: GUN26HS00012 | E48: FOB | F48: 700 | G48: -2.96 | H48: -2.96 | I48: -2.9 | J48: 0.06 | K48: 42 | L48: OK
... B54: Apr-26 | C54: May26 EFP 1 | D54: ARA26HS00044 | E54: Aframax | F54: 700 | G54: 3.43 | H54: 3.63 | I54: 3.43 | J54: -0.2 | K54: -140 | L54: OK

Sheet Cost Dashboard
B2: CARGO COST DASHBOARD — 2026
B3: FILTERS ▼
B4: Load Month | C4: All | E4: Cargoes shown | F4: =SUM(CostInclFlag) -> 19
B5: Vessel Class | C5: All
B6: Exclude flagged | C6: Yes
B8: Total Costs ($k) | C8: Total Volume (kbbl) | D8: Avg Cost ($/bbl) | E8: Freight ($k) | F8: Freight % of Costs | G8: TD7 Credit ($k)
B9: =SUMPRODUCT(CostInclFlag,CostTotalK) -> 164120.47 | C9: =SUMPRODUCT(CostInclFlag,CargoData[Volume (kbbl)]) -> 24996 | D9: =IFERROR(B9/C9,0) -> 6.5658694 | E9: =SUMPRODUCT(CostInclFlag,CostFreightK) -> 152244.62 | F9: =IFERROR(E9/B9,0) -> 0.92763941 | G9: =SUMPRODUCT(CostInclFlag,CostTD7K) -> -4375.723
B12: COSTS BY LOAD MONTH ($k)
B13: Load Month | C13: Cargoes | D13: Volume (kbbl) | E13: (+) Freight | F13: (-) TD7 Freight* | G13: (+) Demurrage | H13: (+) STS | I13: (+) TVM | J13: (+) Other | K13: Total Costs ($k) | L13: $/bbl | AA13: Load Month | AB13: Total Costs ($k) | AD13: Component | AE13: Total ($k) | AG13: Load Month | AH13: $/bbl
B14: {=IFERROR(TEXT(_xlfn._xlws.SORT(_xlfn.UNIQUE(_xlfn._xlws.FILTER(CargoData[Load Month],CostInclFlag=1))),"mmm-yy"),"")} -> Feb-26 | C14: {=IF($B14="","",SUMPRODUCT((CargoData[Load Mo]=$B14)*CostInclFlag))} -> 5 | D14: {=IF($B14="","",SUMPRODUCT((CargoData[Load Mo]=$B14)*CostInclFlag*CargoData[Volume (kbbl)]))} -> 4872 | E14: {=IF($B14="","",SUMPRODUCT((CargoData[Load Mo]=$B14)*CostInclFlag*CostFreightK))} -> 7675.452 | F14: {=IF($B14="","",SUMPRODUCT((CargoData[Load Mo]=$B14)*CostInclFlag*CostTD7K))} -> -761.41674 | G14: {=IF($B14="","",SUMPRODUCT((CargoData[Load Mo]=$B14)*CostInclFlag*CostDemK))} -> 160 | H14: {=IF($B14="","",SUMPRODUCT((CargoData[Load Mo]=$B14)*CostInclFlag*CostSTSK))} -> 915 | I14: {=IF($B14="","",SUMPRODUCT((CargoData[Load Mo]=$B14)*CostInclFlag*CostTVMK))} -> 0 | J14: {=IF($B14="","",SUMPRODUCT((CargoData[Load Mo]=$B14)*CostInclFlag*CostOtherK))} -> 1156 | K14: =IF($B14="","",SUM(E14:J14)) -> 9145.0353 | L14: =IF($B14="","",IFERROR(K14/D14,"")) -> 1.8770598 | AA14: =IF($B14="","",$B14) -> Feb-26 | AB14: =IF($B14="",NA(),$K14) -> 9145.0353 | AD14: =$B35 -> (+) Freight | AE14: =$C35 -> 152244.62 | AG14: =IF($B14="","",$B14) -> Feb-26 | AH14: =IF($B14="",NA(),$L14) -> 1.8770598
B15: Mar-26 | C15: {=IF($B15="","",SUMPRODUCT((CargoData[Load Mo]=$B15)*CostInclFlag))} -> 3 | D15: {=IF($B15="","",SUMPRODUCT((CargoData[Load Mo]=$B15)*CostInclFlag*CargoData[Volume (kbbl)]))} -> 3530 | E15: {=IF($B15="","",SUMPRODUCT((CargoData[Load Mo]=$B15)*CostInclFlag*CostFreightK))} -> 18459.991 | F15: {=IF($B15="","",SUMPRODUCT((CargoData[Load Mo]=$B15)*CostInclFlag*CostTD7K))} -> -974.29125 | G15: {=IF($B15="","",SUMPRODUCT((CargoData[Load Mo]=$B15)*CostInclFlag*CostDemK))} -> 160 | H15: {=IF($B15="","",SUMPRODUCT((CargoData[Load Mo]=$B15)*CostInclFlag*CostSTSK))} -> 450 | I15: {=IF($B15="","",SUMPRODUCT((CargoData[Load Mo]=$B15)*CostInclFlag*CostTVMK))} -> 716.0137 | J15: {=IF($B15="","",SUMPRODUCT((CargoData[Load Mo]=$B15)*CostInclFlag*CostOtherK))} -> 420 | K15: =IF($B15="","",SUM(E15:J15)) -> 19231.713 | L15: =IF($B15="","",IFERROR(K15/D15,"")) -> 5.4480775 | AA15: =IF($B15="","",$B15) -> Mar-26 | AB15: =IF($B15="",NA(),$K15) -> 19231.713 | AD15: =$B36 -> (-) TD7 Freight* | AE15: =$C36 -> -4375.723 | AG15: =IF($B15="","",$B15) -> Mar-26 | AH15: =IF($B15="",NA(),$L15) -> 5.4480775
B16: Apr-26 | C16: {=IF($B16="","",SUMPRODUCT((CargoData[Load Mo]=$B16)*CostInclFlag))} -> 4 | D16: {=IF($B16="","",SUMPRODUCT((CargoData[Load Mo]=$B16)*CostInclFlag*CargoData[Volume (kbbl)]))} -> 6744 | E16: {=IF($B16="","",SUMPRODUCT((CargoData[Load Mo]=$B16)*CostInclFlag*CostFreightK))} -> 37440 | F16: {=IF($B16="","",SUMPRODUCT((CargoData[Load Mo]=$B16)*CostInclFlag*CostTD7K))} -> 0 | G16: {=IF($B16="","",SUMPRODUCT((CargoData[Load Mo]=$B16)*CostInclFlag*CostDemK))} -> 480 | H16: {=IF($B16="","",SUMPRODUCT((CargoData[Load Mo]=$B16)*CostInclFlag*CostSTSK))} -> 1275 | I16: {=IF($B16="","",SUMPRODUCT((CargoData[Load Mo]=$B16)*CostInclFlag*CostTVMK))} -> 0 | J16: {=IF($B16="","",SUMPRODUCT((CargoData[Load Mo]=$B16)*CostInclFlag*CostOtherK))} -> 879.295 | K16: =IF($B16="","",SUM(E16:J16)) -> 40074.295 | L16: =IF($B16="","",IFERROR(K16/D16,"")) -> 5.9422146 | AA16: =IF($B16="","",$B16) -> Apr-26 | AB16: =IF($B16="",NA(),$K16) -> 40074.295 | AD16: =$B37 -> (+) Demurrage | AE16: =$C37 -> 2400 | AG16: =IF($B16="","",$B16) -> Apr-26 | AH16: =IF($B16="",NA(),$L16) -> 5.9422146
B17: May-26 | C17: {=IF($B17="","",SUMPRODUCT((CargoData[Load Mo]=$B17)*CostInclFlag))} -> 2 | D17: {=IF($B17="","",SUMPRODUCT((CargoData[Load Mo]=$B17)*CostInclFlag*CargoData[Volume (kbbl)]))} -> 4204 | E17: {=IF($B17="","",SUMPRODUCT((CargoData[Load Mo]=$B17)*CostInclFlag*CostFreightK))} -> 41700 | F17: {=IF($B17="","",SUMPRODUCT((CargoData[Load Mo]=$B17)*CostInclFlag*CostTD7K))} -> 0 | G17: {=IF($B17="","",SUMPRODUCT((CargoData[Load Mo]=$B17)*CostInclFlag*CostDemK))} -> 800 | H17: {=IF($B17="","",SUMPRODUCT((CargoData[Load Mo]=$B17)*CostInclFlag*CostSTSK))} -> 900 | I17: {=IF($B17="","",SUMPRODUCT((CargoData[Load Mo]=$B17)*CostInclFlag*CostTVMK))} -> 835 | J17: {=IF($B17="","",SUMPRODUCT((CargoData[Load Mo]=$B17)*CostInclFlag*CostOtherK))} -> 1311.55 | K17: =IF($B17="","",SUM(E17:J17)) -> 45546.55 | L17: =IF($B17="","",IFERROR(K17/D17,"")) -> 10.834098 | AA17: =IF($B17="","",$B17) -> May-26 | AB17: =IF($B17="",NA(),$K17) -> 45546.55 | AD17: =$B38 -> (+) STS | AE17: =$C38 -> 4540 | AG17: =IF($B17="","",$B17) -> May-26 | AH17: =IF($B17="",NA(),$L17) -> 10.834098
B18: Jun-26 | C18: {=IF($B18="","",SUMPRODUCT((CargoData[Load Mo]=$B18)*CostInclFlag))} -> 5 | D18: {=IF($B18="","",SUMPRODUCT((CargoData[Load Mo]=$B18)*CostInclFlag*CargoData[Volume (kbbl)]))} -> 5646 | E18: {=IF($B18="","",SUMPRODUCT((CargoData[Load Mo]=$B18)*CostInclFlag*CostFreightK))} -> 46969.175 | F18: {=IF($B18="","",SUMPRODUCT((CargoData[Load Mo]=$B18)*CostInclFlag*CostTD7K))} -> -2640.015 | G18: {=IF($B18="","",SUMPRODUCT((CargoData[Load Mo]=$B18)*CostInclFlag*CostDemK))} -> 800 | H18: {=IF($B18="","",SUMPRODUCT((CargoData[Load Mo]=$B18)*CostInclFlag*CostSTSK))} -> 1000 | I18: {=IF($B18="","",SUMPRODUCT((CargoData[Load Mo]=$B18)*CostInclFlag*CostTVMK))} -> 889.71822 | J18: {=IF($B18="","",SUMPRODUCT((CargoData[Load Mo]=$B18)*CostInclFlag*CostOtherK))} -> 3104 | K18: =IF($B18="","",SUM(E18:J18)) -> 50122.878 | L18: =IF($B18="","",IFERROR(K18/D18,"")) -> 8.8775909 | AA18: =IF($B18="","",$B18) -> Jun-26 | AB18: =IF($B18="",NA(),$K18) -> 50122.878 | AD18: =$B39 -> (+) TVM | AE18: =$C39 -> 2440.7319 | AG18: =IF($B18="","",$B18) -> Jun-26 | AH18: =IF($B18="",NA(),$L18) -> 8.8775909
C19: {=IF($B19="","",SUMPRODUCT((CargoData[Load Mo]=$B19)*CostInclFlag))} | D19: {=IF($B19="","",SUMPRODUCT((CargoData[Load Mo]=$B19)*CostInclFlag*CargoData[Volume (kbbl)]))} | E19: {=IF($B19="","",SUMPRODUCT((CargoData[Load Mo]=$B19)*CostInclFlag*CostFreightK))} | F19: {=IF($B19="","",SUMPRODUCT((CargoData[Load Mo]=$B19)*CostInclFlag*CostTD7K))} | G19: {=IF($B19="","",SUMPRODUCT((CargoData[Load Mo]=$B19)*CostInclFlag*CostDemK))} | H19: {=IF($B19="","",SUMPRODUCT((CargoData[Load Mo]=$B19)*CostInclFlag*CostSTSK))} | I19: {=IF($B19="","",SUMPRODUCT((CargoData[Load Mo]=$B19)*CostInclFlag*CostTVMK))} | J19: {=IF($B19="","",SUMPRODUCT((CargoData[Load Mo]=$B19)*CostInclFlag*CostOtherK))} | K19: =IF($B19="","",SUM(E19:J19)) | L19: =IF($B19="","",IFERROR(K19/D19,"")) | AA19: =IF($B19="","",$B19) | AB19: =IF($B19="",NA(),$K19) -> #N/A | AD19: =$B40 -> (+) Other | AE19: =$C40 -> 6870.845 | AG19: =IF($B19="","",$B19) | AH19: =IF($B19="",NA(),$L19) -> #N/A
B20: Total | C20: =SUM(C14:C19) -> 19 | D20: =SUM(D14:D19) -> 24996 | E20: =SUM(E14:E19) -> 152244.62 | F20: =SUM(F14:F19) -> -4375.723 | G20: =SUM(G14:G19) -> 2400 | H20: =SUM(H14:H19) -> 4540 | I20: =SUM(I14:I19) -> 2440.7319 | J20: =SUM(J14:J19) -> 6870.845 | K20: =SUM(K14:K19) -> 164120.47 | L20: =IFERROR(K20/D20,"") -> 6.5658694
B23: COSTS BY VESSEL CLASS ($k)
B24: Vessel Class | C24: Cargoes | D24: Volume (kbbl) | E24: (+) Freight | F24: (-) TD7 Freight* | G24: (+) Demurrage | H24: (+) STS | I24: (+) TVM | J24: (+) Other | K24: Total Costs ($k) | L24: $/bbl
B25: {=IFERROR(_xlfn._xlws.SORT(_xlfn.UNIQUE(_xlfn._xlws.FILTER(CargoData[Vessel Class],CostInclFlag=1))),"")} -> Aframax | C25: {=IF($B25="","",SUMPRODUCT((CargoData[Vessel Class]=$B25)*CostInclFlag))} -> 7 | D25: {=IF($B25="","",SUMPRODUCT((CargoData[Vessel Class]=$B25)*CostInclFlag*CargoData[Volume (kbbl)]))} -> 4900 | E25: {=IF($B25="","",SUMPRODUCT((CargoData[Vessel Class]=$B25)*CostInclFlag*CostFreightK))} -> 18594.618 | F25: {=IF($B25="","",SUMPRODUCT((CargoData[Vessel Class]=$B25)*CostInclFlag*CostTD7K))} -> -4375.723 | G25: {=IF($B25="","",SUMPRODUCT((CargoData[Vessel Class]=$B25)*CostInclFlag*CostDemK))} -> 0 | H25: {=IF($B25="","",SUMPRODUCT((CargoData[Vessel Class]=$B25)*CostInclFlag*CostSTSK))} -> 465 | I25: {=IF($B25="","",SUMPRODUCT((CargoData[Vessel Class]=$B25)*CostInclFlag*CostTVMK))} -> 84 | J25: {=IF($B25="","",SUMPRODUCT((CargoData[Vessel Class]=$B25)*CostInclFlag*CostOtherK))} -> 0 | K25: =IF($B25="","",SUM(E25:J25)) -> 14767.895 | L25: =IF($B25="","",IFERROR(K25/D25,"")) -> 3.0138561
B26: FOB | C26: {=IF($B26="","",SUMPRODUCT((CargoData[Vessel Class]=$B26)*CostInclFlag))} -> 4 | D26: {=IF($B26="","",SUMPRODUCT((CargoData[Vessel Class]=$B26)*CostInclFlag*CargoData[Volume (kbbl)]))} -> 4000 | E26: {=IF($B26="","",SUMPRODUCT((CargoData[Vessel Class]=$B26)*CostInclFlag*CostFreightK))} -> 0 | F26: {=IF($B26="","",SUMPRODUCT((CargoData[Vessel Class]=$B26)*CostInclFlag*CostTD7K))} -> 0 | G26: {=IF($B26="","",SUMPRODUCT((CargoData[Vessel Class]=$B26)*CostInclFlag*CostDemK))} -> 0 | H26: {=IF($B26="","",SUMPRODUCT((CargoData[Vessel Class]=$B26)*CostInclFlag*CostSTSK))} -> 375 | I26: {=IF($B26="","",SUMPRODUCT((CargoData[Vessel Class]=$B26)*CostInclFlag*CostTVMK))} -> 0 | J26: {=IF($B26="","",SUMPRODUCT((CargoData[Vessel Class]=$B26)*CostInclFlag*CostOtherK))} -> 0 | K26: =IF($B26="","",SUM(E26:J26)) -> 375 | L26: =IF($B26="","",IFERROR(K26/D26,"")) -> 0.09375
B27: VLCC | C27: {=IF($B27="","",SUMPRODUCT((CargoData[Vessel Class]=$B27)*CostInclFlag))} -> 8 | D27: {=IF($B27="","",SUMPRODUCT((CargoData[Vessel Class]=$B27)*CostInclFlag*CargoData[Volume (kbbl)]))} -> 16096 | E27: {=IF($B27="","",SUMPRODUCT((CargoData[Vessel Class]=$B27)*CostInclFlag*CostFreightK))} -> 133650 | F27: {=IF($B27="","",SUMPRODUCT((CargoData[Vessel Class]=$B27)*CostInclFlag*CostTD7K))} -> 0 | G27: {=IF($B27="","",SUMPRODUCT((CargoData[Vessel Class]=$B27)*CostInclFlag*CostDemK))} -> 2400 | H27: {=IF($B27="","",SUMPRODUCT((CargoData[Vessel Class]=$B27)*CostInclFlag*CostSTSK))} -> 3700 | I27: {=IF($B27="","",SUMPRODUCT((CargoData[Vessel Class]=$B27)*CostInclFlag*CostTVMK))} -> 2356.7319 | J27: {=IF($B27="","",SUMPRODUCT((CargoData[Vessel Class]=$B27)*CostInclFlag*CostOtherK))} -> 6870.845 | K27: =IF($B27="","",SUM(E27:J27)) -> 148977.58 | L27: =IF($B27="","",IFERROR(K27/D27,"")) -> 9.2555652
C28: {=IF($B28="","",SUMPRODUCT((CargoData[Vessel Class]=$B28)*CostInclFlag))} | D28: {=IF($B28="","",SUMPRODUCT((CargoData[Vessel Class]=$B28)*CostInclFlag*CargoData[Volume (kbbl)]))} | E28: {=IF($B28="","",SUMPRODUCT((CargoData[Vessel Class]=$B28)*CostInclFlag*CostFreightK))} | F28: {=IF($B28="","",SUMPRODUCT((CargoData[Vessel Class]=$B28)*CostInclFlag*CostTD7K))} | G28: {=IF($B28="","",SUMPRODUCT((CargoData[Vessel Class]=$B28)*CostInclFlag*CostDemK))} | H28: {=IF($B28="","",SUMPRODUCT((CargoData[Vessel Class]=$B28)*CostInclFlag*CostSTSK))} | I28: {=IF($B28="","",SUMPRODUCT((CargoData[Vessel Class]=$B28)*CostInclFlag*CostTVMK))} | J28: {=IF($B28="","",SUMPRODUCT((CargoData[Vessel Class]=$B28)*CostInclFlag*CostOtherK))} | K28: =IF($B28="","",SUM(E28:J28)) | L28: =IF($B28="","",IFERROR(K28/D28,""))
C29: {=IF($B29="","",SUMPRODUCT((CargoData[Vessel Class]=$B29)*CostInclFlag))} | D29: {=IF($B29="","",SUMPRODUCT((CargoData[Vessel Class]=$B29)*CostInclFlag*CargoData[Volume (kbbl)]))} | E29: {=IF($B29="","",SUMPRODUCT((CargoData[Vessel Class]=$B29)*CostInclFlag*CostFreightK))} | F29: {=IF($B29="","",SUMPRODUCT((CargoData[Vessel Class]=$B29)*CostInclFlag*CostTD7K))} | G29: {=IF($B29="","",SUMPRODUCT((CargoData[Vessel Class]=$B29)*CostInclFlag*CostDemK))} | H29: {=IF($B29="","",SUMPRODUCT((CargoData[Vessel Class]=$B29)*CostInclFlag*CostSTSK))} | I29: {=IF($B29="","",SUMPRODUCT((CargoData[Vessel Class]=$B29)*CostInclFlag*CostTVMK))} | J29: {=IF($B29="","",SUMPRODUCT((CargoData[Vessel Class]=$B29)*CostInclFlag*CostOtherK))} | K29: =IF($B29="","",SUM(E29:J29)) | L29: =IF($B29="","",IFERROR(K29/D29,""))
B30: Total | C30: =SUM(C25:C29) -> 19 | D30: =SUM(D25:D29) -> 24996 | E30: =SUM(E25:E29) -> 152244.62 | F30: =SUM(F25:F29) -> -4375.723 | G30: =SUM(G25:G29) -> 2400 | H30: =SUM(H25:H29) -> 4540 | I30: =SUM(I25:I29) -> 2440.7319 | J30: =SUM(J25:J29) -> 6870.845 | K30: =SUM(K25:K29) -> 164120.47 | L30: =IFERROR(K30/D30,"") -> 6.5658694
B33: COST MIX — ALL FILTERED CARGOES
B34: Component | C34: Total ($k) | D34: $/bbl | E34: % of Total
B35: (+) Freight | C35: =SUMPRODUCT(CostInclFlag,CostFreightK) -> 152244.62 | D35: =IFERROR(C35/$C$9,0) -> 6.0907592 | E35: =IFERROR(C35/$C$41,0) -> 0.92763941
B36: (-) TD7 Freight* | C36: =SUMPRODUCT(CostInclFlag,CostTD7K) -> -4375.723 | D36: =IFERROR(C36/$C$9,0) -> -0.17505693 | E36: =IFERROR(C36/$C$41,0) -> -0.026661652
B37: (+) Demurrage | C37: =SUMPRODUCT(CostInclFlag,CostDemK) -> 2400 | D37: =IFERROR(C37/$C$9,0) -> 0.096015362 | E37: =IFERROR(C37/$C$41,0) -> 0.014623404
B38: (+) STS | C38: =SUMPRODUCT(CostInclFlag,CostSTSK) -> 4540 | D38: =IFERROR(C38/$C$9,0) -> 0.18162906 | E38: =IFERROR(C38/$C$41,0) -> 0.027662606
B39: (+) TVM | C39: =SUMPRODUCT(CostInclFlag,CostTVMK) -> 2440.7319 | D39: =IFERROR(C39/$C$9,0) -> 0.0976449 | E39: =IFERROR(C39/$C$41,0) -> 0.014871587
B40: (+) Other | C40: =SUMPRODUCT(CostInclFlag,CostOtherK) -> 6870.845 | D40: =IFERROR(C40/$C$9,0) -> 0.27487778 | E40: =IFERROR(C40/$C$41,0) -> 0.041864643
B41: Total Costs | C41: =SUM(C35:C40) -> 164120.47 | D41: =IFERROR(C41/$C$9,0) -> 6.5658694 | E41: =IFERROR(C41/C41,0) -> 1
B42: * TD7 Freight applies only to Brent EFP cargoes
B45: COST DETAIL BY CARGO (filtered, sorted by Total Costs)
B46: Load Month | C46: Cargo Name | D46: Deal Number | E46: Vessel | F46: Volume (kbbl) | G46: (+) Freight | H46: (-) TD7 Freight* | I46: (+) Demurrage | J46: (+) STS | K46: (+) TVM | L46: (+) Other | M46: Total Costs ($k) | N46: $/bbl
B47: {=IFERROR(_xlfn.LET(_xlpm.d,_xlfn.HSTACK(_xlfn.CHOOSECOLS(CargoData[#Data],3,4,5,6,7),CostFreightK,CostTD7K,CostDemK,CostSTSK,CostTVMK,CostOtherK,CostTotalK),_xlpm.f,_xlfn._xlws.FILTER(_xlpm.d,CostInclFlag=1),_xlpm.s,_xlfn._xlws.SORT(_xlpm.f,12,-1),_xlfn.HSTACK(_xlpm.s,IFERROR(_xlfn.CHOOSECOLS(_xlpm.s,12)/_xlfn.CHOOSECOLS(_xlpm.s,5),0))),"No cargoes match the current filters")} -> May-26 | C47: HDO July26 10-20 | D47: ARA26HS00053 | E47: VLCC | F47: 2065 | G47: 25000 | H47: 0 | I47: 400 | J47: 450 | K47: 0 | L47: 444.55 | M47: 26294.55 | N47: 12.733438
B48: Apr-26 | C48: CPC Taiwan June 18-22 | D48: ARA26HS00045 | E48: VLCC | F48: 2065 | G48: 20650 | H48: 0 | I48: 240 | J48: 450 | K48: 0 | L48: 439.6475 | M48: 21779.647 | N48: 10.547045
B49: Jun-26 | C49: HDO Aug26 22-31 DAP | D49: ARA26HS00078 | E49: VLCC | F49: 1422 | G49: 17800 | H49: 0 | I49: 400 | J49: 500 | K49: 0 | L49: 2468 | M49: 21168 | N49: 14.886076
B50: Jun-26 | C50: GS Caltex Korea Aug 16-22 | D50: ARA26HS00075 | E50: VLCC | F50: 2124 | G50: 17500 | H50: 0 | I50: 400 | J50: 500 | K50: 889.71822 | L50: 636 | M50: 19925.718 | N50: 9.3812233
B51: May-26 | C51: ENEOS July 20-30 | D51: ENE26HS00007 | E51: VLCC | F51: 2139 | G51: 16700 | H51: 0 | I51: 400 | J51: 450 | K51: 835 | L51: 867 | M51: 19252 | N51: 9.0004675
B52: Apr-26 | C52: GS Caltex Taiwan May 24-28 | D52: ARA26HS00046 | E52: VLCC | F52: 2079 | G52: 16650 | H52: 0 | I52: 240 | J52: 450 | K52: 0 | L52: 439.6475 | M52: 17779.647 | N52: 8.552019
B53: Mar-26 | C53: HDO May 1-10 WTI+WTL | D53: ARA26HS00032 | E53: VLCC | F53: 2130 | G53: 14500 | H53: 0 | I53: 160 | J53: 450 | K53: 632.0137 | L53: 420 | M53: 16162.014 | N53: 7.5877999
B54: Feb-26 | C54: Dangote VLCC March 15-25 | D54: ARA26HS00023 | E54: VLCC | F54: 2072 | G54: 4850 | H54: 0 | I54: 160 | J54: 450 | K54: 0 | L54: 1156 | M54: 6616 | N54: 3.1930502
B55: Jun-26 | C55: Jun26 EFP 1 | D55: ARA26HS00069-1 | E55: Aframax | F55: 700 | G55: 5834.5875 | H55: -1320.0075 | I55: 0 | J55: 0 | K55: 0 | L55: 0 | M55: 4514.58 | N55: 6.4494
B56: Jun-26 | C56: Jun26 EFP 2 | D56: ARA26HS00069-2 | E56: Aframax | F56: 700 | G56: 5834.5875 | H56: -1320.0075 | I56: 0 | J56: 0 | K56: 0 | L56: 0 | M56: 4514.58 | N56: 6.4494
B57: Mar-26 | C57: April26 EFP 1 | D57: ARA26HS000036 | E57: Aframax | F57: 700 | G57: 3959.991 | H57: -974.29125 | I57: 0 | J57: 0 | K57: 84 | L57: 0 | M57: 3069.6998 | N57: 4.3852854
B58: Feb-26 | C58: Feb26 EFP 1 | D58: ARA26HS00017 | E58: Aframax | F58: 700 | G58: 2825.452 | H58: -761.41674 | I58: 0 | J58: 0 | K58: 0 | L58: 0 | M58: 2064.0353 | N58: 2.9486218
B59: Feb-26 | C59: Vitol CIF CCLZ Feb 17 | D59: VIT26HS00011 | E59: Aframax | F59: 700 | G59: 0 | H59: 0 | I59: 0 | J59: 465 | K59: 0 | L59: 0 | M59: 465 | N59: 0.66428571
... B65: Jun-26 | C65: BP FOB June26 10-15 | D65: BPO26HS00009 | E65: Aframax | F65: 700 | G65: 0 | H65: 0 | I65: 0 | J65: 0 | K65: 0 | L65: 0 | M65: 0 | N65: 0

Sheet Report
F7: Crude Trading Cargoes P&L
F8: ='PnL26'!P1 -> 46265
F10: ='PnL26'!H8 -> 0 | G10: ='PnL26'!I8 -> 0 | I10: =[1]EXPO!AC58 -> 46081 | J10: =[1]EXPO!AD58 -> 46112 | K10: =[1]EXPO!AE58 -> 0 | L10: =[1]EXPO!AF58 -> 0 | M10: =[1]EXPO!AG58 -> 0 | N10: =[1]EXPO!AH58 -> xCrd-Trading Cargoes | O10: =[1]EXPO!AI58 -> 45382 | P10: =[1]EXPO!AJ58 -> 45412 | ... W10: =[1]EXPO!AQ58 -> 45869 | X10: =[1]EXPO!#REF! -> #REF!
F11: ='PnL26'!H9 -> 0 | G11: ='PnL26'!I9 -> 0 | I11: =[1]EXPO!AC59 -> 0 | J11: =[1]EXPO!AD59 -> 0 | K11: =[1]EXPO!AE59 -> 1145.3922 | L11: =[1]EXPO!AF59 -> 1145.3922 | M11: =[1]EXPO!AG59 -> 0 | N11: =[1]EXPO!AH59 -> Nymex WTI | O11: =[1]EXPO!AI59 -> 0 | P11: =[1]EXPO!AJ59 -> 0 | ... W11: =[1]EXPO!AQ59 -> 0 | X11: =[1]EXPO!#REF! -> #REF! | Y11: =[1]EXPO!#REF! -> #REF!
F12: ='PnL26'!H10 -> 0 | G12: ='PnL26'!I10 -> 0 | I12: =[1]EXPO!AC60 -> 0 | J12: =[1]EXPO!AD60 -> 0 | K12: =[1]EXPO!AE60 -> 0 | L12: =[1]EXPO!AF60 -> 0 | M12: =[1]EXPO!AG60 -> 0 | N12: =[1]EXPO!AH60 -> ICE Brent | O12: =[1]EXPO!AI60 -> 0 | P12: =[1]EXPO!AJ60 -> 0 | ... W12: =[1]EXPO!AQ60 -> 0 | X12: =[1]EXPO!#REF! -> #REF! | Y12: =[1]EXPO!#REF! -> #REF!
F13: ='PnL26'!H11 -> 0 | G13: ='PnL26'!I11 -> 0 | I13: =[1]EXPO!AC61 -> 0 | J13: =[1]EXPO!AD61 -> 0 | K13: =[1]EXPO!AE61 -> 0 | L13: =[1]EXPO!AF61 -> 0 | M13: =[1]EXPO!AG61 -> 0 | N13: =[1]EXPO!AH61 -> Platts Dubai | O13: =[1]EXPO!AI61 -> 0 | P13: =[1]EXPO!AJ61 -> 0 | ... W13: =[1]EXPO!AQ61 -> 0 | X13: =[1]EXPO!#REF! -> #REF! | Y13: =[1]EXPO!#REF! -> #REF!
F14: ='PnL26'!H12 -> 0 | G14: ='PnL26'!I12 -> 0 | I14: =[1]EXPO!AC62 -> 0 | J14: =[1]EXPO!AD62 -> 0 | K14: =[1]EXPO!AE62 -> 0 | L14: =[1]EXPO!AF62 -> 0 | M14: =[1]EXPO!AG62 -> 0 | N14: =[1]EXPO!AH62 -> Dated Brent (DFLs) | O14: =[1]EXPO!AI62 -> 0 | P14: =[1]EXPO!AJ62 -> 0 | ... W14: =[1]EXPO!AQ62 -> 0 | X14: =[1]EXPO!#REF! -> #REF! | Y14: =[1]EXPO!#REF! -> #REF!
F15: ='PnL26'!H13 -> 0 | G15: ='PnL26'!I13 -> 0 | I15: =[1]EXPO!AC63 -> 0 | J15: =[1]EXPO!AD63 -> 0 | K15: =[1]EXPO!AE63 -> 1145.3922 | L15: =[1]EXPO!AF63 -> 0 | M15: =[1]EXPO!AG63 -> 0 | N15: =[1]EXPO!AH63 -> Total | O15: =[1]EXPO!AI63 -> 0 | P15: =[1]EXPO!AJ63 -> 0 | ... W15: =[1]EXPO!AQ63 -> 0 | X15: =[1]EXPO!#REF! -> #REF! | Y15: =[1]EXPO!#REF! -> #REF!
F16: ='PnL26'!H14 -> 0 | G16: ='PnL26'!I14 -> 0
F17: ='PnL26'!H15 -> 0 | G17: ='PnL26'!I15 -> 0
F18: ='PnL26'!H16 -> 0 | G18: ='PnL26'!I16 -> 0
F19: ='PnL26'!H17 -> 0 | G19: ='PnL26'!I17 -> 0
F20: ='PnL26'!H18 -> 0 | G20: ='PnL26'!I18 -> 0

Sheet Control
E1: M1 | F1: m2
B2: WTI Sprds | C2: Futures | D2: WTI Sprds | E2: WTI | F2: WTI | G2: Rdam Flat | H2: 21.86
B3: Brent Sprds | C3: Futures | D3: Brent Sprds | E3: Brent | F3: Brent | G3: Min | H3: 70000
B4: WTI-Brent | C4: Swaps | D4: WTI-Brent | E4: WTI | F4: Brent | H4: 185 | N4: Month | S4: Nov/Dec 25 | T4: Expired
B5: DFL | C5: Swaps | D5: Dated | H5: 700000 | N5: 1 | O5: F | S5: Dec/Jan 25 | T5: Expired
B6: Physical | C6: Physical | D6: Physical | H6: =H3*H2*H4/100 -> 2830870 | N6: =+N5+1 -> 2 | O6: G | S6: Apr07-Apr11/Apr 25 | T6: Expired
B7: CFD | C7: Swaps | D7: Dated | H7: =H6/H5 -> 4.0441 | N7: =+N6+1 -> 3 | O7: H | S7: Apr14-Apr18/Apr 25 | T7: Expired
B8: WTI Sprds-Fly | C8: Futures | D8: =D2 -> WTI Sprds | E8: WTI | F8: WTI | N8: =+N7+1 -> 4 | O8: J | S8: Dec 16-20/Dec 24 | T8: Expired
B9: Freight-TD22 | C9: Freight | D9: Freight | N9: =+N8+1 -> 5 | O9: K | S9: Dec 23-27/Dec 24 | T9: Expired
B10: WTI-Brent - EFP | C10: EFP Value | D10: WTI-Brent | N10: =+N9+1 -> 6 | O10: M | S10: Mar03-Mar07/Jan 25 | T10: Expired
B11: Freight-TD25 | C11: Freight | D11: Freight | N11: =+N10+1 -> 7 | O11: N | S11: Mar17-Mar21/Jan 25 | T11: Expired
B12: Freight-TD7 | C12: Freight | D12: Freight | N12: =+N11+1 -> 8 | O12: Q | S12: May19-May23/Jun 25 | T12: Expired
B13: CFD | C13: Swaps | D13: CFD | N13: =+N12+1 -> 9 | O13: U | S13: May19-May23/May 25 | T13: Expired
B14: MEH | C14: Swaps | D14: MEH | N14: =+N13+1 -> 10 | O14: V | S14: Nov/Dec 24 | T14: Expired
B15: Demurrage | C15: Physical | D15: Physical | N15: =+N14+1 -> 11 | O15: X | S15: Dec/Jan 24 | T15: Expired
B16: WTI CMA Diff | C16: Physical | D16: =D8 -> WTI Sprds | N16: =+N15+1 -> 12 | O16: Z | S16: Jan/Feb 25 | T16: Expired
B17: Legacy 2025 | C17: Legacy 2025 | D17: Legacy 2025 | S17: Feb/Mar 25 | T17: Expired
B18: Legacy 2024 | C18: Legacy 2024 | D18: Legacy 2024 | S18: Mar/Apr 25 | T18: Expired
B19: Legacy 2024 | C19: Legacy 2024 | D19: Legacy 2024 | S19: Apr/May 25 | T19: Expired
S20: May/Jun 25 | T20: Expired
S21: Dec 24 | T21: Expired
B22: Expiry Tables | S22: Jan 25 | T22: Expired
B23: WTI Sprds | S23: Feb 25 | T23: Expired
B24: Brent Sprds | S24: Mar 25 | T24: Expired
B25: WTI-Brent | S25: Apr 25 | T25: Expired
B26: Dated | S26: May 25 | T26: Expired
S27: Oct 24 | T27: Expired
B28: Dated | S28: Nov 24 | T28: Expired
B29: WTI Sprds | S29: Jan 23 | T29: Expired
B30: Freight | S30: Sep/Oct 24 | T30: Expired
B31: WTI-Brent | S31: Jan 6-10/Jan 25 | T31: Expired
B32: Freight | S32: Jan 20-24/Jan 25 | T32: Expired
B33: Freight | S33: Jan27-Jan31/Jan 25 | T33: Expired
B34: CFD | S34: Jun 25 | T34: Expired
B35: MEH | S35: Jun/Jul 25 | T35: Expired
B36: Physical | S36: Jul 25 | T36: Expired
B37: WTI Sprds | S37: Jul/Aug 25 | T37: Expired
B38: Legacy 2024 | S38: Aug/Sep 25 | T38: Expired
S39: Sep/Oct 25 | T39: Expired
S40: Oct/Nov 25 | T40: Expired
S41: May05-May09/May 25 | T41: Expired
S42: Aug 25 | T42: Expired
S43: May12-May16/May 25 | T43: Expired
S44: May26-May30/May 25 | T44: Expired
S45: Jun02-Jun06/Jun 25 | T45: Expired
S46: Jun09-Jun13/Jun 25 | T46: Expired
S47: Sep 25 | T47: Expired
S48: Jun16-Jun20/Jun 25 | T48: Expired
S49: Jan 00 | T49: Expired
S50: Oct 25 | T50: Expired
... S65: Apr/May 26 | T65: Active

Sheet Trades 2026 1.14
A1: Cargo Name | B1: Date | C1: Sub-Instrument | D1: Expo Type | E1: Quantity | F1: Month1 | G1: Month2 | H1: Price | I1: Mtm | J1: PnL | K1: Average | L1: Name | M1: Buy/Sell | N1: Average MtM | O1: Instrument Type | P1: Instrument | Q1: Year | R1: Side | S1: Accounting | T1: Trade ID | U1: Phys Active?
A2: Unallocated | B2: 45980 | C2: WTI Sprds | D2: Hedge | E2: -1122 | F2: 45991 | G2: 46022 | H2: 0.5 | I2: 0.5 | J2: 0 | K2: -561 | L2: Nov/Dec 25 | M2: Sell | N2: -561 | O2: Futures | P2: WTI Sprds | Q2: 2025 | R2: Sell | S2: Expired | T2: UnallocatedWTI SprdsHedge-11220.52 | U2: =IFERROR(_xlfn.XLOOKUP(A2,'2025 EOY'!A:A,'2025 EOY'!B:B),"No") -> No
A3: Unallocated | B3: 45980 | C3: WTI Sprds-Fly | D3: Hedge | E3: 1122 | F3: 45991 | G3: 46022 | H3: 0.5 | I3: 0.5 | K3: 213.18 | L3: Nov/Dec 25 | M3: Buy | N3: 561 | O3: Futures | P3: WTI Sprds | Q3: 2025 | R3: Buy | S3: Expired | T3: UnallocatedWTI Sprds-FlyHedge11220.53 | U3: =IFERROR(_xlfn.XLOOKUP(A3,'2025 EOY'!A:A,'2025 EOY'!B:B),"No") -> No
A4: Unallocated | B4: 45980 | C4: WTI Sprds | D4: Hedge | E4: 1122 | F4: 46022 | G4: 46053 | H4: 0.19 | I4: 0.19 | K4: 561 | L4: Dec/Jan 25 | M4: Buy | N4: 213.18 | O4: Futures | P4: WTI Sprds | Q4: 2025 | R4: Buy | S4: Expired | T4: UnallocatedWTI SprdsHedge11220.194 | U4: =IFERROR(_xlfn.XLOOKUP(A4,'2025 EOY'!A:A,'2025 EOY'!B:B),"No") -> No
A5: Unallocated | B5: 45980 | C5: WTI Sprds-Fly | D5: Hedge | E5: -1122 | F5: 46022 | G5: 46053 | H5: 0.19 | I5: 0.19 | J5: 0 | K5: -213.18 | L5: Dec/Jan 25 | M5: Sell | N5: -213.18 | O5: Futures | P5: WTI Sprds | Q5: 2025 | R5: Sell | S5: Expired | T5: UnallocatedWTI Sprds-FlyHedge-11220.195 | U5: =IFERROR(_xlfn.XLOOKUP(A5,'2025 EOY'!A:A,'2025 EOY'!B:B),"No") -> No
A6: Unallocated | B6: 45906 | C6: CFD | D6: Hedge | E6: -500 | F6: Apr07-Apr11 | G6: 45777 | H6: 2.26 | I6: 2.26 | J6: 0 | K6: -1130 | L6: Apr07-Apr11/Apr 25 | M6: Buy | N6: 397.6 | O6: Swaps | P6: Dated | Q6: 2025 | R6: Sell | S6: Expired | T6: UnallocatedCFDHedge-5002.266 | U6: =IFERROR(_xlfn.XLOOKUP(A6,'2025 EOY'!A:A,'2025 EOY'!B:B),"No") -> No
A7: Unallocated | B7: 45906 | C7: CFD | D7: Hedge | E7: 500 | F7: Apr14-Apr18 | G7: 45777 | H7: 1.86 | I7: 1.86 | J7: 0 | K7: 930 | L7: Apr14-Apr18/Apr 25 | M7: Buy | N7: 397.6 | O7: Swaps | P7: Dated | Q7: 2025 | R7: Buy | S7: Expired | T7: UnallocatedCFDHedge5001.867 | U7: =IFERROR(_xlfn.XLOOKUP(A7,'2025 EOY'!A:A,'2025 EOY'!B:B),"No") -> No
A8: Unallocated | B8: 45906 | C8: CFD | D8: Hedge | E8: 400 | F8: Dec 16-20 | G8: 45657 | H8: 0.847 | I8: 0.847 | J8: 0 | K8: 338.8 | L8: Dec 16-20/Dec 24 | M8: Buy | N8: 397.6 | O8: Swaps | P8: Dated | Q8: 2024 | R8: Buy | S8: Expired | T8: UnallocatedCFDHedge4000.8478 | U8: =IFERROR(_xlfn.XLOOKUP(A8,'2025 EOY'!A:A,'2025 EOY'!B:B),"No") -> No
A9: Unallocated | B9: 45906 | C9: CFD | D9: Hedge | E9: 200 | F9: Dec 23-27 | G9: 45657 | H9: -0.09 | I9: -0.09 | J9: 0 | K9: -18 | L9: Dec 23-27/Dec 24 | M9: Buy | N9: 397.6 | O9: Swaps | P9: Dated | Q9: 2024 | R9: Buy | S9: Expired | T9: UnallocatedCFDHedge200-0.099 | U9: =IFERROR(_xlfn.XLOOKUP(A9,'2025 EOY'!A:A,'2025 EOY'!B:B),"No") -> No
A10: Unallocated | B10: 45719 | C10: CFD | D10: Hedge | E10: -200 | F10: Mar03-Mar07 | G10: 45688 | H10: 1.32 | I10: 1.32 | J10: 0 | K10: -264 | L10: Mar03-Mar07/Jan 25 | M10: Sell | N10: -264 | O10: Swaps | P10: Dated | Q10: 2025 | R10: Sell | S10: Expired | T10: UnallocatedCFDHedge-2001.3210 | U10: =IFERROR(_xlfn.XLOOKUP(A10,'2025 EOY'!A:A,'2025 EOY'!B:B),"No") -> No
A11: Unallocated | B11: 45719 | C11: CFD | D11: Hedge | E11: 200 | F11: Mar17-Mar21 | G11: 45688 | H11: 0.54 | I11: 0.54 | J11: 0 | K11: 108 | L11: Mar17-Mar21/Jan 25 | M11: Buy | N11: 108 | O11: Swaps | P11: Dated | Q11: 2025 | R11: Buy | S11: Expired | T11: UnallocatedCFDHedge2000.5411 | U11: =IFERROR(_xlfn.XLOOKUP(A11,'2025 EOY'!A:A,'2025 EOY'!B:B),"No") -> No
A12: Trafi CIF Rdam June 13-17 | B12: 45804 | C12: CFD | D12: Hedge | E12: -1500 | F12: May19-May23 | G12: 45838 | H12: 0.472 | I12: 0.472 | J12: -1.6653345e-13 | K12: -708 | L12: May19-May23/Jun 25 | M12: Sell | N12: -708 | O12: Swaps | P12: Dated | Q12: 2025 | R12: Sell | S12: Expired | T12: Trafi CIF Rdam June 13-17CFDHedge-15000.47212 | U12: =IFERROR(_xlfn.XLOOKUP(A12,'2025 EOY'!A:A,'2025 EOY'!B:B),"No") -> No
A13: Unallocated | B13: 45793 | C13: CFD | D13: Hedge | E13: 1500 | F13: May19-May23 | G13: 45808 | H13: 0.472 | I13: 0.472 | J13: 0 | K13: 708 | L13: May19-May23/May 25 | M13: Buy | N13: 708 | O13: Swaps | P13: Dated | Q13: 2025 | R13: Buy | S13: Expired | T13: UnallocatedCFDHedge15000.47213 | U13: =IFERROR(_xlfn.XLOOKUP(A13,'2025 EOY'!A:A,'2025 EOY'!B:B),"No") -> No
A14: Unallocated | B14: 45727 | C14: WTI Sprds | D14: Hedge | E14: -4289 | F14: 45626 | G14: 45657 | H14: 0.62 | I14: 0.52 | J14: 428.9 | K14: -2659.18 | L14: Nov/Dec 24 | M14: Sell | N14: -2230.28 | O14: Futures | P14: WTI Sprds | Q14: 2024 | R14: Sell | S14: Expired | T14: UnallocatedWTI SprdsHedge-42890.5214 | U14: =IFERROR(_xlfn.XLOOKUP(A14,'2025 EOY'!A:A,'2025 EOY'!B:B),"No") -> No
A15: Jan 1-10 EXTAP VLCC | B15: 45727 | C15: WTI Sprds | D15: Hedge | E15: 1050 | F15: 45626 | G15: 45657 | H15: 0.62 | I15: 0.52 | J15: -105 | K15: 651 | L15: Nov/Dec 24 | M15: Buy | N15: 546 | O15: Futures | P15: WTI Sprds | Q15: 2024 | R15: Buy | S15: Expired | T15: Jan 1-10 EXTAP VLCCWTI SprdsHedge10500.5215 | U15: =IFERROR(_xlfn.XLOOKUP(A15,'2025 EOY'!A:A,'2025 EOY'!B:B),"No") -> No
A16: Jan 4-6 KAL Afra | B16: 45727 | C16: WTI Sprds | D16: Hedge | E16: 707 | F16: 45626 | G16: 45657 | H16: 0.62 | I16: 0.52 | J16: -70.7 | K16: 438.34 | L16: Nov/Dec 24 | M16: Buy | N16: 367.64 | O16: Futures | P16: WTI Sprds | Q16: 2024 | R16: Buy | S16: Expired | T16: Jan 4-6 KAL AfraWTI SprdsHedge7070.5216 | U16: =IFERROR(_xlfn.XLOOKUP(A16,'2025 EOY'!A:A,'2025 EOY'!B:B),"No") -> No
A17: Nov 19-21 Shell Rdam VLCC | B17: 45727 | C17: WTI Sprds | D17: Hedge | E17: 2100 | F17: 45626 | G17: 45657 | H17: 0.62 | I17: 0.52 | J17: -210 | K17: 1302 | L17: Nov/Dec 24 | M17: Buy | N17: 1092 | O17: Futures | P17: WTI Sprds | Q17: 2024 | R17: Buy | S17: Expired | T17: Nov 19-21 Shell Rdam VLCCWTI SprdsHedge21000.5217 | U17: =IFERROR(_xlfn.XLOOKUP(A17,'2025 EOY'!A:A,'2025 EOY'!B:B),"No") -> No
A18: Nov 22-26 Tranmere Afra | B18: 45727 | C18: WTI Sprds | D18: Hedge | E18: 432 | F18: 45626 | G18: 45657 | H18: 0.62 | I18: 0.52 | J18: -43.2 | K18: 267.84 | L18: Nov/Dec 24 | M18: Buy | N18: 224.64 | O18: Futures | P18: WTI Sprds | Q18: 2024 | R18: Buy | S18: Expired | T18: Nov 22-26 Tranmere AfraWTI SprdsHedge4320.5218 | U18: =IFERROR(_xlfn.XLOOKUP(A18,'2025 EOY'!A:A,'2025 EOY'!B:B),"No") -> No
A19: Unallocated | B19: 45727 | C19: WTI Sprds | D19: Hedge | E19: -1500 | F19: 45657 | G19: 45688 | H19: 0.28 | I19: 0.15 | J19: 195 | K19: -420 | L19: Dec/Jan 24 | M19: Sell | N19: -225 | O19: Futures | P19: WTI Sprds | Q19: 2024 | R19: Sell | S19: Expired | T19: UnallocatedWTI SprdsHedge-15000.1519 | U19: =IFERROR(_xlfn.XLOOKUP(A19,'2025 EOY'!A:A,'2025 EOY'!B:B),"No") -> No
A20: CPC TAIWAN JAN 8-14 | B20: 45727 | C20: WTI Sprds | D20: Hedge | E20: -50 | F20: 45657 | G20: 45688 | H20: 0.28 | I20: 0.15 | J20: 6.5 | K20: -14 | L20: Dec/Jan 24 | M20: Sell | N20: -7.5 | O20: Futures | P20: WTI Sprds | Q20: 2024 | R20: Sell | S20: Expired | T20: CPC TAIWAN JAN 8-14WTI SprdsHedge-500.1520 | U20: =IFERROR(_xlfn.XLOOKUP(A20,'2025 EOY'!A:A,'2025 EOY'!B:B),"No") -> No
A21: EXTAP Feb 15-25 | B21: 45727 | C21: WTI Sprds | D21: Hedge | E21: -24 | F21: 45657 | G21: 45688 | H21: 0.28 | I21: 0.15 | J21: 3.12 | K21: -6.72 | L21: Dec/Jan 24 | M21: Sell | N21: -3.6 | O21: Futures | P21: WTI Sprds | Q21: 2024 | R21: Sell | S21: Expired | T21: EXTAP Feb 15-25WTI SprdsHedge-240.1521 | U21: =IFERROR(_xlfn.XLOOKUP(A21,'2025 EOY'!A:A,'2025 EOY'!B:B),"No") -> No
A22: Gunvor FOB Dec 6-7 | B22: 45727 | C22: WTI Sprds | D22: Hedge | E22: 68 | F22: 45657 | G22: 45688 | H22: 0.28 | I22: 0.15 | J22: -8.84 | K22: 19.04 | L22: Dec/Jan 24 | M22: Buy | N22: 10.2 | O22: Futures | P22: WTI Sprds | Q22: 2024 | R22: Buy | S22: Expired | T22: Gunvor FOB Dec 6-7WTI SprdsHedge680.1522 | U22: =IFERROR(_xlfn.XLOOKUP(A22,'2025 EOY'!A:A,'2025 EOY'!B:B),"No") -> No | Z22: 28
A23: HDO Feb 5-15 | B23: 45727 | C23: WTI Sprds | D23: Hedge | E23: 24 | F23: 45657 | G23: 45688 | H23: 0.28 | I23: 0.15 | J23: -3.12 | K23: 6.72 | L23: Dec/Jan 24 | M23: Buy | N23: 3.6 | O23: Futures | P23: WTI Sprds | Q23: 2024 | R23: Buy | S23: Expired | T23: HDO Feb 5-15WTI SprdsHedge240.1523 | U23: =IFERROR(_xlfn.XLOOKUP(A23,'2025 EOY'!A:A,'2025 EOY'!B:B),"No") -> No
A24: Jan 1-10 EXTAP VLCC | B24: 45727 | C24: WTI Sprds | D24: Hedge | E24: 1050 | F24: 45657 | G24: 45688 | H24: 0.28 | I24: 0.15 | J24: -136.5 | K24: 294 | L24: Dec/Jan 24 | M24: Buy | N24: 157.5 | O24: Futures | P24: WTI Sprds | Q24: 2024 | R24: Buy | S24: Expired | T24: Jan 1-10 EXTAP VLCCWTI SprdsHedge10500.1524 | U24: =IFERROR(_xlfn.XLOOKUP(A24,'2025 EOY'!A:A,'2025 EOY'!B:B),"No") -> No
A25: Nov 22-26 Tranmere Afra | B25: 45727 | C25: WTI Sprds | D25: Hedge | E25: 432 | F25: 45657 | G25: 45688 | H25: 0.28 | I25: 0.15 | J25: -56.16 | K25: 120.96 | L25: Dec/Jan 24 | M25: Buy | N25: 64.8 | O25: Futures | P25: WTI Sprds | Q25: 2024 | R25: Buy | S25: Expired | T25: Nov 22-26 Tranmere AfraWTI SprdsHedge4320.1525 | U25: =IFERROR(_xlfn.XLOOKUP(A25,'2025 EOY'!A:A,'2025 EOY'!B:B),"No") -> No
A26: CPC TAIWAN FEB 20-24 | B26: 45727 | C26: WTI Sprds | D26: Hedge | E26: 800 | F26: 45688 | G26: 45716 | H26: 0.42 | I26: 0.56 | J26: 112 | K26: 336 | L26: Jan/Feb 25 | M26: Buy | N26: 448 | O26: Futures | P26: WTI Sprds | Q26: 2025 | R26: Buy | S26: Expired | T26: CPC TAIWAN FEB 20-24WTI SprdsHedge8000.5626 | U26: =IFERROR(_xlfn.XLOOKUP(A26,'2025 EOY'!A:A,'2025 EOY'!B:B),"No") -> No
A27: CPC TAIWAN MARCH 11-15 | B27: 45727 | C27: WTI Sprds | D27: Hedge | E27: 2096 | F27: 45688 | G27: 45716 | H27: 0.42 | I27: 0.56 | J27: 293.44 | K27: 880.32 | L27: Jan/Feb 25 | M27: Buy | N27: 1173.76 | O27: Futures | P27: WTI Sprds | Q27: 2025 | R27: Buy | S27: Expired | T27: CPC TAIWAN MARCH 11-15WTI SprdsHedge20960.5627 | U27: =IFERROR(_xlfn.XLOOKUP(A27,'2025 EOY'!A:A,'2025 EOY'!B:B),"No") -> No
A28: EXTAP Feb 15-25 | B28: 45727 | C28: WTI Sprds | D28: Hedge | E28: -24 | F28: 45688 | G28: 45716 | H28: 0.42 | I28: 0.56 | J28: -3.36 | K28: -10.08 | L28: Jan/Feb 25 | M28: Sell | N28: -13.44 | O28: Futures | P28: WTI Sprds | Q28: 2025 | R28: Sell | S28: Expired | T28: EXTAP Feb 15-25WTI SprdsHedge-240.5628 | U28: =IFERROR(_xlfn.XLOOKUP(A28,'2025 EOY'!A:A,'2025 EOY'!B:B),"No") -> No
A29: Feb EFP 2 | B29: 45727 | C29: WTI Sprds | D29: Hedge | E29: 700 | F29: 45688 | G29: 45716 | H29: 0.42 | I29: 0.56 | J29: 98 | K29: 294 | L29: Jan/Feb 25 | M29: Buy | N29: 392 | O29: Futures | P29: WTI Sprds | Q29: 2025 | R29: Buy | S29: Expired | T29: Feb EFP 2WTI SprdsHedge7000.5629 | U29: =IFERROR(_xlfn.XLOOKUP(A29,'2025 EOY'!A:A,'2025 EOY'!B:B),"No") -> No
A30: HDO Feb 5-15 | B30: 45727 | C30: WTI Sprds | D30: Hedge | E30: 47 | F30: 45688 | G30: 45716 | H30: 0.42 | I30: 0.56 | J30: 6.58 | K30: 19.74 | L30: Jan/Feb 25 | M30: Buy | N30: 26.32 | O30: Futures | P30: WTI Sprds | Q30: 2025 | R30: Buy | S30: Expired | T30: HDO Feb 5-15WTI SprdsHedge470.5630 | U30: =IFERROR(_xlfn.XLOOKUP(A30,'2025 EOY'!A:A,'2025 EOY'!B:B),"No") -> No
A31: Jan 4-6 KAL Afra | B31: 45727 | C31: WTI Sprds | D31: Hedge | E31: 35 | F31: 45688 | G31: 45716 | H31: 0.42 | I31: 0.56 | J31: 4.9 | K31: 14.7 | L31: Jan/Feb 25 | M31: Buy | N31: 19.6 | O31: Futures | P31: WTI Sprds | Q31: 2025 | R31: Buy | S31: Expired | T31: Jan 4-6 KAL AfraWTI SprdsHedge350.5631 | U31: =IFERROR(_xlfn.XLOOKUP(A31,'2025 EOY'!A:A,'2025 EOY'!B:B),"No") -> No
A32: Mitsui CIF Rdam Jan 27-29 | B32: 45727 | C32: WTI Sprds | D32: Hedge | E32: 735 | F32: 45688 | G32: 45716 | H32: 0.42 | I32: 0.56 | J32: 102.9 | K32: 308.7 | L32: Jan/Feb 25 | M32: Buy | N32: 411.6 | O32: Futures | P32: WTI Sprds | Q32: 2025 | R32: Buy | S32: Expired | T32: Mitsui CIF Rdam Jan 27-29WTI SprdsHedge7350.5632 | U32: =IFERROR(_xlfn.XLOOKUP(A32,'2025 EOY'!A:A,'2025 EOY'!B:B),"No") -> No
A33: Unallocated | B33: 45727 | C33: WTI Sprds | D33: Hedge | E33: -4389 | F33: 45688 | G33: 45716 | H33: 0.42 | I33: 0.56 | J33: -614.46 | K33: -1843.38 | L33: Jan/Feb 25 | M33: Sell | N33: -2457.84 | O33: Futures | P33: WTI Sprds | Q33: 2025 | R33: Sell | S33: Expired | T33: UnallocatedWTI SprdsHedge-43890.5633 | U33: =IFERROR(_xlfn.XLOOKUP(A33,'2025 EOY'!A:A,'2025 EOY'!B:B),"No") -> No
A34: BPCL DES India March 16-22 | B34: 45727 | C34: WTI Sprds | D34: Hedge | E34: 2079 | F34: 45716 | G34: 45747 | H34: 0.39 | I34: 0.49 | J34: 207.9 | K34: 810.81 | L34: Feb/Mar 25 | M34: Buy | N34: 1018.71 | O34: Futures | P34: WTI Sprds | Q34: 2025 | R34: Buy | S34: Expired | T34: BPCL DES India March 16-22WTI SprdsHedge20790.4934 | U34: =IFERROR(_xlfn.XLOOKUP(A34,'2025 EOY'!A:A,'2025 EOY'!B:B),"No") -> No
... A96: Mitsui CIF Rdam Jan 27-29 | B96: 45726 | C96: WTI-Brent | D96: Hedge | E96: 735 | F96: 45747 | G96: 45747 | H96: -3.5 | I96: -4.23 | J96: -536.55 | K96: -2572.5 | L96: Mar 25 | M96: Buy | N96: -3109.05 | O96: Swaps | P96: WTI-Brent | Q96: 2025 | R96: Buy | S96: Expired | T96: Mitsui CIF Rdam Jan 27-29WTI-BrentHedge735-4.2396 | U96: =IFERROR(_xlfn.XLOOKUP(A96,'2025 EOY'!A:A,'2025 EOY'!B:B),"No") -> No
A97: Unallocated | B97: 45726 | C97: WTI-Brent | D97: Hedge | E97: -5614 | F97: 45747 | G97: 45747 | H97: -3.5 | I97: -4.23 | J97: 4098.22 | K97: 19649 | L97: Mar 25 | M97: Sell | N97: 23747.22 | O97: Swaps | P97: WTI-Brent | Q97: 2025 | R97: Sell | S97: Expired | T97: UnallocatedWTI-BrentHedge-5614-4.2397 | U97: =IFERROR(_xlfn.XLOOKUP(A97,'2025 EOY'!A:A,'2025 EOY'!B:B),"No") -> No | W97: 0.35
A98: HDO April 12-22 25 | B98: 45726 | C98: WTI-Brent | D98: Hedge | E98: 68 | F98: 45777 | G98: 45777 | H98: -9.38 | I98: -3.42 | J98: 405.28 | K98: -637.84 | L98: Apr 25 | M98: Buy | N98: -232.56 | O98: Swaps | P98: WTI-Brent | Q98: 2025 | R98: Buy | S98: Expired | T98: HDO April 12-22 25WTI-BrentHedge68-3.4298 | U98: =IFERROR(_xlfn.XLOOKUP(A98,'2025 EOY'!A:A,'2025 EOY'!B:B),"No") -> No | W98: 1.3
A99: Unallocated | B99: 45726 | C99: WTI-Brent | D99: Hedge | E99: -68 | F99: 45777 | G99: 45777 | H99: -9.38 | I99: -3.42 | J99: -405.28 | K99: 637.84 | L99: Apr 25 | M99: Sell | N99: 232.56 | O99: Swaps | P99: WTI-Brent | Q99: 2025 | R99: Sell | S99: Expired | T99: UnallocatedWTI-BrentHedge-68-3.4299 | U99: =IFERROR(_xlfn.XLOOKUP(A99,'2025 EOY'!A:A,'2025 EOY'!B:B),"No") -> No | W99: 0.27
A100: Feb EFP 4 | B100: 45726 | C100: WTI-Brent | D100: Hedge | E100: 700 | F100: 45808 | G100: 45808 | H100: -3.83 | I100: -3.26 | J100: 399 | K100: -2681 | L100: May 25 | M100: Buy | N100: -2282 | O100: Swaps | P100: WTI-Brent | Q100: 2025 | R100: Buy | S100: Expired | T100: Feb EFP 4WTI-BrentHedge700-3.26100 | U100: =IFERROR(_xlfn.XLOOKUP(A100,'2025 EOY'!A:A,'2025 EOY'!B:B),"No") -> No | W100: 0.26
A101: Unallocated | B101: 45726 | C101: WTI-Brent | D101: Hedge | E101: -700 | F101: 45808 | G101: 45808 | H101: -3.83 | I101: -3.26 | J101: -399 | K101: 2681 | L101: May 25 | M101: Sell | N101: 2282 | O101: Swaps | P101: WTI-Brent | Q101: 2025 | R101: Sell | S101: Expired | T101: UnallocatedWTI-BrentHedge-700-3.26101 | U101: =IFERROR(_xlfn.XLOOKUP(A101,'2025 EOY'!A:A,'2025 EOY'!B:B),"No") -> No | W101: -3.76
A102: Vitol FOB March Bookout | B102: 45726 | C102: WTI-Brent | D102: Hedge | E102: 300 | F102: 45808 | G102: 45808 | H102: -3.83 | I102: -3.26 | J102: 171 | K102: -1149 | L102: May 25 | M102: Buy | N102: -978 | O102: Swaps | P102: WTI-Brent | Q102: 2025 | R102: Buy | S102: Expired | T102: Vitol FOB March BookoutWTI-BrentHedge300-3.26102 | U102: =IFERROR(_xlfn.XLOOKUP(A102,'2025 EOY'!A:A,'2025 EOY'!B:B),"No") -> No | W102: -1.58
A103: Unallocated | B103: 45726 | C103: WTI-Brent | D103: Hedge | E103: -300 | F103: 45808 | G103: 45808 | H103: -3.83 | I103: -3.26 | J103: -171 | K103: 1149 | L103: May 25 | M103: Sell | N103: 978 | O103: Swaps | P103: WTI-Brent | Q103: 2025 | R103: Sell | S103: Expired | T103: UnallocatedWTI-BrentHedge-300-3.26103 | U103: =IFERROR(_xlfn.XLOOKUP(A103,'2025 EOY'!A:A,'2025 EOY'!B:B),"No") -> No
A104: Oct 27-29 KAL Afra | B104: 45727 | C104: DFL | D104: Expo | E104: -700 | F104: 45596 | G104: 45596 | H104: 0.27 | I104: 0.27 | J104: 0 | K104: -189 | L104: Oct 24 | M104: Sell | N104: -189 | O104: Swaps | P104: Dated | Q104: 2024 | R104: Sell | S104: Expired | T104: Oct 27-29 KAL AfraDFLExpo-7000.27104 | U104: =IFERROR(_xlfn.XLOOKUP(A104,'2025 EOY'!A:A,'2025 EOY'!B:B),"No") -> No
A105: Unallocated | B105: 45727 | C105: DFL | D105: Expo | E105: -197 | F105: 45626 | G105: 45626 | H105: 1.04 | I105: 1.04 | J105: 0 | K105: -204.88 | L105: Nov 24 | M105: Sell | N105: -204.88 | O105: Swaps | P105: Dated | Q105: 2024 | R105: Sell | S105: Expired | T105: UnallocatedDFLExpo-1971.04105 | U105: =IFERROR(_xlfn.XLOOKUP(A105,'2025 EOY'!A:A,'2025 EOY'!B:B),"No") -> No
A106: Unallocated | B106: 45727 | C106: DFL | D106: Expo | E106: -4683 | F106: 45657 | G106: 45657 | H106: 0.82 | I106: 0.82 | J106: 0 | K106: -3840.06 | L106: Dec 24 | M106: Sell | N106: -3840.06 | O106: Swaps | P106: Dated | Q106: 2024 | R106: Sell | S106: Expired | T106: UnallocatedDFLExpo-46830.82106 | U106: =IFERROR(_xlfn.XLOOKUP(A106,'2025 EOY'!A:A,'2025 EOY'!B:B),"No") -> No
A107: Jan 4-6 KAL Afra | B107: 45722 | C107: DFL | D107: Hedge | E107: 293 | F107: 45626 | G107: 45626 | H107: 0.24 | I107: 1.04 | J107: 234.4 | K107: 70.32 | L107: Nov 24 | M107: Buy | N107: 304.72 | O107: Swaps | P107: Dated | Q107: 2024 | R107: Buy | S107: Expired | T107: Jan 4-6 KAL AfraDFLHedge2931.04107 | U107: =IFERROR(_xlfn.XLOOKUP(A107,'2025 EOY'!A:A,'2025 EOY'!B:B),"No") -> No
A108: Nov 19-21 Shell Rdam VLCC | B108: 45722 | C108: DFL | D108: Hedge | E108: -2100 | F108: 45626 | G108: 45626 | H108: 0.24 | I108: 1.04 | J108: -1680 | K108: -504 | L108: Nov 24 | M108: Sell | N108: -2184 | O108: Swaps | P108: Dated | Q108: 2024 | R108: Sell | S108: Expired | T108: Nov 19-21 Shell Rdam VLCCDFLHedge-21001.04108 | U108: =IFERROR(_xlfn.XLOOKUP(A108,'2025 EOY'!A:A,'2025 EOY'!B:B),"No") -> No
A109: Nov 22-26 Tranmere Afra | B109: 45722 | C109: DFL | D109: Hedge | E109: -690 | F109: 45626 | G109: 45626 | H109: 0.24 | I109: 1.04 | J109: -552 | K109: -165.6 | L109: Nov 24 | M109: Sell | N109: -717.6 | O109: Swaps | P109: Dated | Q109: 2024 | R109: Sell | S109: Expired | T109: Nov 22-26 Tranmere AfraDFLHedge-6901.04109 | U109: =IFERROR(_xlfn.XLOOKUP(A109,'2025 EOY'!A:A,'2025 EOY'!B:B),"No") -> No
A110: Unallocated | B110: 45722 | C110: DFL | D110: Hedge | E110: 2497 | F110: 45626 | G110: 45626 | H110: 0.24 | I110: 1.04 | J110: 1997.6 | K110: 599.28 | L110: Nov 24 | M110: Buy | N110: 2596.88 | O110: Swaps | P110: Dated | Q110: 2024 | R110: Buy | S110: Expired | T110: UnallocatedDFLHedge24971.04110 | U110: =IFERROR(_xlfn.XLOOKUP(A110,'2025 EOY'!A:A,'2025 EOY'!B:B),"No") -> No
A111: CPC TAIWAN JAN 8-14 | B111: 45722 | C111: DFL | D111: Hedge | E111: -2050 | F111: 45657 | G111: 45657 | H111: 0.91 | I111: 0.82 | J111: 184.5 | K111: -1865.5 | L111: Dec 24 | M111: Sell | N111: -1681 | O111: Swaps | P111: Dated | Q111: 2024 | R111: Sell | S111: Expired | T111: CPC TAIWAN JAN 8-14DFLHedge-20500.82111 | U111: =IFERROR(_xlfn.XLOOKUP(A111,'2025 EOY'!A:A,'2025 EOY'!B:B),"No") -> No
A112: Dec 15-25 EXTAP VLCC | B112: 45722 | C112: DFL | D112: Hedge | E112: -2083 | F112: 45657 | G112: 45657 | H112: 0.91 | I112: 0.82 | J112: 187.47 | K112: -1895.53 | L112: Dec 24 | M112: Sell | N112: -1708.06 | O112: Swaps | P112: Dated | Q112: 2024 | R112: Sell | S112: Expired | T112: Dec 15-25 EXTAP VLCCDFLHedge-20830.82112 | U112: =IFERROR(_xlfn.XLOOKUP(A112,'2025 EOY'!A:A,'2025 EOY'!B:B),"No") -> No
A113: EOY Flattening Out | B113: 45722 | C113: DFL | D113: Hedge | E113: 0 | F113: 45657 | G113: 45657 | H113: 0.91 | I113: 0.82 | J113: 0 | K113: 0 | L113: Dec 24 | M113: Buy | N113: 0 | O113: Swaps | P113: Dated | Q113: 2024 | R113: Sell | S113: Expired | T113: EOY Flattening OutDFLHedge00.82113 | U113: =IFERROR(_xlfn.XLOOKUP(A113,'2025 EOY'!A:A,'2025 EOY'!B:B),"No") -> No
A114: Unallocated | B114: 45722 | C114: DFL | D114: Hedge | E114: 4133 | F114: 45657 | G114: 45657 | H114: 0.91 | I114: 0.82 | J114: -371.97 | K114: 3761.03 | L114: Dec 24 | M114: Buy | N114: 3389.06 | O114: Swaps | P114: Dated | Q114: 2024 | R114: Buy | S114: Expired | T114: UnallocatedDFLHedge41330.82114 | U114: =IFERROR(_xlfn.XLOOKUP(A114,'2025 EOY'!A:A,'2025 EOY'!B:B),"No") -> No
... A135: Nov 19-21 Shell Rdam VLCC | B135: 45207 | C135: Physical | D135: Expo | E135: 2100 | F135: 44957 | G135: 44957 | H135: 2.15 | I135: 2.45 | J135: 630 | K135: 4515 | L135: Jan 23 | M135: Buy | N135: 5145 | O135: Physical | P135: Physical | Q135: 2023 | R135: Buy | S135: Active | T135: Nov 19-21 Shell Rdam VLCCPhysicalExpo21002.45135 | U135: =IFERROR(_xlfn.XLOOKUP(A135,'2025 EOY'!A:A,'2025 EOY'!B:B),"No") -> No
A136: Spec | B136: 45461 | C136: WTI Sprds-Fly | D136: Hedge | E136: 0 | F136: 45565 | G136: 45596 | H136: 0.77 | I136: #N/A | K136: 0 | L136: Sep/Oct 24 | M136: Buy | N136: #N/A | O136: Futures | P136: WTI Sprds | Q136: 2024 | R136: Sell | S136: Expired | T136: #N/A | U136: =IFERROR(_xlfn.XLOOKUP(A136,'2025 EOY'!A:A,'2025 EOY'!B:B),"No") -> No
A137: Nov 22-26 Tranmere Afra | B137: 45573 | C137: DFL | D137: Expo | E137: 690 | F137: 45626 | G137: 45626 | H137: 0.13 | I137: 1.04 | J137: 627.9 | K137: 89.7 | L137: Nov 24 | M137: Buy | N137: 717.6 | O137: Swaps | P137: Dated | Q137: 2024 | R137: Buy | S137: Expired | T137: Nov 22-26 Tranmere AfraDFLExpo6901.04137 | U137: =IFERROR(_xlfn.XLOOKUP(A137,'2025 EOY'!A:A,'2025 EOY'!B:B),"No") -> No
A138: Nov 22-26 Tranmere Afra | B138: 45573 | C138: Freight-TD25 | D138: Expo | E138: -690 | F138: 45626 | G138: 45626 | H138: 170 | I138: 166 | J138: -55.2 | K138: -117300 | L138: Nov 24 | M138: Sell | N138: -114540 | O138: Freight | P138: Freight | Q138: 2024 | R138: Sell | S138: Expired | T138: Nov 22-26 Tranmere AfraFreight-TD25Expo-690166138 | U138: =IFERROR(_xlfn.XLOOKUP(A138,'2025 EOY'!A:A,'2025 EOY'!B:B),"No") -> No
A139: Nov 22-26 Tranmere Afra | B139: 45573 | C139: Freight-TD25 | D139: Expo | E139: 690 | F139: 45626 | G139: 45626 | H139: 170 | I139: 166 | J139: 56 | K139: 117300 | L139: Nov 24 | M139: Buy | N139: 114540 | O139: Freight | P139: Freight | Q139: 2024 | R139: Buy | S139: Expired | T139: Nov 22-26 Tranmere AfraFreight-TD25Expo690166139 | U139: =IFERROR(_xlfn.XLOOKUP(A139,'2025 EOY'!A:A,'2025 EOY'!B:B),"No") -> No
A140: Nov 22-26 Tranmere Afra | B140: 45573 | C140: Physical | D140: Expo | E140: -690 | F140: 44957 | G140: 44957 | H140: 1.75 | I140: 1.75 | J140: 0 | K140: -1207.5 | L140: Jan 23 | M140: Sell | N140: -1207.5 | O140: Physical | P140: Physical | Q140: 2023 | R140: Sell | S140: Active | T140: Nov 22-26 Tranmere AfraPhysicalExpo-6901.75140 | U140: =IFERROR(_xlfn.XLOOKUP(A140,'2025 EOY'!A:A,'2025 EOY'!B:B),"No") -> No
A141: Nov 22-26 Tranmere Afra | B141: 45573 | C141: WTI Sprds | D141: Expo | E141: -690 | F141: 45626 | G141: 45657 | H141: 0.58 | I141: 0.52 | J141: 41.4 | K141: -400.2 | L141: Nov/Dec 24 | M141: Sell | N141: -358.8 | O141: Futures | P141: WTI Sprds | Q141: 2024 | R141: Sell | S141: Expired | T141: Nov 22-26 Tranmere AfraWTI SprdsExpo-6900.52141 | U141: =IFERROR(_xlfn.XLOOKUP(A141,'2025 EOY'!A:A,'2025 EOY'!B:B),"No") -> No
A142: Nov 22-26 Tranmere Afra | B142: 45573 | C142: WTI Sprds | D142: Expo | E142: -690 | F142: 45657 | G142: 45688 | H142: 0.44 | I142: 0.15 | J142: 200.1 | K142: -303.6 | L142: Dec/Jan 24 | M142: Sell | N142: -103.5 | O142: Futures | P142: WTI Sprds | Q142: 2024 | R142: Sell | S142: Expired | T142: Nov 22-26 Tranmere AfraWTI SprdsExpo-6900.15142 | U142: =IFERROR(_xlfn.XLOOKUP(A142,'2025 EOY'!A:A,'2025 EOY'!B:B),"No") -> No
A143: Nov 22-26 Tranmere Afra | B143: 45573 | C143: WTI-Brent | D143: Expo | E143: -690 | F143: 45688 | G143: 45688 | H143: -4.21 | I143: -4.94 | J143: 503.7 | K143: 2904.9 | L143: Jan 25 | M143: Sell | N143: 3408.6 | O143: Swaps | P143: WTI-Brent | Q143: 2025 | R143: Sell | S143: Expired | T143: Nov 22-26 Tranmere AfraWTI-BrentExpo-690-4.94143 | U143: =IFERROR(_xlfn.XLOOKUP(A143,'2025 EOY'!A:A,'2025 EOY'!B:B),"No") -> No
A144: Jan 1-10 EXTAP VLCC | B144: 45574 | C144: Brent Sprds | D144: Expo | E144: -2050 | F144: 45688 | G144: 45716 | H144: 0.33 | I144: 1.1 | J144: -1578.5 | K144: -676.5 | L144: Jan/Feb 25 | M144: Sell | N144: -2255 | O144: Futures | P144: Brent Sprds | Q144: 2025 | R144: Sell | S144: Expired | T144: Jan 1-10 EXTAP VLCCBrent SprdsExpo-20501.1144 | U144: =IFERROR(_xlfn.XLOOKUP(A144,'2025 EOY'!A:A,'2025 EOY'!B:B),"No") -> No
A145: Jan 1-10 EXTAP VLCC | B145: 45574 | C145: Brent Sprds | D145: Expo | E145: -2050 | F145: 45716 | G145: 45747 | H145: 0.24 | I145: 0.4 | J145: -328 | K145: -492 | L145: Feb/Mar 25 | M145: Sell | N145: -820 | O145: Futures | P145: Brent Sprds | Q145: 2025 | R145: Sell | S145: Expired | T145: Jan 1-10 EXTAP VLCCBrent SprdsExpo-20500.4145 | U145: =IFERROR(_xlfn.XLOOKUP(A145,'2025 EOY'!A:A,'2025 EOY'!B:B),"No") -> No
A146: Jan 1-10 EXTAP VLCC | B146: 45574 | C146: DFL | D146: Expo | E146: 2069 | F146: 45688 | G146: 45688 | H146: 0.04 | I146: 0.93 | J146: 1841.41 | K146: 82.76 | L146: Jan 25 | M146: Buy | N146: 1924.17 | O146: Swaps | P146: Dated | Q146: 2025 | R146: Buy | S146: Expired | T146: Jan 1-10 EXTAP VLCCDFLExpo20690.93146 | U146: =IFERROR(_xlfn.XLOOKUP(A146,'2025 EOY'!A:A,'2025 EOY'!B:B),"No") -> No
A147: Jan 1-10 EXTAP VLCC | B147: 45574 | C147: Physical | D147: Expo | E147: 2069 | F147: 44957 | G147: 44957 | H147: 3.19 | I147: 3.6 | J147: 848.29 | K147: 6744.94 | L147: Jan 23 | M147: Buy | N147: 7448.4 | O147: Physical | P147: Physical | Q147: 2023 | R147: Buy | S147: Active | T147: Jan 1-10 EXTAP VLCCPhysicalExpo20693.6147 | U147: =IFERROR(_xlfn.XLOOKUP(A147,'2025 EOY'!A:A,'2025 EOY'!B:B),"No") -> No
A148: Jan 1-10 EXTAP VLCC | B148: 45574 | C148: WTI Sprds | D148: Expo | E148: -2050 | F148: 45626 | G148: 45657 | H148: 0.63 | I148: 0.52 | J148: 225.5 | K148: -1291.5 | L148: Nov/Dec 24 | M148: Sell | N148: -1066 | O148: Futures | P148: WTI Sprds | Q148: 2024 | R148: Sell | S148: Expired | T148: Jan 1-10 EXTAP VLCCWTI SprdsExpo-20500.52148 | U148: =IFERROR(_xlfn.XLOOKUP(A148,'2025 EOY'!A:A,'2025 EOY'!B:B),"No") -> No
... A150: Jan 1-10 EXTAP VLCC | B150: 45574 | C150: WTI-Brent | D150: Expo | E150: -2050 | F150: 45688 | G150: 45688 | H150: -4.12 | I150: -4.94 | J150: 1681 | K150: 8446 | L150: Jan 25 | M150: Sell | N150: 10127 | O150: Swaps | P150: WTI-Brent | Q150: 2025 | R150: Sell | S150: Expired | T150: Jan 1-10 EXTAP VLCCWTI-BrentExpo-2050-4.94150 | U150: =IFERROR(_xlfn.XLOOKUP(A150,'2025 EOY'!A:A,'2025 EOY'!B:B),"No") -> No
A151: Jan 1-10 EXTAP VLCC | B151: 45685 | C151: Physical | D151: Expo | E151: 0 | F151: 44957 | G151: 44957 | J151: -700 | K151: 0 | L151: Jan 23 | M151: Buy | N151: 0 | O151: Physical | P151: Physical | Q151: 2023 | R151: Sell | S151: Active | T151: Jan 1-10 EXTAP VLCCPhysicalExpo0151 | U151: =IFERROR(_xlfn.XLOOKUP(A151,'2025 EOY'!A:A,'2025 EOY'!B:B),"No") -> No
A152: Jan 4-6 KAL Afra | B152: 45575 | C152: DFL | D152: Hedge | E152: -500 | F152: 45626 | G152: 45626 | H152: 0.16 | I152: 1.04 | J152: -440 | K152: -80 | L152: Nov 24 | M152: Sell | N152: -520 | O152: Swaps | P152: Dated | Q152: 2024 | R152: Sell | S152: Expired | T152: Jan 4-6 KAL AfraDFLHedge-5001.04152 | U152: =IFERROR(_xlfn.XLOOKUP(A152,'2025 EOY'!A:A,'2025 EOY'!B:B),"No") -> No
A153: Oct 27-29 KAL Afra | B153: 45575 | C153: DFL | D153: Expo | E153: 700 | F153: 45596 | G153: 45596 | H153: 0.4 | I153: 0.27 | J153: -91 | K153: 280 | L153: Oct 24 | M153: Buy | N153: 189 | O153: Swaps | P153: Dated | Q153: 2024 | R153: Buy | S153: Expired | T153: Oct 27-29 KAL AfraDFLExpo7000.27153 | U153: =IFERROR(_xlfn.XLOOKUP(A153,'2025 EOY'!A:A,'2025 EOY'!B:B),"No") -> No
A154: Nov 22-26 Tranmere Afra | B154: 45575 | C154: WTI-Brent | D154: Hedge | E154: 700 | F154: 45688 | G154: 45688 | H154: -4.27 | I154: -4.94 | J154: -469 | K154: -2989 | L154: Jan 25 | M154: Buy | N154: -3458 | O154: Swaps | P154: WTI-Brent | Q154: 2025 | R154: Buy | S154: Expired | T154: Nov 22-26 Tranmere AfraWTI-BrentHedge700-4.94154 | U154: =IFERROR(_xlfn.XLOOKUP(A154,'2025 EOY'!A:A,'2025 EOY'!B:B),"No") -> No
A155: Dec EFP 1 | B155: 45575 | C155: WTI-Brent | D155: Expo | E155: -700 | F155: 45657 | G155: 45657 | H155: -4.19 | I155: -3.9 | J155: -203 | K155: 2933 | L155: Dec 24 | M155: Sell | N155: 2730 | O155: Swaps | P155: WTI-Brent | Q155: 2024 | R155: Sell | S155: Expired | T155: Dec EFP 1WTI-BrentExpo-700-3.9155 | U155: =IFERROR(_xlfn.XLOOKUP(A155,'2025 EOY'!A:A,'2025 EOY'!B:B),"No") -> No
A156: Dec EFP 2 | B156: 45575 | C156: WTI-Brent | D156: Expo | E156: -700 | F156: 45657 | G156: 45657 | H156: -4.19 | I156: -3.9 | J156: -203 | K156: 2933 | L156: Dec 24 | M156: Sell | N156: 2730 | O156: Swaps | P156: WTI-Brent | Q156: 2024 | R156: Sell | S156: Expired | T156: Dec EFP 2WTI-BrentExpo-700-3.9156 | U156: =IFERROR(_xlfn.XLOOKUP(A156,'2025 EOY'!A:A,'2025 EOY'!B:B),"No") -> No
A157: Dec EFP 3 | B157: 45575 | C157: WTI-Brent | D157: Expo | E157: -700 | F157: 45657 | G157: 45657 | H157: -4.19 | I157: -3.9 | J157: -203 | K157: 2933 | L157: Dec 24 | M157: Sell | N157: 2730 | O157: Swaps | P157: WTI-Brent | Q157: 2024 | R157: Sell | S157: Expired | T157: Dec EFP 3WTI-BrentExpo-700-3.9157 | U157: =IFERROR(_xlfn.XLOOKUP(A157,'2025 EOY'!A:A,'2025 EOY'!B:B),"No") -> No
A158: Jan 1-10 EXTAP VLCC | B158: 45575 | C158: WTI-Brent | D158: Hedge | E158: 300 | F158: 45688 | G158: 45688 | H158: -4.27 | I158: -4.94 | J158: -201 | K158: -1281 | L158: Jan 25 | M158: Buy | N158: -1482 | O158: Swaps | P158: WTI-Brent | Q158: 2025 | R158: Buy | S158: Expired | T158: Jan 1-10 EXTAP VLCCWTI-BrentHedge300-4.94158 | U158: =IFERROR(_xlfn.XLOOKUP(A158,'2025 EOY'!A:A,'2025 EOY'!B:B),"No") -> No
A159: Unallocated | B159: 45576 | C159: WTI Sprds | D159: Hedge | E159: 2000 | F159: 45626 | G159: 45657 | H159: 0.71 | I159: 0.52 | J159: -380 | K159: 1420 | L159: Nov/Dec 24 | M159: Buy | N159: 1040 | O159: Futures | P159: WTI Sprds | Q159: 2024 | R159: Buy | S159: Expired | T159: UnallocatedWTI SprdsHedge20000.52159 | U159: =IFERROR(_xlfn.XLOOKUP(A159,'2025 EOY'!A:A,'2025 EOY'!B:B),"No") -> No
A160: Jan 1-10 EXTAP VLCC | B160: 45576 | C160: WTI Sprds | D160: Hedge | E160: 1000 | F160: 45626 | G160: 45657 | H160: 0.71 | I160: 0.52 | J160: -190 | K160: 710 | L160: Nov/Dec 24 | M160: Buy | N160: 520 | O160: Futures | P160: WTI Sprds | Q160: 2024 | R160: Buy | S160: Expired | T160: Jan 1-10 EXTAP VLCCWTI SprdsHedge10000.52160 | U160: =IFERROR(_xlfn.XLOOKUP(A160,'2025 EOY'!A:A,'2025 EOY'!B:B),"No") -> No
A161: Jan 1-10 EXTAP VLCC | B161: 45576 | C161: WTI Sprds | D161: Hedge | E161: 1000 | F161: 45657 | G161: 45688 | H161: 0.54 | I161: 0.15 | J161: -390 | K161: 540 | L161: Dec/Jan 24 | M161: Buy | N161: 150 | O161: Futures | P161: WTI Sprds | Q161: 2024 | R161: Buy | S161: Expired | T161: Jan 1-10 EXTAP VLCCWTI SprdsHedge10000.15161 | U161: =IFERROR(_xlfn.XLOOKUP(A161,'2025 EOY'!A:A,'2025 EOY'!B:B),"No") -> No
A162: Unallocated | B162: 45576 | C162: WTI-Brent | D162: Hedge | E162: 2000 | F162: 45657 | G162: 45657 | H162: -4.19 | I162: -3.9 | J162: 580 | K162: -8380 | L162: Dec 24 | M162: Buy | N162: -7800 | O162: Swaps | P162: WTI-Brent | Q162: 2024 | R162: Buy | S162: Expired | T162: UnallocatedWTI-BrentHedge2000-3.9162 | U162: =IFERROR(_xlfn.XLOOKUP(A162,'2025 EOY'!A:A,'2025 EOY'!B:B),"No") -> No
A163: Jan 1-10 EXTAP VLCC | B163: 45576 | C163: WTI-Brent | D163: Hedge | F163: 45688 | G163: 45688 | H163: -4.29 | I163: -4.94 | J163: 0 | K163: 0 | L163: Jan 25 | M163: Buy | N163: 0 | O163: Swaps | P163: WTI-Brent | Q163: 2025 | R163: Sell | S163: Expired | T163: Jan 1-10 EXTAP VLCCWTI-BrentHedge-4.94163 | U163: =IFERROR(_xlfn.XLOOKUP(A163,'2025 EOY'!A:A,'2025 EOY'!B:B),"No") -> No
A164: Nov 22-26 Tranmere Afra | B164: 45579 | C164: WTI Sprds | D164: Hedge | E164: 258 | F164: 45626 | G164: 45657 | H164: 0.58 | I164: 0.52 | J164: -15.48 | K164: 149.64 | L164: Nov/Dec 24 | M164: Buy | N164: 134.16 | O164: Futures | P164: WTI Sprds | Q164: 2024 | R164: Buy | S164: Expired | T164: Nov 22-26 Tranmere AfraWTI SprdsHedge2580.52164 | U164: =IFERROR(_xlfn.XLOOKUP(A164,'2025 EOY'!A:A,'2025 EOY'!B:B),"No") -> No
A165: Nov 22-26 Tranmere Afra | B165: 45579 | C165: WTI Sprds | D165: Hedge | E165: 258 | F165: 45657 | G165: 45688 | H165: 0.41 | I165: 0.15 | J165: -67.08 | K165: 105.78 | L165: Dec/Jan 24 | M165: Buy | N165: 38.7 | O165: Futures | P165: WTI Sprds | Q165: 2024 | R165: Buy | S165: Expired | T165: Nov 22-26 Tranmere AfraWTI SprdsHedge2580.15165 | U165: =IFERROR(_xlfn.XLOOKUP(A165,'2025 EOY'!A:A,'2025 EOY'!B:B),"No") -> No
A166: Unallocated | B166: 45579 | C166: WTI Sprds | D166: Hedge | E166: 800 | F166: 45626 | G166: 45657 | H166: 0.57 | I166: 0.52 | J166: -40 | K166: 456 | L166: Nov/Dec 24 | M166: Buy | N166: 416 | O166: Futures | P166: WTI Sprds | Q166: 2024 | R166: Buy | S166: Expired | T166: UnallocatedWTI SprdsHedge8000.52166 | U166: =IFERROR(_xlfn.XLOOKUP(A166,'2025 EOY'!A:A,'2025 EOY'!B:B),"No") -> No
A167: Unallocated | B167: 45579 | C167: WTI Sprds | D167: Hedge | E167: 1553 | F167: 45626 | G167: 45657 | H167: 0.52 | I167: 0.52 | J167: 0 | K167: 807.56 | L167: Nov/Dec 24 | M167: Buy | N167: 807.56 | O167: Futures | P167: WTI Sprds | Q167: 2024 | R167: Buy | S167: Expired | T167: UnallocatedWTI SprdsHedge15530.52167 | U167: =IFERROR(_xlfn.XLOOKUP(A167,'2025 EOY'!A:A,'2025 EOY'!B:B),"No") -> No
A168: Unallocated | B168: 45579 | C168: WTI Sprds | D168: Hedge | E168: -64 | F168: 45626 | G168: 45657 | H168: 0.57 | I168: 0.52 | J168: 3.2 | K168: -36.48 | L168: Nov/Dec 24 | M168: Sell | N168: -33.28 | O168: Futures | P168: WTI Sprds | Q168: 2024 | R168: Sell | S168: Expired | T168: UnallocatedWTI SprdsHedge-640.52168 | U168: =IFERROR(_xlfn.XLOOKUP(A168,'2025 EOY'!A:A,'2025 EOY'!B:B),"No") -> No
A169: Nov 22-26 Tranmere Afra | B169: 45579 | C169: WTI-Brent | D169: Hedge | E169: 258 | F169: 45688 | G169: 45688 | H169: -4.28 | I169: -4.94 | J169: -170.28 | K169: -1104.24 | L169: Jan 25 | M169: Buy | N169: -1274.52 | O169: Swaps | P169: WTI-Brent | Q169: 2025 | R169: Buy | S169: Expired | T169: Nov 22-26 Tranmere AfraWTI-BrentHedge258-4.94169 | U169: =IFERROR(_xlfn.XLOOKUP(A169,'2025 EOY'!A:A,'2025 EOY'!B:B),"No") -> No
A170: Jan 4-6 KAL Afra | B170: 45580 | C170: DFL | D170: Hedge | E170: -500 | F170: 45626 | G170: 45626 | H170: 0.01 | I170: 1.04 | J170: -515 | K170: -5 | L170: Nov 24 | M170: Sell | N170: -520 | O170: Swaps | P170: Dated | Q170: 2024 | R170: Sell | S170: Expired | T170: Jan 4-6 KAL AfraDFLHedge-5001.04170 | U170: =IFERROR(_xlfn.XLOOKUP(A170,'2025 EOY'!A:A,'2025 EOY'!B:B),"No") -> No
A171: Unallocated | B171: 45581 | C171: DFL | D171: Hedge | E171: -400 | F171: 45626 | G171: 45626 | H171: 0.14 | I171: 1.04 | J171: -360 | K171: -56 | L171: Nov 24 | M171: Sell | N171: -416 | O171: Swaps | P171: Dated | Q171: 2024 | R171: Sell | S171: Expired | T171: UnallocatedDFLHedge-4001.04171 | U171: =IFERROR(_xlfn.XLOOKUP(A171,'2025 EOY'!A:A,'2025 EOY'!B:B),"No") -> No
A172: Unallocated | B172: 45581 | C172: DFL | D172: Hedge | E172: -100 | F172: 45657 | G172: 45657 | H172: 0.08 | I172: 0.82 | J172: -74 | K172: -8 | L172: Dec 24 | M172: Sell | N172: -82 | O172: Swaps | P172: Dated | Q172: 2024 | R172: Sell | S172: Expired | T172: UnallocatedDFLHedge-1000.82172 | U172: =IFERROR(_xlfn.XLOOKUP(A172,'2025 EOY'!A:A,'2025 EOY'!B:B),"No") -> No
A173: Unallocated | B173: 45581 | C173: DFL | D173: Hedge | E173: -100 | F173: 45688 | G173: 45688 | H173: 0.08 | I173: 0.93 | J173: -85 | K173: -8 | L173: Jan 25 | M173: Sell | N173: -93 | O173: Swaps | P173: Dated | Q173: 2025 | R173: Sell | S173: Expired | T173: UnallocatedDFLHedge-1000.93173 | U173: =IFERROR(_xlfn.XLOOKUP(A173,'2025 EOY'!A:A,'2025 EOY'!B:B),"No") -> No
A174: CPC TAIWAN JAN 8-14 | B174: 45586 | C174: Brent Sprds | D174: Expo | E174: -2050 | F174: 45688 | G174: 45716 | H174: 0.41 | I174: 1.1 | J174: -1414.5 | K174: -840.5 | L174: Jan/Feb 25 | M174: Sell | N174: -2255 | O174: Futures | P174: Brent Sprds | Q174: 2025 | R174: Sell | S174: Expired | T174: CPC TAIWAN JAN 8-14Brent SprdsExpo-20501.1174 | U174: =IFERROR(_xlfn.XLOOKUP(A174,'2025 EOY'!A:A,'2025 EOY'!B:B),"No") -> No
A175: CPC TAIWAN JAN 8-14 | B175: 45586 | C175: DFL | D175: Expo | E175: 2050 | F175: 45657 | G175: 45657 | H175: 0.15 | I175: 0.82 | J175: 1373.5 | K175: 307.5 | L175: Dec 24 | M175: Buy | N175: 1681 | O175: Swaps | P175: Dated | Q175: 2024 | R175: Buy | S175: Expired | T175: CPC TAIWAN JAN 8-14DFLExpo20500.82175 | U175: =IFERROR(_xlfn.XLOOKUP(A175,'2025 EOY'!A:A,'2025 EOY'!B:B),"No") -> No
... A198: Unallocated | B198: 45594 | C198: DFL | D198: Hedge | E198: -200 | F198: 45626 | G198: 45626 | H198: 0.46 | I198: 1.04 | J198: -116 | K198: -92 | L198: Nov 24 | M198: Sell | N198: -208 | O198: Swaps | P198: Dated | Q198: 2024 | R198: Sell | S198: Expired | T198: UnallocatedDFLHedge-2001.04198 | U198: =IFERROR(_xlfn.XLOOKUP(A198,'2025 EOY'!A:A,'2025 EOY'!B:B),"No") -> No
A199: Dec EFP 1 | B199: 45594 | C199: WTI-Brent | D199: Hedge | E199: 700 | F199: 45657 | G199: 45657 | H199: -3.91 | I199: -3.9 | J199: 7 | K199: -2737 | L199: Dec 24 | M199: Buy | N199: -2730 | O199: Swaps | P199: WTI-Brent | Q199: 2024 | R199: Buy | S199: Expired | T199: Dec EFP 1WTI-BrentHedge700-3.9199 | U199: =IFERROR(_xlfn.XLOOKUP(A199,'2025 EOY'!A:A,'2025 EOY'!B:B),"No") -> No | W199: 70
A200: Dec EFP 1 | B200: 45594 | C200: WTI-Brent | D200: Hedge | E200: -700 | F200: 45688 | G200: 45688 | H200: -3.92 | I200: -4.94 | J200: 714 | K200: 2744 | L200: Jan 25 | M200: Sell | N200: 3458 | O200: Swaps | P200: WTI-Brent | Q200: 2025 | R200: Sell | S200: Expired | T200: Dec EFP 1WTI-BrentHedge-700-4.94200 | U200: =IFERROR(_xlfn.XLOOKUP(A200,'2025 EOY'!A:A,'2025 EOY'!B:B),"No") -> No | W200: 0.00125
A201: Dec EFP 2 | B201: 45594 | C201: WTI-Brent | D201: Hedge | E201: 700 | F201: 45657 | G201: 45657 | H201: -3.91 | I201: -3.9 | J201: 7 | K201: -2737 | L201: Dec 24 | M201: Buy | N201: -2730 | O201: Swaps | P201: WTI-Brent | Q201: 2024 | R201: Buy | S201: Expired | T201: Dec EFP 2WTI-BrentHedge700-3.9201 | U201: =IFERROR(_xlfn.XLOOKUP(A201,'2025 EOY'!A:A,'2025 EOY'!B:B),"No") -> No
A202: Dec EFP 2 | B202: 45594 | C202: WTI-Brent | D202: Hedge | E202: -700 | F202: 45688 | G202: 45688 | H202: -3.92 | I202: -4.94 | J202: 714 | K202: 2744 | L202: Jan 25 | M202: Sell | N202: 3458 | O202: Swaps | P202: WTI-Brent | Q202: 2025 | R202: Sell | S202: Expired | T202: Dec EFP 2WTI-BrentHedge-700-4.94202 | U202: =IFERROR(_xlfn.XLOOKUP(A202,'2025 EOY'!A:A,'2025 EOY'!B:B),"No") -> No | W202: 0.0875
A203: Dec EFP 3 | B203: 45594 | C203: WTI-Brent | D203: Hedge | E203: 700 | F203: 45657 | G203: 45657 | H203: -3.91 | I203: -3.9 | J203: 7 | K203: -2737 | L203: Dec 24 | M203: Buy | N203: -2730 | O203: Swaps | P203: WTI-Brent | Q203: 2024 | R203: Buy | S203: Expired | T203: Dec EFP 3WTI-BrentHedge700-3.9203 | U203: =IFERROR(_xlfn.XLOOKUP(A203,'2025 EOY'!A:A,'2025 EOY'!B:B),"No") -> No | V203: 152.5
A204: Dec EFP 3 | B204: 45594 | C204: WTI-Brent | D204: Hedge | E204: -700 | F204: 45688 | G204: 45688 | H204: -3.92 | I204: -4.94 | J204: 714 | K204: 2744 | L204: Jan 25 | M204: Sell | N204: 3458 | O204: Swaps | P204: WTI-Brent | Q204: 2025 | R204: Sell | S204: Expired | T204: Dec EFP 3WTI-BrentHedge-700-4.94204 | U204: =IFERROR(_xlfn.XLOOKUP(A204,'2025 EOY'!A:A,'2025 EOY'!B:B),"No") -> No
...

Sheet Trades 2026
A1: RA Deal Number | B1: SAP Deal Number | C1: Physical Xref | D1: Cargo Name | E1: Date | F1: Sub-Instrument | G1: Expo Type | H1: Quantity | I1: Month1 | J1: Month2 | K1: Price | L1: Mtm | M1: PnL | N1: Average | O1: Name | P1: Buy/Sell | Q1: Average MtM | R1: Instrument Type | S1: Instrument | T1: Year | U1: Side | V1: Accounting | W1: M1 Instrument | X1: M1 Month | Y1: M1 Volume | Z1: M2 | AA1: M2 Month | AB1: M2 Volume
A2: Cargoes | B2: =_xlfn.XLOOKUP(Table3[[#This Row],[Cargo Name]],Ledger[Cargo Name],Ledger[SAP Deal Number]) -> ARA26HS00006 | C2: 0 | D2: CPC Taiwan Jan 17-21 | E2: 46022 | F2: Legacy 2025 | G2: Expo | I2: 45991 | J2: =I2 -> 45991 | M2: -196 | N2: =H2*K2 -> 0 | O2: =IF(I2=J2,TEXT(I2,"MMM YY"),TEXT(I2,"MMM")&"/"&TEXT(J2,"MMM")&" "&RIGHT(T2,2)) -> Nov 25 | P2: =IF(H2<0,"Sell","Buy") -> Buy | Q2: =H2*L2 -> 0 | R2: =VLOOKUP(F2,Control!$B:$C,2,FALSE) -> Legacy 2025 | S2: =VLOOKUP(F2,Control!$B:$D,3,FALSE) -> Legacy 2025 | T2: =YEAR(I2) -> 2025 | U2: =IFERROR(IF(H2>0,"Buy","Sell"),"") -> Sell | V2: Active | W2: =_xlfn.XLOOKUP(Table3[[#This Row],[Instrument]],Control!$B$2:$B$19,Control!$E$2:$E$19) -> 0 | X2: =Table3[[#This Row],[Month1]] -> 45991 | Y2: =Table3[[#This Row],[Quantity]] -> 0 | Z2: =_xlfn.XLOOKUP(Table3[[#This Row],[Instrument]],Control!$B$2:$B$19,Control!$F$2:$F$19) -> 0 | AA2: =Table3[[#This Row],[Month2]] -> 45991 | AB2: =-Y2 -> 0
A3: Cargoes | B3: =_xlfn.XLOOKUP(Table3[[#This Row],[Cargo Name]],Ledger[Cargo Name],Ledger[SAP Deal Number]) -> ARA26HS00013 | C3: 0 | D3: HDO March26 10-20 | E3: 46022 | F3: Legacy 2025 | G3: Expo | I3: 46022 | J3: =I3 -> 46022 | M3: -222 | N3: =H3*K3 -> 0 | O3: =IF(I3=J3,TEXT(I3,"MMM YY"),TEXT(I3,"MMM")&"/"&TEXT(J3,"MMM")&" "&RIGHT(T3,2)) -> Dec 25 | P3: =IF(H3<0,"Sell","Buy") -> Buy | Q3: =H3*L3 -> 0 | R3: =VLOOKUP(F3,Control!$B:$C,2,FALSE) -> Legacy 2025 | S3: =VLOOKUP(F3,Control!$B:$D,3,FALSE) -> Legacy 2025 | T3: =YEAR(I3) -> 2025 | U3: =IFERROR(IF(H3>0,"Buy","Sell"),"") -> Sell | V3: Active | W3: =_xlfn.XLOOKUP(Table3[[#This Row],[Instrument]],Control!$B$2:$B$19,Control!$E$2:$E$19) -> 0 | X3: =Table3[[#This Row],[Month1]] -> 46022 | Y3: =Table3[[#This Row],[Quantity]] -> 0 | Z3: =_xlfn.XLOOKUP(Table3[[#This Row],[Instrument]],Control!$B$2:$B$19,Control!$F$2:$F$19) -> 0 | AA3: =Table3[[#This Row],[Month2]] -> 46022 | AB3: =-Y3 -> 0
A4: Cargoes | B4: =_xlfn.XLOOKUP(Table3[[#This Row],[Cargo Name]],Ledger[Cargo Name],Ledger[SAP Deal Number]) -> ARA26HS00009 | C4: 0 | D4: Exxon CIF Rotts VLCC Jan 19-23 | E4: 46022 | F4: Legacy 2025 | G4: Expo | I4: 46022 | J4: =I4 -> 46022 | M4: 605 | N4: =H4*K4 -> 0 | O4: =IF(I4=J4,TEXT(I4,"MMM YY"),TEXT(I4,"MMM")&"/"&TEXT(J4,"MMM")&" "&RIGHT(T4,2)) -> Dec 25 | P4: =IF(H4<0,"Sell","Buy") -> Buy | Q4: =H4*L4 -> 0 | R4: =VLOOKUP(F4,Control!$B:$C,2,FALSE) -> Legacy 2025 | S4: =VLOOKUP(F4,Control!$B:$D,3,FALSE) -> Legacy 2025 | T4: =YEAR(I4) -> 2025 | U4: =IFERROR(IF(H4>0,"Buy","Sell"),"") -> Sell | V4: Active | W4: =_xlfn.XLOOKUP(Table3[[#This Row],[Instrument]],Control!$B$2:$B$19,Control!$E$2:$E$19) -> 0 | X4: =Table3[[#This Row],[Month1]] -> 46022 | Y4: =Table3[[#This Row],[Quantity]] -> 0 | Z4: =_xlfn.XLOOKUP(Table3[[#This Row],[Instrument]],Control!$B$2:$B$19,Control!$F$2:$F$19) -> 0 | AA4: =Table3[[#This Row],[Month2]] -> 46022 | AB4: =-Y4 -> 0
D5: Legacy 2025 | E5: 46022 | F5: Legacy 2025 | M5: 408 | N5: =H5*K5 -> 0 | P5: =IF(H5<0,"Sell","Buy") -> Buy | Q5: =H5*L5 -> 0 | R5: =VLOOKUP(F5,Control!$B:$C,2,FALSE) -> Legacy 2025 | S5: Brent Sprds | T5: 2025 | U5: =IFERROR(IF(H5>0,"Buy","Sell"),"") -> Sell | V5: Active | W5: =_xlfn.XLOOKUP(Table3[[#This Row],[Instrument]],Control!$B$2:$B$19,Control!$E$2:$E$19) -> Brent | X5: =Table3[[#This Row],[Month1]] -> 0 | Y5: =Table3[[#This Row],[Quantity]] -> 0 | Z5: =_xlfn.XLOOKUP(Table3[[#This Row],[Instrument]],Control!$B$2:$B$19,Control!$F$2:$F$19) -> Brent | AA5: =Table3[[#This Row],[Month2]] -> 0 | AB5: =-Y5 -> 0
D6: Legacy 2025 | E6: 46022 | F6: Legacy 2025 | M6: -191 | N6: =H6*K6 -> 0 | P6: =IF(H6<0,"Sell","Buy") -> Buy | Q6: =H6*L6 -> 0 | R6: =VLOOKUP(F6,Control!$B:$C,2,FALSE) -> Legacy 2025 | S6: WTI Sprds | T6: 2025 | U6: =IFERROR(IF(H6>0,"Buy","Sell"),"") -> Sell | W6: =_xlfn.XLOOKUP(Table3[[#This Row],[Instrument]],Control!$B$2:$B$19,Control!$E$2:$E$19) -> WTI | X6: =Table3[[#This Row],[Month1]] -> 0 | Y6: =Table3[[#This Row],[Quantity]] -> 0 | Z6: =_xlfn.XLOOKUP(Table3[[#This Row],[Instrument]],Control!$B$2:$B$19,Control!$F$2:$F$19) -> WTI | AA6: =Table3[[#This Row],[Month2]] -> 0 | AB6: =-Y6 -> 0
D7: Legacy 2025 | E7: 46022 | F7: Legacy 2025 | M7: 428 | N7: =H7*K7 -> 0 | P7: =IF(H7<0,"Sell","Buy") -> Buy | Q7: =H7*L7 -> 0 | R7: =VLOOKUP(F7,Control!$B:$C,2,FALSE) -> Legacy 2025 | S7: Freight | T7: 2025 | U7: =IFERROR(IF(H7>0,"Buy","Sell"),"") -> Sell | W7: =_xlfn.XLOOKUP(Table3[[#This Row],[Instrument]],Control!$B$2:$B$19,Control!$E$2:$E$19) -> #N/A | X7: =Table3[[#This Row],[Month1]] -> 0 | Y7: =Table3[[#This Row],[Quantity]] -> 0 | Z7: =_xlfn.XLOOKUP(Table3[[#This Row],[Instrument]],Control!$B$2:$B$19,Control!$F$2:$F$19) -> #N/A | AA7: =Table3[[#This Row],[Month2]] -> 0 | AB7: =-Y7 -> 0
D8: Legacy 2025 | E8: 46022 | F8: Legacy 2025 | M8: 386 | N8: =H8*K8 -> 0 | P8: =IF(H8<0,"Sell","Buy") -> Buy | Q8: =H8*L8 -> 0 | R8: =VLOOKUP(F8,Control!$B:$C,2,FALSE) -> Legacy 2025 | S8: Dated | T8: 2025 | U8: =IFERROR(IF(H8>0,"Buy","Sell"),"") -> Sell | W8: =_xlfn.XLOOKUP(Table3[[#This Row],[Instrument]],Control!$B$2:$B$19,Control!$E$2:$E$19) -> #N/A | X8: =Table3[[#This Row],[Month1]] -> 0 | Y8: =Table3[[#This Row],[Quantity]] -> 0 | Z8: =_xlfn.XLOOKUP(Table3[[#This Row],[Instrument]],Control!$B$2:$B$19,Control!$F$2:$F$19) -> #N/A | AA8: =Table3[[#This Row],[Month2]] -> 0 | AB8: =-Y8 -> 0
D9: Legacy 2025 | E9: 46022 | F9: Legacy 2025 | M9: -274 | N9: =H9*K9 -> 0 | P9: =IF(H9<0,"Sell","Buy") -> Buy | Q9: =H9*L9 -> 0 | R9: =VLOOKUP(F9,Control!$B:$C,2,FALSE) -> Legacy 2025 | S9: MEH | T9: 2025 | U9: =IFERROR(IF(H9>0,"Buy","Sell"),"") -> Sell | W9: =_xlfn.XLOOKUP(Table3[[#This Row],[Instrument]],Control!$B$2:$B$19,Control!$E$2:$E$19) -> 0 | X9: =Table3[[#This Row],[Month1]] -> 0 | Y9: =Table3[[#This Row],[Quantity]] -> 0 | Z9: =_xlfn.XLOOKUP(Table3[[#This Row],[Instrument]],Control!$B$2:$B$19,Control!$F$2:$F$19) -> 0 | AA9: =Table3[[#This Row],[Month2]] -> 0 | AB9: =-Y9 -> 0
D10: Legacy 2025 | E10: 46022 | F10: Legacy 2025 | M10: -342 | N10: =H10*K10 -> 0 | P10: =IF(H10<0,"Sell","Buy") -> Buy | Q10: =H10*L10 -> 0 | R10: =VLOOKUP(F10,Control!$B:$C,2,FALSE) -> Legacy 2025 | S10: WTI-Brent | T10: 2025 | U10: =IFERROR(IF(H10>0,"Buy","Sell"),"") -> Sell | W10: =_xlfn.XLOOKUP(Table3[[#This Row],[Instrument]],Control!$B$2:$B$19,Control!$E$2:$E$19) -> WTI | X10: =Table3[[#This Row],[Month1]] -> 0 | Y10: =Table3[[#This Row],[Quantity]] -> 0 | Z10: =_xlfn.XLOOKUP(Table3[[#This Row],[Instrument]],Control!$B$2:$B$19,Control!$F$2:$F$19) -> Brent | AA10: =Table3[[#This Row],[Month2]] -> 0 | AB10: =-Y10 -> 0
A11: Cargoes | B11: =_xlfn.XLOOKUP(Table3[[#This Row],[Cargo Name]],Ledger[Cargo Name],Ledger[SAP Deal Number]) -> BPP25HS00089 | C11: 0 | D11: BP FOB VLCC Nov 15-20 | E11: 45944 | F11: WTI-Brent | G11: Expo | H11: -2100 | I11: 46053 | J11: 46053 | K11: -3.96 | L11: -4.65 | N11: 8316 | O11: Jan 26 | P11: Sell | Q11: 9765 | R11: Swaps | S11: WTI-Brent | T11: 2026 | U11: Sell | V11: Active | W11: =_xlfn.XLOOKUP(Table3[[#This Row],[Instrument]],Control!$B$2:$B$19,Control!$E$2:$E$19) -> WTI | X11: =Table3[[#This Row],[Month1]] -> 46053 | Y11: =Table3[[#This Row],[Quantity]] -> -2100 | Z11: =_xlfn.XLOOKUP(Table3[[#This Row],[Instrument]],Control!$B$2:$B$19,Control!$F$2:$F$19) -> Brent | AA11: =Table3[[#This Row],[Month2]] -> 46053 | AB11: =-Y11 -> 2100
A12: Cargoes | B12: =_xlfn.XLOOKUP(Table3[[#This Row],[Cargo Name]],Ledger[Cargo Name],Ledger[SAP Deal Number]) -> ARA26HS00006 | C12: 0 | D12: CPC Taiwan Jan 17-21 | E12: 45947 | F12: Physical | G12: Expo | H12: 2100 | I12: 45991 | J12: 45991 | K12: ='Cargo Econs 2025'!$J$343 -> 3.8866667 | L12: ='Cargo Econs 2025'!$J$344 -> 3.98 | M12: =IFERROR((L12-K12)*H12,"") -> 196 | N12: =H12*K12 -> 8162 | O12: =IF(I12=J12,TEXT(I12,"MMM YY"),TEXT(I12,"MMM")&"/"&TEXT(J12,"MMM")&" "&RIGHT(T12,2)) -> Nov 25 | P12: =IF(H12<0,"Sell","Buy") -> Buy | Q12: =H12*L12 -> 8358 | R12: =VLOOKUP(F12,Control!$B:$C,2,FALSE) -> Physical | S12: =VLOOKUP(F12,Control!$B:$D,3,FALSE) -> Physical | T12: =YEAR(I12) -> 2025 | U12: =IFERROR(IF(H12>0,"Buy","Sell"),"") -> Buy | V12: Active | W12: =_xlfn.XLOOKUP(Table3[[#This Row],[Instrument]],Control!$B$2:$B$19,Control!$E$2:$E$19) -> 0 | X12: =Table3[[#This Row],[Month1]] -> 45991 | Y12: =Table3[[#This Row],[Quantity]] -> 2100 | Z12: =_xlfn.XLOOKUP(Table3[[#This Row],[Instrument]],Control!$B$2:$B$19,Control!$F$2:$F$19) -> 0 | AA12: =Table3[[#This Row],[Month2]] -> 45991 | AB12: =-Y12 -> -2100
A13: Cargoes | B13: =_xlfn.XLOOKUP(Table3[[#This Row],[Cargo Name]],Ledger[Cargo Name],Ledger[SAP Deal Number]) -> ARA26HS00006 | C13: 0 | D13: CPC Taiwan Jan 17-21 | E13: 45947 | F13: WTI-Brent | G13: Expo | H13: -2100 | I13: 46053 | J13: 46053 | K13: -3.95 | L13: =IF(OR(S13="WTI Sprds",S13="Brent Sprds",S13="WTI-Brent",S13="DFL"),INDEX(INDIRECT("'" & S13 & "'!$A$6:$XFD$1048576"),MATCH('PnL26'!$P$1,INDIRECT("'" & S13 & "'!$A$6:$A$1048576"),0),MATCH(EOMONTH(I13,0),INDIRECT("'" & S13 & "'!$A$4:$XFD$4"),0)),INDEX(BBG!$A:$BA,MATCH('PnL26'!$P$1,BBG!$A:$A,0),MATCH($I13,BBG!$A$4:$BA$4,0))-INDEX(BBG!$A:$BA,MATCH('PnL26'!$P$1,BBG!$A:$A,0),MATCH($J13,BBG!$A$4:$BA$4,0))) -> -4.65 | N13: =H13*K13 -> 8295 | O13: =IF(I13=J13,TEXT(I13,"MMM YY"),TEXT(I13,"MMM")&"/"&TEXT(J13,"MMM")&" "&RIGHT(T13,2)) -> Jan 26 | P13: =IF(H13<0,"Sell","Buy") -> Sell | Q13: =H13*L13 -> 9765 | R13: =VLOOKUP(F13,Control!$B:$C,2,FALSE) -> Swaps | S13: =VLOOKUP(F13,Control!$B:$D,3,FALSE) -> WTI-Brent | T13: =YEAR(I13) -> 2026 | U13: =IFERROR(IF(H13>0,"Buy","Sell"),"") -> Sell | V13: Active | W13: =_xlfn.XLOOKUP(Table3[[#This Row],[Instrument]],Control!$B$2:$B$19,Control!$E$2:$E$19) -> WTI | X13: =Table3[[#This Row],[Month1]] -> 46053 | Y13: =Table3[[#This Row],[Quantity]] -> -2100 | Z13: =_xlfn.XLOOKUP(Table3[[#This Row],[Instrument]],Control!$B$2:$B$19,Control!$F$2:$F$19) -> Brent | AA13: =Table3[[#This Row],[Month2]] -> 46053 | AB13: =-Y13 -> 2100
A14: Cargoes | B14: =_xlfn.XLOOKUP(Table3[[#This Row],[Cargo Name]],Ledger[Cargo Name],Ledger[SAP Deal Number]) -> ARA26HS00006 | C14: 0 | D14: CPC Taiwan Jan 17-21 | E14: 45958 | F14: WTI-Brent | G14: Hedge | H14: 1000 | I14: 46053 | J14: 46053 | K14: -4.05 | L14: =IF(OR(S14="WTI Sprds",S14="Brent Sprds",S14="WTI-Brent",S14="DFL"),INDEX(INDIRECT("'" & S14 & "'!$A$6:$XFD$1048576"),MATCH('PnL26'!$P$1,INDIRECT("'" & S14 & "'!$A$6:$A$1048576"),0),MATCH(EOMONTH(I14,0),INDIRECT("'" & S14 & "'!$A$4:$XFD$4"),0)),INDEX(BBG!$A:$BA,MATCH('PnL26'!$P$1,BBG!$A:$A,0),MATCH($I14,BBG!$A$4:$BA$4,0))-INDEX(BBG!$A:$BA,MATCH('PnL26'!$P$1,BBG!$A:$A,0),MATCH($J14,BBG!$A$4:$BA$4,0))) -> -4.65 | N14: =H14*K14 -> -4050 | O14: =IF(I14=J14,TEXT(I14,"MMM YY"),TEXT(I14,"MMM")&"/"&TEXT(J14,"MMM")&" "&RIGHT(T14,2)) -> Jan 26 | P14: =IF(H14<0,"Sell","Buy") -> Buy | Q14: =H14*L14 -> -4650 | R14: =VLOOKUP(F14,Control!$B:$C,2,FALSE) -> Swaps | S14: =VLOOKUP(F14,Control!$B:$D,3,FALSE) -> WTI-Brent | T14: =YEAR(I14) -> 2026 | U14: =IFERROR(IF(H14>0,"Buy","Sell"),"") -> Buy | V14: Active | W14: =_xlfn.XLOOKUP(Table3[[#This Row],[Instrument]],Control!$B$2:$B$19,Control!$E$2:$E$19) -> WTI | X14: =Table3[[#This Row],[Month1]] -> 46053 | Y14: =Table3[[#This Row],[Quantity]] -> 1000 | Z14: =_xlfn.XLOOKUP(Table3[[#This Row],[Instrument]],Control!$B$2:$B$19,Control!$F$2:$F$19) -> Brent | AA14: =Table3[[#This Row],[Month2]] -> 46053 | AB14: =-Y14 -> -1000
A15: Cargoes | B15: =_xlfn.XLOOKUP(Table3[[#This Row],[Cargo Name]],Ledger[Cargo Name],Ledger[SAP Deal Number]) -> Unallocated | C15: 0 | D15: Unallocated | E15: 45959 | F15: WTI-Brent | G15: Hedge | H15: 1000 | I15: 46053 | J15: 46053 | K15: -4.2 | L15: =IF(OR(S15="WTI Sprds",S15="Brent Sprds",S15="WTI-Brent",S15="DFL"),INDEX(INDIRECT("'" & S15 & "'!$A$6:$XFD$1048576"),MATCH('PnL26'!$P$1,INDIRECT("'" & S15 & "'!$A$6:$A$1048576"),0),MATCH(EOMONTH(I15,0),INDIRECT("'" & S15 & "'!$A$4:$XFD$4"),0)),INDEX(BBG!$A:$BA,MATCH('PnL26'!$P$1,BBG!$A:$A,0),MATCH($I15,BBG!$A$4:$BA$4,0))-INDEX(BBG!$A:$BA,MATCH('PnL26'!$P$1,BBG!$A:$A,0),MATCH($J15,BBG!$A$4:$BA$4,0))) -> -4.65 | N15: =H15*K15 -> -4200 | O15: =IF(I15=J15,TEXT(I15,"MMM YY"),TEXT(I15,"MMM")&"/"&TEXT(J15,"MMM")&" "&RIGHT(T15,2)) -> Jan 26 | P15: =IF(H15<0,"Sell","Buy") -> Buy | Q15: =H15*L15 -> -4650 | R15: =VLOOKUP(F15,Control!$B:$C,2,FALSE) -> Swaps | S15: =VLOOKUP(F15,Control!$B:$D,3,FALSE) -> WTI-Brent | T15: =YEAR(I15) -> 2026 | U15: =IFERROR(IF(H15>0,"Buy","Sell"),"") -> Buy | V15: Active | W15: =_xlfn.XLOOKUP(Table3[[#This Row],[Instrument]],Control!$B$2:$B$19,Control!$E$2:$E$19) -> WTI | X15: =Table3[[#This Row],[Month1]] -> 46053 | Y15: =Table3[[#This Row],[Quantity]] -> 1000 | Z15: =_xlfn.XLOOKUP(Table3[[#This Row],[Instrument]],Control!$B$2:$B$19,Control!$F$2:$F$19) -> Brent | AA15: =Table3[[#This Row],[Month2]] -> 46053 | AB15: =-Y15 -> -1000
A16: Cargoes | B16: =_xlfn.XLOOKUP(Table3[[#This Row],[Cargo Name]],Ledger[Cargo Name],Ledger[SAP Deal Number]) -> #N/A | C16: 0 | D16: Dec25 EFP 2 | E16: 45960 | F16: WTI-Brent | G16: Expo | H16: 0 | I16: 46053 | J16: 46053 | L16: =IF(OR(S16="WTI Sprds",S16="Brent Sprds",S16="WTI-Brent",S16="DFL"),INDEX(INDIRECT("'" & S16 & "'!$A$6:$XFD$1048576"),MATCH('PnL26'!$P$1,INDIRECT("'" & S16 & "'!$A$6:$A$1048576"),0),MATCH(EOMONTH(I16,0),INDIRECT("'" & S16 & "'!$A$4:$XFD$4"),0)),INDEX(BBG!$A:$BA,MATCH('PnL26'!$P$1,BBG!$A:$A,0),MATCH($I16,BBG!$A$4:$BA$4,0))-INDEX(BBG!$A:$BA,MATCH('PnL26'!$P$1,BBG!$A:$A,0),MATCH($J16,BBG!$A$4:$BA$4,0))) -> -4.65 | N16: =H16*K16 -> 0 | O16: =IF(I16=J16,TEXT(I16,"MMM YY"),TEXT(I16,"MMM")&"/"&TEXT(J16,"MMM")&" "&RIGHT(T16,2)) -> Jan 26 | P16: =IF(H16<0,"Sell","Buy") -> Buy | Q16: =H16*L16 -> 0 | R16: =VLOOKUP(F16,Control!$B:$C,2,FALSE) -> Swaps | S16: =VLOOKUP(F16,Control!$B:$D,3,FALSE) -> WTI-Brent | T16: =YEAR(I16) -> 2026 | U16: =IFERROR(IF(H16>0,"Buy","Sell"),"") -> Sell | V16: Active | W16: =_xlfn.XLOOKUP(Table3[[#This Row],[Instrument]],Control!$B$2:$B$19,Control!$E$2:$E$19) -> WTI | X16: =Table3[[#This Row],[Month1]] -> 46053 | Y16: =Table3[[#This Row],[Quantity]] -> 0 | Z16: =_xlfn.XLOOKUP(Table3[[#This Row],[Instrument]],Control!$B$2:$B$19,Control!$F$2:$F$19) -> Brent | AA16: =Table3[[#This Row],[Month2]] -> 46053 | AB16: =-Y16 -> 0
A17: Cargoes | B17: =_xlfn.XLOOKUP(Table3[[#This Row],[Cargo Name]],Ledger[Cargo Name],Ledger[SAP Deal Number]) -> #N/A | C17: 0 | D17: Dec25 EFP 2 | E17: 45966 | F17: WTI-Brent | G17: Hedge | H17: 1200 | I17: 46053 | J17: 46053 | K17: -4.1 | L17: =IF(OR(S17="WTI Sprds",S17="Brent Sprds",S17="WTI-Brent",S17="DFL"),INDEX(INDIRECT("'" & S17 & "'!$A$6:$XFD$1048576"),MATCH('PnL26'!$P$1,INDIRECT("'" & S17 & "'!$A$6:$A$1048576"),0),MATCH(EOMONTH(I17,0),INDIRECT("'" & S17 & "'!$A$4:$XFD$4"),0)),INDEX(BBG!$A:$BA,MATCH('PnL26'!$P$1,BBG!$A:$A,0),MATCH($I17,BBG!$A$4:$BA$4,0))-INDEX(BBG!$A:$BA,MATCH('PnL26'!$P$1,BBG!$A:$A,0),MATCH($J17,BBG!$A$4:$BA$4,0))) -> -4.65 | N17: =H17*K17 -> -4920 | O17: =IF(I17=J17,TEXT(I17,"MMM YY"),TEXT(I17,"MMM")&"/"&TEXT(J17,"MMM")&" "&RIGHT(T17,2)) -> Jan 26 | P17: =IF(H17<0,"Sell","Buy") -> Buy | Q17: =H17*L17 -> -5580 | R17: =VLOOKUP(F17,Control!$B:$C,2,FALSE) -> Swaps | S17: =VLOOKUP(F17,Control!$B:$D,3,FALSE) -> WTI-Brent | T17: =YEAR(I17) -> 2026 | U17: =IFERROR(IF(H17>0,"Buy","Sell"),"") -> Buy | V17: Active | W17: =_xlfn.XLOOKUP(Table3[[#This Row],[Instrument]],Control!$B$2:$B$19,Control!$E$2:$E$19) -> WTI | X17: =Table3[[#This Row],[Month1]] -> 46053 | Y17: =Table3[[#This Row],[Quantity]] -> 1200 | Z17: =_xlfn.XLOOKUP(Table3[[#This Row],[Instrument]],Control!$B$2:$B$19,Control!$F$2:$F$19) -> Brent | AA17: =Table3[[#This Row],[Month2]] -> 46053 | AB17: =-Y17 -> -1200
A18: Cargoes | B18: =_xlfn.XLOOKUP(Table3[[#This Row],[Cargo Name]],Ledger[Cargo Name],Ledger[SAP Deal Number]) -> #N/A | C18: 0 | D18: Dec25 EFP 2 | E18: 45966 | F18: WTI-Brent | G18: Hedge | H18: 893 | I18: 46053 | J18: 46053 | K18: -4.15 | L18: =IF(OR(S18="WTI Sprds",S18="Brent Sprds",S18="WTI-Brent",S18="DFL"),INDEX(INDIRECT("'" & S18 & "'!$A$6:$XFD$1048576"),MATCH('PnL26'!$P$1,INDIRECT("'" & S18 & "'!$A$6:$A$1048576"),0),MATCH(EOMONTH(I18,0),INDIRECT("'" & S18 & "'!$A$4:$XFD$4"),0)),INDEX(BBG!$A:$BA,MATCH('PnL26'!$P$1,BBG!$A:$A,0),MATCH($I18,BBG!$A$4:$BA$4,0))-INDEX(BBG!$A:$BA,MATCH('PnL26'!$P$1,BBG!$A:$A,0),MATCH($J18,BBG!$A$4:$BA$4,0))) -> -4.65 | N18: =H18*K18 -> -3705.95 | O18: =IF(I18=J18,TEXT(I18,"MMM YY"),TEXT(I18,"MMM")&"/"&TEXT(J18,"MMM")&" "&RIGHT(T18,2)) -> Jan 26 | P18: =IF(H18<0,"Sell","Buy") -> Buy | Q18: =H18*L18 -> -4152.45 | R18: =VLOOKUP(F18,Control!$B:$C,2,FALSE) -> Swaps | S18: =VLOOKUP(F18,Control!$B:$D,3,FALSE) -> WTI-Brent | T18: =YEAR(I18) -> 2026 | U18: =IFERROR(IF(H18>0,"Buy","Sell"),"") -> Buy | V18: Active | W18: =_xlfn.XLOOKUP(Table3[[#This Row],[Instrument]],Control!$B$2:$B$19,Control!$E$2:$E$19) -> WTI | X18: =Table3[[#This Row],[Month1]] -> 46053 | Y18: =Table3[[#This Row],[Quantity]] -> 893 | Z18: =_xlfn.XLOOKUP(Table3[[#This Row],[Instrument]],Control!$B$2:$B$19,Control!$F$2:$F$19) -> Brent | AA18: =Table3[[#This Row],[Month2]] -> 46053 | AB18: =-Y18 -> -893
A19: Cargoes | B19: =_xlfn.XLOOKUP(Table3[[#This Row],[Cargo Name]],Ledger[Cargo Name],Ledger[SAP Deal Number]) -> ARA26HS00007 | C19: 0 | D19: HDO Feb26 5-15 | E19: 45973 | F19: WTI-Brent | G19: Expo | H19: -2100 | I19: 46081 | J19: 46081 | K19: -3.98 | L19: =IF(OR(S19="WTI Sprds",S19="Brent Sprds",S19="WTI-Brent",S19="DFL"),INDEX(INDIRECT("'" & S19 & "'!$A$6:$XFD$1048576"),MATCH('PnL26'!$P$1,INDIRECT("'" & S19 & "'!$A$6:$A$1048576"),0),MATCH(EOMONTH(I19,0),INDIRECT("'" & S19 & "'!$A$4:$XFD$4"),0)),INDEX(BBG!$A:$BA,MATCH('PnL26'!$P$1,BBG!$A:$A,0),MATCH($I19,BBG!$A$4:$BA$4,0))-INDEX(BBG!$A:$BA,MATCH('PnL26'!$P$1,BBG!$A:$A,0),MATCH($J19,BBG!$A$4:$BA$4,0))) -> -3.97 | M19: =IFERROR((L19-K19)*H19,"") -> -21 | N19: =H19*K19 -> 8358 | O19: =IF(I19=J19,TEXT(I19,"MMM YY"),TEXT(I19,"MMM")&"/"&TEXT(J19,"MMM")&" "&RIGHT(T19,2)) -> Feb 26 | P19: =IF(H19<0,"Sell","Buy") -> Sell | Q19: =H19*L19 -> 8337 | R19: =VLOOKUP(F19,Control!$B:$C,2,FALSE) -> Swaps | S19: =VLOOKUP(F19,Control!$B:$D,3,FALSE) -> WTI-Brent | T19: =YEAR(I19) -> 2026 | U19: =IFERROR(IF(H19>0,"Buy","Sell"),"") -> Sell | V19: Active | W19: =_xlfn.XLOOKUP(Table3[[#This Row],[Instrument]],Control!$B$2:$B$19,Control!$E$2:$E$19) -> WTI | X19: =Table3[[#This Row],[Month1]] -> 46081 | Y19: =Table3[[#This Row],[Quantity]] -> -2100 | Z19: =_xlfn.XLOOKUP(Table3[[#This Row],[Instrument]],Control!$B$2:$B$19,Control!$F$2:$F$19) -> Brent | AA19: =Table3[[#This Row],[Month2]] -> 46081 | AB19: =-Y19 -> 2100
A20: Cargoes | B20: =_xlfn.XLOOKUP(Table3[[#This Row],[Cargo Name]],Ledger[Cargo Name],Ledger[SAP Deal Number]) -> ARA26HS00007 | C20: 0 | D20: HDO Feb26 5-15 | E20: 45973 | F20: Brent Sprds | G20: Expo | H20: -2005 | I20: 46081 | J20: 46112 | K20: 0.15 | L20: =IF(OR(S20="WTI Sprds",S20="Brent Sprds",S20="WTI-Brent",S20="DFL"),INDEX(INDIRECT("'" & S20 & "'!$A$6:$XFD$1048576"),MATCH('PnL26'!$P$1,INDIRECT("'" & S20 & "'!$A$6:$A$1048576"),0),MATCH(EOMONTH(I20,0),INDIRECT("'" & S20 & "'!$A$4:$XFD$4"),0)),INDEX(BBG!$A:$BA,MATCH('PnL26'!$P$1,BBG!$A:$A,0),MATCH($I20,BBG!$A$4:$BA$4,0))-INDEX(BBG!$A:$BA,MATCH('PnL26'!$P$1,BBG!$A:$A,0),MATCH($J20,BBG!$A$4:$BA$4,0))) -> 0.59 | M20: =IFERROR((L20-K20)*H20,"") -> -882.2 | N20: =H20*K20 -> -300.75 | O20: =IF(I20=J20,TEXT(I20,"MMM YY"),TEXT(I20,"MMM")&"/"&TEXT(J20,"MMM")&" "&RIGHT(T20,2)) -> Feb/Mar 26 | P20: =IF(H20<0,"Sell","Buy") -> Sell | Q20: =H20*L20 -> -1182.95 | R20: =VLOOKUP(F20,Control!$B:$C,2,FALSE) -> Futures | S20: =VLOOKUP(F20,Control!$B:$D,3,FALSE) -> Brent Sprds | T20: =YEAR(I20) -> 2026 | U20: =IFERROR(IF(H20>0,"Buy","Sell"),"") -> Sell | V20: Active | W20: =_xlfn.XLOOKUP(Table3[[#This Row],[Instrument]],Control!$B$2:$B$19,Control!$E$2:$E$19) -> Brent | X20: =Table3[[#This Row],[Month1]] -> 46081 | Y20: =Table3[[#This Row],[Quantity]] -> -2005 | Z20: =_xlfn.XLOOKUP(Table3[[#This Row],[Instrument]],Control!$B$2:$B$19,Control!$F$2:$F$19) -> Brent | AA20: =Table3[[#This Row],[Month2]] -> 46112 | AB20: =-Y20 -> 2005
A21: Cargoes | B21: =_xlfn.XLOOKUP(Table3[[#This Row],[Cargo Name]],Ledger[Cargo Name],Ledger[SAP Deal Number]) -> ARA26HS00007 | C21: 0 | D21: HDO Feb26 5-15 | E21: 45973 | F21: Brent Sprds | G21: Expo | H21: -95 | I21: 46112 | J21: 46142 | K21: 0.05 | L21: =IF(OR(S21="WTI Sprds",S21="Brent Sprds",S21="WTI-Brent",S21="DFL"),INDEX(INDIRECT("'" & S21 & "'!$A$6:$XFD$1048576"),MATCH('PnL26'!$P$1,INDIRECT("'" & S21 & "'!$A$6:$A$1048576"),0),MATCH(EOMONTH(I21,0),INDIRECT("'" & S21 & "'!$A$4:$XFD$4"),0)),INDEX(BBG!$A:$BA,MATCH('PnL26'!$P$1,BBG!$A:$A,0),MATCH($I21,BBG!$A$4:$BA$4,0))-INDEX(BBG!$A:$BA,MATCH('PnL26'!$P$1,BBG!$A:$A,0),MATCH($J21,BBG!$A$4:$BA$4,0))) -> 1.37 | M21: =IFERROR((L21-K21)*H21,"") -> -125.4 | N21: =H21*K21 -> -4.75 | O21: =IF(I21=J21,TEXT(I21,"MMM YY"),TEXT(I21,"MMM")&"/"&TEXT(J21,"MMM")&" "&RIGHT(T21,2)) -> Mar/Apr 26 | P21: =IF(H21<0,"Sell","Buy") -> Sell | Q21: =H21*L21 -> -130.15 | R21: =VLOOKUP(F21,Control!$B:$C,2,FALSE) -> Futures | S21: =VLOOKUP(F21,Control!$B:$D,3,FALSE) -> Brent Sprds | T21: =YEAR(I21) -> 2026 | U21: =IFERROR(IF(H21>0,"Buy","Sell"),"") -> Sell | V21: Active | W21: =_xlfn.XLOOKUP(Table3[[#This Row],[Instrument]],Control!$B$2:$B$19,Control!$E$2:$E$19) -> Brent | X21: =Table3[[#This Row],[Month1]] -> 46112 | Y21: =Table3[[#This Row],[Quantity]] -> -95 | Z21: =_xlfn.XLOOKUP(Table3[[#This Row],[Instrument]],Control!$B$2:$B$19,Control!$F$2:$F$19) -> Brent | AA21: =Table3[[#This Row],[Month2]] -> 46142 | AB21: =-Y21 -> 95
A22: Cargoes | B22: =_xlfn.XLOOKUP(Table3[[#This Row],[Cargo Name]],Ledger[Cargo Name],Ledger[SAP Deal Number]) -> ARA26HS00007 | C22: 0 | D22: HDO Feb26 5-15 | E22: 45972 | F22: WTI-Brent | G22: Hedge | H22: 725 | I22: 46081 | J22: 46081 | K22: -4 | L22: =IF(OR(S22="WTI Sprds",S22="Brent Sprds",S22="WTI-Brent",S22="DFL"),INDEX(INDIRECT("'" & S22 & "'!$A$6:$XFD$1048576"),MATCH('PnL26'!$P$1,INDIRECT("'" & S22 & "'!$A$6:$A$1048576"),0),MATCH(EOMONTH(I22,0),INDIRECT("'" & S22 & "'!$A$4:$XFD$4"),0)),INDEX(BBG!$A:$BA,MATCH('PnL26'!$P$1,BBG!$A:$A,0),MATCH($I22,BBG!$A$4:$BA$4,0))-INDEX(BBG!$A:$BA,MATCH('PnL26'!$P$1,BBG!$A:$A,0),MATCH($J22,BBG!$A$4:$BA$4,0))) -> -3.97 | M22: =IFERROR((L22-K22)*H22,"") -> 21.75 | N22: =H22*K22 -> -2900 | O22: =IF(I22=J22,TEXT(I22,"MMM YY"),TEXT(I22,"MMM")&"/"&TEXT(J22,"MMM")&" "&RIGHT(T22,2)) -> Feb 26 | P22: =IF(H22<0,"Sell","Buy") -> Buy | Q22: =H22*L22 -> -2878.25 | R22: =VLOOKUP(F22,Control!$B:$C,2,FALSE) -> Swaps | S22: =VLOOKUP(F22,Control!$B:$D,3,FALSE) -> WTI-Brent | T22: =YEAR(I22) -> 2026 | U22: =IFERROR(IF(H22>0,"Buy","Sell"),"") -> Buy | V22: Active | W22: =_xlfn.XLOOKUP(Table3[[#This Row],[Instrument]],Control!$B$2:$B$19,Control!$E$2:$E$19) -> WTI | X22: =Table3[[#This Row],[Month1]] -> 46081 | Y22: =Table3[[#This Row],[Quantity]] -> 725 | Z22: =_xlfn.XLOOKUP(Table3[[#This Row],[Instrument]],Control!$B$2:$B$19,Control!$F$2:$F$19) -> Brent | AA22: =Table3[[#This Row],[Month2]] -> 46081 | AB22: =-Y22 -> -725
A23: Cargoes | B23: =_xlfn.XLOOKUP(Table3[[#This Row],[Cargo Name]],Ledger[Cargo Name],Ledger[SAP Deal Number]) -> ARA26HS00007 | C23: 0 | D23: HDO Feb26 5-15 | E23: 45973 | F23: WTI-Brent | G23: Hedge | H23: 1400 | I23: 46081 | J23: 46081 | K23: -4.03 | L23: =IF(OR(S23="WTI Sprds",S23="Brent Sprds",S23="WTI-Brent",S23="DFL"),INDEX(INDIRECT("'" & S23 & "'!$A$6:$XFD$1048576"),MATCH('PnL26'!$P$1,INDIRECT("'" & S23 & "'!$A$6:$A$1048576"),0),MATCH(EOMONTH(I23,0),INDIRECT("'" & S23 & "'!$A$4:$XFD$4"),0)),INDEX(BBG!$A:$BA,MATCH('PnL26'!$P$1,BBG!$A:$A,0),MATCH($I23,BBG!$A$4:$BA$4,0))-INDEX(BBG!$A:$BA,MATCH('PnL26'!$P$1,BBG!$A:$A,0),MATCH($J23,BBG!$A$4:$BA$4,0))) -> -3.97 | M23: =IFERROR((L23-K23)*H23,"") -> 84 | N23: =H23*K23 -> -5642 | O23: =IF(I23=J23,TEXT(I23,"MMM YY"),TEXT(I23,"MMM")&"/"&TEXT(J23,"MMM")&" "&RIGHT(T23,2)) -> Feb 26 | P23: =IF(H23<0,"Sell","Buy") -> Buy | Q23: =H23*L23 -> -5558 | R23: =VLOOKUP(F23,Control!$B:$C,2,FALSE) -> Swaps | S23: =VLOOKUP(F23,Control!$B:$D,3,FALSE) -> WTI-Brent | T23: =YEAR(I23) -> 2026 | U23: =IFERROR(IF(H23>0,"Buy","Sell"),"") -> Buy | V23: Active | W23: =_xlfn.XLOOKUP(Table3[[#This Row],[Instrument]],Control!$B$2:$B$19,Control!$E$2:$E$19) -> WTI | X23: =Table3[[#This Row],[Month1]] -> 46081 | Y23: =Table3[[#This Row],[Quantity]] -> 1400 | Z23: =_xlfn.XLOOKUP(Table3[[#This Row],[Instrument]],Control!$B$2:$B$19,Control!$F$2:$F$19) -> Brent | AA23: =Table3[[#This Row],[Month2]] -> 46081 | AB23: =-Y23 -> -1400
A24: Cargoes | B24: =_xlfn.XLOOKUP(Table3[[#This Row],[Cargo Name]],Ledger[Cargo Name],Ledger[SAP Deal Number]) -> ARA26HS00007 | C24: 0 | D24: HDO Feb26 5-15 | E24: 45978 | F24: Brent Sprds | G24: Hedge | H24: 200 | I24: 46081 | J24: 46112 | K24: 0.25 | L24: =IF(OR(S24="WTI Sprds",S24="Brent Sprds",S24="WTI-Brent",S24="DFL"),INDEX(INDIRECT("'" & S24 & "'!$A$6:$XFD$1048576"),MATCH('PnL26'!$P$1,INDIRECT("'" & S24 & "'!$A$6:$A$1048576"),0),MATCH(EOMONTH(I24,0),INDIRECT("'" & S24 & "'!$A$4:$XFD$4"),0)),INDEX(BBG!$A:$BA,MATCH('PnL26'!$P$1,BBG!$A:$A,0),MATCH($I24,BBG!$A$4:$BA$4,0))-INDEX(BBG!$A:$BA,MATCH('PnL26'!$P$1,BBG!$A:$A,0),MATCH($J24,BBG!$A$4:$BA$4,0))) -> 0.59 | M24: =IFERROR((L24-K24)*H24,"") -> 68 | N24: =H24*K24 -> 50 | O24: =IF(I24=J24,TEXT(I24,"MMM YY"),TEXT(I24,"MMM")&"/"&TEXT(J24,"MMM")&" "&RIGHT(T24,2)) -> Feb/Mar 26 | P24: =IF(H24<0,"Sell","Buy") -> Buy | Q24: =H24*L24 -> 118 | R24: =VLOOKUP(F24,Control!$B:$C,2,FALSE) -> Futures | S24: =VLOOKUP(F24,Control!$B:$D,3,FALSE) -> Brent Sprds | T24: =YEAR(I24) -> 2026 | U24: =IFERROR(IF(H24>0,"Buy","Sell"),"") -> Buy | V24: Active | W24: =_xlfn.XLOOKUP(Table3[[#This Row],[Instrument]],Control!$B$2:$B$19,Control!$E$2:$E$19) -> Brent | X24: =Table3[[#This Row],[Month1]] -> 46081 | Y24: =Table3[[#This Row],[Quantity]] -> 200 | Z24: =_xlfn.XLOOKUP(Table3[[#This Row],[Instrument]],Control!$B$2:$B$19,Control!$F$2:$F$19) -> Brent | AA24: =Table3[[#This Row],[Month2]] -> 46112 | AB24: =-Y24 -> -200
A25: Cargoes | B25: =_xlfn.XLOOKUP(Table3[[#This Row],[Cargo Name]],Ledger[Cargo Name],Ledger[SAP Deal Number]) -> ARA26HS00007 | C25: 0 | D25: HDO Feb26 5-15 | E25: 45978 | F25: Brent Sprds | G25: Hedge | H25: 200 | I25: 46081 | J25: 46112 | K25: 0.24 | L25: =IF(OR(S25="WTI Sprds",S25="Brent Sprds",S25="WTI-Brent",S25="DFL"),INDEX(INDIRECT("'" & S25 & "'!$A$6:$XFD$1048576"),MATCH('PnL26'!$P$1,INDIRECT("'" & S25 & "'!$A$6:$A$1048576"),0),MATCH(EOMONTH(I25,0),INDIRECT("'" & S25 & "'!$A$4:$XFD$4"),0)),INDEX(BBG!$A:$BA,MATCH('PnL26'!$P$1,BBG!$A:$A,0),MATCH($I25,BBG!$A$4:$BA$4,0))-INDEX(BBG!$A:$BA,MATCH('PnL26'!$P$1,BBG!$A:$A,0),MATCH($J25,BBG!$A$4:$BA$4,0))) -> 0.59 | M25: =IFERROR((L25-K25)*H25,"") -> 70 | N25: =H25*K25 -> 48 | O25: =IF(I25=J25,TEXT(I25,"MMM YY"),TEXT(I25,"MMM")&"/"&TEXT(J25,"MMM")&" "&RIGHT(T25,2)) -> Feb/Mar 26 | P25: =IF(H25<0,"Sell","Buy") -> Buy | Q25: =H25*L25 -> 118 | R25: =VLOOKUP(F25,Control!$B:$C,2,FALSE) -> Futures | S25: =VLOOKUP(F25,Control!$B:$D,3,FALSE) -> Brent Sprds | T25: =YEAR(I25) -> 2026 | U25: =IFERROR(IF(H25>0,"Buy","Sell"),"") -> Buy | V25: Active | W25: =_xlfn.XLOOKUP(Table3[[#This Row],[Instrument]],Control!$B$2:$B$19,Control!$E$2:$E$19) -> Brent | X25: =Table3[[#This Row],[Month1]] -> 46081 | Y25: =Table3[[#This Row],[Quantity]] -> 200 | Z25: =_xlfn.XLOOKUP(Table3[[#This Row],[Instrument]],Control!$B$2:$B$19,Control!$F$2:$F$19) -> Brent | AA25: =Table3[[#This Row],[Month2]] -> 46112 | AB25: =-Y25 -> -200
A26: Cargoes | B26: =_xlfn.XLOOKUP(Table3[[#This Row],[Cargo Name]],Ledger[Cargo Name],Ledger[SAP Deal Number]) -> #N/A | C26: 0 | E26: 45979 | F26: WTI-Brent | G26: Expo | H26: -700 | I26: 46081 | J26: 46081 | K26: -4 | L26: =IF(OR(S26="WTI Sprds",S26="Brent Sprds",S26="WTI-Brent",S26="DFL"),INDEX(INDIRECT("'" & S26 & "'!$A$6:$XFD$1048576"),MATCH('PnL26'!$P$1,INDIRECT("'" & S26 & "'!$A$6:$A$1048576"),0),MATCH(EOMONTH(I26,0),INDIRECT("'" & S26 & "'!$A$4:$XFD$4"),0)),INDEX(BBG!$A:$BA,MATCH('PnL26'!$P$1,BBG!$A:$A,0),MATCH($I26,BBG!$A$4:$BA$4,0))-INDEX(BBG!$A:$BA,MATCH('PnL26'!$P$1,BBG!$A:$A,0),MATCH($J26,BBG!$A$4:$BA$4,0))) -> -3.97 | M26: =IFERROR((L26-K26)*H26,"") -> -21 | N26: =H26*K26 -> 2800 | O26: =IF(I26=J26,TEXT(I26,"MMM YY"),TEXT(I26,"MMM")&"/"&TEXT(J26,"MMM")&" "&RIGHT(T26,2)) -> Feb 26 | P26: =IF(H26<0,"Sell","Buy") -> Sell | Q26: =H26*L26 -> 2779 | R26: =VLOOKUP(F26,Control!$B:$C,2,FALSE) -> Swaps | S26: =VLOOKUP(F26,Control!$B:$D,3,FALSE) -> WTI-Brent | T26: =YEAR(I26) -> 2026 | U26: =IFERROR(IF(H26>0,"Buy","Sell"),"") -> Sell | V26: Active | W26: =_xlfn.XLOOKUP(Table3[[#This Row],[Instrument]],Control!$B$2:$B$19,Control!$E$2:$E$19) -> WTI | X26: =Table3[[#This Row],[Month1]] -> 46081 | Y26: =Table3[[#This Row],[Quantity]] -> -700 | Z26: =_xlfn.XLOOKUP(Table3[[#This Row],[Instrument]],Control!$B$2:$B$19,Control!$F$2:$F$19) -> Brent | AA26: =Table3[[#This Row],[Month2]] -> 46081 | AB26: =-Y26 -> 700
A27: Cargoes | B27: =_xlfn.XLOOKUP(Table3[[#This Row],[Cargo Name]],Ledger[Cargo Name],Ledger[SAP Deal Number]) -> #N/A | C27: 0 | E27: 45979 | F27: WTI-Brent | G27: Hedge | H27: 350 | I27: 46081 | J27: 46081 | K27: =K28-0.34 -> -4.02 | L27: =IF(OR(S27="WTI Sprds",S27="Brent Sprds",S27="WTI-Brent",S27="DFL"),INDEX(INDIRECT("'" & S27 & "'!$A$6:$XFD$1048576"),MATCH('PnL26'!$P$1,INDIRECT("'" & S27 & "'!$A$6:$A$1048576"),0),MATCH(EOMONTH(I27,0),INDIRECT("'" & S27 & "'!$A$4:$XFD$4"),0)),INDEX(BBG!$A:$BA,MATCH('PnL26'!$P$1,BBG!$A:$A,0),MATCH($I27,BBG!$A$4:$BA$4,0))-INDEX(BBG!$A:$BA,MATCH('PnL26'!$P$1,BBG!$A:$A,0),MATCH($J27,BBG!$A$4:$BA$4,0))) -> -3.97 | M27: =IFERROR((L27-K27)*H27,"") -> 17.5 | N27: =H27*K27 -> -1407 | O27: =IF(I27=J27,TEXT(I27,"MMM YY"),TEXT(I27,"MMM")&"/"&TEXT(J27,"MMM")&" "&RIGHT(T27,2)) -> Feb 26 | P27: =IF(H27<0,"Sell","Buy") -> Buy | Q27: =H27*L27 -> -1389.5 | R27: =VLOOKUP(F27,Control!$B:$C,2,FALSE) -> Swaps | S27: =VLOOKUP(F27,Control!$B:$D,3,FALSE) -> WTI-Brent | T27: =YEAR(I27) -> 2026 | U27: =IFERROR(IF(H27>0,"Buy","Sell"),"") -> Buy | V27: Active | W27: =_xlfn.XLOOKUP(Table3[[#This Row],[Instrument]],Control!$B$2:$B$19,Control!$E$2:$E$19) -> WTI | X27: =Table3[[#This Row],[Month1]] -> 46081 | Y27: =Table3[[#This Row],[Quantity]] -> 350 | Z27: =_xlfn.XLOOKUP(Table3[[#This Row],[Instrument]],Control!$B$2:$B$19,Control!$F$2:$F$19) -> Brent | AA27: =Table3[[#This Row],[Month2]] -> 46081 | AB27: =-Y27 -> -350
A28: Cargoes | B28: =_xlfn.XLOOKUP(Table3[[#This Row],[Cargo Name]],Ledger[Cargo Name],Ledger[SAP Deal Number]) -> #N/A | C28: 0 | E28: 45979 | F28: WTI-Brent | G28: Hedge | H28: -350 | I28: 46203 | J28: 46203 | K28: -3.68 | L28: =IF(OR(S28="WTI Sprds",S28="Brent Sprds",S28="WTI-Brent",S28="DFL"),INDEX(INDIRECT("'" & S28 & "'!$A$6:$XFD$1048576"),MATCH('PnL26'!$P$1,INDIRECT("'" & S28 & "'!$A$6:$A$1048576"),0),MATCH(EOMONTH(I28,0),INDIRECT("'" & S28 & "'!$A$4:$XFD$4"),0)),INDEX(BBG!$A:$BA,MATCH('PnL26'!$P$1,BBG!$A:$A,0),MATCH($I28,BBG!$A$4:$BA$4,0))-INDEX(BBG!$A:$BA,MATCH('PnL26'!$P$1,BBG!$A:$A,0),MATCH($J28,BBG!$A$4:$BA$4,0))) -> -8.94 | M28: =IFERROR((L28-K28)*H28,"") -> 1841 | N28: =H28*K28 -> 1288 | O28: =IF(I28=J28,TEXT(I28,"MMM YY"),TEXT(I28,"MMM")&"/"&TEXT(J28,"MMM")&" "&RIGHT(T28,2)) -> Jun 26 | P28: =IF(H28<0,"Sell","Buy") -> Sell | Q28: =H28*L28 -> 3129 | R28: =VLOOKUP(F28,Control!$B:$C,2,FALSE) -> Swaps | S28: =VLOOKUP(F28,Control!$B:$D,3,FALSE) -> WTI-Brent | T28: =YEAR(I28) -> 2026 | U28: =IFERROR(IF(H28>0,"Buy","Sell"),"") -> Sell | V28: Active | W28: =_xlfn.XLOOKUP(Table3[[#This Row],[Instrument]],Control!$B$2:$B$19,Control!$E$2:$E$19) -> WTI | X28: =Table3[[#This Row],[Month1]] -> 46203 | Y28: =Table3[[#This Row],[Quantity]] -> -350 | Z28: =_xlfn.XLOOKUP(Table3[[#This Row],[Instrument]],Control!$B$2:$B$19,Control!$F$2:$F$19) -> Brent | AA28: =Table3[[#This Row],[Month2]] -> 46203 | AB28: =-Y28 -> 350
A29: Cargoes | B29: =_xlfn.XLOOKUP(Table3[[#This Row],[Cargo Name]],Ledger[Cargo Name],Ledger[SAP Deal Number]) -> #N/A | C29: 0 | E29: 45980 | F29: WTI-Brent | G29: Hedge | H29: 500 | I29: 46081 | J29: 46081 | K29: -4 | L29: =IF(OR(S29="WTI Sprds",S29="Brent Sprds",S29="WTI-Brent",S29="DFL"),INDEX(INDIRECT("'" & S29 & "'!$A$6:$XFD$1048576"),MATCH('PnL26'!$P$1,INDIRECT("'" & S29 & "'!$A$6:$A$1048576"),0),MATCH(EOMONTH(I29,0),INDIRECT("'" & S29 & "'!$A$4:$XFD$4"),0)),INDEX(BBG!$A:$BA,MATCH('PnL26'!$P$1,BBG!$A:$A,0),MATCH($I29,BBG!$A$4:$BA$4,0))-INDEX(BBG!$A:$BA,MATCH('PnL26'!$P$1,BBG!$A:$A,0),MATCH($J29,BBG!$A$4:$BA$4,0))) -> -3.97 | M29: =IFERROR((L29-K29)*H29,"") -> 15 | N29: =H29*K29 -> -2000 | O29: =IF(I29=J29,TEXT(I29,"MMM YY"),TEXT(I29,"MMM")&"/"&TEXT(J29,"MMM")&" "&RIGHT(T29,2)) -> Feb 26 | P29: =IF(H29<0,"Sell","Buy") -> Buy | Q29: =H29*L29 -> -1985 | R29: =VLOOKUP(F29,Control!$B:$C,2,FALSE) -> Swaps | S29: =VLOOKUP(F29,Control!$B:$D,3,FALSE) -> WTI-Brent | T29: =YEAR(I29) -> 2026 | U29: =IFERROR(IF(H29>0,"Buy","Sell"),"") -> Buy | V29: Active | W29: =_xlfn.XLOOKUP(Table3[[#This Row],[Instrument]],Control!$B$2:$B$19,Control!$E$2:$E$19) -> WTI | X29: =Table3[[#This Row],[Month1]] -> 46081 | Y29: =Table3[[#This Row],[Quantity]] -> 500 | Z29: =_xlfn.XLOOKUP(Table3[[#This Row],[Instrument]],Control!$B$2:$B$19,Control!$F$2:$F$19) -> Brent | AA29: =Table3[[#This Row],[Month2]] -> 46081 | AB29: =-Y29 -> -500
A30: Cargoes | B30: =_xlfn.XLOOKUP(Table3[[#This Row],[Cargo Name]],Ledger[Cargo Name],Ledger[SAP Deal Number]) -> #N/A | C30: 0 | E30: 45980 | F30: WTI-Brent | G30: Hedge | H30: -500 | I30: 46203 | J30: 46203 | K30: =+K29+0.348 -> -3.652 | L30: =IF(OR(S30="WTI Sprds",S30="Brent Sprds",S30="WTI-Brent",S30="DFL"),INDEX(INDIRECT("'" & S30 & "'!$A$6:$XFD$1048576"),MATCH('PnL26'!$P$1,INDIRECT("'" & S30 & "'!$A$6:$A$1048576"),0),MATCH(EOMONTH(I30,0),INDIRECT("'" & S30 & "'!$A$4:$XFD$4"),0)),INDEX(BBG!$A:$BA,MATCH('PnL26'!$P$1,BBG!$A:$A,0),MATCH($I30,BBG!$A$4:$BA$4,0))-INDEX(BBG!$A:$BA,MATCH('PnL26'!$P$1,BBG!$A:$A,0),MATCH($J30,BBG!$A$4:$BA$4,0))) -> -8.94 | M30: =IFERROR((L30-K30)*H30,"") -> 2644 | N30: =H30*K30 -> 1826 | O30: =IF(I30=J30,TEXT(I30,"MMM YY"),TEXT(I30,"MMM")&"/"&TEXT(J30,"MMM")&" "&RIGHT(T30,2)) -> Jun 26 | P30: =IF(H30<0,"Sell","Buy") -> Sell | Q30: =H30*L30 -> 4470 | R30: =VLOOKUP(F30,Control!$B:$C,2,FALSE) -> Swaps | S30: =VLOOKUP(F30,Control!$B:$D,3,FALSE) -> WTI-Brent | T30: =YEAR(I30) -> 2026 | U30: =IFERROR(IF(H30>0,"Buy","Sell"),"") -> Sell | V30: Active | W30: =_xlfn.XLOOKUP(Table3[[#This Row],[Instrument]],Control!$B$2:$B$19,Control!$E$2:$E$19) -> WTI | X30: =Table3[[#This Row],[Month1]] -> 46203 | Y30: =Table3[[#This Row],[Quantity]] -> -500 | Z30: =_xlfn.XLOOKUP(Table3[[#This Row],[Instrument]],Control!$B$2:$B$19,Control!$F$2:$F$19) -> Brent | AA30: =Table3[[#This Row],[Month2]] -> 46203 | AB30: =-Y30 -> 500
A31: Cargoes | B31: =_xlfn.XLOOKUP(Table3[[#This Row],[Cargo Name]],Ledger[Cargo Name],Ledger[SAP Deal Number]) -> EXX26HS00007 | C31: 0 | D31: Exxon CIF Rotts Jan 2-6 | E31: 45980 | F31: Physical | G31: Expo | H31: 700 | I31: 46022 | J31: 46022 | K31: ='Cargo Econs 2025'!D387 -> 1.78 | L31: 1.86 | M31: =IFERROR((L31-K31)*H31,"") -> 56 | N31: =H31*K31 -> 1246 | O31: =IF(I31=J31,TEXT(I31,"MMM YY"),TEXT(I31,"MMM")&"/"&TEXT(J31,"MMM")&" "&RIGHT(T31,2)) -> Dec 25 | P31: =IF(H31<0,"Sell","Buy") -> Buy | Q31: =H31*L31 -> 1302 | R31: =VLOOKUP(F31,Control!$B:$C,2,FALSE) -> Physical | S31: =VLOOKUP(F31,Control!$B:$D,3,FALSE) -> Physical | T31: =YEAR(I31) -> 2025 | U31: =IFERROR(IF(H31>0,"Buy","Sell"),"") -> Buy | V31: Active | W31: =_xlfn.XLOOKUP(Table3[[#This Row],[Instrument]],Control!$B$2:$B$19,Control!$E$2:$E$19) -> 0 | X31: =Table3[[#This Row],[Month1]] -> 46022 | Y31: =Table3[[#This Row],[Quantity]] -> 700 | Z31: =_xlfn.XLOOKUP(Table3[[#This Row],[Instrument]],Control!$B$2:$B$19,Control!$F$2:$F$19) -> 0 | AA31: =Table3[[#This Row],[Month2]] -> 46022 | AB31: =-Y31 -> -700
A32: Cargoes | B32: =_xlfn.XLOOKUP(Table3[[#This Row],[Cargo Name]],Ledger[Cargo Name],Ledger[SAP Deal Number]) -> EXX26HS00007 | C32: 0 | D32: Exxon CIF Rotts Jan 2-6 | E32: 45980 | F32: WTI-Brent | G32: Expo | H32: -700 | I32: 46081 | J32: 46081 | K32: -4.02 | L32: =IF(OR(S32="WTI Sprds",S32="Brent Sprds",S32="WTI-Brent",S32="DFL"),INDEX(INDIRECT("'" & S32 & "'!$A$6:$XFD$1048576"),MATCH('PnL26'!$P$1,INDIRECT("'" & S32 & "'!$A$6:$A$1048576"),0),MATCH(EOMONTH(I32,0),INDIRECT("'" & S32 & "'!$A$4:$XFD$4"),0)),INDEX(BBG!$A:$BA,MATCH('PnL26'!$P$1,BBG!$A:$A,0),MATCH($I32,BBG!$A$4:$BA$4,0))-INDEX(BBG!$A:$BA,MATCH('PnL26'!$P$1,BBG!$A:$A,0),MATCH($J32,BBG!$A$4:$BA$4,0))) -> -3.97 | M32: =IFERROR((L32-K32)*H32,"") -> -35 | N32: =H32*K32 -> 2814 | O32: =IF(I32=J32,TEXT(I32,"MMM YY"),TEXT(I32,"MMM")&"/"&TEXT(J32,"MMM")&" "&RIGHT(T32,2)) -> Feb 26 | P32: =IF(H32<0,"Sell","Buy") -> Sell | Q32: =H32*L32 -> 2779 | R32: =VLOOKUP(F32,Control!$B:$C,2,FALSE) -> Swaps | S32: =VLOOKUP(F32,Control!$B:$D,3,FALSE) -> WTI-Brent | T32: =YEAR(I32) -> 2026 | U32: =IFERROR(IF(H32>0,"Buy","Sell"),"") -> Sell | V32: Active | W32: =_xlfn.XLOOKUP(Table3[[#This Row],[Instrument]],Control!$B$2:$B$19,Control!$E$2:$E$19) -> WTI | X32: =Table3[[#This Row],[Month1]] -> 46081 | Y32: =Table3[[#This Row],[Quantity]] -> -700 | Z32: =_xlfn.XLOOKUP(Table3[[#This Row],[Instrument]],Control!$B$2:$B$19,Control!$F$2:$F$19) -> Brent | AA32: =Table3[[#This Row],[Month2]] -> 46081 | AB32: =-Y32 -> 700
A33: Cargoes | B33: =_xlfn.XLOOKUP(Table3[[#This Row],[Cargo Name]],Ledger[Cargo Name],Ledger[SAP Deal Number]) -> EXX26HS00007 | C33: 0 | D33: Exxon CIF Rotts Jan 2-6 | E33: 45980 | F33: Brent Sprds | G33: Expo | H33: -700 | I33: 46081 | J33: 46112 | K33: 0.33 | L33: =IF(OR(S33="WTI Sprds",S33="Brent Sprds",S33="WTI-Brent",S33="DFL"),INDEX(INDIRECT("'" & S33 & "'!$A$6:$XFD$1048576"),MATCH('PnL26'!$P$1,INDIRECT("'" & S33 & "'!$A$6:$A$1048576"),0),MATCH(EOMONTH(I33,0),INDIRECT("'" & S33 & "'!$A$4:$XFD$4"),0)),INDEX(BBG!$A:$BA,MATCH('PnL26'!$P$1,BBG!$A:$A,0),MATCH($I33,BBG!$A$4:$BA$4,0))-INDEX(BBG!$A:$BA,MATCH('PnL26'!$P$1,BBG!$A:$A,0),MATCH($J33,BBG!$A$4:$BA$4,0))) -> 0.59 | M33: =IFERROR((L33-K33)*H33,"") -> -182 | N33: =H33*K33 -> -231 | O33: =IF(I33=J33,TEXT(I33,"MMM YY"),TEXT(I33,"MMM")&"/"&TEXT(J33,"MMM")&" "&RIGHT(T33,2)) -> Feb/Mar 26 | P33: =IF(H33<0,"Sell","Buy") -> Sell | Q33: =H33*L33 -> -413 | R33: =VLOOKUP(F33,Control!$B:$C,2,FALSE) -> Futures | S33: =VLOOKUP(F33,Control!$B:$D,3,FALSE) -> Brent Sprds | T33: =YEAR(I33) -> 2026 | U33: =IFERROR(IF(H33>0,"Buy","Sell"),"") -> Sell | V33: Active | W33: =_xlfn.XLOOKUP(Table3[[#This Row],[Instrument]],Control!$B$2:$B$19,Control!$E$2:$E$19) -> Brent | X33: =Table3[[#This Row],[Month1]] -> 46081 | Y33: =Table3[[#This Row],[Quantity]] -> -700 | Z33: =_xlfn.XLOOKUP(Table3[[#This Row],[Instrument]],Control!$B$2:$B$19,Control!$F$2:$F$19) -> Brent | AA33: =Table3[[#This Row],[Month2]] -> 46112 | AB33: =-Y33 -> 700
A34: Cargoes | B34: =_xlfn.XLOOKUP(Table3[[#This Row],[Cargo Name]],Ledger[Cargo Name],Ledger[SAP Deal Number]) -> EXX26HS00007 | C34: 0 | D34: Exxon CIF Rotts Jan 2-6 | E34: 45980 | F34: Brent Sprds | G34: Expo | H34: -33 | I34: 46112 | J34: 46142 | K34: 0.17 | L34: =IF(OR(S34="WTI Sprds",S34="Brent Sprds",S34="WTI-Brent",S34="DFL"),INDEX(INDIRECT("'" & S34 & "'!$A$6:$XFD$1048576"),MATCH('PnL26'!$P$1,INDIRECT("'" & S34 & "'!$A$6:$A$1048576"),0),MATCH(EOMONTH(I34,0),INDIRECT("'" & S34 & "'!$A$4:$XFD$4"),0)),INDEX(BBG!$A:$BA,MATCH('PnL26'!$P$1,BBG!$A:$A,0),MATCH($I34,BBG!$A$4:$BA$4,0))-INDEX(BBG!$A:$BA,MATCH('PnL26'!$P$1,BBG!$A:$A,0),MATCH($J34,BBG!$A$4:$BA$4,0))) -> 1.37 | M34: =IFERROR((L34-K34)*H34,"") -> -39.6 | N34: =H34*K34 -> -5.61 | O34: =IF(I34=J34,TEXT(I34,"MMM YY"),TEXT(I34,"MMM")&"/"&TEXT(J34,"MMM")&" "&RIGHT(T34,2)) -> Mar/Apr 26 | P34: =IF(H34<0,"Sell","Buy") -> Sell | Q34: =H34*L34 -> -45.21 | R34: =VLOOKUP(F34,Control!$B:$C,2,FALSE) -> Futures | S34: =VLOOKUP(F34,Control!$B:$D,3,FALSE) -> Brent Sprds | T34: =YEAR(I34) -> 2026 | U34: =IFERROR(IF(H34>0,"Buy","Sell"),"") -> Sell | V34: Active | W34: =_xlfn.XLOOKUP(Table3[[#This Row],[Instrument]],Control!$B$2:$B$19,Control!$E$2:$E$19) -> Brent | X34: =Table3[[#This Row],[Month1]] -> 46112 | Y34: =Table3[[#This Row],[Quantity]] -> -33 | Z34: =_xlfn.XLOOKUP(Table3[[#This Row],[Instrument]],Control!$B$2:$B$19,Control!$F$2:$F$19) -> Brent | AA34: =Table3[[#This Row],[Month2]] -> 46142 | AB34: =-Y34 -> 33
A35: Cargoes | B35: =_xlfn.XLOOKUP(Table3[[#This Row],[Cargo Name]],Ledger[Cargo Name],Ledger[SAP Deal Number]) -> EXX26HS00007 | C35: 0 | D35: Exxon CIF Rotts Jan 2-6 | E35: 45980 | F35: DFL | G35: Expo | H35: 700 | I35: 46053 | J35: 46053 | K35: 0.4 | L35: =VLOOKUP($I35,'PnL26'!$E$7:$F$59,2,FALSE) -> 2.09 | M35: =IFERROR((L35-K35)*H35,"") -> 1183 | N35: =H35*K35 -> 280 | O35: =IF(I35=J35,TEXT(I35,"MMM YY"),TEXT(I35,"MMM")&"/"&TEXT(J35,"MMM")&" "&RIGHT(T35,2)) -> Jan 26 | P35: =IF(H35<0,"Sell","Buy") -> Buy | Q35: =H35*L35 -> 1463 | R35: =VLOOKUP(F35,Control!$B:$C,2,FALSE) -> Swaps | S35: =VLOOKUP(F35,Control!$B:$D,3,FALSE) -> Dated | T35: =YEAR(I35) -> 2026 | U35: =IFERROR(IF(H35>0,"Buy","Sell"),"") -> Buy | V35: Active | W35: =_xlfn.XLOOKUP(Table3[[#This Row],[Instrument]],Control!$B$2:$B$19,Control!$E$2:$E$19) -> #N/A | X35: =Table3[[#This Row],[Month1]] -> 46053 | Y35: =Table3[[#This Row],[Quantity]] -> 700 | Z35: =_xlfn.XLOOKUP(Table3[[#This Row],[Instrument]],Control!$B$2:$B$19,Control!$F$2:$F$19) -> #N/A | AA35: =Table3[[#This Row],[Month2]] -> 46053 | AB35: =-Y35 -> -700
A36: Cargoes | B36: =_xlfn.XLOOKUP(Table3[[#This Row],[Cargo Name]],Ledger[Cargo Name],Ledger[SAP Deal Number]) -> Unallocated | C36: 0 | D36: Unallocated | E36: 45980 | F36: WTI-Brent | G36: Hedge | H36: 107 | I36: 46053 | J36: 46053 | K36: -4.25 | L36: =IF(OR(S36="WTI Sprds",S36="Brent Sprds",S36="WTI-Brent",S36="DFL"),INDEX(INDIRECT("'" & S36 & "'!$A$6:$XFD$1048576"),MATCH('PnL26'!$P$1,INDIRECT("'" & S36 & "'!$A$6:$A$1048576"),0),MATCH(EOMONTH(I36,0),INDIRECT("'" & S36 & "'!$A$4:$XFD$4"),0)),INDEX(BBG!$A:$BA,MATCH('PnL26'!$P$1,BBG!$A:$A,0),MATCH($I36,BBG!$A$4:$BA$4,0))-INDEX(BBG!$A:$BA,MATCH('PnL26'!$P$1,BBG!$A:$A,0),MATCH($J36,BBG!$A$4:$BA$4,0))) -> -4.65 | N36: =H36*K36 -> -454.75 | O36: =IF(I36=J36,TEXT(I36,"MMM YY"),TEXT(I36,"MMM")&"/"&TEXT(J36,"MMM")&" "&RIGHT(T36,2)) -> Jan 26 | P36: =IF(H36<0,"Sell","Buy") -> Buy | Q36: =H36*L36 -> -497.55 | R36: =VLOOKUP(F36,Control!$B:$C,2,FALSE) -> Swaps | S36: =VLOOKUP(F36,Control!$B:$D,3,FALSE) -> WTI-Brent | T36: =YEAR(I36) -> 2026 | U36: =IFERROR(IF(H36>0,"Buy","Sell"),"") -> Buy | V36: Active | W36: =_xlfn.XLOOKUP(Table3[[#This Row],[Instrument]],Control!$B$2:$B$19,Control!$E$2:$E$19) -> WTI | X36: =Table3[[#This Row],[Month1]] -> 46053 | Y36: =Table3[[#This Row],[Quantity]] -> 107 | Z36: =_xlfn.XLOOKUP(Table3[[#This Row],[Instrument]],Control!$B$2:$B$19,Control!$F$2:$F$19) -> Brent | AA36: =Table3[[#This Row],[Month2]] -> 46053 | AB36: =-Y36 -> -107
A37: Cargoes | B37: =_xlfn.XLOOKUP(Table3[[#This Row],[Cargo Name]],Ledger[Cargo Name],Ledger[SAP Deal Number]) -> Unallocated | C37: 0 | D37: Unallocated | E37: 45982 | F37: Brent Sprds | G37: Hedge | H37: 1000 | I37: 46081 | J37: 46112 | K37: 0.34 | L37: =IF(OR(S37="WTI Sprds",S37="Brent Sprds",S37="WTI-Brent",S37="DFL"),INDEX(INDIRECT("'" & S37 & "'!$A$6:$XFD$1048576"),MATCH('PnL26'!$P$1,INDIRECT("'" & S37 & "'!$A$6:$A$1048576"),0),MATCH(EOMONTH(I37,0),INDIRECT("'" & S37 & "'!$A$4:$XFD$4"),0)),INDEX(BBG!$A:$BA,MATCH('PnL26'!$P$1,BBG!$A:$A,0),MATCH($I37,BBG!$A$4:$BA$4,0))-INDEX(BBG!$A:$BA,MATCH('PnL26'!$P$1,BBG!$A:$A,0),MATCH($J37,BBG!$A$4:$BA$4,0))) -> 0.59 | M37: =IFERROR((L37-K37)*H37,"") -> 250 | N37: =H37*K37 -> 340 | O37: =IF(I37=J37,TEXT(I37,"MMM YY"),TEXT(I37,"MMM")&"/"&TEXT(J37,"MMM")&" "&RIGHT(T37,2)) -> Feb/Mar 26 | P37: =IF(H37<0,"Sell","Buy") -> Buy | Q37: =H37*L37 -> 590 | R37: =VLOOKUP(F37,Control!$B:$C,2,FALSE) -> Futures | S37: =VLOOKUP(F37,Control!$B:$D,3,FALSE) -> Brent Sprds | T37: =YEAR(I37) -> 2026 | U37: =IFERROR(IF(H37>0,"Buy","Sell"),"") -> Buy | V37: Active | W37: =_xlfn.XLOOKUP(Table3[[#This Row],[Instrument]],Control!$B$2:$B$19,Control!$E$2:$E$19) -> Brent | X37: =Table3[[#This Row],[Month1]] -> 46081 | Y37: =Table3[[#This Row],[Quantity]] -> 1000 | Z37: =_xlfn.XLOOKUP(Table3[[#This Row],[Instrument]],Control!$B$2:$B$19,Control!$F$2:$F$19) -> Brent | AA37: =Table3[[#This Row],[Month2]] -> 46112 | AB37: =-Y37 -> -1000
A38: Cargoes | B38: =_xlfn.XLOOKUP(Table3[[#This Row],[Cargo Name]],Ledger[Cargo Name],Ledger[SAP Deal Number]) -> Unallocated | C38: 0 | D38: Unallocated | E38: 45985 | F38: DFL | G38: Hedge | H38: -1000 | I38: 46053 | J38: 46053 | K38: 0.48 | L38: =VLOOKUP($I38,'PnL26'!$E$7:$F$59,2,FALSE) -> 2.09 | M38: =IFERROR((L38-K38)*H38,"") -> -1610 | N38: =H38*K38 -> -480 | O38: =IF(I38=J38,TEXT(I38,"MMM YY"),TEXT(I38,"MMM")&"/"&TEXT(J38,"MMM")&" "&RIGHT(T38,2)) -> Jan 26 | P38: =IF(H38<0,"Sell","Buy") -> Sell | Q38: =H38*L38 -> -2090 | R38: =VLOOKUP(F38,Control!$B:$C,2,FALSE) -> Swaps | S38: =VLOOKUP(F38,Control!$B:$D,3,FALSE) -> Dated | T38: =YEAR(I38) -> 2026 | U38: =IFERROR(IF(H38>0,"Buy","Sell"),"") -> Sell | V38: Active | W38: =_xlfn.XLOOKUP(Table3[[#This Row],[Instrument]],Control!$B$2:$B$19,Control!$E$2:$E$19) -> #N/A | X38: =Table3[[#This Row],[Month1]] -> 46053 | Y38: =Table3[[#This Row],[Quantity]] -> -1000 | Z38: =_xlfn.XLOOKUP(Table3[[#This Row],[Instrument]],Control!$B$2:$B$19,Control!$F$2:$F$19) -> #N/A | AA38: =Table3[[#This Row],[Month2]] -> 46053 | AB38: =-Y38 -> 1000
A39: Cargoes | B39: =_xlfn.XLOOKUP(Table3[[#This Row],[Cargo Name]],Ledger[Cargo Name],Ledger[SAP Deal Number]) -> ARA26HS00009 | C39: 0 | D39: Exxon CIF Rotts VLCC Jan 19-23 | E39: 45986 | F39: Physical | G39: Expo | H39: ='Cargo Econs 2025'!G372 -> 1349 | I39: 46022 | J39: 46022 | K39: ='Cargo Econs 2025'!G387 -> 0.75768668 | L39: 0.5 | M39: =IFERROR((L39-K39)*H39,"") -> -347.61933 | N39: =H39*K39 -> 1022.1193 | O39: =IF(I39=J39,TEXT(I39,"MMM YY"),TEXT(I39,"MMM")&"/"&TEXT(J39,"MMM")&" "&RIGHT(T39,2)) -> Dec 25 | P39: =IF(H39<0,"Sell","Buy") -> Buy | Q39: =H39*L39 -> 674.5 | R39: =VLOOKUP(F39,Control!$B:$C,2,FALSE) -> Physical | S39: =VLOOKUP(F39,Control!$B:$D,3,FALSE) -> Physical | T39: =YEAR(I39) -> 2025 | U39: =IFERROR(IF(H39>0,"Buy","Sell"),"") -> Buy | V39: Active | W39: =_xlfn.XLOOKUP(Table3[[#This Row],[Instrument]],Control!$B$2:$B$19,Control!$E$2:$E$19) -> 0 | X39: =Table3[[#This Row],[Month1]] -> 46022 | Y39: =Table3[[#This Row],[Quantity]] -> 1349 | Z39: =_xlfn.XLOOKUP(Table3[[#This Row],[Instrument]],Control!$B$2:$B$19,Control!$F$2:$F$19) -> 0 | AA39: =Table3[[#This Row],[Month2]] -> 46022 | AB39: =-Y39 -> -1349
A40: Cargoes | B40: =_xlfn.XLOOKUP(Table3[[#This Row],[Cargo Name]],Ledger[Cargo Name],Ledger[SAP Deal Number]) -> ARA26HS00009 | C40: 0 | D40: Exxon CIF Rotts VLCC Jan 19-23 | E40: 45986 | F40: Physical | G40: Expo | H40: 700 | I40: 46022 | J40: 46022 | K40: ='Cargo Econs 2025'!H387 -> 0.86768668 | L40: 0.5 | M40: =IFERROR((L40-K40)*H40,"") -> -257.38067 | N40: =H40*K40 -> 607.38067 | O40: =IF(I40=J40,TEXT(I40,"MMM YY"),TEXT(I40,"MMM")&"/"&TEXT(J40,"MMM")&" "&RIGHT(T40,2)) -> Dec 25 | P40: =IF(H40<0,"Sell","Buy") -> Buy | Q40: =H40*L40 -> 350 | R40: =VLOOKUP(F40,Control!$B:$C,2,FALSE) -> Physical | S40: =VLOOKUP(F40,Control!$B:$D,3,FALSE) -> Physical | T40: =YEAR(I40) -> 2025 | U40: =IFERROR(IF(H40>0,"Buy","Sell"),"") -> Buy | V40: Active | W40: =_xlfn.XLOOKUP(Table3[[#This Row],[Instrument]],Control!$B$2:$B$19,Control!$E$2:$E$19) -> 0 | X40: =Table3[[#This Row],[Month1]] -> 46022 | Y40: =Table3[[#This Row],[Quantity]] -> 700 | Z40: =_xlfn.XLOOKUP(Table3[[#This Row],[Instrument]],Control!$B$2:$B$19,Control!$F$2:$F$19) -> 0 | AA40: =Table3[[#This Row],[Month2]] -> 46022 | AB40: =-Y40 -> -700
A41: Cargoes | B41: =_xlfn.XLOOKUP(Table3[[#This Row],[Cargo Name]],Ledger[Cargo Name],Ledger[SAP Deal Number]) -> ARA26HS00009 | C41: 0 | D41: Exxon CIF Rotts VLCC Jan 19-23 | E41: 45986 | F41: WTI-Brent | G41: Expo | H41: =-H39 -> -1349 | I41: 46081 | J41: 46081 | K41: -4.05 | L41: =IF(OR(S41="WTI Sprds",S41="Brent Sprds",S41="WTI-Brent",S41="DFL"),INDEX(INDIRECT("'" & S41 & "'!$A$6:$XFD$1048576"),MATCH('PnL26'!$P$1,INDIRECT("'" & S41 & "'!$A$6:$A$1048576"),0),MATCH(EOMONTH(I41,0),INDIRECT("'" & S41 & "'!$A$4:$XFD$4"),0)),INDEX(BBG!$A:$BA,MATCH('PnL26'!$P$1,BBG!$A:$A,0),MATCH($I41,BBG!$A$4:$BA$4,0))-INDEX(BBG!$A:$BA,MATCH('PnL26'!$P$1,BBG!$A:$A,0),MATCH($J41,BBG!$A$4:$BA$4,0))) -> -3.97 | M41: =IFERROR((L41-K41)*H41,"") -> -107.92 | N41: =H41*K41 -> 5463.45 | O41: =IF(I41=J41,TEXT(I41,"MMM YY"),TEXT(I41,"MMM")&"/"&TEXT(J41,"MMM")&" "&RIGHT(T41,2)) -> Feb 26 | P41: =IF(H41<0,"Sell","Buy") -> Sell | Q41: =H41*L41 -> 5355.53 | R41: =VLOOKUP(F41,Control!$B:$C,2,FALSE) -> Swaps | S41: =VLOOKUP(F41,Control!$B:$D,3,FALSE) -> WTI-Brent | T41: =YEAR(I41) -> 2026 | U41: =IFERROR(IF(H41>0,"Buy","Sell"),"") -> Sell | V41: Active | W41: =_xlfn.XLOOKUP(Table3[[#This Row],[Instrument]],Control!$B$2:$B$19,Control!$E$2:$E$19) -> WTI | X41: =Table3[[#This Row],[Month1]] -> 46081 | Y41: =Table3[[#This Row],[Quantity]] -> -1349 | Z41: =_xlfn.XLOOKUP(Table3[[#This Row],[Instrument]],Control!$B$2:$B$19,Control!$F$2:$F$19) -> Brent | AA41: =Table3[[#This Row],[Month2]] -> 46081 | AB41: =-Y41 -> 1349
A42: Cargoes | B42: =_xlfn.XLOOKUP(Table3[[#This Row],[Cargo Name]],Ledger[Cargo Name],Ledger[SAP Deal Number]) -> ARA26HS00009 | C42: 0 | D42: Exxon CIF Rotts VLCC Jan 19-23 | E42: 45986 | F42: Brent Sprds | G42: Expo | H42: =-H39-H40 -> -2049 | I42: 46081 | J42: 46112 | K42: 0.3 | L42: =IF(OR(S42="WTI Sprds",S42="Brent Sprds",S42="WTI-Brent",S42="DFL"),INDEX(INDIRECT("'" & S42 & "'!$A$6:$XFD$1048576"),MATCH('PnL26'!$P$1,INDIRECT("'" & S42 & "'!$A$6:$A$1048576"),0),MATCH(EOMONTH(I42,0),INDIRECT("'" & S42 & "'!$A$4:$XFD$4"),0)),INDEX(BBG!$A:$BA,MATCH('PnL26'!$P$1,BBG!$A:$A,0),MATCH($I42,BBG!$A$4:$BA$4,0))-INDEX(BBG!$A:$BA,MATCH('PnL26'!$P$1,BBG!$A:$A,0),MATCH($J42,BBG!$A$4:$BA$4,0))) -> 0.59 | M42: =IFERROR((L42-K42)*H42,"") -> -594.21 | N42: =H42*K42 -> -614.7 | O42: =IF(I42=J42,TEXT(I42,"MMM YY"),TEXT(I42,"MMM")&"/"&TEXT(J42,"MMM")&" "&RIGHT(T42,2)) -> Feb/Mar 26 | P42: =IF(H42<0,"Sell","Buy") -> Sell | Q42: =H42*L42 -> -1208.91 | R42: =VLOOKUP(F42,Control!$B:$C,2,FALSE) -> Futures | S42: =VLOOKUP(F42,Control!$B:$D,3,FALSE) -> Brent Sprds | T42: =YEAR(I42) -> 2026 | U42: =IFERROR(IF(H42>0,"Buy","Sell"),"") -> Sell | V42: Active | W42: =_xlfn.XLOOKUP(Table3[[#This Row],[Instrument]],Control!$B$2:$B$19,Control!$E$2:$E$19) -> Brent | X42: =Table3[[#This Row],[Month1]] -> 46081 | Y42: =Table3[[#This Row],[Quantity]] -> -2049 | Z42: =_xlfn.XLOOKUP(Table3[[#This Row],[Instrument]],Control!$B$2:$B$19,Control!$F$2:$F$19) -> Brent | AA42: =Table3[[#This Row],[Month2]] -> 46112 | AB42: =-Y42 -> 2049
A43: Cargoes | B43: =_xlfn.XLOOKUP(Table3[[#This Row],[Cargo Name]],Ledger[Cargo Name],Ledger[SAP Deal Number]) -> ARA26HS00009 | C43: 0 | D43: Exxon CIF Rotts VLCC Jan 19-23 | E43: 45986 | F43: DFL | G43: Expo | H43: =-H42 -> 2049 | I43: 46053 | J43: 46053 | K43: 0.45 | L43: =VLOOKUP($I43,'PnL26'!$E$7:$F$59,2,FALSE) -> 2.09 | M43: =IFERROR((L43-K43)*H43,"") -> 3360.36 | N43: =H43*K43 -> 922.05 | O43: =IF(I43=J43,TEXT(I43,"MMM YY"),TEXT(I43,"MMM")&"/"&TEXT(J43,"MMM")&" "&RIGHT(T43,2)) -> Jan 26 | P43: =IF(H43<0,"Sell","Buy") -> Buy | Q43: =H43*L43 -> 4282.41 | R43: =VLOOKUP(F43,Control!$B:$C,2,FALSE) -> Swaps | S43: =VLOOKUP(F43,Control!$B:$D,3,FALSE) -> Dated | T43: =YEAR(I43) -> 2026 | U43: =IFERROR(IF(H43>0,"Buy","Sell"),"") -> Buy | V43: Active | W43: =_xlfn.XLOOKUP(Table3[[#This Row],[Instrument]],Control!$B$2:$B$19,Control!$E$2:$E$19) -> #N/A | X43: =Table3[[#This Row],[Month1]] -> 46053 | Y43: =Table3[[#This Row],[Quantity]] -> 2049 | Z43: =_xlfn.XLOOKUP(Table3[[#This Row],[Instrument]],Control!$B$2:$B$19,Control!$F$2:$F$19) -> #N/A | AA43: =Table3[[#This Row],[Month2]] -> 46053 | AB43: =-Y43 -> -2049
A44: Cargoes | B44: =_xlfn.XLOOKUP(Table3[[#This Row],[Cargo Name]],Ledger[Cargo Name],Ledger[SAP Deal Number]) -> ARA26HS00007 | C44: 0 | D44: HDO Feb26 5-15 | E44: 45986 | F44: WTI-Brent | G44: Hedge | H44: 450 | I44: 46081 | J44: 46081 | K44: -4.1067 | L44: =IF(OR(S44="WTI Sprds",S44="Brent Sprds",S44="WTI-Brent",S44="DFL"),INDEX(INDIRECT("'" & S44 & "'!$A$6:$XFD$1048576"),MATCH('PnL26'!$P$1,INDIRECT("'" & S44 & "'!$A$6:$A$1048576"),0),MATCH(EOMONTH(I44,0),INDIRECT("'" & S44 & "'!$A$4:$XFD$4"),0)),INDEX(BBG!$A:$BA,MATCH('PnL26'!$P$1,BBG!$A:$A,0),MATCH($I44,BBG!$A$4:$BA$4,0))-INDEX(BBG!$A:$BA,MATCH('PnL26'!$P$1,BBG!$A:$A,0),MATCH($J44,BBG!$A$4:$BA$4,0))) -> -3.97 | M44: =IFERROR((L44-K44)*H44,"") -> 61.515 | N44: =H44*K44 -> -1848.015 | O44: =IF(I44=J44,TEXT(I44,"MMM YY"),TEXT(I44,"MMM")&"/"&TEXT(J44,"MMM")&" "&RIGHT(T44,2)) -> Feb 26 | P44: =IF(H44<0,"Sell","Buy") -> Buy | Q44: =H44*L44 -> -1786.5 | R44: =VLOOKUP(F44,Control!$B:$C,2,FALSE) -> Swaps | S44: =VLOOKUP(F44,Control!$B:$D,3,FALSE) -> WTI-Brent | T44: =YEAR(I44) -> 2026 | U44: =IFERROR(IF(H44>0,"Buy","Sell"),"") -> Buy | V44: Active | W44: =_xlfn.XLOOKUP(Table3[[#This Row],[Instrument]],Control!$B$2:$B$19,Control!$E$2:$E$19) -> WTI | X44: =Table3[[#This Row],[Month1]] -> 46081 | Y44: =Table3[[#This Row],[Quantity]] -> 450 | Z44: =_xlfn.XLOOKUP(Table3[[#This Row],[Instrument]],Control!$B$2:$B$19,Control!$F$2:$F$19) -> Brent | AA44: =Table3[[#This Row],[Month2]] -> 46081 | AB44: =-Y44 -> -450
A45: Cargoes | B45: =_xlfn.XLOOKUP(Table3[[#This Row],[Cargo Name]],Ledger[Cargo Name],Ledger[SAP Deal Number]) -> ARA26HS00007 | C45: 0 | D45: HDO Feb26 5-15 | E45: 45986 | F45: Brent Sprds | G45: Hedge | H45: 1000 | I45: 46081 | J45: 46112 | K45: 0.298 | L45: =IF(OR(S45="WTI Sprds",S45="Brent Sprds",S45="WTI-Brent",S45="DFL"),INDEX(INDIRECT("'" & S45 & "'!$A$6:$XFD$1048576"),MATCH('PnL26'!$P$1,INDIRECT("'" & S45 & "'!$A$6:$A$1048576"),0),MATCH(EOMONTH(I45,0),INDIRECT("'" & S45 & "'!$A$4:$XFD$4"),0)),INDEX(BBG!$A:$BA,MATCH('PnL26'!$P$1,BBG!$A:$A,0),MATCH($I45,BBG!$A$4:$BA$4,0))-INDEX(BBG!$A:$BA,MATCH('PnL26'!$P$1,BBG!$A:$A,0),MATCH($J45,BBG!$A$4:$BA$4,0))) -> 0.59 | M45: =IFERROR((L45-K45)*H45,"") -> 292 | N45: =H45*K45 -> 298 | O45: =IF(I45=J45,TEXT(I45,"MMM YY"),TEXT(I45,"MMM")&"/"&TEXT(J45,"MMM")&" "&RIGHT(T45,2)) -> Feb/Mar 26 | P45: =IF(H45<0,"Sell","Buy") -> Buy | Q45: =H45*L45 -> 590 | R45: =VLOOKUP(F45,Control!$B:$C,2,FALSE) -> Futures | S45: =VLOOKUP(F45,Control!$B:$D,3,FALSE) -> Brent Sprds | T45: =YEAR(I45) -> 2026 | U45: =IFERROR(IF(H45>0,"Buy","Sell"),"") -> Buy | V45: Active | W45: =_xlfn.XLOOKUP(Table3[[#This Row],[Instrument]],Control!$B$2:$B$19,Control!$E$2:$E$19) -> Brent | X45: =Table3[[#This Row],[Month1]] -> 46081 | Y45: =Table3[[#This Row],[Quantity]] -> 1000 | Z45: =_xlfn.XLOOKUP(Table3[[#This Row],[Instrument]],Control!$B$2:$B$19,Control!$F$2:$F$19) -> Brent | AA45: =Table3[[#This Row],[Month2]] -> 46112 | AB45: =-Y45 -> -1000
A46: Cargoes | B46: =_xlfn.XLOOKUP(Table3[[#This Row],[Cargo Name]],Ledger[Cargo Name],Ledger[SAP Deal Number]) -> ARA26HS00007 | C46: 0 | D46: HDO Feb26 5-15 | E46: 45986 | F46: WTI-Brent | G46: Hedge | H46: 1400 | I46: 46081 | J46: 46081 | K46: -4.05 | L46: =IF(OR(S46="WTI Sprds",S46="Brent Sprds",S46="WTI-Brent",S46="DFL"),INDEX(INDIRECT("'" & S46 & "'!$A$6:$XFD$1048576"),MATCH('PnL26'!$P$1,INDIRECT("'" & S46 & "'!$A$6:$A$1048576"),0),MATCH(EOMONTH(I46,0),INDIRECT("'" & S46 & "'!$A$4:$XFD$4"),0)),INDEX(BBG!$A:$BA,MATCH('PnL26'!$P$1,BBG!$A:$A,0),MATCH($I46,BBG!$A$4:$BA$4,0))-INDEX(BBG!$A:$BA,MATCH('PnL26'!$P$1,BBG!$A:$A,0),MATCH($J46,BBG!$A$4:$BA$4,0))) -> -3.97 | M46: =IFERROR((L46-K46)*H46,"") -> 112 | N46: =H46*K46 -> -5670 | O46: =IF(I46=J46,TEXT(I46,"MMM YY"),TEXT(I46,"MMM")&"/"&TEXT(J46,"MMM")&" "&RIGHT(T46,2)) -> Feb 26 | P46: =IF(H46<0,"Sell","Buy") -> Buy | Q46: =H46*L46 -> -5558 | R46: =VLOOKUP(F46,Control!$B:$C,2,FALSE) -> Swaps | S46: =VLOOKUP(F46,Control!$B:$D,3,FALSE) -> WTI-Brent | T46: =YEAR(I46) -> 2026 | U46: =IFERROR(IF(H46>0,"Buy","Sell"),"") -> Buy | V46: Active | W46: =_xlfn.XLOOKUP(Table3[[#This Row],[Instrument]],Control!$B$2:$B$19,Control!$E$2:$E$19) -> WTI | X46: =Table3[[#This Row],[Month1]] -> 46081 | Y46: =Table3[[#This Row],[Quantity]] -> 1400 | Z46: =_xlfn.XLOOKUP(Table3[[#This Row],[Instrument]],Control!$B$2:$B$19,Control!$F$2:$F$19) -> Brent | AA46: =Table3[[#This Row],[Month2]] -> 46081 | AB46: =-Y46 -> -1400
A47: Cargoes | B47: =_xlfn.XLOOKUP(Table3[[#This Row],[Cargo Name]],Ledger[Cargo Name],Ledger[SAP Deal Number]) -> Unallocated | C47: 0 | D47: Unallocated | E47: 45986 | F47: DFL | G47: Hedge | H47: 188 | I47: 46142 | J47: 46142 | K47: 0.45 | L47: =VLOOKUP($I47,'PnL26'!$E$7:$F$59,2,FALSE) -> 17.67875 | M47: =IFERROR((L47-K47)*H47,"") -> 3239.005 | N47: =H47*K47 -> 84.6 | O47: =IF(I47=J47,TEXT(I47,"MMM YY"),TEXT(I47,"MMM")&"/"&TEXT(J47,"MMM")&" "&RIGHT(T47,2)) -> Apr 26 | P47: =IF(H47<0,"Sell","Buy") -> Buy | Q47: =H47*L47 -> 3323.605 | R47: =VLOOKUP(F47,Control!$B:$C,2,FALSE) -> Swaps | S47: =VLOOKUP(F47,Control!$B:$D,3,FALSE) -> Dated | T47: =YEAR(I47) -> 2026 | U47: =IFERROR(IF(H47>0,"Buy","Sell"),"") -> Buy | V47: Active | W47: =_xlfn.XLOOKUP(Table3[[#This Row],[Instrument]],Control!$B$2:$B$19,Control!$E$2:$E$19) -> #N/A | X47: =Table3[[#This Row],[Month1]] -> 46142 | Y47: =Table3[[#This Row],[Quantity]] -> 188 | Z47: =_xlfn.XLOOKUP(Table3[[#This Row],[Instrument]],Control!$B$2:$B$19,Control!$F$2:$F$19) -> #N/A | AA47: =Table3[[#This Row],[Month2]] -> 46142 | AB47: =-Y47 -> -188
A48: Cargoes | B48: =_xlfn.XLOOKUP(Table3[[#This Row],[Cargo Name]],Ledger[Cargo Name],Ledger[SAP Deal Number]) -> Unallocated | C48: 0 | D48: Unallocated | E48: 45986 | F48: DFL | G48: Hedge | H48: 188 | I48: 46173 | J48: 46173 | K48: 0.45 | L48: =VLOOKUP($I48,'PnL26'!$E$7:$F$59,2,FALSE) -> 3.68 | M48: =IFERROR((L48-K48)*H48,"") -> 607.24 | N48: =H48*K48 -> 84.6 | O48: =IF(I48=J48,TEXT(I48,"MMM YY"),TEXT(I48,"MMM")&"/"&TEXT(J48,"MMM")&" "&RIGHT(T48,2)) -> May 26 | P48: =IF(H48<0,"Sell","Buy") -> Buy | Q48: =H48*L48 -> 691.84 | R48: =VLOOKUP(F48,Control!$B:$C,2,FALSE) -> Swaps | S48: =VLOOKUP(F48,Control!$B:$D,3,FALSE) -> Dated | T48: =YEAR(I48) -> 2026 | U48: =IFERROR(IF(H48>0,"Buy","Sell"),"") -> Buy | V48: Active | W48: =_xlfn.XLOOKUP(Table3[[#This Row],[Instrument]],Control!$B$2:$B$19,Control!$E$2:$E$19) -> #N/A | X48: =Table3[[#This Row],[Month1]] -> 46173 | Y48: =Table3[[#This Row],[Quantity]] -> 188 | Z48: =_xlfn.XLOOKUP(Table3[[#This Row],[Instrument]],Control!$B$2:$B$19,Control!$F$2:$F$19) -> #N/A | AA48: =Table3[[#This Row],[Month2]] -> 46173 | AB48: =-Y48 -> -188
A49: Cargoes | B49: =_xlfn.XLOOKUP(Table3[[#This Row],[Cargo Name]],Ledger[Cargo Name],Ledger[SAP Deal Number]) -> Unallocated | C49: 0 | D49: Unallocated | E49: 45986 | F49: DFL | G49: Hedge | H49: 188 | I49: 46203 | J49: 46203 | K49: 0.45 | L49: =VLOOKUP($I49,'PnL26'!$E$7:$F$59,2,FALSE) -> 2.23 | M49: =IFERROR((L49-K49)*H49,"") -> 334.64 | N49: =H49*K49 -> 84.6 | O49: =IF(I49=J49,TEXT(I49,"MMM YY"),TEXT(I49,"MMM")&"/"&TEXT(J49,"MMM")&" "&RIGHT(T49,2)) -> Jun 26 | P49: =IF(H49<0,"Sell","Buy") -> Buy | Q49: =H49*L49 -> 419.24 | R49: =VLOOKUP(F49,Control!$B:$C,2,FALSE) -> Swaps | S49: =VLOOKUP(F49,Control!$B:$D,3,FALSE) -> Dated | T49: =YEAR(I49) -> 2026 | U49: =IFERROR(IF(H49>0,"Buy","Sell"),"") -> Buy | V49: Active | W49: =_xlfn.XLOOKUP(Table3[[#This Row],[Instrument]],Control!$B$2:$B$19,Control!$E$2:$E$19) -> #N/A | X49: =Table3[[#This Row],[Month1]] -> 46203 | Y49: =Table3[[#This Row],[Quantity]] -> 188 | Z49: =_xlfn.XLOOKUP(Table3[[#This Row],[Instrument]],Control!$B$2:$B$19,Control!$F$2:$F$19) -> #N/A | AA49: =Table3[[#This Row],[Month2]] -> 46203 | AB49: =-Y49 -> -188
A50: Cargoes | B50: =_xlfn.XLOOKUP(Table3[[#This Row],[Cargo Name]],Ledger[Cargo Name],Ledger[SAP Deal Number]) -> ARA26HS00009 | C50: 0 | D50: Exxon CIF Rotts VLCC Jan 19-23 | E50: 45986 | F50: Physical | G50: Expo | H50: 0 | I50: 46022 | J50: 46022 | K50: =K39 -> 0.75768668 | L50: 0.5 | M50: =IFERROR((L50-K50)*H50,"") -> 0 | N50: =H50*K50 -> 0 | O50: =IF(I50=J50,TEXT(I50,"MMM YY"),TEXT(I50,"MMM")&"/"&TEXT(J50,"MMM")&" "&RIGHT(T50,2)) -> Dec 25 | P50: =IF(H50<0,"Sell","Buy") -> Buy | Q50: =H50*L50 -> 0 | R50: =VLOOKUP(F50,Control!$B:$C,2,FALSE) -> Physical | S50: =VLOOKUP(F50,Control!$B:$D,3,FALSE) -> Physical | T50: =YEAR(I50) -> 2025 | U50: =IFERROR(IF(H50>0,"Buy","Sell"),"") -> Sell | V50: Active | W50: =_xlfn.XLOOKUP(Table3[[#This Row],[Instrument]],Control!$B$2:$B$19,Control!$E$2:$E$19) -> 0 | X50: =Table3[[#This Row],[Month1]] -> 46022 | Y50: =Table3[[#This Row],[Quantity]] -> 0 | Z50: =_xlfn.XLOOKUP(Table3[[#This Row],[Instrument]],Control!$B$2:$B$19,Control!$F$2:$F$19) -> 0 | AA50: =Table3[[#This Row],[Month2]] -> 46022 | AB50: =-Y50 -> 0
A51: Cargoes | B51: =_xlfn.XLOOKUP(Table3[[#This Row],[Cargo Name]],Ledger[Cargo Name],Ledger[SAP Deal Number]) -> ARA26HS00010 | C51: 0 | D51: January 26 2x EFP | E51: 45987 | F51: WTI-Brent | G51: Expo | H51: -1400 | I51: 46053 | J51: 46053 | K51: -4.44 | L51: =IF(OR(S51="WTI Sprds",S51="Brent Sprds",S51="WTI-Brent",S51="DFL"),INDEX(INDIRECT("'" & S51 & "'!$A$6:$XFD$1048576"),MATCH('PnL26'!$P$1,INDIRECT("'" & S51 & "'!$A$6:$A$1048576"),0),MATCH(EOMONTH(I51,0),INDIRECT("'" & S51 & "'!$A$4:$XFD$4"),0)),INDEX(BBG!$A:$BA,MATCH('PnL26'!$P$1,BBG!$A:$A,0),MATCH($I51,BBG!$A$4:$BA$4,0))-INDEX(BBG!$A:$BA,MATCH('PnL26'!$P$1,BBG!$A:$A,0),MATCH($J51,BBG!$A$4:$BA$4,0))) -> -4.65 | N51: =H51*K51 -> 6216 | O51: =IF(I51=J51,TEXT(I51,"MMM YY"),TEXT(I51,"MMM")&"/"&TEXT(J51,"MMM")&" "&RIGHT(T51,2)) -> Jan 26 | P51: =IF(H51<0,"Sell","Buy") -> Sell | Q51: =H51*L51 -> 6510 | R51: =VLOOKUP(F51,Control!$B:$C,2,FALSE) -> Swaps | S51: =VLOOKUP(F51,Control!$B:$D,3,FALSE) -> WTI-Brent | T51: =YEAR(I51) -> 2026 | U51: =IFERROR(IF(H51>0,"Buy","Sell"),"") -> Sell | V51: Active | W51: =_xlfn.XLOOKUP(Table3[[#This Row],[Instrument]],Control!$B$2:$B$19,Control!$E$2:$E$19) -> WTI | X51: =Table3[[#This Row],[Month1]] -> 46053 | Y51: =Table3[[#This Row],[Quantity]] -> -1400 | Z51: =_xlfn.XLOOKUP(Table3[[#This Row],[Instrument]],Control!$B$2:$B$19,Control!$F$2:$F$19) -> Brent | AA51: =Table3[[#This Row],[Month2]] -> 46053 | AB51: =-Y51 -> 1400
A52: Cargoes | B52: =_xlfn.XLOOKUP(Table3[[#This Row],[Cargo Name]],Ledger[Cargo Name],Ledger[SAP Deal Number]) -> ARA26HS00010 | C52: 0 | D52: January 26 2x EFP | E52: 45960 | F52: Freight-TD25 | G52: Expo | H52: -700 | I52: 46053 | J52: 46053 | K52: 208 | L52: =VLOOKUP(I52,[2]USG!$O$45:$S$100,MATCH(F52,[2]USG!$O$46:$S$46,0),FALSE) -> 268 | M52: =IF(Table3[[#This Row],[Quantity]]>0,-21.47*70*(Table3[[#This Row],[Price]]-Table3[[#This Row],[Mtm]])/100,21.47*70*(Table3[[#This Row],[Price]]-Table3[[#This Row],[Mtm]])/100) -> -901.74 | N52: =H52*K52 -> -145600 | O52: =IF(I52=J52,TEXT(I52,"MMM YY"),TEXT(I52,"MMM")&"/"&TEXT(J52,"MMM")&" "&RIGHT(T52,2)) -> Jan 26 | P52: =IF(H52<0,"Sell","Buy") -> Sell | Q52: =H52*L52 -> -187600 | R52: =VLOOKUP(F52,Control!$B:$C,2,FALSE) -> Freight | S52: =VLOOKUP(F52,Control!$B:$D,3,FALSE) -> Freight | T52: =YEAR(I52) -> 2026 | U52: =IFERROR(IF(H52>0,"Buy","Sell"),"") -> Sell | V52: Active | W52: =_xlfn.XLOOKUP(Table3[[#This Row],[Instrument]],Control!$B$2:$B$19,Control!$E$2:$E$19) -> #N/A | X52: =Table3[[#This Row],[Month1]] -> 46053 | Y52: =Table3[[#This Row],[Quantity]] -> -700 | Z52: =_xlfn.XLOOKUP(Table3[[#This Row],[Instrument]],Control!$B$2:$B$19,Control!$F$2:$F$19) -> #N/A | AA52: =Table3[[#This Row],[Month2]] -> 46053 | AB52: =-Y52 -> 700
A53: Cargoes | B53: =_xlfn.XLOOKUP(Table3[[#This Row],[Cargo Name]],Ledger[Cargo Name],Ledger[SAP Deal Number]) -> ARA26HS00010 | C53: 0 | D53: January 26 2x EFP | E53: 45960 | F53: Freight-TD25 | G53: Expo | H53: -700 | I53: 46053 | J53: 46053 | K53: 208 | L53: =VLOOKUP(I53,[2]USG!$O$45:$S$100,MATCH(F53,[2]USG!$O$46:$S$46,0),FALSE) -> 268 | M53: =IF(Table3[[#This Row],[Quantity]]>0,-21.47*70*(Table3[[#This Row],[Price]]-Table3[[#This Row],[Mtm]])/100,21.47*70*(Table3[[#This Row],[Price]]-Table3[[#This Row],[Mtm]])/100) -> -901.74 | N53: =H53*K53 -> -145600 | O53: =IF(I53=J53,TEXT(I53,"MMM YY"),TEXT(I53,"MMM")&"/"&TEXT(J53,"MMM")&" "&RIGHT(T53,2)) -> Jan 26 | P53: =IF(H53<0,"Sell","Buy") -> Sell | Q53: =H53*L53 -> -187600 | R53: =VLOOKUP(F53,Control!$B:$C,2,FALSE) -> Freight | S53: =VLOOKUP(F53,Control!$B:$D,3,FALSE) -> Freight | T53: =YEAR(I53) -> 2026 | U53: =IFERROR(IF(H53>0,"Buy","Sell"),"") -> Sell | V53: Active | W53: =_xlfn.XLOOKUP(Table3[[#This Row],[Instrument]],Control!$B$2:$B$19,Control!$E$2:$E$19) -> #N/A | X53: =Table3[[#This Row],[Month1]] -> 46053 | Y53: =Table3[[#This Row],[Quantity]] -> -700 | Z53: =_xlfn.XLOOKUP(Table3[[#This Row],[Instrument]],Control!$B$2:$B$19,Control!$F$2:$F$19) -> #N/A | AA53: =Table3[[#This Row],[Month2]] -> 46053 | AB53: =-Y53 -> 700
A54: Cargoes | B54: =_xlfn.XLOOKUP(Table3[[#This Row],[Cargo Name]],Ledger[Cargo Name],Ledger[SAP Deal Number]) -> ARA26HS00010 | C54: 0 | D54: January 26 2x EFP | E54: 46014 | F54: Freight-TD25 | G54: Hedge | H54: 700 | I54: 46053 | J54: 46053 | K54: 215 | L54: =VLOOKUP(I54,[2]USG!$O$45:$S$100,MATCH(F54,[2]USG!$O$46:$S$46,0),FALSE) -> 268 | M54: =IF(Table3[[#This Row],[Quantity]]>0,-21.47*70*(Table3[[#This Row],[Price]]-Table3[[#This Row],[Mtm]])/100,21.47*70*(Table3[[#This Row],[Price]]-Table3[[#This Row],[Mtm]])/100) -> 796.537 | N54: =H54*K54 -> 150500 | O54: =IF(I54=J54,TEXT(I54,"MMM YY"),TEXT(I54,"MMM")&"/"&TEXT(J54,"MMM")&" "&RIGHT(T54,2)) -> Jan 26 | P54: =IF(H54<0,"Sell","Buy") -> Buy | Q54: =H54*L54 -> 187600 | R54: =VLOOKUP(F54,Control!$B:$C,2,FALSE) -> Freight | S54: =VLOOKUP(F54,Control!$B:$D,3,FALSE) -> Freight | T54: =YEAR(I54) -> 2026 | U54: =IFERROR(IF(H54>0,"Buy","Sell"),"") -> Buy | V54: Active | W54: =_xlfn.XLOOKUP(Table3[[#This Row],[Instrument]],Control!$B$2:$B$19,Control!$E$2:$E$19) -> #N/A | X54: =Table3[[#This Row],[Month1]] -> 46053 | Y54: =Table3[[#This Row],[Quantity]] -> 700 | Z54: =_xlfn.XLOOKUP(Table3[[#This Row],[Instrument]],Control!$B$2:$B$19,Control!$F$2:$F$19) -> #N/A | AA54: =Table3[[#This Row],[Month2]] -> 46053 | AB54: =-Y54 -> -700
A55: Cargoes | B55: =_xlfn.XLOOKUP(Table3[[#This Row],[Cargo Name]],Ledger[Cargo Name],Ledger[SAP Deal Number]) -> ARA26HS00010 | C55: 0 | D55: January 26 2x EFP | E55: 46014 | F55: Freight-TD25 | G55: Hedge | H55: 700 | I55: 46053 | J55: 46053 | K55: 215 | L55: =VLOOKUP(I55,[2]USG!$O$45:$S$100,MATCH(F55,[2]USG!$O$46:$S$46,0),FALSE) -> 268 | M55: =IF(Table3[[#This Row],[Quantity]]>0,-21.47*70*(Table3[[#This Row],[Price]]-Table3[[#This Row],[Mtm]])/100,21.47*70*(Table3[[#This Row],[Price]]-Table3[[#This Row],[Mtm]])/100) -> 796.537 | N55: =H55*K55 -> 150500 | O55: =IF(I55=J55,TEXT(I55,"MMM YY"),TEXT(I55,"MMM")&"/"&TEXT(J55,"MMM")&" "&RIGHT(T55,2)) -> Jan 26 | P55: =IF(H55<0,"Sell","Buy") -> Buy | Q55: =H55*L55 -> 187600 | R55: =VLOOKUP(F55,Control!$B:$C,2,FALSE) -> Freight | S55: =VLOOKUP(F55,Control!$B:$D,3,FALSE) -> Freight | T55: =YEAR(I55) -> 2026 | U55: =IFERROR(IF(H55>0,"Buy","Sell"),"") -> Buy | V55: Active | W55: =_xlfn.XLOOKUP(Table3[[#This Row],[Instrument]],Control!$B$2:$B$19,Control!$E$2:$E$19) -> #N/A | X55: =Table3[[#This Row],[Month1]] -> 46053 | Y55: =Table3[[#This Row],[Quantity]] -> 700 | Z55: =_xlfn.XLOOKUP(Table3[[#This Row],[Instrument]],Control!$B$2:$B$19,Control!$F$2:$F$19) -> #N/A | AA55: =Table3[[#This Row],[Month2]] -> 46053 | AB55: =-Y55 -> -700
A56: Cargoes | B56: =_xlfn.XLOOKUP(Table3[[#This Row],[Cargo Name]],Ledger[Cargo Name],Ledger[SAP Deal Number]) -> ARA26HS00010 | C56: 0 | D56: January 26 2x EFP | E56: 45960 | F56: Freight-TD7 | G56: Expo | H56: 700 | I56: 46053 | J56: 46053 | K56: 140 | L56: =VLOOKUP(I56,[2]USG!$O$45:$S$100,MATCH(F56,[2]USG!$O$46:$S$46,0),FALSE) -> 175.25 | M56: =IF(Table3[[#This Row],[Quantity]]>0,-7.14*86.7*(Table3[[#This Row],[Price]]-Table3[[#This Row],[Mtm]])/100,7.14*86.7*(Table3[[#This Row],[Price]]-Table3[[#This Row],[Mtm]])/100) -> 218.2109 | N56: =H56*K56 -> 98000 | O56: =IF(I56=J56,TEXT(I56,"MMM YY"),TEXT(I56,"MMM")&"/"&TEXT(J56,"MMM")&" "&RIGHT(T56,2)) -> Jan 26 | P56: =IF(H56<0,"Sell","Buy") -> Buy | Q56: =H56*L56 -> 122675 | R56: =VLOOKUP(F56,Control!$B:$C,2,FALSE) -> Freight | S56: =VLOOKUP(F56,Control!$B:$D,3,FALSE) -> Freight | T56: =YEAR(I56) -> 2026 | U56: =IFERROR(IF(H56>0,"Buy","Sell"),"") -> Buy | V56: Active | W56: =_xlfn.XLOOKUP(Table3[[#This Row],[Instrument]],Control!$B$2:$B$19,Control!$E$2:$E$19) -> #N/A | X56: =Table3[[#This Row],[Month1]] -> 46053 | Y56: =Table3[[#This Row],[Quantity]] -> 700 | Z56: =_xlfn.XLOOKUP(Table3[[#This Row],[Instrument]],Control!$B$2:$B$19,Control!$F$2:$F$19) -> #N/A | AA56: =Table3[[#This Row],[Month2]] -> 46053 | AB56: =-Y56 -> -700
A57: Cargoes | B57: =_xlfn.XLOOKUP(Table3[[#This Row],[Cargo Name]],Ledger[Cargo Name],Ledger[SAP Deal Number]) -> ARA26HS00010 | C57: 0 | D57: January 26 2x EFP | E57: 45960 | F57: Freight-TD7 | G57: Expo | H57: 700 | I57: 46053 | J57: 46053 | K57: 140 | L57: =VLOOKUP(I57,[2]USG!$O$45:$S$100,MATCH(F57,[2]USG!$O$46:$S$46,0),FALSE) -> 175.25 | M57: =IF(Table3[[#This Row],[Quantity]]>0,-7.14*86.7*(Table3[[#This Row],[Price]]-Table3[[#This Row],[Mtm]])/100,7.14*86.7*(Table3[[#This Row],[Price]]-Table3[[#This Row],[Mtm]])/100) -> 218.2109 | N57: =H57*K57 -> 98000 | O57: =IF(I57=J57,TEXT(I57,"MMM YY"),TEXT(I57,"MMM")&"/"&TEXT(J57,"MMM")&" "&RIGHT(T57,2)) -> Jan 26 | P57: =IF(H57<0,"Sell","Buy") -> Buy | Q57: =H57*L57 -> 122675 | R57: =VLOOKUP(F57,Control!$B:$C,2,FALSE) -> Freight | S57: =VLOOKUP(F57,Control!$B:$D,3,FALSE) -> Freight | T57: =YEAR(I57) -> 2026 | U57: =IFERROR(IF(H57>0,"Buy","Sell"),"") -> Buy | V57: Active | W57: =_xlfn.XLOOKUP(Table3[[#This Row],[Instrument]],Control!$B$2:$B$19,Control!$E$2:$E$19) -> #N/A | X57: =Table3[[#This Row],[Month1]] -> 46053 | Y57: =Table3[[#This Row],[Quantity]] -> 700 | Z57: =_xlfn.XLOOKUP(Table3[[#This Row],[Instrument]],Control!$B$2:$B$19,Control!$F$2:$F$19) -> #N/A | AA57: =Table3[[#This Row],[Month2]] -> 46053 | AB57: =-Y57 -> -700
A58: Cargoes | B58: =_xlfn.XLOOKUP(Table3[[#This Row],[Cargo Name]],Ledger[Cargo Name],Ledger[SAP Deal Number]) -> ARA26HS00010 | C58: 0 | D58: January 26 2x EFP | E58: 45994 | F58: Freight-TD7 | G58: Hedge | H58: -1400 | I58: 46053 | J58: 46053 | K58: 14.23 | L58: =VLOOKUP(I58,[2]USG!$O$45:$S100,MATCH("Freight-TD7 $/MT",[2]USG!$O$46:$S$46,0),FALSE) -> 18.2961 | M58: =-(K58-L58)*-160 -> -650.576 | N58: =H58*K58 -> -19922 | O58: =IF(I58=J58,TEXT(I58,"MMM YY"),TEXT(I58,"MMM")&"/"&TEXT(J58,"MMM")&" "&RIGHT(T58,2)) -> Jan 26 | P58: =IF(H58<0,"Sell","Buy") -> Sell | Q58: =H58*L58 -> -25614.54 | R58: =VLOOKUP(F58,Control!$B:$C,2,FALSE) -> Freight | S58: =VLOOKUP(F58,Control!$B:$D,3,FALSE) -> Freight | T58: =YEAR(I58) -> 2026 | U58: =IFERROR(IF(H58>0,"Buy","Sell"),"") -> Sell | V58: Active | W58: =_xlfn.XLOOKUP(Table3[[#This Row],[Instrument]],Control!$B$2:$B$19,Control!$E$2:$E$19) -> #N/A | X58: =Table3[[#This Row],[Month1]] -> 46053 | Y58: =Table3[[#This Row],[Quantity]] -> -1400 | Z58: =_xlfn.XLOOKUP(Table3[[#This Row],[Instrument]],Control!$B$2:$B$19,Control!$F$2:$F$19) -> #N/A | AA58: =Table3[[#This Row],[Month2]] -> 46053 | AB58: =-Y58 -> 1400
A59: Cargoes | B59: =_xlfn.XLOOKUP(Table3[[#This Row],[Cargo Name]],Ledger[Cargo Name],Ledger[SAP Deal Number]) -> Unallocated | C59: 0 | D59: Unallocated | E59: 45986 | F59: DFL | G59: Hedge | H59: -1075 | I59: 46053 | J59: 46053 | K59: 0.44 | L59: =VLOOKUP($I59,'PnL26'!$E$7:$F$59,2,FALSE) -> 2.09 | M59: =IFERROR((L59-K59)*H59,"") -> -1773.75 | N59: =H59*K59 -> -473 | O59: =IF(I59=J59,TEXT(I59,"MMM YY"),TEXT(I59,"MMM")&"/"&TEXT(J59,"MMM")&" "&RIGHT(T59,2)) -> Jan 26 | P59: =IF(H59<0,"Sell","Buy") -> Sell | Q59: =H59*L59 -> -2246.75 | R59: =VLOOKUP(F59,Control!$B:$C,2,FALSE) -> Swaps | S59: =VLOOKUP(F59,Control!$B:$D,3,FALSE) -> Dated | T59: =YEAR(I59) -> 2026 | U59: =IFERROR(IF(H59>0,"Buy","Sell"),"") -> Sell | V59: Active | W59: =_xlfn.XLOOKUP(Table3[[#This Row],[Instrument]],Control!$B$2:$B$19,Control!$E$2:$E$19) -> #N/A | X59: =Table3[[#This Row],[Month1]] -> 46053 | Y59: =Table3[[#This Row],[Quantity]] -> -1075 | Z59: =_xlfn.XLOOKUP(Table3[[#This Row],[Instrument]],Control!$B$2:$B$19,Control!$F$2:$F$19) -> #N/A | AA59: =Table3[[#This Row],[Month2]] -> 46053 | AB59: =-Y59 -> 1075
A60: Cargoes | B60: =_xlfn.XLOOKUP(Table3[[#This Row],[Cargo Name]],Ledger[Cargo Name],Ledger[SAP Deal Number]) -> ARA26HS00010 | C60: 0 | D60: January 26 2x EFP | E60: 45987 | F60: WTI-Brent | G60: Expo | H60: 1400 | I60: 46053 | J60: 46053 | K60: -4.44 | L60: =IF(OR(S60="WTI Sprds",S60="Brent Sprds",S60="WTI-Brent",S60="DFL"),INDEX(INDIRECT("'" & S60 & "'!$A$6:$XFD$1048576"),MATCH('PnL26'!$P$1,INDIRECT("'" & S60 & "'!$A$6:$A$1048576"),0),MATCH(EOMONTH(I60,0),INDIRECT("'" & S60 & "'!$A$4:$XFD$4"),0)),INDEX(BBG!$A:$BA,MATCH('PnL26'!$P$1,BBG!$A:$A,0),MATCH($I60,BBG!$A$4:$BA$4,0))-INDEX(BBG!$A:$BA,MATCH('PnL26'!$P$1,BBG!$A:$A,0),MATCH($J60,BBG!$A$4:$BA$4,0))) -> -4.65 | N60: =H60*K60 -> -6216 | O60: =IF(I60=J60,TEXT(I60,"MMM YY"),TEXT(I60,"MMM")&"/"&TEXT(J60,"MMM")&" "&RIGHT(T60,2)) -> Jan 26 | P60: =IF(H60<0,"Sell","Buy") -> Buy | Q60: =H60*L60 -> -6510 | R60: =VLOOKUP(F60,Control!$B:$C,2,FALSE) -> Swaps | S60: =VLOOKUP(F60,Control!$B:$D,3,FALSE) -> WTI-Brent | T60: =YEAR(I60) -> 2026 | U60: =IFERROR(IF(H60>0,"Buy","Sell"),"") -> Buy | V60: Active | W60: =_xlfn.XLOOKUP(Table3[[#This Row],[Instrument]],Control!$B$2:$B$19,Control!$E$2:$E$19) -> WTI | X60: =Table3[[#This Row],[Month1]] -> 46053 | Y60: =Table3[[#This Row],[Quantity]] -> 1400 | Z60: =_xlfn.XLOOKUP(Table3[[#This Row],[Instrument]],Control!$B$2:$B$19,Control!$F$2:$F$19) -> Brent | AA60: =Table3[[#This Row],[Month2]] -> 46053 | AB60: =-Y60 -> -1400
A61: Cargoes | B61: =_xlfn.XLOOKUP(Table3[[#This Row],[Cargo Name]],Ledger[Cargo Name],Ledger[SAP Deal Number]) -> Unallocated | C61: 0 | D61: Unallocated | E61: 45987 | F61: WTI Sprds | G61: Hedge | H61: 134 | I61: 46081 | J61: 46112 | K61: 0.16 | L61: =IF(OR(S61="WTI Sprds",S61="Brent Sprds",S61="WTI-Brent",S61="DFL"),INDEX(INDIRECT("'" & S61 & "'!$A$6:$XFD$1048576"),MATCH('PnL26'!$P$1,INDIRECT("'" & S61 & "'!$A$6:$A$1048576"),0),MATCH(EOMONTH(I61,0),INDIRECT("'" & S61 & "'!$A$4:$XFD$4"),0)),INDEX(BBG!$A:$BA,MATCH('PnL26'!$P$1,BBG!$A:$A,0),MATCH($I61,BBG!$A$4:$BA$4,0))-INDEX(BBG!$A:$BA,MATCH('PnL26'!$P$1,BBG!$A:$A,0),MATCH($J61,BBG!$A$4:$BA$4,0))) -> 0.1 | M61: =IFERROR((L61-K61)*H61,"") -> -8.04 | N61: =H61*K61 -> 21.44 | O61: =IF(I61=J61,TEXT(I61,"MMM YY"),TEXT(I61,"MMM")&"/"&TEXT(J61,"MMM")&" "&RIGHT(T61,2)) -> Feb/Mar 26 | P61: =IF(H61<0,"Sell","Buy") -> Buy | Q61: =H61*L61 -> 13.4 | R61: =VLOOKUP(F61,Control!$B:$C,2,FALSE) -> Futures | S61: =VLOOKUP(F61,Control!$B:$D,3,FALSE) -> WTI Sprds | T61: =YEAR(I61) -> 2026 | U61: =IFERROR(IF(H61>0,"Buy","Sell"),"") -> Buy | V61: Active | W61: =_xlfn.XLOOKUP(Table3[[#This Row],[Instrument]],Control!$B$2:$B$19,Control!$E$2:$E$19) -> WTI | X61: =Table3[[#This Row],[Month1]] -> 46081 | Y61: =Table3[[#This Row],[Quantity]] -> 134 | Z61: =_xlfn.XLOOKUP(Table3[[#This Row],[Instrument]],Control!$B$2:$B$19,Control!$F$2:$F$19) -> WTI | AA61: =Table3[[#This Row],[Month2]] -> 46112 | AB61: =-Y61 -> -134
A62: Cargoes | B62: =_xlfn.XLOOKUP(Table3[[#This Row],[Cargo Name]],Ledger[Cargo Name],Ledger[SAP Deal Number]) -> Unallocated | C62: 0 | D62: Unallocated | E62: 45989 | F62: WTI Sprds | G62: Hedge | H62: 134 | I62: 46081 | J62: 46112 | K62: 0.2 | L62: =IF(OR(S62="WTI Sprds",S62="Brent Sprds",S62="WTI-Brent",S62="DFL"),INDEX(INDIRECT("'" & S62 & "'!$A$6:$XFD$1048576"),MATCH('PnL26'!$P$1,INDIRECT("'" & S62 & "'!$A$6:$A$1048576"),0),MATCH(EOMONTH(I62,0),INDIRECT("'" & S62 & "'!$A$4:$XFD$4"),0)),INDEX(BBG!$A:$BA,MATCH('PnL26'!$P$1,BBG!$A:$A,0),MATCH($I62,BBG!$A$4:$BA$4,0))-INDEX(BBG!$A:$BA,MATCH('PnL26'!$P$1,BBG!$A:$A,0),MATCH($J62,BBG!$A$4:$BA$4,0))) -> 0.1 | M62: =IFERROR((L62-K62)*H62,"") -> -13.4 | N62: =H62*K62 -> 26.8 | O62: =IF(I62=J62,TEXT(I62,"MMM YY"),TEXT(I62,"MMM")&"/"&TEXT(J62,"MMM")&" "&RIGHT(T62,2)) -> Feb/Mar 26 | P62: =IF(H62<0,"Sell","Buy") -> Buy | Q62: =H62*L62 -> 13.4 | R62: =VLOOKUP(F62,Control!$B:$C,2,FALSE) -> Futures | S62: =VLOOKUP(F62,Control!$B:$D,3,FALSE) -> WTI Sprds | T62: =YEAR(I62) -> 2026 | U62: =IFERROR(IF(H62>0,"Buy","Sell"),"") -> Buy | V62: Active | W62: =_xlfn.XLOOKUP(Table3[[#This Row],[Instrument]],Control!$B$2:$B$19,Control!$E$2:$E$19) -> WTI | X62: =Table3[[#This Row],[Month1]] -> 46081 | Y62: =Table3[[#This Row],[Quantity]] -> 134 | Z62: =_xlfn.XLOOKUP(Table3[[#This Row],[Instrument]],Control!$B$2:$B$19,Control!$F$2:$F$19) -> WTI | AA62: =Table3[[#This Row],[Month2]] -> 46112 | AB62: =-Y62 -> -134
A63: Cargoes | B63: =_xlfn.XLOOKUP(Table3[[#This Row],[Cargo Name]],Ledger[Cargo Name],Ledger[SAP Deal Number]) -> Unallocated | C63: 0 | D63: Unallocated | E63: 45992 | F63: WTI Sprds | G63: Hedge | H63: 134 | I63: 46081 | J63: 46112 | K63: 0.2 | L63: =IF(OR(S63="WTI Sprds",S63="Brent Sprds",S63="WTI-Brent",S63="DFL"),INDEX(INDIRECT("'" & S63 & "'!$A$6:$XFD$1048576"),MATCH('PnL26'!$P$1,INDIRECT("'" & S63 & "'!$A$6:$A$1048576"),0),MATCH(EOMONTH(I63,0),INDIRECT("'" & S63 & "'!$A$4:$XFD$4"),0)),INDEX(BBG!$A:$BA,MATCH('PnL26'!$P$1,BBG!$A:$A,0),MATCH($I63,BBG!$A$4:$BA$4,0))-INDEX(BBG!$A:$BA,MATCH('PnL26'!$P$1,BBG!$A:$A,0),MATCH($J63,BBG!$A$4:$BA$4,0))) -> 0.1 | M63: =IFERROR((L63-K63)*H63,"") -> -13.4 | N63: =H63*K63 -> 26.8 | O63: =IF(I63=J63,TEXT(I63,"MMM YY"),TEXT(I63,"MMM")&"/"&TEXT(J63,"MMM")&" "&RIGHT(T63,2)) -> Feb/Mar 26 | P63: =IF(H63<0,"Sell","Buy") -> Buy | Q63: =H63*L63 -> 13.4 | R63: =VLOOKUP(F63,Control!$B:$C,2,FALSE) -> Futures | S63: =VLOOKUP(F63,Control!$B:$D,3,FALSE) -> WTI Sprds | T63: =YEAR(I63) -> 2026 | U63: =IFERROR(IF(H63>0,"Buy","Sell"),"") -> Buy | V63: Active | W63: =_xlfn.XLOOKUP(Table3[[#This Row],[Instrument]],Control!$B$2:$B$19,Control!$E$2:$E$19) -> WTI | X63: =Table3[[#This Row],[Month1]] -> 46081 | Y63: =Table3[[#This Row],[Quantity]] -> 134 | Z63: =_xlfn.XLOOKUP(Table3[[#This Row],[Instrument]],Control!$B$2:$B$19,Control!$F$2:$F$19) -> WTI | AA63: =Table3[[#This Row],[Month2]] -> 46112 | AB63: =-Y63 -> -134
A64: Cargoes | B64: =_xlfn.XLOOKUP(Table3[[#This Row],[Cargo Name]],Ledger[Cargo Name],Ledger[SAP Deal Number]) -> Unallocated | C64: 0 | D64: Unallocated | E64: 45992 | F64: Brent Sprds | G64: Hedge | H64: 429 | I64: 46081 | J64: 46112 | K64: 0.38 | L64: =IF(OR(S64="WTI Sprds",S64="Brent Sprds",S64="WTI-Brent",S64="DFL"),INDEX(INDIRECT("'" & S64 & "'!$A$6:$XFD$1048576"),MATCH('PnL26'!$P$1,INDIRECT("'" & S64 & "'!$A$6:$A$1048576"),0),MATCH(EOMONTH(I64,0),INDIRECT("'" & S64 & "'!$A$4:$XFD$4"),0)),INDEX(BBG!$A:$BA,MATCH('PnL26'!$P$1,BBG!$A:$A,0),MATCH($I64,BBG!$A$4:$BA$4,0))-INDEX(BBG!$A:$BA,MATCH('PnL26'!$P$1,BBG!$A:$A,0),MATCH($J64,BBG!$A$4:$BA$4,0))) -> 0.59 | M64: =IFERROR((L64-K64)*H64,"") -> 90.09 | N64: =H64*K64 -> 163.02 | O64: =IF(I64=J64,TEXT(I64,"MMM YY"),TEXT(I64,"MMM")&"/"&TEXT(J64,"MMM")&" "&RIGHT(T64,2)) -> Feb/Mar 26 | P64: =IF(H64<0,"Sell","Buy") -> Buy | Q64: =H64*L64 -> 253.11 | R64: =VLOOKUP(F64,Control!$B:$C,2,FALSE) -> Futures | S64: =VLOOKUP(F64,Control!$B:$D,3,FALSE) -> Brent Sprds | T64: =YEAR(I64) -> 2026 | U64: =IFERROR(IF(H64>0,"Buy","Sell"),"") -> Buy | V64: Active | W64: =_xlfn.XLOOKUP(Table3[[#This Row],[Instrument]],Control!$B$2:$B$19,Control!$E$2:$E$19) -> Brent | X64: =Table3[[#This Row],[Month1]] -> 46081 | Y64: =Table3[[#This Row],[Quantity]] -> 429 | Z64: =_xlfn.XLOOKUP(Table3[[#This Row],[Instrument]],Control!$B$2:$B$19,Control!$F$2:$F$19) -> Brent | AA64: =Table3[[#This Row],[Month2]] -> 46112 | AB64: =-Y64 -> -429
A65: Cargoes | B65: =_xlfn.XLOOKUP(Table3[[#This Row],[Cargo Name]],Ledger[Cargo Name],Ledger[SAP Deal Number]) -> Unallocated | C65: 0 | D65: Unallocated | E65: 45993 | F65: DFL | G65: Hedge | H65: -400 | I65: 46053 | J65: 46053 | K65: 0.45 | L65: =VLOOKUP($I65,'PnL26'!$E$7:$F$59,2,FALSE) -> 2.09 | M65: =IFERROR((L65-K65)*H65,"") -> -656 | N65: =H65*K65 -> -180 | O65: =IF(I65=J65,TEXT(I65,"MMM YY"),TEXT(I65,"MMM")&"/"&TEXT(J65,"MMM")&" "&RIGHT(T65,2)) -> Jan 26 | P65: =IF(H65<0,"Sell","Buy") -> Sell | Q65: =H65*L65 -> -836 | R65: =VLOOKUP(F65,Control!$B:$C,2,FALSE) -> Swaps | S65: =VLOOKUP(F65,Control!$B:$D,3,FALSE) -> Dated | T65: =YEAR(I65) -> 2026 | U65: =IFERROR(IF(H65>0,"Buy","Sell"),"") -> Sell | V65: Active | W65: =_xlfn.XLOOKUP(Table3[[#This Row],[Instrument]],Control!$B$2:$B$19,Control!$E$2:$E$19) -> #N/A | X65: =Table3[[#This Row],[Month1]] -> 46053 | Y65: =Table3[[#This Row],[Quantity]] -> -400 | Z65: =_xlfn.XLOOKUP(Table3[[#This Row],[Instrument]],Control!$B$2:$B$19,Control!$F$2:$F$19) -> #N/A | AA65: =Table3[[#This Row],[Month2]] -> 46053 | AB65: =-Y65 -> 400
A66: Cargoes | B66: =_xlfn.XLOOKUP(Table3[[#This Row],[Cargo Name]],Ledger[Cargo Name],Ledger[SAP Deal Number]) -> Unallocated | C66: 0 | D66: Unallocated | E66: 45993 | F66: Brent Sprds | G66: Hedge | H66: 200 | I66: 46081 | J66: 46112 | K66: 0.39 | L66: =IF(OR(S66="WTI Sprds",S66="Brent Sprds",S66="WTI-Brent",S66="DFL"),INDEX(INDIRECT("'" & S66 & "'!$A$6:$XFD$1048576"),MATCH('PnL26'!$P$1,INDIRECT("'" & S66 & "'!$A$6:$A$1048576"),0),MATCH(EOMONTH(I66,0),INDIRECT("'" & S66 & "'!$A$4:$XFD$4"),0)),INDEX(BBG!$A:$BA,MATCH('PnL26'!$P$1,BBG!$A:$A,0),MATCH($I66,BBG!$A$4:$BA$4,0))-INDEX(BBG!$A:$BA,MATCH('PnL26'!$P$1,BBG!$A:$A,0),MATCH($J66,BBG!$A$4:$BA$4,0))) -> 0.59 | M66: =IFERROR((L66-K66)*H66,"") -> 40 | N66: =H66*K66 -> 78 | O66: =IF(I66=J66,TEXT(I66,"MMM YY"),TEXT(I66,"MMM")&"/"&TEXT(J66,"MMM")&" "&RIGHT(T66,2)) -> Feb/Mar 26 | P66: =IF(H66<0,"Sell","Buy") -> Buy | Q66: =H66*L66 -> 118 | R66: =VLOOKUP(F66,Control!$B:$C,2,FALSE) -> Futures | S66: =VLOOKUP(F66,Control!$B:$D,3,FALSE) -> Brent Sprds | T66: =YEAR(I66) -> 2026 | U66: =IFERROR(IF(H66>0,"Buy","Sell"),"") -> Buy | V66: Active | W66: =_xlfn.XLOOKUP(Table3[[#This Row],[Instrument]],Control!$B$2:$B$19,Control!$E$2:$E$19) -> Brent | X66: =Table3[[#This Row],[Month1]] -> 46081 | Y66: =Table3[[#This Row],[Quantity]] -> 200 | Z66: =_xlfn.XLOOKUP(Table3[[#This Row],[Instrument]],Control!$B$2:$B$19,Control!$F$2:$F$19) -> Brent | AA66: =Table3[[#This Row],[Month2]] -> 46112 | AB66: =-Y66 -> -200
A67: Cargoes | B67: =_xlfn.XLOOKUP(Table3[[#This Row],[Cargo Name]],Ledger[Cargo Name],Ledger[SAP Deal Number]) -> Unallocated | C67: 0 | D67: Unallocated | E67: 45993 | F67: Brent Sprds | G67: Hedge | H67: 200 | I67: 46081 | J67: 46112 | K67: 0.38 | L67: =IF(OR(S67="WTI Sprds",S67="Brent Sprds",S67="WTI-Brent",S67="DFL"),INDEX(INDIRECT("'" & S67 & "'!$A$6:$XFD$1048576"),MATCH('PnL26'!$P$1,INDIRECT("'" & S67 & "'!$A$6:$A$1048576"),0),MATCH(EOMONTH(I67,0),INDIRECT("'" & S67 & "'!$A$4:$XFD$4"),0)),INDEX(BBG!$A:$BA,MATCH('PnL26'!$P$1,BBG!$A:$A,0),MATCH($I67,BBG!$A$4:$BA$4,0))-INDEX(BBG!$A:$BA,MATCH('PnL26'!$P$1,BBG!$A:$A,0),MATCH($J67,BBG!$A$4:$BA$4,0))) -> 0.59 | M67: =IFERROR((L67-K67)*H67,"") -> 42 | N67: =H67*K67 -> 76 | O67: =IF(I67=J67,TEXT(I67,"MMM YY"),TEXT(I67,"MMM")&"/"&TEXT(J67,"MMM")&" "&RIGHT(T67,2)) -> Feb/Mar 26 | P67: =IF(H67<0,"Sell","Buy") -> Buy | Q67: =H67*L67 -> 118 | R67: =VLOOKUP(F67,Control!$B:$C,2,FALSE) -> Futures | S67: =VLOOKUP(F67,Control!$B:$D,3,FALSE) -> Brent Sprds | T67: =YEAR(I67) -> 2026 | U67: =IFERROR(IF(H67>0,"Buy","Sell"),"") -> Buy | V67: Active | W67: =_xlfn.XLOOKUP(Table3[[#This Row],[Instrument]],Control!$B$2:$B$19,Control!$E$2:$E$19) -> Brent | X67: =Table3[[#This Row],[Month1]] -> 46081 | Y67: =Table3[[#This Row],[Quantity]] -> 200 | Z67: =_xlfn.XLOOKUP(Table3[[#This Row],[Instrument]],Control!$B$2:$B$19,Control!$F$2:$F$19) -> Brent | AA67: =Table3[[#This Row],[Month2]] -> 46112 | AB67: =-Y67 -> -200
A68: Cargoes | B68: =_xlfn.XLOOKUP(Table3[[#This Row],[Cargo Name]],Ledger[Cargo Name],Ledger[SAP Deal Number]) -> Unallocated | C68: 0 | D68: Unallocated | E68: 45993 | F68: Brent Sprds | G68: Hedge | H68: 200 | I68: 46081 | J68: 46112 | K68: 0.37 | L68: =IF(OR(S68="WTI Sprds",S68="Brent Sprds",S68="WTI-Brent",S68="DFL"),INDEX(INDIRECT("'" & S68 & "'!$A$6:$XFD$1048576"),MATCH('PnL26'!$P$1,INDIRECT("'" & S68 & "'!$A$6:$A$1048576"),0),MATCH(EOMONTH(I68,0),INDIRECT("'" & S68 & "'!$A$4:$XFD$4"),0)),INDEX(BBG!$A:$BA,MATCH('PnL26'!$P$1,BBG!$A:$A,0),MATCH($I68,BBG!$A$4:$BA$4,0))-INDEX(BBG!$A:$BA,MATCH('PnL26'!$P$1,BBG!$A:$A,0),MATCH($J68,BBG!$A$4:$BA$4,0))) -> 0.59 | M68: =IFERROR((L68-K68)*H68,"") -> 44 | N68: =H68*K68 -> 74 | O68: =IF(I68=J68,TEXT(I68,"MMM YY"),TEXT(I68,"MMM")&"/"&TEXT(J68,"MMM")&" "&RIGHT(T68,2)) -> Feb/Mar 26 | P68: =IF(H68<0,"Sell","Buy") -> Buy | Q68: =H68*L68 -> 118 | R68: =VLOOKUP(F68,Control!$B:$C,2,FALSE) -> Futures | S68: =VLOOKUP(F68,Control!$B:$D,3,FALSE) -> Brent Sprds | T68: =YEAR(I68) -> 2026 | U68: =IFERROR(IF(H68>0,"Buy","Sell"),"") -> Buy | V68: Active | W68: =_xlfn.XLOOKUP(Table3[[#This Row],[Instrument]],Control!$B$2:$B$19,Control!$E$2:$E$19) -> Brent | X68: =Table3[[#This Row],[Month1]] -> 46081 | Y68: =Table3[[#This Row],[Quantity]] -> 200 | Z68: =_xlfn.XLOOKUP(Table3[[#This Row],[Instrument]],Control!$B$2:$B$19,Control!$F$2:$F$19) -> Brent | AA68: =Table3[[#This Row],[Month2]] -> 46112 | AB68: =-Y68 -> -200
A69: Cargoes | B69: =_xlfn.XLOOKUP(Table3[[#This Row],[Cargo Name]],Ledger[Cargo Name],Ledger[SAP Deal Number]) -> Unallocated | C69: 0 | D69: Unallocated | E69: 45993 | F69: Brent Sprds | G69: Hedge | H69: 200 | I69: 46081 | J69: 46112 | K69: 0.36 | L69: =IF(OR(S69="WTI Sprds",S69="Brent Sprds",S69="WTI-Brent",S69="DFL"),INDEX(INDIRECT("'" & S69 & "'!$A$6:$XFD$1048576"),MATCH('PnL26'!$P$1,INDIRECT("'" & S69 & "'!$A$6:$A$1048576"),0),MATCH(EOMONTH(I69,0),INDIRECT("'" & S69 & "'!$A$4:$XFD$4"),0)),INDEX(BBG!$A:$BA,MATCH('PnL26'!$P$1,BBG!$A:$A,0),MATCH($I69,BBG!$A$4:$BA$4,0))-INDEX(BBG!$A:$BA,MATCH('PnL26'!$P$1,BBG!$A:$A,0),MATCH($J69,BBG!$A$4:$BA$4,0))) -> 0.59 | M69: =IFERROR((L69-K69)*H69,"") -> 46 | N69: =H69*K69 -> 72 | O69: =IF(I69=J69,TEXT(I69,"MMM YY"),TEXT(I69,"MMM")&"/"&TEXT(J69,"MMM")&" "&RIGHT(T69,2)) -> Feb/Mar 26 | P69: =IF(H69<0,"Sell","Buy") -> Buy | Q69: =H69*L69 -> 118 | R69: =VLOOKUP(F69,Control!$B:$C,2,FALSE) -> Futures | S69: =VLOOKUP(F69,Control!$B:$D,3,FALSE) -> Brent Sprds | T69: =YEAR(I69) -> 2026 | U69: =IFERROR(IF(H69>0,"Buy","Sell"),"") -> Buy | V69: Active | W69: =_xlfn.XLOOKUP(Table3[[#This Row],[Instrument]],Control!$B$2:$B$19,Control!$E$2:$E$19) -> Brent | X69: =Table3[[#This Row],[Month1]] -> 46081 | Y69: =Table3[[#This Row],[Quantity]] -> 200 | Z69: =_xlfn.XLOOKUP(Table3[[#This Row],[Instrument]],Control!$B$2:$B$19,Control!$F$2:$F$19) -> Brent | AA69: =Table3[[#This Row],[Month2]] -> 46112 | AB69: =-Y69 -> -200
A70: Cargoes | B70: =_xlfn.XLOOKUP(Table3[[#This Row],[Cargo Name]],Ledger[Cargo Name],Ledger[SAP Deal Number]) -> Unallocated | C70: 0 | D70: Unallocated | E70: 45993 | F70: WTI Sprds | G70: Hedge | H70: 134 | I70: 46081 | J70: 46112 | K70: 0.2 | L70: =IF(OR(S70="WTI Sprds",S70="Brent Sprds",S70="WTI-Brent",S70="DFL"),INDEX(INDIRECT("'" & S70 & "'!$A$6:$XFD$1048576"),MATCH('PnL26'!$P$1,INDIRECT("'" & S70 & "'!$A$6:$A$1048576"),0),MATCH(EOMONTH(I70,0),INDIRECT("'" & S70 & "'!$A$4:$XFD$4"),0)),INDEX(BBG!$A:$BA,MATCH('PnL26'!$P$1,BBG!$A:$A,0),MATCH($I70,BBG!$A$4:$BA$4,0))-INDEX(BBG!$A:$BA,MATCH('PnL26'!$P$1,BBG!$A:$A,0),MATCH($J70,BBG!$A$4:$BA$4,0))) -> 0.1 | M70: =IFERROR((L70-K70)*H70,"") -> -13.4 | N70: =H70*K70 -> 26.8 | O70: =IF(I70=J70,TEXT(I70,"MMM YY"),TEXT(I70,"MMM")&"/"&TEXT(J70,"MMM")&" "&RIGHT(T70,2)) -> Feb/Mar 26 | P70: =IF(H70<0,"Sell","Buy") -> Buy | Q70: =H70*L70 -> 13.4 | R70: =VLOOKUP(F70,Control!$B:$C,2,FALSE) -> Futures | S70: =VLOOKUP(F70,Control!$B:$D,3,FALSE) -> WTI Sprds | T70: =YEAR(I70) -> 2026 | U70: =IFERROR(IF(H70>0,"Buy","Sell"),"") -> Buy | V70: Active | W70: =_xlfn.XLOOKUP(Table3[[#This Row],[Instrument]],Control!$B$2:$B$19,Control!$E$2:$E$19) -> WTI | X70: =Table3[[#This Row],[Month1]] -> 46081 | Y70: =Table3[[#This Row],[Quantity]] -> 134 | Z70: =_xlfn.XLOOKUP(Table3[[#This Row],[Instrument]],Control!$B$2:$B$19,Control!$F$2:$F$19) -> WTI | AA70: =Table3[[#This Row],[Month2]] -> 46112 | AB70: =-Y70 -> -134
A71: Cargoes | B71: =_xlfn.XLOOKUP(Table3[[#This Row],[Cargo Name]],Ledger[Cargo Name],Ledger[SAP Deal Number]) -> BPO26HS00002 | C71: 0 | D71: BP FOB Jan26 11-15 | E71: 46000 | F71: WTI Sprds | G71: Expo | H71: -233 | I71: 46081 | J71: 46112 | K71: 0.12 | L71: =IF(OR(S71="WTI Sprds",S71="Brent Sprds",S71="WTI-Brent",S71="DFL"),INDEX(INDIRECT("'" & S71 & "'!$A$6:$XFD$1048576"),MATCH('PnL26'!$P$1,INDIRECT("'" & S71 & "'!$A$6:$A$1048576"),0),MATCH(EOMONTH(I71,0),INDIRECT("'" & S71 & "'!$A$4:$XFD$4"),0)),INDEX(BBG!$A:$BA,MATCH('PnL26'!$P$1,BBG!$A:$A,0),MATCH($I71,BBG!$A$4:$BA$4,0))-INDEX(BBG!$A:$BA,MATCH('PnL26'!$P$1,BBG!$A:$A,0),MATCH($J71,BBG!$A$4:$BA$4,0))) -> 0.1 | M71: =IFERROR((L71-K71)*H71,"") -> 4.66 | N71: =H71*K71 -> -27.96 | O71: =IF(I71=J71,TEXT(I71,"MMM YY"),TEXT(I71,"MMM")&"/"&TEXT(J71,"MMM")&" "&RIGHT(T71,2)) -> Feb/Mar 26 | P71: =IF(H71<0,"Sell","Buy") -> Sell | Q71: =H71*L71 -> -23.3 | R71: =VLOOKUP(F71,Control!$B:$C,2,FALSE) -> Futures | S71: =VLOOKUP(F71,Control!$B:$D,3,FALSE) -> WTI Sprds | T71: =YEAR(I71) -> 2026 | U71: =IFERROR(IF(H71>0,"Buy","Sell"),"") -> Sell | V71: Active | W71: =_xlfn.XLOOKUP(Table3[[#This Row],[Instrument]],Control!$B$2:$B$19,Control!$E$2:$E$19) -> WTI | X71: =Table3[[#This Row],[Month1]] -> 46081 | Y71: =Table3[[#This Row],[Quantity]] -> -233 | Z71: =_xlfn.XLOOKUP(Table3[[#This Row],[Instrument]],Control!$B$2:$B$19,Control!$F$2:$F$19) -> WTI | AA71: =Table3[[#This Row],[Month2]] -> 46112 | AB71: =-Y71 -> 233
A72: Cargoes | B72: =_xlfn.XLOOKUP(Table3[[#This Row],[Cargo Name]],Ledger[Cargo Name],Ledger[SAP Deal Number]) -> Unallocated | C72: 0 | D72: Unallocated | E72: 46000 | F72: CFD | G72: Hedge | H72: -200 | I72: Jan05-Jan09 | J72: 46053 | K72: 0.52 | L72: =VLOOKUP($I72,'PnL26'!B:C,2,FALSE) -> 1.54 | M72: =IFERROR((L72-K72)*H72,"") -> -204 | N72: =H72*K72 -> -104 | O72: =O65 -> Jan 26 | P72: =IF(H72<0,"Sell","Buy") -> Sell | Q72: =H72*L72 -> -308 | R72: =VLOOKUP(F72,Control!$B:$C,2,FALSE) -> Swaps | S72: =VLOOKUP(F72,Control!$B:$D,3,FALSE) -> Dated | T72: 2025 | U72: =IFERROR(IF(H72>0,"Buy","Sell"),"") -> Sell | V72: Active | W72: =_xlfn.XLOOKUP(Table3[[#This Row],[Instrument]],Control!$B$2:$B$19,Control!$E$2:$E$19) -> #N/A | X72: =Table3[[#This Row],[Month1]] -> Jan05-Jan09 | Y72: =Table3[[#This Row],[Quantity]] -> -200 | Z72: =_xlfn.XLOOKUP(Table3[[#This Row],[Instrument]],Control!$B$2:$B$19,Control!$F$2:$F$19) -> #N/A | AA72: =Table3[[#This Row],[Month2]] -> 46053 | AB72: =-Y72 -> 200
A73: Cargoes | B73: =_xlfn.XLOOKUP(Table3[[#This Row],[Cargo Name]],Ledger[Cargo Name],Ledger[SAP Deal Number]) -> Unallocated | C73: 0 | D73: Unallocated | E73: 46000 | F73: CFD | G73: Hedge | H73: 200 | I73: Jan19-Jan23 | J73: 46053 | K73: 0.24869 | L73: =VLOOKUP($I73,'PnL26'!B:C,2,FALSE) -> 2.5 | M73: =IFERROR((L73-K73)*H73,"") -> 450.262 | N73: =H73*K73 -> 49.738 | O73: =O72 -> Jan 26 | P73: =IF(H73<0,"Sell","Buy") -> Buy | Q73: =H73*L73 -> 500 | R73: =VLOOKUP(F73,Control!$B:$C,2,FALSE) -> Swaps | S73: =VLOOKUP(F73,Control!$B:$D,3,FALSE) -> Dated | T73: 2025 | U73: =IFERROR(IF(H73>0,"Buy","Sell"),"") -> Buy | V73: Active | W73: =_xlfn.XLOOKUP(Table3[[#This Row],[Instrument]],Control!$B$2:$B$19,Control!$E$2:$E$19) -> #N/A | X73: =Table3[[#This Row],[Month1]] -> Jan19-Jan23 | Y73: =Table3[[#This Row],[Quantity]] -> 200 | Z73: =_xlfn.XLOOKUP(Table3[[#This Row],[Instrument]],Control!$B$2:$B$19,Control!$F$2:$F$19) -> #N/A | AA73: =Table3[[#This Row],[Month2]] -> 46053 | AB73: =-Y73 -> -200
A74: Cargoes | B74: =_xlfn.XLOOKUP(Table3[[#This Row],[Cargo Name]],Ledger[Cargo Name],Ledger[SAP Deal Number]) -> ARA26HS00013 | C74: 0 | D74: HDO March26 10-20 | E74: 46002 | F74: Physical | G74: Expo | H74: 2073 | I74: 46053 | J74: 46053 | K74: ='Cargo Econs 2025'!D434 -> 4.8628992 | L74: ='Cargo Econs 2025'!D435 -> 5.25 | M74: =IFERROR((L74-K74)*H74,"") -> 802.46 | N74: =H74*K74 -> 10080.79 | O74: =IF(I74=J74,TEXT(I74,"MMM YY"),TEXT(I74,"MMM")&"/"&TEXT(J74,"MMM")&" "&RIGHT(T74,2)) -> Jan 26 | P74: =IF(H74<0,"Sell","Buy") -> Buy | Q74: =H74*L74 -> 10883.25 | R74: =VLOOKUP(F74,Control!$B:$C,2,FALSE) -> Physical | S74: =VLOOKUP(F74,Control!$B:$D,3,FALSE) -> Physical | T74: =YEAR(I74) -> 2026 | U74: =IFERROR(IF(H74>0,"Buy","Sell"),"") -> Buy | V74: Active | W74: =_xlfn.XLOOKUP(Table3[[#This Row],[Instrument]],Control!$B$2:$B$19,Control!$E$2:$E$19) -> 0 | X74: =Table3[[#This Row],[Month1]] -> 46053 | Y74: =Table3[[#This Row],[Quantity]] -> 2073 | Z74: =_xlfn.XLOOKUP(Table3[[#This Row],[Instrument]],Control!$B$2:$B$19,Control!$F$2:$F$19) -> 0 | AA74: =Table3[[#This Row],[Month2]] -> 46053 | AB74: =-Y74 -> -2073
A75: Cargoes | B75: =_xlfn.XLOOKUP(Table3[[#This Row],[Cargo Name]],Ledger[Cargo Name],Ledger[SAP Deal Number]) -> ARA26HS00013 | C75: 0 | D75: HDO March26 10-20 | E75: 46002 | F75: WTI Sprds | G75: Expo | H75: -2073 | I75: 46081 | J75: 46112 | K75: 0.1 | L75: =IF(OR(S75="WTI Sprds",S75="Brent Sprds",S75="WTI-Brent",S75="DFL"),INDEX(INDIRECT("'" & S75 & "'!$A$6:$XFD$1048576"),MATCH('PnL26'!$P$1,INDIRECT("'" & S75 & "'!$A$6:$A$1048576"),0),MATCH(EOMONTH(I75,0),INDIRECT("'" & S75 & "'!$A$4:$XFD$4"),0)),INDEX(BBG!$A:$BA,MATCH('PnL26'!$P$1,BBG!$A:$A,0),MATCH($I75,BBG!$A$4:$BA$4,0))-INDEX(BBG!$A:$BA,MATCH('PnL26'!$P$1,BBG!$A:$A,0),MATCH($J75,BBG!$A$4:$BA$4,0))) -> 0.1 | M75: =IFERROR((L75-K75)*H75,"") -> 0 | N75: =H75*K75 -> -207.3 | O75: =IF(I75=J75,TEXT(I75,"MMM YY"),TEXT(I75,"MMM")&"/"&TEXT(J75,"MMM")&" "&RIGHT(T75,2)) -> Feb/Mar 26 | P75: =IF(H75<0,"Sell","Buy") -> Sell | Q75: =H75*L75 -> -207.3 | R75: =VLOOKUP(F75,Control!$B:$C,2,FALSE) -> Futures | S75: =VLOOKUP(F75,Control!$B:$D,3,FALSE) -> WTI Sprds | T75: =YEAR(I75) -> 2026 | U75: =IFERROR(IF(H75>0,"Buy","Sell"),"") -> Sell | V75: Active | W75: =_xlfn.XLOOKUP(Table3[[#This Row],[Instrument]],Control!$B$2:$B$19,Control!$E$2:$E$19) -> WTI | X75: =Table3[[#This Row],[Month1]] -> 46081 | Y75: =Table3[[#This Row],[Quantity]] -> -2073 | Z75: =_xlfn.XLOOKUP(Table3[[#This Row],[Instrument]],Control!$B$2:$B$19,Control!$F$2:$F$19) -> WTI | AA75: =Table3[[#This Row],[Month2]] -> 46112 | AB75: =-Y75 -> 2073
A76: Cargoes | B76: =_xlfn.XLOOKUP(Table3[[#This Row],[Cargo Name]],Ledger[Cargo Name],Ledger[SAP Deal Number]) -> ARA26HS00013 | C76: 0 | D76: HDO March26 10-20 | E76: 46002 | F76: WTI-Brent | G76: Expo | H76: -2073 | I76: 46112 | J76: 46112 | K76: -3.75 | L76: =IF(OR(S76="WTI Sprds",S76="Brent Sprds",S76="WTI-Brent",S76="DFL"),INDEX(INDIRECT("'" & S76 & "'!$A$6:$XFD$1048576"),MATCH('PnL26'!$P$1,INDIRECT("'" & S76 & "'!$A$6:$A$1048576"),0),MATCH(EOMONTH(I76,0),INDIRECT("'" & S76 & "'!$A$4:$XFD$4"),0)),INDEX(BBG!$A:$BA,MATCH('PnL26'!$P$1,BBG!$A:$A,0),MATCH($I76,BBG!$A$4:$BA$4,0))-INDEX(BBG!$A:$BA,MATCH('PnL26'!$P$1,BBG!$A:$A,0),MATCH($J76,BBG!$A$4:$BA$4,0))) -> -5.48 | M76: =IFERROR((L76-K76)*H76,"") -> 3586.29 | N76: =H76*K76 -> 7773.75 | O76: =IF(I76=J76,TEXT(I76,"MMM YY"),TEXT(I76,"MMM")&"/"&TEXT(J76,"MMM")&" "&RIGHT(T76,2)) -> Mar 26 | P76: =IF(H76<0,"Sell","Buy") -> Sell | Q76: =H76*L76 -> 11360.04 | R76: =VLOOKUP(F76,Control!$B:$C,2,FALSE) -> Swaps | S76: =VLOOKUP(F76,Control!$B:$D,3,FALSE) -> WTI-Brent | T76: =YEAR(I76) -> 2026 | U76: =IFERROR(IF(H76>0,"Buy","Sell"),"") -> Sell | V76: Active | W76: =_xlfn.XLOOKUP(Table3[[#This Row],[Instrument]],Control!$B$2:$B$19,Control!$E$2:$E$19) -> WTI | X76: =Table3[[#This Row],[Month1]] -> 46112 | Y76: =Table3[[#This Row],[Quantity]] -> -2073 | Z76: =_xlfn.XLOOKUP(Table3[[#This Row],[Instrument]],Control!$B$2:$B$19,Control!$F$2:$F$19) -> Brent | AA76: =Table3[[#This Row],[Month2]] -> 46112 | AB76: =-Y76 -> 2073
A77: Cargoes | B77: =_xlfn.XLOOKUP(Table3[[#This Row],[Cargo Name]],Ledger[Cargo Name],Ledger[SAP Deal Number]) -> ARA26HS00013 | C77: 0 | D77: HDO March26 10-20 | E77: 46002 | F77: Brent Sprds | G77: Expo | H77: -1980 | I77: 46112 | J77: 46142 | K77: 0.16 | L77: =IF(OR(S77="WTI Sprds",S77="Brent Sprds",S77="WTI-Brent",S77="DFL"),INDEX(INDIRECT("'" & S77 & "'!$A$6:$XFD$1048576"),MATCH('PnL26'!$P$1,INDIRECT("'" & S77 & "'!$A$6:$A$1048576"),0),MATCH(EOMONTH(I77,0),INDIRECT("'" & S77 & "'!$A$4:$XFD$4"),0)),INDEX(BBG!$A:$BA,MATCH('PnL26'!$P$1,BBG!$A:$A,0),MATCH($I77,BBG!$A$4:$BA$4,0))-INDEX(BBG!$A:$BA,MATCH('PnL26'!$P$1,BBG!$A:$A,0),MATCH($J77,BBG!$A$4:$BA$4,0))) -> 1.37 | M77: =IFERROR((L77-K77)*H77,"") -> -2395.8 | N77: =H77*K77 -> -316.8 | O77: =IF(I77=J77,TEXT(I77,"MMM YY"),TEXT(I77,"MMM")&"/"&TEXT(J77,"MMM")&" "&RIGHT(T77,2)) -> Mar/Apr 26 | P77: =IF(H77<0,"Sell","Buy") -> Sell | Q77: =H77*L77 -> -2712.6 | R77: =VLOOKUP(F77,Control!$B:$C,2,FALSE) -> Futures | S77: =VLOOKUP(F77,Control!$B:$D,3,FALSE) -> Brent Sprds | T77: =YEAR(I77) -> 2026 | U77: =IFERROR(IF(H77>0,"Buy","Sell"),"") -> Sell | V77: Active | W77: =_xlfn.XLOOKUP(Table3[[#This Row],[Instrument]],Control!$B$2:$B$19,Control!$E$2:$E$19) -> Brent | X77: =Table3[[#This Row],[Month1]] -> 46112 | Y77: =Table3[[#This Row],[Quantity]] -> -1980 | Z77: =_xlfn.XLOOKUP(Table3[[#This Row],[Instrument]],Control!$B$2:$B$19,Control!$F$2:$F$19) -> Brent | AA77: =Table3[[#This Row],[Month2]] -> 46142 | AB77: =-Y77 -> 1980
A78: Cargoes | B78: =_xlfn.XLOOKUP(Table3[[#This Row],[Cargo Name]],Ledger[Cargo Name],Ledger[SAP Deal Number]) -> ARA26HS00013 | C78: 0 | D78: HDO March26 10-20 | E78: 46002 | F78: Brent Sprds | G78: Expo | H78: -93 | I78: 46142 | J78: 46173 | K78: 0.05 | L78: =IF(OR(S78="WTI Sprds",S78="Brent Sprds",S78="WTI-Brent",S78="DFL"),INDEX(INDIRECT("'" & S78 & "'!$A$6:$XFD$1048576"),MATCH('PnL26'!$P$1,INDIRECT("'" & S78 & "'!$A$6:$A$1048576"),0),MATCH(EOMONTH(I78,0),INDIRECT("'" & S78 & "'!$A$4:$XFD$4"),0)),INDEX(BBG!$A:$BA,MATCH('PnL26'!$P$1,BBG!$A:$A,0),MATCH($I78,BBG!$A$4:$BA$4,0))-INDEX(BBG!$A:$BA,MATCH('PnL26'!$P$1,BBG!$A:$A,0),MATCH($J78,BBG!$A$4:$BA$4,0))) -> -0.39 | M78: =IFERROR((L78-K78)*H78,"") -> 40.92 | N78: =H78*K78 -> -4.65 | O78: =IF(I78=J78,TEXT(I78,"MMM YY"),TEXT(I78,"MMM")&"/"&TEXT(J78,"MMM")&" "&RIGHT(T78,2)) -> Apr/May 26 | P78: =IF(H78<0,"Sell","Buy") -> Sell | Q78: =H78*L78 -> 36.27 | R78: =VLOOKUP(F78,Control!$B:$C,2,FALSE) -> Futures | S78: =VLOOKUP(F78,Control!$B:$D,3,FALSE) -> Brent Sprds | T78: =YEAR(I78) -> 2026 | U78: =IFERROR(IF(H78>0,"Buy","Sell"),"") -> Sell | V78: Active | W78: =_xlfn.XLOOKUP(Table3[[#This Row],[Instrument]],Control!$B$2:$B$19,Control!$E$2:$E$19) -> Brent | X78: =Table3[[#This Row],[Month1]] -> 46142 | Y78: =Table3[[#This Row],[Quantity]] -> -93 | Z78: =_xlfn.XLOOKUP(Table3[[#This Row],[Instrument]],Control!$B$2:$B$19,Control!$F$2:$F$19) -> Brent | AA78: =Table3[[#This Row],[Month2]] -> 46173 | AB78: =-Y78 -> 93
A79: Cargoes | B79: =_xlfn.XLOOKUP(Table3[[#This Row],[Cargo Name]],Ledger[Cargo Name],Ledger[SAP Deal Number]) -> ARA26HS00013 | C79: 0 | D79: HDO March26 10-20 | E79: 46002 | F79: Freight-TD22 | G79: Expo | H79: -2000 | I79: 46053 | J79: 46053 | K79: 13750 | L79: =K79 -> 13750 | M79: =L79-K79 -> 0 | N79: =L79-K79 -> 0 | O79: =IF(I79=J79,TEXT(I79,"MMM YY"),TEXT(I79,"MMM")&"/"&TEXT(J79,"MMM")&" "&RIGHT(T79,2)) -> Jan 26 | P79: =IF(H79<0,"Sell","Buy") -> Sell | Q79: =H79*L79 -> -27500000 | R79: =VLOOKUP(F79,Control!$B:$C,2,FALSE) -> Freight | S79: =VLOOKUP(F79,Control!$B:$D,3,FALSE) -> Freight | T79: =YEAR(I79) -> 2026 | U79: =IFERROR(IF(H79>0,"Buy","Sell"),"") -> Sell | V79: Active | W79: =_xlfn.XLOOKUP(Table3[[#This Row],[Instrument]],Control!$B$2:$B$19,Control!$E$2:$E$19) -> #N/A | X79: =Table3[[#This Row],[Month1]] -> 46053 | Y79: =Table3[[#This Row],[Quantity]] -> -2000 | Z79: =_xlfn.XLOOKUP(Table3[[#This Row],[Instrument]],Control!$B$2:$B$19,Control!$F$2:$F$19) -> #N/A | AA79: =Table3[[#This Row],[Month2]] -> 46053 | AB79: =-Y79 -> 2000
A80: Cargoes | B80: =_xlfn.XLOOKUP(Table3[[#This Row],[Cargo Name]],Ledger[Cargo Name],Ledger[SAP Deal Number]) -> ARA26HS00013 | C80: 0 | D80: HDO March26 10-20 | E80: 46002 | F80: Freight-TD22 | G80: Hedge | H80: 2000 | I80: 46053 | J80: 46053 | K80: 13300 | L80: =L79 -> 13750 | M80: =L80-K80 -> 450 | N80: =K79-K80 -> 450 | O80: =IF(I80=J80,TEXT(I80,"MMM YY"),TEXT(I80,"MMM")&"/"&TEXT(J80,"MMM")&" "&RIGHT(T80,2)) -> Jan 26 | P80: =IF(H80<0,"Sell","Buy") -> Buy | Q80: =H80*L80 -> 27500000 | R80: =VLOOKUP(F80,Control!$B:$C,2,FALSE) -> Freight | S80: =VLOOKUP(F80,Control!$B:$D,3,FALSE) -> Freight | T80: =YEAR(I80) -> 2026 | U80: =IFERROR(IF(H80>0,"Buy","Sell"),"") -> Buy | V80: Active | W80: =_xlfn.XLOOKUP(Table3[[#This Row],[Instrument]],Control!$B$2:$B$19,Control!$E$2:$E$19) -> #N/A | X80: =Table3[[#This Row],[Month1]] -> 46053 | Y80: =Table3[[#This Row],[Quantity]] -> 2000 | Z80: =_xlfn.XLOOKUP(Table3[[#This Row],[Instrument]],Control!$B$2:$B$19,Control!$F$2:$F$19) -> #N/A | AA80: =Table3[[#This Row],[Month2]] -> 46053 | AB80: =-Y80 -> -2000
A81: Cargoes | B81: =_xlfn.XLOOKUP(Table3[[#This Row],[Cargo Name]],Ledger[Cargo Name],Ledger[SAP Deal Number]) -> ARA26HS00013 | C81: 0 | D81: HDO March26 10-20 | E81: 46002 | F81: WTI Sprds | G81: Hedge | H81: 1024 | I81: 46081 | J81: 46112 | K81: 0.1 | L81: =IF(OR(S81="WTI Sprds",S81="Brent Sprds",S81="WTI-Brent",S81="DFL"),INDEX(INDIRECT("'" & S81 & "'!$A$6:$XFD$1048576"),MATCH('PnL26'!$P$1,INDIRECT("'" & S81 & "'!$A$6:$A$1048576"),0),MATCH(EOMONTH(I81,0),INDIRECT("'" & S81 & "'!$A$4:$XFD$4"),0)),INDEX(BBG!$A:$BA,MATCH('PnL26'!$P$1,BBG!$A:$A,0),MATCH($I81,BBG!$A$4:$BA$4,0))-INDEX(BBG!$A:$BA,MATCH('PnL26'!$P$1,BBG!$A:$A,0),MATCH($J81,BBG!$A$4:$BA$4,0))) -> 0.1 | M81: =IFERROR((L81-K81)*H81,"") -> 0 | N81: =H81*K81 -> 102.4 | O81: =IF(I81=J81,TEXT(I81,"MMM YY"),TEXT(I81,"MMM")&"/"&TEXT(J81,"MMM")&" "&RIGHT(T81,2)) -> Feb/Mar 26 | P81: =IF(H81<0,"Sell","Buy") -> Buy | Q81: =H81*L81 -> 102.4 | R81: =VLOOKUP(F81,Control!$B:$C,2,FALSE) -> Futures | S81: =VLOOKUP(F81,Control!$B:$D,3,FALSE) -> WTI Sprds | T81: =YEAR(I81) -> 2026 | U81: =IFERROR(IF(H81>0,"Buy","Sell"),"") -> Buy | V81: Active | W81: =_xlfn.XLOOKUP(Table3[[#This Row],[Instrument]],Control!$B$2:$B$19,Control!$E$2:$E$19) -> WTI | X81: =Table3[[#This Row],[Month1]] -> 46081 | Y81: =Table3[[#This Row],[Quantity]] -> 1024 | Z81: =_xlfn.XLOOKUP(Table3[[#This Row],[Instrument]],Control!$B$2:$B$19,Control!$F$2:$F$19) -> WTI | AA81: =Table3[[#This Row],[Month2]] -> 46112 | AB81: =-Y81 -> -1024
A82: Cargoes | B82: =_xlfn.XLOOKUP(Table3[[#This Row],[Cargo Name]],Ledger[Cargo Name],Ledger[SAP Deal Number]) -> ARA26HS00013 | C82: 0 | D82: HDO March26 10-20 | E82: 46002 | F82: WTI-Brent | G82: Hedge | H82: 1024 | I82: 46112 | J82: 46112 | K82: -3.72 | L82: =IF(OR(S82="WTI Sprds",S82="Brent Sprds",S82="WTI-Brent",S82="DFL"),INDEX(INDIRECT("'" & S82 & "'!$A$6:$XFD$1048576"),MATCH('PnL26'!$P$1,INDIRECT("'" & S82 & "'!$A$6:$A$1048576"),0),MATCH(EOMONTH(I82,0),INDIRECT("'" & S82 & "'!$A$4:$XFD$4"),0)),INDEX(BBG!$A:$BA,MATCH('PnL26'!$P$1,BBG!$A:$A,0),MATCH($I82,BBG!$A$4:$BA$4,0))-INDEX(BBG!$A:$BA,MATCH('PnL26'!$P$1,BBG!$A:$A,0),MATCH($J82,BBG!$A$4:$BA$4,0))) -> -5.48 | M82: =IFERROR((L82-K82)*H82,"") -> -1802.24 | N82: =H82*K82 -> -3809.28 | O82: =IF(I82=J82,TEXT(I82,"MMM YY"),TEXT(I82,"MMM")&"/"&TEXT(J82,"MMM")&" "&RIGHT(T82,2)) -> Mar 26 | P82: =IF(H82<0,"Sell","Buy") -> Buy | Q82: =H82*L82 -> -5611.52 | R82: =VLOOKUP(F82,Control!$B:$C,2,FALSE) -> Swaps | S82: =VLOOKUP(F82,Control!$B:$D,3,FALSE) -> WTI-Brent | T82: =YEAR(I82) -> 2026 | U82: =IFERROR(IF(H82>0,"Buy","Sell"),"") -> Buy | V82: Active | W82: =_xlfn.XLOOKUP(Table3[[#This Row],[Instrument]],Control!$B$2:$B$19,Control!$E$2:$E$19) -> WTI | X82: =Table3[[#This Row],[Month1]] -> 46112 | Y82: =Table3[[#This Row],[Quantity]] -> 1024 | Z82: =_xlfn.XLOOKUP(Table3[[#This Row],[Instrument]],Control!$B$2:$B$19,Control!$F$2:$F$19) -> Brent | AA82: =Table3[[#This Row],[Month2]] -> 46112 | AB82: =-Y82 -> -1024
A83: Cargoes | B83: =_xlfn.XLOOKUP(Table3[[#This Row],[Cargo Name]],Ledger[Cargo Name],Ledger[SAP Deal Number]) -> ARA26HS00013 | C83: 0 | D83: HDO March26 10-20 | E83: 46002 | F83: WTI-Brent | G83: Hedge | H83: 500 | I83: 46112 | J83: 46112 | K83: -3.71 | L83: =IF(OR(S83="WTI Sprds",S83="Brent Sprds",S83="WTI-Brent",S83="DFL"),INDEX(INDIRECT("'" & S83 & "'!$A$6:$XFD$1048576"),MATCH('PnL26'!$P$1,INDIRECT("'" & S83 & "'!$A$6:$A$1048576"),0),MATCH(EOMONTH(I83,0),INDIRECT("'" & S83 & "'!$A$4:$XFD$4"),0)),INDEX(BBG!$A:$BA,MATCH('PnL26'!$P$1,BBG!$A:$A,0),MATCH($I83,BBG!$A$4:$BA$4,0))-INDEX(BBG!$A:$BA,MATCH('PnL26'!$P$1,BBG!$A:$A,0),MATCH($J83,BBG!$A$4:$BA$4,0))) -> -5.48 | M83: =IFERROR((L83-K83)*H83,"") -> -885 | N83: =H83*K83 -> -1855 | O83: =IF(I83=J83,TEXT(I83,"MMM YY"),TEXT(I83,"MMM")&"/"&TEXT(J83,"MMM")&" "&RIGHT(T83,2)) -> Mar 26 | P83: =IF(H83<0,"Sell","Buy") -> Buy | Q83: =H83*L83 -> -2740 | R83: =VLOOKUP(F83,Control!$B:$C,2,FALSE) -> Swaps | S83: =VLOOKUP(F83,Control!$B:$D,3,FALSE) -> WTI-Brent | T83: =YEAR(I83) -> 2026 | U83: =IFERROR(IF(H83>0,"Buy","Sell"),"") -> Buy | V83: Active | W83: =_xlfn.XLOOKUP(Table3[[#This Row],[Instrument]],Control!$B$2:$B$19,Control!$E$2:$E$19) -> WTI | X83: =Table3[[#This Row],[Month1]] -> 46112 | Y83: =Table3[[#This Row],[Quantity]] -> 500 | Z83: =_xlfn.XLOOKUP(Table3[[#This Row],[Instrument]],Control!$B$2:$B$19,Control!$F$2:$F$19) -> Brent | AA83: =Table3[[#This Row],[Month2]] -> 46112 | AB83: =-Y83 -> -500
A84: Cargoes | B84: =_xlfn.XLOOKUP(Table3[[#This Row],[Cargo Name]],Ledger[Cargo Name],Ledger[SAP Deal Number]) -> ARA26HS00013 | C84: 0 | D84: HDO March26 10-20 | E84: 46002 | F84: Brent Sprds | G84: Hedge | H84: 2000 | I84: 46112 | J84: 46142 | K84: 0.16 | L84: =IF(OR(S84="WTI Sprds",S84="Brent Sprds",S84="WTI-Brent",S84="DFL"),INDEX(INDIRECT("'" & S84 & "'!$A$6:$XFD$1048576"),MATCH('PnL26'!$P$1,INDIRECT("'" & S84 & "'!$A$6:$A$1048576"),0),MATCH(EOMONTH(I84,0),INDIRECT("'" & S84 & "'!$A$4:$XFD$4"),0)),INDEX(BBG!$A:$BA,MATCH('PnL26'!$P$1,BBG!$A:$A,0),MATCH($I84,BBG!$A$4:$BA$4,0))-INDEX(BBG!$A:$BA,MATCH('PnL26'!$P$1,BBG!$A:$A,0),MATCH($J84,BBG!$A$4:$BA$4,0))) -> 1.37 | M84: =IFERROR((L84-K84)*H84,"") -> 2420 | N84: =H84*K84 -> 320 | O84: =IF(I84=J84,TEXT(I84,"MMM YY"),TEXT(I84,"MMM")&"/"&TEXT(J84,"MMM")&" "&RIGHT(T84,2)) -> Mar/Apr 26 | P84: =IF(H84<0,"Sell","Buy") -> Buy | Q84: =H84*L84 -> 2740 | R84: =VLOOKUP(F84,Control!$B:$C,2,FALSE) -> Futures | S84: =VLOOKUP(F84,Control!$B:$D,3,FALSE) -> Brent Sprds | T84: =YEAR(I84) -> 2026 | U84: =IFERROR(IF(H84>0,"Buy","Sell"),"") -> Buy | V84: Active | W84: =_xlfn.XLOOKUP(Table3[[#This Row],[Instrument]],Control!$B$2:$B$19,Control!$E$2:$E$19) -> Brent | X84: =Table3[[#This Row],[Month1]] -> 46112 | Y84: =Table3[[#This Row],[Quantity]] -> 2000 | Z84: =_xlfn.XLOOKUP(Table3[[#This Row],[Instrument]],Control!$B$2:$B$19,Control!$F$2:$F$19) -> Brent | AA84: =Table3[[#This Row],[Month2]] -> 46142 | AB84: =-Y84 -> -2000
A85: Cargoes | B85: =_xlfn.XLOOKUP(Table3[[#This Row],[Cargo Name]],Ledger[Cargo Name],Ledger[SAP Deal Number]) -> ARA26HS00013 | C85: 0 | D85: HDO March26 10-20 | E85: 46002 | F85: Brent Sprds | G85: Hedge | H85: 1000 | I85: 46081 | J85: 46112 | K85: 0.23 | L85: =IF(OR(S85="WTI Sprds",S85="Brent Sprds",S85="WTI-Brent",S85="DFL"),INDEX(INDIRECT("'" & S85 & "'!$A$6:$XFD$1048576"),MATCH('PnL26'!$P$1,INDIRECT("'" & S85 & "'!$A$6:$A$1048576"),0),MATCH(EOMONTH(I85,0),INDIRECT("'" & S85 & "'!$A$4:$XFD$4"),0)),INDEX(BBG!$A:$BA,MATCH('PnL26'!$P$1,BBG!$A:$A,0),MATCH($I85,BBG!$A$4:$BA$4,0))-INDEX(BBG!$A:$BA,MATCH('PnL26'!$P$1,BBG!$A:$A,0),MATCH($J85,BBG!$A$4:$BA$4,0))) -> 0.59 | M85: =IFERROR((L85-K85)*H85,"") -> 360 | N85: =H85*K85 -> 230 | O85: =IF(I85=J85,TEXT(I85,"MMM YY"),TEXT(I85,"MMM")&"/"&TEXT(J85,"MMM")&" "&RIGHT(T85,2)) -> Feb/Mar 26 | P85: =IF(H85<0,"Sell","Buy") -> Buy | Q85: =H85*L85 -> 590 | R85: =VLOOKUP(F85,Control!$B:$C,2,FALSE) -> Futures | S85: =VLOOKUP(F85,Control!$B:$D,3,FALSE) -> Brent Sprds | T85: =YEAR(I85) -> 2026 | U85: =IFERROR(IF(H85>0,"Buy","Sell"),"") -> Buy | V85: Active | W85: =_xlfn.XLOOKUP(Table3[[#This Row],[Instrument]],Control!$B$2:$B$19,Control!$E$2:$E$19) -> Brent | X85: =Table3[[#This Row],[Month1]] -> 46081 | Y85: =Table3[[#This Row],[Quantity]] -> 1000 | Z85: =_xlfn.XLOOKUP(Table3[[#This Row],[Instrument]],Control!$B$2:$B$19,Control!$F$2:$F$19) -> Brent | AA85: =Table3[[#This Row],[Month2]] -> 46112 | AB85: =-Y85 -> -1000
A86: Cargoes | B86: =_xlfn.XLOOKUP(Table3[[#This Row],[Cargo Name]],Ledger[Cargo Name],Ledger[SAP Deal Number]) -> ARA26HS00013 | C86: 0 | D86: HDO March26 10-20 | E86: 46003 | F86: WTI-Brent | G86: Hedge | H86: 500 | I86: 46112 | J86: 46112 | K86: -3.73 | L86: =IF(OR(S86="WTI Sprds",S86="Brent Sprds",S86="WTI-Brent",S86="DFL"),INDEX(INDIRECT("'" & S86 & "'!$A$6:$XFD$1048576"),MATCH('PnL26'!$P$1,INDIRECT("'" & S86 & "'!$A$6:$A$1048576"),0),MATCH(EOMONTH(I86,0),INDIRECT("'" & S86 & "'!$A$4:$XFD$4"),0)),INDEX(BBG!$A:$BA,MATCH('PnL26'!$P$1,BBG!$A:$A,0),MATCH($I86,BBG!$A$4:$BA$4,0))-INDEX(BBG!$A:$BA,MATCH('PnL26'!$P$1,BBG!$A:$A,0),MATCH($J86,BBG!$A$4:$BA$4,0))) -> -5.48 | M86: =IFERROR((L86-K86)*H86,"") -> -875 | N86: =H86*K86 -> -1865 | O86: =IF(I86=J86,TEXT(I86,"MMM YY"),TEXT(I86,"MMM")&"/"&TEXT(J86,"MMM")&" "&RIGHT(T86,2)) -> Mar 26 | P86: =IF(H86<0,"Sell","Buy") -> Buy | Q86: =H86*L86 -> -2740 | R86: =VLOOKUP(F86,Control!$B:$C,2,FALSE) -> Swaps | S86: =VLOOKUP(F86,Control!$B:$D,3,FALSE) -> WTI-Brent | T86: =YEAR(I86) -> 2026 | U86: =IFERROR(IF(H86>0,"Buy","Sell"),"") -> Buy | V86: Active | W86: =_xlfn.XLOOKUP(Table3[[#This Row],[Instrument]],Control!$B$2:$B$19,Control!$E$2:$E$19) -> WTI | X86: =Table3[[#This Row],[Month1]] -> 46112 | Y86: =Table3[[#This Row],[Quantity]] -> 500 | Z86: =_xlfn.XLOOKUP(Table3[[#This Row],[Instrument]],Control!$B$2:$B$19,Control!$F$2:$F$19) -> Brent | AA86: =Table3[[#This Row],[Month2]] -> 46112 | AB86: =-Y86 -> -500
A87: Cargoes | B87: =_xlfn.XLOOKUP(Table3[[#This Row],[Cargo Name]],Ledger[Cargo Name],Ledger[SAP Deal Number]) -> Unallocated | C87: 0 | D87: Unallocated | E87: 46006 | F87: DFL | G87: Hedge | H87: -375 | I87: 46053 | J87: 46053 | K87: 0.33 | L87: =VLOOKUP($I87,'PnL26'!$E$7:$F$59,2,FALSE) -> 2.09 | M87: =IFERROR((L87-K87)*H87,"") -> -660 | N87: =H87*K87 -> -123.75 | O87: =IF(I87=J87,TEXT(I87,"MMM YY"),TEXT(I87,"MMM")&"/"&TEXT(J87,"MMM")&" "&RIGHT(T87,2)) -> Jan 26 | P87: =IF(H87<0,"Sell","Buy") -> Sell | Q87: =H87*L87 -> -783.75 | R87: =VLOOKUP(F87,Control!$B:$C,2,FALSE) -> Swaps | S87: =VLOOKUP(F87,Control!$B:$D,3,FALSE) -> Dated | T87: =YEAR(I87) -> 2026 | U87: =IFERROR(IF(H87>0,"Buy","Sell"),"") -> Sell | V87: Active | W87: =_xlfn.XLOOKUP(Table3[[#This Row],[Instrument]],Control!$B$2:$B$19,Control!$E$2:$E$19) -> #N/A | X87: =Table3[[#This Row],[Month1]] -> 46053 | Y87: =Table3[[#This Row],[Quantity]] -> -375 | Z87: =_xlfn.XLOOKUP(Table3[[#This Row],[Instrument]],Control!$B$2:$B$19,Control!$F$2:$F$19) -> #N/A | AA87: =Table3[[#This Row],[Month2]] -> 46053 | AB87: =-Y87 -> 375
A88: Cargoes | B88: =_xlfn.XLOOKUP(Table3[[#This Row],[Cargo Name]],Ledger[Cargo Name],Ledger[SAP Deal Number]) -> ARA26HS00013 | C88: 0 | D88: HDO March26 10-20 | E88: 46007 | F88: WTI Sprds | G88: Hedge | H88: 92 | I88: 46081 | J88: 46112 | K88: 0.08 | L88: =IF(OR(S88="WTI Sprds",S88="Brent Sprds",S88="WTI-Brent",S88="DFL"),INDEX(INDIRECT("'" & S88 & "'!$A$6:$XFD$1048576"),MATCH('PnL26'!$P$1,INDIRECT("'" & S88 & "'!$A$6:$A$1048576"),0),MATCH(EOMONTH(I88,0),INDIRECT("'" & S88 & "'!$A$4:$XFD$4"),0)),INDEX(BBG!$A:$BA,MATCH('PnL26'!$P$1,BBG!$A:$A,0),MATCH($I88,BBG!$A$4:$BA$4,0))-INDEX(BBG!$A:$BA,MATCH('PnL26'!$P$1,BBG!$A:$A,0),MATCH($J88,BBG!$A$4:$BA$4,0))) -> 0.1 | M88: =IFERROR((L88-K88)*H88,"") -> 1.84 | N88: =H88*K88 -> 7.36 | O88: =IF(I88=J88,TEXT(I88,"MMM YY"),TEXT(I88,"MMM")&"/"&TEXT(J88,"MMM")&" "&RIGHT(T88,2)) -> Feb/Mar 26 | P88: =IF(H88<0,"Sell","Buy") -> Buy | Q88: =H88*L88 -> 9.2 | R88: =VLOOKUP(F88,Control!$B:$C,2,FALSE) -> Futures | S88: =VLOOKUP(F88,Control!$B:$D,3,FALSE) -> WTI Sprds | T88: =YEAR(I88) -> 2026 | U88: =IFERROR(IF(H88>0,"Buy","Sell"),"") -> Buy | V88: Active | W88: =_xlfn.XLOOKUP(Table3[[#This Row],[Instrument]],Control!$B$2:$B$19,Control!$E$2:$E$19) -> WTI | X88: =Table3[[#This Row],[Month1]] -> 46081 | Y88: =Table3[[#This Row],[Quantity]] -> 92 | Z88: =_xlfn.XLOOKUP(Table3[[#This Row],[Instrument]],Control!$B$2:$B$19,Control!$F$2:$F$19) -> WTI | AA88: =Table3[[#This Row],[Month2]] -> 46112 | AB88: =-Y88 -> -92
A89: Cargoes | B89: =_xlfn.XLOOKUP(Table3[[#This Row],[Cargo Name]],Ledger[Cargo Name],Ledger[SAP Deal Number]) -> ARA26HS00013 | C89: 0 | D89: HDO March26 10-20 | E89: 46008 | F89: WTI Sprds | G89: Hedge | H89: 92 | I89: 46081 | J89: 46112 | K89: 0.08 | L89: =IF(OR(S89="WTI Sprds",S89="Brent Sprds",S89="WTI-Brent",S89="DFL"),INDEX(INDIRECT("'" & S89 & "'!$A$6:$XFD$1048576"),MATCH('PnL26'!$P$1,INDIRECT("'" & S89 & "'!$A$6:$A$1048576"),0),MATCH(EOMONTH(I89,0),INDIRECT("'" & S89 & "'!$A$4:$XFD$4"),0)),INDEX(BBG!$A:$BA,MATCH('PnL26'!$P$1,BBG!$A:$A,0),MATCH($I89,BBG!$A$4:$BA$4,0))-INDEX(BBG!$A:$BA,MATCH('PnL26'!$P$1,BBG!$A:$A,0),MATCH($J89,BBG!$A$4:$BA$4,0))) -> 0.1 | M89: =IFERROR((L89-K89)*H89,"") -> 1.84 | N89: =H89*K89 -> 7.36 | O89: =IF(I89=J89,TEXT(I89,"MMM YY"),TEXT(I89,"MMM")&"/"&TEXT(J89,"MMM")&" "&RIGHT(T89,2)) -> Feb/Mar 26 | P89: =IF(H89<0,"Sell","Buy") -> Buy | Q89: =H89*L89 -> 9.2 | R89: =VLOOKUP(F89,Control!$B:$C,2,FALSE) -> Futures | S89: =VLOOKUP(F89,Control!$B:$D,3,FALSE) -> WTI Sprds | T89: =YEAR(I89) -> 2026 | U89: =IFERROR(IF(H89>0,"Buy","Sell"),"") -> Buy | V89: Active | W89: =_xlfn.XLOOKUP(Table3[[#This Row],[Instrument]],Control!$B$2:$B$19,Control!$E$2:$E$19) -> WTI | X89: =Table3[[#This Row],[Month1]] -> 46081 | Y89: =Table3[[#This Row],[Quantity]] -> 92 | Z89: =_xlfn.XLOOKUP(Table3[[#This Row],[Instrument]],Control!$B$2:$B$19,Control!$F$2:$F$19) -> WTI | AA89: =Table3[[#This Row],[Month2]] -> 46112 | AB89: =-Y89 -> -92
A90: Cargoes | B90: =_xlfn.XLOOKUP(Table3[[#This Row],[Cargo Name]],Ledger[Cargo Name],Ledger[SAP Deal Number]) -> ARA26HS00013 | C90: 0 | D90: HDO March26 10-20 | E90: 46009 | F90: WTI Sprds | G90: Hedge | H90: 92 | I90: 46081 | J90: 46112 | K90: 0.08 | L90: =IF(OR(S90="WTI Sprds",S90="Brent Sprds",S90="WTI-Brent",S90="DFL"),INDEX(INDIRECT("'" & S90 & "'!$A$6:$XFD$1048576"),MATCH('PnL26'!$P$1,INDIRECT("'" & S90 & "'!$A$6:$A$1048576"),0),MATCH(EOMONTH(I90,0),INDIRECT("'" & S90 & "'!$A$4:$XFD$4"),0)),INDEX(BBG!$A:$BA,MATCH('PnL26'!$P$1,BBG!$A:$A,0),MATCH($I90,BBG!$A$4:$BA$4,0))-INDEX(BBG!$A:$BA,MATCH('PnL26'!$P$1,BBG!$A:$A,0),MATCH($J90,BBG!$A$4:$BA$4,0))) -> 0.1 | M90: =IFERROR((L90-K90)*H90,"") -> 1.84 | N90: =H90*K90 -> 7.36 | O90: =IF(I90=J90,TEXT(I90,"MMM YY"),TEXT(I90,"MMM")&"/"&TEXT(J90,"MMM")&" "&RIGHT(T90,2)) -> Feb/Mar 26 | P90: =IF(H90<0,"Sell","Buy") -> Buy | Q90: =H90*L90 -> 9.2 | R90: =VLOOKUP(F90,Control!$B:$C,2,FALSE) -> Futures | S90: =VLOOKUP(F90,Control!$B:$D,3,FALSE) -> WTI Sprds | T90: =YEAR(I90) -> 2026 | U90: =IFERROR(IF(H90>0,"Buy","Sell"),"") -> Buy | V90: Active | W90: =_xlfn.XLOOKUP(Table3[[#This Row],[Instrument]],Control!$B$2:$B$19,Control!$E$2:$E$19) -> WTI | X90: =Table3[[#This Row],[Month1]] -> 46081 | Y90: =Table3[[#This Row],[Quantity]] -> 92 | Z90: =_xlfn.XLOOKUP(Table3[[#This Row],[Instrument]],Control!$B$2:$B$19,Control!$F$2:$F$19) -> WTI | AA90: =Table3[[#This Row],[Month2]] -> 46112 | AB90: =-Y90 -> -92
A91: Cargoes | B91: =_xlfn.XLOOKUP(Table3[[#This Row],[Cargo Name]],Ledger[Cargo Name],Ledger[SAP Deal Number]) -> ARA26HS00013 | C91: 0 | D91: HDO March26 10-20 | E91: 46008 | F91: WTI-Brent | G91: Hedge | H91: 500 | I91: 46203 | J91: 46203 | K91: -3.45 | L91: =IF(OR(S91="WTI Sprds",S91="Brent Sprds",S91="WTI-Brent",S91="DFL"),INDEX(INDIRECT("'" & S91 & "'!$A$6:$XFD$1048576"),MATCH('PnL26'!$P$1,INDIRECT("'" & S91 & "'!$A$6:$A$1048576"),0),MATCH(EOMONTH(I91,0),INDIRECT("'" & S91 & "'!$A$4:$XFD$4"),0)),INDEX(BBG!$A:$BA,MATCH('PnL26'!$P$1,BBG!$A:$A,0),MATCH($I91,BBG!$A$4:$BA$4,0))-INDEX(BBG!$A:$BA,MATCH('PnL26'!$P$1,BBG!$A:$A,0),MATCH($J91,BBG!$A$4:$BA$4,0))) -> -8.94 | M91: =IFERROR((L91-K91)*H91,"") -> -2745 | N91: =H91*K91 -> -1725 | O91: =IF(I91=J91,TEXT(I91,"MMM YY"),TEXT(I91,"MMM")&"/"&TEXT(J91,"MMM")&" "&RIGHT(T91,2)) -> Jun 26 | P91: =IF(H91<0,"Sell","Buy") -> Buy | Q91: =H91*L91 -> -4470 | R91: =VLOOKUP(F91,Control!$B:$C,2,FALSE) -> Swaps | S91: =VLOOKUP(F91,Control!$B:$D,3,FALSE) -> WTI-Brent | T91: =YEAR(I91) -> 2026 | U91: =IFERROR(IF(H91>0,"Buy","Sell"),"") -> Buy | V91: Active | W91: =_xlfn.XLOOKUP(Table3[[#This Row],[Instrument]],Control!$B$2:$B$19,Control!$E$2:$E$19) -> WTI | X91: =Table3[[#This Row],[Month1]] -> 46203 | Y91: =Table3[[#This Row],[Quantity]] -> 500 | Z91: =_xlfn.XLOOKUP(Table3[[#This Row],[Instrument]],Control!$B$2:$B$19,Control!$F$2:$F$19) -> Brent | AA91: =Table3[[#This Row],[Month2]] -> 46203 | AB91: =-Y91 -> -500
A92: Cargoes | B92: =_xlfn.XLOOKUP(Table3[[#This Row],[Cargo Name]],Ledger[Cargo Name],Ledger[SAP Deal Number]) -> Unallocated | C92: 0 | D92: Unallocated | E92: 46009 | F92: WTI-Brent | G92: Hedge | H92: 409 | I92: 46112 | J92: 46112 | K92: -3.7 | L92: =IF(OR(S92="WTI Sprds",S92="Brent Sprds",S92="WTI-Brent",S92="DFL"),INDEX(INDIRECT("'" & S92 & "'!$A$6:$XFD$1048576"),MATCH('PnL26'!$P$1,INDIRECT("'" & S92 & "'!$A$6:$A$1048576"),0),MATCH(EOMONTH(I92,0),INDIRECT("'" & S92 & "'!$A$4:$XFD$4"),0)),INDEX(BBG!$A:$BA,MATCH('PnL26'!$P$1,BBG!$A:$A,0),MATCH($I92,BBG!$A$4:$BA$4,0))-INDEX(BBG!$A:$BA,MATCH('PnL26'!$P$1,BBG!$A:$A,0),MATCH($J92,BBG!$A$4:$BA$4,0))) -> -5.48 | M92: =IFERROR((L92-K92)*H92,"") -> -728.02 | N92: =H92*K92 -> -1513.3 | O92: =IF(I92=J92,TEXT(I92,"MMM YY"),TEXT(I92,"MMM")&"/"&TEXT(J92,"MMM")&" "&RIGHT(T92,2)) -> Mar 26 | P92: =IF(H92<0,"Sell","Buy") -> Buy | Q92: =H92*L92 -> -2241.32 | R92: =VLOOKUP(F92,Control!$B:$C,2,FALSE) -> Swaps | S92: =VLOOKUP(F92,Control!$B:$D,3,FALSE) -> WTI-Brent | T92: =YEAR(I92) -> 2026 | U92: =IFERROR(IF(H92>0,"Buy","Sell"),"") -> Buy | V92: Active | W92: =_xlfn.XLOOKUP(Table3[[#This Row],[Instrument]],Control!$B$2:$B$19,Control!$E$2:$E$19) -> WTI | X92: =Table3[[#This Row],[Month1]] -> 46112 | Y92: =Table3[[#This Row],[Quantity]] -> 409 | Z92: =_xlfn.XLOOKUP(Table3[[#This Row],[Instrument]],Control!$B$2:$B$19,Control!$F$2:$F$19) -> Brent | AA92: =Table3[[#This Row],[Month2]] -> 46112 | AB92: =-Y92 -> -409
A93: Cargoes | B93: =_xlfn.XLOOKUP(Table3[[#This Row],[Cargo Name]],Ledger[Cargo Name],Ledger[SAP Deal Number]) -> Unallocated | C93: 0 | D93: Unallocated | E93: 46009 | F93: WTI Sprds | G93: Hedge | H93: 1000 | I93: 46081 | J93: 46112 | K93: 0.14 | L93: =IF(OR(S93="WTI Sprds",S93="Brent Sprds",S93="WTI-Brent",S93="DFL"),INDEX(INDIRECT("'" & S93 & "'!$A$6:$XFD$1048576"),MATCH('PnL26'!$P$1,INDIRECT("'" & S93 & "'!$A$6:$A$1048576"),0),MATCH(EOMONTH(I93,0),INDIRECT("'" & S93 & "'!$A$4:$XFD$4"),0)),INDEX(BBG!$A:$BA,MATCH('PnL26'!$P$1,BBG!$A:$A,0),MATCH($I93,BBG!$A$4:$BA$4,0))-INDEX(BBG!$A:$BA,MATCH('PnL26'!$P$1,BBG!$A:$A,0),MATCH($J93,BBG!$A$4:$BA$4,0))) -> 0.1 | M93: =IFERROR((L93-K93)*H93,"") -> -40 | N93: =H93*K93 -> 140 | O93: =IF(I93=J93,TEXT(I93,"MMM YY"),TEXT(I93,"MMM")&"/"&TEXT(J93,"MMM")&" "&RIGHT(T93,2)) -> Feb/Mar 26 | P93: =IF(H93<0,"Sell","Buy") -> Buy | Q93: =H93*L93 -> 100 | R93: =VLOOKUP(F93,Control!$B:$C,2,FALSE) -> Futures | S93: =VLOOKUP(F93,Control!$B:$D,3,FALSE) -> WTI Sprds | T93: =YEAR(I93) -> 2026 | U93: =IFERROR(IF(H93>0,"Buy","Sell"),"") -> Buy | V93: Active | W93: =_xlfn.XLOOKUP(Table3[[#This Row],[Instrument]],Control!$B$2:$B$19,Control!$E$2:$E$19) -> WTI | X93: =Table3[[#This Row],[Month1]] -> 46081 | Y93: =Table3[[#This Row],[Quantity]] -> 1000 | Z93: =_xlfn.XLOOKUP(Table3[[#This Row],[Instrument]],Control!$B$2:$B$19,Control!$F$2:$F$19) -> WTI | AA93: =Table3[[#This Row],[Month2]] -> 46112 | AB93: =-Y93 -> -1000
A94: Cargoes | B94: =_xlfn.XLOOKUP(Table3[[#This Row],[Cargo Name]],Ledger[Cargo Name],Ledger[SAP Deal Number]) -> Unallocated | C94: 0 | D94: Unallocated | E94: 46009 | F94: WTI Sprds | G94: Hedge | H94: 1000 | I94: 46112 | J94: 46142 | K94: 0.07 | L94: =IF(OR(S94="WTI Sprds",S94="Brent Sprds",S94="WTI-Brent",S94="DFL"),INDEX(INDIRECT("'" & S94 & "'!$A$6:$XFD$1048576"),MATCH('PnL26'!$P$1,INDIRECT("'" & S94 & "'!$A$6:$A$1048576"),0),MATCH(EOMONTH(I94,0),INDIRECT("'" & S94 & "'!$A$4:$XFD$4"),0)),INDEX(BBG!$A:$BA,MATCH('PnL26'!$P$1,BBG!$A:$A,0),MATCH($I94,BBG!$A$4:$BA$4,0))-INDEX(BBG!$A:$BA,MATCH('PnL26'!$P$1,BBG!$A:$A,0),MATCH($J94,BBG!$A$4:$BA$4,0))) -> 0.03 | M94: =IFERROR((L94-K94)*H94,"") -> -40 | N94: =H94*K94 -> 70 | O94: =IF(I94=J94,TEXT(I94,"MMM YY"),TEXT(I94,"MMM")&"/"&TEXT(J94,"MMM")&" "&RIGHT(T94,2)) -> Mar/Apr 26 | P94: =IF(H94<0,"Sell","Buy") -> Buy | Q94: =H94*L94 -> 30 | R94: =VLOOKUP(F94,Control!$B:$C,2,FALSE) -> Futures | S94: =VLOOKUP(F94,Control!$B:$D,3,FALSE) -> WTI Sprds | T94: =YEAR(I94) -> 2026 | U94: =IFERROR(IF(H94>0,"Buy","Sell"),"") -> Buy | V94: Active | W94: =_xlfn.XLOOKUP(Table3[[#This Row],[Instrument]],Control!$B$2:$B$19,Control!$E$2:$E$19) -> WTI | X94: =Table3[[#This Row],[Month1]] -> 46112 | Y94: =Table3[[#This Row],[Quantity]] -> 1000 | Z94: =_xlfn.XLOOKUP(Table3[[#This Row],[Instrument]],Control!$B$2:$B$19,Control!$F$2:$F$19) -> WTI | AA94: =Table3[[#This Row],[Month2]] -> 46142 | AB94: =-Y94 -> -1000
A95: Cargoes | B95: =_xlfn.XLOOKUP(Table3[[#This Row],[Cargo Name]],Ledger[Cargo Name],Ledger[SAP Deal Number]) -> Unallocated | C95: 0 | D95: Unallocated | E95: 46009 | F95: WTI Sprds | G95: Hedge | H95: 1000 | I95: 46142 | J95: 46173 | K95: 0 | L95: =IF(OR(S95="WTI Sprds",S95="Brent Sprds",S95="WTI-Brent",S95="DFL"),INDEX(INDIRECT("'" & S95 & "'!$A$6:$XFD$1048576"),MATCH('PnL26'!$P$1,INDIRECT("'" & S95 & "'!$A$6:$A$1048576"),0),MATCH(EOMONTH(I95,0),INDIRECT("'" & S95 & "'!$A$4:$XFD$4"),0)),INDEX(BBG!$A:$BA,MATCH('PnL26'!$P$1,BBG!$A:$A,0),MATCH($I95,BBG!$A$4:$BA$4,0))-INDEX(BBG!$A:$BA,MATCH('PnL26'!$P$1,BBG!$A:$A,0),MATCH($J95,BBG!$A$4:$BA$4,0))) -> 0.59 | M95: =IFERROR((L95-K95)*H95,"") -> 590 | N95: =H95*K95 -> 0 | O95: =IF(I95=J95,TEXT(I95,"MMM YY"),TEXT(I95,"MMM")&"/"&TEXT(J95,"MMM")&" "&RIGHT(T95,2)) -> Apr/May 26 | P95: =IF(H95<0,"Sell","Buy") -> Buy | Q95: =H95*L95 -> 590 | R95: =VLOOKUP(F95,Control!$B:$C,2,FALSE) -> Futures | S95: =VLOOKUP(F95,Control!$B:$D,3,FALSE) -> WTI Sprds | T95: =YEAR(I95) -> 2026 | U95: =IFERROR(IF(H95>0,"Buy","Sell"),"") -> Buy | V95: Active | W95: =_xlfn.XLOOKUP(Table3[[#This Row],[Instrument]],Control!$B$2:$B$19,Control!$E$2:$E$19) -> WTI | X95: =Table3[[#This Row],[Month1]] -> 46142 | Y95: =Table3[[#This Row],[Quantity]] -> 1000 | Z95: =_xlfn.XLOOKUP(Table3[[#This Row],[Instrument]],Control!$B$2:$B$19,Control!$F$2:$F$19) -> WTI | AA95: =Table3[[#This Row],[Month2]] -> 46173 | AB95: =-Y95 -> -1000
A96: Cargoes | B96: =_xlfn.XLOOKUP(Table3[[#This Row],[Cargo Name]],Ledger[Cargo Name],Ledger[SAP Deal Number]) -> GLE26HS00001 | C96: 0 | D96: Glencore FOB VLCC Jan26-30 | E96: 46014 | F96: Physical | G96: Expo | H96: 1400 | I96: 46053 | J96: 46053 | K96: ='Cargo Econs 2025'!D457 -> -2.45 | L96: ='Cargo Econs 2025'!D458 -> -2.02 | M96: =IFERROR((L96-K96)*H96,"") -> 602 | N96: =H96*K96 -> -3430 | O96: =IF(I96=J96,TEXT(I96,"MMM YY"),TEXT(I96,"MMM")&"/"&TEXT(J96,"MMM")&" "&RIGHT(T96,2)) -> Jan 26 | P96: =IF(H96<0,"Sell","Buy") -> Buy | Q96: =H96*L96 -> -2828 | R96: =VLOOKUP(F96,Control!$B:$C,2,FALSE) -> Physical | S96: =VLOOKUP(F96,Control!$B:$D,3,FALSE) -> Physical | T96: =YEAR(I96) -> 2026 | U96: =IFERROR(IF(H96>0,"Buy","Sell"),"") -> Buy | V96: Active | W96: =_xlfn.XLOOKUP(Table3[[#This Row],[Instrument]],Control!$B$2:$B$19,Control!$E$2:$E$19) -> 0 | X96: =Table3[[#This Row],[Month1]] -> 46053 | Y96: =Table3[[#This Row],[Quantity]] -> 1400 | Z96: =_xlfn.XLOOKUP(Table3[[#This Row],[Instrument]],Control!$B$2:$B$19,Control!$F$2:$F$19) -> 0 | AA96: =Table3[[#This Row],[Month2]] -> 46053 | AB96: =-Y96 -> -1400
A97: Cargoes | B97: =_xlfn.XLOOKUP(Table3[[#This Row],[Cargo Name]],Ledger[Cargo Name],Ledger[SAP Deal Number]) -> GLE26HS00001 | C97: 0 | D97: Glencore FOB VLCC Jan26-30 | E97: 46014 | F97: WTI Sprds | G97: Expo | H97: -1400 | I97: 46081 | J97: 46112 | K97: 0.22 | L97: =IF(OR(S97="WTI Sprds",S97="Brent Sprds",S97="WTI-Brent",S97="DFL"),INDEX(INDIRECT("'" & S97 & "'!$A$6:$XFD$1048576"),MATCH('PnL26'!$P$1,INDIRECT("'" & S97 & "'!$A$6:$A$1048576"),0),MATCH(EOMONTH(I97,0),INDIRECT("'" & S97 & "'!$A$4:$XFD$4"),0)),INDEX(BBG!$A:$BA,MATCH('PnL26'!$P$1,BBG!$A:$A,0),MATCH($I97,BBG!$A$4:$BA$4,0))-INDEX(BBG!$A:$BA,MATCH('PnL26'!$P$1,BBG!$A:$A,0),MATCH($J97,BBG!$A$4:$BA$4,0))) -> 0.1 | M97: =IFERROR((L97-K97)*H97,"") -> 168 | N97: =H97*K97 -> -308 | O97: =IF(I97=J97,TEXT(I97,"MMM YY"),TEXT(I97,"MMM")&"/"&TEXT(J97,"MMM")&" "&RIGHT(T97,2)) -> Feb/Mar 26 | P97: =IF(H97<0,"Sell","Buy") -> Sell | Q97: =H97*L97 -> -140 | R97: =VLOOKUP(F97,Control!$B:$C,2,FALSE) -> Futures | S97: =VLOOKUP(F97,Control!$B:$D,3,FALSE) -> WTI Sprds | T97: =YEAR(I97) -> 2026 | U97: =IFERROR(IF(H97>0,"Buy","Sell"),"") -> Sell | V97: Active | W97: =_xlfn.XLOOKUP(Table3[[#This Row],[Instrument]],Control!$B$2:$B$19,Control!$E$2:$E$19) -> WTI | X97: =Table3[[#This Row],[Month1]] -> 46081 | Y97: =Table3[[#This Row],[Quantity]] -> -1400 | Z97: =_xlfn.XLOOKUP(Table3[[#This Row],[Instrument]],Control!$B$2:$B$19,Control!$F$2:$F$19) -> WTI | AA97: =Table3[[#This Row],[Month2]] -> 46112 | AB97: =-Y97 -> 1400
