Workbook

Sheet Sheet1
Z1: 2.3
J2: 12/10/2025 | S2: Brent | W2: WTI | X2: BRENT | AB2: CMA to MEH Premium
B3: Link Data Services End of Day | P3: =EOMONTH(BBG!D5,0) -> 46356 | Q3: =BBG!E5 -> 93.14 | R3: =BBG!F5 -> 90.42 | S3: =EOMONTH(BBG!H5,0) -> 46387 | T3: =BBG!K5 -> 102.49 | U3: =BBG!L5 -> 98.03 | V3: =EOMONTH(TODAY(),0) -> 46326 | W3: =BBG!E63 -> 92.39 | X3: =BBG!K63 -> 102.31 | Y3: =W3-X3 -> -9.92
B4: US DOMESTIC PIPELINE ASSESSMENTS | P4: =EOMONTH(P3,1) -> 46387 | Q4: =BBG!E6 -> 91.08 | R4: =BBG!F6 -> 88.42 | S4: =EOMONTH(S3,1) -> 46418 | T4: =BBG!K6 -> 98.62 | U4: =BBG!L6 -> 95.09 | V4: =EOMONTH(V3,1) -> 46356 | W4: =BBG!E64 -> 90.56 | X4: =BBG!K64 -> 98.46 | Y4: =W4-X4 -> -7.9 | Z4: =Y4+Z1 -> -5.6 | AB4: =VLOOKUP(USG!E25,$P$3:$Q$41,2,FALSE)-VLOOKUP(USG!E25,$V$3:$W$41,2,FALSE) -> 2.58
B5: GRADE | C5: 46296 | D5: 46327 | E5: 46357 | F5: 46388 | G5: 46419 | H5: 46447 | I5: 46478 | J5: 46508 | K5: 46539 | L5: 46569 | M5: 46600 | N5: 46631 | P5: =EOMONTH(P4,1) -> 46418 | Q5: =BBG!E7 -> 88.99 | R5: =BBG!F7 -> 86.73 | S5: =EOMONTH(S4,1) -> 46446 | T5: =BBG!K7 -> 95.54 | U5: =BBG!L7 -> 92.85 | V5: =EOMONTH(V4,1) -> 46387 | W5: =BBG!E65 -> 88.3 | X5: =BBG!K65 -> 95.32 | Y5: =W5-X5 -> -7.02 | Z5: =T5-W5 -> 7.24 | AB5: =VLOOKUP(USG!E28,$P$3:$Q$41,2,FALSE)-VLOOKUP(USG!E28,$V$3:$W$41,2,FALSE) -> #N/A
B6: CMA | C6: 8.25 | D6: 4.308 | E6: 3.383 | F6: 2.453 | G6: 1.768 | H6: 1.642 | I6: 1.565 | J6: 1.36 | K6: 1.254 | L6: 1.254 | M6: 1.095 | N6: 0.993 | P6: =EOMONTH(P5,1) -> 46446 | Q6: =BBG!E8 -> 86.89 | R6: =BBG!F8 -> 85.11 | S6: =EOMONTH(S5,1) -> 46477 | T6: =BBG!K8 -> 93.22 | U6: =BBG!L8 -> 91.15 | V6: =EOMONTH(V5,1) -> 46418 | W6: =BBG!E66 -> 86.13 | X6: =BBG!K66 -> 93.12 | Y6: =W6-X6 -> -6.99 | Z6: mat | AB6: =VLOOKUP(USG!E29,$P$3:$Q$41,2,FALSE)-VLOOKUP(USG!E29,$V$3:$W$41,2,FALSE) -> #N/A
B7: MEH | C7: 0.75 | D7: 1.35 | E7: 1 | F7: 1.2 | G7: 1.4 | H7: 1.55 | I7: 1.75 | J7: 1.8 | K7: 1.85 | L7: 1.85 | M7: 1.85 | N7: 1.85 | P7: =EOMONTH(P6,1) -> 46477 | Q7: =BBG!E9 -> 84.93 | R7: =BBG!F9 -> 83.71 | S7: =EOMONTH(S6,1) -> 46507 | T7: =BBG!K9 -> 91.31 | U7: =BBG!L9 -> 89.67 | V7: =EOMONTH(V6,1) -> 46446 | W7: =BBG!E67 -> 84.57 | X7: =BBG!K67 -> 91.21 | Y7: =W7-X7 -> -6.64 | AB7: =VLOOKUP(USG!E30,$P$3:$Q$41,2,FALSE)-VLOOKUP(USG!E30,$V$3:$W$41,2,FALSE) -> #N/A
B8: MIDSWT | C8: -2.5 | D8: 0.7 | E8: 0.35 | F8: 0.65 | G8: 0.85 | H8: 1 | I8: 1.15 | J8: 1.2 | K8: 1.25 | L8: 1.25 | M8: 1.25 | N8: 1.25 | P8: =EOMONTH(P7,1) -> 46507 | Q8: =BBG!E10 -> 83.27 | R8: =BBG!F10 -> 82.45 | S8: =EOMONTH(S7,1) -> 46538 | T8: =BBG!K10 -> 89.62 | U8: =BBG!L10 -> 88.34 | V8: =EOMONTH(V7,1) -> 46477 | W8: =BBG!E68 -> 82.89 | X8: =BBG!K68 -> 89.53 | Y8: =W8-X8 -> -6.64 | AB8: =VLOOKUP(USG!E32,$P$3:$Q$41,2,FALSE)-VLOOKUP(USG!E32,$V$3:$W$41,2,FALSE) -> #N/A
B9: WTL | C9: -3.15 | D9: 0.15 | E9: -0.2 | F9: 0.1 | G9: 0.3 | H9: 0.45 | I9: 0.6 | J9: 0.65 | K9: 0.7 | L9: 0.7 | M9: 0.7 | N9: 0.7 | P9: =EOMONTH(P8,1) -> 46538 | Q9: =BBG!E11 -> 81.91 | R9: =BBG!F11 -> 81.32 | S9: =EOMONTH(S8,1) -> 46568 | T9: =BBG!K11 -> 88.09 | U9: =BBG!L11 -> 87.09 | V9: =EOMONTH(V8,1) -> 46507 | W9: =BBG!E69 -> 81.43 | X9: =BBG!K69 -> 88.01 | Y9: =W9-X9 -> -6.58 | AB9: =VLOOKUP(USG!E33,$P$3:$Q$41,2,FALSE)-VLOOKUP(USG!E33,$V$3:$W$41,2,FALSE) -> #N/A
B10: WTS | C10: -5.5 | D10: -6 | E10: -6 | F10: -6.1 | G10: -6.1 | H10: -6.1 | I10: -6.1 | J10: -6.1 | K10: -6.1 | L10: -6.1 | M10: -6.1 | N10: -6.1 | P10: =EOMONTH(P9,1) -> 46568 | Q10: =BBG!E12 -> 80.65 | R10: =BBG!F12 -> 80.28 | S10: =EOMONTH(S9,1) -> 46599 | T10: =BBG!K12 -> 86.69 | U10: =BBG!L12 -> 85.91 | V10: =EOMONTH(V9,1) -> 46538 | W10: =BBG!E70 -> 80.32 | X10: =BBG!K70 -> 86.57 | Y10: =W10-X10 -> -6.25 | AB10: =VLOOKUP(USG!E34,$P$3:$Q$41,2,FALSE)-VLOOKUP(USG!E34,$V$3:$W$41,2,FALSE) -> #N/A
B11: WTI EX BASIN | C11: 0.9 | D11: 1.05 | E11: 0.7 | F11: 1 | G11: 1.2 | H11: 1.35 | I11: 1.5 | J11: 1.55 | K11: 1.6 | L11: 1.6 | M11: 1.6 | N11: 1.6 | P11: =EOMONTH(P10,1) -> 46599 | Q11: =BBG!E13 -> 79.51 | R11: =BBG!F13 -> 79.31 | S11: =EOMONTH(S10,1) -> 46630 | T11: =BBG!K13 -> 85.46 | U11: =BBG!L13 -> 84.81 | V11: =EOMONTH(V10,1) -> 46568 | W11: =BBG!E71 -> 79.26 | X11: =BBG!K71 -> 85.38 | Y11: =W11-X11 -> -6.12 | AB11: =VLOOKUP(USG!E35,$P$3:$Q$41,2,FALSE)-VLOOKUP(USG!E35,$V$3:$W$41,2,FALSE) -> #N/A
B12: LLS | C12: 3.25 | D12: 2.15 | E12: 2.05 | F12: 1.7 | G12: 1.85 | H12: 2 | I12: 2.2 | J12: 2.25 | K12: 2.3 | L12: 2.3 | M12: 2.3 | N12: 2.3 | P12: =EOMONTH(P11,1) -> 46630 | Q12: =BBG!E14 -> 78.62 | R12: =BBG!F14 -> 78.4 | S12: =EOMONTH(S11,1) -> 46660 | T12: =BBG!K14 -> 84.33 | U12: =BBG!L14 -> 83.79 | V12: =EOMONTH(V11,1) -> 46599 | W12: =BBG!E72 -> 78.19 | X12: =BBG!K72 -> 84.25 | Y12: =W12-X12 -> -6.06 | AB12: =VLOOKUP(USG!E36,$P$3:$Q$41,2,FALSE)-VLOOKUP(USG!E36,$V$3:$W$41,2,FALSE) -> #N/A
B13: HLS | C13: 0 | D13: 4 | E13: 4 | F13: 3.75 | G13: 3.75 | H13: 3.75 | I13: 4 | J13: 4 | K13: 4 | L13: 4 | M13: 4 | N13: 4 | P13: =EOMONTH(P12,1) -> 46660 | Q13: =BBG!E15 -> 77.59 | R13: =BBG!F15 -> 77.55 | S13: =EOMONTH(S12,1) -> 46691 | T13: =BBG!K15 -> 83.23 | U13: =BBG!L15 -> 82.86 | V13: =EOMONTH(V12,1) -> 46630 | W13: =BBG!E73 -> 77.36 | X13: =BBG!K73 -> 83.24 | Y13: =W13-X13 -> -5.88 | AB13: =VLOOKUP(USG!E37,$P$3:$Q$41,2,FALSE)-VLOOKUP(USG!E37,$V$3:$W$41,2,FALSE) -> #N/A
B14: MARS | C14: -5 | D14: -1 | E14: -1 | F14: -1.25 | G14: -1.25 | H14: -1.25 | I14: -1 | J14: -1 | K14: -1 | L14: -1 | M14: -1 | N14: -1 | P14: =EOMONTH(P13,1) -> 46691 | Q14: =BBG!E16 -> 76.84 | R14: =BBG!F16 -> 76.78 | S14: =EOMONTH(S13,1) -> 46721 | T14: =BBG!K16 -> 82.43 | U14: =BBG!L16 -> 82.03 | V14: =EOMONTH(V13,1) -> 46660 | W14: =BBG!E74 -> 76.55 | X14: =BBG!K74 -> 82.36 | Y14: =W14-X14 -> -5.81 | AB14: =VLOOKUP(USG!E38,$P$3:$Q$41,2,FALSE)-VLOOKUP(USG!E38,$V$3:$W$41,2,FALSE) -> #N/A
B15: LOOP SOUR | C15: -5.65 | D15: -1.65 | E15: -1.65 | F15: -1.9 | G15: -1.9 | H15: -1.9 | I15: -1.65 | J15: -1.65 | K15: -1.65 | L15: -1.65 | M15: -1.65 | N15: -1.65 | P15: =EOMONTH(P14,1) -> 46721 | Q15: =BBG!E17 -> 76.12 | R15: =BBG!F17 -> 76.1 | S15: =EOMONTH(S14,1) -> 46752 | T15: =BBG!K17 -> 81.58 | U15: =BBG!L17 -> 81.25 | V15: =EOMONTH(V14,1) -> 46691 | W15: =BBG!E75 -> 75.82 | X15: =BBG!K75 -> 81.52 | Y15: =W15-X15 -> -5.7 | AB15: =VLOOKUP(USG!E39,$P$3:$Q$41,2,FALSE)-VLOOKUP(USG!E39,$V$3:$W$41,2,FALSE) -> #N/A
B16: POSEIDON | C16: -5.35 | D16: -1.35 | E16: -1.35 | F16: -1.6 | G16: -1.6 | H16: -1.6 | I16: -1.35 | J16: -1.35 | K16: -1.35 | L16: -1.35 | M16: -1.35 | N16: -1.35 | P16: =EOMONTH(P15,1) -> 46752 | Q16: =BBG!E18 -> 75.36 | R16: =BBG!F18 -> 75.44 | S16: =EOMONTH(S15,1) -> 46783 | T16: =BBG!K18 -> 80.81 | U16: =BBG!L18 -> 80.51 | V16: =EOMONTH(V15,1) -> 46721 | W16: =BBG!E76 -> 75.17 | X16: =BBG!K76 -> 80.72 | Y16: =W16-X16 -> -5.55 | AB16: =VLOOKUP(USG!E40,$P$3:$Q$41,2,FALSE)-VLOOKUP(USG!E40,$V$3:$W$41,2,FALSE) -> #N/A
B17: T-HORSE | C17: -4 | D17: 0 | E17: 0 | F17: -0.25 | G17: -0.25 | H17: -0.25 | I17: 0 | J17: 0 | K17: 0 | L17: 0 | M17: 0 | N17: 0 | P17: =EOMONTH(P16,1) -> 46783 | Q17: =BBG!E19 -> 74.79 | R17: =BBG!F19 -> 74.84 | S17: =EOMONTH(S16,1) -> 46812 | T17: =BBG!K19 -> 80.07 | U17: =BBG!L19 -> 79.82 | V17: =EOMONTH(V16,1) -> 46752 | W17: =BBG!E77 -> 74.47 | X17: =BBG!K77 -> 79.95 | Y17: =W17-X17 -> -5.48 | AB17: =VLOOKUP(USG!G41,$P$3:$Q$41,2,FALSE)-VLOOKUP(USG!G41,$V$3:$W$41,2,FALSE) -> #N/A
B18: SGC | C18: -6 | D18: -3 | E18: -3 | F18: -2.25 | G18: -2.25 | H18: -2.25 | I18: -1.5 | J18: -1.5 | K18: -1.5 | L18: -1.25 | M18: -1.25 | N18: -1.25 | P18: =EOMONTH(P17,1) -> 46812 | Q18: =BBG!E20 -> 74.19 | R18: =BBG!F20 -> 74.27 | S18: =EOMONTH(S17,1) -> 46843 | T18: =BBG!K20 -> 79.41 | U18: =BBG!L20 -> 79.22 | V18: =EOMONTH(V17,1) -> 46783 | W18: =BBG!E78 -> 73.89 | X18: =BBG!K78 -> 79.33 | Y18: =W18-X18 -> -5.44 | AB18: =VLOOKUP(USG!G42,$P$3:$Q$41,2,FALSE)-VLOOKUP(USG!G42,$V$3:$W$41,2,FALSE) -> #N/A
B19: ROCKIES AND MIDCONTINENT PIPELINE ASSESSMENTS | P19: =EOMONTH(P18,1) -> 46843 | Q19: =BBG!E21 -> 73.65 | R19: =BBG!F21 -> 73.76 | S19: =EOMONTH(S18,1) -> 46873 | T19: =BBG!K21 -> 78.82 | U19: =BBG!L21 -> 78.69 | V19: =EOMONTH(V18,1) -> 46812 | W19: =BBG!E79 -> 73.41 | X19: =BBG!K79 -> 78.73 | Y19: =W19-X19 -> -5.32 | AB19: =VLOOKUP(USG!G43,$P$3:$Q$41,2,FALSE)-VLOOKUP(USG!G43,$V$3:$W$41,2,FALSE) -> #N/A
B20: GRADE | C20: 46296 | D20: 46327 | E20: 46357 | F20: 46388 | G20: 46419 | H20: 46447 | I20: 46478 | J20: 46508 | K20: 46539 | L20: 46569 | M20: 46600 | N20: 46631 | P20: =EOMONTH(P19,1) -> 46873 | Q20: =BBG!E22 -> 73.15 | R20: =BBG!F22 -> 73.29 | S20: =EOMONTH(S19,1) -> 46904 | T20: =BBG!K22 -> 78.29 | U20: =BBG!L22 -> 78.22 | V20: =EOMONTH(V19,1) -> 46843 | W20: =BBG!E80 -> 72.87 | X20: =BBG!K80 -> 78.2 | Y20: =W20-X20 -> -5.33 | AB20: =VLOOKUP(USG!G44,$P$3:$Q$41,2,FALSE)-VLOOKUP(USG!G44,$V$3:$W$41,2,FALSE) -> #N/A
B21: BLS CUSHING | C21: 1 | D21: 1 | E21: 1 | F21: 1 | G21: 1 | H21: 1 | I21: 1 | J21: 1 | K21: 1 | L21: 1 | M21: 1 | N21: 1 | P21: =EOMONTH(P20,1) -> 46904 | Q21: =BBG!E23 -> 72.69 | R21: =BBG!F23 -> 72.87 | S21: =EOMONTH(S20,1) -> 46934 | T21: =BBG!K23 -> 77.75 | U21: =BBG!L23 -> 77.78 | V21: =EOMONTH(V20,1) -> 46873 | W21: =BBG!E81 -> 72.42 | X21: =BBG!K81 -> 77.72 | Y21: =W21-X21 -> -5.3 | AB21: =VLOOKUP(USG!#REF!,$P$3:$Q$41,2,FALSE)-VLOOKUP(USG!#REF!,$V$3:$W$41,2,FALSE) -> #REF!
B22: NIO CUSHING | C22: 1.15 | D22: 1.15 | E22: 1.15 | F22: 1.15 | G22: 1.15 | H22: 1.15 | I22: 1.15 | J22: 1.15 | K22: 1.15 | L22: 1.15 | M22: 1.15 | N22: 1.15 | P22: =EOMONTH(P21,1) -> 46934 | Q22: =BBG!E24 -> 72.15 | R22: =BBG!F24 -> 72.46 | S22: =EOMONTH(S21,1) -> 46965 | T22: =BBG!K24 -> 77.31 | U22: =BBG!L24 -> 77.34 | V22: =EOMONTH(V21,1) -> 46904 | W22: =BBG!E82 -> 71.99 | X22: =BBG!K82 -> 77.24 | Y22: =W22-X22 -> -5.25 | AB22: =VLOOKUP(#REF!,$P$3:$Q$41,2,FALSE)-VLOOKUP(#REF!,$V$3:$W$41,2,FALSE) -> #REF!
B23: SHL LIGHT | C23: 0.3 | D23: 0.3 | E23: 0.3 | F23: 0.3 | G23: 0.3 | H23: 0.3 | I23: 0.3 | J23: 0.3 | K23: 0.3 | L23: 0.3 | M23: 0.3 | N23: 0.3 | P23: =EOMONTH(P22,1) -> 46965 | Q23: =BBG!E25 -> 71.79 | R23: =BBG!F25 -> 72.03 | S23: =EOMONTH(S22,1) -> 46996 | T23: =BBG!K25 -> 76.83 | U23: =BBG!L25 -> 76.89 | V23: =EOMONTH(V22,1) -> 46934 | W23: =BBG!E83 -> 71.49 | X23: =BBG!K83 -> 76.76 | Y23: =W23-X23 -> -5.27 | AB23: =VLOOKUP(#REF!,$P$3:$Q$41,2,FALSE)-VLOOKUP(#REF!,$V$3:$W$41,2,FALSE) -> #REF!
B24: SHL CRUDE | C24: 1.35 | D24: 1.35 | E24: 1.35 | F24: 1.35 | G24: 1.35 | H24: 1.35 | I24: 1.35 | J24: 1.35 | K24: 1.35 | L24: 1.35 | M24: 1.35 | N24: 1.35 | P24: =EOMONTH(P23,1) -> 46996 | Q24: =BBG!E26 -> 71.33 | R24: =BBG!F26 -> 71.62 | S24: =EOMONTH(S23,1) -> 47026 | T24: =BBG!K26 -> 76.36 | U24: =BBG!L26 -> 76.46 | V24: =EOMONTH(V23,1) -> 46965 | W24: =BBG!E84 -> 71.06 | X24: =BBG!K84 -> 76.29 | Y24: =W24-X24 -> -5.23 | AB24: =VLOOKUP(USG!#REF!,$P$3:$Q$41,2,FALSE)-VLOOKUP(USG!#REF!,$V$3:$W$41,2,FALSE) -> #REF!
B25: WHITECLIFFS | C25: 0.3 | D25: 0.3 | E25: 0.3 | F25: 0.3 | G25: 0.3 | H25: 0.3 | I25: 0.3 | J25: 0.3 | K25: 0.3 | L25: 0.3 | M25: 0.3 | N25: 0.3 | P25: =EOMONTH(P24,1) -> 47026 | Q25: =BBG!E27 -> 70.92 | R25: =BBG!F27 -> 71.24 | S25: =EOMONTH(S24,1) -> 47057 | T25: =BBG!K27 -> 75.89 | U25: =BBG!L27 -> 76.03 | V25: =EOMONTH(V24,1) -> 46996 | W25: =BBG!E85 -> 70.67 | X25: =BBG!K85 -> 75.82 | Y25: =W25-X25 -> -5.15 | AB25: =VLOOKUP(USG!E24,$P$3:$Q$41,2,FALSE)-VLOOKUP(USG!E24,$V$3:$W$41,2,FALSE) -> #N/A
B26: GRAND MESA LT | C26: 0.3 | D26: 0.3 | E26: 0.3 | F26: 0.3 | G26: 0.3 | H26: 0.3 | I26: 0.3 | J26: 0.3 | K26: 0.3 | L26: 0.3 | M26: 0.3 | N26: 0.3 | P26: =EOMONTH(P25,1) -> 47057 | Q26: =BBG!E28 -> 70.53 | R26: =BBG!F28 -> 70.86 | S26: =EOMONTH(S25,1) -> 47087 | T26: =BBG!K28 -> 75.45 | U26: =BBG!L28 -> 75.63 | V26: =EOMONTH(V25,1) -> 47026 | W26: =BBG!E86 -> 70.27 | X26: =BBG!K86 -> 75.38 | Y26: =W26-X26 -> -5.11 | AB26: =VLOOKUP(#REF!,$P$3:$Q$41,2,FALSE)-VLOOKUP(#REF!,$V$3:$W$41,2,FALSE) -> #REF!
B27: BAKKEN US GULF | C27: 1.65 | D27: 1.65 | E27: 1.65 | F27: 1.65 | G27: 1.65 | H27: 1.65 | I27: 1.65 | J27: 1.65 | K27: 1.65 | L27: 1.65 | M27: 1.65 | N27: 1.65 | P27: =EOMONTH(P26,1) -> 47087 | Q27: =BBG!E29 -> 70.18 | R27: =BBG!F29 -> 70.54 | S27: =EOMONTH(S26,1) -> 47118 | T27: =BBG!K29 -> 75.08 | U27: =BBG!L29 -> 75.29 | V27: =EOMONTH(V26,1) -> 47057 | W27: =BBG!E87 -> 69.94 | X27: =BBG!K87 -> 75.02 | Y27: =W27-X27 -> -5.08 | AB27: =VLOOKUP(#REF!,$P$3:$Q$41,2,FALSE)-VLOOKUP(#REF!,$V$3:$W$41,2,FALSE) -> #REF!
B28: CANADIAN PIPELINE ASSESSMENTS | P28: =EOMONTH(P27,1) -> 47118 | Q28: =BBG!E30 -> 69.74 | R28: =BBG!F30 -> 70.24 | S28: =EOMONTH(S27,1) -> 47149 | T28: =BBG!K30 -> 74.68 | U28: =BBG!L30 -> 74.94 | V28: =EOMONTH(V27,1) -> 47087 | W28: =BBG!E88 -> 69.6 | X28: =BBG!K88 -> 74.63 | Y28: =W28-X28 -> -5.03 | AB28: =VLOOKUP(USG!D1,$P$3:$Q$41,2,FALSE)-VLOOKUP(USG!D1,$V$3:$W$41,2,FALSE) -> #N/A
B29: GRADE | C29: 46296 | D29: 46327 | E29: 46357 | F29: 46388 | G29: 46419 | H29: 46447 | I29: 46478 | J29: 46508 | K29: 46539 | L29: 46569 | M29: 46600 | N29: 46631 | P29: =EOMONTH(P28,1) -> 47149 | Q29: =BBG!E31 -> 69.47 | R29: =BBG!F31 -> 69.91 | S29: =EOMONTH(S28,1) -> 47177 | T29: =BBG!K31 -> 74.32 | U29: =BBG!L31 -> 74.61 | V29: =EOMONTH(V28,1) -> 47118 | W29: =BBG!E89 -> 69.22 | X29: =BBG!K89 -> 74.26 | Y29: =W29-X29 -> -5.04 | AB29: =VLOOKUP(USG!D2,$P$3:$Q$41,2,FALSE)-VLOOKUP(USG!D2,$V$3:$W$41,2,FALSE) -> #N/A
B30: WCS CUSHING | C30: -15.25 | D30: -13.1 | E30: -12.55 | F30: -11.85 | G30: -11.45 | H30: -11.05 | I30: -10.6 | J30: -10.15 | K30: -9.7 | L30: -9.8 | M30: -9.9 | N30: -10 | P30: =EOMONTH(P29,1) -> 47177 | Q30: =BBG!E32 -> 69.1 | R30: =BBG!F32 -> 69.55 | S30: =EOMONTH(S29,1) -> 47208 | T30: =BBG!K32 -> 74.04 | U30: =BBG!L32 -> 74.35 | V30: =EOMONTH(V29,1) -> 47149 | W30: =BBG!E90 -> 68.86 | X30: =BBG!K90 -> 74 | Y30: =W30-X30 -> -5.14 | AB30: =VLOOKUP(USG!D4,$P$3:$Q$41,2,FALSE)-VLOOKUP(USG!D4,$V$3:$W$41,2,FALSE) -> #N/A
B31: CLK CUSHING | C31: -15.25 | D31: -13.1 | E31: -12.55 | F31: -11.85 | G31: -11.45 | H31: -11.05 | I31: -10.6 | J31: -10.15 | K31: -9.7 | L31: -9.8 | M31: -9.9 | N31: -10 | P31: =EOMONTH(P30,1) -> 47208 | Q31: =BBG!E33 -> 68.74 | R31: =BBG!F33 -> 69.22 | S31: =EOMONTH(S30,1) -> 47238 | T31: =BBG!K33 -> 73.76 | U31: =BBG!L33 -> 74.09 | V31: =EOMONTH(V30,1) -> 47177 | W31: =BBG!E91 -> 68.52 | X31: =BBG!K91 -> 73.72 | Y31: =W31-X31 -> -5.2 | AB31: =VLOOKUP(USG!D3,$P$3:$Q$41,2,FALSE)-VLOOKUP(USG!D3,$V$3:$W$41,2,FALSE) -> #N/A
B32: AWB CUSHING | C32: -15.5 | D32: -13.35 | E32: -12.8 | F32: -12.1 | G32: -11.7 | H32: -11.3 | I32: -10.85 | J32: -10.4 | K32: -9.95 | L32: -10.05 | M32: -10.15 | N32: -10.25 | P32: =EOMONTH(P31,1) -> 47238 | Q32: =BBG!E34 -> 68.4 | R32: =BBG!F34 -> 68.9 | S32: =EOMONTH(S31,1) -> 47269 | T32: =BBG!K34 -> 73.47 | U32: =BBG!L34 -> 73.82 | V32: =EOMONTH(V31,1) -> 47208 | W32: =BBG!E92 -> 68.19 | X32: =BBG!K92 -> 73.43 | Y32: =W32-X32 -> -5.24 | AB32: =VLOOKUP(USG!D5,$P$3:$Q$41,2,FALSE)-VLOOKUP(USG!D5,$V$3:$W$41,2,FALSE) -> #N/A
B33: WCS US GULF | C33: -14.25 | D33: -12 | E33: -11.45 | F33: -11.05 | G33: -10.65 | H33: -10.25 | I33: -9.8 | J33: -9.35 | K33: -8.9 | L33: -9 | M33: -9.1 | N33: -9.2 | P33: =EOMONTH(P32,1) -> 47269 | Q33: =BBG!E35 -> 68.1 | R33: =BBG!F35 -> 68.6 | S33: =EOMONTH(S32,1) -> 47299 | T33: =BBG!K35 -> 73.17 | U33: =BBG!L35 -> 73.54 | V33: =EOMONTH(V32,1) -> 47238 | W33: =BBG!E93 -> 67.88 | X33: =BBG!K93 -> 73.15 | Y33: =W33-X33 -> -5.27 | AB33: =VLOOKUP(USG!D6,$P$3:$Q$41,2,FALSE)-VLOOKUP(USG!D6,$V$3:$W$41,2,FALSE) -> #N/A
B34: CLK US GULF | C34: -14.25 | D34: -12 | E34: -11.45 | F34: -11.05 | G34: -10.65 | H34: -10.25 | I34: -9.8 | J34: -9.35 | K34: -8.9 | L34: -9 | M34: -9.1 | N34: -9.2 | P34: =EOMONTH(P33,1) -> 47299 | Q34: =BBG!E36 -> 67.65 | R34: =BBG!F36 -> 68.27 | S34: =EOMONTH(S33,1) -> 47330 | T34: =BBG!K36 -> 72.85 | U34: =BBG!L36 -> 73.24 | V34: =EOMONTH(V33,1) -> 47269 | W34: =BBG!E94 -> 67.55 | X34: =BBG!K94 -> 72.84 | Y34: =W34-X34 -> -5.29 | AB34: =VLOOKUP(USG!D7,$P$3:$Q$41,2,FALSE)-VLOOKUP(USG!D7,$V$3:$W$41,2,FALSE) -> #N/A
B35: AWB US GULF | C35: -15.45 | D35: -13.2 | E35: -12.65 | F35: -12.25 | G35: -11.85 | H35: -11.45 | I35: -11 | J35: -10.55 | K35: -10.1 | L35: -10.2 | M35: -10.3 | N35: -10.4 | P35: =EOMONTH(P34,1) -> 47330 | Q35: =BBG!E37 -> 67.41 | R35: =BBG!F37 -> 67.91 | S35: =EOMONTH(S34,1) -> 47361 | T35: =BBG!K37 -> 72.57 | U35: =BBG!L37 -> 72.97 | V35: =EOMONTH(V34,1) -> 47299 | W35: =BBG!E95 -> 67.18 | X35: =BBG!K95 -> 72.56 | Y35: =W35-X35 -> -5.38 | AB35: =VLOOKUP(USG!D8,$P$3:$Q$41,2,FALSE)-VLOOKUP(USG!D8,$V$3:$W$41,2,FALSE) -> #N/A
B36: CLK @ PATOKA | C36: -16.25 | D36: -14.1 | E36: -13.55 | F36: -12.85 | G36: -12.45 | H36: -12.05 | I36: -11.6 | J36: -11.15 | K36: -10.7 | L36: -10.8 | M36: -10.9 | N36: -11 | P36: =EOMONTH(P35,1) -> 47361 | Q36: =BBG!E38 -> 67.1 | R36: =BBG!F38 -> 67.61 | S36: =EOMONTH(S35,1) -> 47391 | T36: =BBG!K38 -> 72.28 | U36: =BBG!L38 -> 72.69 | V36: =EOMONTH(V35,1) -> 47330 | W36: =BBG!E96 -> 66.88 | X36: =BBG!K96 -> 72.27 | Y36: =W36-X36 -> -5.39 | AB36: =VLOOKUP(USG!D10,$P$3:$Q$41,2,FALSE)-VLOOKUP(USG!D10,$V$3:$W$41,2,FALSE) -> #N/A
B37: PHYSICAL FORWARD PIPELINE ASSESSMENTS | P37: =EOMONTH(P36,1) -> 47391 | Q37: =BBG!E39 -> 66.78 | R37: =BBG!F39 -> 67.3 | S37: =EOMONTH(S36,1) -> 47422 | T37: =BBG!K39 -> 72 | U37: =BBG!L39 -> 72.42 | V37: =EOMONTH(V36,1) -> 47361 | W37: =BBG!E97 -> 66.56 | X37: =BBG!K97 -> 71.99 | Y37: =W37-X37 -> -5.43 | AB37: =VLOOKUP(USG!D9,$P$3:$Q$41,2,FALSE)-VLOOKUP(USG!D9,$V$3:$W$41,2,FALSE) -> #N/A
B38: GRADE | C38: 4Q26 | D38: 1Q27 | E38: 2Q27 | F38: 3Q27 | G38: 4Q27 | H38: 1Q28 | I38: 1H27 | J38: 2H27 | K38: 1H28 | L38: Cal 27 | M38: Cal 28 | N38: Cal 29 | P38: =EOMONTH(P37,1) -> 47422 | Q38: =BBG!E40 -> 66.47 | R38: =BBG!F40 -> 67 | S38: =EOMONTH(S37,1) -> 47452 | T38: =BBG!K40 -> 71.69 | U38: =BBG!L40 -> 72.12 | V38: =EOMONTH(V37,1) -> 47391 | W38: =BBG!E98 -> 66.27 | X38: =BBG!K98 -> 71.68 | Y38: =W38-X38 -> -5.41 | AB38: =VLOOKUP(USG!D11,$P$3:$Q$41,2,FALSE)-VLOOKUP(USG!D11,$V$3:$W$41,2,FALSE) -> #N/A
B39: MIDSWT | C39: -0.483 | D39: 0.833 | E39: 1.2 | F39: 1.25 | G39: 1.25 | H39: 1.28 | I39: 1.017 | J39: 1.25 | K39: 1.28 | L39: 1.133 | M39: 1.3 | N39: 1.33 | P39: =EOMONTH(P38,1) -> 47452 | Q39: =BBG!E41 -> 66.18 | R39: =BBG!F41 -> 66.72 | S39: =EOMONTH(S38,1) -> 47483 | T39: =BBG!K41 -> 71.41 | U39: =BBG!L41 -> 71.84 | V39: =EOMONTH(V38,1) -> 47422 | W39: =BBG!E99 -> 65.97 | X39: =BBG!K99 -> 71.4 | Y39: =W39-X39 -> -5.43 | AB39: =VLOOKUP(USG!D12,$P$3:$Q$41,2,FALSE)-VLOOKUP(USG!D12,$V$3:$W$41,2,FALSE) -> #N/A
B40: MEH | C40: 1.033 | D40: 1.383 | E40: 1.8 | F40: 1.85 | G40: 1.9 | H40: 1.95 | I40: 1.592 | J40: 1.875 | K40: 1.95 | L40: 1.733 | M40: 1.98 | N40: 2.03 | P40: =EOMONTH(P39,1) -> 47483 | Q40: =BBG!E42 -> 65.75 | R40: =BBG!F42 -> 66.42 | S40: =EOMONTH(S39,1) -> 47514 | T40: =BBG!K42 -> 71.1 | U40: =BBG!L42 -> 71.54 | V40: =EOMONTH(V39,1) -> 47452 | W40: =BBG!E100 -> 65.62 | X40: =BBG!K100 -> 71.09 | Y40: =W40-X40 -> -5.47 | AB40: =VLOOKUP(USG!D13,$P$3:$Q$41,2,FALSE)-VLOOKUP(USG!D13,$V$3:$W$41,2,FALSE) -> #N/A
B41: WTS | C41: -5.833 | D41: -6.1 | E41: -6.1 | F41: -6.1 | G41: -6.1 | H41: -6.1 | I41: -6.1 | J41: -6.1 | K41: -6.1 | L41: -6.1 | M41: -0.5 | N41: -0.5 | P41: =EOMONTH(P40,1) -> 47514 | Q41: =BBG!E43 -> 65.51 | R41: =BBG!F43 -> 66.09 | S41: =EOMONTH(S40,1) -> 47542 | T41: =BBG!K43 -> 70.93 | U41: =BBG!L43 -> 71.39 | V41: =EOMONTH(V40,1) -> 47483 | W41: =BBG!E101 -> 65.31 | X41: =BBG!K101 -> 70.92 | Y41: =W41-X41 -> -5.61 | AB41: =VLOOKUP(USG!D15,$P$3:$Q$41,2,FALSE)-VLOOKUP(USG!D15,$V$3:$W$41,2,FALSE) -> #N/A
B42: LLS | C42: 2.483 | D42: 1.85 | E42: 2.25 | F42: 2.3 | G42: 2.4 | H42: 2.4 | I42: 2.05 | J42: 2.35 | K42: 2.4 | L42: 2.2 | M42: 2.25 | N42: 2.5
B43: MARS | C43: -2.333 | D43: -1.25 | E43: -1 | F43: -1 | G43: -1 | H43: -1 | I43: -1.125 | J43: -1 | K43: -1 | L43: -1.063 | M43: -1.25 | N43: -1
B44: WCS CUSHING | C44: -13.633 | D44: -11.45 | E44: -10.15 | F44: -9.9 | G44: -10.3 | H44: -10.45 | I44: -10.8 | J44: -10.1 | K44: -10.45 | L44: -10.45 | M44: -10.45 | N44: -10.45
B45: CLK CUSHING | C45: -13.633 | D45: -11.45 | E45: -10.15 | F45: -9.9 | G45: -10.3 | H45: -10.45 | I45: -10.8 | J45: -10.1 | K45: -10.45 | L45: -10.45 | M45: -10.45 | N45: -10.45
B46: AWB CUSHING | C46: -13.883 | D46: -11.7 | E46: -10.4 | F46: -10.15 | G46: -10.55 | H46: -10.7 | I46: -11.05 | J46: -10.35 | K46: -10.7 | L46: -10.7 | M46: -10.7 | N46: -10.7
B47: WCS US GULF | C47: -12.567 | D47: -10.65 | E47: -9.35 | F47: -9.1 | G47: -9.5 | H47: -9.65 | I47: -10 | J47: -9.3 | K47: -9.65 | L47: -9.65 | M47: -9.65 | N47: -9.65
B48: CLK US GULF | C48: -12.567 | D48: -10.65 | E48: -9.35 | F48: -9.1 | G48: -9.5 | H48: -9.65 | I48: -10 | J48: -9.3 | K48: -9.65 | L48: -9.65 | M48: -9.65 | N48: -9.65
B49: AWB US GULF | C49: -13.767 | D49: -11.85 | E49: -10.55 | F49: -10.3 | G49: -10.7 | H49: -10.85 | I49: -11.2 | J49: -10.5 | K49: -10.85 | L49: -10.85 | M49: -10.85 | N49: -10.85
D52: =D40-D39 -> 0.55 | E52: =E40-E39 -> 0.6 | F52: =F40-F39 -> 0.6 | G52: =G40-G39 -> 0.65 | H52: =H40-H39 -> 0.67
H53: =AVERAGE(D52:H52) -> 0.614
R54: 10 | S54: 0.4
H55: =1.28-H53 -> 0.666 | R55: 20 | S55: 0.55
H56: =1.98-H53 -> 1.366 | J56: =140000*30 -> 4200000 | R56: =R57-R54-R55 -> 45 | S56: 0.66
J57: 65 | R57: 75 | S57: {=SUMPRODUCT(S54:S56,R54:R56/SUM(R54:R56))+0.05} -> 0.646
H58: =AVERAGE(H55:H56) -> 1.016 | J58: 0.002
L59: =J61/J56 -> 0.13
J61: =J56*J57*J58 -> 546000
L62: vs. Cal Month Arrival Dated
E63: MEH Premium | F63: Decade Loader | G63: FFA Curve Value (WS) | H63: FOB Level vs ICE Brent | I63: Arrival Month | J63: Spreads | K63: DFLs | L63: Landed Rotterdam | M63: Landed Augusta | N63: Landed Kalundborg (720kb)
E64: 0.9 | F64: 1st | G64: =VLOOKUP(Sheet1!I64,Freight!$A$3:$E$14,5,FALSE) -> 16.1025 | H64: =#REF!+E64 -> #REF! | I64: =FWD!M5 -> 46356 | J64: 0 | K64: =FWD!$O$5 -> 3.33 | L64: =H64+FWD!N5+Sheet1!J64-Sheet1!K64 -> #REF! | M64: =L64+$K$60 -> #REF! | N64: =L64+$K$59 -> #REF!
E65: 0.5 | F65: 2nd | G65: =$G$64 -> 16.1025 | H65: =#REF!+E65 -> #REF! | I65: =FWD!M6 -> 46387 | J65: =FWD!Y5 -> 2.24 | K65: =FWD!$O$6 -> 2.61 | L65: =H65+FWD!N5+Sheet1!J65-Sheet1!K65 -> #REF! | M65: =L65+$K$60 -> #REF! | N65: =L65+$K$59 -> #REF!
E66: 0.25 | F66: 3rd | G66: =$G$64 -> 16.1025 | H66: =#REF!+E66 -> #REF! | I66: =I65 -> 46387 | J66: =J65 -> 2.24 | K66: =FWD!$O$6 -> 2.61 | L66: =H66+FWD!N5+Sheet1!J66-Sheet1!K66 -> #REF! | M66: =L66+$K$60 -> #REF! | N66: =L66+$K$59 -> #REF!
K68: **STS at Disport for Buyer's account
E69: MEH Premium | F69: Decade Loader | G69: VLCC Freight LS ($MMs) | H69: FOB Level vs ICE Brent | I69: Arrival Month | J69: Spreads | K69: DFLs | L69: Landed Rotterdam
E70: =E64 -> 0.9 | F70: 1st | G70: =[1]WTI!$AD$58/1000000 -> 0.000795 | H70: =#REF!+E70 -> #REF! | I70: =I65 -> 46387 | J70: =J65 -> 2.24 | K70: =K65 -> 2.61 | L70: =H70+#REF!+Sheet1!J70-Sheet1!K70 -> #REF!
E71: =E65 -> 0.5 | F71: 2nd | G71: =$G$70 -> 0.000795 | H71: =#REF!+E71 -> #REF! | I71: =I65 -> 46387 | J71: =$J$65 -> 2.24 | K71: =K65 -> 2.61 | L71: =H71+#REF!+Sheet1!J71-Sheet1!K71 -> #REF!
E72: =E66 -> 0.25 | F72: 3rd | G72: =$G$70 -> 0.000795 | H72: =#REF!+E72 -> #REF! | I72: =EOMONTH(I71,1) -> 46418 | J72: =FWD!Y6 -> 1.7 | K72: =FWD!O7 -> 2.03 | L72: =H72+#REF!+Sheet1!J72-Sheet1!K72 -> #REF!
E74: MEH Premium | F74: Decade Loader | G74: VLCC Freight LS ($MMs) | H74: FOB Level vs ICE Brent | I74: Arrival Month | J74: Spreads | K74: DFLs | L74: Landed Rotterdam
E75: 0.45 | F75: 1st | G75: =G72 -> 0.000795 | H75: =#REF!+E75 -> #REF! | I75: =I70 -> 46387 | J75: =J70 -> 2.24 | K75: =K70 -> 2.61 | L75: =H75+#REF!+Sheet1!J75-Sheet1!K75 -> #REF!
E76: 0.3 | F76: 2nd | G76: =$G$70 -> 0.000795 | H76: =#REF!+E76 -> #REF! | I76: =I70 -> 46387 | J76: =$J$65 -> 2.24 | K76: =K70 -> 2.61 | L76: =H76+#REF!+Sheet1!J76-Sheet1!K76 -> #REF!
E77: 0.25 | F77: 3rd | G77: =$G$70 -> 0.000795 | H77: =#REF!+E77 -> #REF! | I77: =EOMONTH(I76,1) -> 46418 | J77: =FWD!Y11 -> 1.02 | K77: =FWD!O12 -> 1.32 | L77: =H77+#REF!+Sheet1!J77-Sheet1!K77 -> #REF!
E86: Marker Grade | F86: Grade Marker | G86: FOB diff | H86: vs June ICE Brent | I86: vs July ICE Brent
E87: WTI (Corpus) | F87: MEH | G87: =FWD!A2 -> 0 | H87: =FWD!J5 -> -3.32 | I87: =FWD!J6 -> -3.43
E88: EF45* | F88: MEH | G88: =G87-0.4 -> -0.4 | H88: =H87-(G87-G88) -> -3.72 | I88: =I87-(G87-G88) -> -3.83
E89: Mars VLCC (LOOP) | F89: Mars | G89: 2.5 | H89: =H87-(Sheet1!C20-Sheet1!C26)-G87+G89 -> -46296.52 | I89: =I87-(Sheet1!D20-Sheet1!D26)-G87+G89 -> -46327.63
E90: WTL (Corpus) | F90: MEH | G90: =G87-0.3 -> -0.3 | H90: =H87-(G87-G90) -> -3.62 | I90: =I87-(G87-G90) -> -3.73
E91: CLK (Freeport) | F91: CMA | G91: =#REF! -> #REF! | H91: =#REF! -> #REF! | I91: =#REF! -> #REF!
E92: AWB | F92: CMA | G92: =#REF! -> #REF! | H92: =H91-0.75 -> #REF! | I92: =I91-0.75 -> #REF!
E98: WTI MIDLAND / BRENT EFP Arbs
N99: WTI Avails
E100: US Load Month | F100: (Closed)/Open | H100: Europe Arrival Month | I100: (Closed)/Open
E101: =IF(FWD!V4="Expired","Balmo "&TEXT(FWD!E4,"Mmm-yy"),FWD!E4) -> Balmo Oct-26 | F101: =FWD!AD4 -> Expired | H101: 45869 | I101: =IFERROR((FWD!V5*1/3)+(FWD!AD4*2/3),"Expired") -> Expired | N101: Load Window | P101: Volume | R101: CIF Rotterdam (DATED Cal Month Arrival) | V101: DAP Korea (Cal Month DUBAI M-1 Arrival)
E102: =IF(FWD!V5="Expired","Balmo "&TEXT(FWD!E5,"Mmm-yy"),FWD!E5) -> Balmo Nov-26 | F102: =FWD!AD5 -> -7.2386071 | H102: =EOMONTH(H101,1) -> 45900 | I102: =IFERROR((FWD!V6*1/3)+(FWD!AD5*2/3),"Expired") -> -5.8827405 | M102: Houstom | N102: 45789 | O102: =+N102+1 -> 45790 | P102: 700 | R102: =O102+17 -> 45807 | S102: =R102+4 -> 45811 | T102: =FWD!$AB$5 -> 12.5325
E103: =FWD!E6 -> 46387 | F103: =IFERROR((FWD!V6*1/3)+(FWD!AD6*2/3),"Expired") -> -4.5113042 | H103: =EOMONTH(H102,1) -> 45930 | I103: =IFERROR((FWD!V7*1/3)+(FWD!AD6*2/3),"Expired") -> -3.944611 | L103: delayed to 23-24 | M103: Houston | N103: 45792 | O103: =+N103+1 -> 45793 | P103: 700 | R103: =O103+17 -> 45810 | S103: =R103+4 -> 45814 | T103: =FWD!$AB$5 -> 12.5325
E104: =FWD!E7 -> 46418 | F104: =IFERROR((FWD!V7*1/3)+(FWD!AD7*2/3),"Expired") -> -1.5134587 | H104: =EOMONTH(H103,1) -> 45961 | I104: =IFERROR((FWD!V8*1/3)+(FWD!AD7*2/3),"Expired") -> -1.0102962 | L104: can be delayed to 27-28 | M104: Corpus | N104: 45794 | O104: =+N104+1 -> 45795 | P104: 700 | R104: =O104+17 -> 45812 | S104: =R104+4 -> 45816 | T104: =FWD!$AB$5 -> 12.5325
E105: =FWD!E8 -> 46446 | F105: =IFERROR((FWD!V8*1/3)+(FWD!AD8*2/3),"Expired") -> -1.022132 | H105: =EOMONTH(H104,1) -> 45991 | I105: =IFERROR((FWD!V9*1/3)+(FWD!AD8*2/3),"Expired") -> -1.0847166
E106: =FWD!E9 -> 46477 | F106: =IFERROR((FWD!V9*1/3)+(FWD!AD9*2/3),"Expired") -> -1.2405072 | H106: =EOMONTH(H105,1) -> 46022 | I106: =IFERROR((FWD!V10*1/3)+(FWD!AD9*2/3),"Expired") -> -1.2880622 | M106: Corpus | N106: 45800 | O106: =+N106+1 -> 45801 | P106: 700 | R106: =O106+17 -> 45818 | S106: =R106+4 -> 45822 | T106: =T102 -> 12.5325
E107: =FWD!E10 -> 46507 | F107: =IFERROR((FWD!V10*1/3)+(FWD!AD10*2/3),"Expired") -> -0.83565537 | H107: =EOMONTH(H106,1) -> 46053 | I107: =IFERROR((FWD!V11*1/3)+(FWD!AD10*2/3),"Expired") -> -0.6720309 | N107: 45806 | O107: =+N107+1 -> 45807 | P107: 700 | R107: =O107+17 -> 45824 | S107: =R107+4 -> 45828
E108: =FWD!E11 -> 46538 | F108: =IFERROR((FWD!V11*1/3)+(FWD!AD11*2/3),"Expired") -> -0.58098537 | H108: =EOMONTH(H107,1) -> 46081 | I108: =IFERROR((FWD!V12*1/3)+(FWD!AD11*2/3),"Expired") -> -0.66765203 | L108: Sold June EFP | M108: EHSC | N108: 45803 | O108: =+N108+1 -> 45804 | P108: 700 | R108: =O108+17 -> 45821 | S108: =R108+4 -> 45825 | T108: =T103 -> 12.5325
E109: =FWD!E12 -> 46568 | F109: =IFERROR((FWD!V12*1/3)+(FWD!AD12*2/3),"Expired") -> -0.84674807 | H109: =EOMONTH(H108,1) -> 46112 | I109: =IFERROR((FWD!V13*1/3)+(FWD!AD12*2/3),"Expired") -> -0.58863307
E110: =FWD!E13 -> 46599 | F110: =IFERROR((FWD!V13*1/3)+(FWD!AD13*2/3),"Expired") -> 0.046692963 | H110: =EOMONTH(H109,1) -> 46142 | I110: =IFERROR((FWD!V14*1/3)+(FWD!AD13*2/3),"Expired") -> -0.016640371
E111: =FWD!E14 -> 46630 | F111: =IFERROR((FWD!V14*1/3)+(FWD!AD14*2/3),"Expired") -> -0.12330704 | H111: =EOMONTH(H110,1) -> 46173 | I111: =IFERROR((FWD!V15*1/3)+(FWD!AD14*2/3),"Expired") -> -0.1799737 | M111: Houston | N111: 45814 | O111: =+N111+1 -> 45815 | P111: 700 | R111: =O111+17 -> 45832 | S111: =R111+4 -> 45836
E112: =FWD!E15 -> 46660 | F112: =IFERROR((FWD!V15*1/3)+(FWD!AD15*2/3),"Expired") -> -0.12178163 | H112: =EOMONTH(H111,1) -> 46203 | I112: =IFERROR((FWD!V16*1/3)+(FWD!AD15*2/3),"Expired") -> -0.16711364 | L112: Sold ex-pipe | M112: Corpus | N112: 45816 | O112: =N112+1 -> 45817 | P112: 700 | R112: =O112+17 -> 45834 | S112: =R112+4 -> 45838
E113: =FWD!E16 -> 46691 | F113: =IFERROR((FWD!V16*1/3)+(FWD!AD16*2/3),"Expired") -> -0.30263641 | H113: =EOMONTH(H112,1) -> 46234 | I113: =IFERROR((FWD!V17*1/3)+(FWD!AD16*2/3),"Expired") -> -0.33596974
E114: =FWD!E17 -> 46721 | F114: =IFERROR((FWD!V17*1/3)+(FWD!AD17*2/3),"Expired") -> -0.34263641 | H114: =EOMONTH(H113,1) -> 46265 | I114: =IFERROR((FWD!V18*1/3)+(FWD!AD17*2/3),"Expired") -> -0.38263641
E115: =FWD!E18 -> 46752 | F115: =IFERROR((FWD!V18*1/3)+(FWD!AD18*2/3),"Expired") -> 0.10925261 | H115: =EOMONTH(H114,1) -> 46295 | I115: =IFERROR((FWD!V19*1/3)+(FWD!AD18*2/3),"Expired") -> 0.32519713 | M115: Houstom | N115: 45820 | O115: =+N115+1 -> 45821 | P115: 700 | R115: =O115+17 -> 45838 | S115: =R115+4 -> 45842
E116: =FWD!E19 -> 46783 | F116: =IFERROR((FWD!V19*1/3)+(FWD!AD19*2/3),"Expired") -> 0.22519713 | H116: =EOMONTH(H115,1) -> 46326 | I116: =IFERROR((FWD!V20*1/3)+(FWD!AD19*2/3),"Expired") -> 0.18519713 | M116: Corpus | N116: 45824 | O116: =+N116+1 -> 45825 | P116: 700 | R116: =O116+17 -> 45842 | S116: =R116+4 -> 45846
E117: =FWD!E20 -> 46812 | F117: =IFERROR((FWD!V20*1/3)+(FWD!AD20*2/3),"Expired") -> 0.14519713 | H117: =EOMONTH(H116,1) -> 46356 | I117: =IFERROR((FWD!V21*1/3)+(FWD!AD20*2/3),"Expired") -> 0.11519713 | M117: Houstom | N117: 45825 | O117: =+N117+1 -> 45826 | P117: 700 | R117: =O117+17 -> 45843 | S117: =R117+4 -> 45847
E118: =FWD!E21 -> 46843 | F118: =IFERROR((FWD!V21*1/3)+(FWD!AD21*2/3),"Expired") -> 0.099924296 | H118: =EOMONTH(H117,1) -> 46387 | I118: =IFERROR((FWD!V22*1/3)+(FWD!AD21*2/3),"Expired") -> 0.072287882 | M118: Corpus | N118: 45827 | O118: =+N118+1 -> 45828 | P118: 2000 | R118: =O118+17 -> 45845 | S118: =R118+4 -> 45849
...

Sheet USG
A1: 46293 | C1: CFD WEEKS | E1: =Sheet1!S3 -> 46387 | F1: =EOMONTH(E1,1) -> 46418 | G1: =EOMONTH(F1,1) -> 46446 | H1: =EOMONTH(G1,1) -> 46477 | I1: vs. Cal Dtd | J1: 1-Wkr | K1: 2-Wkr | L1: 3-Wkr | N1: WTI arrivals (MEH FLAT, Platts pxg)
A2: =A1+7 -> 46300 | D2: Week | F2: =-(Sheet1!T4-Sheet1!T3) -> 3.87 | G2: =Sheet1!T4-Sheet1!T5 -> 3.08 | H2: =Sheet1!U4-Sheet1!U5 -> 2.24 | N2: =Q3 -> CFD Week | O2: =AB3 -> Curve Value | Q2: 1 | R2: =TEXT(A1,"mmmdd")&"-"&TEXT(WORKDAY(A1,4),"mmmdd") -> Sep28-Oct02
A3: =A2+7 -> 46307 | D3: Balmo | Q3: CFD Week | R3: vs. ICE Brent | S3: Diff | U3: Delivery Window | X3: MEH/Brent | Y3: FOB Premium | Z3: Cash Roll | AA3: Freight+Cost | AB3: Curve Value | AH3: USGC Load Window | AP3: Load WTI | AQ3: Delivery Brent
A4: =A3+7 -> 46314 | C4: 2670 | D4: =TEXT(A1,"mmmdd")&"-"&TEXT(WORKDAY(A1,4),"mmmdd") -> Sep28-Oct02 | E4: =C4/100 -> 26.7 | F4: =(E4)+F$2 -> 30.57 | G4: =(F4)+G$2 -> 33.65 | H4: =(G4)+H$2 -> 35.89 | J4: =C4-C5 -> 500 | K4: =C4-C6 -> 1210 | L4: =J4+J3+J5 -> 1210 | N4: =D4 -> Sep28-Oct02 | O4: =AB4 -> #N/A | P4: =VLOOKUP(Q4,USG!$D$1:$H$19,MATCH(USG!R4,USG!$D$1:$H$1,0),FALSE) -> 26.7 | Q4: =TEXT(A1,"mmmdd")&"-"&TEXT(WORKDAY(A1,4),"mmmdd") -> Sep28-Oct02 | R4: =EOMONTH(V4,2) -> 46387 | S4: =P4 -> 26.7 | U4: =A1 -> 46293 | V4: =WORKDAY(U4,4) -> 46297 | X4: =VLOOKUP(AP$4,Sheet1!$P$3:$Q$41,2,FALSE)-VLOOKUP($AQ4,Sheet1!$S$3:$T$41,2,FALSE)+HLOOKUP(AP4,$D$25:$H$26,2,FALSE) -> #N/A | Y4: 0 | Z4: =IF(EOMONTH(AI4,0)<AP4,USG!$D$29,0) -> 3 | AA4: =IFERROR(VLOOKUP(AG4,Freight!$A$3:$F$22,MATCH("TD25",Freight!$A$3:$F$3,0),FALSE),VLOOKUP(EOMONTH(AG4,1),Freight!$A$3:$F$22,MATCH("TD25",Freight!$A$3:$F$3,0),FALSE))+$AB$28 -> #VALUE! | AB4: =SUM(X4:AA4)-S4 -> #N/A | AG4: =IF(AH4<TODAY()+10,"Balmo",EOMONTH(AH4,0)) -> Balmo | AH4: =U4-17 -> 46276 | AI4: =V4-17 -> 46280 | AO4: =EOMONTH(AH4,0) -> 46295 | AP4: =IF(AI4>USG!$E$25,EOMONTH(AI4,0),USG!$E$25) -> 46356 | AQ4: =EOMONTH(U4,2) -> 46356
A5: =A4+7 -> 46321 | C5: 2170 | D5: =TEXT(A2,"mmmdd")&"-"&TEXT(WORKDAY(A2,4),"mmmdd") -> Oct05-Oct09 | E5: =C5/100 -> 21.7 | F5: =(E5)+F$2 -> 25.57 | G5: =(F5)+G$2 -> 28.65 | H5: =(G5)+H$2 -> 30.89 | J5: =C5-C6 -> 710 | K5: =J5+J6 -> 1310 | L5: =J5+J6+J7 -> 1585 | N5: =D5 -> Oct05-Oct09 | O5: =AB5 -> #VALUE! | P5: =VLOOKUP(Q5,USG!$D$1:$H$19,MATCH(USG!R5,USG!$D$1:$H$1,0),FALSE) -> 21.7 | Q5: =TEXT(A2,"mmmdd")&"-"&TEXT(WORKDAY(A2,4),"mmmdd") -> Oct05-Oct09 | R5: =EOMONTH(V5,2) -> 46387 | S5: =P5 -> 21.7 | U5: =WORKDAY(V4,1) -> 46300 | V5: =WORKDAY(U5,4) -> 46304 | X5: =VLOOKUP(AP$4,Sheet1!$P$3:$Q$41,2,FALSE)-VLOOKUP($AQ5,Sheet1!$S$3:$T$41,2,FALSE)+HLOOKUP(AP5,$D$25:$H$26,2,FALSE) -> -8.1 | Y5: 0 | Z5: =IF(EOMONTH(AI5,0)<AP5,USG!$D$29,0) -> 3 | AA5: =IFERROR(VLOOKUP(AG5,Freight!$A$3:$F$22,MATCH("TD25",Freight!$A$3:$F$3,0),FALSE),VLOOKUP(EOMONTH(AG5,1),Freight!$A$3:$F$22,MATCH("TD25",Freight!$A$3:$F$3,0),FALSE))+$AB$28 -> #VALUE! | AB5: =SUM(X5:AA5)-S5 -> #VALUE! | AG5: =IF(AH5<TODAY()+10,"Balmo",EOMONTH(AH5,0)) -> Balmo | AH5: =U5-17 -> 46283 | AI5: =V5-17 -> 46287 | AO5: =EOMONTH(AH5,0) -> 46295 | AP5: =IF(AI5>USG!$E$25,EOMONTH(AI5,0),USG!$E$25) -> 46356 | AQ5: =EOMONTH(U5,2) -> 46387
A6: =A5+7 -> 46328 | C6: 1460 | D6: =TEXT(A3,"mmmdd")&"-"&TEXT(WORKDAY(A3,4),"mmmdd") -> Oct12-Oct16 | E6: =C6/100 -> 14.6 | F6: =(E6)+F$2 -> 18.47 | G6: =(F6)+G$2 -> 21.55 | H6: =(G6)+H$2 -> 23.79 | J6: =C6-C7 -> 600 | K6: =J6+J7 -> 875 | L6: =J6+J7+J8 -> 1040 | N6: =D6 -> Oct12-Oct16 | O6: =AB6 -> #VALUE! | P6: =VLOOKUP(Q6,USG!$D$1:$H$19,MATCH(USG!R6,USG!$D$1:$H$1,0),FALSE) -> 14.6 | Q6: =TEXT(A3,"mmmdd")&"-"&TEXT(WORKDAY(A3,4),"mmmdd") -> Oct12-Oct16 | R6: =EOMONTH(V6,2) -> 46387 | S6: =P6 -> 14.6 | U6: =WORKDAY(V5,1) -> 46307 | V6: =WORKDAY(U6,4) -> 46311 | X6: =VLOOKUP(AP$4,Sheet1!$P$3:$Q$41,2,FALSE)-VLOOKUP($AQ6,Sheet1!$S$3:$T$41,2,FALSE)+HLOOKUP(AP6,$D$25:$H$26,2,FALSE) -> -8.1 | Y6: 0 | Z6: =IF(EOMONTH(AI6,0)<AP6,USG!$D$29,0) -> 3 | AA6: =IFERROR(VLOOKUP(AG6,Freight!$A$3:$F$22,MATCH("TD25",Freight!$A$3:$F$3,0),FALSE),VLOOKUP(EOMONTH(AG6,1),Freight!$A$3:$F$22,MATCH("TD25",Freight!$A$3:$F$3,0),FALSE))+$AB$28 -> #VALUE! | AB6: =SUM(X6:AA6)-S6 -> #VALUE! | AG6: =IF(AH6<TODAY()+10,"Balmo",EOMONTH(AH6,0)) -> Balmo | AH6: =U6-17 -> 46290 | AI6: =V6-17 -> 46294 | AO6: =EOMONTH(AH6,0) -> 46295 | AP6: =IF(AI6>USG!$E$25,EOMONTH(AI6,0),USG!$E$25) -> 46356 | AQ6: =EOMONTH(U6,2) -> 46387
C7: 860 | D7: =TEXT(A4,"mmmdd")&"-"&TEXT(WORKDAY(A4,4),"mmmdd") -> Oct19-Oct23 | E7: =C7/100 -> 8.6 | F7: =(E7)+F$2 -> 12.47 | G7: =(F7)+G$2 -> 15.55 | H7: =(G7)+H$2 -> 17.79 | J7: =C7-C8 -> 275 | K7: =J7+J8 -> 440 | L7: =J7+J8+J10 -> 630 | N7: =D7 -> Oct19-Oct23 | O7: =AB7 -> #VALUE! | P7: =VLOOKUP(Q7,USG!$D$1:$H$19,MATCH(USG!R7,USG!$D$1:$H$1,0),FALSE) -> 8.6 | Q7: =TEXT(A4,"mmmdd")&"-"&TEXT(WORKDAY(A4,4),"mmmdd") -> Oct19-Oct23 | R7: =EOMONTH(V7,2) -> 46387 | S7: =P7 -> 8.6 | U7: =WORKDAY(V6,1) -> 46314 | V7: =WORKDAY(U7,4) -> 46318 | X7: =VLOOKUP(AP$4,Sheet1!$P$3:$Q$41,2,FALSE)-VLOOKUP($AQ7,Sheet1!$S$3:$T$41,2,FALSE)+HLOOKUP(AP7,$D$25:$H$26,2,FALSE) -> -8.1 | Y7: 0 | Z7: =IF(EOMONTH(AI7,0)<AP7,USG!$D$29,0) -> 3 | AA7: =IFERROR(VLOOKUP(AG7,Freight!$A$3:$F$22,MATCH("TD25",Freight!$A$3:$F$3,0),FALSE),VLOOKUP(EOMONTH(AG7,1),Freight!$A$3:$F$22,MATCH("TD25",Freight!$A$3:$F$3,0),FALSE))+$AB$28 -> #VALUE! | AB7: =SUM(X7:AA7)-S7 -> #VALUE! | AG7: =IF(AH7<TODAY()+10,"Balmo",EOMONTH(AH7,0)) -> Balmo | AH7: =U7-17 -> 46297 | AI7: =V7-17 -> 46301 | AO7: =EOMONTH(AH7,0) -> 46326 | AP7: =IF(AI7>USG!$E$25,EOMONTH(AI7,0),USG!$E$25) -> 46356 | AQ7: =EOMONTH(U7,2) -> 46387
A8: =A9+7 -> 46342 | C8: 585 | D8: =TEXT(A5,"mmmdd")&"-"&TEXT(WORKDAY(A5,4),"mmmdd") -> Oct26-Oct30 | E8: =C8/100 -> 5.85 | F8: =(E8)+F$2 -> 9.72 | G8: =(F8)+G$2 -> 12.8 | H8: =(G8)+H$2 -> 15.04 | J8: =C8-C10 -> 165 | K8: =C8-C11 -> 355 | L8: =J8+J7+J10 -> 630 | N8: =D8 -> Oct26-Oct30 | O8: =AB8 -> #VALUE! | P8: =VLOOKUP(Q8,USG!$D$1:$H$19,MATCH(USG!R8,USG!$D$1:$H$1,0),FALSE) -> 5.85 | Q8: =TEXT(A5,"mmmdd")&"-"&TEXT(WORKDAY(A5,4),"mmmdd") -> Oct26-Oct30 | R8: =EOMONTH(V8,2) -> 46387 | S8: =P8 -> 5.85 | U8: =WORKDAY(V7,1) -> 46321 | V8: =WORKDAY(U8,4) -> 46325 | X8: =VLOOKUP(AP$4,Sheet1!$P$3:$Q$41,2,FALSE)-VLOOKUP($AQ8,Sheet1!$S$3:$T$41,2,FALSE)+HLOOKUP(AP8,$D$25:$H$26,2,FALSE) -> -8.1 | Y8: 0 | Z8: =IF(EOMONTH(AI8,0)<AP8,USG!$D$29,0) -> 3 | AA8: =IFERROR(VLOOKUP(AG8,Freight!$A$3:$F$22,MATCH("TD25",Freight!$A$3:$F$3,0),FALSE),VLOOKUP(EOMONTH(AG8,1),Freight!$A$3:$F$22,MATCH("TD25",Freight!$A$3:$F$3,0),FALSE))+$AB$28 -> #VALUE! | AB8: =SUM(X8:AA8)-S8 -> #VALUE! | AG8: =IF(AH8<TODAY()+10,"Balmo",EOMONTH(AH8,0)) -> Balmo | AH8: =U8-17 -> 46304 | AI8: =V8-17 -> 46308 | AO8: =EOMONTH(AH8,0) -> 46326 | AP8: =IF(AI8>USG!$E$25,EOMONTH(AI8,0),USG!$E$25) -> 46356 | AQ8: =EOMONTH(U8,2) -> 46387
A9: =A6+7 -> 46335 | D9: Full Month | E9: =AVERAGE(E4:E8) -> 15.49 | F9: =AVERAGE(F4:F8) -> 19.36 | G9: =AVERAGE(G4:G8) -> 22.44 | H9: =AVERAGE(H4:H8) -> 24.68 | N9: =D9 -> Full Month | O9: =AVERAGE(O4:O7) -> #N/A
A10: =A8+7 -> 46349 | C10: 420 | D10: =TEXT(A6,"mmmdd")&"-"&TEXT(WORKDAY(A6,4),"mmmdd") -> Nov02-Nov06 | E10: =C10/100 -> 4.2 | F10: =(E10)+F$2 -> 8.07 | G10: =(F10)+G$2 -> 11.15 | H10: =(G10)+H$2 -> 13.39 | J10: =C10-C11 -> 190 | K10: =C10-C12 -> 375 | L10: =J10+J9+J11 -> 375 | N10: =D10 -> Nov02-Nov06 | O10: =AB10 -> 7.94865 | P10: =VLOOKUP(Q10,USG!$D$1:$H$19,MATCH(USG!R10,USG!$D$1:$H$1,0),FALSE) -> 8.07 | Q10: =TEXT(A6,"mmmdd")&"-"&TEXT(WORKDAY(A6,4),"mmmdd") -> Nov02-Nov06 | R10: =EOMONTH(V10,2) -> 46418 | S10: =P10 -> 8.07 | U10: =WORKDAY(V8,1) -> 46328 | V10: =WORKDAY(U10,4) -> 46332 | X10: =VLOOKUP(AP$4,Sheet1!$P$3:$Q$41,2,FALSE)-VLOOKUP($AQ10,Sheet1!$S$3:$T$41,2,FALSE)+HLOOKUP(AP10,$D$25:$H$26,2,FALSE) -> -4.23 | Z10: =IF(EOMONTH(AI10,0)<AP10,USG!$D$29,0) -> 3 | AA10: =IFERROR(VLOOKUP(AG10,Freight!$A$3:$F$22,MATCH("TD25",Freight!$A$3:$F$3,0),FALSE),VLOOKUP(EOMONTH(AG10,1),Freight!$A$3:$F$22,MATCH("TD25",Freight!$A$3:$F$3,0),FALSE))+$AB$28 -> 17.24865 | AB10: =SUM(X10:AA10)-S10 -> 7.94865 | AG10: =IF(AH10<TODAY()+10,"Balmo",EOMONTH(AH10,0)) -> 46326 | AH10: =U10-17 -> 46311 | AI10: =V10-17 -> 46315 | AO10: =EOMONTH(AH10,0) -> 46326 | AP10: =IF(AI10>USG!$E$25,EOMONTH(AI10,0),USG!$E$25) -> 46356 | AQ10: =EOMONTH(U10,2) -> 46418
A11: =A10+7 -> 46356 | C11: 230 | D11: =TEXT(A9,"mmmdd")&"-"&TEXT(WORKDAY(A9,4),"mmmdd") -> Nov09-Nov13 | E11: =C11/100 -> 2.3 | F11: =(E11)+F$2 -> 6.17 | G11: =(F11)+G$2 -> 9.25 | H11: =(G11)+H$2 -> 11.49 | J11: =C11-C12 -> 185 | K11: =C11-C13 -> 285 | L11: =J11+J8+J12 -> 450 | N11: =D11 -> Nov09-Nov13 | O11: =AB11 -> 9.84865 | P11: =VLOOKUP(Q11,USG!$D$1:$H$19,MATCH(USG!R11,USG!$D$1:$H$1,0),FALSE) -> 6.17 | Q11: =TEXT(A9,"mmmdd")&"-"&TEXT(WORKDAY(A9,4),"mmmdd") -> Nov09-Nov13 | R11: =EOMONTH(V11,2) -> 46418 | S11: =P11 -> 6.17 | U11: =WORKDAY(V10,1) -> 46335 | V11: =WORKDAY(U11,4) -> 46339 | X11: =VLOOKUP(AP$4,Sheet1!$P$3:$Q$41,2,FALSE)-VLOOKUP($AQ11,Sheet1!$S$3:$T$41,2,FALSE)+HLOOKUP(AP11,$D$25:$H$26,2,FALSE) -> -4.23 | Z11: =IF(EOMONTH(AI11,0)<AP11,USG!$D$29,0) -> 3 | AA11: =IFERROR(VLOOKUP(AG11,Freight!$A$3:$F$22,MATCH("TD25",Freight!$A$3:$F$3,0),FALSE),VLOOKUP(EOMONTH(AG11,1),Freight!$A$3:$F$22,MATCH("TD25",Freight!$A$3:$F$3,0),FALSE))+$AB$28 -> 17.24865 | AB11: =SUM(X11:AA11)-S11 -> 9.84865 | AG11: =IF(AH11<TODAY()+10,"Balmo",EOMONTH(AH11,0)) -> 46326 | AH11: =U11-17 -> 46318 | AI11: =V11-17 -> 46322 | AO11: =EOMONTH(AH11,0) -> 46326 | AP11: =IF(AI11>USG!$E$25,EOMONTH(AI11,0),USG!$E$25) -> 46356 | AQ11: =EOMONTH(U11,2) -> 46418
A12: =A11+7 -> 46363 | C12: 45 | D12: =TEXT(A8,"mmmdd")&"-"&TEXT(WORKDAY(A8,4),"mmmdd") -> Nov16-Nov20 | E12: =C12/100 -> 0.45 | F12: =(E12)+F$2 -> 4.32 | G12: =(F12)+G$2 -> 7.4 | H12: =(G12)+H$2 -> 9.64 | J12: =C12-C13 -> 100 | K12: =C12-C15 -> 185 | L12: =J12+J10+J13 -> 375 | N12: =D12 -> Nov16-Nov20 | O12: =AB12 -> 8.69865 | P12: =VLOOKUP(Q12,USG!$D$1:$H$19,MATCH(USG!R12,USG!$D$1:$H$1,0),FALSE) -> 4.32 | Q12: =TEXT(A8,"mmmdd")&"-"&TEXT(WORKDAY(A8,4),"mmmdd") -> Nov16-Nov20 | R12: =EOMONTH(V12,2) -> 46418 | S12: =P12 -> 4.32 | U12: =WORKDAY(V11,1) -> 46342 | V12: =WORKDAY(U12,4) -> 46346 | X12: =VLOOKUP(AP$4,Sheet1!$P$3:$Q$41,2,FALSE)-VLOOKUP($AQ12,Sheet1!$S$3:$T$41,2,FALSE)+HLOOKUP(AP12,$D$25:$H$26,2,FALSE) -> -4.23 | Z12: =IF(EOMONTH(AI12,0)<AP12,USG!$D$29,0) -> 0 | AA12: =IFERROR(VLOOKUP(AG12,Freight!$A$3:$F$22,MATCH("TD25",Freight!$A$3:$F$3,0),FALSE),VLOOKUP(EOMONTH(AG12,1),Freight!$A$3:$F$22,MATCH("TD25",Freight!$A$3:$F$3,0),FALSE))+$AB$28 -> 17.24865 | AB12: =SUM(X12:AA12)-S12 -> 8.69865 | AG12: =IF(AH12<TODAY()+10,"Balmo",EOMONTH(AH12,0)) -> 46326 | AH12: =U12-17 -> 46325 | AI12: =V12-17 -> 46329 | AO12: =EOMONTH(AH12,0) -> 46326 | AP12: =IF(AI12>USG!$E$25,EOMONTH(AI12,0),USG!$E$25) -> 46356 | AQ12: =EOMONTH(U12,2) -> 46418
A13: =A14+7 -> 46377 | C13: -55 | D13: =TEXT(A10,"mmmdd")&"-"&TEXT(WORKDAY(A10,4),"mmmdd") -> Nov23-Nov27 | E13: =C13/100 -> -0.55 | F13: =(E13)+F$2 -> 3.32 | G13: =(F13)+G$2 -> 6.4 | H13: =(G13)+H$2 -> 8.64 | J13: =C13-C15 -> 85 | K13: =C13-C16 -> 170 | L13: =J13+J11+J14 -> 270 | N13: =D14 -> Full Month
A14: =A12+7 -> 46370 | D14: Full Month | E14: =AVERAGE(E10:E13) -> 1.6 | F14: =AVERAGE(F10:F13) -> 5.47 | G14: =AVERAGE(G10:G13) -> 8.55 | H14: =AVERAGE(H10:H13) -> 10.79 | N14: =D13 -> Nov23-Nov27 | O14: =AB14 -> 8.7325 | P14: =VLOOKUP(Q14,USG!$D$1:$H$19,MATCH(USG!R14,USG!$D$1:$H$1,0),FALSE) -> 3.32 | Q14: =TEXT(A10,"mmmdd")&"-"&TEXT(WORKDAY(A10,4),"mmmdd") -> Nov23-Nov27 | R14: =EOMONTH(V14,2) -> 46418 | S14: =P14 -> 3.32 | U14: =WORKDAY(V12,1) -> 46349 | V14: =WORKDAY(U14,4) -> 46353 | X14: =VLOOKUP(AP$4,Sheet1!$P$3:$Q$41,2,FALSE)-VLOOKUP($AQ14,Sheet1!$S$3:$T$41,2,FALSE)+HLOOKUP(AP14,$D$25:$H$26,2,FALSE) -> -4.23 | Z14: =IF(EOMONTH(AI14,0)<AP14,USG!$D$29,0) -> 0 | AA14: =IFERROR(VLOOKUP(AG14,Freight!$A$3:$F$22,MATCH("TD25",Freight!$A$3:$F$3,0),FALSE),VLOOKUP(EOMONTH(AG14,1),Freight!$A$3:$F$22,MATCH("TD25",Freight!$A$3:$F$3,0),FALSE))+$AB$28 -> 16.2825 | AB14: =SUM(X14:AA14)-S14 -> 8.7325 | AG14: =IF(AH14<TODAY()+10,"Balmo",EOMONTH(AH14,0)) -> 46356 | AH14: =U14-17 -> 46332 | AI14: =V14-17 -> 46336 | AO14: =EOMONTH(AH14,0) -> 46356 | AP14: =IF(AI14>USG!$E$25,EOMONTH(AI14,0),USG!$E$25) -> 46356 | AQ14: =EOMONTH(U14,2) -> 46418
A15: =A13+7 -> 46384 | C15: -140 | D15: =TEXT(A11,"mmmdd")&"-"&TEXT(WORKDAY(A11,4),"mmmdd") -> Nov30-Dec04 | E15: =C15/100 -> -1.4 | F15: =(E15)+F$2 -> 2.47 | G15: =(F15)+G$2 -> 5.55 | H15: =(G15)+H$2 -> 7.79 | J15: =C15-C16 -> 85 | K15: =C15-C17 -> 165 | L15: =J15+J14+J16 -> 165 | N15: =D15 -> Nov30-Dec04 | O15: =AB15 -> 6.5025 | P15: =VLOOKUP(Q15,USG!$D$1:$H$19,MATCH(USG!R15,USG!$D$1:$H$1,0),FALSE) -> 5.55 | Q15: =TEXT(A11,"mmmdd")&"-"&TEXT(WORKDAY(A11,4),"mmmdd") -> Nov30-Dec04 | R15: =EOMONTH(V15,2) -> 46446 | S15: =P15 -> 5.55 | U15: =WORKDAY(V14,1) -> 46356 | V15: =WORKDAY(U15,4) -> 46360 | X15: =VLOOKUP(AP$4,Sheet1!$P$3:$Q$41,2,FALSE)-VLOOKUP($AQ15,Sheet1!$S$3:$T$41,2,FALSE)+HLOOKUP(AP15,$D$25:$H$26,2,FALSE) -> -4.23 | Y15: 0 | Z15: =IF(EOMONTH(AI15,0)<AP15,USG!$D$29,0) -> 0 | AA15: =IFERROR(VLOOKUP(AG15,Freight!$A$3:$F$22,MATCH("TD25",Freight!$A$3:$F$3,0),FALSE),VLOOKUP(EOMONTH(AG15,1),Freight!$A$3:$F$22,MATCH("TD25",Freight!$A$3:$F$3,0),FALSE))+$AB$28 -> 16.2825 | AB15: =SUM(X15:AA15)-S15 -> 6.5025 | AG15: =IF(AH15<TODAY()+10,"Balmo",EOMONTH(AH15,0)) -> 46356 | AH15: =U15-17 -> 46339 | AI15: =V15-17 -> 46343 | AO15: =EOMONTH(AH15,0) -> 46356 | AP15: =IF(AI15>USG!$E$25,EOMONTH(AI15,0),USG!$E$25) -> 46356 | AQ15: =EOMONTH(U15,2) -> 46418
A16: =A15+7 -> 46391 | C16: -225 | D16: =TEXT(A12,"mmmdd")&"-"&TEXT(WORKDAY(A12,4),"mmmdd") -> Dec07-Dec11 | E16: =C16/100 -> -2.25 | F16: =(E16)+F$2 -> 1.62 | G16: =(F16)+G$2 -> 4.7 | H16: =(G16)+H$2 -> 6.94 | J16: =C16-C17 -> 80 | K16: =J16+J17 -> 150 | L16: =J16+J17+J18 -> -225 | N16: =D16 -> Dec07-Dec11 | O16: =AB16 -> 10.4325 | P16: =VLOOKUP(Q16,USG!$D$1:$H$19,MATCH(USG!R16,USG!$D$1:$H$1,0),FALSE) -> 4.7 | Q16: =TEXT(A12,"mmmdd")&"-"&TEXT(WORKDAY(A12,4),"mmmdd") -> Dec07-Dec11 | R16: =EOMONTH(V16,2) -> 46446 | S16: =P16 -> 4.7 | U16: =WORKDAY(V15,1) -> 46363 | V16: =WORKDAY(U16,4) -> 46367 | X16: =VLOOKUP(AP$4,Sheet1!$P$3:$Q$41,2,FALSE)-VLOOKUP($AQ16,Sheet1!$S$3:$T$41,2,FALSE)+HLOOKUP(AP16,$D$25:$H$26,2,FALSE) -> -1.15 | Y16: 0 | Z16: =IF(EOMONTH(AI16,0)<AP16,USG!$D$29,0) -> 0 | AA16: =IFERROR(VLOOKUP(AG16,Freight!$A$3:$F$22,MATCH("TD25",Freight!$A$3:$F$3,0),FALSE),VLOOKUP(EOMONTH(AG16,1),Freight!$A$3:$F$22,MATCH("TD25",Freight!$A$3:$F$3,0),FALSE))+$AB$28 -> 16.2825 | AB16: =SUM(X16:AA16)-S16 -> 10.4325 | AG16: =IF(AH16<TODAY()+10,"Balmo",EOMONTH(AH16,0)) -> 46356 | AH16: =U16-17 -> 46346 | AI16: =V16-17 -> 46350 | AO16: =EOMONTH(AH16,0) -> 46356 | AP16: =IF(AI16>USG!$E$25,EOMONTH(AI16,0),USG!$E$25) -> 46356 | AQ16: =EOMONTH(U16,2) -> 46446
A17: =A16+7 -> 46398 | C17: -305 | D17: =TEXT(A14,"mmmdd")&"-"&TEXT(WORKDAY(A14,4),"mmmdd") -> Dec14-Dec18 | E17: =C17/100 -> -3.05 | F17: =(E17)+F$2 -> 0.82 | G17: =(F17)+G$2 -> 3.9 | H17: =(G17)+H$2 -> 6.14 | J17: =C17-C18 -> 70 | K17: =J17+J18 -> -305 | L17: =J17+J18+J20 -> -305 | N17: =D17 -> Dec14-Dec18 | O17: =AB17 -> 10.8825 | P17: =VLOOKUP(Q17,USG!$D$1:$H$19,MATCH(USG!R17,USG!$D$1:$H$1,0),FALSE) -> 3.9 | Q17: =TEXT(A14,"mmmdd")&"-"&TEXT(WORKDAY(A14,4),"mmmdd") -> Dec14-Dec18 | R17: =EOMONTH(V17,2) -> 46446 | S17: =P17 -> 3.9 | U17: =WORKDAY(V16,1) -> 46370 | V17: =WORKDAY(U17,4) -> 46374 | X17: =VLOOKUP(AP$4,Sheet1!$P$3:$Q$41,2,FALSE)-VLOOKUP($AQ17,Sheet1!$S$3:$T$41,2,FALSE)+HLOOKUP(AP17,$D$25:$H$26,2,FALSE) -> -1.5 | Y17: 0 | Z17: =IF(EOMONTH(AI17,0)<AP17,USG!$D$29,0) -> 0 | AA17: =IFERROR(VLOOKUP(AG17,Freight!$A$3:$F$22,MATCH("TD25",Freight!$A$3:$F$3,0),FALSE),VLOOKUP(EOMONTH(AG17,1),Freight!$A$3:$F$22,MATCH("TD25",Freight!$A$3:$F$3,0),FALSE))+$AB$28 -> 16.2825 | AB17: =SUM(X17:AA17)-S17 -> 10.8825 | AG17: =IF(AH17<TODAY()+10,"Balmo",EOMONTH(AH17,0)) -> 46356 | AH17: =U17-17 -> 46353 | AI17: =V17-17 -> 46357 | AO17: =EOMONTH(AH17,0) -> 46356 | AP17: =IF(AI17>USG!$E$25,EOMONTH(AI17,0),USG!$E$25) -> 46387 | AQ17: =EOMONTH(U17,2) -> 46446
C18: -375 | D18: =TEXT(A13,"mmmdd")&"-"&TEXT(WORKDAY(A13,4),"mmmdd") -> Dec21-Dec25 | E18: =C18/100 -> -3.75 | F18: =(E18)+F$2 -> 0.12 | G18: =(F18)+G$2 -> 3.2 | H18: =(G18)+H$2 -> 5.44 | J18: =C18-C20 -> -375 | K18: =J18+J20 -> -375 | L18: =J18+J20+J21 -> -375 | N18: =D18 -> Dec21-Dec25 | O18: =AB18 -> 8.1473 | P18: =VLOOKUP(Q18,USG!$D$1:$H$19,MATCH(USG!R18,USG!$D$1:$H$1,0),FALSE) -> 3.2 | Q18: =TEXT(A13,"mmmdd")&"-"&TEXT(WORKDAY(A13,4),"mmmdd") -> Dec21-Dec25 | R18: =EOMONTH(V18,2) -> 46446 | S18: =P18 -> 3.2 | U18: =WORKDAY(V17,1) -> 46377 | V18: =WORKDAY(U18,4) -> 46381 | X18: =VLOOKUP(AP$4,Sheet1!$P$3:$Q$41,2,FALSE)-VLOOKUP($AQ18,Sheet1!$S$3:$T$41,2,FALSE)+HLOOKUP(AP18,$D$25:$H$26,2,FALSE) -> -1.5 | Y18: 0 | Z18: =IF(EOMONTH(AI18,0)<AP18,USG!$D$29,0) -> 0 | AA18: =IFERROR(VLOOKUP(AG18,Freight!$A$3:$F$22,MATCH("TD25",Freight!$A$3:$F$3,0),FALSE),VLOOKUP(EOMONTH(AG18,1),Freight!$A$3:$F$22,MATCH("TD25",Freight!$A$3:$F$3,0),FALSE))+$AB$28 -> 12.8473 | AB18: =SUM(X18:AA18)-S18 -> 8.1473 | AG18: =IF(AH18<TODAY()+10,"Balmo",EOMONTH(AH18,0)) -> 46387 | AH18: =U18-17 -> 46360 | AI18: =V18-17 -> 46364 | AO18: =EOMONTH(AH18,0) -> 46387 | AP18: =IF(AI18>USG!$E$25,EOMONTH(AI18,0),USG!$E$25) -> 46387 | AQ18: =EOMONTH(U18,2) -> 46446
D19: Full Month | E19: =AVERAGE(E15:E18) -> -2.6125 | F19: =AVERAGE(F15:F18,F13) -> 1.67 | G19: =AVERAGE(G15:G18,G13) -> 4.75 | H19: =AVERAGE(H15:H18) -> 6.5775 | N19: Full Month | O19: =AVERAGE(O15:O18) -> 8.9912
Q20: CFD Weeker | R20: vs. ICE Brent | S20: Diff | U20: Delivery Window | X20: MEH/Brent | Y20: FOB Premium | Z20: Cash Roll | AA20: Freight+Cost | AB20: Curve Value | AD20: Platts Window | AH20: USGC Load Window | AO20: =EOMONTH(AH21,0) -> #NUM! | AP20: =IF(AI21>USG!$E$25,EOMONTH(AI21,0),USG!$E$25) -> 46356 | AQ20: =EOMONTH(U20,2) -> #VALUE! | AS20: =WORKDAY(AT20,-1) -> #NUM! | AT20: =WORKDAY(AU20,-1) -> #NUM! | AU20: =WORKDAY(U22,-1) -> #NUM! | AV20: =WORKDAY(AU20,1) -> #NUM! | AW20: =WORKDAY(AV20,1) -> #NUM! | AX20: =IF(AI23>USG!$E$25,EOMONTH(AI23,0),USG!$E$25) -> 46356
Q21: Gunvor | R21: =EOMONTH(V21,2) -> 91 | S21: 0.88 | X21: =VLOOKUP(AP$21,Sheet1!$P$3:$Q$41,2,FALSE)-VLOOKUP(EOMONTH($AP4,2),Sheet1!$S$3:$T$41,2,FALSE)+HLOOKUP(AP4,$K$24:$O$25,2,FALSE) -> #N/A | Y21: =AD21-AB21 -> #NUM! | Z21: =$Z$4 -> 3 | AA21: =IFERROR(VLOOKUP(EOMONTH(AH21,0),Freight!$A$3:$F$22,MATCH("TD25",Freight!$A$3:$F$3,0),FALSE),VLOOKUP(EOMONTH(AH21,1),Freight!$A$3:$F$22,MATCH("TD25",Freight!$A$3:$F$3,0),FALSE))+$AB$28 -> #NUM! | AB21: =SUM(Z21:AA21)-S21+X21 -> #NUM! | AD21: 1.2 | AE21: =AS18 -> 0 | AF21: =AW18 -> 0 | AH21: =U21-17 -> -17 | AI21: =V21-17 -> -17 | AO21: =EOMONTH(AH23,0) -> #NUM! | AP21: =IF(AI23>USG!$E$25,EOMONTH(AI23,0),USG!$E$25) -> 46356 | AQ21: =EOMONTH(U21,2) -> 91 | AS21: =WORKDAY(AT21,-1) -> #NUM! | AT21: =WORKDAY(AU21,-1) -> #NUM! | AU21: =WORKDAY(U23,-1) -> #NUM! | AV21: =WORKDAY(AU21,1) -> #NUM! | AW21: =WORKDAY(AV21,1) -> #NUM! | AX21: =IF(AI24>USG!$E$25,EOMONTH(AI24,0),USG!$E$25) -> 46356 | BS21: =3-E51 -> 24.4
Q22: Gunvor | R22: =EOMONTH(V22,2) -> 91 | S22: 0.86 | X22: =VLOOKUP(AP$21,Sheet1!$P$3:$Q$41,2,FALSE)-VLOOKUP(EOMONTH($AP5,2),Sheet1!$S$3:$T$41,2,FALSE)+HLOOKUP(AP5,$K$24:$O$25,2,FALSE) -> #N/A | Y22: =AD22-AB22 -> #NUM! | Z22: =$Z$4 -> 3 | AA22: =IFERROR(VLOOKUP(EOMONTH(AH22,0),Freight!$A$3:$F$22,MATCH("TD25",Freight!$A$3:$F$3,0),FALSE),VLOOKUP(EOMONTH(AH22,1),Freight!$A$3:$F$22,MATCH("TD25",Freight!$A$3:$F$3,0),FALSE))+$AB$28 -> #NUM! | AB22: =SUM(Z22:AA22)-S22+X22 -> #NUM! | AD22: 1.2 | AE22: =AS20 -> #NUM! | AF22: =AW20 -> #NUM! | AH22: =U22-17 -> -17 | AI22: =V22-17 -> -17 | AO22: =EOMONTH(AH24,0) -> #NUM! | AP22: =IF(AI24>USG!$E$25,EOMONTH(AI24,0),USG!$E$25) -> 46356 | AQ22: =EOMONTH(U22,2) -> 91 | AS22: =WORKDAY(AT22,-1) -> #NUM! | AT22: =WORKDAY(AU22,-1) -> #NUM! | AU22: =WORKDAY(U24,-1) -> #NUM! | AV22: =WORKDAY(AU22,1) -> #NUM! | AW22: =WORKDAY(AV22,1) -> #NUM! | AX22: =IF(AI25>USG!$E$25,EOMONTH(AI25,0),USG!$E$25) -> 46356
X23: =VLOOKUP(AP$21,Sheet1!$P$3:$Q$41,2,FALSE)-VLOOKUP(EOMONTH($AP6,2),Sheet1!$S$3:$T$41,2,FALSE)+HLOOKUP(AP6,$K$24:$O$25,2,FALSE) -> #N/A | Y23: =AD23-AB23 -> #NUM! | Z23: =$Z$4 -> 3 | AA23: =IFERROR(VLOOKUP(EOMONTH(AH23,0),Freight!$A$3:$F$22,MATCH("TD25",Freight!$A$3:$F$3,0),FALSE),VLOOKUP(EOMONTH(AH23,1),Freight!$A$3:$F$22,MATCH("TD25",Freight!$A$3:$F$3,0),FALSE))+$AB$28 -> #NUM! | AB23: =SUM(Z23:AA23)-S23+X23 -> #NUM! | AD23: 1.2 | AE23: =AS21 -> #NUM! | AF23: =AW21 -> #NUM! | AH23: =U23-17 -> -17 | AI23: =V23-17 -> -17 | AO23: =EOMONTH(AH24,0) -> #NUM! | AP23: =IF(AI24>USG!$E$25,EOMONTH(AI24,0),USG!$E$25) -> 46356 | AQ23: =EOMONTH(U23,2) -> 91 | AS23: =WORKDAY(AT23,-1) -> #NUM! | AT23: =WORKDAY(AU23,-1) -> #NUM! | AU23: =WORKDAY(U25,-1) -> #NUM! | AV23: =WORKDAY(AU23,1) -> #NUM! | AW23: =WORKDAY(AV23,1) -> #NUM! | AX23: =IF(AI25>USG!$E$25,EOMONTH(AI25,0),USG!$E$25) -> 46356
B24: =Sheet1!AB4 -> 2.58 | C24: MID/MEH | D24: =Sheet1!B7-Sheet1!B8 -> #VALUE! | E24: =Sheet1!C7-Sheet1!C8 -> 3.25 | F24: =Sheet1!D7-Sheet1!D8 -> 0.65 | G24: =Sheet1!E7-Sheet1!E8 -> 0.65 | H24: =Sheet1!F7-Sheet1!F8 -> 0.55 | I24: =Sheet1!G7-Sheet1!G8 -> 0.55 | J24: =Sheet1!H7-Sheet1!H8 -> 0.55 | K24: =Sheet1!I7-Sheet1!I8 -> 0.6 | L24: =Sheet1!J7-Sheet1!J8 -> 0.6 | AH24: =U24-17 -> -17 | AO24: =EOMONTH(AH25,0) -> #NUM! | AP24: =IF(AI25>USG!$E$25,EOMONTH(AI25,0),USG!$E$25) -> 46356 | AQ24: =EOMONTH(U24,2) -> 91 | AS24: =WORKDAY(AT24,-1) -> #NUM! | AT24: =WORKDAY(AU24,-1) -> #NUM! | AU24: =WORKDAY(U26,-1) -> #NUM! | AV24: =WORKDAY(AU24,1) -> #NUM! | AW24: =WORKDAY(AV24,1) -> #NUM! | AX24: =IF(AI26>USG!$E$25,EOMONTH(AI26,0),USG!$E$25) -> 46356
C25: MEH | D25: =E25 -> 46356 | E25: =Sheet1!P3 -> 46356 | F25: =EOMONTH(E25,1) -> 46387 | G25: =EOMONTH(F25,1) -> 46418 | H25: =EOMONTH(G25,1) -> 46446 | I25: =EOMONTH(H25,1) -> 46477 | J25: =EOMONTH(I25,1) -> 46507 | K25: =EOMONTH(J25,1) -> 46538 | L25: =EOMONTH(K25,1) -> 46568 | AH25: =U25-17 -> -17 | AS25: =WORKDAY(AT25,-1) -> #NUM! | AT25: =WORKDAY(AU25,-1) -> #NUM! | AU25: =WORKDAY(U27,-1) -> #NUM! | AV25: =WORKDAY(AU25,1) -> #NUM! | AW25: =WORKDAY(AV25,1) -> #NUM! | AX25: =IF(AI27>USG!$E$25,EOMONTH(AI27,0),USG!$E$25) -> 46356
C26: HTT | D26: =E26 -> 1.25 | E26: 1.25 | F26: =E26+(-INDEX(Sheet1!$B$6:$N$18,MATCH("MEH",Sheet1!$B$6:$B$18,0),MATCH(EOMONTH(E25,-1)+1,Sheet1!$B$5:$N$5,0))+INDEX(Sheet1!$B$6:$N$18,MATCH("MEH",Sheet1!$B$6:$B$18,0),MATCH(EOMONTH(F25,-1)+1,Sheet1!$B$5:$N$5,0))) -> 0.9 | G26: =F26+(-INDEX(Sheet1!$B$6:$N$18,MATCH("MEH",Sheet1!$B$6:$B$18,0),MATCH(EOMONTH(F25,-1)+1,Sheet1!$B$5:$N$5,0))+INDEX(Sheet1!$B$6:$N$18,MATCH("MEH",Sheet1!$B$6:$B$18,0),MATCH(EOMONTH(G25,-1)+1,Sheet1!$B$5:$N$5,0))) -> 1.1 | H26: =G26+(-INDEX(Sheet1!$B$6:$N$18,MATCH("MEH",Sheet1!$B$6:$B$18,0),MATCH(EOMONTH(G25,-1)+1,Sheet1!$B$5:$N$5,0))+INDEX(Sheet1!$B$6:$N$18,MATCH("MEH",Sheet1!$B$6:$B$18,0),MATCH(EOMONTH(H25,-1)+1,Sheet1!$B$5:$N$5,0))) -> 1.3 | I26: =H26+(-INDEX(Sheet1!$B$6:$N$18,MATCH("MEH",Sheet1!$B$6:$B$18,0),MATCH(EOMONTH(H25,-1)+1,Sheet1!$B$5:$N$5,0))+INDEX(Sheet1!$B$6:$N$18,MATCH("MEH",Sheet1!$B$6:$B$18,0),MATCH(EOMONTH(I25,-1)+1,Sheet1!$B$5:$N$5,0))) -> 1.45 | J26: =I26+(-INDEX(Sheet1!$B$6:$N$18,MATCH("MEH",Sheet1!$B$6:$B$18,0),MATCH(EOMONTH(I25,-1)+1,Sheet1!$B$5:$N$5,0))+INDEX(Sheet1!$B$6:$N$18,MATCH("MEH",Sheet1!$B$6:$B$18,0),MATCH(EOMONTH(J25,-1)+1,Sheet1!$B$5:$N$5,0))) -> 1.65 | K26: =J26+(-INDEX(Sheet1!$B$6:$N$18,MATCH("MEH",Sheet1!$B$6:$B$18,0),MATCH(EOMONTH(J25,-1)+1,Sheet1!$B$5:$N$5,0))+INDEX(Sheet1!$B$6:$N$18,MATCH("MEH",Sheet1!$B$6:$B$18,0),MATCH(EOMONTH(K25,-1)+1,Sheet1!$B$5:$N$5,0))) -> 1.7 | L26: =K26+(-INDEX(Sheet1!$B$6:$N$18,MATCH("MEH",Sheet1!$B$6:$B$18,0),MATCH(EOMONTH(K25,-1)+1,Sheet1!$B$5:$N$5,0))+INDEX(Sheet1!$B$6:$N$18,MATCH("MEH",Sheet1!$B$6:$B$18,0),MATCH(EOMONTH(L25,-1)+1,Sheet1!$B$5:$N$5,0))) -> 1.75
C27: WTI | BM27: 1.25 | BN27: 1
C28: PREMIUM | E28: 0.3 | F28: 0 | AB28: 0.18
C29: CASH | D29: 3
C30: CASH PREMIUM | Y30: FOB | Z30: -3
Y31: Aug DFL | Z31: -0.16
C32: =EOMONTH(C33,-1) -> 46356 | D32: =VLOOKUP(D$25,Sheet1!$P$3:$Q$41,2,FALSE)+D$26-VLOOKUP($C32,Sheet1!$S$3:$T$41,2,FALSE)+D28+D29 -> #N/A | E32: =VLOOKUP(E$25,Sheet1!$P$3:$Q$41,2,FALSE)+E$26-VLOOKUP($C32,Sheet1!$S$3:$T$41,2,FALSE) -> #N/A | F32: =VLOOKUP(F$25,Sheet1!$P$3:$Q$41,2,FALSE)+F$26-VLOOKUP($C32,Sheet1!$S$3:$T$41,2,FALSE) -> #N/A | P32: =E25 -> 46356 | Q32: TD25 | R32: TD7 | S32: CIF Rdam | U32: CIF Nsea | V32: Open/Closed | Y32: Oct Arbs | Z32: -4.2
C33: =EOMONTH(E25,1) -> 46387 | D33: =VLOOKUP(D$25,Sheet1!$P$3:$Q$41,2,FALSE)+D$26-VLOOKUP($C33,Sheet1!$S$3:$T$41,2,FALSE)+$D$29+$D$30 -> -5.1 | E33: =VLOOKUP(E$25,Sheet1!$P$3:$Q$41,2,FALSE)+E$26-VLOOKUP($C33,Sheet1!$S$3:$T$41,2,FALSE) -> -8.1 | F33: =VLOOKUP(F$25,Sheet1!$P$3:$Q$41,2,FALSE)+F$26-VLOOKUP($C33,Sheet1!$S$3:$T$41,2,FALSE) -> -10.51 | G33: =VLOOKUP(G$25,Sheet1!$P$3:$Q$41,2,FALSE)+G$26-VLOOKUP($C33,Sheet1!$S$3:$T$41,2,FALSE) -> -12.4 | H33: =VLOOKUP(H$25,Sheet1!$P$3:$Q$41,2,FALSE)+H$26-VLOOKUP($C33,Sheet1!$S$3:$T$41,2,FALSE) -> -14.3 | I33: =VLOOKUP(I$25,Sheet1!$P$3:$Q$41,2,FALSE)+I$26-VLOOKUP($C33,Sheet1!$S$3:$T$41,2,FALSE) -> -16.11 | J33: =VLOOKUP(J$25,Sheet1!$P$3:$Q$41,2,FALSE)+J$26-VLOOKUP($C33,Sheet1!$S$3:$T$41,2,FALSE) -> -17.57 | K33: =VLOOKUP(K$25,Sheet1!$P$3:$Q$41,2,FALSE)+K$26-VLOOKUP($C33,Sheet1!$S$3:$T$41,2,FALSE) -> -18.88 | L33: =VLOOKUP(L$25,Sheet1!$P$3:$Q$41,2,FALSE)+L$26-VLOOKUP($C33,Sheet1!$S$3:$T$41,2,FALSE) -> -20.09 | Y33: Sep/Oct WTI | Z33: 0.5
C34: =EOMONTH(C33,1) -> 46418 | D34: =VLOOKUP(D$25,Sheet1!$P$3:$Q$41,2,FALSE)+D$26-VLOOKUP($C34,Sheet1!$S$3:$T$41,2,FALSE)+$D$29+$D$30 -> -1.23 | E34: =VLOOKUP(E$25,Sheet1!$P$3:$Q$41,2,FALSE)+E$26-VLOOKUP($C34,Sheet1!$S$3:$T$41,2,FALSE)+$E$28 -> -3.93 | F34: =VLOOKUP(F$25,Sheet1!$P$3:$Q$41,2,FALSE)+F$26-VLOOKUP($C34,Sheet1!$S$3:$T$41,2,FALSE) -> -6.64 | G34: =VLOOKUP(G$25,Sheet1!$P$3:$Q$41,2,FALSE)+G$26-VLOOKUP($C34,Sheet1!$S$3:$T$41,2,FALSE) -> -8.53 | H34: =VLOOKUP(H$25,Sheet1!$P$3:$Q$41,2,FALSE)+H$26-VLOOKUP($C34,Sheet1!$S$3:$T$41,2,FALSE)+H$28 -> -10.43 | I34: =VLOOKUP(I$25,Sheet1!$P$3:$Q$41,2,FALSE)+I$26-VLOOKUP($C34,Sheet1!$S$3:$T$41,2,FALSE)+I$28 -> -12.24 | J34: =VLOOKUP(J$25,Sheet1!$P$3:$Q$41,2,FALSE)+J$26-VLOOKUP($C34,Sheet1!$S$3:$T$41,2,FALSE)+J$28 -> -13.7 | K34: =VLOOKUP(K$25,Sheet1!$P$3:$Q$41,2,FALSE)+K$26-VLOOKUP($C34,Sheet1!$S$3:$T$41,2,FALSE)+K$28 -> -15.01 | L34: =VLOOKUP(L$25,Sheet1!$P$3:$Q$41,2,FALSE)+L$26-VLOOKUP($C34,Sheet1!$S$3:$T$41,2,FALSE)+L$28 -> -16.22 | Y34: vs Sep WTI | Z34: =Z30+Z31-Z32-Z33 -> 0.54
C35: =EOMONTH(C34,1) -> 46446 | D35: =VLOOKUP(D$25,Sheet1!$P$3:$Q$41,2,FALSE)+D$26-VLOOKUP($C35,Sheet1!$S$3:$T$41,2,FALSE)+$D$29+$D$30 -> 1.85 | E35: =VLOOKUP(E$25,Sheet1!$P$3:$Q$41,2,FALSE)+E$26-VLOOKUP($C35,Sheet1!$S$3:$T$41,2,FALSE)+$E$28 -> -0.85 | F35: =VLOOKUP(F$25,Sheet1!$P$3:$Q$41,2,FALSE)+F$26-VLOOKUP($C35,Sheet1!$S$3:$T$41,2,FALSE)+F$28 -> -3.56 | G35: =VLOOKUP(G$25,Sheet1!$P$3:$Q$41,2,FALSE)+G$26-VLOOKUP($C35,Sheet1!$S$3:$T$41,2,FALSE)+G$28 -> -5.45 | H35: =VLOOKUP(H$25,Sheet1!$P$3:$Q$41,2,FALSE)+H$26-VLOOKUP($C35,Sheet1!$S$3:$T$41,2,FALSE)+H$28 -> -7.35 | I35: =VLOOKUP(I$25,Sheet1!$P$3:$Q$41,2,FALSE)+I$26-VLOOKUP($C35,Sheet1!$S$3:$T$41,2,FALSE)+I$28 -> -9.16 | J35: =VLOOKUP(J$25,Sheet1!$P$3:$Q$41,2,FALSE)+J$26-VLOOKUP($C35,Sheet1!$S$3:$T$41,2,FALSE)+J$28 -> -10.62 | K35: =VLOOKUP(K$25,Sheet1!$P$3:$Q$41,2,FALSE)+K$26-VLOOKUP($C35,Sheet1!$S$3:$T$41,2,FALSE)+K$28 -> -11.93 | L35: =VLOOKUP(L$25,Sheet1!$P$3:$Q$41,2,FALSE)+L$26-VLOOKUP($C35,Sheet1!$S$3:$T$41,2,FALSE)+L$28 -> -13.14 | O35: 46356 | P35: =D33 -> -5.1 | Q35: =P59 -> 460.5 | R35: =Q62 -> 300 | S35: =P35+(Q35*21.47*70/700/100) -> 4.786935 | U35: =7.25*R35*86.7/100/700 -> 2.6938929 | V35: =U35-S35 -> -2.0930421
C36: =EOMONTH(C35,1) -> 46477 | D36: =VLOOKUP(D$25,Sheet1!$P$3:$Q$41,2,FALSE)+D$26-VLOOKUP($C36,Sheet1!$S$3:$T$41,2,FALSE)+$D$29+$D$30 -> 4.17 | E36: =VLOOKUP(E$25,Sheet1!$P$3:$Q$41,2,FALSE)+E$26-VLOOKUP($C36,Sheet1!$S$3:$T$41,2,FALSE)+$E$28 -> 1.47 | F36: =VLOOKUP(F$25,Sheet1!$P$3:$Q$41,2,FALSE)+F$26-VLOOKUP($C36,Sheet1!$S$3:$T$41,2,FALSE)+F$28 -> -1.24 | G36: =VLOOKUP(G$25,Sheet1!$P$3:$Q$41,2,FALSE)+G$26-VLOOKUP($C36,Sheet1!$S$3:$T$41,2,FALSE)+G$28 -> -3.13 | H36: =VLOOKUP(H$25,Sheet1!$P$3:$Q$41,2,FALSE)+H$26-VLOOKUP($C36,Sheet1!$S$3:$T$41,2,FALSE)+H$28 -> -5.03 | I36: =VLOOKUP(I$25,Sheet1!$P$3:$Q$41,2,FALSE)+I$26-VLOOKUP($C36,Sheet1!$S$3:$T$41,2,FALSE)+I$28 -> -6.84 | J36: =VLOOKUP(J$25,Sheet1!$P$3:$Q$41,2,FALSE)+J$26-VLOOKUP($C36,Sheet1!$S$3:$T$41,2,FALSE)+J$28 -> -8.3 | K36: =VLOOKUP(K$25,Sheet1!$P$3:$Q$41,2,FALSE)+K$26-VLOOKUP($C36,Sheet1!$S$3:$T$41,2,FALSE)+K$28 -> -9.61 | L36: =VLOOKUP(L$25,Sheet1!$P$3:$Q$41,2,FALSE)+L$26-VLOOKUP($C36,Sheet1!$S$3:$T$41,2,FALSE)+L$28 -> -10.82 | Y36: Freight | Z36: =+AA36/950 -> 3.6842105 | AA36: 3500
C37: =EOMONTH(C36,1) -> 46507 | D37: =VLOOKUP(D$25,Sheet1!$P$3:$Q$41,2,FALSE)+D$26-VLOOKUP($C37,Sheet1!$S$3:$T$41,2,FALSE)+$D$29+$D$30 -> 6.08 | E37: =VLOOKUP(E$25,Sheet1!$P$3:$Q$41,2,FALSE)+E$26-VLOOKUP($C37,Sheet1!$S$3:$T$41,2,FALSE)+$E$28 -> 3.38 | F37: =VLOOKUP(F$25,Sheet1!$P$3:$Q$41,2,FALSE)+F$26-VLOOKUP($C37,Sheet1!$S$3:$T$41,2,FALSE)+F$28 -> 0.67 | G37: =VLOOKUP(G$25,Sheet1!$P$3:$Q$41,2,FALSE)+G$26-VLOOKUP($C37,Sheet1!$S$3:$T$41,2,FALSE)+G$28 -> -1.22 | H37: =VLOOKUP(H$25,Sheet1!$P$3:$Q$41,2,FALSE)+H$26-VLOOKUP($C37,Sheet1!$S$3:$T$41,2,FALSE)+H$28 -> -3.12 | I37: =VLOOKUP(I$25,Sheet1!$P$3:$Q$41,2,FALSE)+I$26-VLOOKUP($C37,Sheet1!$S$3:$T$41,2,FALSE)+I$28 -> -4.93 | J37: =VLOOKUP(J$25,Sheet1!$P$3:$Q$41,2,FALSE)+J$26-VLOOKUP($C37,Sheet1!$S$3:$T$41,2,FALSE)+J$28 -> -6.39 | K37: =VLOOKUP(K$25,Sheet1!$P$3:$Q$41,2,FALSE)+K$26-VLOOKUP($C37,Sheet1!$S$3:$T$41,2,FALSE)+K$28 -> -7.7 | L37: =VLOOKUP(L$25,Sheet1!$P$3:$Q$41,2,FALSE)+L$26-VLOOKUP($C37,Sheet1!$S$3:$T$41,2,FALSE)+L$28 -> -8.91 | O37: 46387 | P37: =F33 -> -10.51 | Q37: =AVERAGE(P61:P62) -> 670 | R37: =R35 -> 300 | S37: =P37+(Q37*21.47*70/700/100) -> 3.8749 | U37: =7.25*R37*86.7/100/700 -> 2.6938929 | V37: =U37-S37 -> -1.1810071 | Y37: Secondary | Z37: 0.6 | BA37: 700 | BB37: -1.6 | BC37: 0.89 | BD37: =SUM(BB37:BC37) -> -0.71 | BE37: 0.1
B38: ICE Brent | C38: =EOMONTH(C37,1) -> 46538 | D38: =VLOOKUP(D$25,Sheet1!$P$3:$Q$41,2,FALSE)+D$26-VLOOKUP($C38,Sheet1!$S$3:$T$41,2,FALSE)+$D$29+$D$30 -> 7.77 | E38: =VLOOKUP(E$25,Sheet1!$P$3:$Q$41,2,FALSE)+E$26-VLOOKUP($C38,Sheet1!$S$3:$T$41,2,FALSE)+$E$28 -> 5.07 | F38: =VLOOKUP(F$25,Sheet1!$P$3:$Q$41,2,FALSE)+F$26-VLOOKUP($C38,Sheet1!$S$3:$T$41,2,FALSE)+F$28 -> 2.36 | G38: =VLOOKUP(G$25,Sheet1!$P$3:$Q$41,2,FALSE)+G$26-VLOOKUP($C38,Sheet1!$S$3:$T$41,2,FALSE)+G$28 -> 0.47 | H38: =VLOOKUP(H$25,Sheet1!$P$3:$Q$41,2,FALSE)+H$26-VLOOKUP($C38,Sheet1!$S$3:$T$41,2,FALSE)+H$28 -> -1.43 | I38: =VLOOKUP(I$25,Sheet1!$P$3:$Q$41,2,FALSE)+I$26-VLOOKUP($C38,Sheet1!$S$3:$T$41,2,FALSE)+I$28 -> -3.24 | J38: =VLOOKUP(J$25,Sheet1!$P$3:$Q$41,2,FALSE)+J$26-VLOOKUP($C38,Sheet1!$S$3:$T$41,2,FALSE)+J$28 -> -4.7 | K38: =VLOOKUP(K$25,Sheet1!$P$3:$Q$41,2,FALSE)+K$26-VLOOKUP($C38,Sheet1!$S$3:$T$41,2,FALSE)+K$28 -> -6.01 | L38: =VLOOKUP(L$25,Sheet1!$P$3:$Q$41,2,FALSE)+L$26-VLOOKUP($C38,Sheet1!$S$3:$T$41,2,FALSE)+L$28 -> -7.22 | O38: 46387 | P38: =F34 -> -6.64 | Q38: =P62 -> 590 | R38: =R37 -> 300 | S38: =P38+(Q38*21.47*70/700/100) -> 6.0273 | U38: =7.25*R38*86.7/100/700 -> 2.6938929 | V38: =U38-S38 -> -3.3334071 | Y38: Liza CFR USG | Z38: =Z36+Z34+Z37 -> 4.8242105 | BA38: 700 | BB38: -1.6 | BC38: 0.89 | BD38: =SUM(BB38:BC38) -> -0.71 | BE38: 0.1
C39: =EOMONTH(C38,1) -> 46568 | D39: =VLOOKUP(D$25,Sheet1!$P$3:$Q$41,2,FALSE)+D$26-VLOOKUP($C39,Sheet1!$S$3:$T$41,2,FALSE)+$D$29+$D$30 -> 9.3 | E39: =VLOOKUP(E$25,Sheet1!$P$3:$Q$41,2,FALSE)+E$26-VLOOKUP($C39,Sheet1!$S$3:$T$41,2,FALSE)+$E$28 -> 6.6 | F39: =VLOOKUP(F$25,Sheet1!$P$3:$Q$41,2,FALSE)+F$26-VLOOKUP($C39,Sheet1!$S$3:$T$41,2,FALSE)+F$28 -> 3.89 | G39: =VLOOKUP(G$25,Sheet1!$P$3:$Q$41,2,FALSE)+G$26-VLOOKUP($C39,Sheet1!$S$3:$T$41,2,FALSE)+G$28 -> 2 | H39: =VLOOKUP(H$25,Sheet1!$P$3:$Q$41,2,FALSE)+H$26-VLOOKUP($C39,Sheet1!$S$3:$T$41,2,FALSE)+H$28 -> 0.1 | I39: =VLOOKUP(I$25,Sheet1!$P$3:$Q$41,2,FALSE)+I$26-VLOOKUP($C39,Sheet1!$S$3:$T$41,2,FALSE)+I$28 -> -1.71 | J39: =VLOOKUP(J$25,Sheet1!$P$3:$Q$41,2,FALSE)+J$26-VLOOKUP($C39,Sheet1!$S$3:$T$41,2,FALSE)+J$28 -> -3.17 | K39: =VLOOKUP(K$25,Sheet1!$P$3:$Q$41,2,FALSE)+K$26-VLOOKUP($C39,Sheet1!$S$3:$T$41,2,FALSE)+K$28 -> -4.48 | L39: =VLOOKUP(L$25,Sheet1!$P$3:$Q$41,2,FALSE)+L$26-VLOOKUP($C39,Sheet1!$S$3:$T$41,2,FALSE)+L$28 -> -5.69 | BA39: 700 | BB39: =-0.84-0.89 -> -1.73 | BD39: -0.84 | BE39: -0.13
C40: =EOMONTH(C39,1) -> 46599 | D40: =VLOOKUP(D$25,Sheet1!$P$3:$Q$41,2,FALSE)+D$26-VLOOKUP($C40,Sheet1!$S$3:$T$41,2,FALSE)+$D$29+$D$30 -> 10.7 | E40: =VLOOKUP(E$25,Sheet1!$P$3:$Q$41,2,FALSE)+E$26-VLOOKUP($C40,Sheet1!$S$3:$T$41,2,FALSE)+$E$28 -> 8 | F40: =VLOOKUP(F$25,Sheet1!$P$3:$Q$41,2,FALSE)+F$26-VLOOKUP($C40,Sheet1!$S$3:$T$41,2,FALSE)+F$28 -> 5.29 | G40: =VLOOKUP(G$25,Sheet1!$P$3:$Q$41,2,FALSE)+G$26-VLOOKUP($C40,Sheet1!$S$3:$T$41,2,FALSE)+G$28 -> 3.4 | H40: =VLOOKUP(H$25,Sheet1!$P$3:$Q$41,2,FALSE)+H$26-VLOOKUP($C40,Sheet1!$S$3:$T$41,2,FALSE)+H$28 -> 1.5 | I40: =VLOOKUP(I$25,Sheet1!$P$3:$Q$41,2,FALSE)+I$26-VLOOKUP($C40,Sheet1!$S$3:$T$41,2,FALSE)+I$28 -> -0.31 | J40: =VLOOKUP(J$25,Sheet1!$P$3:$Q$41,2,FALSE)+J$26-VLOOKUP($C40,Sheet1!$S$3:$T$41,2,FALSE)+J$28 -> -1.77 | K40: =VLOOKUP(K$25,Sheet1!$P$3:$Q$41,2,FALSE)+K$26-VLOOKUP($C40,Sheet1!$S$3:$T$41,2,FALSE)+K$28 -> -3.08 | L40: =VLOOKUP(L$25,Sheet1!$P$3:$Q$41,2,FALSE)+L$26-VLOOKUP($C40,Sheet1!$S$3:$T$41,2,FALSE)+L$28 -> -4.29 | O40: 46053 | P40: =G34 -> -8.53 | Q40: =AVERAGE(P62:P63) -> 486.57544 | R40: =Q63 -> 212.24087 | S40: =P40+(Q40*21.47*70/700/100) -> 1.9167747 | U40: =7.25*R40*86.7/100/700 -> 1.9058472 | V40: =U40-S40 -> -0.010927502 | Y40: Sep SGC | Z40: -2.5 | BB40: =AVERAGE(BB37:BB39) -> -1.6433333 | BD40: =-AVERAGE(BD37:BD39) -> 0.75333333 | BE40: {=SUMPRODUCT(BE37:BE39,BA37:BA39/SUM(BA37:BA39))} -> 0.023333333
Y41: RCV | Z41: 9.2 | AR41: Feb | AT41: March | AW41: April | AY41: June | BA41: September | BC41: October
D42: =D33-E33 -> 3 | E42: =E33-F33 -> 2.41 | F42: =F33-G33 -> 1.89 | G42: =G33-H33 -> 1.9 | H42: =H33-I33 -> 1.81 | I42: =I33-J33 -> 1.46 | J42: =J33-K33 -> 1.31 | K42: =K33-L33 -> 1.21 | L42: =L33-M33 -> -20.09 | Y42: Breakeven | Z42: =Z41+Z40 -> 6.7 | AQ42: Taiwan | AR42: =AR43+AR44 -> 9 | AT42: Taiwan | AU42: =AU43+AU44 -> 12 | AW42: Taiwan | AX42: =AX43+AX44 -> 3 | AY42: Taiwan | AZ42: =AZ43+AZ44 -> 8 | BA42: Taiwan | BB42: =BB43+BB44 -> 7 | BC42: Taiwan | BD42: =BD43+BD44 -> 3
AQ43: CPC Term | AR43: 3 | AT43: CPC Term | AU43: 3 | AW43: CPC Term | AX43: 3 | AY43: CPC Term | AZ43: 3 | BA43: CPC Term | BB43: 3 | BC43: CPC Term | BD43: 3
Y44: Margin | Z44: =Z42-Z38 -> 1.8757895 | AQ44: CPC Spot | AR44: 6 | AT44: CPC Spot | AU44: 9 | AW44: CPC Spot | AX44: 0 | AY44: CPC Spot | AZ44: 5 | BA44: CPC Spot | BB44: 4 | BC44: CPC Spot
D45: 46326 | E45: =EOMONTH(D45,1) -> 46356 | F45: =EOMONTH(E45,1) -> 46387 | G45: =EOMONTH(F45,1) -> 46418 | O45: Freight | P45: =Freight!B28 -> 46296 | AQ45: Korea | AR45: =+AR46+AR47+AR48 -> 15 | AT45: Korea | AU45: =+AU46+AU47+AU48 -> 15.4 | AW45: Korea | AX45: =+AX46+AX47+AX48 -> 11 | AY45: Korea | AZ45: =+AZ46+AZ47+AZ48 -> 11 | BA45: Korea | BB45: =+BB46+BB47+BB48 -> 16 | BC45: Korea | BD45: =+BD46+BD47+BD48 -> 7
C46: CLK US GULF | D46: 1.955 | E46: -13.5 | F46: =-8.5+1 -> -7.5 | G46: -7 | P46: Freight-TD25 | Q46: Freight-TD7 | R46: Freight-TD25 $/MT | S46: Freight-TD7 $/MT | AQ46: SK | AR46: =2+2+1+2 -> 7 | AT46: SK | AU46: 4.7 | AW46: SK | AX46: 4 | AY46: SK | AZ46: 5 | BA46: SK | BB46: 6 | BC46: SK | BD46: 7
O47: =Freight!A4 -> Balmo | P47: =_xlfn.XLOOKUP(USG!O47,Freight!$A$3:$A$22,Freight!$J$3:$J$22) -> #DIV/0! | Q47: =_xlfn.XLOOKUP(O47,Freight!$A$3:$A$22,Freight!$K$3:$K$22) -> #DIV/0! | R47: =_xlfn.XLOOKUP(O47,Freight!$A$3:$A$22,Freight!$M$3:$M$22) -> #DIV/0! | S47: =_xlfn.XLOOKUP(O47,Freight!$A$3:$A$22,Freight!$N$3:$N$22) -> #DIV/0! | AQ47: GS | AR47: =2+2+2 -> 6 | AT47: GS | AU47: 6 | AW47: GS | AX47: 4 | AY47: GS | AZ47: 2 | BA47: GS | BB47: 6 | BC47: GS | BD47: 0
K48: =D26 -> 1.25 | L48: =E26 -> 1.25 | O48: 45961 | P48: 175.15 | Q48: 145.05 | R48: 175.15 | AQ48: Hyundai | AR48: 2 | AT48: Hyundai | AU48: 4.7 | AW48: Hyundai | AX48: 3 | AY48: Hyundai | AZ48: 4 | BA48: Hyundai | BB48: =2+2 -> 4 | BC48: Hyundai | BD48: 0
C49: CLK | K49: =D29 -> 3 | O49: =EOMONTH(O48,1) -> 45991 | P49: 212.3 | Q49: 158 | R49: 212.3 | AQ49: Japan | AR49: =+AR50+AR52 -> 3 | AT49: Japan | AU49: =+AU50+AU52+AU51 -> 6 | AW49: Japan | AX49: =+AX50+AX52+AX51 -> 0 | AY49: Japan | AZ49: =+AZ50+AZ52+AZ51 -> 0 | BA49: Japan | BB49: =+BB50+BB52+BB51 -> 7 | BC49: Japan | BD49: =+BD50+BD52+BD51 -> 1
C50: =D45 -> 46326 | D50: =_xlfn.XLOOKUP(D$45,BBG!$B$63:$B$101,BBG!$E$63:$E$101)-_xlfn.XLOOKUP($C50,BBG!$H$63:$H$101,BBG!$K$63:$K$101)+D$46 -> -7.965 | E50: =_xlfn.XLOOKUP(E$45,BBG!$B$63:$B$101,BBG!$E$63:$E$101)-_xlfn.XLOOKUP($C50,BBG!$H$63:$H$101,BBG!$K$63:$K$101)+E$46 -> -25.25 | F50: =_xlfn.XLOOKUP(F$45,BBG!$B$63:$B$101,BBG!$E$63:$E$101)-_xlfn.XLOOKUP($C50,BBG!$H$63:$H$101,BBG!$K$63:$K$101)+F$46 -> -21.51 | G50: =_xlfn.XLOOKUP(G$45,BBG!$B$63:$B$101,BBG!$E$63:$E$101)-_xlfn.XLOOKUP($C50,BBG!$H$63:$H$101,BBG!$K$63:$K$101)+G$46 -> -23.18 | K50: 0.15 | L50: =K51-L48 -> 3.15 | O50: =EOMONTH(O49,1) -> 46022 | P50: 208.93 | Q50: 160 | R50: 44.98 | S50: 16.61 | AQ50: Taiyo | AR50: 2 | AT50: Taiyo | AU50: 2 | AW50: Taiyo | AX50: 0 | AY50: Taiyo | AZ50: 0 | BA50: Taiyo | BB50: 2 | BC50: Taiyo | BD50: 1
C51: =EOMONTH(C50,1) -> 46356 | D51: =_xlfn.XLOOKUP(D$45,BBG!$B$63:$B$101,BBG!$E$63:$E$101)-_xlfn.XLOOKUP($C51,BBG!$H$63:$H$101,BBG!$K$63:$K$101)+D$46 -> -4.115 | E51: =_xlfn.XLOOKUP(E$45,BBG!$B$63:$B$101,BBG!$E$63:$E$101)-_xlfn.XLOOKUP($C51,BBG!$H$63:$H$101,BBG!$K$63:$K$101)+E$46 -> -21.4 | F51: =_xlfn.XLOOKUP(F$45,BBG!$B$63:$B$101,BBG!$E$63:$E$101)-_xlfn.XLOOKUP($C51,BBG!$H$63:$H$101,BBG!$K$63:$K$101)+F$46 -> -17.66 | G51: =_xlfn.XLOOKUP(G$45,BBG!$B$63:$B$101,BBG!$E$63:$E$101)-_xlfn.XLOOKUP($C51,BBG!$H$63:$H$101,BBG!$K$63:$K$101)+G$46 -> -19.33 | K51: =SUM(K48:K50) -> 4.4 | O51: =EOMONTH(O50,1) -> 46053 | P51: 268 | Q51: 175.25 | R51: 47.234 | S51: 18.2961 | AQ51: Cosmo | AT51: Cosmo | AU51: 2 | AW51: Cosmo | AX51: 0 | AY51: Cosmo | AZ51: 0 | BA51: Cosmo | BB51: 2 | BC51: Cosmo | BD51: 0
C52: =EOMONTH(C51,1) -> 46387 | D52: =_xlfn.XLOOKUP(D$45,BBG!$B$63:$B$101,BBG!$E$63:$E$101)-_xlfn.XLOOKUP($C52,BBG!$H$63:$H$101,BBG!$K$63:$K$101)+D$46 -> -0.975 | E52: =_xlfn.XLOOKUP(E$45,BBG!$B$63:$B$101,BBG!$E$63:$E$101)-_xlfn.XLOOKUP($C52,BBG!$H$63:$H$101,BBG!$K$63:$K$101)+E$46 -> -18.26 | F52: =_xlfn.XLOOKUP(F$45,BBG!$B$63:$B$101,BBG!$E$63:$E$101)-_xlfn.XLOOKUP($C52,BBG!$H$63:$H$101,BBG!$K$63:$K$101)+F$46 -> -14.52 | G52: =_xlfn.XLOOKUP(G$45,BBG!$B$63:$B$101,BBG!$E$63:$E$101)-_xlfn.XLOOKUP($C52,BBG!$H$63:$H$101,BBG!$K$63:$K$101)+G$46 -> -16.19 | O52: =EOMONTH(O51,1) -> 46081 | P52: 290 | Q52: 192.5 | R52: 62.263 | S52: 20.097 | AQ52: Eneos | AR52: 1 | AT52: Eneos | AU52: 2 | AW52: Eneos | AX52: 0 | AY52: Eneos | AZ52: 0 | BA52: Eneos | BB52: 3 | BC52: Eneos | BD52: 0
C53: =EOMONTH(C52,1) -> 46418 | D53: =_xlfn.XLOOKUP(D$45,BBG!$B$63:$B$101,BBG!$E$63:$E$101)-_xlfn.XLOOKUP($C53,BBG!$H$63:$H$101,BBG!$K$63:$K$101)+D$46 -> 1.225 | E53: =_xlfn.XLOOKUP(E$45,BBG!$B$63:$B$101,BBG!$E$63:$E$101)-_xlfn.XLOOKUP($C53,BBG!$H$63:$H$101,BBG!$K$63:$K$101)+E$46 -> -16.06 | F53: =_xlfn.XLOOKUP(F$45,BBG!$B$63:$B$101,BBG!$E$63:$E$101)-_xlfn.XLOOKUP($C53,BBG!$H$63:$H$101,BBG!$K$63:$K$101)+F$46 -> -12.32 | G53: =_xlfn.XLOOKUP(G$45,BBG!$B$63:$B$101,BBG!$E$63:$E$101)-_xlfn.XLOOKUP($C53,BBG!$H$63:$H$101,BBG!$K$63:$K$101)+G$46 -> -13.99 | O53: =EOMONTH(O52,1) -> 46112 | P53: 465 | Q53: 283 | R53: 97.6965 | S53: 39.8625 | AQ53: Singapore Area | AR53: =+AR54+AR55+AR56+AR57+AR58+AR59 -> 15.1 | AT53: Singapore Area | AU53: =+AU54+AU55+AU56+AU57+AU58+AU59 -> 8 | AW53: Singapore Area | AX53: =+AX54+AX55+AX56+AX57+AX58+AX59 -> 0 | AY53: Singapore Area | AZ53: =+AZ54+AZ55+AZ56+AZ57+AZ58+AZ59 -> 3.8 | BA53: Singapore Area | BB53: =+BB54+BB55+BB56+BB57+BB58+BB59 -> 7.4 | BC53: Singapore Area | BD53: =+BD54+BD55+BD56+BD57+BD58+BD59 -> 0
O54: =EOMONTH(O53,1) -> 46142 | P54: 477.5 | Q54: 313.5 | R54: 100.32275 | S54: 22.323 | AQ54: EXXON SG | AR54: 8 | AT54: EXXON SG | AU54: 6 | AW54: EXXON SG | AX54: 0 | AY54: EXXON SG | AZ54: 0 | BA54: EXXON SG | BB54: 0 | BC54: EXXON SG | BD54: 0
O55: =EOMONTH(O54,1) -> 46173 | P55: 265.5 | Q55: 188.5 | R55: 55.78155 | S55: 20.03755 | AQ55: PTT | AR55: 4 | AT55: PTT | AU55: 2 | AW55: PTT | AX55: 0 | AY55: PTT | AZ55: 2 | BA55: PTT | BB55: 2 | BC55: PTT | BD55: 0
O56: =EOMONTH(O55,1) -> 46203 | P56: 202 | Q56: 146.75 | R56: 42.4402 | S56: 15.599525 | AQ56: SPRC | AR56: 1 | AT56: SPRC | AU56: 0 | AW56: SPRC | AX56: 0 | AY56: SPRC | AZ56: 0 | BA56: SPRC | BB56: 0 | BC56: SPRC | BD56: 0
O57: =EOMONTH(O56,1) -> 46234 | P57: 296 | Q57: 191.5 | R57: 62.1896 | S57: 20.35645 | AQ57: Ampol | AR57: 0.7 | AT57: Ampol | AU57: 0 | AW57: Ampol | AX57: 0 | AY57: Ampol | AZ57: 0 | BA57: Ampol | BB57: =0.7*2 -> 1.4 | BC57: Ampol | BD57: 0
K58: 200000000 | O58: =EOMONTH(O57,1) -> 46265 | P58: =_xlfn.XLOOKUP(USG!O58,Freight!$A$3:$A$22,Freight!$J$3:$J$22) -> #N/A | Q58: =_xlfn.XLOOKUP(O58,Freight!$A$3:$A$22,Freight!$K$3:$K$22) -> #N/A | R58: =_xlfn.XLOOKUP(O58,Freight!$A$3:$A$22,Freight!$M$3:$M$22) -> #N/A | S58: =_xlfn.XLOOKUP(O58,Freight!$A$3:$A$22,Freight!$N$3:$N$22) -> #N/A | AQ58: BSR | AR58: 0.7 | AT58: BSR | AU58: 0 | AW58: BSR | AX58: 0 | AY58: BSR | AZ58: 1.8 | BA58: BSR | BB58: =1+1 -> 2 | BC58: BSR | BD58: 0
K59: =+K58*0.03 -> 6000000 | O59: =EOMONTH(O58,1) -> 46295 | P59: 460.5 | Q59: 300 | R59: 96.75105 | S59: 31.89 | AQ59: Geelong | AR59: 0.7 | AT59: Geelong | AU59: 0 | AW59: Geelong | AX59: 0 | AY59: Geelong | AZ59: 0 | BA59: Geelong | BB59: 2 | BC59: Geelong | BD59: 0
O60: =EOMONTH(O59,1) -> 46326 | P60: =_xlfn.XLOOKUP(USG!O60,Freight!$A$3:$A$22,Freight!$J$3:$J$22) -> 795 | Q60: =_xlfn.XLOOKUP(O60,Freight!$A$3:$A$22,Freight!$K$3:$K$22) -> 400 | R60: =_xlfn.XLOOKUP(O60,Freight!$A$3:$A$22,Freight!$M$3:$M$22) -> 167.0295 | S60: =_xlfn.XLOOKUP(O60,Freight!$A$3:$A$22,Freight!$N$3:$N$22) -> 42.52 | AQ60: China | AR60: =+AR61 -> 2 | AT60: China | AU60: =+AU61 -> 0.7 | AW60: China | AX60: =+AX61 -> 0 | AY60: China | AZ60: =+AZ61 -> 0 | BA60: China | BB60: =+BB61 -> 0 | BC60: China | BD60: =+BD61 -> 0
O61: =EOMONTH(O60,1) -> 46356 | P61: =_xlfn.XLOOKUP(USG!O61,Freight!$A$3:$A$22,Freight!$J$3:$J$22) -> 750 | Q61: =_xlfn.XLOOKUP(O61,Freight!$A$3:$A$22,Freight!$K$3:$K$22) -> 350 | R61: =_xlfn.XLOOKUP(O61,Freight!$A$3:$A$22,Freight!$M$3:$M$22) -> 157.575 | S61: =_xlfn.XLOOKUP(O61,Freight!$A$3:$A$22,Freight!$N$3:$N$22) -> 37.205 | AQ61: Unipec | AR61: 2 | AT61: Unipec | AU61: 0.7 | AW61: Unipec | AX61: 0 | AY61: Unipec | AZ61: 0 | BA61: Unipec | BB61: 0 | BC61: Unipec | BD61: 0
O62: =EOMONTH(O61,1) -> 46387 | P62: =_xlfn.XLOOKUP(USG!O62,Freight!$A$3:$A$22,Freight!$J$3:$J$22) -> 590 | Q62: =_xlfn.XLOOKUP(O62,Freight!$A$3:$A$22,Freight!$K$3:$K$22) -> 300 | R62: =_xlfn.XLOOKUP(O62,Freight!$A$3:$A$22,Freight!$M$3:$M$22) -> 123.959 | S62: =_xlfn.XLOOKUP(O62,Freight!$A$3:$A$22,Freight!$N$3:$N$22) -> 31.89 | AQ62: India | AR62: =+AR63+AR67 -> 8 | AT62: India | AU62: =SUM(AU63:AU67) -> 5 | AW62: India | AX62: =SUM(AX63:AX67) -> 4 | AY62: India | AZ62: =SUM(AZ63:AZ67) -> 6 | BA62: India | BB62: =SUM(BB63:BB67) -> 9 | BC62: India | BD62: =SUM(BD63:BD67) -> 3
O63: =EOMONTH(O62,1) -> 46418 | P63: =_xlfn.XLOOKUP(USG!O63,Freight!$A$3:$A$22,Freight!$J$3:$J$22) -> 383.15088 | Q63: =_xlfn.XLOOKUP(O63,Freight!$A$3:$A$22,Freight!$K$3:$K$22) -> 212.24087 | R63: =_xlfn.XLOOKUP(O63,Freight!$A$3:$A$22,Freight!$M$3:$M$22) -> 80.5 | S63: =_xlfn.XLOOKUP(O63,Freight!$A$3:$A$22,Freight!$N$3:$N$22) -> 22.561204 | AQ63: IOC | AR63: 5 | AT63: IOC | AU63: 2 | AW63: IOC | AX63: 2 | AY63: IOC | AZ63: 2 | BA63: IOC | BB63: =2+4 -> 6 | BC63: IOC | BD63: 0
G64: 250 | H64: =G64*0.25 -> 62.5 | I64: =G64*0.17 -> 42.5 | J64: =H64+I64 -> 105 | O64: =EOMONTH(O63,1) -> 46446 | P64: =_xlfn.XLOOKUP(USG!O64,Freight!$A$3:$A$22,Freight!$J$3:$J$22) -> 368.87197 | Q64: =_xlfn.XLOOKUP(O64,Freight!$A$3:$A$22,Freight!$K$3:$K$22) -> 207.30503 | R64: =_xlfn.XLOOKUP(O64,Freight!$A$3:$A$22,Freight!$M$3:$M$22) -> 77.5 | S64: =_xlfn.XLOOKUP(O64,Freight!$A$3:$A$22,Freight!$N$3:$N$22) -> 22.036525 | AQ64: HPCL | AT64: HPCL | AW64: HPCL | AY64: HPCL | BA64: HPCL | BC64: HPCL | BD64: 0
G65: 275 | H65: =G65*0.25 -> 68.75 | I65: =G65*0.17 -> 46.75 | J65: =H65+I65 -> 115.5 | O65: =EOMONTH(O64,1) -> 46477 | P65: =_xlfn.XLOOKUP(USG!O65,Freight!$A$3:$A$22,Freight!$J$3:$J$22) -> 354.59305 | Q65: =_xlfn.XLOOKUP(O65,Freight!$A$3:$A$22,Freight!$K$3:$K$22) -> 202.3692 | R65: =_xlfn.XLOOKUP(O65,Freight!$A$3:$A$22,Freight!$M$3:$M$22) -> 74.5 | S65: =_xlfn.XLOOKUP(O65,Freight!$A$3:$A$22,Freight!$N$3:$N$22) -> 21.511846 | AQ65: Reliance | AT65: Reliance | AW65: Reliance | AY65: Reliance | BA65: Reliance | BC65: Reliance | BD65: 2
O66: =EOMONTH(O65,1) -> 46507 | P66: =_xlfn.XLOOKUP(USG!O66,Freight!$A$3:$A$22,Freight!$J$3:$J$22) -> 314.13613 | Q66: =_xlfn.XLOOKUP(O66,Freight!$A$3:$A$22,Freight!$K$3:$K$22) -> 167.81836 | R66: =_xlfn.XLOOKUP(O66,Freight!$A$3:$A$22,Freight!$M$3:$M$22) -> 66 | S66: =_xlfn.XLOOKUP(O66,Freight!$A$3:$A$22,Freight!$N$3:$N$22) -> 17.839092 | AQ66: MRPL | AR66: 0 | AT66: MRPL | AU66: 2 | AW66: MRPL | AX66: 0 | AY66: MRPL | AZ66: 0 | BA66: MRPL | BB66: 0 | BC66: MRPL | BD66: 0
G67: 204 | H67: 165.1 | I67: =(H67-G67)/G67 -> -0.19068627 | O67: =EOMONTH(O66,1) -> 46538 | P67: =_xlfn.XLOOKUP(USG!O67,Freight!$A$3:$A$22,Freight!$J$3:$J$22) -> 299.85721 | Q67: =_xlfn.XLOOKUP(O67,Freight!$A$3:$A$22,Freight!$K$3:$K$22) -> 167.81836 | R67: =_xlfn.XLOOKUP(O67,Freight!$A$3:$A$22,Freight!$M$3:$M$22) -> 63 | S67: =_xlfn.XLOOKUP(O67,Freight!$A$3:$A$22,Freight!$N$3:$N$22) -> 17.839092 | AQ67: BPCL | AR67: 3 | AT67: BPCL | AU67: 1 | AW67: BPCL | AX67: 2 | AY67: BPCL | AZ67: 4 | BA67: BPCL | BB67: 3 | BC67: BPCL | BD67: 1
I68: =H67-G67 -> -38.9 | AQ68: Total | AR68: =AR42+AR45+AR49+AR53+AR60+AR62 -> 52.1 | AT68: Total | AU68: =AU42+AU45+AU49+AU53+AU60+AU62 -> 47.1 | AW68: Total | AX68: =AX42+AX45+AX49+AX53+AX60+AX62 -> 18 | AY68: Total | AZ68: =AZ42+AZ45+AZ49+AZ53+AZ60+AZ62 -> 28.8 | BA68: Total | BB68: =BB42+BB45+BB49+BB53+BB60+BB62 -> 46.4 | BC68: Total | BD68: =BD42+BD45+BD49+BD53+BD60+BD62 -> 14
AQ69: kbd | AR69: =AR68/28 -> 1.8607143 | AT69: kbd | AU69: =AU68/31 -> 1.5193548 | AW69: kbd | AX69: =AX68/31 -> 0.58064516 | AY69: kbd | AZ69: =AZ68/30 -> 0.96 | BA69: kbd | BB69: =BB68/30 -> 1.5466667 | BC69: kbd | BD69: =BD68/30 -> 0.46666667
A71: 0.39
I74: 2026 | J74: 2027 | K74: 2028 | L74: 2029 | M74: 2030 | N74: 2031
D75: 2026 | E75: 600 | H75: A26 | J75: =E75*0.5 -> 300 | K75: =J75*0.5 -> 150 | L75: =K75 -> 150
D76: 2027 | E76: 300 | H76: A27 | K76: =E76*0.5 -> 150 | L76: =K76*0.5 -> 75 | M76: =L76 -> 75
D77: 2028 | E77: 300 | H77: A28 | L77: =E77*0.5 -> 150 | M77: =L77*0.5 -> 75 | N77: =M77 -> 75
H78: A.De | I78: 50 | J78: =92.5+50 -> 142.5 | K78: =J78 -> 142.5
H80: Total | I80: =SUM(I75:I78) -> 50 | J80: =SUM(J75:J78) -> 442.5 | K80: =SUM(K75:K78) -> 442.5 | L80: =SUM(L75:L78) -> 375 | M80: =SUM(M75:M78) -> 150 | N80: =SUM(N75:N78) -> 75 | P80: =SUM(I80:N80) -> 1535
I83: 2026 | J83: 2027 | K83: 2028 | L83: 2029 | M83: 2030 | N83: 2031
D84: 2026 | E84: 420 | H84: A26 | J84: =E84*0.5 -> 210 | K84: =J84 -> 210
D85: 2027 | E85: 420 | H85: A27 | K85: =E85*0.5 -> 210 | L85: =K85 -> 210
D86: 2028 | E86: 420 | H86: A28 | L86: =E86*0.5 -> 210 | M86: =L86 -> 210 | S86: 1.6
H87: Sal | I87: 15 | J87: 50 | K87: 50 | L87: 50 | M87: 50 | N87: 50
H89: Total | I89: =SUM(I84:I87) -> 15 | J89: =SUM(J84:J87) -> 260 | K89: =SUM(K84:K87) -> 470 | L89: =SUM(L84:L87) -> 470 | M89: =SUM(M84:M87) -> 260 | N89: =SUM(N84:N87) -> 50 | P89: =SUM(I89:N89) -> 1525
I92: Alt 1 (I80:N80) | J92: Alt 2 (I89:N89) | P92: =P89-P80 -> -10
H93: NPV @ 5% | I93: =I80+NPV(0.05,J80:N80) -> 1378.898 | J93: =I89+NPV(0.05,J89:N89) -> 1348.0055
H94: NPV @ 7% | I94: =I80+NPV(0.07,J80:N80) -> 1324.068 | J94: =I89+NPV(0.07,J89:N89) -> 1286.1689
T123: =EOMONTH(P117,0) -> 31
T124: =EOMONTH(P118,0) -> 31
T125: =EOMONTH(P119,0) -> 31
T126: =EOMONTH(P120,0) -> 31
T127: =EOMONTH(P121,0) -> 31
T128: =EOMONTH(P122,0) -> 31
T129: =EOMONTH(P123,0) -> 31

Sheet FWD
A1: 0 | B1: 1 | D1: 0.7 | M1: EUROPE vs BFOETM Cash (Cal Dated basis) | AF1: ASIA vs. Murban (m-1 Dubai basis)
J2: =J5-0.81 -> -4.13 | M2: First decade loaders | X2: Second/Third Decade | AN2: ** 2/3 of actual spread
C3: Freight | D3: Diff | E3: Load | F3: MEH | G3: WTI Sprds | H3: Arbs | I3: FOB Premium | J3: FOB WTI vs. Brent | K3: HTT-BK | M3: Arrival | N3: Freight | O3: DFLs | P3: WTI CIF Rdam | Q3: FOB Nsea | R3: X-Nsea Freight | S3: M1-M3 Brent | T3: DFLs | U3: Cash BFOETM | V3: (Closed)/Open | X3: Arrival | Y3: Brent Sprds | Z3: Freight | AA3: DFLs | AB3: =P3 -> WTI CIF Rdam | AC3: Cash BFOETM | AD3: (Closed)/Open | AF3: Arrival | AG3: Brent Sprds | AH3: Freight | AI3: B/D | AJ3: WTI CFR N.Asia vs DUB | AL3: Load | AM3: Murban FOB | AN3: Brent Sprds | AO3: Freight | AP3: B/D | AQ3: Arrival | AR3: MURBAN CFR N.Asia vs DUB | AT3: (Closed)/Open
C4: =E4 -> 46326 | D4: =EOMONTH(E4,-1)+1 -> 46296 | E4: =EOMONTH(E5,-1) -> 46326 | F4: =IFERROR(INDEX(Sheet1!$B$5:$N$27,MATCH(FWD!$F$3,Sheet1!$B$5:$B$27,0),MATCH(FWD!D4,Sheet1!$B$5:$N$5,0)),F5) -> 0.75 | G4: =BBG!F5-BBG!F6 -> 2 | H4: =IF(BBG!$D$5=BBG!$J$5,BBG!F6-BBG!L6,BBG!F6-BBG!L5) -> -9.61 | I4: =$B$6 -> 3 | J4: =SUM(F4:I4) -> -3.86 | M4: =EOMONTH(M5,-1) -> 46326 | N4: =VLOOKUP($C4,Freight!$A$3:$F$17,MATCH(FWD!$N$41,Freight!$A$3:$F$3,0),FALSE)+$B$7 -> 17.18865 | O4: =VLOOKUP(EOMONTH(M4,0),BBG!$N$63:$R$123,5,FALSE) -> 9.01 | P4: =J4+N4-O4 -> 4.31865 | R4: =VLOOKUP($C4,Freight!$A$3:$F$17,MATCH(FWD!$U$41,Freight!$A$3:$F$3,0),FALSE) -> 3.5918571 | S4: =INDEX(BBG!$H$4:$L$53,MATCH(FWD!$M4,BBG!$H$4:$H$53,0),MATCH("Settle",BBG!$H$4:$L$4,0))-INDEX(BBG!$H$4:$L$53,MATCH(FWD!$M6,BBG!$H$4:$H$53,0),MATCH("Settle",BBG!$H$4:$L$4,0)) -> #N/A | T4: =O4 -> 9.01 | U4: =SUM(Q4:S4)-T4 -> #N/A | V4: =IFERROR(U4-P4,"Expired") -> Expired | X4: =EOMONTH(M4,1) -> 46356 | Y4: =IF(BBG!$D$5=BBG!$J$5,BBG!L6-BBG!L7,BBG!L5-BBG!L6) -> 2.94 | Z4: =VLOOKUP($C4,Freight!$A$3:$F$17,MATCH(FWD!$N$41,Freight!$A$3:$F$3,0),FALSE)+$B$7 -> 17.18865 | AA4: =VLOOKUP(EOMONTH(X4,0),BBG!$N$63:$R$123,5,FALSE) -> 3.33 | AB4: =J4+Y4+Z4-AA4 -> 12.93865 | AC4: =U5 -> #N/A | AD4: =IFERROR(AC4-AB4,"Expired") -> Expired
A5: EFP | B5: 0.03 | C5: =E5 -> 46356 | D5: =EOMONTH(E5,-1)+1 -> 46327 | E5: =USG!E25 -> 46356 | F5: =+INDEX(Sheet1!$B$5:$N$27,MATCH(FWD!$F$3,Sheet1!$B$5:$B$27,0),MATCH(FWD!D5,Sheet1!$B$5:$N$5,0)) -> 1.35 | G5: =BBG!F5-BBG!F7 -> 3.69 | H5: =IF(BBG!$D$5=BBG!$J$5,BBG!F7-BBG!L7,BBG!F7-BBG!L6) -> -8.36 | I5: 0 | J5: =SUM(F5:I5) -> -3.32 | K5: =BBG!G64+FWD!F5 -> -5.6333 | M5: =EOMONTH(E5,0) -> 46356 | N5: =AVERAGE(VLOOKUP($C5,Freight!$A$3:$F$17,MATCH(FWD!$N$41,Freight!$A$3:$F$3,0),FALSE),VLOOKUP($C4,Freight!$A$3:$F$17,MATCH(FWD!$N$41,Freight!$A$3:$F$3,0),FALSE))+$B$7 -> 16.705575 | O5: =VLOOKUP(EOMONTH(M5,0),BBG!$N$63:$R$123,5,FALSE) -> 3.33 | P5: =J5+N5-O5 -> 10.055575 | Q5: =$B$5 -> 0.03 | R5: =VLOOKUP($C5,Freight!$A$3:$F$17,MATCH(FWD!$U$41,Freight!$A$3:$F$3,0),FALSE) -> 3.142875 | S5: =INDEX(BBG!$H$4:$L$53,MATCH(FWD!$M5,BBG!$H$4:$H$53,0),MATCH("Settle",BBG!$H$4:$L$4,0))-INDEX(BBG!$H$4:$L$53,MATCH(FWD!$M7,BBG!$H$4:$H$53,0),MATCH("Settle",BBG!$H$4:$L$4,0)) -> #N/A | T5: =O5 -> 3.33 | U5: =SUM(Q5:S5)-T5 -> #N/A | V5: =IFERROR(U5-P5,"Expired") -> Expired | X5: =EOMONTH(M5,1) -> 46387 | Y5: =IF(BBG!$D$5=BBG!$J$5,BBG!L7-BBG!L8,BBG!L6-BBG!L7) -> 2.24 | Z5: =VLOOKUP($C5,Freight!$A$3:$F$17,MATCH(FWD!$N$41,Freight!$A$3:$F$3,0),FALSE)+$B$7 -> 16.2225 | AA5: =VLOOKUP(EOMONTH(X5,0),BBG!$N$63:$R$123,5,FALSE) -> 2.61 | AB5: =J5+Y5+Z5-AA5 -> 12.5325 | AC5: =U6 -> 5.2938929 | AD5: =IFERROR(AC5-AB5,"Expired") -> -7.2386071 | AF5: =EOMONTH(E5,2) -> 46418 | AG5: =Y5 -> 2.24 | AH5: =VLOOKUP($C4,Freight!$A$3:$F$17,MATCH(FWD!$AH$41,Freight!$A$3:$F$3,0),FALSE) -> 26.349086 | AI5: =VLOOKUP(X5,BBG!$U$63:$Y$123,4,FALSE) -> 0.607 | AJ5: =AI5+J5+AH5+AG5 -> 25.876086 | AL5: =EOMONTH(E5,1) -> 46387 | AM5: =VLOOKUP(AL5,BBG!$AE$64:$AJ$100,6,FALSE) -> 9.5545 | AN5: =Y6 -> 1.7 | AO5: =VLOOKUP($C5,Freight!$A$3:$G$22,MATCH(FWD!$AO$41,Freight!$A$3:$G$3,0),FALSE) -> 27.22356 | AP5: =AI5 -> 0.607 | AQ5: =AF5 -> 46418 | AR5: =AM5+AN5+AO5+AP5 -> 39.08506 | AT5: =-(AJ5-AR5) -> 13.208974
A6: Cash | B6: =USG!D29 -> 3 | C6: =E6 -> 46387 | D6: =EOMONTH(E6,-1)+1 -> 46357 | E6: =EOMONTH(E5,1) -> 46387 | F6: =+INDEX(Sheet1!$B$5:$N$27,MATCH(FWD!$F$3,Sheet1!$B$5:$B$27,0),MATCH(FWD!D6,Sheet1!$B$5:$N$5,0)) -> 1 | G6: =BBG!F6-BBG!F8 -> 3.31 | H6: =IF(BBG!$D$5=BBG!$J$5,BBG!F8-BBG!L8,BBG!F8-BBG!L7) -> -7.74 | I6: =I5 -> 0 | J6: =SUM(F6:I6) -> -3.43 | K6: =BBG!G65+FWD!F6 -> -5.4855 | M6: =EOMONTH(E6,0) -> 46387 | N6: =AVERAGE(VLOOKUP($C6,Freight!$A$3:$F$17,MATCH(FWD!$N$41,Freight!$A$3:$F$3,0),FALSE),VLOOKUP($C5,Freight!$A$3:$F$17,MATCH(FWD!$N$41,Freight!$A$3:$F$3,0),FALSE))+$B$7 -> 14.5049 | O6: =VLOOKUP(EOMONTH(M6,0),BBG!$N$63:$R$123,5,FALSE) -> 2.61 | P6: =J6+N6-O6 -> 8.4649 | Q6: =$B$5 -> 0.03 | R6: =VLOOKUP($C6,Freight!$A$3:$F$17,MATCH(FWD!$U$41,Freight!$A$3:$F$3,0),FALSE) -> 2.6938929 | S6: =INDEX(BBG!$H$4:$L$53,MATCH(FWD!$M6,BBG!$H$4:$H$53,0),MATCH("Settle",BBG!$H$4:$L$4,0))-INDEX(BBG!$H$4:$L$53,MATCH(FWD!$M8,BBG!$H$4:$H$53,0),MATCH("Settle",BBG!$H$4:$L$4,0)) -> 5.18 | T6: =O6 -> 2.61 | U6: =SUM(Q6:S6)-T6 -> 5.2938929 | V6: =IFERROR(U6-P6,"Expired") -> -3.1710071 | X6: =EOMONTH(M6,1) -> 46418 | Y6: =IF(BBG!$D$5=BBG!$J$5,BBG!L8-BBG!L9,BBG!L7-BBG!L8) -> 1.7 | Z6: =VLOOKUP($C6,Freight!$A$3:$F$17,MATCH(FWD!$N$41,Freight!$A$3:$F$3,0),FALSE)+$B$7 -> 12.7873 | AA6: =VLOOKUP(EOMONTH(X6,0),BBG!$N$63:$R$123,5,FALSE) -> 2.03 | AB6: =J6+Y6+Z6-AA6 -> 9.0273 | AC6: =U7 -> 3.8458472 | AD6: =IFERROR(AC6-AB6,"Expired") -> -5.1814528 | AF6: =EOMONTH(E6,2) -> 46446 | AG6: =IF(BBG!$D$5=BBG!$J$5,BBG!L8-BBG!L10,BBG!L7-BBG!L9)*2/3 -> 2.12 | AH6: =VLOOKUP($C6,Freight!$A$3:$F$17,MATCH(FWD!$AH$41,Freight!$A$3:$F$3,0),FALSE)+$B$7 -> 19.152013 | AI6: =VLOOKUP(X6,BBG!$U$63:$Y$123,4,FALSE) -> 0.527 | AJ6: =AI6+J6+AH6+AG6 -> 18.369013 | AL6: =EOMONTH(E6,1) -> 46418 | AM6: =VLOOKUP(AL6,BBG!$AE$64:$AJ$100,6,FALSE) -> 3.444 | AN6: =Y7 -> 1.48 | AO6: =VLOOKUP($C6,Freight!$A$3:$G$22,MATCH(FWD!$AO$41,Freight!$A$3:$G$3,0),FALSE) -> 23.231644 | AP6: =AI6 -> 0.527 | AQ6: =AF6 -> 46446 | AR6: =AM6+AN6+AO6+AP6 -> 28.682644 | AT6: =-(AJ6-AR6) -> 10.313631
A7: tvm, ETC | B7: 0.12 | C7: =E7 -> 46418 | D7: =EOMONTH(E7,-1)+1 -> 46388 | E7: =EOMONTH(E6,1) -> 46418 | F7: =+INDEX(Sheet1!$B$5:$N$27,MATCH(FWD!$F$3,Sheet1!$B$5:$B$27,0),MATCH(FWD!D7,Sheet1!$B$5:$N$5,0)) -> 1.2 | G7: =BBG!F7-BBG!F9 -> 3.02 | H7: =IF(BBG!$D$5=BBG!$J$5,BBG!F9-BBG!L9,BBG!F9-BBG!L8) -> -7.44 | I7: =I6 -> 0 | J7: =SUM(F7:I7) -> -3.22 | K7: =BBG!G66+FWD!F7 -> -5.286 | M7: =EOMONTH(E7,0) -> 46418 | N7: =AVERAGE(VLOOKUP($C7,Freight!$A$3:$F$17,MATCH(FWD!$N$41,Freight!$A$3:$F$3,0),FALSE),VLOOKUP($C6,Freight!$A$3:$F$17,MATCH(FWD!$N$41,Freight!$A$3:$F$3,0),FALSE))+$B$7 -> 10.566775 | O7: =VLOOKUP(EOMONTH(M7,0),BBG!$N$63:$R$123,5,FALSE) -> 2.03 | P7: =J7+N7-O7 -> 5.3167747 | Q7: =$B$5 -> 0.03 | R7: =VLOOKUP($C7,Freight!$A$3:$F$17,MATCH(FWD!$U$41,Freight!$A$3:$F$3,0),FALSE) -> 1.9058472 | S7: =INDEX(BBG!$H$4:$L$53,MATCH(FWD!$M7,BBG!$H$4:$H$53,0),MATCH("Settle",BBG!$H$4:$L$4,0))-INDEX(BBG!$H$4:$L$53,MATCH(FWD!$M9,BBG!$H$4:$H$53,0),MATCH("Settle",BBG!$H$4:$L$4,0)) -> 3.94 | T7: =O7 -> 2.03 | U7: =SUM(Q7:S7)-T7 -> 3.8458472 | V7: =IFERROR(U7-P7,"Expired") -> -1.4709275 | X7: =EOMONTH(M7,1) -> 46446 | Y7: =IF(BBG!$D$5=BBG!$J$5,BBG!L9-BBG!L10,BBG!L8-BBG!L9) -> 1.48 | Z7: =VLOOKUP($C7,Freight!$A$3:$F$17,MATCH(FWD!$N$41,Freight!$A$3:$F$3,0),FALSE)+$B$7 -> 8.3462494 | AA7: =VLOOKUP(EOMONTH(X7,0),BBG!$N$63:$R$123,5,FALSE) -> 1.85 | AB7: =J7+Y7+Z7-AA7 -> 4.7562494 | AC7: =U8 -> 3.2215252 | AD7: =IFERROR(AC7-AB7,"Expired") -> -1.5347242 | AF7: =EOMONTH(E7,2) -> 46477 | AG7: =IF(BBG!$D$5=BBG!$J$5,BBG!L9-BBG!L11,BBG!L8-BBG!L10)*2/3 -> 1.8733333 | AH7: =VLOOKUP($C7,Freight!$A$3:$F$17,MATCH(FWD!$AH$41,Freight!$A$3:$F$3,0),FALSE)+$B$7 -> 16.712989 | AI7: =VLOOKUP(X7,BBG!$U$63:$Y$123,4,FALSE) -> 0.478 | AJ7: =AI7+J7+AH7+AG7 -> 15.844322 | AL7: =EOMONTH(E7,1) -> 46446 | AM7: =VLOOKUP(AL7,BBG!$AE$64:$AJ$100,6,FALSE) -> 2.1865 | AN7: =Y8 -> 1.33 | AO7: =VLOOKUP($C7,Freight!$A$3:$G$22,MATCH(FWD!$AO$41,Freight!$A$3:$G$3,0),FALSE) -> 23.508336 | AP7: =AI7 -> 0.478 | AQ7: =AF7 -> 46477 | AR7: =AM7+AN7+AO7+AP7 -> 27.502836 | AT7: =-(AJ7-AR7) -> 11.658514
B8: 0.12 | C8: =E8 -> 46446 | D8: =EOMONTH(E8,-1)+1 -> 46419 | E8: =EOMONTH(E7,1) -> 46446 | F8: =+INDEX(Sheet1!$B$5:$N$27,MATCH(FWD!$F$3,Sheet1!$B$5:$B$27,0),MATCH(FWD!D8,Sheet1!$B$5:$N$5,0)) -> 1.4 | G8: =BBG!F8-BBG!F10 -> 2.66 | H8: =IF(BBG!$D$5=BBG!$J$5,BBG!F10-BBG!L10,BBG!F10-BBG!L9) -> -7.22 | I8: =I7 -> 0 | J8: =SUM(F8:I8) -> -3.16 | K8: =BBG!G67+FWD!F8 -> -4.7635 | M8: =EOMONTH(E8,0) -> 46446 | N8: =AVERAGE(VLOOKUP($C8,Freight!$A$3:$F$17,MATCH(FWD!$N$41,Freight!$A$3:$F$3,0),FALSE),VLOOKUP($C7,Freight!$A$3:$F$17,MATCH(FWD!$N$41,Freight!$A$3:$F$3,0),FALSE))+$B$7 -> 8.1929653 | O8: =VLOOKUP(EOMONTH(M8,0),BBG!$N$63:$R$123,5,FALSE) -> 1.85 | P8: =J8+N8-O8 -> 3.1829653 | Q8: =$B$5 -> 0.03 | R8: =VLOOKUP($C8,Freight!$A$3:$F$17,MATCH(FWD!$U$41,Freight!$A$3:$F$3,0),FALSE) -> 1.8615252 | S8: =INDEX(BBG!$H$4:$L$53,MATCH(FWD!$M8,BBG!$H$4:$H$53,0),MATCH("Settle",BBG!$H$4:$L$4,0))-INDEX(BBG!$H$4:$L$53,MATCH(FWD!$M10,BBG!$H$4:$H$53,0),MATCH("Settle",BBG!$H$4:$L$4,0)) -> 3.18 | T8: =O8 -> 1.85 | U8: =SUM(Q8:S8)-T8 -> 3.2215252 | V8: =IFERROR(U8-P8,"Expired") -> 0.038559918 | X8: =EOMONTH(M8,1) -> 46477 | Y8: =IF(BBG!$D$5=BBG!$J$5,BBG!L10-BBG!L11,BBG!L9-BBG!L10) -> 1.33 | Z8: =VLOOKUP($C8,Freight!$A$3:$F$17,MATCH(FWD!$N$41,Freight!$A$3:$F$3,0),FALSE)+$B$7 -> 8.0396811 | AA8: =VLOOKUP(EOMONTH(X8,0),BBG!$N$63:$R$123,5,FALSE) -> 1.71 | AB8: =J8+Y8+Z8-AA8 -> 4.4996811 | AC8: =U9 -> 2.9472031 | AD8: =IFERROR(AC8-AB8,"Expired") -> -1.552478 | AF8: =EOMONTH(E8,2) -> 46507 | AG8: =IF(BBG!$D$5=BBG!$J$5,BBG!L10-BBG!L12,BBG!L9-BBG!L11)*2/3 -> 1.72 | AH8: =VLOOKUP($C8,Freight!$A$3:$F$17,MATCH(FWD!$AH$41,Freight!$A$3:$F$3,0),FALSE)+$B$7 -> 15.737379 | AI8: =VLOOKUP(X8,BBG!$U$63:$Y$123,4,FALSE) -> 0.437 | AJ8: =AI8+J8+AH8+AG8 -> 14.734379 | AL8: =EOMONTH(E8,1) -> 46477 | AM8: =VLOOKUP(AL8,BBG!$AE$64:$AJ$100,6,FALSE) -> 1.0068 | AN8: =Y9 -> 1.25 | AO8: =VLOOKUP($C8,Freight!$A$3:$G$22,MATCH(FWD!$AO$41,Freight!$A$3:$G$3,0),FALSE) -> 19.622661 | AP8: =AI8 -> 0.437 | AQ8: =AF8 -> 46507 | AR8: =AM8+AN8+AO8+AP8 -> 22.316461 | AT8: =-(AJ8-AR8) -> 7.5820818
A9: Dated | C9: =E9 -> 46477 | D9: =EOMONTH(E9,-1)+1 -> 46447 | E9: =EOMONTH(E8,1) -> 46477 | F9: =+INDEX(Sheet1!$B$5:$N$27,MATCH(FWD!$F$3,Sheet1!$B$5:$B$27,0),MATCH(FWD!D9,Sheet1!$B$5:$N$5,0)) -> 1.55 | G9: =BBG!F9-BBG!F11 -> 2.39 | H9: =IF(BBG!$D$5=BBG!$J$5,BBG!F11-BBG!L11,BBG!F11-BBG!L10) -> -7.02 | I9: =I8 -> 0 | J9: =SUM(F9:I9) -> -3.08 | K9: =BBG!G68+FWD!F9 -> -4.5932 | M9: =EOMONTH(E9,0) -> 46477 | N9: =AVERAGE(VLOOKUP($C9,Freight!$A$3:$F$17,MATCH(FWD!$N$41,Freight!$A$3:$F$3,0),FALSE),VLOOKUP($C8,Freight!$A$3:$F$17,MATCH(FWD!$N$41,Freight!$A$3:$F$3,0),FALSE))+$B$7 -> 7.886397 | O9: =VLOOKUP(EOMONTH(M9,0),BBG!$N$63:$R$123,5,FALSE) -> 1.71 | P9: =J9+N9-O9 -> 3.096397 | Q9: =$B$5 -> 0.03 | R9: =VLOOKUP($C9,Freight!$A$3:$F$17,MATCH(FWD!$U$41,Freight!$A$3:$F$3,0),FALSE) -> 1.8172031 | S9: =INDEX(BBG!$H$4:$L$53,MATCH(FWD!$M9,BBG!$H$4:$H$53,0),MATCH("Settle",BBG!$H$4:$L$4,0))-INDEX(BBG!$H$4:$L$53,MATCH(FWD!$M11,BBG!$H$4:$H$53,0),MATCH("Settle",BBG!$H$4:$L$4,0)) -> 2.81 | T9: =O9 -> 1.71 | U9: =SUM(Q9:S9)-T9 -> 2.9472031 | V9: =IFERROR(U9-P9,"Expired") -> -0.14919381 | X9: =EOMONTH(M9,1) -> 46507 | Y9: =IF(BBG!$D$5=BBG!$J$5,BBG!L11-BBG!L12,BBG!L10-BBG!L11) -> 1.25 | Z9: =VLOOKUP($C9,Freight!$A$3:$F$17,MATCH(FWD!$N$41,Freight!$A$3:$F$3,0),FALSE)+$B$7 -> 7.7331128 | AA9: =VLOOKUP(EOMONTH(X9,0),BBG!$N$63:$R$123,5,FALSE) -> 1.59 | AB9: =J9+Y9+Z9-AA9 -> 4.3131128 | AC9: =U10 -> 2.5269489 | AD9: =IFERROR(AC9-AB9,"Expired") -> -1.7861639 | AF9: =EOMONTH(E9,2) -> 46538 | AG9: =IF(BBG!$D$5=BBG!$J$5,BBG!L11-BBG!L13,BBG!L10-BBG!L12)*2/3 -> 1.62 | AH9: =VLOOKUP($C9,Freight!$A$3:$F$17,MATCH(FWD!$AH$41,Freight!$A$3:$F$3,0),FALSE)+$B$7 -> 14.761769 | AI9: =VLOOKUP(X9,BBG!$U$63:$Y$123,4,FALSE) -> 0.357 | AJ9: =AI9+J9+AH9+AG9 -> 13.658769 | AL9: =EOMONTH(E9,1) -> 46507 | AM9: =VLOOKUP(AL9,BBG!$AE$64:$AJ$100,6,FALSE) -> #VALUE! | AN9: =Y10 -> 1.1 | AO9: =VLOOKUP($C9,Freight!$A$3:$G$22,MATCH(FWD!$AO$41,Freight!$A$3:$G$3,0),FALSE) -> 17.485539 | AP9: =AI9 -> 0.357 | AQ9: =AF9 -> 46538 | AR9: =AM9+AN9+AO9+AP9 -> #VALUE! | AT9: =-(AJ9-AR9) -> #VALUE!
C10: =E10 -> 46507 | D10: =EOMONTH(E10,-1)+1 -> 46478 | E10: =EOMONTH(E9,1) -> 46507 | F10: =+INDEX(Sheet1!$B$5:$N$27,MATCH(FWD!$F$3,Sheet1!$B$5:$B$27,0),MATCH(FWD!D10,Sheet1!$B$5:$N$5,0)) -> 1.75 | G10: =BBG!F10-BBG!F12 -> 2.17 | H10: =IF(BBG!$D$5=BBG!$J$5,BBG!F12-BBG!L12,BBG!F12-BBG!L11) -> -6.81 | I10: =I9 -> 0 | J10: =SUM(F10:I10) -> -2.89 | K10: =BBG!G69+FWD!F10 -> -4.3464 | M10: =EOMONTH(E10,0) -> 46507 | N10: =AVERAGE(VLOOKUP($C10,Freight!$A$3:$F$17,MATCH(FWD!$N$41,Freight!$A$3:$F$3,0),FALSE),VLOOKUP($C9,Freight!$A$3:$F$17,MATCH(FWD!$N$41,Freight!$A$3:$F$3,0),FALSE))+$B$7 -> 7.2988077 | O10: =VLOOKUP(EOMONTH(M10,0),BBG!$N$63:$R$123,5,FALSE) -> 1.59 | P10: =J10+N10-O10 -> 2.8188077 | Q10: =$B$5 -> 0.03 | R10: =VLOOKUP($C10,Freight!$A$3:$F$17,MATCH(FWD!$U$41,Freight!$A$3:$F$3,0),FALSE) -> 1.5069489 | S10: =INDEX(BBG!$H$4:$L$53,MATCH(FWD!$M10,BBG!$H$4:$H$53,0),MATCH("Settle",BBG!$H$4:$L$4,0))-INDEX(BBG!$H$4:$L$53,MATCH(FWD!$M12,BBG!$H$4:$H$53,0),MATCH("Settle",BBG!$H$4:$L$4,0)) -> 2.58 | T10: =O10 -> 1.59 | U10: =SUM(Q10:S10)-T10 -> 2.5269489 | V10: =IFERROR(U10-P10,"Expired") -> -0.29185876 | X10: =EOMONTH(M10,1) -> 46538 | Y10: =IF(BBG!$D$5=BBG!$J$5,BBG!L13-BBG!L14,BBG!L12-BBG!L13) -> 1.1 | Z10: =VLOOKUP($C10,Freight!$A$3:$F$17,MATCH(FWD!$N$41,Freight!$A$3:$F$3,0),FALSE)+$B$7 -> 6.8645026 | AA10: =VLOOKUP(EOMONTH(X10,0),BBG!$N$63:$R$123,5,FALSE) -> 1.44 | AB10: =J10+Y10+Z10-AA10 -> 3.6345026 | AC10: =U11 -> 2.5269489 | AD10: =IFERROR(AC10-AB10,"Expired") -> -1.1075537 | AF10: =EOMONTH(E10,2) -> 46568 | AG10: =IF(BBG!$D$5=BBG!$J$5,BBG!L12-BBG!L14,BBG!L11-BBG!L13)*2/3 -> 1.52 | AH10: =VLOOKUP($C10,Freight!$A$3:$F$17,MATCH(FWD!$AH$41,Freight!$A$3:$F$3,0),FALSE)+$B$7 -> 12.322745 | AI10: =VLOOKUP(X10,BBG!$U$63:$Y$123,4,FALSE) -> 0.307 | AJ10: =AI10+J10+AH10+AG10 -> 11.259745 | AL10: =EOMONTH(E10,1) -> 46538 | AM10: =VLOOKUP(AL10,BBG!$AE$64:$AJ$100,6,FALSE) -> #VALUE! | AN10: =Y11 -> 1.02 | AO10: =VLOOKUP($C10,Freight!$A$3:$G$22,MATCH(FWD!$AO$41,Freight!$A$3:$G$3,0),FALSE) -> 15.542702 | AP10: =AI10 -> 0.307 | AQ10: =AF10 -> 46568 | AR10: =AM10+AN10+AO10+AP10 -> #VALUE! | AT10: =-(AJ10-AR10) -> #VALUE!
B11: =VLOOKUP(E11,$E$82:$I$118,5,FALSE) -> Q2-27 | C11: =E11 -> 46538 | D11: =EOMONTH(E11,-1)+1 -> 46508 | E11: =EOMONTH(E10,1) -> 46538 | F11: =+INDEX(Sheet1!$B$5:$N$27,MATCH(FWD!$F$3,Sheet1!$B$5:$B$27,0),MATCH(FWD!D11,Sheet1!$B$5:$N$5,0)) -> 1.8 | G11: =BBG!F11-BBG!F13 -> 2.01 | H11: =IF(BBG!$D$5=BBG!$J$5,BBG!F13-BBG!L13,BBG!F13-BBG!L12) -> -6.6 | I11: =I10 -> 0 | J11: =SUM(F11:I11) -> -2.79 | K11: =BBG!G70+FWD!F11 -> -4.0152 | M11: =EOMONTH(E11,0) -> 46538 | N11: =IFERROR(VLOOKUP($C11,Freight!$A$3:$F$17,MATCH(FWD!$N$41,Freight!$A$3:$F$3,0),FALSE)+$B$7,VLOOKUP($B11,Freight!$A$3:$F$17,MATCH(FWD!$N$41,Freight!$A$3:$F$3,0),FALSE)+$B$7) -> 6.5579343 | O11: =VLOOKUP(EOMONTH(M11,0),BBG!$N$63:$R$123,5,FALSE) -> 1.44 | P11: =J11+N11-O11 -> 2.3279343 | Q11: =$B$5 -> 0.03 | R11: =IFERROR(VLOOKUP($C11,Freight!$A$3:$F$22,MATCH(FWD!$U$41,Freight!$A$3:$F$3,0),FALSE),VLOOKUP($B11,Freight!$A$3:$F$22,MATCH(FWD!$U$41,Freight!$A$3:$F$3,0),FALSE)) -> 1.5069489 | S11: =INDEX(BBG!$H$4:$L$53,MATCH(FWD!$M11,BBG!$H$4:$H$53,0),MATCH("Settle",BBG!$H$4:$L$4,0))-INDEX(BBG!$H$4:$L$53,MATCH(FWD!$M13,BBG!$H$4:$H$53,0),MATCH("Settle",BBG!$H$4:$L$4,0)) -> 2.43 | T11: =O11 -> 1.44 | U11: =SUM(Q11:S11)-T11 -> 2.5269489 | V11: =IFERROR(U11-P11,"Expired") -> 0.19901463 | X11: =EOMONTH(M11,1) -> 46568 | Y11: =IF(BBG!$D$5=BBG!$J$5,BBG!L14-BBG!L15,BBG!L13-BBG!L14) -> 1.02 | Z11: =IFERROR(VLOOKUP($C11,Freight!$A$3:$F$17,MATCH(FWD!$N$41,Freight!$A$3:$F$3,0),FALSE)+$B$7,VLOOKUP($B11,Freight!$A$3:$F$17,MATCH(FWD!$N$41,Freight!$A$3:$F$3,0),FALSE)+$B$7) -> 6.5579343 | AA11: =VLOOKUP(EOMONTH(X11,0),BBG!$N$63:$R$123,5,FALSE) -> 1.32 | AB11: =J11+Y11+Z11-AA11 -> 3.4679343 | AC11: =U12 -> 2.4969489 | AD11: =IFERROR(AC11-AB11,"Expired") -> -0.97098537 | AF11: =EOMONTH(E11,2) -> 46599 | AG11: =IF(BBG!$D$5=BBG!$J$5,BBG!L13-BBG!L15,BBG!L12-BBG!L14)*2/3 -> 1.4133333 | AH11: =VLOOKUP($C11,Freight!$A$3:$F$17,MATCH(FWD!$AH$41,Freight!$A$3:$F$3,0),FALSE)+$B$7 -> 12.322745 | AI11: =VLOOKUP(X11,BBG!$U$63:$Y$123,4,FALSE) -> 0.3 | AJ11: =AI11+J11+AH11+AG11 -> 11.246078 | AL11: =EOMONTH(E11,1) -> 46568 | AM11: =VLOOKUP(AL11,BBG!$AE$64:$AJ$100,6,FALSE) -> #VALUE! | AN11: =Y12 -> 0.93 | AO11: =VLOOKUP($C11,Freight!$A$3:$G$22,MATCH(FWD!$AO$41,Freight!$A$3:$G$3,0),FALSE) -> 12.952251 | AP11: =AI11 -> 0.3 | AQ11: =AF11 -> 46599 | AR11: =AM11+AN11+AO11+AP11 -> #VALUE! | AT11: =-(AJ11-AR11) -> #VALUE!
B12: =VLOOKUP(E12,$E$82:$I$118,5,FALSE) -> Q2-27 | C12: =E12 -> 46568 | D12: =EOMONTH(E12,-1)+1 -> 46539 | E12: =EOMONTH(E11,1) -> 46568 | F12: =+INDEX(Sheet1!$B$5:$N$27,MATCH(FWD!$F$3,Sheet1!$B$5:$B$27,0),MATCH(FWD!D12,Sheet1!$B$5:$N$5,0)) -> 1.85 | G12: =BBG!F12-BBG!F14 -> 1.88 | H12: =IF(BBG!$D$5=BBG!$J$5,BBG!F14-BBG!L14,BBG!F14-BBG!L13) -> -6.41 | I12: =I11 -> 0 | J12: =SUM(F12:I12) -> -2.68 | K12: =BBG!G71+FWD!F12 -> -3.8636 | M12: =EOMONTH(E12,0) -> 46568 | N12: =IFERROR(VLOOKUP($C12,Freight!$A$3:$F$17,MATCH(FWD!$N$41,Freight!$A$3:$F$3,0),FALSE)+$B$7,VLOOKUP($B12,Freight!$A$3:$F$17,MATCH(FWD!$N$41,Freight!$A$3:$F$3,0),FALSE)+$B$7) -> 6.5579343 | O12: =VLOOKUP(EOMONTH(M12,0),BBG!$N$63:$R$123,5,FALSE) -> 1.32 | P12: =J12+N12-O12 -> 2.5579343 | Q12: =$B$5 -> 0.03 | R12: =IFERROR(VLOOKUP($C12,Freight!$A$3:$F$22,MATCH(FWD!$U$41,Freight!$A$3:$F$3,0),FALSE),VLOOKUP($B12,Freight!$A$3:$F$22,MATCH(FWD!$U$41,Freight!$A$3:$F$3,0),FALSE)) -> 1.5069489 | S12: =INDEX(BBG!$H$4:$L$53,MATCH(FWD!$M12,BBG!$H$4:$H$53,0),MATCH("Settle",BBG!$H$4:$L$4,0))-INDEX(BBG!$H$4:$L$53,MATCH(FWD!$M14,BBG!$H$4:$H$53,0),MATCH("Settle",BBG!$H$4:$L$4,0)) -> 2.28 | T12: =O12 -> 1.32 | U12: =SUM(Q12:S12)-T12 -> 2.4969489 | V12: =IFERROR(U12-P12,"Expired") -> -0.060985368 | X12: =EOMONTH(M12,1) -> 46599 | Y12: =IF(BBG!$D$5=BBG!$J$5,BBG!L15-BBG!L16,BBG!L14-BBG!L15) -> 0.93 | Z12: =IFERROR(VLOOKUP($C12,Freight!$A$3:$F$17,MATCH(FWD!$N$41,Freight!$A$3:$F$3,0),FALSE)+$B$7,VLOOKUP($B12,Freight!$A$3:$F$17,MATCH(FWD!$N$41,Freight!$A$3:$F$3,0),FALSE)+$B$7) -> 6.5579343 | AA12: =VLOOKUP(EOMONTH(X12,0),BBG!$N$63:$R$123,5,FALSE) -> 1.23 | AB12: =J12+Y12+Z12-AA12 -> 3.5779343 | AC12: =U13 -> 2.3383049 | AD12: =IFERROR(AC12-AB12,"Expired") -> -1.2396294 | AF12: =EOMONTH(E12,2) -> 46630 | AG12: =IF(BBG!$D$5=BBG!$J$5,BBG!L14-BBG!L16,BBG!L13-BBG!L15)*2/3 -> 1.3 | AH12: =IFERROR(VLOOKUP($C12,Freight!$A$3:$F$22,MATCH(FWD!$AH$41,Freight!$A$3:$F$3,0),FALSE)+$B$7,VLOOKUP($B12,Freight!$A$3:$F$22,MATCH(FWD!$AH$41,Freight!$A$3:$F$3,0),FALSE)+$B$7) -> 12.322745 | AI12: =VLOOKUP(X12,BBG!$U$63:$Y$123,4,FALSE) -> 0.389 | AJ12: =AI12+J12+AH12+AG12 -> 11.331745 | AL12: =EOMONTH(E12,1) -> 46599 | AM12: =VLOOKUP(AL12,BBG!$AE$64:$AJ$100,6,FALSE) -> #VALUE! | AN12: =Y13 -> 0.83 | AO12: =VLOOKUP($B12,Freight!$A$3:$G$22,MATCH(FWD!$AO$41,Freight!$A$3:$G$3,0),FALSE) -> 12.952251 | AP12: =AI12 -> 0.389 | AQ12: =AF12 -> 46630 | AR12: =AM12+AN12+AO12+AP12 -> #VALUE! | AT12: =-(AJ12-AR12) -> #VALUE!
B13: =VLOOKUP(E13,$E$82:$I$118,5,FALSE) -> Q3-27 | C13: =E13 -> 46599 | D13: =EOMONTH(E13,-1)+1 -> 46569 | E13: =EOMONTH(E12,1) -> 46599 | F13: =+INDEX(Sheet1!$B$5:$N$27,MATCH(FWD!$F$3,Sheet1!$B$5:$B$27,0),MATCH(FWD!D13,Sheet1!$B$5:$N$5,0)) -> 1.85 | G13: =BBG!F13-BBG!F15 -> 1.76 | H13: =IF(BBG!$D$5=BBG!$J$5,BBG!F15-BBG!L15,BBG!F15-BBG!L14) -> -6.24 | I13: =I12 -> 0 | J13: =SUM(F13:I13) -> -2.63 | K13: =BBG!G72+FWD!F13 -> -3.8177 | M13: =EOMONTH(E13,0) -> 46599 | N13: =IFERROR(VLOOKUP($C13,Freight!$A$3:$F$17,MATCH(FWD!$N$41,Freight!$A$3:$F$3,0),FALSE)+$B$7,VLOOKUP($B13,Freight!$A$3:$F$17,MATCH(FWD!$N$41,Freight!$A$3:$F$3,0),FALSE)+$B$7) -> 5.4849453 | O13: =VLOOKUP(EOMONTH(M13,0),BBG!$N$63:$R$123,5,FALSE) -> 1.23 | P13: =J13+N13-O13 -> 1.6249453 | Q13: =$B$5 -> 0.03 | R13: =IFERROR(VLOOKUP($C13,Freight!$A$3:$F$22,MATCH(FWD!$U$41,Freight!$A$3:$F$3,0),FALSE),VLOOKUP($B13,Freight!$A$3:$F$22,MATCH(FWD!$U$41,Freight!$A$3:$F$3,0),FALSE)) -> 1.4183049 | S13: =INDEX(BBG!$H$4:$L$53,MATCH(FWD!$M13,BBG!$H$4:$H$53,0),MATCH("Settle",BBG!$H$4:$L$4,0))-INDEX(BBG!$H$4:$L$53,MATCH(FWD!$M15,BBG!$H$4:$H$53,0),MATCH("Settle",BBG!$H$4:$L$4,0)) -> 2.12 | T13: =O13 -> 1.23 | U13: =SUM(Q13:S13)-T13 -> 2.3383049 | V13: =IFERROR(U13-P13,"Expired") -> 0.71335963 | X13: =EOMONTH(M13,1) -> 46630 | Y13: =IF(BBG!$D$5=BBG!$J$5,BBG!L16-BBG!L17,BBG!L15-BBG!L16) -> 0.83 | Z13: =IFERROR(VLOOKUP($C13,Freight!$A$3:$F$17,MATCH(FWD!$N$41,Freight!$A$3:$F$3,0),FALSE)+$B$7,VLOOKUP($B13,Freight!$A$3:$F$17,MATCH(FWD!$N$41,Freight!$A$3:$F$3,0),FALSE)+$B$7) -> 5.4849453 | AA13: =VLOOKUP(EOMONTH(X13,0),BBG!$N$63:$R$123,5,FALSE) -> 1.14 | AB13: =J13+Y13+Z13-AA13 -> 2.5449453 | AC13: =U14 -> 2.2583049 | AD13: =IFERROR(AC13-AB13,"Expired") -> -0.28664037 | AF13: =EOMONTH(E13,2) -> 46660 | AG13: =IF(BBG!$D$5=BBG!$J$5,BBG!L15-BBG!L17,BBG!L14-BBG!L16)*2/3 -> 1.1733333 | AH13: =IFERROR(VLOOKUP($C13,Freight!$A$3:$F$22,MATCH(FWD!$AH$41,Freight!$A$3:$F$3,0),FALSE)+$B$7,VLOOKUP($B13,Freight!$A$3:$F$22,MATCH(FWD!$AH$41,Freight!$A$3:$F$3,0),FALSE)+$B$7) -> 10.493477 | AI13: =VLOOKUP(X13,BBG!$U$63:$Y$123,4,FALSE) -> 0.389 | AJ13: =AI13+J13+AH13+AG13 -> 9.4258099 | AL13: =EOMONTH(E13,1) -> 46630 | AM13: =VLOOKUP(AL13,BBG!$AE$64:$AJ$100,6,FALSE) -> #VALUE! | AN13: =Y14 -> 0.78 | AO13: =VLOOKUP($B13,Freight!$A$3:$G$22,MATCH(FWD!$AO$41,Freight!$A$3:$G$3,0),FALSE) -> 6.9942157 | AP13: =AI13 -> 0.389 | AQ13: =AF13 -> 46660 | AR13: =AM13+AN13+AO13+AP13 -> #VALUE! | AT13: =-(AJ13-AR13) -> #VALUE!
B14: =VLOOKUP(E14,$E$82:$I$118,5,FALSE) -> Q3-27 | C14: =E14 -> 46630 | D14: =EOMONTH(E14,-1)+1 -> 46600 | E14: =EOMONTH(E13,1) -> 46630 | F14: =+INDEX(Sheet1!$B$5:$N$27,MATCH(FWD!$F$3,Sheet1!$B$5:$B$27,0),MATCH(FWD!D14,Sheet1!$B$5:$N$5,0)) -> 1.85 | G14: =BBG!F14-BBG!F16 -> 1.62 | H14: =IF(BBG!$D$5=BBG!$J$5,BBG!F16-BBG!L16,BBG!F16-BBG!L15) -> -6.08 | I14: =I13 -> 0 | J14: =SUM(F14:I14) -> -2.61 | K14: =BBG!G73+FWD!F14 -> -3.6623 | M14: =EOMONTH(E14,0) -> 46630 | N14: =IFERROR(VLOOKUP($C14,Freight!$A$3:$F$17,MATCH(FWD!$N$41,Freight!$A$3:$F$3,0),FALSE)+$B$7,VLOOKUP($B14,Freight!$A$3:$F$17,MATCH(FWD!$N$41,Freight!$A$3:$F$3,0),FALSE)+$B$7) -> 5.4849453 | O14: =VLOOKUP(EOMONTH(M14,0),BBG!$N$63:$R$123,5,FALSE) -> 1.14 | P14: =J14+N14-O14 -> 1.7349453 | Q14: =$B$5 -> 0.03 | R14: =IFERROR(VLOOKUP($C14,Freight!$A$3:$F$22,MATCH(FWD!$U$41,Freight!$A$3:$F$3,0),FALSE),VLOOKUP($B14,Freight!$A$3:$F$22,MATCH(FWD!$U$41,Freight!$A$3:$F$3,0),FALSE)) -> 1.4183049 | S14: =INDEX(BBG!$H$4:$L$53,MATCH(FWD!$M14,BBG!$H$4:$H$53,0),MATCH("Settle",BBG!$H$4:$L$4,0))-INDEX(BBG!$H$4:$L$53,MATCH(FWD!$M16,BBG!$H$4:$H$53,0),MATCH("Settle",BBG!$H$4:$L$4,0)) -> 1.95 | T14: =O14 -> 1.14 | U14: =SUM(Q14:S14)-T14 -> 2.2583049 | V14: =U14-P14 -> 0.52335963 | X14: =EOMONTH(M14,1) -> 46660 | Y14: =IF(BBG!$D$5=BBG!$J$5,BBG!L17-BBG!L18,BBG!L16-BBG!L17) -> 0.78 | Z14: =IFERROR(VLOOKUP($C14,Freight!$A$3:$F$17,MATCH(FWD!$N$41,Freight!$A$3:$F$3,0),FALSE)+$B$7,VLOOKUP($B14,Freight!$A$3:$F$17,MATCH(FWD!$N$41,Freight!$A$3:$F$3,0),FALSE)+$B$7) -> 5.4849453 | AA14: =VLOOKUP(EOMONTH(X14,0),BBG!$N$63:$R$123,5,FALSE) -> 1.06 | AB14: =J14+Y14+Z14-AA14 -> 2.5949453 | AC14: =U15 -> 2.1483049 | AD14: =AC14-AB14 -> -0.44664037 | AF14: =EOMONTH(E14,2) -> 46691 | AG14: =IF(BBG!$D$5=BBG!$J$5,BBG!L16-BBG!L18,BBG!L15-BBG!L17)*2/3 -> 1.0733333 | AH14: =IFERROR(VLOOKUP($C14,Freight!$A$3:$F$22,MATCH(FWD!$AH$41,Freight!$A$3:$F$3,0),FALSE)+$B$7,VLOOKUP($B14,Freight!$A$3:$F$22,MATCH(FWD!$AH$41,Freight!$A$3:$F$3,0),FALSE)+$B$7) -> 10.493477 | AI14: =VLOOKUP(X14,BBG!$U$63:$Y$123,4,FALSE) -> 0.389 | AJ14: =AI14+J14+AH14+AG14 -> 9.3458099 | AL14: =EOMONTH(E14,1) -> 46660 | AM14: =VLOOKUP(AL14,BBG!$AE$64:$AJ$100,6,FALSE) -> #VALUE! | AN14: =Y15 -> 0.74 | AO14: =VLOOKUP($B14,Freight!$A$3:$G$22,MATCH(FWD!$AO$41,Freight!$A$3:$G$3,0),FALSE) -> 6.9942157 | AP14: =AI14 -> 0.389 | AQ14: =AF14 -> 46691 | AR14: =AM14+AN14+AO14+AP14 -> #VALUE! | AT14: =-(AJ14-AR14) -> #VALUE!
B15: =VLOOKUP(E15,$E$82:$I$118,5,FALSE) -> Q3-27 | C15: =E15 -> 46660 | D15: =EOMONTH(E15,-1)+1 -> 46631 | E15: =EOMONTH(E14,1) -> 46660 | F15: =+INDEX(Sheet1!$B$5:$N$27,MATCH(FWD!$F$3,Sheet1!$B$5:$B$27,0),MATCH(FWD!D15,Sheet1!$B$5:$N$5,0)) -> 1.85 | G15: =BBG!F15-BBG!F17 -> 1.45 | H15: =IF(BBG!$D$5=BBG!$J$5,BBG!F17-BBG!L17,BBG!F17-BBG!L16) -> -5.93 | I15: =I14 -> 0 | J15: =SUM(F15:I15) -> -2.63 | K15: =BBG!G74+FWD!F15 -> -3.5945 | M15: =EOMONTH(E15,0) -> 46660 | N15: =IFERROR(VLOOKUP($C15,Freight!$A$3:$F$17,MATCH(FWD!$N$41,Freight!$A$3:$F$3,0),FALSE)+$B$7,VLOOKUP($B15,Freight!$A$3:$F$17,MATCH(FWD!$N$41,Freight!$A$3:$F$3,0),FALSE)+$B$7) -> 5.4849453 | O15: =VLOOKUP(EOMONTH(M15,0),BBG!$N$63:$R$123,5,FALSE) -> 1.06 | P15: =J15+N15-O15 -> 1.7949453 | Q15: =$B$5 -> 0.03 | R15: =IFERROR(VLOOKUP($C15,Freight!$A$3:$F$22,MATCH(FWD!$U$41,Freight!$A$3:$F$3,0),FALSE),VLOOKUP($B15,Freight!$A$3:$F$22,MATCH(FWD!$U$41,Freight!$A$3:$F$3,0),FALSE)) -> 1.4183049 | S15: =INDEX(BBG!$H$4:$L$53,MATCH(FWD!$M15,BBG!$H$4:$H$53,0),MATCH("Settle",BBG!$H$4:$L$4,0))-INDEX(BBG!$H$4:$L$53,MATCH(FWD!$M17,BBG!$H$4:$H$53,0),MATCH("Settle",BBG!$H$4:$L$4,0)) -> 1.76 | T15: =O15 -> 1.06 | U15: =SUM(Q15:S15)-T15 -> 2.1483049 | V15: =U15-P15 -> 0.35335963 | X15: =EOMONTH(M15,1) -> 46691 | Y15: =IF(BBG!$D$5=BBG!$J$5,BBG!L18-BBG!L19,BBG!L17-BBG!L18) -> 0.74 | Z15: =IFERROR(VLOOKUP($C15,Freight!$A$3:$F$17,MATCH(FWD!$N$41,Freight!$A$3:$F$3,0),FALSE)+$B$7,VLOOKUP($B15,Freight!$A$3:$F$17,MATCH(FWD!$N$41,Freight!$A$3:$F$3,0),FALSE)+$B$7) -> 5.4849453 | AA15: =VLOOKUP(EOMONTH(X15,0),BBG!$N$63:$R$123,5,FALSE) -> 0.99 | AB15: =J15+Y15+Z15-AA15 -> 2.6049453 | AC15: =U16 -> 2.245593 | AD15: =AC15-AB15 -> -0.35935226 | AF15: =EOMONTH(E15,2) -> 46721 | AG15: =IF(BBG!$D$5=BBG!$J$5,BBG!L17-BBG!L19,BBG!L16-BBG!L18)*2/3 -> 1.0133333 | AH15: =IFERROR(VLOOKUP($C15,Freight!$A$3:$F$22,MATCH(FWD!$AH$41,Freight!$A$3:$F$3,0),FALSE)+$B$7,VLOOKUP($B15,Freight!$A$3:$F$22,MATCH(FWD!$AH$41,Freight!$A$3:$F$3,0),FALSE)+$B$7) -> 10.493477 | AI15: =VLOOKUP(X15,BBG!$U$63:$Y$123,4,FALSE) -> 0.41 | AJ15: =AI15+J15+AH15+AG15 -> 9.2868099 | AL15: =EOMONTH(E15,1) -> 46691 | AM15: =VLOOKUP(AL15,BBG!$AE$64:$AJ$100,6,FALSE) -> #VALUE! | AN15: =Y16 -> 0.69 | AO15: =VLOOKUP($B15,Freight!$A$3:$G$22,MATCH(FWD!$AO$41,Freight!$A$3:$G$3,0),FALSE) -> 6.9942157 | AP15: =AI15 -> 0.41 | AQ15: =AF15 -> 46721 | AR15: =AM15+AN15+AO15+AP15 -> #VALUE! | AT15: =-(AJ15-AR15) -> #VALUE!
B16: =VLOOKUP(E16,$E$82:$I$118,5,FALSE) -> Q4-27 | C16: =E16 -> 46691 | D16: =EOMONTH(E16,-1)+1 -> 46661 | E16: =EOMONTH(E15,1) -> 46691 | F16: =IFERROR(INDEX(Sheet1!$B$5:$N$27,MATCH(FWD!$F$3,Sheet1!$B$5:$B$27,0),MATCH(FWD!D16,Sheet1!$B$5:$N$5,0)),F15) -> 1.85 | G16: =BBG!F16-BBG!F18 -> 1.34 | H16: =IF(BBG!$D$5=BBG!$J$5,BBG!F18-BBG!L18,BBG!F18-BBG!L17) -> -5.81 | I16: =I15 -> 0 | J16: =SUM(F16:I16) -> -2.62 | K16: =BBG!G75+FWD!F16 -> -3.4848 | M16: =EOMONTH(E16,0) -> 46691 | N16: =IFERROR(VLOOKUP($C16,Freight!$A$3:$F$22,MATCH(FWD!$N$41,Freight!$A$3:$F$3,0),FALSE)+$B$7,VLOOKUP($B16,Freight!$A$3:$F$22,MATCH(FWD!$N$41,Freight!$A$3:$F$3,0),FALSE)+$B$7) -> 5.6382294 | O16: =VLOOKUP(EOMONTH(M16,0),BBG!$N$63:$R$123,5,FALSE) -> 0.99 | P16: =J16+N16-O16 -> 2.0282294 | Q16: =$B$5 -> 0.03 | R16: =IFERROR(VLOOKUP($C16,Freight!$A$3:$F$22,MATCH(FWD!$U$41,Freight!$A$3:$F$3,0),FALSE),VLOOKUP($B16,Freight!$A$3:$F$22,MATCH(FWD!$U$41,Freight!$A$3:$F$3,0),FALSE)) -> 1.595593 | S16: =INDEX(BBG!$H$4:$L$53,MATCH(FWD!$M16,BBG!$H$4:$H$53,0),MATCH("Settle",BBG!$H$4:$L$4,0))-INDEX(BBG!$H$4:$L$53,MATCH(FWD!$M18,BBG!$H$4:$H$53,0),MATCH("Settle",BBG!$H$4:$L$4,0)) -> 1.61 | T16: =O16 -> 0.99 | U16: =SUM(Q16:S16)-T16 -> 2.245593 | V16: =U16-P16 -> 0.21736359 | X16: =EOMONTH(M16,1) -> 46721 | Y16: =IF(BBG!$D$5=BBG!$J$5,BBG!L19-BBG!L20,BBG!L18-BBG!L19) -> 0.69 | Z16: =IFERROR(VLOOKUP($C17,Freight!$A$3:$F$22,MATCH(FWD!$N$41,Freight!$A$3:$F$3,0),FALSE)+$B$7,VLOOKUP($B17,Freight!$A$3:$F$22,MATCH(FWD!$N$41,Freight!$A$3:$F$3,0),FALSE)+$B$7) -> 5.6382294 | AA16: =VLOOKUP(EOMONTH(X16,0),BBG!$N$63:$R$123,5,FALSE) -> 0.93 | AB16: =J16+Y16+Z16-AA16 -> 2.7782294 | AC16: =U17 -> 2.215593 | AD16: =AC16-AB16 -> -0.56263641 | AF16: =EOMONTH(E16,2) -> 46752 | AG16: =IF(BBG!$D$5=BBG!$J$5,BBG!L18-BBG!L20,BBG!L17-BBG!L19)*2/3 -> 0.95333333 | AH16: =IFERROR(VLOOKUP($C16,Freight!$A$3:$F$22,MATCH(FWD!$AH$41,Freight!$A$3:$F$3,0),FALSE)+$B$7,VLOOKUP($B16,Freight!$A$3:$F$22,MATCH(FWD!$AH$41,Freight!$A$3:$F$3,0),FALSE)+$B$7) -> 11.469086 | AI16: =VLOOKUP(X16,BBG!$U$63:$Y$123,4,FALSE) -> 0.41 | AJ16: =AI16+J16+AH16+AG16 -> 10.21242 | AL16: =EOMONTH(E16,1) -> 46721 | AM16: =VLOOKUP(AL16,BBG!$AE$64:$AJ$100,6,FALSE) -> #VALUE! | AN16: =Y17 -> 0.6 | AO16: =VLOOKUP($B16,Freight!$A$3:$G$22,MATCH(FWD!$AO$41,Freight!$A$3:$G$3,0),FALSE) -> 5.1809005 | AP16: =AI16 -> 0.41 | AQ16: =AF16 -> 46752 | AR16: =AM16+AN16+AO16+AP16 -> #VALUE! | AT16: =-(AJ16-AR16) -> #VALUE!
B17: =VLOOKUP(E17,$E$82:$I$118,5,FALSE) -> Q4-27 | C17: =E17 -> 46721 | D17: =_xlfn.XLOOKUP(B17,$I$82:$I$125,$J$82:$J$125) -> 2Q27 | E17: =EOMONTH(E16,1) -> 46721 | F17: =INDEX(Sheet1!$B$38:$N$49,MATCH("MEH",Sheet1!$B$38:$B$49,0),MATCH(FWD!D17,Sheet1!$B$38:$N$38,0)) -> 1.8 | G17: =BBG!F17-BBG!F19 -> 1.26 | H17: =IF(BBG!$D$5=BBG!$J$5,BBG!F19-BBG!L19,BBG!F19-BBG!L18) -> -5.67 | I17: =I16 -> 0 | J17: =SUM(F17:I17) -> -2.61 | K17: =BBG!G76+FWD!F17 -> -3.4086 | M17: =EOMONTH(E17,0) -> 46721 | N17: =IFERROR(VLOOKUP($C17,Freight!$A$3:$F$22,MATCH(FWD!$N$41,Freight!$A$3:$F$3,0),FALSE)+$B$7,VLOOKUP($B17,Freight!$A$3:$F$22,MATCH(FWD!$N$41,Freight!$A$3:$F$3,0),FALSE)+$B$7) -> 5.6382294 | O17: =VLOOKUP(EOMONTH(M17,0),BBG!$N$63:$R$123,5,FALSE) -> 0.93 | P17: =J17+N17-O17 -> 2.0982294 | Q17: =$B$5 -> 0.03 | R17: =IFERROR(VLOOKUP($C17,Freight!$A$3:$F$22,MATCH(FWD!$U$41,Freight!$A$3:$F$3,0),FALSE),VLOOKUP($B17,Freight!$A$3:$F$22,MATCH(FWD!$U$41,Freight!$A$3:$F$3,0),FALSE)) -> 1.595593 | S17: =INDEX(BBG!$H$4:$L$53,MATCH(FWD!$M17,BBG!$H$4:$H$53,0),MATCH("Settle",BBG!$H$4:$L$4,0))-INDEX(BBG!$H$4:$L$53,MATCH(FWD!$M19,BBG!$H$4:$H$53,0),MATCH("Settle",BBG!$H$4:$L$4,0)) -> 1.52 | T17: =O17 -> 0.93 | U17: =SUM(Q17:S17)-T17 -> 2.215593 | V17: =U17-P17 -> 0.11736359 | X17: =EOMONTH(M17,1) -> 46752 | Y17: =IF(BBG!$D$5=BBG!$J$5,BBG!L20-BBG!L21,BBG!L19-BBG!L20) -> 0.6 | Z17: =IFERROR(VLOOKUP($C18,Freight!$A$3:$F$22,MATCH(FWD!$N$41,Freight!$A$3:$F$3,0),FALSE)+$B$7,VLOOKUP($B18,Freight!$A$3:$F$22,MATCH(FWD!$N$41,Freight!$A$3:$F$3,0),FALSE)+$B$7) -> 5.6382294 | AA17: =VLOOKUP(EOMONTH(X17,0),BBG!$N$63:$R$123,5,FALSE) -> 0.87 | AB17: =J17+Y17+Z17-AA17 -> 2.7582294 | AC17: =U18 -> 2.185593 | AD17: =AC17-AB17 -> -0.57263641 | AF17: =EOMONTH(E17,2) -> 46783 | AG17: =IF(BBG!$D$5=BBG!$J$5,BBG!L19-BBG!L21,BBG!L18-BBG!L20)*2/3 -> 0.86 | AH17: =IFERROR(VLOOKUP($C17,Freight!$A$3:$F$22,MATCH(FWD!$AH$41,Freight!$A$3:$F$3,0),FALSE)+$B$7,VLOOKUP($B17,Freight!$A$3:$F$22,MATCH(FWD!$AH$41,Freight!$A$3:$F$3,0),FALSE)+$B$7) -> 11.469086 | AI17: =VLOOKUP(X17,BBG!$U$63:$Y$123,4,FALSE) -> 0.41 | AJ17: =AI17+J17+AH17+AG17 -> 10.129086 | AL17: =EOMONTH(E17,1) -> 46752 | AM17: =VLOOKUP(AL17,BBG!$AE$64:$AJ$100,6,FALSE) -> #VALUE! | AN17: =Y18 -> 0.53 | AO17: =VLOOKUP($B17,Freight!$A$3:$G$22,MATCH(FWD!$AO$41,Freight!$A$3:$G$3,0),FALSE) -> 5.1809005 | AP17: =AI17 -> 0.41 | AQ17: =AF17 -> 46783 | AR17: =AM17+AN17+AO17+AP17 -> #VALUE! | AT17: =-(AJ17-AR17) -> #VALUE!
B18: =VLOOKUP(E18,$E$82:$I$118,5,FALSE) -> Q4-27 | C18: =E18 -> 46752 | D18: =_xlfn.XLOOKUP(B18,$I$82:$I$125,$J$82:$J$125) -> 2Q27 | E18: =EOMONTH(E17,1) -> 46752 | F18: =INDEX(Sheet1!$B$38:$N$49,MATCH("MEH",Sheet1!$B$38:$B$49,0),MATCH(FWD!D18,Sheet1!$B$38:$N$38,0)) -> 1.8 | G18: =BBG!F18-BBG!F20 -> 1.17 | H18: =IF(BBG!$D$5=BBG!$J$5,BBG!F20-BBG!L20,BBG!F20-BBG!L19) -> -5.55 | I18: =I17 -> 0 | J18: =SUM(F18:I18) -> -2.58 | K18: =BBG!G77+FWD!F18 -> -3.3329 | M18: =EOMONTH(E18,0) -> 46752 | N18: =IFERROR(VLOOKUP($C18,Freight!$A$3:$F$22,MATCH(FWD!$N$41,Freight!$A$3:$F$3,0),FALSE)+$B$7,VLOOKUP($B18,Freight!$A$3:$F$22,MATCH(FWD!$N$41,Freight!$A$3:$F$3,0),FALSE)+$B$7) -> 5.6382294 | O18: =VLOOKUP(EOMONTH(M18,0),BBG!$N$63:$R$123,5,FALSE) -> 0.87 | P18: =J18+N18-O18 -> 2.1882294 | Q18: =$B$5 -> 0.03 | R18: =IFERROR(VLOOKUP($C18,Freight!$A$3:$F$22,MATCH(FWD!$U$41,Freight!$A$3:$F$3,0),FALSE),VLOOKUP($B18,Freight!$A$3:$F$22,MATCH(FWD!$U$41,Freight!$A$3:$F$3,0),FALSE)) -> 1.595593 | S18: =INDEX(BBG!$H$4:$L$53,MATCH(FWD!$M18,BBG!$H$4:$H$53,0),MATCH("Settle",BBG!$H$4:$L$4,0))-INDEX(BBG!$H$4:$L$53,MATCH(FWD!$M20,BBG!$H$4:$H$53,0),MATCH("Settle",BBG!$H$4:$L$4,0)) -> 1.43 | T18: =O18 -> 0.87 | U18: =SUM(Q18:S18)-T18 -> 2.185593 | V18: =U18-P18 -> -0.0026364093 | X18: =EOMONTH(M18,1) -> 46783 | Y18: =IF(BBG!$D$5=BBG!$J$5,BBG!L21-BBG!L22,BBG!L20-BBG!L21) -> 0.53 | Z18: =IFERROR(VLOOKUP($C19,Freight!$A$3:$F$22,MATCH(FWD!$N$41,Freight!$A$3:$F$3,0),FALSE)+$B$7,VLOOKUP($B19,Freight!$A$3:$F$22,MATCH(FWD!$N$41,Freight!$A$3:$F$3,0),FALSE)+$B$7) -> 4.6674298 | AA18: =VLOOKUP(EOMONTH(X18,0),BBG!$N$63:$R$123,5,FALSE) -> 0.82 | AB18: =J18+Y18+Z18-AA18 -> 1.7974298 | AC18: =U19 -> 1.9626269 | AD18: =AC18-AB18 -> 0.16519713 | AF18: =EOMONTH(E18,2) -> 46812 | AG18: =IF(BBG!$D$5=BBG!$J$5,BBG!L20-BBG!L22,BBG!L19-BBG!L21)*2/3 -> 0.75333333 | AH18: =IFERROR(VLOOKUP($C18,Freight!$A$3:$F$22,MATCH(FWD!$AH$41,Freight!$A$3:$F$3,0),FALSE)+$B$7,VLOOKUP($B18,Freight!$A$3:$F$22,MATCH(FWD!$AH$41,Freight!$A$3:$F$3,0),FALSE)+$B$7) -> 11.469086 | AI18: =VLOOKUP(X18,BBG!$U$63:$Y$123,4,FALSE) -> 0.44 | AJ18: =AI18+J18+AH18+AG18 -> 10.08242 | AL18: =EOMONTH(E18,1) -> 46783 | AM18: =VLOOKUP(AL18,BBG!$AE$64:$AJ$100,6,FALSE) -> #VALUE! | AN18: =Y19 -> 0.47 | AO18: =VLOOKUP($B18,Freight!$A$3:$G$22,MATCH(FWD!$AO$41,Freight!$A$3:$G$3,0),FALSE) -> 5.1809005 | AP18: =AI18 -> 0.44 | AQ18: =AF18 -> 46812 | AR18: =AM18+AN18+AO18+AP18 -> #VALUE! | AT18: =-(AJ18-AR18) -> #VALUE!
B19: =VLOOKUP(E19,$E$82:$I$118,5,FALSE) -> Q1-28 | C19: =E19 -> 46783 | D19: =_xlfn.XLOOKUP(B19,$I$82:$I$125,$J$82:$J$125) -> 3Q27 | E19: =EOMONTH(E18,1) -> 46783 | F19: =INDEX(Sheet1!$B$38:$N$49,MATCH("MEH",Sheet1!$B$38:$B$49,0),MATCH(FWD!D19,Sheet1!$B$38:$N$38,0)) -> 1.85 | G19: =BBG!F19-BBG!F21 -> 1.08 | H19: =IF(BBG!$D$5=BBG!$J$5,BBG!F21-BBG!L21,BBG!F21-BBG!L20) -> -5.46 | I19: =I18 -> 0 | J19: =SUM(F19:I19) -> -2.53 | K19: =BBG!G78+FWD!F19 -> -3.2548 | M19: =EOMONTH(E19,0) -> 46783 | N19: =IFERROR(VLOOKUP($C19,Freight!$A$3:$F$22,MATCH(FWD!$N$41,Freight!$A$3:$F$3,0),FALSE)+$B$7,VLOOKUP($B19,Freight!$A$3:$F$22,MATCH(FWD!$N$41,Freight!$A$3:$F$3,0),FALSE)+$B$7) -> 4.6674298 | O19: =VLOOKUP(EOMONTH(M19,0),BBG!$N$63:$R$123,5,FALSE) -> 0.82 | P19: =J19+N19-O19 -> 1.3174298 | Q19: =$B$5 -> 0.03 | R19: =IFERROR(VLOOKUP($C19,Freight!$A$3:$F$22,MATCH(FWD!$U$41,Freight!$A$3:$F$3,0),FALSE),VLOOKUP($B19,Freight!$A$3:$F$22,MATCH(FWD!$U$41,Freight!$A$3:$F$3,0),FALSE)) -> 1.4626269 | S19: =INDEX(BBG!$H$4:$L$53,MATCH(FWD!$M19,BBG!$H$4:$H$53,0),MATCH("Settle",BBG!$H$4:$L$4,0))-INDEX(BBG!$H$4:$L$53,MATCH(FWD!$M21,BBG!$H$4:$H$53,0),MATCH("Settle",BBG!$H$4:$L$4,0)) -> 1.29 | T19: =O19 -> 0.82 | U19: =SUM(Q19:S19)-T19 -> 1.9626269 | V19: =U19-P19 -> 0.64519713 | X19: =EOMONTH(M19,1) -> 46812 | Y19: =IF(BBG!$D$5=BBG!$J$5,BBG!L22-BBG!L23,BBG!L21-BBG!L22) -> 0.47 | Z19: =IFERROR(VLOOKUP($C20,Freight!$A$3:$F$22,MATCH(FWD!$N$41,Freight!$A$3:$F$3,0),FALSE)+$B$7,VLOOKUP($B20,Freight!$A$3:$F$22,MATCH(FWD!$N$41,Freight!$A$3:$F$3,0),FALSE)+$B$7) -> 4.6674298 | AA19: =VLOOKUP(EOMONTH(X19,0),BBG!$N$63:$R$123,5,FALSE) -> 0.76 | AB19: =J19+Y19+Z19-AA19 -> 1.8474298 | AC19: =U20 -> 1.8626269 | AD19: =AC19-AB19 -> 0.015197126 | AF19: =EOMONTH(E19,2) -> 46843 | AG19: =IF(BBG!$D$5=BBG!$J$5,BBG!L21-BBG!L23,BBG!L20-BBG!L22)*2/3 -> 0.66666667 | AH19: =IFERROR(VLOOKUP($C19,Freight!$A$3:$F$22,MATCH(FWD!$AH$41,Freight!$A$3:$F$3,0),FALSE)+$B$7,VLOOKUP($B19,Freight!$A$3:$F$22,MATCH(FWD!$AH$41,Freight!$A$3:$F$3,0),FALSE)+$B$7) -> 11.712989 | AI19: =VLOOKUP(X19,BBG!$U$63:$Y$123,4,FALSE) -> 0.44 | AJ19: =AI19+J19+AH19+AG19 -> 10.289655 | AL19: =EOMONTH(E19,1) -> 46812 | AM19: =VLOOKUP(AL19,BBG!$AE$64:$AJ$100,6,FALSE) -> #VALUE! | AN19: =Y20 -> 0.44 | AO19: =VLOOKUP($B19,Freight!$A$3:$G$22,MATCH(FWD!$AO$41,Freight!$A$3:$G$3,0),FALSE) -> 3.8727232 | AP19: =AI19 -> 0.44 | AQ19: =AF19 -> 46843 | AR19: =AM19+AN19+AO19+AP19 -> #VALUE! | AT19: =-(AJ19-AR19) -> #VALUE!
B20: =VLOOKUP(E20,$E$82:$I$118,5,FALSE) -> Q1-28 | C20: =E20 -> 46812 | D20: =_xlfn.XLOOKUP(B20,$I$82:$I$125,$J$82:$J$125) -> 3Q27 | E20: =EOMONTH(E19,1) -> 46812 | F20: =INDEX(Sheet1!$B$38:$N$49,MATCH("MEH",Sheet1!$B$38:$B$49,0),MATCH(FWD!D20,Sheet1!$B$38:$N$38,0)) -> 1.85 | G20: =BBG!F20-BBG!F22 -> 0.98 | H20: =IF(BBG!$D$5=BBG!$J$5,BBG!F22-BBG!L22,BBG!F22-BBG!L21) -> -5.4 | I20: =I19 -> 0 | J20: =SUM(F20:I20) -> -2.57 | K20: =BBG!G79+FWD!F20 -> -3.1776 | M20: =EOMONTH(E20,0) -> 46812 | N20: =IFERROR(VLOOKUP($C20,Freight!$A$3:$F$22,MATCH(FWD!$N$41,Freight!$A$3:$F$3,0),FALSE)+$B$7,VLOOKUP($B20,Freight!$A$3:$F$22,MATCH(FWD!$N$41,Freight!$A$3:$F$3,0),FALSE)+$B$7) -> 4.6674298 | O20: =VLOOKUP(EOMONTH(M20,0),BBG!$N$63:$R$123,5,FALSE) -> 0.76 | P20: =J20+N20-O20 -> 1.3374298 | Q20: =$B$5 -> 0.03 | R20: =IFERROR(VLOOKUP($C20,Freight!$A$3:$F$22,MATCH(FWD!$U$41,Freight!$A$3:$F$3,0),FALSE),VLOOKUP($B20,Freight!$A$3:$F$22,MATCH(FWD!$U$41,Freight!$A$3:$F$3,0),FALSE)) -> 1.4626269 | S20: =INDEX(BBG!$H$4:$L$53,MATCH(FWD!$M20,BBG!$H$4:$H$53,0),MATCH("Settle",BBG!$H$4:$L$4,0))-INDEX(BBG!$H$4:$L$53,MATCH(FWD!$M22,BBG!$H$4:$H$53,0),MATCH("Settle",BBG!$H$4:$L$4,0)) -> 1.13 | T20: =O20 -> 0.76 | U20: =SUM(Q20:S20)-T20 -> 1.8626269 | V20: =U20-P20 -> 0.52519713 | X20: =EOMONTH(M20,1) -> 46843 | Y20: =IF(BBG!$D$5=BBG!$J$5,BBG!L23-BBG!L24,BBG!L22-BBG!L23) -> 0.44 | Z20: =IFERROR(VLOOKUP($C21,Freight!$A$3:$F$22,MATCH(FWD!$N$41,Freight!$A$3:$F$3,0),FALSE)+$B$7,VLOOKUP($B21,Freight!$A$3:$F$22,MATCH(FWD!$N$41,Freight!$A$3:$F$3,0),FALSE)+$B$7) -> 4.6674298 | AA20: =VLOOKUP(EOMONTH(X20,0),BBG!$N$63:$R$123,5,FALSE) -> 0.72 | AB20: =J20+Y20+Z20-AA20 -> 1.8174298 | AC20: =U21 -> 1.7726269 | AD20: =AC20-AB20 -> -0.044802874 | AF20: =EOMONTH(E20,2) -> 46873 | AG20: =IF(BBG!$D$5=BBG!$J$5,BBG!L22-BBG!L24,BBG!L21-BBG!L23)*2/3 -> 0.60666667 | AH20: =IFERROR(VLOOKUP($C20,Freight!$A$3:$F$22,MATCH(FWD!$AH$41,Freight!$A$3:$F$3,0),FALSE)+$B$7,VLOOKUP($B20,Freight!$A$3:$F$22,MATCH(FWD!$AH$41,Freight!$A$3:$F$3,0),FALSE)+$B$7) -> 11.712989 | AI20: =VLOOKUP(X20,BBG!$U$63:$Y$123,4,FALSE) -> 0.44 | AJ20: =AI20+J20+AH20+AG20 -> 10.189655 | AL20: =EOMONTH(E20,1) -> 46843 | AM20: =VLOOKUP(AL20,BBG!$AE$64:$AJ$100,6,FALSE) -> #VALUE! | AN20: =Y21 -> 0.44 | AO20: =VLOOKUP($B20,Freight!$A$3:$G$22,MATCH(FWD!$AO$41,Freight!$A$3:$G$3,0),FALSE) -> 3.8727232 | AP20: =AI20 -> 0.44 | AQ20: =AF20 -> 46873 | AR20: =AM20+AN20+AO20+AP20 -> #VALUE! | AT20: =-(AJ20-AR20) -> #VALUE!
B21: =VLOOKUP(E21,$E$82:$I$118,5,FALSE) -> Q1-28 | C21: =E21 -> 46843 | D21: =_xlfn.XLOOKUP(B21,$I$82:$I$125,$J$82:$J$125) -> 3Q27 | E21: =EOMONTH(E20,1) -> 46843 | F21: =INDEX(Sheet1!$B$38:$N$49,MATCH("MEH",Sheet1!$B$38:$B$49,0),MATCH(FWD!D21,Sheet1!$B$38:$N$38,0)) -> 1.85 | G21: =BBG!F21-BBG!F23 -> 0.89 | H21: =IF(BBG!$D$5=BBG!$J$5,BBG!F23-BBG!L23,BBG!F23-BBG!L22) -> -5.35 | I21: =I20 -> 0 | J21: =SUM(F21:I21) -> -2.61 | K21: =BBG!G80+FWD!F21 -> -3.2109 | M21: =EOMONTH(E21,0) -> 46843 | N21: =IFERROR(VLOOKUP($C21,Freight!$A$3:$F$22,MATCH(FWD!$N$41,Freight!$A$3:$F$3,0),FALSE)+$B$7,VLOOKUP($B21,Freight!$A$3:$F$22,MATCH(FWD!$N$41,Freight!$A$3:$F$3,0),FALSE)+$B$7) -> 4.6674298 | O21: =VLOOKUP(EOMONTH(M21,0),BBG!$N$63:$R$123,5,FALSE) -> 0.72 | P21: =J21+N21-O21 -> 1.3374298 | Q21: =$B$5 -> 0.03 | R21: =IFERROR(VLOOKUP($C21,Freight!$A$3:$F$22,MATCH(FWD!$U$41,Freight!$A$3:$F$3,0),FALSE),VLOOKUP($B21,Freight!$A$3:$F$22,MATCH(FWD!$U$41,Freight!$A$3:$F$3,0),FALSE)) -> 1.4626269 | S21: =INDEX(BBG!$H$4:$L$53,MATCH(FWD!$M21,BBG!$H$4:$H$53,0),MATCH("Settle",BBG!$H$4:$L$4,0))-INDEX(BBG!$H$4:$L$53,MATCH(FWD!$M23,BBG!$H$4:$H$53,0),MATCH("Settle",BBG!$H$4:$L$4,0)) -> 1 | T21: =O21 -> 0.72 | U21: =SUM(Q21:S21)-T21 -> 1.7726269 | V21: =U21-P21 -> 0.43519713 | X21: =EOMONTH(M21,1) -> 46873 | Y21: =IF(BBG!$D$5=BBG!$J$5,BBG!L24-BBG!L25,BBG!L23-BBG!L24) -> 0.44 | Z21: =IFERROR(VLOOKUP($C22,Freight!$A$3:$F$22,MATCH(FWD!$N$41,Freight!$A$3:$F$3,0),FALSE)+$B$7,VLOOKUP($B22,Freight!$A$3:$F$22,MATCH(FWD!$N$41,Freight!$A$3:$F$3,0),FALSE)+$B$7) -> 4.4630509 | AA21: =VLOOKUP(EOMONTH(X21,0),BBG!$N$63:$R$123,5,FALSE) -> 0.68 | AB21: =J21+Y21+Z21-AA21 -> 1.6130509 | AC21: =U22 -> 1.5453388 | AD21: =AC21-AB21 -> -0.067712118 | AF21: =EOMONTH(E21,2) -> 46904 | AG21: =IF(BBG!$D$5=BBG!$J$5,BBG!L23-BBG!L25,BBG!L22-BBG!L24)*2/3 -> 0.58666667 | AH21: =IFERROR(VLOOKUP($C21,Freight!$A$3:$F$22,MATCH(FWD!$AH$41,Freight!$A$3:$F$3,0),FALSE)+$B$7,VLOOKUP($B21,Freight!$A$3:$F$22,MATCH(FWD!$AH$41,Freight!$A$3:$F$3,0),FALSE)+$B$7) -> 11.712989 | AI21: =VLOOKUP(X21,BBG!$U$63:$Y$123,4,FALSE) -> 0.44 | AJ21: =AI21+J21+AH21+AG21 -> 10.129655 | AL21: =EOMONTH(E21,1) -> 46873 | AM21: =VLOOKUP(AL21,BBG!$AE$64:$AJ$100,6,FALSE) -> #VALUE! | AN21: =Y22 -> 0.43 | AO21: =VLOOKUP($B21,Freight!$A$3:$G$22,MATCH(FWD!$AO$41,Freight!$A$3:$G$3,0),FALSE) -> 3.8727232 | AP21: =AI21 -> 0.44 | AQ21: =AF21 -> 46904 | AR21: =AM21+AN21+AO21+AP21 -> #VALUE! | AT21: =-(AJ21-AR21) -> #VALUE!
B22: =VLOOKUP(E22,$E$82:$I$118,5,FALSE) -> Q2-28 | C22: =E22 -> 46873 | D22: =_xlfn.XLOOKUP(B22,$I$82:$I$125,$J$82:$J$125) -> 4Q27 | E22: =EOMONTH(E21,1) -> 46873 | F22: =INDEX(Sheet1!$B$38:$N$49,MATCH("MEH",Sheet1!$B$38:$B$49,0),MATCH(FWD!D22,Sheet1!$B$38:$N$38,0)) -> 1.9 | G22: =BBG!F22-BBG!F24 -> 0.83 | H22: =IF(BBG!$D$5=BBG!$J$5,BBG!F24-BBG!L24,BBG!F24-BBG!L23) -> -5.32 | I22: =I21 -> 0 | J22: =SUM(F22:I22) -> -2.59 | K22: =BBG!G81+FWD!F22 -> -3.1168 | M22: =EOMONTH(E22,0) -> 46873 | N22: =IFERROR(VLOOKUP($C22,Freight!$A$3:$F$22,MATCH(FWD!$N$41,Freight!$A$3:$F$3,0),FALSE)+$B$7,VLOOKUP($B22,Freight!$A$3:$F$22,MATCH(FWD!$N$41,Freight!$A$3:$F$3,0),FALSE)+$B$7) -> 4.4630509 | O22: =VLOOKUP(EOMONTH(M22,0),BBG!$N$63:$R$123,5,FALSE) -> 0.68 | P22: =J22+N22-O22 -> 1.1930509 | Q22: =$B$5 -> 0.03 | R22: =IFERROR(VLOOKUP($C22,Freight!$A$3:$F$22,MATCH(FWD!$U$41,Freight!$A$3:$F$3,0),FALSE),VLOOKUP($B22,Freight!$A$3:$F$22,MATCH(FWD!$U$41,Freight!$A$3:$F$3,0),FALSE)) -> 1.2853388 | S22: =INDEX(BBG!$H$4:$L$53,MATCH(FWD!$M22,BBG!$H$4:$H$53,0),MATCH("Settle",BBG!$H$4:$L$4,0))-INDEX(BBG!$H$4:$L$53,MATCH(FWD!$M24,BBG!$H$4:$H$53,0),MATCH("Settle",BBG!$H$4:$L$4,0)) -> 0.91 | T22: =O22 -> 0.68 | U22: =SUM(Q22:S22)-T22 -> 1.5453388 | V22: =U22-P22 -> 0.35228788 | X22: =EOMONTH(M22,1) -> 46904 | Y22: =IF(BBG!$D$5=BBG!$J$5,BBG!L26-BBG!L27,BBG!L25-BBG!L26) -> 0.43 | Z22: =IFERROR(VLOOKUP($C23,Freight!$A$3:$F$22,MATCH(FWD!$N$41,Freight!$A$3:$F$3,0),FALSE)+$B$7,VLOOKUP($B23,Freight!$A$3:$F$22,MATCH(FWD!$N$41,Freight!$A$3:$F$3,0),FALSE)+$B$7) -> 4.4630509 | AA22: =VLOOKUP(EOMONTH(X22,0),BBG!$N$63:$R$123,5,FALSE) -> 0.64 | AB22: =J22+Y22+Z22-AA22 -> 1.6630509 | AC22: =U23 -> 1.5553388 | AD22: =AC22-AB22 -> -0.10771212 | AF22: =EOMONTH(E22,2) -> 46934 | AG22: =IF(BBG!$D$5=BBG!$J$5,BBG!L24-BBG!L26,BBG!L23-BBG!L25)*2/3 -> 0.59333333 | AH22: =IFERROR(VLOOKUP($C22,Freight!$A$3:$F$22,MATCH(FWD!$AH$41,Freight!$A$3:$F$3,0),FALSE)+$B$7,VLOOKUP($B22,Freight!$A$3:$F$22,MATCH(FWD!$AH$41,Freight!$A$3:$F$3,0),FALSE)+$B$7) -> 10.737379 | AI22: =VLOOKUP(X22,BBG!$U$63:$Y$123,4,FALSE) -> 0.44 | AJ22: =AI22+J22+AH22+AG22 -> 9.1807124 | AL22: =EOMONTH(E22,1) -> 46904 | AM22: =VLOOKUP(AL22,BBG!$AE$64:$AJ$100,6,FALSE) -> #VALUE! | AN22: =Y23 -> 0.43 | AO22: =VLOOKUP($B22,Freight!$A$3:$G$22,MATCH(FWD!$AO$41,Freight!$A$3:$G$3,0),FALSE) -> 3.6136781 | AP22: =AI22 -> 0.44 | AQ22: =AF22 -> 46934 | AR22: =AM22+AN22+AO22+AP22 -> #VALUE! | AT22: =-(AJ22-AR22) -> #VALUE!
B23: =VLOOKUP(E23,$E$82:$I$118,5,FALSE) -> Q2-28 | C23: =E23 -> 46904 | D23: =_xlfn.XLOOKUP(B23,$I$82:$I$125,$J$82:$J$125) -> 4Q27 | E23: =EOMONTH(E22,1) -> 46904 | F23: =INDEX(Sheet1!$B$38:$N$49,MATCH("MEH",Sheet1!$B$38:$B$49,0),MATCH(FWD!D23,Sheet1!$B$38:$N$38,0)) -> 1.9 | G23: =BBG!F23-BBG!F25 -> 0.84 | H23: =IF(BBG!$D$5=BBG!$J$5,BBG!F25-BBG!L25,BBG!F25-BBG!L24) -> -5.31 | I23: =I22 -> 0 | J23: =SUM(F23:I23) -> -2.57 | K23: =BBG!G82+FWD!F23 -> -3.0804 | M23: =EOMONTH(E23,0) -> 46904 | N23: =IFERROR(VLOOKUP($C23,Freight!$A$3:$F$22,MATCH(FWD!$N$41,Freight!$A$3:$F$3,0),FALSE)+$B$7,VLOOKUP($B23,Freight!$A$3:$F$22,MATCH(FWD!$N$41,Freight!$A$3:$F$3,0),FALSE)+$B$7) -> 4.4630509 | O23: =VLOOKUP(EOMONTH(M23,0),BBG!$N$63:$R$123,5,FALSE) -> 0.64 | P23: =J23+N23-O23 -> 1.2530509 | Q23: =$B$5 -> 0.03 | R23: =IFERROR(VLOOKUP($C23,Freight!$A$3:$F$22,MATCH(FWD!$U$41,Freight!$A$3:$F$3,0),FALSE),VLOOKUP($B23,Freight!$A$3:$F$22,MATCH(FWD!$U$41,Freight!$A$3:$F$3,0),FALSE)) -> 1.2853388 | S23: =INDEX(BBG!$H$4:$L$53,MATCH(FWD!$M23,BBG!$H$4:$H$53,0),MATCH("Settle",BBG!$H$4:$L$4,0))-INDEX(BBG!$H$4:$L$53,MATCH(FWD!$M25,BBG!$H$4:$H$53,0),MATCH("Settle",BBG!$H$4:$L$4,0)) -> 0.88 | T23: =O23 -> 0.64 | U23: =SUM(Q23:S23)-T23 -> 1.5553388 | V23: =U23-P23 -> 0.30228788 | X23: =EOMONTH(M23,1) -> 46934 | Y23: =IF(BBG!$D$5=BBG!$J$5,BBG!L27-BBG!L28,BBG!L26-BBG!L27) -> 0.43 | Z23: =IFERROR(VLOOKUP($C24,Freight!$A$3:$F$22,MATCH(FWD!$N$41,Freight!$A$3:$F$3,0),FALSE)+$B$7,VLOOKUP($B24,Freight!$A$3:$F$22,MATCH(FWD!$N$41,Freight!$A$3:$F$3,0),FALSE)+$B$7) -> 4.4630509 | AA23: =VLOOKUP(EOMONTH(X23,0),BBG!$N$63:$R$123,5,FALSE) -> 0.6 | AB23: =J23+Y23+Z23-AA23 -> 1.7230509 | AC23: =U24 -> 1.6053388 | AD23: =AC23-AB23 -> -0.11771212 | AF23: =EOMONTH(E23,2) -> 46965 | AG23: =IF(BBG!$D$5=BBG!$J$5,BBG!L25-BBG!L27,BBG!L24-BBG!L26)*2/3 -> 0.58666667 | AH23: =IFERROR(VLOOKUP($C23,Freight!$A$3:$F$22,MATCH(FWD!$AH$41,Freight!$A$3:$F$3,0),FALSE)+$B$7,VLOOKUP($B23,Freight!$A$3:$F$22,MATCH(FWD!$AH$41,Freight!$A$3:$F$3,0),FALSE)+$B$7) -> 10.737379 | AI23: =VLOOKUP(X23,BBG!$U$63:$Y$123,4,FALSE) -> 0.44 | AJ23: =AI23+J23+AH23+AG23 -> 9.1940457 | AL23: =EOMONTH(E23,1) -> 46934 | AM23: =VLOOKUP(AL23,BBG!$AE$64:$AJ$100,6,FALSE) -> #VALUE! | AN23: =Y24 -> 0.4 | AO23: =VLOOKUP($B23,Freight!$A$3:$G$22,MATCH(FWD!$AO$41,Freight!$A$3:$G$3,0),FALSE) -> 3.6136781 | AP23: =AI23 -> 0.44 | AQ23: =AF23 -> 46965 | AR23: =AM23+AN23+AO23+AP23 -> #VALUE! | AT23: =-(AJ23-AR23) -> #VALUE!
B24: =VLOOKUP(E24,$E$82:$I$118,5,FALSE) -> Q2-28 | C24: =E24 -> 46934 | D24: =D25 -> Cal 28 | E24: =EOMONTH(E23,1) -> 46934 | F24: =INDEX(Sheet1!$B$38:$N$49,MATCH("MEH",Sheet1!$B$38:$B$49,0),MATCH(FWD!D24,Sheet1!$B$38:$N$38,0)) -> 1.98 | G24: =BBG!F24-BBG!F26 -> 0.84 | H24: =IF(BBG!$D$5=BBG!$J$5,BBG!F26-BBG!L26,BBG!F26-BBG!L25) -> -5.27 | I24: =I23 -> 0 | J24: =SUM(F24:I24) -> -2.45 | K24: =BBG!G83+FWD!F24 -> -3.0205 | M24: =EOMONTH(E24,0) -> 46934 | N24: =IFERROR(VLOOKUP($C24,Freight!$A$3:$F$22,MATCH(FWD!$N$41,Freight!$A$3:$F$3,0),FALSE)+$B$7,VLOOKUP($B24,Freight!$A$3:$F$22,MATCH(FWD!$N$41,Freight!$A$3:$F$3,0),FALSE)+$B$7) -> 4.4630509 | O24: =VLOOKUP(EOMONTH(M24,0),BBG!$N$63:$R$123,5,FALSE) -> 0.6 | P24: =J24+N24-O24 -> 1.4130509 | Q24: =$B$5 -> 0.03 | R24: =IFERROR(VLOOKUP($C24,Freight!$A$3:$F$22,MATCH(FWD!$U$41,Freight!$A$3:$F$3,0),FALSE),VLOOKUP($B24,Freight!$A$3:$F$22,MATCH(FWD!$U$41,Freight!$A$3:$F$3,0),FALSE)) -> 1.2853388 | S24: =INDEX(BBG!$H$4:$L$53,MATCH(FWD!$M24,BBG!$H$4:$H$53,0),MATCH("Settle",BBG!$H$4:$L$4,0))-INDEX(BBG!$H$4:$L$53,MATCH(FWD!$M26,BBG!$H$4:$H$53,0),MATCH("Settle",BBG!$H$4:$L$4,0)) -> 0.89 | T24: =O24 -> 0.6 | U24: =SUM(Q24:S24)-T24 -> 1.6053388 | V24: =U24-P24 -> 0.19228788 | X24: =EOMONTH(M24,1) -> 46965 | Y24: =IF(BBG!$D$5=BBG!$J$5,BBG!L28-BBG!L29,BBG!L27-BBG!L28) -> 0.4 | Z24: =IFERROR(VLOOKUP($C25,Freight!$A$3:$F$22,MATCH(FWD!$N$41,Freight!$A$3:$F$3,0),FALSE)+$B$7,VLOOKUP($B25,Freight!$A$3:$F$22,MATCH(FWD!$N$41,Freight!$A$3:$F$3,0),FALSE)+$B$7) -> 4.4630509 | AA24: =VLOOKUP(EOMONTH(X24,0),BBG!$N$63:$R$123,5,FALSE) -> 0.55 | AB24: =J24+Y24+Z24-AA24 -> 1.8630509 | AC24: =U25 -> 1.6453388 | AD24: =AC24-AB24 -> -0.21771212 | AF24: =EOMONTH(E24,2) -> 46996 | AG24: =IF(BBG!$D$5=BBG!$J$5,BBG!L26-BBG!L28,BBG!L25-BBG!L27)*2/3 -> 0.57333333 | AH24: =IFERROR(VLOOKUP($C24,Freight!$A$3:$F$22,MATCH(FWD!$AH$41,Freight!$A$3:$F$3,0),FALSE)+$B$7,VLOOKUP($B24,Freight!$A$3:$F$22,MATCH(FWD!$AH$41,Freight!$A$3:$F$3,0),FALSE)+$B$7) -> 10.737379 | AI24: =VLOOKUP(X24,BBG!$U$63:$Y$123,4,FALSE) -> 0.44 | AJ24: =AI24+J24+AH24+AG24 -> 9.3007124 | AL24: =EOMONTH(E24,1) -> 46965 | AM24: =VLOOKUP(AL24,BBG!$AE$64:$AJ$100,6,FALSE) -> #VALUE! | AN24: =Y25 -> 0.34 | AO24: =VLOOKUP($B24,Freight!$A$3:$G$22,MATCH(FWD!$AO$41,Freight!$A$3:$G$3,0),FALSE) -> 3.6136781 | AP24: =AI24 -> 0.44 | AQ24: =AF24 -> 46996 | AR24: =AM24+AN24+AO24+AP24 -> #VALUE! | AT24: =-(AJ24-AR24) -> #VALUE!
B25: Cal-28 | C25: =E25 -> 46965 | D25: Cal 28 | E25: =EOMONTH(E24,1) -> 46965 | F25: =INDEX(Sheet1!$B$38:$N$49,MATCH("MEH",Sheet1!$B$38:$B$49,0),MATCH(FWD!D25,Sheet1!$B$38:$N$38,0)) -> 1.98 | G25: =BBG!F25-BBG!F27 -> 0.79 | H25: =IF(BBG!$D$5=BBG!$J$5,BBG!F27-BBG!L27,BBG!F27-BBG!L26) -> -5.22 | I25: =I24 -> 0 | J25: =SUM(F25:I25) -> -2.45 | K25: =BBG!G84+FWD!F25 -> -2.9695 | M25: =EOMONTH(E25,0) -> 46965 | N25: =IFERROR(VLOOKUP($C25,Freight!$A$3:$F$22,MATCH(FWD!$N$41,Freight!$A$3:$F$3,0),FALSE)+$B$7,VLOOKUP($B25,Freight!$A$3:$F$22,MATCH(FWD!$N$41,Freight!$A$3:$F$3,0),FALSE)+$B$7) -> 4.4630509 | O25: =VLOOKUP(EOMONTH(M25,0),BBG!$N$63:$R$123,5,FALSE) -> 0.55 | P25: =J25+N25-O25 -> 1.4630509 | Q25: =$B$5 -> 0.03 | R25: =IFERROR(VLOOKUP($C25,Freight!$A$3:$F$22,MATCH(FWD!$U$41,Freight!$A$3:$F$3,0),FALSE),VLOOKUP($B25,Freight!$A$3:$F$22,MATCH(FWD!$U$41,Freight!$A$3:$F$3,0),FALSE)) -> 1.2853388 | S25: =INDEX(BBG!$H$4:$L$53,MATCH(FWD!$M25,BBG!$H$4:$H$53,0),MATCH("Settle",BBG!$H$4:$L$4,0))-INDEX(BBG!$H$4:$L$53,MATCH(FWD!$M27,BBG!$H$4:$H$53,0),MATCH("Settle",BBG!$H$4:$L$4,0)) -> 0.88 | T25: =O25 -> 0.55 | U25: =SUM(Q25:S25)-T25 -> 1.6453388 | V25: =U25-P25 -> 0.18228788 | X25: =EOMONTH(M25,1) -> 46996 | Y25: =IF(BBG!$D$5=BBG!$J$5,BBG!L29-BBG!L30,BBG!L28-BBG!L29) -> 0.34 | Z25: =IFERROR(VLOOKUP($C26,Freight!$A$3:$F$22,MATCH(FWD!$N$41,Freight!$A$3:$F$3,0),FALSE)+$B$7,VLOOKUP($B26,Freight!$A$3:$F$22,MATCH(FWD!$N$41,Freight!$A$3:$F$3,0),FALSE)+$B$7) -> 4.4630509 | AA25: =VLOOKUP(EOMONTH(X25,0),BBG!$N$63:$R$123,5,FALSE) -> 0.54 | AB25: =J25+Y25+Z25-AA25 -> 1.8130509 | AC25: =U26 -> 1.6353388 | AD25: =AC25-AB25 -> -0.17771212 | AF25: =EOMONTH(E25,2) -> 47026 | AG25: =IF(BBG!$D$5=BBG!$J$5,BBG!L27-BBG!L29,BBG!L26-BBG!L28)*2/3 -> 0.55333333 | AH25: =IFERROR(VLOOKUP($C25,Freight!$A$3:$F$22,MATCH(FWD!$AH$41,Freight!$A$3:$F$3,0),FALSE)+$B$7,VLOOKUP($B25,Freight!$A$3:$F$22,MATCH(FWD!$AH$41,Freight!$A$3:$F$3,0),FALSE)+$B$7) -> 12.505672 | AI25: =VLOOKUP(X25,BBG!$U$63:$Y$123,4,FALSE) -> 0.44 | AJ25: =AI25+J25+AH25+AG25 -> 11.049005 | AL25: =EOMONTH(E25,1) -> 46996 | AM25: =VLOOKUP(AL25,BBG!$AE$64:$AJ$100,6,FALSE) -> #VALUE! | AN25: =Y26 -> 0.35 | AO25: =VLOOKUP($B25,Freight!$A$3:$G$22,MATCH(FWD!$AO$41,Freight!$A$3:$G$3,0),FALSE) -> 3.6136781 | AP25: =AI25 -> 0.44 | AQ25: =AF25 -> 47026 | AR25: =AM25+AN25+AO25+AP25 -> #VALUE! | AT25: =-(AJ25-AR25) -> #VALUE!
B26: Cal-28 | C26: =E26 -> 46996 | D26: Cal 28 | E26: =EOMONTH(E25,1) -> 46996 | F26: =INDEX(Sheet1!$B$38:$N$49,MATCH("MEH",Sheet1!$B$38:$B$49,0),MATCH(FWD!D26,Sheet1!$B$38:$N$38,0)) -> 1.98 | G26: =BBG!F26-BBG!F28 -> 0.76 | H26: =IF(BBG!$D$5=BBG!$J$5,BBG!F28-BBG!L28,BBG!F28-BBG!L27) -> -5.17 | I26: =I25 -> 0 | J26: =SUM(F26:I26) -> -2.43 | K26: =BBG!G85+FWD!F26 -> -2.9126 | M26: =EOMONTH(E26,0) -> 46996 | N26: =IFERROR(VLOOKUP($C26,Freight!$A$3:$F$22,MATCH(FWD!$N$41,Freight!$A$3:$F$3,0),FALSE)+$B$7,VLOOKUP($B26,Freight!$A$3:$F$22,MATCH(FWD!$N$41,Freight!$A$3:$F$3,0),FALSE)+$B$7) -> 4.4630509 | O26: =VLOOKUP(EOMONTH(M26,0),BBG!$N$63:$R$123,5,FALSE) -> 0.54 | P26: =J26+N26-O26 -> 1.4930509 | Q26: =$B$5 -> 0.03 | R26: =IFERROR(VLOOKUP($C26,Freight!$A$3:$F$22,MATCH(FWD!$U$41,Freight!$A$3:$F$3,0),FALSE),VLOOKUP($B26,Freight!$A$3:$F$22,MATCH(FWD!$U$41,Freight!$A$3:$F$3,0),FALSE)) -> 1.2853388 | S26: =INDEX(BBG!$H$4:$L$53,MATCH(FWD!$M26,BBG!$H$4:$H$53,0),MATCH("Settle",BBG!$H$4:$L$4,0))-INDEX(BBG!$H$4:$L$53,MATCH(FWD!$M28,BBG!$H$4:$H$53,0),MATCH("Settle",BBG!$H$4:$L$4,0)) -> 0.86 | T26: =O26 -> 0.54 | U26: =SUM(Q26:S26)-T26 -> 1.6353388 | V26: =U26-P26 -> 0.14228788 | X26: =EOMONTH(M26,1) -> 47026 | Y26: =IF(BBG!$D$5=BBG!$J$5,BBG!L30-BBG!L31,BBG!L29-BBG!L30) -> 0.35 | Z26: =IFERROR(VLOOKUP($C27,Freight!$A$3:$F$22,MATCH(FWD!$N$41,Freight!$A$3:$F$3,0),FALSE)+$B$7,VLOOKUP($B27,Freight!$A$3:$F$22,MATCH(FWD!$N$41,Freight!$A$3:$F$3,0),FALSE)+$B$7) -> 4.4630509 | AA26: =VLOOKUP(EOMONTH(X26,0),BBG!$N$63:$R$123,5,FALSE) -> 0.54 | AB26: =J26+Y26+Z26-AA26 -> 1.8430509 | AC26: =U27 -> 1.6053388 | AD26: =AC26-AB26 -> -0.23771212 | AF26: =EOMONTH(E26,2) -> 47057 | AG26: =IF(BBG!$D$5=BBG!$J$5,BBG!L28-BBG!L30,BBG!L27-BBG!L29)*2/3 -> 0.49333333 | AH26: =IFERROR(VLOOKUP($C26,Freight!$A$3:$F$22,MATCH(FWD!$AH$41,Freight!$A$3:$F$3,0),FALSE)+$B$7,VLOOKUP($B26,Freight!$A$3:$F$22,MATCH(FWD!$AH$41,Freight!$A$3:$F$3,0),FALSE)+$B$7) -> 12.505672 | AI26: =VLOOKUP(X26,BBG!$U$63:$Y$123,4,FALSE) -> 0.44 | AJ26: =AI26+J26+AH26+AG26 -> 11.009005 | AL26: =EOMONTH(E26,1) -> 47026 | AM26: =VLOOKUP(AL26,BBG!$AE$64:$AJ$100,6,FALSE) -> #VALUE! | AN26: =Y27 -> 0.33 | AO26: =VLOOKUP($B26,Freight!$A$3:$G$22,MATCH(FWD!$AO$41,Freight!$A$3:$G$3,0),FALSE) -> 3.6136781 | AP26: =AI26 -> 0.44 | AQ26: =AF26 -> 47057 | AR26: =AM26+AN26+AO26+AP26 -> #VALUE! | AT26: =-(AJ26-AR26) -> #VALUE!
B27: Cal-28 | C27: =E27 -> 47026 | D27: Cal 28 | E27: =EOMONTH(E26,1) -> 47026 | F27: =INDEX(Sheet1!$B$38:$N$49,MATCH("MEH",Sheet1!$B$38:$B$49,0),MATCH(FWD!D27,Sheet1!$B$38:$N$38,0)) -> 1.98 | G27: =BBG!F27-BBG!F29 -> 0.7 | H27: =IF(BBG!$D$5=BBG!$J$5,BBG!F29-BBG!L29,BBG!F29-BBG!L28) -> -5.09 | I27: =I26 -> 0 | J27: =SUM(F27:I27) -> -2.41 | K27: =BBG!G86+FWD!F27 -> -2.8838 | M27: =EOMONTH(E27,0) -> 47026 | N27: =IFERROR(VLOOKUP($C27,Freight!$A$3:$F$22,MATCH(FWD!$N$41,Freight!$A$3:$F$3,0),FALSE)+$B$7,VLOOKUP($B27,Freight!$A$3:$F$22,MATCH(FWD!$N$41,Freight!$A$3:$F$3,0),FALSE)+$B$7) -> 4.4630509 | O27: =VLOOKUP(EOMONTH(M27,0),BBG!$N$63:$R$123,5,FALSE) -> 0.54 | P27: =J27+N27-O27 -> 1.5130509 | Q27: =$B$5 -> 0.03 | R27: =IFERROR(VLOOKUP($C27,Freight!$A$3:$F$22,MATCH(FWD!$U$41,Freight!$A$3:$F$3,0),FALSE),VLOOKUP($B27,Freight!$A$3:$F$22,MATCH(FWD!$U$41,Freight!$A$3:$F$3,0),FALSE)) -> 1.2853388 | S27: =INDEX(BBG!$H$4:$L$53,MATCH(FWD!$M27,BBG!$H$4:$H$53,0),MATCH("Settle",BBG!$H$4:$L$4,0))-INDEX(BBG!$H$4:$L$53,MATCH(FWD!$M29,BBG!$H$4:$H$53,0),MATCH("Settle",BBG!$H$4:$L$4,0)) -> 0.83 | T27: =O27 -> 0.54 | U27: =SUM(Q27:S27)-T27 -> 1.6053388 | V27: =U27-P27 -> 0.092287882 | X27: =EOMONTH(M27,1) -> 47057 | Y27: =IF(BBG!$D$5=BBG!$J$5,BBG!L31-BBG!L32,BBG!L30-BBG!L31) -> 0.33 | Z27: =IFERROR(VLOOKUP($C28,Freight!$A$3:$F$22,MATCH(FWD!$N$41,Freight!$A$3:$F$3,0),FALSE)+$B$7,VLOOKUP($B28,Freight!$A$3:$F$22,MATCH(FWD!$N$41,Freight!$A$3:$F$3,0),FALSE)+$B$7) -> 4.4630509 | AA27: =VLOOKUP(EOMONTH(X27,0),BBG!$N$63:$R$123,5,FALSE) -> 0.53 | AB27: =J27+Y27+Z27-AA27 -> 1.8530509 | AC27: =U28 -> 1.5253388 | AD27: =AC27-AB27 -> -0.32771212 | AF27: =EOMONTH(E27,2) -> 47087 | AG27: =IF(BBG!$D$5=BBG!$J$5,BBG!L29-BBG!L31,BBG!L28-BBG!L30)*2/3 -> 0.46 | AH27: =IFERROR(VLOOKUP($C27,Freight!$A$3:$F$22,MATCH(FWD!$AH$41,Freight!$A$3:$F$3,0),FALSE)+$B$7,VLOOKUP($B27,Freight!$A$3:$F$22,MATCH(FWD!$AH$41,Freight!$A$3:$F$3,0),FALSE)+$B$7) -> 12.505672 | AI27: =VLOOKUP(X27,BBG!$U$63:$Y$123,4,FALSE) -> 0.44 | AJ27: =AI27+J27+AH27+AG27 -> 10.995672 | AL27: =EOMONTH(E27,1) -> 47057 | AM27: =IFERROR(VLOOKUP(AL27,BBG!$AE$64:$AJ$100,6,FALSE),AM26) -> #VALUE! | AN27: =Y28 -> 0.26 | AO27: =VLOOKUP($B27,Freight!$A$3:$G$22,MATCH(FWD!$AO$41,Freight!$A$3:$G$3,0),FALSE) -> 3.6136781 | AP27: =AI27 -> 0.44 | AQ27: =AF27 -> 47087 | AR27: =AM27+AN27+AO27+AP27 -> #VALUE! | AT27: =-(AJ27-AR27) -> #VALUE!
B28: Cal-28 | C28: =E28 -> 47057 | D28: Cal 28 | E28: =EOMONTH(E27,1) -> 47057 | F28: =INDEX(Sheet1!$B$38:$N$49,MATCH("MEH",Sheet1!$B$38:$B$49,0),MATCH(FWD!D28,Sheet1!$B$38:$N$38,0)) -> 1.98 | G28: =BBG!F28-BBG!F30 -> 0.62 | H28: =IF(BBG!$D$5=BBG!$J$5,BBG!F30-BBG!L30,BBG!F30-BBG!L29) -> -5.05 | I28: =I27 -> 0 | J28: =SUM(F28:I28) -> -2.45 | K28: =BBG!G87+FWD!F28 -> -2.8541 | M28: =EOMONTH(E28,0) -> 47057 | N28: =IFERROR(VLOOKUP($C28,Freight!$A$3:$F$22,MATCH(FWD!$N$41,Freight!$A$3:$F$3,0),FALSE)+$B$7,VLOOKUP($B28,Freight!$A$3:$F$22,MATCH(FWD!$N$41,Freight!$A$3:$F$3,0),FALSE)+$B$7) -> 4.4630509 | O28: =VLOOKUP(EOMONTH(M28,0),BBG!$N$63:$R$123,5,FALSE) -> 0.53 | P28: =J28+N28-O28 -> 1.4830509 | Q28: =$B$5 -> 0.03 | R28: =IFERROR(VLOOKUP($C28,Freight!$A$3:$F$22,MATCH(FWD!$U$41,Freight!$A$3:$F$3,0),FALSE),VLOOKUP($B28,Freight!$A$3:$F$22,MATCH(FWD!$U$41,Freight!$A$3:$F$3,0),FALSE)) -> 1.2853388 | S28: =INDEX(BBG!$H$4:$L$53,MATCH(FWD!$M28,BBG!$H$4:$H$53,0),MATCH("Settle",BBG!$H$4:$L$4,0))-INDEX(BBG!$H$4:$L$53,MATCH(FWD!$M30,BBG!$H$4:$H$53,0),MATCH("Settle",BBG!$H$4:$L$4,0)) -> 0.74 | T28: =O28 -> 0.53 | U28: =SUM(Q28:S28)-T28 -> 1.5253388 | V28: =U28-P28 -> 0.042287882 | X28: =EOMONTH(M28,1) -> 47087 | Y28: =IF(BBG!$D$5=BBG!$J$5,BBG!L32-BBG!L33,BBG!L31-BBG!L32) -> 0.26 | Z28: =IFERROR(VLOOKUP($C29,Freight!$A$3:$F$22,MATCH(FWD!$N$41,Freight!$A$3:$F$3,0),FALSE)+$B$7,VLOOKUP($B29,Freight!$A$3:$F$22,MATCH(FWD!$N$41,Freight!$A$3:$F$3,0),FALSE)+$B$7) -> 4.4630509 | AA28: =VLOOKUP(EOMONTH(X28,0),BBG!$N$63:$R$123,5,FALSE) -> 0.53 | AB28: =J28+Y28+Z28-AA28 -> 1.7430509 | AC28: =U29 -> 1.4753388 | AD28: =AC28-AB28 -> -0.26771212 | AF28: =EOMONTH(E28,2) -> 47118 | AG28: =IF(BBG!$D$5=BBG!$J$5,BBG!L30-BBG!L32,BBG!L29-BBG!L31)*2/3 -> 0.45333333 | AH28: =IFERROR(VLOOKUP($C28,Freight!$A$3:$F$22,MATCH(FWD!$AH$41,Freight!$A$3:$F$3,0),FALSE)+$B$7,VLOOKUP($B28,Freight!$A$3:$F$22,MATCH(FWD!$AH$41,Freight!$A$3:$F$3,0),FALSE)+$B$7) -> 12.505672 | AI28: =VLOOKUP(X28,BBG!$U$63:$Y$123,4,FALSE) -> 0.44 | AJ28: =AI28+J28+AH28+AG28 -> 10.949005 | AL28: =EOMONTH(E28,1) -> 47087 | AM28: =IFERROR(VLOOKUP(AL28,BBG!$AE$64:$AJ$100,6,FALSE),AM27) -> #VALUE! | AN28: =Y29 -> 0.26 | AO28: =VLOOKUP($B28,Freight!$A$3:$G$22,MATCH(FWD!$AO$41,Freight!$A$3:$G$3,0),FALSE) -> 3.6136781 | AP28: =AI28 -> 0.44 | AQ28: =AF28 -> 47118 | AR28: =AM28+AN28+AO28+AP28 -> #VALUE! | AT28: =-(AJ28-AR28) -> #VALUE!
B29: Cal-28 | C29: =E29 -> 47087 | D29: Cal 28 | E29: =EOMONTH(E28,1) -> 47087 | F29: =INDEX(Sheet1!$B$38:$N$49,MATCH("MEH",Sheet1!$B$38:$B$49,0),MATCH(FWD!D29,Sheet1!$B$38:$N$38,0)) -> 1.98 | G29: =BBG!F29-BBG!F31 -> 0.63 | H29: =IF(BBG!$D$5=BBG!$J$5,BBG!F31-BBG!L31,BBG!F31-BBG!L30) -> -5.03 | I29: =I28 -> 0 | J29: =SUM(F29:I29) -> -2.42 | K29: =BBG!G88+FWD!F29 -> -2.815 | M29: =EOMONTH(E29,0) -> 47087 | N29: =IFERROR(VLOOKUP($C29,Freight!$A$3:$F$22,MATCH(FWD!$N$41,Freight!$A$3:$F$3,0),FALSE)+$B$7,VLOOKUP($B29,Freight!$A$3:$F$22,MATCH(FWD!$N$41,Freight!$A$3:$F$3,0),FALSE)+$B$7) -> 4.4630509 | O29: =VLOOKUP(EOMONTH(M29,0),BBG!$N$63:$R$123,5,FALSE) -> 0.53 | P29: =J29+N29-O29 -> 1.5130509 | Q29: =$B$5 -> 0.03 | R29: =IFERROR(VLOOKUP($C29,Freight!$A$3:$F$22,MATCH(FWD!$U$41,Freight!$A$3:$F$3,0),FALSE),VLOOKUP($B29,Freight!$A$3:$F$22,MATCH(FWD!$U$41,Freight!$A$3:$F$3,0),FALSE)) -> 1.2853388 | S29: =INDEX(BBG!$H$4:$L$53,MATCH(FWD!$M29,BBG!$H$4:$H$53,0),MATCH("Settle",BBG!$H$4:$L$4,0))-INDEX(BBG!$H$4:$L$53,MATCH(FWD!$M31,BBG!$H$4:$H$53,0),MATCH("Settle",BBG!$H$4:$L$4,0)) -> 0.69 | T29: =O29 -> 0.53 | U29: =SUM(Q29:S29)-T29 -> 1.4753388 | V29: =U29-P29 -> -0.037712118 | X29: =EOMONTH(M29,1) -> 47118 | Y29: =IF(BBG!$D$5=BBG!$J$5,BBG!L33-BBG!L34,BBG!L32-BBG!L33) -> 0.26 | Z29: =IFERROR(VLOOKUP($C30,Freight!$A$3:$F$22,MATCH(FWD!$N$41,Freight!$A$3:$F$3,0),FALSE)+$B$7,VLOOKUP($B30,Freight!$A$3:$F$22,MATCH(FWD!$N$41,Freight!$A$3:$F$3,0),FALSE)+$B$7) -> 4.4630509 | AA29: =VLOOKUP(EOMONTH(X29,0),BBG!$N$63:$R$123,5,FALSE) -> 0.53 | AB29: =J29+Y29+Z29-AA29 -> 1.7730509 | AC29: =U30 -> 1.4653388 | AD29: =AC29-AB29 -> -0.30771212 | AF29: =EOMONTH(E29,2) -> 47149 | AG29: =IF(BBG!$D$5=BBG!$J$5,BBG!L31-BBG!L33,BBG!L30-BBG!L32)*2/3 -> 0.39333333 | AH29: =IFERROR(VLOOKUP($C29,Freight!$A$3:$F$22,MATCH(FWD!$AH$41,Freight!$A$3:$F$3,0),FALSE)+$B$7,VLOOKUP($B29,Freight!$A$3:$F$22,MATCH(FWD!$AH$41,Freight!$A$3:$F$3,0),FALSE)+$B$7) -> 12.505672 | AI29: =VLOOKUP(X29,BBG!$U$63:$Y$123,4,FALSE) -> 0.44 | AJ29: =AI29+J29+AH29+AG29 -> 10.919005 | AL29: =EOMONTH(E29,1) -> 47118 | AM29: =IFERROR(VLOOKUP(AL29,BBG!$AE$64:$AJ$100,6,FALSE),AM28) -> #VALUE! | AN29: =Y30 -> 0.27 | AO29: =VLOOKUP($B29,Freight!$A$3:$G$22,MATCH(FWD!$AO$41,Freight!$A$3:$G$3,0),FALSE) -> 3.6136781 | AP29: =AI29 -> 0.44 | AQ29: =AF29 -> 47149 | AR29: =AM29+AN29+AO29+AP29 -> #VALUE! | AT29: =-(AJ29-AR29) -> #VALUE!
B30: Cal-28 | C30: =E30 -> 47118 | D30: Cal 28 | E30: =EOMONTH(E29,1) -> 47118 | F30: =INDEX(Sheet1!$B$38:$N$49,MATCH("MEH",Sheet1!$B$38:$B$49,0),MATCH(FWD!D30,Sheet1!$B$38:$N$38,0)) -> 1.98 | G30: =BBG!F30-BBG!F32 -> 0.69 | H30: =IF(BBG!$D$5=BBG!$J$5,BBG!F32-BBG!L32,BBG!F32-BBG!L31) -> -5.06 | I30: =I29 -> 0 | J30: =SUM(F30:I30) -> -2.39 | K30: =BBG!G89+FWD!F30 -> -2.824 | M30: =EOMONTH(E30,0) -> 47118 | N30: =IFERROR(VLOOKUP($C30,Freight!$A$3:$F$22,MATCH(FWD!$N$41,Freight!$A$3:$F$3,0),FALSE)+$B$7,VLOOKUP($B30,Freight!$A$3:$F$22,MATCH(FWD!$N$41,Freight!$A$3:$F$3,0),FALSE)+$B$7) -> 4.4630509 | O30: =VLOOKUP(EOMONTH(M30,0),BBG!$N$63:$R$123,5,FALSE) -> 0.53 | P30: =J30+N30-O30 -> 1.5430509 | Q30: =$B$5 -> 0.03 | R30: =IFERROR(VLOOKUP($C30,Freight!$A$3:$F$22,MATCH(FWD!$U$41,Freight!$A$3:$F$3,0),FALSE),VLOOKUP($B30,Freight!$A$3:$F$22,MATCH(FWD!$U$41,Freight!$A$3:$F$3,0),FALSE)) -> 1.2853388 | S30: =INDEX(BBG!$H$4:$L$53,MATCH(FWD!$M30,BBG!$H$4:$H$53,0),MATCH("Settle",BBG!$H$4:$L$4,0))-INDEX(BBG!$H$4:$L$53,MATCH(FWD!$M32,BBG!$H$4:$H$53,0),MATCH("Settle",BBG!$H$4:$L$4,0)) -> 0.68 | T30: =O30 -> 0.53 | U30: =SUM(Q30:S30)-T30 -> 1.4653388 | V30: =U30-P30 -> -0.077712118 | X30: =EOMONTH(M30,1) -> 47149 | Y30: =IF(BBG!$D$5=BBG!$J$5,BBG!L34-BBG!L35,BBG!L33-BBG!L34) -> 0.27 | Z30: =IFERROR(VLOOKUP($C31,Freight!$A$3:$F$22,MATCH(FWD!$N$41,Freight!$A$3:$F$3,0),FALSE)+$B$7,VLOOKUP($B31,Freight!$A$3:$F$22,MATCH(FWD!$N$41,Freight!$A$3:$F$3,0),FALSE)+$B$7) -> 4.4630509 | AA30: =VLOOKUP(EOMONTH(X30,0),BBG!$N$63:$R$123,5,FALSE) -> 0.54 | AB30: =J30+Y30+Z30-AA30 -> 1.8030509 | AC30: =U31 -> 1.3653388 | AD30: =AC30-AB30 -> -0.43771212 | AF30: =EOMONTH(E30,2) -> 47177 | AG30: =IF(BBG!$D$5=BBG!$J$5,BBG!L32-BBG!L34,BBG!L31-BBG!L33)*2/3 -> 0.34666667 | AH30: =IFERROR(VLOOKUP($C30,Freight!$A$3:$F$22,MATCH(FWD!$AH$41,Freight!$A$3:$F$3,0),FALSE)+$B$7,VLOOKUP($B30,Freight!$A$3:$F$22,MATCH(FWD!$AH$41,Freight!$A$3:$F$3,0),FALSE)+$B$7) -> 12.505672 | AI30: =VLOOKUP(X30,BBG!$U$63:$Y$123,4,FALSE) -> 0.44 | AJ30: =AI30+J30+AH30+AG30 -> 10.902338 | AL30: =EOMONTH(E30,1) -> 47149 | AM30: =IFERROR(VLOOKUP(AL30,BBG!$AE$64:$AJ$100,6,FALSE),AM29) -> #VALUE! | AN30: =Y31 -> 0.28 | AO30: =VLOOKUP($B30,Freight!$A$3:$G$22,MATCH(FWD!$AO$41,Freight!$A$3:$G$3,0),FALSE) -> 3.6136781 | AP30: =AI30 -> 0.44 | AQ30: =AF30 -> 47177 | AR30: =AM30+AN30+AO30+AP30 -> #VALUE! | AT30: =-(AJ30-AR30) -> #VALUE!
B31: Cal-28 | C31: =E31 -> 47149 | D31: Cal 28 | E31: =EOMONTH(E30,1) -> 47149 | F31: =INDEX(Sheet1!$B$38:$N$49,MATCH("MEH",Sheet1!$B$38:$B$49,0),MATCH(FWD!D31,Sheet1!$B$38:$N$38,0)) -> 1.98 | G31: =BBG!F31-BBG!F33 -> 0.69 | H31: =IF(BBG!$D$5=BBG!$J$5,BBG!F33-BBG!L33,BBG!F33-BBG!L32) -> -5.13 | I31: =I30 -> 0 | J31: =SUM(F31:I31) -> -2.46 | K31: =BBG!G90+FWD!F31 -> -2.9182 | M31: =EOMONTH(E31,0) -> 47149 | N31: =IFERROR(VLOOKUP($C31,Freight!$A$3:$F$22,MATCH(FWD!$N$41,Freight!$A$3:$F$3,0),FALSE)+$B$7,VLOOKUP($B31,Freight!$A$3:$F$22,MATCH(FWD!$N$41,Freight!$A$3:$F$3,0),FALSE)+$B$7) -> 4.4630509 | O31: =VLOOKUP(EOMONTH(M31,0),BBG!$N$63:$R$123,5,FALSE) -> 0.54 | P31: =J31+N31-O31 -> 1.4630509 | Q31: =$B$5 -> 0.03 | R31: =IFERROR(VLOOKUP($C31,Freight!$A$3:$F$22,MATCH(FWD!$U$41,Freight!$A$3:$F$3,0),FALSE),VLOOKUP($B31,Freight!$A$3:$F$22,MATCH(FWD!$U$41,Freight!$A$3:$F$3,0),FALSE)) -> 1.2853388 | S31: =INDEX(BBG!$H$4:$L$53,MATCH(FWD!$M31,BBG!$H$4:$H$53,0),MATCH("Settle",BBG!$H$4:$L$4,0))-INDEX(BBG!$H$4:$L$53,MATCH(FWD!$M33,BBG!$H$4:$H$53,0),MATCH("Settle",BBG!$H$4:$L$4,0)) -> 0.59 | T31: =O31 -> 0.54 | U31: =SUM(Q31:S31)-T31 -> 1.3653388 | V31: =U31-P31 -> -0.097712118 | X31: =EOMONTH(M31,1) -> 47177 | Y31: =IF(BBG!$D$5=BBG!$J$5,BBG!L35-BBG!L36,BBG!L34-BBG!L35) -> 0.28 | Z31: =IFERROR(VLOOKUP($C32,Freight!$A$3:$F$22,MATCH(FWD!$N$41,Freight!$A$3:$F$3,0),FALSE)+$B$7,VLOOKUP($B32,Freight!$A$3:$F$22,MATCH(FWD!$N$41,Freight!$A$3:$F$3,0),FALSE)+$B$7) -> 4.4630509 | AA31: =VLOOKUP(EOMONTH(X31,0),BBG!$N$63:$R$123,5,FALSE) -> 0.53 | AB31: =J31+Y31+Z31-AA31 -> 1.7530509 | AC31: =U32 -> 1.3053388 | AD31: =AC31-AB31 -> -0.44771212 | AF31: =EOMONTH(E31,2) -> 47208 | AG31: =IF(BBG!$D$5=BBG!$J$5,BBG!L33-BBG!L35,BBG!L32-BBG!L34)*2/3 -> 0.35333333 | AH31: =IFERROR(VLOOKUP($C31,Freight!$A$3:$F$22,MATCH(FWD!$AH$41,Freight!$A$3:$F$3,0),FALSE)+$B$7,VLOOKUP($B31,Freight!$A$3:$F$22,MATCH(FWD!$AH$41,Freight!$A$3:$F$3,0),FALSE)+$B$7) -> 12.505672 | AI31: =VLOOKUP(X31,BBG!$U$63:$Y$123,4,FALSE) -> 0.44 | AJ31: =AI31+J31+AH31+AG31 -> 10.839005 | AL31: =EOMONTH(E31,1) -> 47177 | AM31: =IFERROR(VLOOKUP(AL31,BBG!$AE$64:$AJ$100,6,FALSE),AM30) -> #VALUE! | AN31: =Y32 -> 0.3 | AO31: =VLOOKUP($B31,Freight!$A$3:$G$22,MATCH(FWD!$AO$41,Freight!$A$3:$G$3,0),FALSE) -> 3.6136781 | AP31: =AI31 -> 0.44 | AQ31: =AF31 -> 47208 | AR31: =AM31+AN31+AO31+AP31 -> #VALUE! | AT31: =-(AJ31-AR31) -> #VALUE!
B32: Cal-28 | C32: =E32 -> 47177 | D32: Cal 28 | E32: =EOMONTH(E31,1) -> 47177 | F32: =INDEX(Sheet1!$B$38:$N$49,MATCH("MEH",Sheet1!$B$38:$B$49,0),MATCH(FWD!D32,Sheet1!$B$38:$N$38,0)) -> 1.98 | G32: =BBG!F32-BBG!F34 -> 0.65 | H32: =IF(BBG!$D$5=BBG!$J$5,BBG!F34-BBG!L34,BBG!F34-BBG!L33) -> -5.19 | I32: =I31 -> 0 | J32: =SUM(F32:I32) -> -2.56 | K32: =BBG!G91+FWD!F32 -> -2.9765 | M32: =EOMONTH(E32,0) -> 47177 | N32: =IFERROR(VLOOKUP($C32,Freight!$A$3:$F$22,MATCH(FWD!$N$41,Freight!$A$3:$F$3,0),FALSE)+$B$7,VLOOKUP($B32,Freight!$A$3:$F$22,MATCH(FWD!$N$41,Freight!$A$3:$F$3,0),FALSE)+$B$7) -> 4.4630509 | O32: =VLOOKUP(EOMONTH(M32,0),BBG!$N$63:$R$123,5,FALSE) -> 0.53 | P32: =J32+N32-O32 -> 1.3730509 | Q32: =$B$5 -> 0.03 | R32: =IFERROR(VLOOKUP($C32,Freight!$A$3:$F$22,MATCH(FWD!$U$41,Freight!$A$3:$F$3,0),FALSE),VLOOKUP($B32,Freight!$A$3:$F$22,MATCH(FWD!$U$41,Freight!$A$3:$F$3,0),FALSE)) -> 1.2853388 | S32: =INDEX(BBG!$H$4:$L$53,MATCH(FWD!$M32,BBG!$H$4:$H$53,0),MATCH("Settle",BBG!$H$4:$L$4,0))-INDEX(BBG!$H$4:$L$53,MATCH(FWD!$M34,BBG!$H$4:$H$53,0),MATCH("Settle",BBG!$H$4:$L$4,0)) -> 0.52 | T32: =O32 -> 0.53 | U32: =SUM(Q32:S32)-T32 -> 1.3053388 | V32: =U32-P32 -> -0.067712118 | X32: =EOMONTH(M32,1) -> 47208 | Y32: =IF(BBG!$D$5=BBG!$J$5,BBG!L36-BBG!L37,BBG!L35-BBG!L36) -> 0.3 | Z32: =IFERROR(VLOOKUP($C33,Freight!$A$3:$F$22,MATCH(FWD!$N$41,Freight!$A$3:$F$3,0),FALSE)+$B$7,VLOOKUP($B33,Freight!$A$3:$F$22,MATCH(FWD!$N$41,Freight!$A$3:$F$3,0),FALSE)+$B$7) -> 4.4630509 | AA32: =VLOOKUP(EOMONTH(X32,0),BBG!$N$63:$R$123,5,FALSE) -> 0.53 | AB32: =J32+Y32+Z32-AA32 -> 1.6730509 | AC32: =U33 -> 1.3153388 | AD32: =AC32-AB32 -> -0.35771212 | AF32: =EOMONTH(E32,2) -> 47238 | AG32: =IF(BBG!$D$5=BBG!$J$5,BBG!L34-BBG!L36,BBG!L33-BBG!L35)*2/3 -> 0.36666667 | AH32: =IFERROR(VLOOKUP($C32,Freight!$A$3:$F$22,MATCH(FWD!$AH$41,Freight!$A$3:$F$3,0),FALSE)+$B$7,VLOOKUP($B32,Freight!$A$3:$F$22,MATCH(FWD!$AH$41,Freight!$A$3:$F$3,0),FALSE)+$B$7) -> 12.505672 | AI32: =VLOOKUP(X32,BBG!$U$63:$Y$123,4,FALSE) -> 0.44 | AJ32: =AI32+J32+AH32+AG32 -> 10.752338 | AL32: =EOMONTH(E32,1) -> 47208 | AM32: =IFERROR(VLOOKUP(AL32,BBG!$AE$64:$AJ$100,6,FALSE),AM31) -> #VALUE! | AN32: =Y33 -> 0.27 | AO32: =VLOOKUP($B32,Freight!$A$3:$G$22,MATCH(FWD!$AO$41,Freight!$A$3:$G$3,0),FALSE) -> 3.6136781 | AP32: =AI32 -> 0.44 | AQ32: =AF32 -> 47238 | AR32: =AM32+AN32+AO32+AP32 -> #VALUE! | AT32: =-(AJ32-AR32) -> #VALUE!
B33: Cal-28 | C33: =E33 -> 47208 | D33: Cal 28 | E33: =EOMONTH(E32,1) -> 47208 | F33: =INDEX(Sheet1!$B$38:$N$49,MATCH("MEH",Sheet1!$B$38:$B$49,0),MATCH(FWD!D33,Sheet1!$B$38:$N$38,0)) -> 1.98 | G33: =BBG!F33-BBG!F35 -> 0.62 | H33: =IF(BBG!$D$5=BBG!$J$5,BBG!F35-BBG!L35,BBG!F35-BBG!L34) -> -5.22 | I33: =I32 -> 0 | J33: =SUM(F33:I33) -> -2.62 | K33: =BBG!G92+FWD!F33 -> -3.0267 | M33: =EOMONTH(E33,0) -> 47208 | N33: =IFERROR(VLOOKUP($C33,Freight!$A$3:$F$22,MATCH(FWD!$N$41,Freight!$A$3:$F$3,0),FALSE)+$B$7,VLOOKUP($B33,Freight!$A$3:$F$22,MATCH(FWD!$N$41,Freight!$A$3:$F$3,0),FALSE)+$B$7) -> 4.4630509 | O33: =VLOOKUP(EOMONTH(M33,0),BBG!$N$63:$R$123,5,FALSE) -> 0.53 | P33: =J33+N33-O33 -> 1.3130509 | Q33: =$B$5 -> 0.03 | R33: =IFERROR(VLOOKUP($C33,Freight!$A$3:$F$22,MATCH(FWD!$U$41,Freight!$A$3:$F$3,0),FALSE),VLOOKUP($B33,Freight!$A$3:$F$22,MATCH(FWD!$U$41,Freight!$A$3:$F$3,0),FALSE)) -> 1.2853388 | S33: =INDEX(BBG!$H$4:$L$53,MATCH(FWD!$M33,BBG!$H$4:$H$53,0),MATCH("Settle",BBG!$H$4:$L$4,0))-INDEX(BBG!$H$4:$L$53,MATCH(FWD!$M35,BBG!$H$4:$H$53,0),MATCH("Settle",BBG!$H$4:$L$4,0)) -> 0.53 | T33: =O33 -> 0.53 | U33: =SUM(Q33:S33)-T33 -> 1.3153388 | V33: =U33-P33 -> 0.0022878816 | X33: =EOMONTH(M33,1) -> 47238 | Y33: =IF(BBG!$D$5=BBG!$J$5,BBG!L37-BBG!L38,BBG!L36-BBG!L37) -> 0.27 | Z33: =IFERROR(VLOOKUP($C34,Freight!$A$3:$F$22,MATCH(FWD!$N$41,Freight!$A$3:$F$3,0),FALSE)+$B$7,VLOOKUP($B34,Freight!$A$3:$F$22,MATCH(FWD!$N$41,Freight!$A$3:$F$3,0),FALSE)+$B$7) -> 4.4630509 | AA33: =VLOOKUP(EOMONTH(X33,0),BBG!$N$63:$R$123,5,FALSE) -> 0.53 | AB33: =J33+Y33+Z33-AA33 -> 1.5830509 | AC33: =U34 -> 1.3353388 | AD33: =AC33-AB33 -> -0.24771212 | AF33: =EOMONTH(E33,2) -> 47269 | AG33: =IF(BBG!$D$5=BBG!$J$5,BBG!L35-BBG!L37,BBG!L34-BBG!L36)*2/3 -> 0.38666667 | AH33: =IFERROR(VLOOKUP($C33,Freight!$A$3:$F$22,MATCH(FWD!$AH$41,Freight!$A$3:$F$3,0),FALSE)+$B$7,VLOOKUP($B33,Freight!$A$3:$F$22,MATCH(FWD!$AH$41,Freight!$A$3:$F$3,0),FALSE)+$B$7) -> 12.505672 | AI33: =VLOOKUP(X33,BBG!$U$63:$Y$123,4,FALSE) -> 0.44 | AJ33: =AI33+J33+AH33+AG33 -> 10.712338 | AL33: =EOMONTH(E33,1) -> 47238 | AM33: =IFERROR(VLOOKUP(AL33,BBG!$AE$64:$AJ$100,6,FALSE),AM32) -> #VALUE! | AN33: =Y34 -> 0.27 | AO33: =VLOOKUP($B33,Freight!$A$3:$G$22,MATCH(FWD!$AO$41,Freight!$A$3:$G$3,0),FALSE) -> 3.6136781 | AP33: =AI33 -> 0.44 | AQ33: =AF33 -> 47269 | AR33: =AM33+AN33+AO33+AP33 -> #VALUE! | AT33: =-(AJ33-AR33) -> #VALUE!
B34: Cal-28 | C34: =E34 -> 47238 | D34: Cal 28 | E34: =EOMONTH(E33,1) -> 47238 | F34: =INDEX(Sheet1!$B$38:$N$49,MATCH("MEH",Sheet1!$B$38:$B$49,0),MATCH(FWD!D34,Sheet1!$B$38:$N$38,0)) -> 1.98 | G34: =BBG!F34-BBG!F36 -> 0.63 | H34: =IF(BBG!$D$5=BBG!$J$5,BBG!F36-BBG!L36,BBG!F36-BBG!L35) -> -5.27 | I34: =I33 -> 0 | J34: =SUM(F34:I34) -> -2.66 | K34: =BBG!G93+FWD!F34 -> -3.0357 | M34: =EOMONTH(E34,0) -> 47238 | N34: =IFERROR(VLOOKUP($C34,Freight!$A$3:$F$22,MATCH(FWD!$N$41,Freight!$A$3:$F$3,0),FALSE)+$B$7,VLOOKUP($B34,Freight!$A$3:$F$22,MATCH(FWD!$N$41,Freight!$A$3:$F$3,0),FALSE)+$B$7) -> 4.4630509 | O34: =VLOOKUP(EOMONTH(M34,0),BBG!$N$63:$R$123,5,FALSE) -> 0.53 | P34: =J34+N34-O34 -> 1.2730509 | Q34: =$B$5 -> 0.03 | R34: =IFERROR(VLOOKUP($C34,Freight!$A$3:$F$22,MATCH(FWD!$U$41,Freight!$A$3:$F$3,0),FALSE),VLOOKUP($B34,Freight!$A$3:$F$22,MATCH(FWD!$U$41,Freight!$A$3:$F$3,0),FALSE)) -> 1.2853388 | S34: =INDEX(BBG!$H$4:$L$53,MATCH(FWD!$M34,BBG!$H$4:$H$53,0),MATCH("Settle",BBG!$H$4:$L$4,0))-INDEX(BBG!$H$4:$L$53,MATCH(FWD!$M36,BBG!$H$4:$H$53,0),MATCH("Settle",BBG!$H$4:$L$4,0)) -> 0.55 | T34: =O34 -> 0.53 | U34: =SUM(Q34:S34)-T34 -> 1.3353388 | V34: =U34-P34 -> 0.062287882 | X34: =EOMONTH(M34,1) -> 47269 | Y34: =IF(BBG!$D$5=BBG!$J$5,BBG!L39-BBG!L40,BBG!L38-BBG!L39) -> 0.27 | Z34: =IFERROR(VLOOKUP($C35,Freight!$A$3:$F$22,MATCH(FWD!$N$41,Freight!$A$3:$F$3,0),FALSE)+$B$7,VLOOKUP($B35,Freight!$A$3:$F$22,MATCH(FWD!$N$41,Freight!$A$3:$F$3,0),FALSE)+$B$7) -> 4.4630509 | AA34: =VLOOKUP(EOMONTH(X34,0),BBG!$N$63:$R$123,5,FALSE) -> 0.53 | AB34: =J34+Y34+Z34-AA34 -> 1.5430509 | AC34: =U35 -> 1.3653388 | AD34: =AC34-AB34 -> -0.17771212 | AF34: =EOMONTH(E34,2) -> 47299 | AG34: =IF(BBG!$D$5=BBG!$J$5,BBG!L36-BBG!L38,BBG!L35-BBG!L37)*2/3 -> 0.38 | AH34: =IFERROR(VLOOKUP($C34,Freight!$A$3:$F$22,MATCH(FWD!$AH$41,Freight!$A$3:$F$3,0),FALSE)+$B$7,VLOOKUP($B34,Freight!$A$3:$F$22,MATCH(FWD!$AH$41,Freight!$A$3:$F$3,0),FALSE)+$B$7) -> 12.505672 | AI34: =VLOOKUP(X34,BBG!$U$63:$Y$123,4,FALSE) -> 0.44 | AJ34: =AI34+J34+AH34+AG34 -> 10.665672 | AL34: =EOMONTH(E34,1) -> 47269 | AM34: =IFERROR(VLOOKUP(AL34,BBG!$AE$64:$AJ$100,6,FALSE),AM33) -> #VALUE! | AN34: =Y35 -> 0.3 | AO34: =VLOOKUP($B34,Freight!$A$3:$G$22,MATCH(FWD!$AO$41,Freight!$A$3:$G$3,0),FALSE) -> 3.6136781 | AP34: =AI34 -> 0.44 | AQ34: =AF34 -> 47299 | AR34: =AM34+AN34+AO34+AP34 -> #VALUE! | AT34: =-(AJ34-AR34) -> #VALUE!
B35: Cal-28 | C35: =E35 -> 47269 | D35: Cal 28 | E35: =EOMONTH(E34,1) -> 47269 | F35: =INDEX(Sheet1!$B$38:$N$49,MATCH("MEH",Sheet1!$B$38:$B$49,0),MATCH(FWD!D35,Sheet1!$B$38:$N$38,0)) -> 1.98 | G35: =BBG!F35-BBG!F37 -> 0.69 | H35: =IF(BBG!$D$5=BBG!$J$5,BBG!F37-BBG!L37,BBG!F37-BBG!L36) -> -5.33 | I35: =I34 -> 0 | J35: =SUM(F35:I35) -> -2.66 | K35: =BBG!G94+FWD!F35 -> -3.0783 | M35: =EOMONTH(E35,0) -> 47269 | N35: =IFERROR(VLOOKUP($C35,Freight!$A$3:$F$22,MATCH(FWD!$N$41,Freight!$A$3:$F$3,0),FALSE)+$B$7,VLOOKUP($B35,Freight!$A$3:$F$22,MATCH(FWD!$N$41,Freight!$A$3:$F$3,0),FALSE)+$B$7) -> 4.4630509 | O35: =VLOOKUP(EOMONTH(M35,0),BBG!$N$63:$R$123,5,FALSE) -> 0.53 | P35: =J35+N35-O35 -> 1.2730509 | Q35: =$B$5 -> 0.03 | R35: =IFERROR(VLOOKUP($C35,Freight!$A$3:$F$22,MATCH(FWD!$U$41,Freight!$A$3:$F$3,0),FALSE),VLOOKUP($B35,Freight!$A$3:$F$22,MATCH(FWD!$U$41,Freight!$A$3:$F$3,0),FALSE)) -> 1.2853388 | S35: =INDEX(BBG!$H$4:$L$53,MATCH(FWD!$M35,BBG!$H$4:$H$53,0),MATCH("Settle",BBG!$H$4:$L$4,0))-INDEX(BBG!$H$4:$L$53,MATCH(FWD!$M37,BBG!$H$4:$H$53,0),MATCH("Settle",BBG!$H$4:$L$4,0)) -> 0.58 | T35: =O35 -> 0.53 | U35: =SUM(Q35:S35)-T35 -> 1.3653388 | V35: =U35-P35 -> 0.092287882 | X35: =EOMONTH(M35,1) -> 47299 | Y35: =IF(BBG!$D$5=BBG!$J$5,BBG!L40-BBG!L41,BBG!L39-BBG!L40) -> 0.3 | Z35: =IFERROR(VLOOKUP($C36,Freight!$A$3:$F$22,MATCH(FWD!$N$41,Freight!$A$3:$F$3,0),FALSE)+$B$7,VLOOKUP($B36,Freight!$A$3:$F$22,MATCH(FWD!$N$41,Freight!$A$3:$F$3,0),FALSE)+$B$7) -> 3.5944407 | AA35: =VLOOKUP(EOMONTH(X35,0),BBG!$N$63:$R$123,5,FALSE) -> 0.53 | AB35: =J35+Y35+Z35-AA35 -> 0.70444074 | AC35: =U36 -> 1.3342202 | AD35: =AC35-AB35 -> 0.62977943 | AF35: =EOMONTH(E35,2) -> 47330 | AG35: =IF(BBG!$D$5=BBG!$J$5,BBG!L37-BBG!L39,BBG!L36-BBG!L38)*2/3 -> 0.36666667 | AH35: =IFERROR(VLOOKUP($C35,Freight!$A$3:$F$22,MATCH(FWD!$AH$41,Freight!$A$3:$F$3,0),FALSE)+$B$7,VLOOKUP($B35,Freight!$A$3:$F$22,MATCH(FWD!$AH$41,Freight!$A$3:$F$3,0),FALSE)+$B$7) -> 12.505672 | AI35: =VLOOKUP(X35,BBG!$U$63:$Y$123,4,FALSE) -> 0.44 | AJ35: =AI35+J35+AH35+AG35 -> 10.652338 | AL35: =EOMONTH(E35,1) -> 47299 | AM35: =IFERROR(VLOOKUP(AL35,BBG!$AE$64:$AJ$100,6,FALSE),AM34) -> #VALUE! | AN35: =Y36 -> 0.28 | AO35: =VLOOKUP($B35,Freight!$A$3:$G$22,MATCH(FWD!$AO$41,Freight!$A$3:$G$3,0),FALSE) -> 3.6136781 | AP35: =AI35 -> 0.44 | AQ35: =AF35 -> 47330 | AR35: =AM35+AN35+AO35+AP35 -> #VALUE! | AT35: =-(AJ35-AR35) -> #VALUE!
B36: Cal-29 | C36: =E36 -> 47299 | D36: Cal 29 | E36: =EOMONTH(E35,1) -> 47299 | F36: =INDEX(Sheet1!$B$38:$N$49,MATCH("MEH",Sheet1!$B$38:$B$49,0),MATCH(FWD!D36,Sheet1!$B$38:$N$38,0)) -> 2.03 | G36: =BBG!F36-BBG!F38 -> 0.66 | H36: =IF(BBG!$D$5=BBG!$J$5,BBG!F38-BBG!L38,BBG!F38-BBG!L37) -> -5.36 | I36: =I35 -> 0 | J36: =SUM(F36:I36) -> -2.67 | K36: =BBG!G95+FWD!F36 -> -3.1167 | M36: =EOMONTH(E36,0) -> 47299 | N36: =IFERROR(VLOOKUP($C36,Freight!$A$3:$F$22,MATCH(FWD!$N$41,Freight!$A$3:$F$3,0),FALSE)+$B$7,VLOOKUP($B36,Freight!$A$3:$F$22,MATCH(FWD!$N$41,Freight!$A$3:$F$3,0),FALSE)+$B$7) -> 3.5944407 | O36: =VLOOKUP(EOMONTH(M36,0),BBG!$N$63:$R$123,5,FALSE) -> 0.53 | P36: =J36+N36-O36 -> 0.39444074 | Q36: =$B$5 -> 0.03 | R36: =IFERROR(VLOOKUP($C36,Freight!$A$3:$F$22,MATCH(FWD!$U$41,Freight!$A$3:$F$3,0),FALSE),VLOOKUP($B36,Freight!$A$3:$F$22,MATCH(FWD!$U$41,Freight!$A$3:$F$3,0),FALSE)) -> 1.2642202 | S36: =INDEX(BBG!$H$4:$L$53,MATCH(FWD!$M36,BBG!$H$4:$H$53,0),MATCH("Settle",BBG!$H$4:$L$4,0))-INDEX(BBG!$H$4:$L$53,MATCH(FWD!$M38,BBG!$H$4:$H$53,0),MATCH("Settle",BBG!$H$4:$L$4,0)) -> 0.57 | T36: =O36 -> 0.53 | U36: =SUM(Q36:S36)-T36 -> 1.3342202 | V36: =U36-P36 -> 0.93977943 | X36: =EOMONTH(M36,1) -> 47330 | Y36: =IF(BBG!$D$5=BBG!$J$5,BBG!L41-BBG!L42,BBG!L40-BBG!L41) -> 0.28 | Z36: =IFERROR(VLOOKUP($C37,Freight!$A$3:$F$22,MATCH(FWD!$N$41,Freight!$A$3:$F$3,0),FALSE)+$B$7,VLOOKUP($B37,Freight!$A$3:$F$22,MATCH(FWD!$N$41,Freight!$A$3:$F$3,0),FALSE)+$B$7) -> 3.5944407 | AA36: =VLOOKUP(EOMONTH(X36,0),BBG!$N$63:$R$123,5,FALSE) -> 0.53 | AB36: =J36+Y36+Z36-AA36 -> 0.67444074 | AC36: =U37 -> 1.3142202 | AD36: =AC36-AB36 -> 0.63977943 | AF36: =EOMONTH(E36,2) -> 47361 | AG36: =IF(BBG!$D$5=BBG!$J$5,BBG!L38-BBG!L40,BBG!L37-BBG!L39)*2/3 -> 0.36666667 | AH36: =IFERROR(VLOOKUP($C36,Freight!$A$3:$F$22,MATCH(FWD!$AH$41,Freight!$A$3:$F$3,0),FALSE)+$B$7,VLOOKUP($B36,Freight!$A$3:$F$22,MATCH(FWD!$AH$41,Freight!$A$3:$F$3,0),FALSE)+$B$7) -> 10.737379 | AI36: =VLOOKUP(X36,BBG!$U$63:$Y$123,4,FALSE) -> 0.44 | AJ36: =AI36+J36+AH36+AG36 -> 8.8740457 | AL36: =EOMONTH(E36,1) -> 47330 | AM36: =IFERROR(VLOOKUP(AL36,BBG!$AE$64:$AJ$100,6,FALSE),AM35) -> #VALUE! | AN36: =Y37 -> 0.3 | AO36: =VLOOKUP($B36,Freight!$A$3:$G$22,MATCH(FWD!$AO$41,Freight!$A$3:$G$3,0),FALSE) -> 2.5904503 | AP36: =AI36 -> 0.44 | AQ36: =AF36 -> 47361 | AR36: =AM36+AN36+AO36+AP36 -> #VALUE! | AT36: =-(AJ36-AR36) -> #VALUE!
B37: Cal-29 | C37: =E37 -> 47330 | D37: Cal 29 | E37: =EOMONTH(E36,1) -> 47330 | F37: =INDEX(Sheet1!$B$38:$N$49,MATCH("MEH",Sheet1!$B$38:$B$49,0),MATCH(FWD!D37,Sheet1!$B$38:$N$38,0)) -> 2.03 | G37: =BBG!F37-BBG!F39 -> 0.61 | H37: =IF(BBG!$D$5=BBG!$J$5,BBG!F39-BBG!L39,BBG!F39-BBG!L38) -> -5.39 | I37: =I36 -> 0 | J37: =SUM(F37:I37) -> -2.75 | K37: =BBG!G96+FWD!F37 -> -3.1377 | M37: =EOMONTH(E37,0) -> 47330 | N37: =IFERROR(VLOOKUP($C37,Freight!$A$3:$F$22,MATCH(FWD!$N$41,Freight!$A$3:$F$3,0),FALSE)+$B$7,VLOOKUP($B37,Freight!$A$3:$F$22,MATCH(FWD!$N$41,Freight!$A$3:$F$3,0),FALSE)+$B$7) -> 3.5944407 | O37: =VLOOKUP(EOMONTH(M37,0),BBG!$N$63:$R$123,5,FALSE) -> 0.53 | P37: =J37+N37-O37 -> 0.31444074 | Q37: =$B$5 -> 0.03 | R37: =IFERROR(VLOOKUP($C37,Freight!$A$3:$F$22,MATCH(FWD!$U$41,Freight!$A$3:$F$3,0),FALSE),VLOOKUP($B37,Freight!$A$3:$F$22,MATCH(FWD!$U$41,Freight!$A$3:$F$3,0),FALSE)) -> 1.2642202 | S37: =INDEX(BBG!$H$4:$L$53,MATCH(FWD!$M37,BBG!$H$4:$H$53,0),MATCH("Settle",BBG!$H$4:$L$4,0))-INDEX(BBG!$H$4:$L$53,MATCH(FWD!$M39,BBG!$H$4:$H$53,0),MATCH("Settle",BBG!$H$4:$L$4,0)) -> 0.55 | T37: =O37 -> 0.53 | U37: =SUM(Q37:S37)-T37 -> 1.3142202 | V37: =U37-P37 -> 0.99977943 | X37: =EOMONTH(M37,1) -> 47361 | Y37: =IF(BBG!$D$5=BBG!$J$5,BBG!L42-BBG!L43,BBG!L41-BBG!L42) -> 0.3 | Z37: =IFERROR(VLOOKUP($C38,Freight!$A$3:$F$22,MATCH(FWD!$N$41,Freight!$A$3:$F$3,0),FALSE)+$B$7,VLOOKUP($B38,Freight!$A$3:$F$22,MATCH(FWD!$N$41,Freight!$A$3:$F$3,0),FALSE)+$B$7) -> 3.5944407 | AA37: =VLOOKUP(EOMONTH(X37,0),BBG!$N$63:$R$123,5,FALSE) -> 0.53 | AB37: =J37+Y37+Z37-AA37 -> 0.61444074 | AC37: =U38 -> 1.3142202 | AD37: =AC37-AB37 -> 0.69977943 | AF37: =EOMONTH(E37,2) -> 47391 | AG37: =IF(BBG!$D$5=BBG!$J$5,BBG!L39-BBG!L41,BBG!L38-BBG!L40)*2/3 -> 0.38 | AH37: =IFERROR(VLOOKUP($C37,Freight!$A$3:$F$22,MATCH(FWD!$AH$41,Freight!$A$3:$F$3,0),FALSE)+$B$7,VLOOKUP($B37,Freight!$A$3:$F$22,MATCH(FWD!$AH$41,Freight!$A$3:$F$3,0),FALSE)+$B$7) -> 10.737379 | AI37: =VLOOKUP(X37,BBG!$U$63:$Y$123,4,FALSE) -> 0.44 | AJ37: =AI37+J37+AH37+AG37 -> 8.807379 | AL37: =EOMONTH(E37,1) -> 47361 | AM37: =IFERROR(VLOOKUP(AL37,BBG!$AE$64:$AJ$100,6,FALSE),AM36) -> #VALUE! | AN37: =Y38 -> 0.15 | AO37: =VLOOKUP($B37,Freight!$A$3:$G$22,MATCH(FWD!$AO$41,Freight!$A$3:$G$3,0),FALSE) -> 2.5904503 | AP37: =AI37 -> 0.44 | AQ37: =AF37 -> 47391 | AR37: =AM37+AN37+AO37+AP37 -> #VALUE! | AT37: =-(AJ37-AR37) -> #VALUE!
B38: Cal-29 | C38: =E38 -> 47361 | D38: Cal 29 | E38: =EOMONTH(E37,1) -> 47361 | F38: =INDEX(Sheet1!$B$38:$N$49,MATCH("MEH",Sheet1!$B$38:$B$49,0),MATCH(FWD!D38,Sheet1!$B$38:$N$38,0)) -> 2.03 | G38: =BBG!F38-BBG!F40 -> 0.61 | H38: =IF(BBG!$D$5=BBG!$J$5,BBG!F40-BBG!L40,BBG!F40-BBG!L39) -> -5.42 | I38: =I37 -> 0 | J38: =SUM(F38:I38) -> -2.78 | K38: =BBG!G97+FWD!F38 -> -3.177 | M38: =EOMONTH(E38,0) -> 47361 | N38: =IFERROR(VLOOKUP($C38,Freight!$A$3:$F$22,MATCH(FWD!$N$41,Freight!$A$3:$F$3,0),FALSE)+$B$7,VLOOKUP($B38,Freight!$A$3:$F$22,MATCH(FWD!$N$41,Freight!$A$3:$F$3,0),FALSE)+$B$7) -> 3.5944407 | O38: =VLOOKUP(EOMONTH(M38,0),BBG!$N$63:$R$123,5,FALSE) -> 0.53 | P38: =J38+N38-O38 -> 0.28444074 | Q38: =$B$5 -> 0.03 | R38: =IFERROR(VLOOKUP($C38,Freight!$A$3:$F$22,MATCH(FWD!$U$41,Freight!$A$3:$F$3,0),FALSE),VLOOKUP($B38,Freight!$A$3:$F$22,MATCH(FWD!$U$41,Freight!$A$3:$F$3,0),FALSE)) -> 1.2642202 | S38: =INDEX(BBG!$H$4:$L$53,MATCH(FWD!$M38,BBG!$H$4:$H$53,0),MATCH("Settle",BBG!$H$4:$L$4,0))-INDEX(BBG!$H$4:$L$53,MATCH(FWD!$M40,BBG!$H$4:$H$53,0),MATCH("Settle",BBG!$H$4:$L$4,0)) -> 0.55 | T38: =O38 -> 0.53 | U38: =SUM(Q38:S38)-T38 -> 1.3142202 | V38: =U38-P38 -> 1.0297794 | X38: =EOMONTH(M38,1) -> 47391 | Y38: =IF(BBG!$D$5=BBG!$J$5,BBG!L43-BBG!L44,BBG!L42-BBG!L43) -> 0.15 | Z38: =IFERROR(VLOOKUP($C39,Freight!$A$3:$F$22,MATCH(FWD!$N$41,Freight!$A$3:$F$3,0),FALSE)+$B$7,VLOOKUP($B39,Freight!$A$3:$F$22,MATCH(FWD!$N$41,Freight!$A$3:$F$3,0),FALSE)+$B$7) -> 3.5944407 | AA38: =VLOOKUP(EOMONTH(X38,0),BBG!$N$63:$R$123,5,FALSE) -> 0.53 | AB38: =J38+Y38+Z38-AA38 -> 0.43444074 | AC38: =U39 -> #N/A | AD38: =AC38-AB38 -> #N/A | AF38: =EOMONTH(E38,2) -> 47422 | AG38: =IF(BBG!$D$5=BBG!$J$5,BBG!L40-BBG!L42,BBG!L39-BBG!L41)*2/3 -> 0.38666667 | AH38: =IFERROR(VLOOKUP($C38,Freight!$A$3:$F$22,MATCH(FWD!$AH$41,Freight!$A$3:$F$3,0),FALSE)+$B$7,VLOOKUP($B38,Freight!$A$3:$F$22,MATCH(FWD!$AH$41,Freight!$A$3:$F$3,0),FALSE)+$B$7) -> 10.737379 | AI38: =VLOOKUP(X38,BBG!$U$63:$Y$123,4,FALSE) -> 0.44 | AJ38: =AI38+J38+AH38+AG38 -> 8.7840457 | AL38: =EOMONTH(E38,1) -> 47391 | AM38: =IFERROR(VLOOKUP(AL38,BBG!$AE$64:$AJ$100,6,FALSE),AM37) -> #VALUE! | AN38: =Y39 -> 0.15 | AO38: =VLOOKUP($B38,Freight!$A$3:$G$22,MATCH(FWD!$AO$41,Freight!$A$3:$G$3,0),FALSE) -> 2.5904503 | AP38: =AI38 -> 0.44 | AQ38: =AF38 -> 47422 | AR38: =AM38+AN38+AO38+AP38 -> #VALUE! | AT38: =-(AJ38-AR38) -> #VALUE!
B39: Cal-29 | C39: =E39 -> 47391 | D39: Cal 29 | E39: =EOMONTH(E38,1) -> 47391 | F39: =INDEX(Sheet1!$B$38:$N$49,MATCH("MEH",Sheet1!$B$38:$B$49,0),MATCH(FWD!D39,Sheet1!$B$38:$N$38,0)) -> 2.03 | G39: =BBG!F39-BBG!F41 -> 0.58 | H39: =IF(BBG!$D$5=BBG!$J$5,BBG!F41-BBG!L41,BBG!F41-BBG!L40) -> -5.4 | I39: =I38 -> 0 | J39: =SUM(F39:I39) -> -2.79 | K39: =BBG!G98+FWD!F39 -> -3.166 | M39: =EOMONTH(E39,0) -> 47391 | N39: =IFERROR(VLOOKUP($C39,Freight!$A$3:$F$22,MATCH(FWD!$N$41,Freight!$A$3:$F$3,0),FALSE)+$B$7,VLOOKUP($B39,Freight!$A$3:$F$22,MATCH(FWD!$N$41,Freight!$A$3:$F$3,0),FALSE)+$B$7) -> 3.5944407 | O39: =VLOOKUP(EOMONTH(M39,0),BBG!$N$63:$R$123,5,FALSE) -> 0.53 | P39: =J39+N39-O39 -> 0.27444074 | Q39: =$B$5 -> 0.03 | R39: =IFERROR(VLOOKUP($C39,Freight!$A$3:$F$22,MATCH(FWD!$U$41,Freight!$A$3:$F$3,0),FALSE),VLOOKUP($B39,Freight!$A$3:$F$22,MATCH(FWD!$U$41,Freight!$A$3:$F$3,0),FALSE)) -> 1.2642202 | S39: =INDEX(BBG!$H$4:$L$53,MATCH(FWD!$M39,BBG!$H$4:$H$53,0),MATCH("Settle",BBG!$H$4:$L$4,0))-INDEX(BBG!$H$4:$L$53,MATCH(FWD!$M41,BBG!$H$4:$H$53,0),MATCH("Settle",BBG!$H$4:$L$4,0)) -> #N/A | T39: =O39 -> 0.53 | U39: =SUM(Q39:S39)-T39 -> #N/A | V39: =U39-P39 -> #N/A | X39: =EOMONTH(M39,1) -> 47422 | Y39: =IF(BBG!$D$5=BBG!$J$5,BBG!L44-BBG!L45,BBG!L43-BBG!L44) -> 0.15 | Z39: =IFERROR(VLOOKUP($C40,Freight!$A$3:$F$22,MATCH(FWD!$N$41,Freight!$A$3:$F$3,0),FALSE)+$B$7,VLOOKUP($B40,Freight!$A$3:$F$22,MATCH(FWD!$N$41,Freight!$A$3:$F$3,0),FALSE)+$B$7) -> 3.5944407 | AA39: =VLOOKUP(EOMONTH(X39,0),BBG!$N$63:$R$123,5,FALSE) -> 0.53 | AB39: =J39+Y39+Z39-AA39 -> 0.42444074 | AC39: =U40 -> #N/A | AD39: =AC39-AB39 -> #N/A | AF39: =EOMONTH(E39,2) -> 47452 | AG39: =IF(BBG!$D$5=BBG!$J$5,BBG!L41-BBG!L43,BBG!L40-BBG!L42)*2/3 -> 0.38666667 | AH39: =IFERROR(VLOOKUP($C39,Freight!$A$3:$F$22,MATCH(FWD!$AH$41,Freight!$A$3:$F$3,0),FALSE)+$B$7,VLOOKUP($B39,Freight!$A$3:$F$22,MATCH(FWD!$AH$41,Freight!$A$3:$F$3,0),FALSE)+$B$7) -> 10.737379 | AI39: =VLOOKUP(X39,BBG!$U$63:$Y$123,4,FALSE) -> 0.44 | AJ39: =AI39+J39+AH39+AG39 -> 8.7740457 | AL39: =EOMONTH(E39,1) -> 47422 | AM39: =IFERROR(VLOOKUP(AL39,BBG!$AE$64:$AJ$100,6,FALSE),AM38) -> #VALUE! | AN39: =Y40 -> 0.16 | AO39: =VLOOKUP($B39,Freight!$A$3:$G$22,MATCH(FWD!$AO$41,Freight!$A$3:$G$3,0),FALSE) -> 2.5904503 | AP39: =AI39 -> 0.44 | AQ39: =AF39 -> 47452 | AR39: =AM39+AN39+AO39+AP39 -> #VALUE! | AT39: =-(AJ39-AR39) -> #VALUE!
B40: Cal-29 | C40: =E40 -> 47422 | D40: Cal 29 | E40: =EOMONTH(E39,1) -> 47422 | F40: =INDEX(Sheet1!$B$38:$N$49,MATCH("MEH",Sheet1!$B$38:$B$49,0),MATCH(FWD!D40,Sheet1!$B$38:$N$38,0)) -> 2.03 | G40: =BBG!F40-BBG!F42 -> 0.58 | H40: =IF(BBG!$D$5=BBG!$J$5,BBG!F42-BBG!L42,BBG!F42-BBG!L41) -> -5.42 | I40: =I39 -> 0 | J40: =SUM(F40:I40) -> -2.81 | K40: =BBG!G99+FWD!F40 -> -3.167 | M40: =EOMONTH(E40,0) -> 47422 | N40: =IFERROR(VLOOKUP($C40,Freight!$A$3:$F$22,MATCH(FWD!$N$41,Freight!$A$3:$F$3,0),FALSE)+$B$7,VLOOKUP($B40,Freight!$A$3:$F$22,MATCH(FWD!$N$41,Freight!$A$3:$F$3,0),FALSE)+$B$7) -> 3.5944407 | O40: =VLOOKUP(EOMONTH(M40,0),BBG!$N$63:$R$123,5,FALSE) -> 0.53 | P40: =J40+N40-O40 -> 0.25444074 | Q40: =$B$5 -> 0.03 | R40: =IFERROR(VLOOKUP($C40,Freight!$A$3:$F$22,MATCH(FWD!$U$41,Freight!$A$3:$F$3,0),FALSE),VLOOKUP($B40,Freight!$A$3:$F$22,MATCH(FWD!$U$41,Freight!$A$3:$F$3,0),FALSE)) -> 1.2642202 | S40: =INDEX(BBG!$H$4:$L$53,MATCH(FWD!$M40,BBG!$H$4:$H$53,0),MATCH("Settle",BBG!$H$4:$L$4,0))-INDEX(BBG!$H$4:$L$53,MATCH(FWD!$M74,BBG!$H$4:$H$53,0),MATCH("Settle",BBG!$H$4:$L$4,0)) -> #N/A | T40: =O40 -> 0.53 | U40: =SUM(Q40:S40)-T40 -> #N/A | V40: =U40-P40 -> #N/A | X40: =EOMONTH(M40,1) -> 47452 | Y40: =IF(BBG!$D$5=BBG!$J$5,BBG!L45-BBG!L46,BBG!L44-BBG!L45) -> 0.16 | Z40: =IFERROR(VLOOKUP($C41,Freight!$A$3:$F$22,MATCH(FWD!$N$41,Freight!$A$3:$F$3,0),FALSE)+$B$7,VLOOKUP($B41,Freight!$A$3:$F$22,MATCH(FWD!$N$41,Freight!$A$3:$F$3,0),FALSE)+$B$7) -> #N/A | AA40: =VLOOKUP(EOMONTH(X40,0),BBG!$N$63:$R$123,5,FALSE) -> 0.54 | AB40: =J40+Y40+Z40-AA40 -> #N/A | AC40: =U41 -> TD9 | AD40: =AC40-AB40 -> #VALUE! | AF40: =EOMONTH(E40,2) -> 47483 | AG40: =IF(BBG!$D$5=BBG!$J$5,BBG!L42-BBG!L44,BBG!L41-BBG!L43)*2/3 -> 0.3 | AH40: =IFERROR(VLOOKUP($C40,Freight!$A$3:$F$22,MATCH(FWD!$AH$41,Freight!$A$3:$F$3,0),FALSE)+$B$7,VLOOKUP($B40,Freight!$A$3:$F$22,MATCH(FWD!$AH$41,Freight!$A$3:$F$3,0),FALSE)+$B$7) -> 10.737379 | AI40: =VLOOKUP(X40,BBG!$U$63:$Y$123,4,FALSE) -> 0.44 | AJ40: =AI40+J40+AH40+AG40 -> 8.667379 | AL40: =EOMONTH(E40,1) -> 47452 | AM40: =IFERROR(VLOOKUP(AL40,BBG!$AE$64:$AJ$100,6,FALSE),AM39) -> #VALUE! | AN40: =Y41 -> 0 | AO40: =VLOOKUP($B40,Freight!$A$3:$G$22,MATCH(FWD!$AO$41,Freight!$A$3:$G$3,0),FALSE) -> 2.5904503 | AP40: =AI40 -> 0.44 | AQ40: =AF40 -> 47483 | AR40: =AM40+AN40+AO40+AP40 -> #VALUE! | AT40: =-(AJ40-AR40) -> #VALUE!
N41: TD25 | U41: TD9 | AC41: =U41 -> TD9 | AH41: TD22 | AO41: Murban
AJ44: 75
A45: Dated | AJ45: 35
A46: ICE | AJ46: 0
E82: =E4 -> 46326 | F82: =MONTH(E82) -> 10 | G82: =VLOOKUP(MONTH(E82),$P$105:$Q$116,2,FALSE) -> 4 | H82: =RIGHT(YEAR(E82),2) -> 26 | I82: ="Q"&G82&"-"&H82 -> Q4-26
E83: =E5 -> 46356 | F83: =MONTH(E83) -> 11 | G83: =VLOOKUP(MONTH(E83),$P$105:$Q$116,2,FALSE) -> 4 | H83: =RIGHT(YEAR(E83),2) -> 26 | I83: ="Q"&G83&"-"&H83 -> Q4-26
E84: =E6 -> 46387 | F84: =MONTH(E84) -> 12 | G84: =VLOOKUP(MONTH(E84),$P$105:$Q$116,2,FALSE) -> 4 | H84: =RIGHT(YEAR(E84),2) -> 26 | I84: ="Q"&G84&"-"&H84 -> Q4-26
E85: =E7 -> 46418 | F85: =MONTH(E85) -> 1 | G85: =VLOOKUP(MONTH(E85),$P$105:$Q$116,2,FALSE) -> 1 | H85: =RIGHT(YEAR(E85),2) -> 27 | I85: ="Q"&G85&"-"&H85 -> Q1-27
E86: =E8 -> 46446 | F86: =MONTH(E86) -> 2 | G86: =VLOOKUP(MONTH(E86),$P$105:$Q$116,2,FALSE) -> 1 | H86: =RIGHT(YEAR(E86),2) -> 27 | I86: ="Q"&G86&"-"&H86 -> Q1-27
E87: =E9 -> 46477 | F87: =MONTH(E87) -> 3 | G87: =VLOOKUP(MONTH(E87),$P$105:$Q$116,2,FALSE) -> 1 | H87: =RIGHT(YEAR(E87),2) -> 27 | I87: ="Q"&G87&"-"&H87 -> Q1-27
E88: =E10 -> 46507 | F88: =MONTH(E88) -> 4 | G88: =VLOOKUP(MONTH(E88),$P$105:$Q$116,2,FALSE) -> 2 | H88: =RIGHT(YEAR(E88),2) -> 27 | I88: ="Q"&G88&"-"&H88 -> Q2-27
E89: =E11 -> 46538 | F89: =MONTH(E89) -> 5 | G89: =VLOOKUP(MONTH(E89),$P$105:$Q$116,2,FALSE) -> 2 | H89: =RIGHT(YEAR(E89),2) -> 27 | I89: ="Q"&G89&"-"&H89 -> Q2-27
E90: =E12 -> 46568 | F90: =MONTH(E90) -> 6 | G90: =VLOOKUP(MONTH(E90),$P$105:$Q$116,2,FALSE) -> 2 | H90: =RIGHT(YEAR(E90),2) -> 27 | I90: ="Q"&G90&"-"&H90 -> Q2-27 | J90: 1Q27 | P90: Grade | U90: Diff to Dated | V90: vs. FM ICE | X90: EFP Value | AC90: Arb?
E91: =E13 -> 46599 | F91: =MONTH(E91) -> 7 | G91: =VLOOKUP(MONTH(E91),$P$105:$Q$116,2,FALSE) -> 3 | H91: =RIGHT(YEAR(E91),2) -> 27 | I91: ="Q"&G91&"-"&H91 -> Q3-27 | J91: 1Q27 | P91: Brent | U91: -0.1 | V91: =U91+$T$6 -> 2.51 | X91: 0.05 | AC91: =X91-V91 -> -2.46
E92: =E14 -> 46630 | F92: =MONTH(E92) -> 8 | G92: =VLOOKUP(MONTH(E92),$P$105:$Q$116,2,FALSE) -> 3 | H92: =RIGHT(YEAR(E92),2) -> 27 | I92: ="Q"&G92&"-"&H92 -> Q3-27 | J92: 1Q27 | P92: Forties | U92: -0.74 | V92: =U92+$T$6 -> 1.87 | X92: 0.05 | AC92: =X92-V92 -> -1.82
E93: =E15 -> 46660 | F93: =MONTH(E93) -> 9 | G93: =VLOOKUP(MONTH(E93),$P$105:$Q$116,2,FALSE) -> 3 | H93: =RIGHT(YEAR(E93),2) -> 27 | I93: ="Q"&G93&"-"&H93 -> Q3-27 | J93: 2Q27 | P93: Oseberg | U93: 1.375 | V93: =U93+$T$6 -> 3.985 | X93: 0.05 | AC93: =X93-V93 -> -3.935
E94: =E16 -> 46691 | F94: =MONTH(E94) -> 10 | G94: =VLOOKUP(MONTH(E94),$P$105:$Q$116,2,FALSE) -> 4 | H94: =RIGHT(YEAR(E94),2) -> 27 | I94: ="Q"&G94&"-"&H94 -> Q4-27 | J94: 2Q27 | P94: Ekofisk | U94: 0.725 | V94: =U94+$T$6 -> 3.335 | X94: 0.05 | AC94: =X94-V94 -> -3.285
E95: =E17 -> 46721 | F95: =MONTH(E95) -> 11 | G95: =VLOOKUP(MONTH(E95),$P$105:$Q$116,2,FALSE) -> 4 | H95: =RIGHT(YEAR(E95),2) -> 27 | I95: ="Q"&G95&"-"&H95 -> Q4-27 | J95: 2Q27 | P95: Troll | U95: 1.675 | V95: =U95+$T$6 -> 4.285 | X95: 0.05 | AC95: =X95-V95 -> -4.235
E96: =E18 -> 46752 | F96: =MONTH(E96) -> 12 | G96: =VLOOKUP(MONTH(E96),$P$105:$Q$116,2,FALSE) -> 4 | H96: =RIGHT(YEAR(E96),2) -> 27 | I96: ="Q"&G96&"-"&H96 -> Q4-27 | J96: 3Q27
E97: =E19 -> 46783 | F97: =MONTH(E97) -> 1 | G97: =VLOOKUP(MONTH(E97),$P$105:$Q$116,2,FALSE) -> 1 | H97: =RIGHT(YEAR(E97),2) -> 28 | I97: ="Q"&G97&"-"&H97 -> Q1-28 | J97: 3Q27
E98: =E20 -> 46812 | F98: =MONTH(E98) -> 2 | G98: =VLOOKUP(MONTH(E98),$P$105:$Q$116,2,FALSE) -> 1 | H98: =RIGHT(YEAR(E98),2) -> 28 | I98: ="Q"&G98&"-"&H98 -> Q1-28 | J98: 3Q27
E99: =E21 -> 46843 | F99: =MONTH(E99) -> 3 | G99: =VLOOKUP(MONTH(E99),$P$105:$Q$116,2,FALSE) -> 1 | H99: =RIGHT(YEAR(E99),2) -> 28 | I99: ="Q"&G99&"-"&H99 -> Q1-28 | J99: 4Q27
E100: =E22 -> 46873 | F100: =MONTH(E100) -> 4 | G100: =VLOOKUP(MONTH(E100),$P$105:$Q$116,2,FALSE) -> 2 | H100: =RIGHT(YEAR(E100),2) -> 28 | I100: ="Q"&G100&"-"&H100 -> Q2-28 | J100: 4Q27
E101: =E23 -> 46904 | F101: =MONTH(E101) -> 5 | G101: =VLOOKUP(MONTH(E101),$P$105:$Q$116,2,FALSE) -> 2 | H101: =RIGHT(YEAR(E101),2) -> 28 | I101: ="Q"&G101&"-"&H101 -> Q2-28 | J101: 4Q27
E102: =E24 -> 46934 | F102: =MONTH(E102) -> 6 | G102: =VLOOKUP(MONTH(E102),$P$105:$Q$116,2,FALSE) -> 2 | H102: =RIGHT(YEAR(E102),2) -> 28 | I102: ="Q"&G102&"-"&H102 -> Q2-28 | J102: 1Q28
E103: =E25 -> 46965 | F103: =MONTH(E103) -> 7 | G103: =VLOOKUP(MONTH(E103),$P$105:$Q$116,2,FALSE) -> 3 | H103: =RIGHT(YEAR(E103),2) -> 28 | I103: ="Q"&G103&"-"&H103 -> Q3-28 | J103: 1Q28
E104: =E26 -> 46996 | F104: =MONTH(E104) -> 8 | G104: =VLOOKUP(MONTH(E104),$P$105:$Q$116,2,FALSE) -> 3 | H104: =RIGHT(YEAR(E104),2) -> 28 | I104: ="Q"&G104&"-"&H104 -> Q3-28 | J104: 1Q28
E105: =E27 -> 47026 | F105: =MONTH(E105) -> 9 | G105: =VLOOKUP(MONTH(E105),$P$105:$Q$116,2,FALSE) -> 3 | H105: =RIGHT(YEAR(E105),2) -> 28 | I105: ="Q"&G105&"-"&H105 -> Q3-28 | J105: 2Q28 | P105: 1 | Q105: 1
E106: =E28 -> 47057 | F106: =MONTH(E106) -> 10 | G106: =VLOOKUP(MONTH(E106),$P$105:$Q$116,2,FALSE) -> 4 | H106: =RIGHT(YEAR(E106),2) -> 28 | I106: ="Q"&G106&"-"&H106 -> Q4-28 | J106: 2Q28 | P106: =+P105+1 -> 2 | Q106: 1
E107: =E29 -> 47087 | F107: =MONTH(E107) -> 11 | G107: =VLOOKUP(MONTH(E107),$P$105:$Q$116,2,FALSE) -> 4 | H107: =RIGHT(YEAR(E107),2) -> 28 | I107: ="Q"&G107&"-"&H107 -> Q4-28 | J107: 2Q28 | P107: =+P106+1 -> 3 | Q107: 1
E108: =E30 -> 47118 | F108: =MONTH(E108) -> 12 | G108: =VLOOKUP(MONTH(E108),$P$105:$Q$116,2,FALSE) -> 4 | H108: =RIGHT(YEAR(E108),2) -> 28 | I108: ="Q"&G108&"-"&H108 -> Q4-28 | J108: Q328 | P108: =+P107+1 -> 4 | Q108: 2
E109: =E31 -> 47149 | F109: =MONTH(E109) -> 1 | G109: =VLOOKUP(MONTH(E109),$P$105:$Q$116,2,FALSE) -> 1 | H109: =RIGHT(YEAR(E109),2) -> 29 | I109: ="Q"&G109&"-"&H109 -> Q1-29 | J109: Q328 | P109: =+P108+1 -> 5 | Q109: 2
E110: =E32 -> 47177 | F110: =MONTH(E110) -> 2 | G110: =VLOOKUP(MONTH(E110),$P$105:$Q$116,2,FALSE) -> 1 | H110: =RIGHT(YEAR(E110),2) -> 29 | I110: ="Q"&G110&"-"&H110 -> Q1-29 | J110: Q328 | P110: =+P109+1 -> 6 | Q110: 2
E111: =E33 -> 47208 | F111: =MONTH(E111) -> 3 | G111: =VLOOKUP(MONTH(E111),$P$105:$Q$116,2,FALSE) -> 1 | H111: =RIGHT(YEAR(E111),2) -> 29 | I111: ="Q"&G111&"-"&H111 -> Q1-29 | J111: Q428 | P111: =+P110+1 -> 7 | Q111: 3
E112: =E34 -> 47238 | F112: =MONTH(E112) -> 4 | G112: =VLOOKUP(MONTH(E112),$P$105:$Q$116,2,FALSE) -> 2 | H112: =RIGHT(YEAR(E112),2) -> 29 | I112: ="Q"&G112&"-"&H112 -> Q2-29 | J112: Q428 | P112: =+P111+1 -> 8 | Q112: 3
E113: =E35 -> 47269 | F113: =MONTH(E113) -> 5 | G113: =VLOOKUP(MONTH(E113),$P$105:$Q$116,2,FALSE) -> 2 | H113: =RIGHT(YEAR(E113),2) -> 29 | I113: ="Q"&G113&"-"&H113 -> Q2-29 | J113: Q428 | P113: =+P112+1 -> 9 | Q113: 3
E114: =E36 -> 47299 | F114: =MONTH(E114) -> 6 | G114: =VLOOKUP(MONTH(E114),$P$105:$Q$116,2,FALSE) -> 2 | H114: =RIGHT(YEAR(E114),2) -> 29 | I114: ="Q"&G114&"-"&H114 -> Q2-29 | J114: 1Q37 | P114: =+P113+1 -> 10 | Q114: 4
E115: =E37 -> 47330 | F115: =MONTH(E115) -> 7 | G115: =VLOOKUP(MONTH(E115),$P$105:$Q$116,2,FALSE) -> 3 | H115: =RIGHT(YEAR(E115),2) -> 29 | I115: ="Q"&G115&"-"&H115 -> Q3-29 | J115: 1Q37 | P115: =+P114+1 -> 11 | Q115: 4
E116: =E38 -> 47361 | F116: =MONTH(E116) -> 8 | G116: =VLOOKUP(MONTH(E116),$P$105:$Q$116,2,FALSE) -> 3 | H116: =RIGHT(YEAR(E116),2) -> 29 | I116: ="Q"&G116&"-"&H116 -> Q3-29 | J116: 1Q37 | P116: =+P115+1 -> 12 | Q116: 4
E117: =E39 -> 47391 | F117: =MONTH(E117) -> 9 | G117: =VLOOKUP(MONTH(E117),$P$105:$Q$116,2,FALSE) -> 3 | H117: =RIGHT(YEAR(E117),2) -> 29 | I117: ="Q"&G117&"-"&H117 -> Q3-29 | J117: 2Q29
E118: =E40 -> 47422 | F118: =MONTH(E118) -> 10 | G118: =VLOOKUP(MONTH(E118),$P$105:$Q$116,2,FALSE) -> 4 | H118: =RIGHT(YEAR(E118),2) -> 29 | I118: ="Q"&G118&"-"&H118 -> Q4-29 | J118: 2Q29
J119: 2Q29
J120: Q329
J121: Q329
J122: Q329
J123: Q429
J124: Q429
J125: Q429

Sheet EFPs
A1: 0 | B1: 1 | D1: 0.7 | L1: EUROPE vs BFOETM Cash (Cal Dated basis)
J2: =J5-0.81 -> -9.4 | L2: First decade loaders | W2: Second/Third Decade
C3: Freight | D3: Diff | E3: Load | F3: MEH | G3: WTI Sprds | H3: Arbs | I3: FOB Premium | J3: FOB WTI vs. Brent | L3: Arrival | M3: Freight | N3: DFLs | O3: WTI CIF Rdam | P3: FOB Nsea | Q3: X-Nsea Freight | R3: M1-M3 Brent | S3: DFLs | T3: Cash BFOETM | U3: (Closed)/Open | W3: Arrival | X3: Brent Sprds | Y3: Freight | Z3: DFLs | AA3: =O3 -> WTI CIF Rdam | AB3: Cash BFOETM | AC3: (Closed)/Open
C4: =E4 -> 46326 | D4: =EOMONTH(E4,-1)+1 -> 46296 | E4: =EOMONTH(E5,-1) -> 46326 | F4: =IFERROR(INDEX(Sheet1!$B$5:$N$27,MATCH(EFPs!$F$3,Sheet1!$B$5:$B$27,0),MATCH(EFPs!D4,Sheet1!$B$5:$N$5,0)),F5) -> 0.75 | I4: 0 | J4: =_xlfn.XLOOKUP(EOMONTH(E4,2),BBG!$X$5:$X$28,BBG!$AB$5:$AB$28) -> -8.59 | L4: =EOMONTH(L5,-1) -> 46326 | M4: =VLOOKUP($C4,Freight!$A$3:$F$17,MATCH(EFPs!$M$30,Freight!$A$3:$F$3,0),FALSE)+$B$7 -> 17.18865 | O4: =J4+M4-N4 -> 8.59865 | P4: #N/A | Q4: =VLOOKUP($C4,Freight!$A$3:$F$17,MATCH(EFPs!$T$30,Freight!$A$3:$F$3,0),FALSE) -> 3.5918571 | S4: =N4 -> 0 | T4: =IFERROR(P4+Q4,"Expired") -> Expired | U4: =IFERROR(T4-O4,"Expired") -> Expired | W4: =EOMONTH(L4,1) -> 46356 | Y4: =VLOOKUP($C4,Freight!$A$3:$F$17,MATCH(EFPs!$M$30,Freight!$A$3:$F$3,0),FALSE)+$B$7 -> 17.18865 | AA4: =J4+X4+Y4-Z4 -> 8.59865 | AB4: =T5 -> Expired | AC4: Expired
A5: EFP | B5: 0 | C5: =E5 -> 46356 | D5: =EOMONTH(E5,-1)+1 -> 46327 | E5: =USG!E25 -> 46356 | F5: =+INDEX(Sheet1!$B$5:$N$27,MATCH(EFPs!$F$3,Sheet1!$B$5:$B$27,0),MATCH(EFPs!D5,Sheet1!$B$5:$N$5,0)) -> 1.35 | I5: 0 | J5: =_xlfn.XLOOKUP(EOMONTH(E5,1),BBG!$X$5:$X$28,BBG!$AB$5:$AB$28) -> -8.59 | L5: =EOMONTH(E5,0) -> 46356 | M5: =VLOOKUP($C4,Freight!$A$3:$F$17,MATCH(EFPs!$M$30,Freight!$A$3:$F$3,0),FALSE)+$B$7 -> 17.18865 | O5: =J5+M5-N5 -> 8.59865 | P5: #N/A | Q5: =VLOOKUP($C5,Freight!$A$3:$F$17,MATCH(EFPs!$T$30,Freight!$A$3:$F$3,0),FALSE) -> 3.142875 | S5: =N5 -> 0 | T5: =IFERROR(P5+Q5,"Expired") -> Expired | U5: =IFERROR(T5-O5,"Expired") -> Expired | W5: =EOMONTH(L5,1) -> 46387 | Y5: =VLOOKUP($C5,Freight!$A$3:$F$17,MATCH(EFPs!$M$30,Freight!$A$3:$F$3,0),FALSE)+$B$7 -> 16.2225 | AA5: =J5+X5+Y5-Z5 -> 7.6325 | AB5: =T6 -> 2.6938929 | AC5: =IFERROR(AB5-AA5,"Expired") -> -4.9386071
A6: Cash | C6: =E6 -> 46387 | D6: =EOMONTH(E6,-1)+1 -> 46357 | E6: =EOMONTH(E5,1) -> 46387 | F6: =+INDEX(Sheet1!$B$5:$N$27,MATCH(EFPs!$F$3,Sheet1!$B$5:$B$27,0),MATCH(EFPs!D6,Sheet1!$B$5:$N$5,0)) -> 1 | I6: =I5 -> 0 | J6: =_xlfn.XLOOKUP(EOMONTH(E6,0),BBG!$X$5:$X$28,BBG!$AB$5:$AB$28) -> -8.59 | L6: =EOMONTH(E6,0) -> 46387 | M6: =VLOOKUP($C5,Freight!$A$3:$F$17,MATCH(EFPs!$M$30,Freight!$A$3:$F$3,0),FALSE)+$B$7 -> 16.2225 | O6: =J6+M6-N6 -> 7.6325 | P6: =$B$5 -> 0 | Q6: =VLOOKUP($C6,Freight!$A$3:$F$17,MATCH(EFPs!$T$30,Freight!$A$3:$F$3,0),FALSE) -> 2.6938929 | S6: =N6 -> 0 | T6: =IFERROR(P6+Q6,"Expired") -> 2.6938929 | U6: =IFERROR(T6-O6,"Expired") -> -4.9386071 | W6: =EOMONTH(L6,1) -> 46418 | X6: =IF(BBG!$D$5=BBG!$J$5,BBG!L6-BBG!L7,BBG!L5-BBG!L6) -> 2.94 | Y6: =VLOOKUP($C6,Freight!$A$3:$F$17,MATCH(EFPs!$M$30,Freight!$A$3:$F$3,0),FALSE)+$B$7 -> 12.7873 | AA6: =J6+X6+Y6-Z6 -> 7.1373 | AB6: =T7 -> 1.9058472 | AC6: =IFERROR(AB6-AA6,"Expired") -> -5.2314528
A7: tvm, ETC | B7: 0.12 | C7: =E7 -> 46418 | D7: =EOMONTH(E7,-1)+1 -> 46388 | E7: =EOMONTH(E6,1) -> 46418 | F7: =+INDEX(Sheet1!$B$5:$N$27,MATCH(EFPs!$F$3,Sheet1!$B$5:$B$27,0),MATCH(EFPs!D7,Sheet1!$B$5:$N$5,0)) -> 1.2 | I7: =I6 -> 0 | J7: =_xlfn.XLOOKUP(EOMONTH(E7,0),BBG!$X$5:$X$28,BBG!$AB$5:$AB$28) -> -7.08 | L7: =EOMONTH(E7,0) -> 46418 | M7: =VLOOKUP($C6,Freight!$A$3:$F$17,MATCH(EFPs!$M$30,Freight!$A$3:$F$3,0),FALSE)+$B$7 -> 12.7873 | O7: =J7+M7-N7 -> 5.7073 | P7: =$B$5 -> 0 | Q7: =VLOOKUP($C7,Freight!$A$3:$F$17,MATCH(EFPs!$T$30,Freight!$A$3:$F$3,0),FALSE) -> 1.9058472 | S7: =N7 -> 0 | T7: =IFERROR(P7+Q7,"Expired") -> 1.9058472 | U7: =IFERROR(T7-O7,"Expired") -> -3.8014528 | W7: =EOMONTH(L7,1) -> 46446 | X7: =IF(BBG!$D$5=BBG!$J$5,BBG!L7-BBG!L8,BBG!L6-BBG!L7) -> 2.24 | Y7: =VLOOKUP($C7,Freight!$A$3:$F$17,MATCH(EFPs!$M$30,Freight!$A$3:$F$3,0),FALSE)+$B$7 -> 8.3462494 | AA7: =J7+X7+Y7-Z7 -> 3.5062494 | AB7: =T8 -> 1.8615252 | AC7: =IFERROR(AB7-AA7,"Expired") -> -1.6447242
B8: 0.12 | C8: =E8 -> 46446 | D8: =EOMONTH(E8,-1)+1 -> 46419 | E8: =EOMONTH(E7,1) -> 46446 | F8: =+INDEX(Sheet1!$B$5:$N$27,MATCH(EFPs!$F$3,Sheet1!$B$5:$B$27,0),MATCH(EFPs!D8,Sheet1!$B$5:$N$5,0)) -> 1.4 | I8: =I7 -> 0 | J8: =_xlfn.XLOOKUP(EOMONTH(E8,0),BBG!$X$5:$X$28,BBG!$AB$5:$AB$28) -> -6.38 | L8: =EOMONTH(E8,0) -> 46446 | M8: =VLOOKUP($C7,Freight!$A$3:$F$17,MATCH(EFPs!$M$30,Freight!$A$3:$F$3,0),FALSE)+$B$7 -> 8.3462494 | O8: =J8+M8-N8 -> 1.9662494 | P8: =$B$5 -> 0 | Q8: =VLOOKUP($C8,Freight!$A$3:$F$17,MATCH(EFPs!$T$30,Freight!$A$3:$F$3,0),FALSE) -> 1.8615252 | S8: =N8 -> 0 | T8: =IFERROR(P8+Q8,"Expired") -> 1.8615252 | U8: =IFERROR(T8-O8,"Expired") -> -0.10472423 | W8: =EOMONTH(L8,1) -> 46477 | X8: =IF(BBG!$D$5=BBG!$J$5,BBG!L8-BBG!L9,BBG!L7-BBG!L8) -> 1.7 | Y8: =VLOOKUP($C8,Freight!$A$3:$F$17,MATCH(EFPs!$M$30,Freight!$A$3:$F$3,0),FALSE)+$B$7 -> 8.0396811 | AA8: =J8+X8+Y8-Z8 -> 3.3596811 | AB8: =T9 -> 1.8172031 | AC8: =IFERROR(AB8-AA8,"Expired") -> -1.542478
A9: Dated | C9: =E9 -> 46477 | D9: =EOMONTH(E9,-1)+1 -> 46447 | E9: =EOMONTH(E8,1) -> 46477 | F9: =+INDEX(Sheet1!$B$5:$N$27,MATCH(EFPs!$F$3,Sheet1!$B$5:$B$27,0),MATCH(EFPs!D9,Sheet1!$B$5:$N$5,0)) -> 1.55 | I9: =I8 -> 0 | J9: =_xlfn.XLOOKUP(EOMONTH(E9,0),BBG!$X$5:$X$28,BBG!$AB$5:$AB$28) -> -6 | L9: =EOMONTH(E9,0) -> 46477 | M9: =VLOOKUP($C9,Freight!$A$3:$F$17,MATCH(EFPs!$M$30,Freight!$A$3:$F$3,0),FALSE)+$B$7 -> 7.7331128 | O9: =J9+M9-N9 -> 1.7331128 | P9: =$B$5 -> 0 | Q9: =VLOOKUP($C9,Freight!$A$3:$F$17,MATCH(EFPs!$T$30,Freight!$A$3:$F$3,0),FALSE) -> 1.8172031 | S9: =N9 -> 0 | T9: =IFERROR(P9+Q9,"Expired") -> 1.8172031 | U9: =IFERROR(T9-O9,"Expired") -> 0.084090341 | W9: =EOMONTH(L9,1) -> 46507 | X9: =IF(BBG!$D$5=BBG!$J$5,BBG!L9-BBG!L10,BBG!L8-BBG!L9) -> 1.48 | Y9: =VLOOKUP($C9,Freight!$A$3:$F$17,MATCH(EFPs!$M$30,Freight!$A$3:$F$3,0),FALSE)+$B$7 -> 7.7331128 | AA9: =J9+X9+Y9-Z9 -> 3.2131128 | AB9: =T10 -> 1.5069489 | AC9: =IFERROR(AB9-AA9,"Expired") -> -1.7061639
C10: =E10 -> 46507 | D10: =EOMONTH(E10,-1)+1 -> 46478 | E10: =EOMONTH(E9,1) -> 46507 | F10: =+INDEX(Sheet1!$B$5:$N$27,MATCH(EFPs!$F$3,Sheet1!$B$5:$B$27,0),MATCH(EFPs!D10,Sheet1!$B$5:$N$5,0)) -> 1.75 | I10: =I9 -> 0 | J10: =_xlfn.XLOOKUP(EOMONTH(E10,0),BBG!$X$5:$X$28,BBG!$AB$5:$AB$28) -> -5.7 | L10: =EOMONTH(E10,0) -> 46507 | M10: =VLOOKUP($C10,Freight!$A$3:$F$17,MATCH(EFPs!$M$30,Freight!$A$3:$F$3,0),FALSE)+$B$7 -> 6.8645026 | O10: =J10+M10-N10 -> 1.1645026 | P10: =$B$5 -> 0 | Q10: =VLOOKUP($C10,Freight!$A$3:$F$17,MATCH(EFPs!$T$30,Freight!$A$3:$F$3,0),FALSE) -> 1.5069489 | S10: =N10 -> 0 | T10: =IFERROR(P10+Q10,"Expired") -> 1.5069489 | U10: =IFERROR(T10-O10,"Expired") -> 0.34244633 | W10: =EOMONTH(L10,1) -> 46538 | X10: =IF(BBG!$D$5=BBG!$J$5,BBG!L10-BBG!L11,BBG!L9-BBG!L10) -> 1.33 | Y10: =VLOOKUP($C10,Freight!$A$3:$F$17,MATCH(EFPs!$M$30,Freight!$A$3:$F$3,0),FALSE)+$B$7 -> 6.8645026 | AA10: =J10+X10+Y10-Z10 -> 2.4945026 | AB10: =T11 -> 1.5069489 | AC10: =IFERROR(AB10-AA10,"Expired") -> -0.98755367
B11: =VLOOKUP(E11,$E$71:$I$107,5,FALSE) -> Q2-27 | C11: =E11 -> 46538 | D11: =EOMONTH(E11,-1)+1 -> 46508 | E11: =EOMONTH(E10,1) -> 46538 | F11: =+INDEX(Sheet1!$B$5:$N$27,MATCH(EFPs!$F$3,Sheet1!$B$5:$B$27,0),MATCH(EFPs!D11,Sheet1!$B$5:$N$5,0)) -> 1.8 | I11: =I10 -> 0 | J11: =_xlfn.XLOOKUP(EOMONTH(E11,0),BBG!$X$5:$X$28,BBG!$AB$5:$AB$28) -> -5.42 | L11: =EOMONTH(E11,0) -> 46538 | M11: =IFERROR(VLOOKUP($C11,Freight!$A$3:$F$17,MATCH(EFPs!$M$30,Freight!$A$3:$F$3,0),FALSE)+$B$7,VLOOKUP($B11,Freight!$A$3:$F$17,MATCH(EFPs!$M$30,Freight!$A$3:$F$3,0),FALSE)+$B$7) -> 6.5579343 | O11: =J11+M11-N11 -> 1.1379343 | P11: =$B$5 -> 0 | Q11: =IFERROR(VLOOKUP($C11,Freight!$A$3:$F$22,MATCH(EFPs!$T$30,Freight!$A$3:$F$3,0),FALSE),VLOOKUP($B11,Freight!$A$3:$F$22,MATCH(EFPs!$T$30,Freight!$A$3:$F$3,0),FALSE)) -> 1.5069489 | S11: =N11 -> 0 | T11: =IFERROR(P11+Q11,"Expired") -> 1.5069489 | U11: =IFERROR(T11-O11,"Expired") -> 0.36901463 | W11: =EOMONTH(L11,1) -> 46568 | X11: =IF(BBG!$D$5=BBG!$J$5,BBG!L11-BBG!L12,BBG!L10-BBG!L11) -> 1.25 | Y11: =IFERROR(VLOOKUP($C11,Freight!$A$3:$F$17,MATCH(EFPs!$M$30,Freight!$A$3:$F$3,0),FALSE)+$B$7,VLOOKUP($B11,Freight!$A$3:$F$17,MATCH(EFPs!$M$30,Freight!$A$3:$F$3,0),FALSE)+$B$7) -> 6.5579343 | AA11: =J11+X11+Y11-Z11 -> 2.3879343 | AB11: =T12 -> 1.5069489 | AC11: =IFERROR(AB11-AA11,"Expired") -> -0.88098537
B12: =VLOOKUP(E12,$E$71:$I$107,5,FALSE) -> Q2-27 | C12: =E12 -> 46568 | D12: =EOMONTH(E12,-1)+1 -> 46539 | E12: =EOMONTH(E11,1) -> 46568 | F12: =+INDEX(Sheet1!$B$5:$N$27,MATCH(EFPs!$F$3,Sheet1!$B$5:$B$27,0),MATCH(EFPs!D12,Sheet1!$B$5:$N$5,0)) -> 1.85 | I12: =I11 -> 0 | J12: =_xlfn.XLOOKUP(EOMONTH(E12,0),BBG!$X$5:$X$28,BBG!$AB$5:$AB$28) -> -5.04 | L12: =EOMONTH(E12,0) -> 46568 | M12: =IFERROR(VLOOKUP($C12,Freight!$A$3:$F$17,MATCH(EFPs!$M$30,Freight!$A$3:$F$3,0),FALSE)+$B$7,VLOOKUP($B12,Freight!$A$3:$F$17,MATCH(EFPs!$M$30,Freight!$A$3:$F$3,0),FALSE)+$B$7) -> 6.5579343 | O12: =J12+M12-N12 -> 1.5179343 | P12: =$B$5 -> 0 | Q12: =IFERROR(VLOOKUP($C12,Freight!$A$3:$F$22,MATCH(EFPs!$T$30,Freight!$A$3:$F$3,0),FALSE),VLOOKUP($B12,Freight!$A$3:$F$22,MATCH(EFPs!$T$30,Freight!$A$3:$F$3,0),FALSE)) -> 1.5069489 | S12: =N12 -> 0 | T12: =IFERROR(P12+Q12,"Expired") -> 1.5069489 | U12: =IFERROR(T12-O12,"Expired") -> -0.010985368 | W12: =EOMONTH(L12,1) -> 46599 | X12: =IF(BBG!$D$5=BBG!$J$5,BBG!L12-BBG!L13,BBG!L11-BBG!L12) -> 1.18 | Y12: =IFERROR(VLOOKUP($C12,Freight!$A$3:$F$17,MATCH(EFPs!$M$30,Freight!$A$3:$F$3,0),FALSE)+$B$7,VLOOKUP($B12,Freight!$A$3:$F$17,MATCH(EFPs!$M$30,Freight!$A$3:$F$3,0),FALSE)+$B$7) -> 6.5579343 | AA12: =J12+X12+Y12-Z12 -> 2.6979343 | AB12: =T13 -> 1.4183049 | AC12: =IFERROR(AB12-AA12,"Expired") -> -1.2796294
B13: =VLOOKUP(E13,$E$71:$I$107,5,FALSE) -> Q3-27 | C13: =E13 -> 46599 | D13: =EOMONTH(E13,-1)+1 -> 46569 | E13: =EOMONTH(E12,1) -> 46599 | F13: =+INDEX(Sheet1!$B$5:$N$27,MATCH(EFPs!$F$3,Sheet1!$B$5:$B$27,0),MATCH(EFPs!D13,Sheet1!$B$5:$N$5,0)) -> 1.85 | I13: =I12 -> 0 | J13: =_xlfn.XLOOKUP(EOMONTH(E13,0),BBG!$X$5:$X$28,BBG!$AB$5:$AB$28) -> -4.74 | L13: =EOMONTH(E13,0) -> 46599 | M13: =IFERROR(VLOOKUP($C13,Freight!$A$3:$F$17,MATCH(EFPs!$M$30,Freight!$A$3:$F$3,0),FALSE)+$B$7,VLOOKUP($B13,Freight!$A$3:$F$17,MATCH(EFPs!$M$30,Freight!$A$3:$F$3,0),FALSE)+$B$7) -> 5.4849453 | O13: =J13+M13-N13 -> 0.74494526 | P13: =$B$5 -> 0 | Q13: =IFERROR(VLOOKUP($C13,Freight!$A$3:$F$22,MATCH(EFPs!$T$30,Freight!$A$3:$F$3,0),FALSE),VLOOKUP($B13,Freight!$A$3:$F$22,MATCH(EFPs!$T$30,Freight!$A$3:$F$3,0),FALSE)) -> 1.4183049 | S13: =N13 -> 0 | T13: =IFERROR(P13+Q13,"Expired") -> 1.4183049 | U13: =IFERROR(T13-O13,"Expired") -> 0.67335963 | W13: =EOMONTH(L13,1) -> 46630 | X13: =IF(BBG!$D$5=BBG!$J$5,BBG!L13-BBG!L14,BBG!L12-BBG!L13) -> 1.1 | Y13: =IFERROR(VLOOKUP($C13,Freight!$A$3:$F$17,MATCH(EFPs!$M$30,Freight!$A$3:$F$3,0),FALSE)+$B$7,VLOOKUP($B13,Freight!$A$3:$F$17,MATCH(EFPs!$M$30,Freight!$A$3:$F$3,0),FALSE)+$B$7) -> 5.4849453 | AA13: =J13+X13+Y13-Z13 -> 1.8449453 | AB13: =T14 -> 1.4183049 | AC13: =IFERROR(AB13-AA13,"Expired") -> -0.42664037
B14: =VLOOKUP(E14,$E$71:$I$107,5,FALSE) -> Q3-27 | C14: =E14 -> 46630 | D14: 3Q26 | E14: =EOMONTH(E13,1) -> 46630 | F14: =INDEX(Sheet1!$B$38:$N$49,MATCH("MEH",Sheet1!$B$38:$B$49,0),MATCH(EFPs!D14,Sheet1!$B$38:$N$38,0)) -> #N/A | I14: =I13 -> 0 | J14: =_xlfn.XLOOKUP(EOMONTH(E14,0),BBG!$X$5:$X$28,BBG!$AB$5:$AB$28) -> -4.52 | L14: =EOMONTH(E14,0) -> 46630 | M14: =IFERROR(VLOOKUP($C14,Freight!$A$3:$F$17,MATCH(EFPs!$M$30,Freight!$A$3:$F$3,0),FALSE)+$B$7,VLOOKUP($B14,Freight!$A$3:$F$17,MATCH(EFPs!$M$30,Freight!$A$3:$F$3,0),FALSE)+$B$7) -> 5.4849453 | O14: =J14+M14-N14 -> 0.96494526 | P14: =$B$5 -> 0 | Q14: =IFERROR(VLOOKUP($C14,Freight!$A$3:$F$22,MATCH(EFPs!$T$30,Freight!$A$3:$F$3,0),FALSE),VLOOKUP($B14,Freight!$A$3:$F$22,MATCH(EFPs!$T$30,Freight!$A$3:$F$3,0),FALSE)) -> 1.4183049 | S14: =N14 -> 0 | T14: =IFERROR(P14+Q14,"Expired") -> 1.4183049 | U14: =T14-O14 -> 0.45335963 | W14: =EOMONTH(L14,1) -> 46660 | X14: =IF(BBG!$D$5=BBG!$J$5,BBG!L14-BBG!L15,BBG!L13-BBG!L14) -> 1.02 | Y14: =IFERROR(VLOOKUP($C14,Freight!$A$3:$F$17,MATCH(EFPs!$M$30,Freight!$A$3:$F$3,0),FALSE)+$B$7,VLOOKUP($B14,Freight!$A$3:$F$17,MATCH(EFPs!$M$30,Freight!$A$3:$F$3,0),FALSE)+$B$7) -> 5.4849453 | AA14: =J14+X14+Y14-Z14 -> 1.9849453 | AB14: =T15 -> 1.4183049 | AC14: =AB14-AA14 -> -0.56664037
B15: =VLOOKUP(E15,$E$71:$I$107,5,FALSE) -> Q3-27 | C15: =E15 -> 46660 | D15: 3Q26 | E15: =EOMONTH(E14,1) -> 46660 | F15: =INDEX(Sheet1!$B$38:$N$49,MATCH("MEH",Sheet1!$B$38:$B$49,0),MATCH(EFPs!D15,Sheet1!$B$38:$N$38,0)) -> #N/A | I15: =I14 -> 0 | J15: =_xlfn.XLOOKUP(EOMONTH(E15,0),BBG!$X$5:$X$28,BBG!$AB$5:$AB$28) -> -4.36 | L15: =EOMONTH(E15,0) -> 46660 | M15: =IFERROR(VLOOKUP($C15,Freight!$A$3:$F$17,MATCH(EFPs!$M$30,Freight!$A$3:$F$3,0),FALSE)+$B$7,VLOOKUP($B15,Freight!$A$3:$F$17,MATCH(EFPs!$M$30,Freight!$A$3:$F$3,0),FALSE)+$B$7) -> 5.4849453 | O15: =J15+M15-N15 -> 1.1249453 | P15: =$B$5 -> 0 | Q15: =IFERROR(VLOOKUP($C15,Freight!$A$3:$F$22,MATCH(EFPs!$T$30,Freight!$A$3:$F$3,0),FALSE),VLOOKUP($B15,Freight!$A$3:$F$22,MATCH(EFPs!$T$30,Freight!$A$3:$F$3,0),FALSE)) -> 1.4183049 | S15: =N15 -> 0 | T15: =IFERROR(P15+Q15,"Expired") -> 1.4183049 | U15: =T15-O15 -> 0.29335963 | W15: =EOMONTH(L15,1) -> 46691 | X15: =IF(BBG!$D$5=BBG!$J$5,BBG!L15-BBG!L16,BBG!L14-BBG!L15) -> 0.93 | Y15: =IFERROR(VLOOKUP($C15,Freight!$A$3:$F$17,MATCH(EFPs!$M$30,Freight!$A$3:$F$3,0),FALSE)+$B$7,VLOOKUP($B15,Freight!$A$3:$F$17,MATCH(EFPs!$M$30,Freight!$A$3:$F$3,0),FALSE)+$B$7) -> 5.4849453 | AA15: =J15+X15+Y15-Z15 -> 2.0549453 | AB15: =T16 -> 1.595593 | AC15: =AB15-AA15 -> -0.45935226
B16: =VLOOKUP(E16,$E$71:$I$107,5,FALSE) -> Q4-27 | C16: =E16 -> 46691 | D16: 4Q26 | E16: =EOMONTH(E15,1) -> 46691 | F16: =INDEX(Sheet1!$B$38:$N$49,MATCH("MEH",Sheet1!$B$38:$B$49,0),MATCH(EFPs!D16,Sheet1!$B$38:$N$38,0)) -> 1.033 | I16: =I15 -> 0 | J16: =_xlfn.XLOOKUP(EOMONTH(E16,0),BBG!$X$5:$X$28,BBG!$AB$5:$AB$28) -> -4.12 | L16: =EOMONTH(E16,0) -> 46691 | M16: =IFERROR(VLOOKUP($C16,Freight!$A$3:$F$22,MATCH(EFPs!$M$30,Freight!$A$3:$F$3,0),FALSE)+$B$7,VLOOKUP($B16,Freight!$A$3:$F$22,MATCH(EFPs!$M$30,Freight!$A$3:$F$3,0),FALSE)+$B$7) -> 5.6382294 | O16: =J16+M16-N16 -> 1.5182294 | P16: =$B$5 -> 0 | Q16: =IFERROR(VLOOKUP($C16,Freight!$A$3:$F$22,MATCH(EFPs!$T$30,Freight!$A$3:$F$3,0),FALSE),VLOOKUP($B16,Freight!$A$3:$F$22,MATCH(EFPs!$T$30,Freight!$A$3:$F$3,0),FALSE)) -> 1.595593 | S16: =N16 -> 0 | T16: =IFERROR(P16+Q16,"Expired") -> 1.595593 | U16: =T16-O16 -> 0.077363591 | W16: =EOMONTH(L16,1) -> 46721 | X16: =IF(BBG!$D$5=BBG!$J$5,BBG!L16-BBG!L17,BBG!L15-BBG!L16) -> 0.83 | Y16: =IFERROR(VLOOKUP($C17,Freight!$A$3:$F$22,MATCH(EFPs!$M$30,Freight!$A$3:$F$3,0),FALSE)+$B$7,VLOOKUP($B17,Freight!$A$3:$F$22,MATCH(EFPs!$M$30,Freight!$A$3:$F$3,0),FALSE)+$B$7) -> 5.6382294 | AA16: =J16+X16+Y16-Z16 -> 2.3482294 | AB16: =T17 -> 1.595593 | AC16: =AB16-AA16 -> -0.75263641
B17: =VLOOKUP(E17,$E$71:$I$107,5,FALSE) -> Q4-27 | C17: =E17 -> 46721 | D17: 4Q26 | E17: =EOMONTH(E16,1) -> 46721 | F17: =INDEX(Sheet1!$B$38:$N$49,MATCH("MEH",Sheet1!$B$38:$B$49,0),MATCH(EFPs!D17,Sheet1!$B$38:$N$38,0)) -> 1.033 | I17: =I16 -> 0 | J17: =_xlfn.XLOOKUP(EOMONTH(E17,0),BBG!$X$5:$X$28,BBG!$AB$5:$AB$28) -> -3.98 | L17: =EOMONTH(E17,0) -> 46721 | M17: =IFERROR(VLOOKUP($C17,Freight!$A$3:$F$22,MATCH(EFPs!$M$30,Freight!$A$3:$F$3,0),FALSE)+$B$7,VLOOKUP($B17,Freight!$A$3:$F$22,MATCH(EFPs!$M$30,Freight!$A$3:$F$3,0),FALSE)+$B$7) -> 5.6382294 | O17: =J17+M17-N17 -> 1.6582294 | P17: =$B$5 -> 0 | Q17: =IFERROR(VLOOKUP($C17,Freight!$A$3:$F$22,MATCH(EFPs!$T$30,Freight!$A$3:$F$3,0),FALSE),VLOOKUP($B17,Freight!$A$3:$F$22,MATCH(EFPs!$T$30,Freight!$A$3:$F$3,0),FALSE)) -> 1.595593 | S17: =N17 -> 0 | T17: =IFERROR(P17+Q17,"Expired") -> 1.595593 | U17: =T17-O17 -> -0.062636409 | W17: =EOMONTH(L17,1) -> 46752 | X17: =IF(BBG!$D$5=BBG!$J$5,BBG!L17-BBG!L18,BBG!L16-BBG!L17) -> 0.78 | Y17: =IFERROR(VLOOKUP($C18,Freight!$A$3:$F$22,MATCH(EFPs!$M$30,Freight!$A$3:$F$3,0),FALSE)+$B$7,VLOOKUP($B18,Freight!$A$3:$F$22,MATCH(EFPs!$M$30,Freight!$A$3:$F$3,0),FALSE)+$B$7) -> 5.6382294 | AA17: =J17+X17+Y17-Z17 -> 2.4382294 | AB17: =T18 -> 1.595593 | AC17: =AB17-AA17 -> -0.84263641
B18: =VLOOKUP(E18,$E$71:$I$107,5,FALSE) -> Q4-27 | C18: =E18 -> 46752 | D18: 4Q26 | E18: =EOMONTH(E17,1) -> 46752 | F18: =INDEX(Sheet1!$B$38:$N$49,MATCH("MEH",Sheet1!$B$38:$B$49,0),MATCH(EFPs!D18,Sheet1!$B$38:$N$38,0)) -> 1.033 | I18: =I17 -> 0 | J18: =_xlfn.XLOOKUP(EOMONTH(E18,0),BBG!$X$5:$X$28,BBG!$AB$5:$AB$28) -> -3.87 | L18: =EOMONTH(E18,0) -> 46752 | M18: =IFERROR(VLOOKUP($C18,Freight!$A$3:$F$22,MATCH(EFPs!$M$30,Freight!$A$3:$F$3,0),FALSE)+$B$7,VLOOKUP($B18,Freight!$A$3:$F$22,MATCH(EFPs!$M$30,Freight!$A$3:$F$3,0),FALSE)+$B$7) -> 5.6382294 | O18: =J18+M18-N18 -> 1.7682294 | P18: =$B$5 -> 0 | Q18: =IFERROR(VLOOKUP($C18,Freight!$A$3:$F$22,MATCH(EFPs!$T$30,Freight!$A$3:$F$3,0),FALSE),VLOOKUP($B18,Freight!$A$3:$F$22,MATCH(EFPs!$T$30,Freight!$A$3:$F$3,0),FALSE)) -> 1.595593 | S18: =N18 -> 0 | T18: =IFERROR(P18+Q18,"Expired") -> 1.595593 | U18: =T18-O18 -> -0.17263641 | W18: =EOMONTH(L18,1) -> 46783 | X18: =IF(BBG!$D$5=BBG!$J$5,BBG!L18-BBG!L19,BBG!L17-BBG!L18) -> 0.74 | Y18: =IFERROR(VLOOKUP($C19,Freight!$A$3:$F$22,MATCH(EFPs!$M$30,Freight!$A$3:$F$3,0),FALSE)+$B$7,VLOOKUP($B19,Freight!$A$3:$F$22,MATCH(EFPs!$M$30,Freight!$A$3:$F$3,0),FALSE)+$B$7) -> 4.6674298 | AA18: =J18+X18+Y18-Z18 -> 1.5374298 | AB18: =T19 -> 1.4626269 | AC18: =AB18-AA18 -> -0.074802874
B19: =VLOOKUP(E19,$E$71:$I$107,5,FALSE) -> Q1-28 | C19: =E19 -> 46783 | D19: 1H27 | E19: =EOMONTH(E18,1) -> 46783 | F19: =INDEX(Sheet1!$B$38:$N$49,MATCH("MEH",Sheet1!$B$38:$B$49,0),MATCH(EFPs!D19,Sheet1!$B$38:$N$38,0)) -> 1.592 | I19: =I18 -> 0 | J19: =_xlfn.XLOOKUP(EOMONTH(E19,0),BBG!$X$5:$X$28,BBG!$AB$5:$AB$28) -> -3.76 | L19: =EOMONTH(E19,0) -> 46783 | M19: =IFERROR(VLOOKUP($C19,Freight!$A$3:$F$22,MATCH(EFPs!$M$30,Freight!$A$3:$F$3,0),FALSE)+$B$7,VLOOKUP($B19,Freight!$A$3:$F$22,MATCH(EFPs!$M$30,Freight!$A$3:$F$3,0),FALSE)+$B$7) -> 4.6674298 | O19: =J19+M19-N19 -> 0.9074298 | P19: =$B$5 -> 0 | Q19: =IFERROR(VLOOKUP($C19,Freight!$A$3:$F$22,MATCH(EFPs!$T$30,Freight!$A$3:$F$3,0),FALSE),VLOOKUP($B19,Freight!$A$3:$F$22,MATCH(EFPs!$T$30,Freight!$A$3:$F$3,0),FALSE)) -> 1.4626269 | S19: =N19 -> 0 | T19: =IFERROR(P19+Q19,"Expired") -> 1.4626269 | U19: =T19-O19 -> 0.55519713 | W19: =EOMONTH(L19,1) -> 46812 | X19: =IF(BBG!$D$5=BBG!$J$5,BBG!L19-BBG!L20,BBG!L18-BBG!L19) -> 0.69 | Y19: =IFERROR(VLOOKUP($C20,Freight!$A$3:$F$22,MATCH(EFPs!$M$30,Freight!$A$3:$F$3,0),FALSE)+$B$7,VLOOKUP($B20,Freight!$A$3:$F$22,MATCH(EFPs!$M$30,Freight!$A$3:$F$3,0),FALSE)+$B$7) -> 4.6674298 | AA19: =J19+X19+Y19-Z19 -> 1.5974298 | AB19: =T20 -> 1.4626269 | AC19: =AB19-AA19 -> -0.13480287
B20: =VLOOKUP(E20,$E$71:$I$107,5,FALSE) -> Q1-28 | C20: =E20 -> 46812 | D20: 1H27 | E20: =EOMONTH(E19,1) -> 46812 | F20: =INDEX(Sheet1!$B$38:$N$49,MATCH("MEH",Sheet1!$B$38:$B$49,0),MATCH(EFPs!D20,Sheet1!$B$38:$N$38,0)) -> 1.592 | I20: =I19 -> 0 | J20: =_xlfn.XLOOKUP(EOMONTH(E20,0),BBG!$X$5:$X$28,BBG!$AB$5:$AB$28) -> -3.61 | L20: =EOMONTH(E20,0) -> 46812 | M20: =IFERROR(VLOOKUP($C20,Freight!$A$3:$F$22,MATCH(EFPs!$M$30,Freight!$A$3:$F$3,0),FALSE)+$B$7,VLOOKUP($B20,Freight!$A$3:$F$22,MATCH(EFPs!$M$30,Freight!$A$3:$F$3,0),FALSE)+$B$7) -> 4.6674298 | O20: =J20+M20-N20 -> 1.0574298 | P20: =$B$5 -> 0 | Q20: =IFERROR(VLOOKUP($C20,Freight!$A$3:$F$22,MATCH(EFPs!$T$30,Freight!$A$3:$F$3,0),FALSE),VLOOKUP($B20,Freight!$A$3:$F$22,MATCH(EFPs!$T$30,Freight!$A$3:$F$3,0),FALSE)) -> 1.4626269 | S20: =N20 -> 0 | T20: =IFERROR(P20+Q20,"Expired") -> 1.4626269 | U20: =T20-O20 -> 0.40519713 | W20: =EOMONTH(L20,1) -> 46843 | X20: =IF(BBG!$D$5=BBG!$J$5,BBG!L20-BBG!L21,BBG!L19-BBG!L20) -> 0.6 | Y20: =IFERROR(VLOOKUP($C21,Freight!$A$3:$F$22,MATCH(EFPs!$M$30,Freight!$A$3:$F$3,0),FALSE)+$B$7,VLOOKUP($B21,Freight!$A$3:$F$22,MATCH(EFPs!$M$30,Freight!$A$3:$F$3,0),FALSE)+$B$7) -> 4.6674298 | AA20: =J20+X20+Y20-Z20 -> 1.6574298 | AB20: =T21 -> 1.4626269 | AC20: =AB20-AA20 -> -0.19480287
B21: =VLOOKUP(E21,$E$71:$I$107,5,FALSE) -> Q1-28 | C21: =E21 -> 46843 | D21: 1H27 | E21: =EOMONTH(E20,1) -> 46843 | F21: =INDEX(Sheet1!$B$38:$N$49,MATCH("MEH",Sheet1!$B$38:$B$49,0),MATCH(EFPs!D21,Sheet1!$B$38:$N$38,0)) -> 1.592 | I21: =I20 -> 0 | J21: =_xlfn.XLOOKUP(EOMONTH(E21,0),BBG!$X$5:$X$28,BBG!$AB$5:$AB$28) -> -3.44 | L21: =EOMONTH(E21,0) -> 46843 | M21: =IFERROR(VLOOKUP($C21,Freight!$A$3:$F$22,MATCH(EFPs!$M$30,Freight!$A$3:$F$3,0),FALSE)+$B$7,VLOOKUP($B21,Freight!$A$3:$F$22,MATCH(EFPs!$M$30,Freight!$A$3:$F$3,0),FALSE)+$B$7) -> 4.6674298 | O21: =J21+M21-N21 -> 1.2274298 | P21: =$B$5 -> 0 | Q21: =IFERROR(VLOOKUP($C21,Freight!$A$3:$F$22,MATCH(EFPs!$T$30,Freight!$A$3:$F$3,0),FALSE),VLOOKUP($B21,Freight!$A$3:$F$22,MATCH(EFPs!$T$30,Freight!$A$3:$F$3,0),FALSE)) -> 1.4626269 | S21: =N21 -> 0 | T21: =IFERROR(P21+Q21,"Expired") -> 1.4626269 | U21: =T21-O21 -> 0.23519713 | W21: =EOMONTH(L21,1) -> 46873 | X21: =IF(BBG!$D$5=BBG!$J$5,BBG!L21-BBG!L22,BBG!L20-BBG!L21) -> 0.53 | Y21: =IFERROR(VLOOKUP($C22,Freight!$A$3:$F$22,MATCH(EFPs!$M$30,Freight!$A$3:$F$3,0),FALSE)+$B$7,VLOOKUP($B22,Freight!$A$3:$F$22,MATCH(EFPs!$M$30,Freight!$A$3:$F$3,0),FALSE)+$B$7) -> 4.4630509 | AA21: =J21+X21+Y21-Z21 -> 1.5530509 | AB21: =T22 -> 1.2853388 | AC21: =AB21-AA21 -> -0.26771212
B22: =VLOOKUP(E22,$E$71:$I$107,5,FALSE) -> Q2-28 | C22: =E22 -> 46873 | D22: 1H27 | E22: =EOMONTH(E21,1) -> 46873 | F22: =INDEX(Sheet1!$B$38:$N$49,MATCH("MEH",Sheet1!$B$38:$B$49,0),MATCH(EFPs!D22,Sheet1!$B$38:$N$38,0)) -> 1.592 | I22: =I21 -> 0 | J22: =_xlfn.XLOOKUP(EOMONTH(E22,0),BBG!$X$5:$X$28,BBG!$AB$5:$AB$28) -> -3.41 | L22: =EOMONTH(E22,0) -> 46873 | M22: =IFERROR(VLOOKUP($C22,Freight!$A$3:$F$22,MATCH(EFPs!$M$30,Freight!$A$3:$F$3,0),FALSE)+$B$7,VLOOKUP($B22,Freight!$A$3:$F$22,MATCH(EFPs!$M$30,Freight!$A$3:$F$3,0),FALSE)+$B$7) -> 4.4630509 | O22: =J22+M22-N22 -> 1.0530509 | P22: =$B$5 -> 0 | Q22: =IFERROR(VLOOKUP($C22,Freight!$A$3:$F$22,MATCH(EFPs!$T$30,Freight!$A$3:$F$3,0),FALSE),VLOOKUP($B22,Freight!$A$3:$F$22,MATCH(EFPs!$T$30,Freight!$A$3:$F$3,0),FALSE)) -> 1.2853388 | S22: =N22 -> 0 | T22: =IFERROR(P22+Q22,"Expired") -> 1.2853388 | U22: =T22-O22 -> 0.23228788 | W22: =EOMONTH(L22,1) -> 46904 | X22: =IF(BBG!$D$5=BBG!$J$5,BBG!L22-BBG!L23,BBG!L21-BBG!L22) -> 0.47 | Y22: =IFERROR(VLOOKUP($C23,Freight!$A$3:$F$22,MATCH(EFPs!$M$30,Freight!$A$3:$F$3,0),FALSE)+$B$7,VLOOKUP($B23,Freight!$A$3:$F$22,MATCH(EFPs!$M$30,Freight!$A$3:$F$3,0),FALSE)+$B$7) -> 4.4630509 | AA22: =J22+X22+Y22-Z22 -> 1.5230509 | AB22: =T23 -> 1.2853388 | AC22: =AB22-AA22 -> -0.23771212
B23: =VLOOKUP(E23,$E$71:$I$107,5,FALSE) -> Q2-28 | C23: =E23 -> 46904 | D23: 1H27 | E23: =EOMONTH(E22,1) -> 46904 | F23: =INDEX(Sheet1!$B$38:$N$49,MATCH("MEH",Sheet1!$B$38:$B$49,0),MATCH(EFPs!D23,Sheet1!$B$38:$N$38,0)) -> 1.592 | I23: =I22 -> 0 | J23: =_xlfn.XLOOKUP(EOMONTH(E23,0),BBG!$X$5:$X$28,BBG!$AB$5:$AB$28) -> -3.42 | L23: =EOMONTH(E23,0) -> 46904 | M23: =IFERROR(VLOOKUP($C23,Freight!$A$3:$F$22,MATCH(EFPs!$M$30,Freight!$A$3:$F$3,0),FALSE)+$B$7,VLOOKUP($B23,Freight!$A$3:$F$22,MATCH(EFPs!$M$30,Freight!$A$3:$F$3,0),FALSE)+$B$7) -> 4.4630509 | O23: =J23+M23-N23 -> 1.0430509 | P23: =$B$5 -> 0 | Q23: =IFERROR(VLOOKUP($C23,Freight!$A$3:$F$22,MATCH(EFPs!$T$30,Freight!$A$3:$F$3,0),FALSE),VLOOKUP($B23,Freight!$A$3:$F$22,MATCH(EFPs!$T$30,Freight!$A$3:$F$3,0),FALSE)) -> 1.2853388 | S23: =N23 -> 0 | T23: =IFERROR(P23+Q23,"Expired") -> 1.2853388 | U23: =T23-O23 -> 0.24228788 | W23: =EOMONTH(L23,1) -> 46934 | X23: =IF(BBG!$D$5=BBG!$J$5,BBG!L23-BBG!L24,BBG!L22-BBG!L23) -> 0.44 | Y23: =IFERROR(VLOOKUP($C24,Freight!$A$3:$F$22,MATCH(EFPs!$M$30,Freight!$A$3:$F$3,0),FALSE)+$B$7,VLOOKUP($B24,Freight!$A$3:$F$22,MATCH(EFPs!$M$30,Freight!$A$3:$F$3,0),FALSE)+$B$7) -> 4.4630509 | AA23: =J23+X23+Y23-Z23 -> 1.4830509 | AB23: =T24 -> 1.2853388 | AC23: =AB23-AA23 -> -0.19771212
B24: =VLOOKUP(E24,$E$71:$I$107,5,FALSE) -> Q2-28 | C24: =E24 -> 46934 | D24: 1H27 | E24: =EOMONTH(E23,1) -> 46934 | F24: =INDEX(Sheet1!$B$38:$N$49,MATCH("MEH",Sheet1!$B$38:$B$49,0),MATCH(EFPs!D24,Sheet1!$B$38:$N$38,0)) -> 1.592 | I24: =I23 -> 0 | J24: =_xlfn.XLOOKUP(EOMONTH(E24,0),BBG!$X$5:$X$28,BBG!$AB$5:$AB$28) -> -3.4 | L24: =EOMONTH(E24,0) -> 46934 | M24: =IFERROR(VLOOKUP($C24,Freight!$A$3:$F$22,MATCH(EFPs!$M$30,Freight!$A$3:$F$3,0),FALSE)+$B$7,VLOOKUP($B24,Freight!$A$3:$F$22,MATCH(EFPs!$M$30,Freight!$A$3:$F$3,0),FALSE)+$B$7) -> 4.4630509 | O24: =J24+M24-N24 -> 1.0630509 | P24: =$B$5 -> 0 | Q24: =IFERROR(VLOOKUP($C24,Freight!$A$3:$F$22,MATCH(EFPs!$T$30,Freight!$A$3:$F$3,0),FALSE),VLOOKUP($B24,Freight!$A$3:$F$22,MATCH(EFPs!$T$30,Freight!$A$3:$F$3,0),FALSE)) -> 1.2853388 | S24: =N24 -> 0 | T24: =IFERROR(P24+Q24,"Expired") -> 1.2853388 | U24: =T24-O24 -> 0.22228788 | W24: =EOMONTH(L24,1) -> 46965 | X24: =IF(BBG!$D$5=BBG!$J$5,BBG!L24-BBG!L25,BBG!L23-BBG!L24) -> 0.44 | Y24: =IFERROR(VLOOKUP($C25,Freight!$A$3:$F$22,MATCH(EFPs!$M$30,Freight!$A$3:$F$3,0),FALSE)+$B$7,VLOOKUP($B25,Freight!$A$3:$F$22,MATCH(EFPs!$M$30,Freight!$A$3:$F$3,0),FALSE)+$B$7) -> #N/A | AA24: =J24+X24+Y24-Z24 -> #N/A | AB24: =T25 -> Expired | AC24: =AB24-AA24 -> #VALUE!
B25: Cal-26 | C25: =E25 -> 46965 | D25: 1H27 | E25: =EOMONTH(E24,1) -> 46965 | F25: =INDEX(Sheet1!$B$38:$N$49,MATCH("MEH",Sheet1!$B$38:$B$49,0),MATCH(EFPs!D25,Sheet1!$B$38:$N$38,0)) -> 1.592 | I25: =I24 -> 0 | J25: =_xlfn.XLOOKUP(EOMONTH(E25,0),BBG!$X$5:$X$28,BBG!$AB$5:$AB$28) -> -3.38 | L25: =EOMONTH(E25,0) -> 46965 | M25: =IFERROR(VLOOKUP($C25,Freight!$A$3:$F$22,MATCH(EFPs!$M$30,Freight!$A$3:$F$3,0),FALSE)+$B$7,VLOOKUP($B25,Freight!$A$3:$F$22,MATCH(EFPs!$M$30,Freight!$A$3:$F$3,0),FALSE)+$B$7) -> #N/A | O25: =J25+M25-N25 -> #N/A | P25: =$B$5 -> 0 | Q25: =IFERROR(VLOOKUP($C25,Freight!$A$3:$F$22,MATCH(EFPs!$T$30,Freight!$A$3:$F$3,0),FALSE),VLOOKUP($B25,Freight!$A$3:$F$22,MATCH(EFPs!$T$30,Freight!$A$3:$F$3,0),FALSE)) -> #N/A | S25: =N25 -> 0 | T25: =IFERROR(P25+Q25,"Expired") -> Expired | U25: =T25-O25 -> #VALUE! | W25: =EOMONTH(L25,1) -> 46996 | X25: =IF(BBG!$D$5=BBG!$J$5,BBG!L25-BBG!L26,BBG!L24-BBG!L25) -> 0.45 | Y25: =IFERROR(VLOOKUP($C26,Freight!$A$3:$F$22,MATCH(EFPs!$M$30,Freight!$A$3:$F$3,0),FALSE)+$B$7,VLOOKUP($B26,Freight!$A$3:$F$22,MATCH(EFPs!$M$30,Freight!$A$3:$F$3,0),FALSE)+$B$7) -> #N/A | AA25: =J25+X25+Y25-Z25 -> #N/A | AB25: =T26 -> Expired | AC25: =AB25-AA25 -> #VALUE!
