Workbook
Name Index: Control!$Q$3:$U$62
Name Lightering: Control!$AB$3:$AF$69
Name Overages: Control!$E$17:$O$21
Name Overages_Column: Control!$E$17:$E$21
Name Overages_Row: Control!$E$17:$O$17
Name Port_Info: Control!$Q$3:$T$62
Name Port_List: Control!$B$3:$B$1048576
Name TVM_PortList: Control!$Q$3:$Q$62
Name Vessel_Minimum_MT: Control!$E$11:$O$15
Name Zones: Control!$B$3:$C$63

Sheet Control
W1: 2 | X1: 1
B2: Port/Zone Locator | E2: CANAL OPTIONS | H2: Overages | Q2: Port Info | W2: =W3-W7 -> -10 | X2: =X3-X7 -> 0 | AB2: Lightering/Reverse Lightering | AK2: Lightering/Reverse Lightering | AW2: Load | AY2: STS+Load | AZ2: Sail | BA2: Transit | BB2: Arrive | BC2: NOR+xx | BD2: BL+30 Pay Out | BE2: Domestic
B3: Saint John | C3: ECC | E3: NEW | H3: 0 | Q3: Port | R3: Outturn Losses | S3: EU TAX | T3: Payment | U3: Type | V3: Location | W3: =WTI!B9+30 -> 46366 | X3: =W3 -> 46366 | AB3: Port | AC3: Panamax | AD3: Aframax | AE3: Suezmax | AF3: VLCC | AG3: VLCC-MODA | AH3: VLCC-STG | AI3: Suezmax-MODA | AK3: Port | AL3: Panamax | AM3: Aframax | AN3: Suezmax | AO3: VLCC | AW3: =WTI!A9 -> 46334 | AX3: 700 | AY3: =AW3+1+3 -> 46338 | AZ3: =$AY$5 -> 46341 | BA3: 54 | BB3: =AZ3+BA3 -> 46395 | BC3: =BB3+T59 -> 46405 | BD3: =AW3+1+30 -> 46365 | BE3: =EOMONTH($AW$3,0)+20 -> 46376 | BG3: =BC3-BD3 -> 40 | BH3: =BC3-BE3 -> 29
B4: Augusta | C4: Med | E4: OLD | H4: 0.5 | Q4: Saint John | R4: 0 | S4: 0 | T4: 30 | U4: BL | V4: US | AB4: Liza FPSO | AC4: 0 | AD4: 0 | AE4: 0 | AF4: 0 | AG4: 0 | AH4: 0 | AI4: 0 | AK4: Augusta | AM4: 60 | AN4: 72.5 | AO4: 100 | AW4: =AW3+1.5 -> 46335.5 | AX4: 700 | AY4: =AW4+1+3 -> 46339.5 | AZ4: =$AY$5 -> 46341 | BA4: 54 | BB4: =AZ4+BA4 -> 46395 | BC4: =BB4+T60 -> 46405 | BD4: =AW4+1+30 -> 46366.5 | BE4: =EOMONTH($AW$3,0)+20 -> 46376 | BG4: =BC4-BD4 -> 38.5 | BH4: =BC4-BE4 -> 29
B5: Sao Sebastiao | C5: BAYOVAR+T | E5: Vessel List | Q5: Corpus Christi - MODA | R5: 1 | S5: 1 | T5: =T7 -> 30 | U5: BL | V5: US | W5: =W7 -> 46376 | X5: =X7 -> 46366 | AB5: Augusta | AC5: 0 | AD5: 0 | AE5: 0 | AF5: 0 | AG5: 0 | AH5: 0 | AI5: 0 | AK5: Pembroke | AW5: =AW4+1.5 -> 46337 | AX5: 700 | AY5: =AW5+1+3 -> 46341 | AZ5: =$AY$5 -> 46341 | BA5: 54 | BB5: =AZ5+BA5 -> 46395 | BC5: =BB5+T61 -> 46405 | BD5: =AW5+1+30 -> 46368 | BE5: =EOMONTH($AW$3,0)+20 -> 46376 | BG5: =BC5-BD5 -> 37 | BH5: =BC5-BE5 -> 29
B6: Corpus Christi - MODA | C6: USGC | E6: Panamax | Q6: Corpus Christi - STG | R6: 1 | S6: 1 | T6: 30 | U6: BL | V6: US | W6: =W5 -> 46376 | X6: =X5 -> 46366 | AB6: Sao Sebastiao | AC6: 0 | AD6: 0 | AE6: 1 | AF6: 1 | AG6: 1 | AH6: 1 | AI6: 1 | AK6: Rotterdam | AM6: 60 | AN6: =$AN$4 -> 72.5 | AO6: =$AO$4 -> 100 | BC6: =AVERAGE(BC3:BC5) -> 46405 | BD6: =AVERAGE(BD3:BD5) -> 46366.5 | BE6: =AVERAGE(BE3:BE5) -> 46376 | BF6: =BD6-BE6 -> -9.5 | BG6: =AVERAGE(BG3:BG5) -> 38.5 | BH6: =AVERAGE(BH3:BH5) -> 29
B7: Taiwan | C7: TAIWAN | E7: Aframax | Q7: Corpus Christi | R7: 0 | S7: 0 | T7: 30 | U7: BL | V7: US | W7: =W58 -> 46376 | X7: =WTI!B9+30 -> 46366 | AB7: Beaumont | AC7: 0 | AD7: 0 | AE7: 1 | AF7: 1 | AG7: 1 | AH7: 1 | AI7: 1 | AK7: Tranmere | AM7: 60 | AN7: =$AN$4 -> 72.5 | AO7: =$AO$4 -> 100
B8: Corpus Christi - STG | C8: USGC | E8: Suezmax | Q8: El Segundo | R8: 1 | S8: 1 | T8: 13 | U8: NOR | V8: US | AB8: Corpus Christi - STG | AC8: 0 | AD8: 0 | AE8: 0 | AF8: 0 | AG8: 0 | AH8: 0 | AI8: 0 | AK8: Trieste | AM8: 60 | AN8: =$AN$4 -> 72.5 | AO8: =$AO$4 -> 100 | AW8: Load | AY8: STS+Load | AZ8: Sail | BA8: Transit | BB8: Arrive | BC8: NOR+xx | BD8: BL+30 Pay Out | BE8: Domestic
B9: Chiba | C9: JAPAN | E9: VLCC | Q9: Canaport SPM | R9: 0 | S9: 0 | T9: 30 | U9: BL | V9: US | AB9: Chiba | AC9: 0 | AD9: 0 | AE9: 0 | AF9: 0 | AG9: 0 | AH9: 0 | AI9: 0 | AK9: Antwerp | AM9: 60 | AN9: =$AN$4 -> 72.5 | AO9: =$AO$4 -> 100 | AW9: =WTI!A15 -> 46334 | AX9: 1400 | AY9: =AW9+1+3 -> 46338 | AZ9: =$AY$5 -> 46341 | BA9: 54 | BB9: =AZ9+BA9 -> 46395 | BC9: =BB9+T65 -> 46395 | BD9: =AW9+1+30 -> 46365 | BE9: =EOMONTH($AW$3,0)+20 -> 46376 | BG9: =BC9-BD9 -> 30 | BH9: =BC9-BE9 -> 19
B10: Chiriqui Grande | C10: CARIBS | Q10: Houston | R10: 1 | S10: 0 | T10: 30 | U10: BL | V10: US | AB10: Chiriqui Grande | AC10: 0 | AD10: 0 | AE10: 0 | AF10: 0 | AG10: 0 | AH10: 0 | AI10: 0 | AK10: Finnart | AM10: 60 | AN10: =$AN$4 -> 72.5 | AO10: =$AO$4 -> 100 | AW10: =AW9+1.5 -> 46335.5 | AX10: 700 | AY10: =AW10+1+3 -> 46339.5 | AZ10: =$AY$5 -> 46341 | BA10: 54 | BB10: =AZ10+BA10 -> 46395 | BC10: =BB10+T66 -> 46395 | BD10: =AW10+1+30 -> 46366.5 | BE10: =EOMONTH($AW$3,0)+20 -> 46376 | BG10: =BC10-BD10 -> 28.5 | BH10: =BC10-BE10 -> 19
B11: Conchan/Talara | C11: CONCHAN+T | E11: Vessel Minimum MT | F11: Covenas | G11: Chiriqui Grande | H11: Puerto Armuelles | I11: Corpus Christi | J11: Corpus Christi - MODA | K11: Rotterdam-STS | L11: La Paloma (Alpha Ligh. Zone) | M11: Liza FPSO | N11: Loop | O11: Nederland | Q11: LA+SF | R11: 1 | S11: 1 | T11: 13 | U11: NOR | V11: US | AB11: Conchan/Talara | AC11: 0 | AD11: 0 | AE11: 0 | AF11: 0 | AG11: 0 | AH11: 0 | AI11: 0 | AK11: Whitegate
B12: Corpus Christi | C12: USGC | E12: Panamax | F12: 50000 | G12: =$F12 -> 50000 | H12: =$I12 -> 50000 | I12: 50000 | J12: 50000 | K12: =F12 -> 50000 | L12: =I12 -> 50000 | M12: 50000 | N12: =J12 -> 50000 | O12: 50000 | Q12: Loop | R12: 1 | S12: 0 | T12: 30 | U12: BL | V12: US | AB12: Corpus Christi | AC12: 0 | AD12: 0 | AE12: 1 | AF12: 1 | AG12: 1 | AH12: 1 | AI12: 1 | AK12: Gdansk | AM12: 60 | AN12: =$AN$4 -> 72.5 | AO12: =$AO$4 -> 100 | BC12: =AVERAGE(BC9:BC11) -> 46395 | BD12: =AVERAGE(BD9:BD11) -> 46365.75 | BE12: =AVERAGE(BE9:BE11) -> 46376 | BF12: =BD12-BE12 -> -10.25 | BG12: =AVERAGE(BG9:BG11) -> 29.25 | BH12: =AVERAGE(BH9:BH11) -> 19
B13: Covenas | C13: CARIBS | E13: Aframax | F13: 70000 | G13: =$F13 -> 70000 | H13: =$I13 -> 70000 | I13: 70000 | J13: 70000 | K13: 80000 | L13: =I13 -> 70000 | M13: 70000 | N13: =J13 -> 70000 | O13: 70000 | Q13: Los Angeles | R13: 1 | S13: 1 | T13: 13 | U13: NOR | V13: US | AB13: Covenas | AC13: 0 | AD13: 0 | AE13: 0 | AF13: 0 | AG13: 0 | AH13: 0 | AI13: 0 | AK13: Lagos | AM13: 60 | AN13: =$AN$4 -> 72.5 | AO13: =$AO$4 -> 100
B14: El Segundo | C14: USWC | E14: Suezmax | F14: 150000 | G14: 150000 | H14: =$I14 -> 145000 | I14: 145000 | J14: 145000 | K14: 145000 | L14: =I14 -> 145000 | M14: 145000 | N14: =J14 -> 145000 | O14: 130000 | Q14: Paulsboro | R14: 0 | S14: 0 | T14: 30 | U14: BL | V14: US | AB14: El Segundo | AC14: 0 | AD14: 0 | AE14: 0 | AF14: 0 | AG14: 0 | AH14: 0 | AI14: 0 | AK14: Sines | AM14: 60 | AN14: =$AN$4 -> 72.5 | AO14: =$AO$4 -> 100
B15: Quebec | C15: ECC | E15: VLCC | F15: 270000 | G15: =$F15 -> 270000 | H15: =$I15 -> 270000 | I15: 270000 | J15: 270000 | K15: =F15 -> 270000 | L15: =I15 -> 270000 | M15: 270000 | N15: =J15 -> 270000 | O15: 270000 | Q15: Quebec | R15: 0 | S15: 0 | T15: 30 | U15: BL | V15: US | AB15: ES+Richmond | AC15: 0 | AD15: 0 | AE15: 0 | AF15: 0 | AG15: 0 | AH15: 0 | AI15: 0 | AK15: Milazzo | AM15: 60 | AN15: =$AN$4 -> 72.5 | AO15: =$AO$4 -> 100
B16: Rotterdam-STS | C16: Nsea | Q16: Pascagoula | R16: 1 | S16: 0 | T16: 13 | U16: NOR | V16: US | AB16: Esmeraldas | AC16: 0 | AD16: 0 | AE16: 0 | AF16: 0 | AG16: 0 | AH16: 0 | AI16: 0 | AK16: Butinge | AM16: 60 | AN16: =$AN$4 -> 72.5 | AO16: =$AO$4 -> 100
B17: Houston | C17: USGC | E17: Overages | F17: Covenas | G17: Chiriqui Grande | H17: Puerto Armuelles | I17: Corpus Christi | J17: Corpus Christi - MODA | K17: =K11 -> Rotterdam-STS | L17: La Paloma (Alpha Ligh. Zone) | M17: =M11 -> Liza FPSO | N17: Loop | O17: =O11 -> Nederland | Q17: Omisalj | R17: 0 | S17: 0 | T17: 30 | U17: BL | V17: South America | W17: =$W$7 -> 46376 | X17: =$X$7 -> 46366 | Y17: =X17-W17 -> -10 | AB17: Corpus Christi | AC17: 0 | AD17: 0 | AE17: 1 | AF17: 1 | AG17: 1 | AH17: 1 | AI17: 1 | AK17: Porvoo | AM17: 60 | AN17: =$AN$4 -> 72.5 | AO17: =$AO$4 -> 100 | AS17: Load | AT17: =WTI!A9 -> 46334 | AX17: 9 | AY17: 700 | BA17: 0 | BB17: 700
B18: Jamnagar | C18: INDIA | E18: Panamax | F18: 0.5 | G18: =$F18 -> 0.5 | H18: =$I18 -> 0.5 | I18: 0.5 | J18: 0.5 | K18: 0.5 | L18: =I18 -> 0.5 | M18: 0.5 | N18: =J18 -> 0.5 | O18: 50000 | Q18: Sao Sebastiao | R18: 0 | S18: 0 | T18: 13 | U18: NOR | V18: South America | AB18: Jamnagar | AC18: 0 | AD18: 0 | AE18: 0 | AF18: 0 | AG18: 0 | AH18: 0 | AI18: 0 | AK18: La Coruña | AM18: 60 | AN18: =$AN$4 -> 72.5 | AO18: =$AO$4 -> 100 | AS18: Transit | AT18: =WTI!BC43+AY20+1 -> 59 | AX18: 6 | AY18: 700 | BA18: 3 | BB18: 1400
B19: Omisalj | C19: Med | E19: Aframax | F19: 0 | G19: =$F19 -> 0 | H19: =$K19 -> 0.5 | I19: 0 | J19: 0 | K19: 0.5 | L19: =I19 -> 0 | M19: 0 | N19: =J19 -> 0 | O19: 70000 | Q19: Chiriqui Grande | R19: 1 | S19: 0 | T19: 13 | U19: NOR | V19: South America | AB19: Kingston | AC19: 0 | AD19: 0 | AE19: 0 | AF19: 0 | AG19: 0 | AH19: 0 | AI19: 0 | AK19: Algericas | AM19: 60 | AN19: =$AN$4 -> 72.5 | AO19: =$AO$4 -> 100 | AS19: NOR | AT19: =AT17+AT18 -> 46393 | AX19: 3 | AY19: 700 | BB19: {=SUMPRODUCT(BA17:BA18,BB17:BB18/SUM(BB17:BB18))} -> 2
B20: La Paloma (Alpha Ligh. Zone) | C20: LATAM EAST | E20: Suezmax | F20: 0.5 | G20: =$F20 -> 0.5 | H20: =$I20 -> 0.5 | I20: 0.5 | J20: 0.5 | K20: 0.5 | L20: =I20 -> 0.5 | M20: 0.5 | N20: =J20 -> 0.5 | O20: 130000 | Q20: Conchan/Talara | R20: 0 | S20: 0 | T20: 17 | U20: NOR | V20: South America | AB20: La Paloma (Alpha Ligh. Zone) | AC20: 0 | AD20: 0 | AE20: 0 | AF20: 0 | AG20: 0 | AH20: 0 | AI20: 0 | AK20: Wilhelmshaven | AM20: 60 | AN20: =$AN$4 -> 72.5 | AO20: =$AO$4 -> 100 | AS20: xxx | AT20: =+AT19+T59 -> 46403 | AU20: =AT17+1+30 -> 46365 | AV20: =AT20-AU20 -> 38 | AY20: {=SUMPRODUCT(AX17:AX19,AY17:AY19/SUM(AY17:AY19))} -> 6
B21: La Pampilla | C21: PAMPILLA | E21: VLCC | F21: 0.5 | G21: =$F21 -> 0.5 | H21: =$I21 -> 0.5 | I21: 0.5 | J21: 0.5 | K21: 0.5 | L21: =I21 -> 0.5 | M21: 0.5 | N21: =J21 -> 0.5 | O21: 270000 | Q21: Covenas | R21: 1 | S21: 0 | T21: 15 | U21: NOR | V21: South America | AB21: La Pampilla | AC21: 0 | AD21: 0 | AE21: 0 | AF21: 0 | AG21: 0 | AH21: 0 | AI21: 0 | AK21: Kalundborg | AM21: 60 | AN21: =$AN$4 -> 72.5 | AO21: =$AO$4 -> 100 | AU21: =$W$17 -> 46376 | AV21: =AT20-AU21 -> 27
B22: LA+SF | C22: USWC | Q22: Rotterdam-STS | R22: 0 | S22: 0 | T22: 15 | U22: BL | V22: South America | AB22: LA+SF | AC22: 0 | AD22: 0 | AE22: 0 | AF22: 0 | AG22: 0 | AH22: 0 | AI22: 0 | AK22: Aliaga | AM22: 60 | AN22: =$AN$4 -> 72.5 | AO22: =$AO$4 -> 100 | AZ22: Load | BA22: STS | BB22: Sail | BC22: Payment
B23: Los Angeles | C23: USWC | Q23: Omisalj | R23: 1 | S23: 0 | T23: 30 | U23: BL | V23: South America | AB23: Los Angeles | AC23: 0 | AD23: 0 | AE23: 0 | AF23: 0 | AG23: 0 | AH23: 0 | AI23: 0 | AK23: Botas Ceyhan | AM23: 60 | AN23: =$AN$4 -> 72.5 | AO23: =$AO$4 -> 100 | AS23: Chiba | AT23: =AT24-2 -> 36.5 | AY23: 700 | AZ23: 45734 | BA23: 3 | BB23: =BA23+AZ23 -> 45737
B24: Ningbo | C24: KOREA | E24: Max Load | F24: Beaumont | G24: Corpu Christi | H24: Houston | I24: LOOP | J24: Puerto Armuelles | Q24: La Paloma (Alpha Ligh. Zone) | R24: 1 | S24: 0 | T24: 30 | U24: NOR | V24: South America | AB24: Ningbo | AC24: 0 | AD24: 0 | AE24: 0 | AF24: 0 | AG24: 0 | AH24: 0 | AI24: 0 | AK24: Agioi Theodori | AM24: 60 | AN24: =$AN$4 -> 72.5 | AO24: =$AO$4 -> 100 | AS24: Daesan | AT24: =$BG$6 -> 38.5 | AY24: 700 | AZ24: =+AZ23+2 -> 45736 | BA24: 3 | BB24: =BA24+AZ24 -> 45739
B25: Paulsboro | C25: USGC | E25: Panamax | F25: 490000 | G25: 490000 | H25: 490000 | I25: 490000 | Q25: La Pampilla | R25: 0 | S25: 0 | T25: 13 | U25: NOR | V25: South America | AB25: Paulsboro | AC25: 0 | AD25: 0 | AE25: 0 | AF25: 0 | AG25: 0 | AH25: 0 | AI25: 0 | AK25: Thessalonski | AM25: 60 | AN25: =$AN$4 -> 72.5 | AO25: =$AO$4 -> 100 | AS25: Jamnagar | AT25: =AT27-3 -> 25.5 | AY25: 700 | AZ25: =+AZ24+2 -> 45738 | BA25: 3 | BB25: =BA25+AZ25 -> 45741
B26: Puerto Armuelles | C26: Panama WC | E26: Aframax | F26: 500000 | G26: 750000 | H26: 700000 | I26: 750000 | Q26: Liza FPSO | R26: 1 | S26: 0 | T26: 30 | U26: BL | V26: South America | AB26: Puerto Armuelles | AC26: 0 | AD26: 0 | AE26: 0 | AF26: 0 | AG26: 0 | AH26: 0 | AI26: 0 | AK26: Odessa | AM26: 60 | AN26: =$AN$4 -> 72.5 | AO26: =$AO$4 -> 100 | AS26: Ningbo | AT26: =AT23-1 -> 35.5
B27: Quintero (MB) | C27: LATAM WEST | E27: Suezmax | F27: 700000 | G27: 850000 | H27: 0 | I27: 1000000 | Q27: Mamonal | R27: 1 | S27: 0 | T27: 13 | U27: NOR | V27: South America | AB27: Quintero (MB) | AC27: 0 | AD27: 0 | AE27: 0 | AF27: 0 | AG27: 0 | AH27: 0 | AI27: 0 | AK27: Savona | AM27: 60 | AN27: =$AN$4 -> 72.5 | AO27: =$AO$4 -> 100 | AS27: Singapore | AT27: =AT24-10 -> 28.5
B28: Quintero (Port) | C28: LATAM WEST | E28: VLCC | F28: 0 | G28: 1250000 | H28: 0 | I28: 2000000 | Q28: Puerto Armuelles | R28: 1 | S28: 0 | T28: 15 | U28: BL | V28: South America | AB28: Quintero (Port) | AC28: 0 | AD28: 0 | AE28: 0 | AF28: 0 | AG28: 0 | AH28: 0 | AI28: 0 | AK28: Midla | AM28: 60 | AN28: =$AN$4 -> 72.5 | AO28: =$AO$4 -> 100 | AS28: Taiwan | AT28: =AT24-3 -> 35.5
B29: Pembroke | C29: Nsea | E29: STS Size | F29: =F26 -> 500000 | G29: =G26 -> 750000 | H29: =H26 -> 700000 | I29: =I26 -> 750000 | Q29: Quintero (MB) | R29: 0 | S29: 0 | T29: 30 | U29: BL | V29: South America | AB29: Richmond | AC29: 0 | AD29: 0 | AE29: 0 | AF29: 0 | AG29: 0 | AH29: 0 | AI29: 0 | AK29: Rotterdam-CASH | AM29: 60 | AN29: =$AN$4 -> 72.5 | AO29: =$AO$4 -> 100
B30: Rotterdam | C30: Nsea | Q30: Quintero (Port) | R30: 0 | S30: 0 | T30: 30 | U30: BL | V30: South America | AB30: Rotterdam | AC30: 0 | AD30: 0 | AE30: 0 | AF30: 0 | AG30: 0 | AH30: 0 | AI30: 0
B31: Canaport SPM | C31: ECC | E31: Load | F31: 2000000 | G31: =F31-G28 -> 750000 | H31: =G31/J28 -> #DIV/0! | Q31: San Vicente | R31: 1 | S31: 0 | T31: 13 | U31: NOR | V31: Europe | AB31: San Francisco | AC31: 0 | AD31: 0 | AE31: 0 | AF31: 0 | AG31: 0 | AH31: 0 | AI31: 0
B32: San Vicente | C32: LATAM WEST | E32: STS Size | F32: 700000 | H32: =COUNT(H31) -> 0 | P32: 1 | Q32: Augusta | R32: 0 | S32: 0 | T32: 30 | U32: BL | V32: Europe | W32: =$W$7 -> 46376 | X32: =$X$7 -> 46366 | Y32: =X32-W32 -> -10 | AB32: San Vicente | AC32: 0 | AD32: 0 | AE32: 0 | AF32: 0 | AG32: 0 | AH32: 0 | AI32: 0
B33: Trieste | C33: Med | Q33: Pembroke | R33: 0 | S33: 0 | T33: 30 | U33: BL | V33: Europe | W33: =$W$7 -> 46376 | X33: =$X$7 -> 46366 | Y33: =X33-W33 -> -10 | AB33: Trieste | AC33: 0 | AD33: 0 | AE33: 0 | AF33: 0 | AG33: 0 | AH33: 0 | AI33: 0
B34: Tranmere | C34: Nsea | P34: 1 | Q34: Rotterdam | R34: 0 | S34: 0 | T34: 30 | U34: BL | V34: Europe | W34: =$W$7 -> 46376 | X34: =$X$7 -> 46366 | Y34: =X34-W34 -> -10 | AB34: Tranmere | AC34: 0 | AD34: 0 | AE34: 0 | AF34: 0 | AG34: 0 | AH34: 0 | AI34: 0
B35: Mamonal | C35: CARIBS | P35: 1 | Q35: Tranmere | R35: 0 | S35: 0 | T35: 30 | U35: BL | V35: Asia | W35: =$W$7 -> 46376 | X35: =$X$7 -> 46366 | Y35: =X35-W35 -> -10 | AB35: Mamonal | AC35: 0 | AD35: 0 | AE35: 0 | AF35: 0 | AG35: 0 | AH35: 0 | AI35: 0 | AS35: TVM Calcs | AT35: 8 | AU35: 2 | AW35: 10
B36: Liza FPSO | C36: CARIBS | P36: 1 | Q36: Trieste | R36: 0 | S36: 0 | T36: 30 | U36: =U32 -> BL | V36: Asia | W36: =$W$7 -> 46376 | X36: =$X$7 -> 46366 | Y36: =X36-W36 -> -10 | AB36: =Q59 -> Daesan | AC36: 0 | AD36: 0 | AE36: 0 | AF36: 0 | AG36: 0 | AH36: 0 | AI36: 0 | AT36: ATA Sourced | AU36: BL+30 | AX36: ATA TVM | AY36: Ext. TVM
B37: LOOP | C37: USGC | P37: 1 | Q37: Antwerp | R37: 0 | S37: 0 | T37: 30 | U37: BL | V37: Asia | W37: =$W$7 -> 46376 | X37: =$X$7 -> 46366 | Y37: =X37-W37 -> -10 | AB37: Loop | AC37: 0 | AD37: 0 | AE37: 0 | AF37: 0 | AG37: 0 | AH37: 0 | AI37: 0 | AS37: Chiba | AT37: =AT38-2 -> 25 | AU37: =Control!AT23 -> 36.5 | AV37: =SUMPRODUCT(AT37:AU37,$AT$35:$AU$35/SUM($AT$35:$AU$35)) -> 27.3 | AX37: =$AX$38 -> -9.5 | AY37: =AU37 -> 36.5 | BE37: BL Date | BF37: Transit | BG37: NOR | BH37: 10
B38: Daesan | C38: KOREA | P38: 1 | Q38: Finnart | R38: 0 | S38: 0 | T38: 30 | U38: BL | V38: Asia | W38: =$W$7 -> 46376 | X38: =$X$7 -> 46366 | Y38: =X38-W38 -> -10 | AB38: Daesan | AC38: 0 | AD38: 0 | AE38: 0 | AF38: 0 | AG38: 0 | AH38: 0 | AI38: 0 | AS38: Daesan | AT38: =AV21 -> 27 | AU38: =Control!AT24 -> 38.5 | AV38: =SUMPRODUCT(AT38:AU38,$AT$35:$AU$35/SUM($AT$35:$AU$35)) -> 29.3 | AX38: =BF6 -> -9.5 | AY38: =AU38 -> 38.5 | BD38: 45734 | BE38: =BD38+3 -> 45737 | BF38: =54+9 -> 63 | BG38: =BD38+BF38 -> 45797 | BH38: =BG38+10 -> 45807
B39: Singapore | C39: Singapore | Q39: Whitegate | R39: 0 | S39: 0 | T39: 30 | U39: BL | V39: Asia | W39: =$W$7 -> 46376 | X39: =$X$7 -> 46366 | Y39: =X39-W39 -> -10 | AB39: Singapore | AC39: 0 | AD39: 0 | AE39: 0 | AF39: 0 | AG39: 0 | AH39: 0 | AI39: 0 | AS39: Jamnagar | AT39: =AT41-3 -> 14 | AU39: =Control!AT25 -> 25.5 | AV39: =SUMPRODUCT(AT39:AU39,$AT$35:$AU$35/SUM($AT$35:$AU$35)) -> 16.3 | AX39: =$AX$38 -> -9.5 | AY39: =AU39 -> 25.5
B40: Nederland | C40: USGC | P40: 1 | Q40: Gdansk | R40: 1 | S40: 0 | T40: 30 | U40: BL | W40: =$W$7 -> 46376 | X40: =$X$7 -> 46366 | Y40: =X40-W40 -> -10 | AB40: Augusta | AC40: 0 | AD40: 0 | AE40: 0 | AF40: 0 | AG40: 0 | AH40: 0 | AI40: 0 | AS40: Ningbo | AT40: =AT37-1 -> 24 | AU40: =Control!AT26 -> 35.5 | AV40: =SUMPRODUCT(AT40:AU40,$AT$35:$AU$35/SUM($AT$35:$AU$35)) -> 26.3 | AX40: =$AX$38 -> -9.5 | AY40: =AU40 -> 35.5 | BD40: BL+30 | BE40: =BD38+30 -> 45764 | BF40: =BF41 -> 45807 | BG40: =BF40-BE40 -> 43
B41: Antwerp | C41: Nsea | G41: VLCC | H41: 3 | I41: 3 | J41: =I41*H41 -> 9 | K41: =J41/3*4 -> 12 | P41: 1 | Q41: Lagos | R41: 0 | S41: 0 | T41: 30 | U41: BL | W41: =$W$7 -> 46376 | X41: =$X$7 -> 46366 | Y41: =X41-W41 -> -10 | AB41: Pembroke | AC41: 0 | AD41: 0 | AE41: 0 | AF41: 0 | AG41: 0 | AH41: 0 | AI41: 0 | AS41: Singapore | AT41: =AT38-10 -> 17 | AU41: =Control!AT27 -> 28.5 | AV41: =SUMPRODUCT(AT41:AU41,$AT$35:$AU$35/SUM($AT$35:$AU$35)) -> 19.3 | AX41: =$AX$38 -> -9.5 | AY41: =AU41 -> 28.5 | BD41: Domestic | BE41: 45767 | BF41: =BH38 -> 45807 | BG41: =BF41-BE41 -> 40
B42: Finnart | C42: Nsea | G42: Suezmax | H42: 1 | I42: 3 | J42: =I42*H42 -> 3 | K42: =J42/3*4 -> 4 | P42: 1 | Q42: Sines | R42: 0 | S42: 0 | T42: 30 | U42: BL | W42: =$W$7 -> 46376 | X42: =$X$7 -> 46366 | Y42: =X42-W42 -> -10 | AB42: Rotterdam | AC42: 0 | AD42: 0 | AE42: 0 | AF42: 0 | AG42: 0 | AH42: 0 | AI42: 0 | AS42: Taiwan | AT42: =AT38-3-5 -> 19 | AU42: =Control!AT28-5 -> 30.5 | AV42: =SUMPRODUCT(AT42:AU42,$AT$35:$AU$35/SUM($AT$35:$AU$35)) -> 21.3 | AX42: =$AX$38 -> -9.5 | AY42: =AU42 -> 30.5
B43: Whitegate | C43: Nsea | G43: Aframax | H43: 0 | I43: 3 | J43: =I43*H43 -> 0 | K43: =J43/3*4 -> 0 | P43: 1 | Q43: Milazzo | R43: 0 | S43: 0 | T43: 30 | U43: BL | W43: =$W$7 -> 46376 | X43: =$X$7 -> 46366 | Y43: =X43-W43 -> -10 | AB43: Tranmere | AC43: 0 | AD43: 0 | AE43: 0 | AF43: 0 | AG43: 0 | AH43: 0 | AI43: 0 | AS43: Augusta | AT43: =Y32 -> -10 | AU43: 0 | AV43: =SUMPRODUCT(AT43:AU43,$AT$35:$AU$35/SUM($AT$35:$AU$35)) -> -8 | AX43: =AT43 -> -10 | AY43: =AU43 -> 0
A44: 1 | B44: Gdansk | C44: Nsea | G44: VLCC-MODA | H44: 1 | I44: 3 | J44: =I44*H44 -> 3 | K44: 3 | P44: 1 | Q44: Butinge | R44: 1 | S44: 0 | T44: 30 | U44: BL | W44: =$W$7 -> 46376 | X44: =$X$7 -> 46366 | Y44: =X44-W44 -> -10 | AB44: Trieste | AC44: 0 | AD44: 0 | AE44: 0 | AF44: 0 | AG44: 0 | AH44: 0 | AI44: 0 | AS44: Pembroke | AT44: =Y33 -> -10 | AU44: 0 | AV44: =SUMPRODUCT(AT44:AU44,$AT$35:$AU$35/SUM($AT$35:$AU$35)) -> -8 | AX44: =AT44 -> -10 | AY44: =AU44 -> 0
A45: 2 | B45: Lagos | C45: Nsea | G45: VLCC-STG | H45: 1 | I45: 3 | J45: =I45*H45 -> 3 | K45: 3 | P45: 1 | Q45: Porvoo | R45: 0 | S45: 0 | T45: 30 | U45: BL | W45: =$W$7 -> 46376 | X45: =$X$7 -> 46366 | Y45: =X45-W45 -> -10 | AB45: Antwerp | AC45: 0 | AD45: 0 | AE45: 0 | AF45: 0 | AG45: 0 | AH45: 0 | AI45: 0 | AS45: Rotterdam | AT45: =Y34 -> -10 | AU45: 0 | AV45: =SUMPRODUCT(AT45:AU45,$AT$35:$AU$35/SUM($AT$35:$AU$35)) -> -8 | AX45: =AT45 -> -10 | AY45: =AU45 -> 0
A46: 3 | B46: Sines | C46: Nsea | P46: 1 | Q46: La Coruña | R46: 0 | S46: 0 | T46: 30 | U46: BL | W46: =$W$7 -> 46376 | X46: =$X$7 -> 46366 | Y46: =X46-W46 -> -10 | AB46: Finnart | AC46: 0 | AD46: 0 | AE46: 0 | AF46: 0 | AG46: 0 | AH46: 0 | AI46: 0 | AS46: Tranmere | AT46: =Y35 -> -10 | AU46: 0 | AV46: =SUMPRODUCT(AT46:AU46,$AT$35:$AU$35/SUM($AT$35:$AU$35)) -> -8 | AX46: =AT46 -> -10 | AY46: =AU46 -> 0
B47: Milazzo | C47: Nsea | P47: 1 | Q47: Algericas | R47: 0 | S47: 0 | T47: 30 | U47: BL | W47: =$W$7 -> 46376 | X47: =$X$7 -> 46366 | Y47: =X47-W47 -> -10 | AB47: Whitegate | AC47: 0 | AD47: 0 | AE47: 0 | AF47: 0 | AG47: 0 | AH47: 0 | AI47: 0 | AS47: Trieste | AT47: =Y36 -> -10 | AU47: 0 | AV47: =SUMPRODUCT(AT47:AU47,$AT$35:$AU$35/SUM($AT$35:$AU$35)) -> -8 | AX47: =AT47 -> -10 | AY47: =AU47 -> 0
A48: 4 | B48: Butinge | C48: Nsea | P48: 1 | Q48: Wilhelmshaven | R48: 0 | S48: 0 | T48: 30 | U48: BL | W48: =$W$7 -> 46376 | X48: =$X$7 -> 46366 | Y48: =X48-W48 -> -10 | AB48: Gdansk | AC48: 0 | AD48: 0 | AE48: 0 | AF48: 0 | AG48: 0 | AH48: 0 | AI48: 0 | AS48: Antwerp | AT48: =Y37 -> -10 | AU48: 0 | AV48: =SUMPRODUCT(AT48:AU48,$AT$35:$AU$35/SUM($AT$35:$AU$35)) -> -8 | AX48: =AT48 -> -10 | AY48: =AU48 -> 0
B49: Porvoo | C49: Nsea | P49: 1 | Q49: Kalundborg | R49: 0 | S49: 0 | T49: 30 | U49: BL | W49: =$W$7 -> 46376 | X49: =$X$7 -> 46366 | Y49: =X49-W49 -> -10 | AB49: Lagos | AC49: 0 | AD49: 0 | AE49: 0 | AF49: 0 | AG49: 0 | AH49: 0 | AI49: 0 | AS49: Finnart | AT49: =Y38 -> -10 | AU49: 0 | AV49: =SUMPRODUCT(AT49:AU49,$AT$35:$AU$35/SUM($AT$35:$AU$35)) -> -8 | AX49: =AT49 -> -10 | AY49: =AU49 -> 0
A50: 5 | B50: La Coruña | C50: Nsea | P50: 1 | Q50: Aliaga | R50: 0 | S50: 0 | T50: 30 | U50: BL | W50: =$W$7 -> 46376 | X50: =$X$7 -> 46366 | Y50: =X50-W50 -> -10 | AB50: Sines | AC50: 0 | AD50: 0 | AE50: 0 | AF50: 0 | AG50: 0 | AH50: 0 | AI50: 0 | AS50: Whitegate | AT50: =Y39 -> -10 | AU50: 0 | AV50: =SUMPRODUCT(AT50:AU50,$AT$35:$AU$35/SUM($AT$35:$AU$35)) -> -8 | AX50: =AT50 -> -10 | AY50: =AU50 -> 0
A51: 6 | B51: Algericas | C51: Nsea | P51: 1 | Q51: Botas Ceyhan | R51: 0 | S51: 0 | T51: 30 | U51: BL | W51: =$W$7 -> 46376 | X51: =$X$7 -> 46366 | Y51: =X51-W51 -> -10 | AB51: Milazzo | AC51: 0 | AD51: 0 | AE51: 0 | AF51: 0 | AG51: 0 | AH51: 0 | AI51: 0 | AS51: Gdansk | AT51: =Y40 -> -10 | AU51: 0 | AV51: =SUMPRODUCT(AT51:AU51,$AT$35:$AU$35/SUM($AT$35:$AU$35)) -> -8 | AX51: =AT51 -> -10 | AY51: =AU51 -> 0
B52: Caliari/Sarroch | C52: Nsea | P52: 1 | Q52: Agioi Theodori | R52: 0 | S52: 0 | T52: 30 | U52: BL | W52: =$W$7 -> 46376 | X52: =$X$7 -> 46366 | Y52: =X52-W52 -> -10 | AB52: Butinge | AC52: 0 | AD52: 0 | AE52: 0 | AF52: 0 | AG52: 0 | AH52: 0 | AI52: 0 | AS52: Lagos | AT52: =Y41 -> -10 | AU52: 0 | AV52: =SUMPRODUCT(AT52:AU52,$AT$35:$AU$35/SUM($AT$35:$AU$35)) -> -8 | AX52: =AT52 -> -10 | AY52: =AU52 -> 0
A53: 7 | B53: Kalundborg | C53: Nsea | P53: 1 | Q53: Thessalonski | R53: 0 | S53: 0 | T53: 30 | U53: BL | W53: =$W$7 -> 46376 | X53: =$X$7 -> 46366 | Y53: =X53-W53 -> -10 | AB53: Porvoo | AC53: 0 | AD53: 0 | AE53: 0 | AF53: 0 | AG53: 0 | AH53: 0 | AI53: 0 | AS53: Sines | AT53: =Y42 -> -10 | AU53: 0 | AV53: =SUMPRODUCT(AT53:AU53,$AT$35:$AU$35/SUM($AT$35:$AU$35)) -> -8 | AX53: =AT53 -> -10 | AY53: =AU53 -> 0
A54: 8 | B54: Aliaga | C54: Nsea | P54: 1 | Q54: Odessa | R54: 0 | S54: 0 | T54: 30 | U54: BL | W54: =$W$7 -> 46376 | X54: =$X$7 -> 46366 | Y54: =X54-W54 -> -10 | AB54: La Coruña | AC54: 0 | AD54: 0 | AE54: 0 | AF54: 0 | AG54: 0 | AH54: 0 | AI54: 0 | AS54: Milazzo | AT54: =Y43 -> -10 | AU54: 0 | AV54: =SUMPRODUCT(AT54:AU54,$AT$35:$AU$35/SUM($AT$35:$AU$35)) -> -8 | AX54: =AT54 -> -10 | AY54: =AU54 -> 0
A55: 9 | B55: Botas Ceyhan | C55: Nsea | P55: 1 | Q55: Savona | R55: 0 | S55: 0 | T55: 30 | U55: BL | W55: =$W$7 -> 46376 | X55: =$X$7 -> 46366 | Y55: =X55-W55 -> -10 | AB55: Algericas | AC55: 0 | AD55: 0 | AE55: 0 | AF55: 0 | AG55: 0 | AH55: 0 | AI55: 0 | AS55: Butinge | AT55: =Y44 -> -10 | AU55: 0 | AV55: =SUMPRODUCT(AT55:AU55,$AT$35:$AU$35/SUM($AT$35:$AU$35)) -> -8 | AX55: =AT55 -> -10 | AY55: =AU55 -> 0
B56: Agioi Theodori | C56: Nsea | P56: 1 | Q56: Cartagena | R56: 0 | S56: 0 | T56: 30 | U56: BL | W56: =$W$7 -> 46376 | X56: =$X$7 -> 46366 | Y56: =X56-W56 -> -10 | AB56: Caliari/Sarroch | AC56: 0 | AD56: 0 | AE56: 0 | AF56: 0 | AG56: 0 | AH56: 0 | AI56: 0 | AS56: Porvoo | AT56: =Y45 -> -10 | AU56: 0 | AV56: =SUMPRODUCT(AT56:AU56,$AT$35:$AU$35/SUM($AT$35:$AU$35)) -> -8 | AX56: =AT56 -> -10 | AY56: =AU56 -> 0
B57: Thessalonski | C57: Nsea | P57: 1 | Q57: Rotterdam-CASH | R57: 0 | S57: 0 | T57: 44 | U57: BL | W57: =$W$7 -> 46376 | X57: =$X$7 -> 46366 | Y57: =X57-W57 -> -10 | AB57: Kalundborg | AC57: 0 | AD57: 0 | AE57: 0 | AF57: 0 | AG57: 0 | AH57: 0 | AI57: 0 | AS57: La Coruña | AT57: =Y46 -> -10 | AU57: 0 | AV57: =SUMPRODUCT(AT57:AU57,$AT$35:$AU$35/SUM($AT$35:$AU$35)) -> -8 | AX57: =AT57 -> -10 | AY57: =AU57 -> 0
B58: Odessa | C58: Nsea | Q58: Chiba | R58: 1 | S58: 0 | T58: 10 | U58: NOR | W58: =Control!$C$101 -> 46376 | X58: =X59-2 -> 46403 | Y58: =X58-W58 -> 27 | AB58: Aliaga | AC58: 0 | AD58: 0 | AE58: 0 | AF58: 0 | AG58: 0 | AH58: 0 | AI58: 0 | AS58: Algericas | AT58: =Y47 -> -10 | AU58: 0 | AV58: =SUMPRODUCT(AT58:AU58,$AT$35:$AU$35/SUM($AT$35:$AU$35)) -> -8 | AX58: =AT58 -> -10 | AY58: =AU58 -> 0
B59: Savona | C59: Nsea | Q59: Daesan | R59: 1 | S59: 0 | T59: 10 | U59: NOR | W59: =Control!$C$101 -> 46376 | X59: =WTI!A28+WTI!BC28+T59+WTI!D43 -> 46405 | Y59: =X59-W59 -> 29 | AB59: Botas Ceyhan | AC59: 0 | AD59: 0 | AE59: 0 | AF59: 0 | AG59: 0 | AH59: 0 | AI59: 0 | AS59: Wilhelmshaven | AT59: =Y48 -> -10 | AU59: 0 | AV59: =SUMPRODUCT(AT59:AU59,$AT$35:$AU$35/SUM($AT$35:$AU$35)) -> -8 | AX59: =AT59 -> -10 | AY59: =AU59 -> 0
B60: Midla | C60: Nsea | Q60: Jamnagar | R60: 1 | S60: 0 | T60: 10 | U60: NOR | W60: =Control!$C$101 -> 46376 | X60: =X59-13 -> 46392 | Y60: =X60-W60 -> 16 | AB60: Agioi Theodori | AC60: 0 | AD60: 0 | AE60: 0 | AF60: 0 | AG60: 0 | AH60: 0 | AI60: 0 | AS60: Kalundborg | AT60: =Y49 -> -10 | AU60: 0 | AV60: =SUMPRODUCT(AT60:AU60,$AT$35:$AU$35/SUM($AT$35:$AU$35)) -> -8 | AX60: =AT60 -> -10 | AY60: =AU60 -> 0
B61: Pachi | C61: Nsea | Q61: Ningbo | R61: 1 | S61: 0 | T61: 10 | U61: NOR | W61: =Control!$C$101 -> 46376 | X61: =X59-3 -> 46402 | Y61: =X61-W61 -> 26 | AB61: Thessalonski | AC61: 0 | AD61: 0 | AE61: 0 | AF61: 0 | AG61: 0 | AH61: 0 | AI61: 0 | AS61: Aliaga | AT61: =Y50 -> -10 | AU61: 0 | AV61: =SUMPRODUCT(AT61:AU61,$AT$35:$AU$35/SUM($AT$35:$AU$35)) -> -8 | AX61: =AT61 -> -10 | AY61: =AU61 -> 0
B62: Pascagoula | C62: USGC | Q62: Singapore | R62: 1 | S62: 0 | T62: 10 | U62: NOR | W62: =Control!$C$101 -> 46376 | X62: =X59-10 -> 46395 | Y62: =X62-W62 -> 19 | AB62: Odessa | AC62: 0 | AD62: 0 | AE62: 0 | AF62: 0 | AG62: 0 | AH62: 0 | AI62: 0 | AS62: Botas Ceyhan | AT62: =Y51 -> -10 | AU62: 0 | AV62: =SUMPRODUCT(AT62:AU62,$AT$35:$AU$35/SUM($AT$35:$AU$35)) -> -8 | AX62: =AT62 -> -10 | AY62: =AU62 -> 0
B63: Wilhelmshaven | C63: Nsea | AB63: Savona | AC63: 0 | AD63: 0 | AE63: 0 | AF63: 0 | AG63: 0 | AH63: 0 | AI63: 0 | AS63: Agioi Theodori | AT63: =Y52 -> -10 | AU63: 0 | AV63: =SUMPRODUCT(AT63:AU63,$AT$35:$AU$35/SUM($AT$35:$AU$35)) -> -8 | AX63: =AT63 -> -10 | AY63: =AU63 -> 0
B64: Omisalj | C64: Nsea | AB64: Midla | AC64: 0 | AD64: 0 | AE64: 0 | AF64: 0 | AG64: 0 | AH64: 0 | AI64: 0 | AS64: Thessalonski | AT64: =Y53 -> -10 | AU64: 0 | AV64: =SUMPRODUCT(AT64:AU64,$AT$35:$AU$35/SUM($AT$35:$AU$35)) -> -8 | AX64: =AT64 -> -10 | AY64: =AU64 -> 0
AB65: Pachi | AC65: 0 | AD65: 0 | AE65: 0 | AF65: 0 | AG65: 0 | AH65: 0 | AI65: 0 | AS65: Odessa | AT65: =Y54 -> -10 | AU65: 0 | AV65: =SUMPRODUCT(AT65:AU65,$AT$35:$AU$35/SUM($AT$35:$AU$35)) -> -8 | AX65: =AT65 -> -10 | AY65: =AU65 -> 0
Q66: =WTI!A9 -> 46334 | AB66: Liza FPSO | AC66: 0 | AD66: 0 | AE66: 0 | AF66: 0 | AG66: 0 | AH66: 0 | AI66: 0 | AS66: Savona | AT66: =Y55 -> -10 | AU66: 0 | AV66: =SUMPRODUCT(AT66:AU66,$AT$35:$AU$35/SUM($AT$35:$AU$35)) -> -8 | AX66: =AT66 -> -10 | AY66: =AU66 -> 0
Q67: =WTI!BC28 -> 52 | AB67: Pascagoula | AC67: 0 | AD67: 0 | AE67: 0 | AF67: 0 | AG67: 0 | AH67: 0 | AI67: 0 | AS67: Cartagena | AT67: =Y56 -> -10 | AU67: 0 | AV67: =SUMPRODUCT(AT67:AU67,$AT$35:$AU$35/SUM($AT$35:$AU$35)) -> -8 | AX67: =AT67 -> -10 | AY67: =AU67 -> 0
Q68: =T58 -> 10 | AB68: Port Neches | AC68: 0 | AD68: 0 | AE68: 0 | AF68: 0 | AG68: 0 | AH68: 0 | AI68: 0 | AS68: Rotterdam-CASH | AT68: =Y57 -> -10 | AU68: 14 | AV68: =SUMPRODUCT(AT68:AU68,$AT$35:$AU$35/SUM($AT$35:$AU$35)) -> -5.2 | AX68: =AT68 -> -10 | AY68: =AU68 -> 14
Q69: =Q66+Q67+Q68 -> 46396 | AB69: Trinidad | AC69: 0 | AD69: 0 | AE69: 0 | AF69: 0 | AG69: 0 | AH69: 0 | AI69: 0 | AS69: Omisalj | AT69: =Y17 -> -10 | AU69: 0 | AV69: =SUMPRODUCT(AT69:AU69,$AT$35:$AU$35/SUM($AT$35:$AU$35)) -> -8 | AX69: =AT69 -> -10 | AY69: =AU69 -> 0
B74: Secondary Costs Breakdown
B75: API | D75: 43.3 | F75: Demurrage | H75: Caribs | J75: Max Load
B76: USG Oil Spill Tax | F76: Panamax | H76: 45000 | J76: Panamax | K76: 490000
B77: TVOM | D77: =D88 -> 0.013036164 | F77: Aframax | H77: 80000 | J77: Aframax | K77: 750000
B78: Insurance | F78: Suezmax | H78: 95000 | J78: Suezmax | K78: 850000
B79: Inspection+Port+Superintendent | D79: =0.0003+0.05+0.004+0.013 -> 0.0673 | F79: VLCC | H79: 450000 | J79: VLCC | K79: 0
F80: VLCC-MODA | H80: =H79 -> 450000 | J80: VLCC-MODA | K80: 1500000
B81: Outturn Losses | D81: 100 | E81: 0.002 | F81: VLCC-STG | H81: =H80 -> 450000 | J81: VLCC-STG | K81: 1500000
B82: EU TAX | D82: 0 | F82: Suezmax-MODA | H82: =H78 -> 95000 | J82: Suezmax-MODA | K82: 1050000
B83: Corpus Dock Fee | D83: 300000
B84: CONVERSION FACTOR | D84: =($D$75+131.5)/(141.5*0.159) -> 7.7694068
B85: Afra STS | D85: 750000
B86: Suez STS | D86: 850000 | J86: =(2000000-K79)/K80 -> 1.3333333
B87: Forties STS | D87: =600000*3 -> 1800000
B88: Financing | C88: =+C91+C92 -> 4.7582 | D88: =$C$88*$D$81/365/100 -> 0.013036164 | J88: =IF(WTI!AB24-VLOOKUP(WTI!Y24,$J$76:$K$80,2,FALSE)/$K$80>0,H90/WTI!AB24,0) -> 2.4666667
F89: Reverse Lightering | H89: Caribs
F90: VLCC | H90: 1850000 | I90: 75000
B91: SOFR | C91: 3.6582 | F91: VLCC-MODA | H91: =H90+200000 -> 2050000
B92: Premium | C92: 1.1 | F92: VLCC-STG | H92: =H91 -> 2050000 | O92: =1/1.22*10 -> 8.1967213
F93: Pipeline Fee | G93: 0.55
O94: 1000
B95: =EOMONTH(WTI!A21,0)+20 -> 46376 | O95: =O94*1.22 -> 1220
C100: =EOMONTH(WTI!A17,0)+20 -> #VALUE! | D100: =INDEX(Index,MATCH(WTI!V31,TVM_PortList,0),MATCH("Payment",Control!$Q$3:$U$3,0)) -> 30
C101: =EOMONTH(WTI!A9,0)+20 -> 46376 | D101: =IF(INDEX(Index,MATCH(WTI!Z43,TVM_PortList,0),MATCH("Type",Control!$Q$3:$U$3,0))="BL",WTI!$A$9+INDEX(Index,MATCH(WTI!V17,TVM_PortList,0),MATCH("Payment",Control!$Q$3:$U$3,0)),WTI!$A$9+INDEX(Index,MATCH(WTI!Z43,TVM_PortList,0),MATCH("Payment",Control!$Q$3:$U$3,0))+WTI!BC43) -> 46396
D104: =INDEX(Index,MATCH(WTI!V43,TVM_PortList,0),MATCH("Payment",Control!$Q$3:$U$3,0)) -> 30
C106: =EOMONTH(WTI!#REF!,0)+20 -> #REF! | D106: =INDEX(Index,MATCH(WTI!V44,TVM_PortList,0),MATCH("Payment",Control!$Q$3:$U$3,0)) -> 30
F107: =WTI!AV54-WTI!AV52 -> -2.0662571 | G107: =WTI!AV24-WTI!AV31 -> -18.212261
F108: =D101-C101 -> 20
F109: =D102-C102 -> 0
F112: =WTI!AV58-WTI!AV56 -> -4.876 | G112: =WTI!AV29-WTI!AV43 -> -2.979663
F114: =WTI!AV60-WTI!AV58 -> 0.1385 | G114: =WTI!AV31-WTI!AV44 -> -2.2280483
...

Sheet WTI
W1: =INDEX(Vessel_Minimum_MT,MATCH(Y1,Control!$E$11:$E$15,0),MATCH(V1,Control!$E$11:$J$11,0)) -> #N/A | AI1: =AF1*VLOOKUP($Y1,Control!$F$75:$H$79,3,FALSE)/$AB1 -> #N/A
D2: WTI MIDLAND
D3: FOB Corpus Christi | Y3: -3.6 | AD3: 1400 | AE3: 0.8 | AJ3: ATA TVM | AK3: 0 | AL3: 1 | AV3: ICE Brent | AW3: Dubai | AX3: Dated | BC3: 1 | BD3: 46296 | BE3: =EOMONTH(BD3,1) -> 46356 | BF3: =EOMONTH(BE3,1) -> 46387 | BG3: =EOMONTH(BF3,1) -> 46418 | BH3: =EOMONTH(BG3,1) -> 46446 | BJ3: 46101 | BL3: 4480 | BO3: 25
D4: MEH/Brent | T4: Leave | U4: Payment Terms | V4: Payment Date | AD4: 700 | AE4: 0.1 | AJ4: Ext. TVM | AK4: 1 | AV4: 0 | AW4: 1 | AX4: 2 | AZ4: <----- | BC4: Spreads | BD4: 3.75 | BE4: 2.9 | BF4: 2.25 | BG4: 1.9 | BH4: 1.7 | BJ4: =BJ3+19 -> 46120 | BL4: 4867 | BO4: 15
D5: EFP | T5: =A9 -> 46334 | U5: 13 | V5: =T5+BC31+U5 -> 46396 | AE5: {=SUMPRODUCT(AE3:AE4,AD3:AD4/SUM(AD3:AD4))} -> 0.56666667 | AV5: ICE Brent | AW5: Dubai | AX5: Dated | BC5: Dated | BD5: 13.5 | BE5: 5.28 | BF5: 3.98 | BG5: 2.93 | BH5: 2.45 | BJ5: =BJ4-30 -> 46090 | BL5: 3665 | BO5: =AVERAGE(BO3:BO4) -> 20
AZ6: EXTAP Toggle | BC6: Dubai | BD6: -5.25 | BE6: -1.7 | BF6: -0.9 | BG6: -0.7 | BH6: -0.65 | BI6: 0.17 | BL6: =AVERAGE(BL3:BL4) -> 4673.5
BC7: CMA | BD7: 21 | BE7: 22 | BF7: 23 | BG7: 21 | BH7: 22
A8: Load Window | Y8: CORPUS-ASIA | BC8: 1 | BD8: --> 1, Natural Arrival ; 0 M-1 | BH8: 1 | BL8: =BL6/30 -> 155.78333
A9: 46334 | B9: =A9+2 -> 46336 | D9: STS Time | E9: Depart | T9: Flat | U9: Overages | V9: Loadport | W9: Vessel MT | X9: Actual MT | Y9: Vessel | Z9: Destination | AA9: Route | AB9: Volume | AC9: Current WS Rate | AD9: WS Rate Call | AE9: Destination Freight | AF9: Demurrage | AG9: ATA TVM | AH9: Ext. TVM | AI9: Demurrage $ | AJ9: TVM | AL9: STS | AM9: Wharfage | AN9: Panama Canal | AO9: Insurance | AP9: Inspection | AQ9: Outturn Losses | AR9: EU TAX | AS9: Other costs | AT9: Pipeline Fee | AU9: Total Secondary Costs | AV9: All In Cost | AW9: Structure | AX9: Basis | AY9: Brt Swap | AZ9: DES Price | BC9: Transit Time | BD9: Arrival Window | BF9: Basis | BG9: Pricing Month | BH9: Delivery Month
A10: =+$A$9 -> 46334 | B10: =IF(ISBLANK(A10),"",A10+2) -> 46336 | D10: =IF(AL10=0,0,VLOOKUP(Y10,Control!$G$41:$J$44,4,FALSE)) -> 0 | T10: #N/A | U10: =INDEX(Control!$E$17:$J$21,MATCH(Y10,Control!$E$17:$E$21,0),MATCH(V10,Control!$E$17:$J$17,0)) -> 0.5 | V10: Puerto Armuelles | W10: =INDEX(Vessel_Minimum_MT,MATCH(Y10,Control!$E$11:$E$15,0),MATCH(V10,Control!$E$11:$J$11,0)) -> 50000 | X10: =AB10/Control!$D$84 -> 62424.328 | Y10: Panamax | Z10: Quintero (MB) | AA10: =IF(Z10=V10,"",CONCATENATE(CONCATENATE(VLOOKUP(V10,Zones,2,FALSE),"/",VLOOKUP(Z10,Zones,2,FALSE)))) -> Panama WC/LATAM WEST | AB10: 485000 | AC10: 245 | AD10: 100 | AE10: =IF(AD10>1000,IF(AD10=0,AD10,AD10)/AB10,((W10*T10*(IF(AD10=0,AD10,AD10)/100))+IF(X10<W10,0,(X10-W10)*T10*IF(AD10=0,AD10,AD10)/100*U10))/AB10) -> #N/A | AF10: 5 | AG10: =IF(INDEX(Index,MATCH(Z10,TVM_PortList,0),MATCH("Type",Control!$Q$3:$U$3,0))="BL",INDEX(Index,MATCH(Z10,TVM_PortList,0),MATCH("Payment",Control!$Q$3:$U$3,0))-INDEX(Index,MATCH(V10,TVM_PortList,0),MATCH("Payment",Control!$Q$3:$U$3,0)),BC10+INDEX(Index,MATCH(Z10,TVM_PortList,0),MATCH("Payment",Control!$Q$3:$U$3,0))-INDEX(Index,MATCH(V10,TVM_PortList,0),MATCH("Payment",Control!$Q$3:$U$3,0))) -> 15 | AI10: =AF10*VLOOKUP($Y10,Control!$F$75:$H$79,3,FALSE)/$AB10 -> 0.46391753 | AJ10: =IF(AG10<0,0,$AG10*Control!$D$77) -> 0.19554247 | AL10: =INDEX(Lightering,MATCH($V10,Control!$AB$3:$AB$29,0),MATCH(WTI!$Y10,Control!$AB$3:$AF$3,0))*($AB10/Control!$D$85)*Control!$H$90/$AB10 -> 0 | AM10: =IF(I10="Corpus Christi",Control!$D$76,0) -> 0 | AN10: 0 | AO10: =Control!$D$78 -> 0 | AP10: =Control!$D$79 -> 0.0673 | AQ10: =IF(INDEX(Control!$Q$3:$S$62,MATCH($Z10,Control!$Q$3:$Q$62,0),MATCH(AQ$9,Control!$Q$3:$S$3,0))=1,Control!$D$81*Control!$E$81,0) -> 0 | AR10: =IF(INDEX(Control!$Q$3:$S$62,MATCH($Z10,Control!$Q$3:$Q$62,0),MATCH(AR$9,Control!$Q$3:$S$3,0))=1,Control!$D$82/$AB10,0) -> 0 | AT10: =IF(AND(L10="Chiriqui Grande",V10="Puerto Armuelles"),Control!$G$93,0) -> 0 | AU10: =SUM(AI10:AT10) -> 0.72675999 | AV10: =+R10+AE10+AU10 -> #N/A | AW10: =IF((MONTH(A10)=MONTH(BE10)),0,IF((MONTH(BE10)+12)-(MONTH(A10)+12)>1,VLOOKUP("Spreads",$BC$3:$BG$4,MATCH(EOMONTH(BE10,0),$BC$3:$BG$3,0),FALSE)+VLOOKUP("Spreads",$BC$3:$BG$4,MATCH(EOMONTH(BE10,-1),$BC$3:$BG$3,0),FALSE),VLOOKUP("Spreads",$BC$3:$BG$4,MATCH(EOMONTH(A10,0),$BC$3:$BG$3,0)))) -> #N/A | AX10: 0 | AZ10: =$Y$3+AV10+AW10+AX10 -> #N/A | BC10: =INDEX('[1]Transit Time'!$A:$DZ,MATCH(I10,'[1]Transit Time'!$A:$A,0),MATCH(L10,'[1]Transit Time'!$A$1:$DZ$1,0))+INDEX('[1]Transit Time'!$A:$DZ,MATCH(L10,'[1]Transit Time'!$A:$A,0),MATCH(V10,'[1]Transit Time'!$A$1:$DZ$1,0))+INDEX('[1]Transit Time'!$A:$DZ,MATCH(V10,'[1]Transit Time'!$A:$A,0),MATCH(Z10,'[1]Transit Time'!$A$1:$DZ$1,0)) -> #N/A | BD10: =IF(ISBLANK(A10),"",A10+$BC10+D10) -> #N/A | BE10: =IF(ISBLANK(B10),"",B10+$BC10) -> #N/A
A11: =+$A$10 -> 46334 | B11: =IF(ISBLANK(A11),"",A11+2) -> 46336 | D11: =IF(AL11=0,0,VLOOKUP(Y11,Control!$G$41:$J$44,4,FALSE)) -> 0 | T11: =INDEX('[2]Flat Rates 2025'!$A:$DZ,MATCH(V11,'[2]Flat Rates 2025'!$A:$A,0),MATCH(Z11,'[2]Flat Rates 2025'!$A$1:$DZ$1,0)) -> 10.63 | U11: =INDEX(Control!$E$17:$J$21,MATCH(Y11,Control!$E$17:$E$21,0),MATCH(V11,Control!$E$17:$J$17,0)) -> 0.5 | V11: Puerto Armuelles | W11: =INDEX(Vessel_Minimum_MT,MATCH(Y11,Control!$E$11:$E$15,0),MATCH(V11,Control!$E$11:$J$11,0)) -> 70000 | X11: =AB11/Control!$D$84 -> 96532.466 | Y11: Aframax | Z11: Quintero (MB) | AA11: =IF(Z11=V11,"",CONCATENATE(CONCATENATE(VLOOKUP(V11,Zones,2,FALSE),"/",VLOOKUP(Z11,Zones,2,FALSE)))) -> Panama WC/LATAM WEST | AB11: 750000 | AC11: 155 | AE11: =IF(AC11>1000,IF(AD11=0,AC11,AD11)/AB11,((W11*T11*(IF(AD11=0,AC11,AD11)/100))+IF(X11<W11,0,(X11-W11)*T11*IF(AD11=0,AC11,AD11)/100*U11))/AB11) -> 1.8292481 | AF11: 0 | AG11: =IF(INDEX(Index,MATCH(Z11,TVM_PortList,0),MATCH("Type",Control!$Q$3:$U$3,0))="BL",INDEX(Index,MATCH(Z11,TVM_PortList,0),MATCH("Payment",Control!$Q$3:$U$3,0))-INDEX(Index,MATCH(V11,TVM_PortList,0),MATCH("Payment",Control!$Q$3:$U$3,0)),BC11+INDEX(Index,MATCH(Z11,TVM_PortList,0),MATCH("Payment",Control!$Q$3:$U$3,0))-INDEX(Index,MATCH(V11,TVM_PortList,0),MATCH("Payment",Control!$Q$3:$U$3,0))) -> 15 | AI11: =AF11*VLOOKUP($Y11,Control!$F$75:$H$79,3,FALSE)/$AB11 -> 0 | AJ11: =IF(AG11<0,0,$AG11*Control!$D$77) -> 0.19554247 | AL11: =INDEX(Lightering,MATCH($V11,Control!$AB$3:$AB$29,0),MATCH(WTI!$Y11,Control!$AB$3:$AF$3,0))*($AB11/Control!$D$85)*Control!$H$90/$AB11 -> 0 | AM11: =IF(I11="Corpus Christi",Control!$D$76,0) -> 0 | AN11: 0 | AO11: =Control!$D$78 -> 0 | AP11: =Control!$D$79 -> 0.0673 | AQ11: =IF(INDEX(Control!$Q$3:$S$62,MATCH($Z11,Control!$Q$3:$Q$62,0),MATCH(AQ$9,Control!$Q$3:$S$3,0))=1,Control!$D$81*Control!$E$81,0) -> 0 | AR11: =IF(INDEX(Control!$Q$3:$S$62,MATCH($Z11,Control!$Q$3:$Q$62,0),MATCH(AR$9,Control!$Q$3:$S$3,0))=1,Control!$D$82/$AB11,0) -> 0 | AT11: =IF(AND(L11="Chiriqui Grande",V11="Puerto Armuelles"),Control!$G$93,0) -> 0 | AU11: =SUM(AI11:AT11) -> 0.26284247 | AV11: =+R11+AE11+AU11 -> 2.0920906 | AW11: =IF((MONTH(A11)=MONTH(BE11)),0,IF((MONTH(BE11)+12)-(MONTH(A11)+12)>1,VLOOKUP("Spreads",$BC$3:$BG$4,MATCH(EOMONTH(BE11,0),$BC$3:$BG$3,0),FALSE)+VLOOKUP("Spreads",$BC$3:$BG$4,MATCH(EOMONTH(BE11,-1),$BC$3:$BG$3,0),FALSE),VLOOKUP("Spreads",$BC$3:$BG$4,MATCH(EOMONTH(A11,0),$BC$3:$BG$3,0)))) -> #VALUE! | AX11: 0 | AZ11: =$Y$3+AV11+AW11+AX11 -> #VALUE! | BC11: =INDEX('[1]Transit Time'!$A:$DZ,MATCH(I11,'[1]Transit Time'!$A:$A,0),MATCH(L11,'[1]Transit Time'!$A$1:$DZ$1,0))+INDEX('[1]Transit Time'!$A:$DZ,MATCH(L11,'[1]Transit Time'!$A:$A,0),MATCH(V11,'[1]Transit Time'!$A$1:$DZ$1,0))+INDEX('[1]Transit Time'!$A:$DZ,MATCH(V11,'[1]Transit Time'!$A:$A,0),MATCH(Z11,'[1]Transit Time'!$A$1:$DZ$1,0)) -> #N/A | BD11: =IF(ISBLANK(A11),"",A11+$BC11) -> #N/A | BE11: =IFERROR(IF(ISBLANK(B11),"",B11+$BC11),"")
A12: =+$A$10 -> 46334 | B12: =IF(ISBLANK(A12),"",A12+2) -> 46336 | D12: =IF(AL12=0,0,VLOOKUP(Y12,Control!$G$41:$J$44,4,FALSE)) -> 0 | T12: =INDEX('[2]Flat Rates 2025'!$A:$DZ,MATCH(V12,'[2]Flat Rates 2025'!$A:$A,0),MATCH(Z12,'[2]Flat Rates 2025'!$A$1:$DZ$1,0)) -> 10.63 | U12: =INDEX(Control!$E$17:$J$21,MATCH(Y12,Control!$E$17:$E$21,0),MATCH(V12,Control!$E$17:$J$17,0)) -> 0.5 | V12: Puerto Armuelles | W12: =INDEX(Vessel_Minimum_MT,MATCH(Y12,Control!$E$11:$E$15,0),MATCH(V12,Control!$E$11:$J$11,0)) -> 145000 | X12: =AB12/Control!$D$84 -> 128709.95 | Y12: Suezmax | Z12: Quintero (MB) | AA12: =IF(Z12=V12,"",CONCATENATE(CONCATENATE(VLOOKUP(V12,Zones,2,FALSE),"/",VLOOKUP(Z12,Zones,2,FALSE)))) -> Panama WC/LATAM WEST | AB12: 1000000 | AC12: 110 | AE12: =IF(AC12>1000,IF(AD12=0,AC12,AD12)/AB12,((W12*T12*(IF(AD12=0,AC12,AD12)/100))+IF(X12<W12,0,(X12-W12)*T12*IF(AD12=0,AC12,AD12)/100*U12))/AB12) -> 1.695485 | AF12: 0 | AG12: =IF(INDEX(Index,MATCH(Z12,TVM_PortList,0),MATCH("Type",Control!$Q$3:$U$3,0))="BL",INDEX(Index,MATCH(Z12,TVM_PortList,0),MATCH("Payment",Control!$Q$3:$U$3,0))-INDEX(Index,MATCH(V12,TVM_PortList,0),MATCH("Payment",Control!$Q$3:$U$3,0)),BC12+INDEX(Index,MATCH(Z12,TVM_PortList,0),MATCH("Payment",Control!$Q$3:$U$3,0))-INDEX(Index,MATCH(V12,TVM_PortList,0),MATCH("Payment",Control!$Q$3:$U$3,0))) -> 15 | AI12: =AF12*VLOOKUP($Y12,Control!$F$75:$H$79,3,FALSE)/$AB12 -> 0 | AJ12: =IF(AG12<0,0,$AG12*Control!$D$77) -> 0.19554247 | AL12: =INDEX(Lightering,MATCH($V12,Control!$AB$3:$AB$29,0),MATCH(WTI!$Y12,Control!$AB$3:$AF$3,0))*($AB12/Control!$D$85)*Control!$H$90/$AB12 -> 0 | AM12: =IF(I12="Corpus Christi",Control!$D$76,0) -> 0 | AN12: 0 | AO12: =Control!$D$78 -> 0 | AP12: =Control!$D$79 -> 0.0673 | AQ12: =IF(INDEX(Control!$Q$3:$S$62,MATCH($Z12,Control!$Q$3:$Q$62,0),MATCH(AQ$9,Control!$Q$3:$S$3,0))=1,Control!$D$81*Control!$E$81,0) -> 0 | AR12: =IF(INDEX(Control!$Q$3:$S$62,MATCH($Z12,Control!$Q$3:$Q$62,0),MATCH(AR$9,Control!$Q$3:$S$3,0))=1,Control!$D$82/$AB12,0) -> 0 | AT12: =IF(AND(L12="Chiriqui Grande",V12="Puerto Armuelles"),Control!$G$93,0) -> 0 | AU12: =SUM(AI12:AT12) -> 0.26284247 | AV12: =+R12+AE12+AU12 -> 1.9583275 | AW12: =IF((MONTH(A12)=MONTH(BE12)),0,IF((MONTH(BE12)+12)-(MONTH(A12)+12)>1,VLOOKUP("Spreads",$BC$3:$BG$4,MATCH(EOMONTH(BE12,0),$BC$3:$BG$3,0),FALSE)+VLOOKUP("Spreads",$BC$3:$BG$4,MATCH(EOMONTH(BE12,-1),$BC$3:$BG$3,0),FALSE),VLOOKUP("Spreads",$BC$3:$BG$4,MATCH(EOMONTH(A12,0),$BC$3:$BG$3,0)))) -> #VALUE! | AX12: 0 | AZ12: =$Y$3+AV12+AW12+AX12 -> #VALUE! | BC12: =INDEX('[1]Transit Time'!$A:$DZ,MATCH(I12,'[1]Transit Time'!$A:$A,0),MATCH(L12,'[1]Transit Time'!$A$1:$DZ$1,0))+INDEX('[1]Transit Time'!$A:$DZ,MATCH(L12,'[1]Transit Time'!$A:$A,0),MATCH(V12,'[1]Transit Time'!$A$1:$DZ$1,0))+INDEX('[1]Transit Time'!$A:$DZ,MATCH(V12,'[1]Transit Time'!$A:$A,0),MATCH(Z12,'[1]Transit Time'!$A$1:$DZ$1,0)) -> #N/A | BD12: =IF(ISBLANK(A12),"",A12+$BC12) -> #N/A | BE12: =IFERROR(IF(ISBLANK(B12),"",B12+$BC12),"")
A13: =+$A$10 -> 46334 | B13: =IF(ISBLANK(A13),"",A13+2) -> 46336 | D13: =IF(AL13=0,0,VLOOKUP(Y13,Control!$G$41:$J$44,4,FALSE)) -> 0 | T13: =INDEX('[2]Flat Rates 2025'!$A:$DZ,MATCH(V13,'[2]Flat Rates 2025'!$A:$A,0),MATCH(Z13,'[2]Flat Rates 2025'!$A$1:$DZ$1,0)) -> 5.93 | U13: =INDEX(Control!$E$17:$J$21,MATCH(Y13,Control!$E$17:$E$21,0),MATCH(V13,Control!$E$17:$J$17,0)) -> 0.5 | V13: Puerto Armuelles | W13: =INDEX(Vessel_Minimum_MT,MATCH(Y13,Control!$E$11:$E$15,0),MATCH(V13,Control!$E$11:$J$11,0)) -> 50000 | X13: =AB13/Control!$D$84 -> 61137.228 | Y13: Panamax | Z13: La Pampilla | AA13: =IF(Z13=V13,"",CONCATENATE(CONCATENATE(VLOOKUP(V13,Zones,2,FALSE),"/",VLOOKUP(Z13,Zones,2,FALSE)))) -> Panama WC/PAMPILLA | AB13: 475000 | AC13: 1001 | AD13: 700000 | AE13: =IF(AC13>1000,IF(AD13=0,AC13,AD13)/AB13,((W13*T13*(IF(AD13=0,AC13,AD13)/100))+IF(X13<W13,0,(X13-W13)*T13*IF(AD13=0,AC13,AD13)/100*U13))/AB13) -> 1.4736842 | AF13: 0 | AG13: =IF(INDEX(Index,MATCH(Z13,TVM_PortList,0),MATCH("Type",Control!$Q$3:$U$3,0))="BL",INDEX(Index,MATCH(Z13,TVM_PortList,0),MATCH("Payment",Control!$Q$3:$U$3,0))-INDEX(Index,MATCH(V13,TVM_PortList,0),MATCH("Payment",Control!$Q$3:$U$3,0)),BC13+INDEX(Index,MATCH(Z13,TVM_PortList,0),MATCH("Payment",Control!$Q$3:$U$3,0))-INDEX(Index,MATCH(V13,TVM_PortList,0),MATCH("Payment",Control!$Q$3:$U$3,0))) -> #N/A | AI13: =AF13*VLOOKUP($Y13,Control!$F$75:$H$79,3,FALSE)/$AB13 -> 0 | AJ13: =IF(AG13<0,0,$AG13*Control!$D$77) -> #N/A | AL13: =INDEX(Lightering,MATCH($V13,Control!$AB$3:$AB$29,0),MATCH(WTI!$Y13,Control!$AB$3:$AF$3,0))*($AB13/Control!$D$85)*Control!$H$90/$AB13 -> 0 | AM13: =IF(I13="Corpus Christi",Control!$D$76,0) -> 0 | AN13: 0 | AO13: =Control!$D$78 -> 0 | AP13: =Control!$D$79 -> 0.0673 | AQ13: =IF(INDEX(Control!$Q$3:$S$62,MATCH($Z13,Control!$Q$3:$Q$62,0),MATCH(AQ$9,Control!$Q$3:$S$3,0))=1,Control!$D$81*Control!$E$81,0) -> 0 | AR13: =IF(INDEX(Control!$Q$3:$S$62,MATCH($Z13,Control!$Q$3:$Q$62,0),MATCH(AR$9,Control!$Q$3:$S$3,0))=1,Control!$D$82/$AB13,0) -> 0 | AT13: =IF(AND(L13="Chiriqui Grande",V13="Puerto Armuelles"),Control!$G$93,0) -> 0 | AU13: =SUM(AI13:AT13) -> #N/A | AV13: =+R13+AE13+AU13 -> #N/A | AW13: =IF((MONTH(A13)=MONTH(BE13)),0,IF((MONTH(BE13)+12)-(MONTH(A13)+12)>1,VLOOKUP("Spreads",$BC$3:$BG$4,MATCH(EOMONTH(BE13,0),$BC$3:$BG$3,0),FALSE)+VLOOKUP("Spreads",$BC$3:$BG$4,MATCH(EOMONTH(BE13,-1),$BC$3:$BG$3,0),FALSE),VLOOKUP("Spreads",$BC$3:$BG$4,MATCH(EOMONTH(A13,0),$BC$3:$BG$3,0)))) -> #VALUE! | AX13: 0 | AZ13: =$Y$3+AV13+AW13+AX13 -> #N/A | BC13: =INDEX('[1]Transit Time'!$A:$DZ,MATCH(I13,'[1]Transit Time'!$A:$A,0),MATCH(L13,'[1]Transit Time'!$A$1:$DZ$1,0))+INDEX('[1]Transit Time'!$A:$DZ,MATCH(L13,'[1]Transit Time'!$A:$A,0),MATCH(V13,'[1]Transit Time'!$A$1:$DZ$1,0))+INDEX('[1]Transit Time'!$A:$DZ,MATCH(V13,'[1]Transit Time'!$A:$A,0),MATCH(Z13,'[1]Transit Time'!$A$1:$DZ$1,0)) -> #N/A | BD13: =IF(ISBLANK(A13),"",A13+$BC13) -> #N/A | BE13: =IFERROR(IF(ISBLANK(B13),"",B13+$BC13),"")
A14: =+$A$10 -> 46334 | B14: =IF(ISBLANK(A14),"",A14+2) -> 46336 | D14: =IF(AL14=0,0,VLOOKUP(Y14,Control!$G$41:$J$44,4,FALSE)) -> 0 | T14: =INDEX('[2]Flat Rates 2025'!$A:$DZ,MATCH(V14,'[2]Flat Rates 2025'!$A:$A,0),MATCH(Z14,'[2]Flat Rates 2025'!$A$1:$DZ$1,0)) -> 5.93 | U14: =INDEX(Control!$E$17:$J$21,MATCH(Y14,Control!$E$17:$E$21,0),MATCH(V14,Control!$E$17:$J$17,0)) -> 0.5 | V14: Puerto Armuelles | W14: =INDEX(Vessel_Minimum_MT,MATCH(Y14,Control!$E$11:$E$15,0),MATCH(V14,Control!$E$11:$J$11,0)) -> 70000 | X14: =AB14/Control!$D$84 -> 84948.57 | Y14: Aframax | Z14: La Pampilla | AA14: =IF(Z14=V14,"",CONCATENATE(CONCATENATE(VLOOKUP(V14,Zones,2,FALSE),"/",VLOOKUP(Z14,Zones,2,FALSE)))) -> Panama WC/PAMPILLA | AB14: 660000 | AC14: 205 | AD14: 0 | AE14: =IF(AC14>1000,IF(AD14=0,AC14,AD14)/AB14,((W14*T14*(IF(AD14=0,AC14,AD14)/100))+IF(X14<W14,0,(X14-W14)*T14*IF(AD14=0,AC14,AD14)/100*U14))/AB14) -> 1.4269942 | AF14: 0 | AG14: =IF(INDEX(Index,MATCH(Z14,TVM_PortList,0),MATCH("Type",Control!$Q$3:$U$3,0))="BL",INDEX(Index,MATCH(Z14,TVM_PortList,0),MATCH("Payment",Control!$Q$3:$U$3,0))-INDEX(Index,MATCH(V14,TVM_PortList,0),MATCH("Payment",Control!$Q$3:$U$3,0)),BC14+INDEX(Index,MATCH(Z14,TVM_PortList,0),MATCH("Payment",Control!$Q$3:$U$3,0))-INDEX(Index,MATCH(V14,TVM_PortList,0),MATCH("Payment",Control!$Q$3:$U$3,0))) -> #N/A | AI14: =AF14*VLOOKUP($Y14,Control!$F$75:$H$79,3,FALSE)/$AB14 -> 0 | AJ14: =IF(AG14<0,0,$AG14*Control!$D$77) -> #N/A | AL14: =INDEX(Lightering,MATCH($V14,Control!$AB$3:$AB$29,0),MATCH(WTI!$Y14,Control!$AB$3:$AF$3,0))*($AB14/Control!$D$85)*Control!$H$90/$AB14 -> 0 | AM14: =IF(I14="Corpus Christi",Control!$D$76,0) -> 0 | AN14: 0 | AO14: =Control!$D$78 -> 0 | AP14: =Control!$D$79 -> 0.0673 | AQ14: =IF(INDEX(Control!$Q$3:$S$62,MATCH($Z14,Control!$Q$3:$Q$62,0),MATCH(AQ$9,Control!$Q$3:$S$3,0))=1,Control!$D$81*Control!$E$81,0) -> 0 | AR14: =IF(INDEX(Control!$Q$3:$S$62,MATCH($Z14,Control!$Q$3:$Q$62,0),MATCH(AR$9,Control!$Q$3:$S$3,0))=1,Control!$D$82/$AB14,0) -> 0 | AT14: =IF(AND(L14="Chiriqui Grande",V14="Puerto Armuelles"),Control!$G$93,0) -> 0 | AU14: =SUM(AI14:AT14) -> #N/A | AV14: =+R14+AE14+AU14 -> #N/A | AW14: =IF((MONTH(A14)=MONTH(BE14)),0,IF((MONTH(BE14)+12)-(MONTH(A14)+12)>1,VLOOKUP("Spreads",$BC$3:$BG$4,MATCH(EOMONTH(BE14,0),$BC$3:$BG$3,0),FALSE)+VLOOKUP("Spreads",$BC$3:$BG$4,MATCH(EOMONTH(BE14,-1),$BC$3:$BG$3,0),FALSE),VLOOKUP("Spreads",$BC$3:$BG$4,MATCH(EOMONTH(A14,0),$BC$3:$BG$3,0)))) -> #VALUE! | AX14: 0 | AZ14: =$Y$3+AV14+AW14+AX14 -> #N/A | BC14: =INDEX('[1]Transit Time'!$A:$DZ,MATCH(I14,'[1]Transit Time'!$A:$A,0),MATCH(L14,'[1]Transit Time'!$A$1:$DZ$1,0))+INDEX('[1]Transit Time'!$A:$DZ,MATCH(L14,'[1]Transit Time'!$A:$A,0),MATCH(V14,'[1]Transit Time'!$A$1:$DZ$1,0))+INDEX('[1]Transit Time'!$A:$DZ,MATCH(V14,'[1]Transit Time'!$A:$A,0),MATCH(Z14,'[1]Transit Time'!$A$1:$DZ$1,0)) -> #N/A | BD14: =IF(ISBLANK(A14),"",A14+$BC14) -> #N/A | BE14: =IFERROR(IF(ISBLANK(B14),"",B14+$BC14),"")
A15: =+$A$10 -> 46334 | B15: =IF(ISBLANK(A15),"",A15+2) -> 46336 | D15: =IF(AL15=0,0,VLOOKUP(Y15,Control!$G$41:$J$44,4,FALSE)) -> 0 | T15: =INDEX('[2]Flat Rates 2025'!$A:$DZ,MATCH(V15,'[2]Flat Rates 2025'!$A:$A,0),MATCH(Z15,'[2]Flat Rates 2025'!$A$1:$DZ$1,0)) -> #N/A | U15: =INDEX(Control!$E$17:$J$21,MATCH(Y15,Control!$E$17:$E$21,0),MATCH(V15,Control!$E$17:$J$17,0)) -> 0.5 | V15: Puerto Armuelles | W15: =INDEX(Vessel_Minimum_MT,MATCH(Y15,Control!$E$11:$E$15,0),MATCH(V15,Control!$E$11:$J$11,0)) -> 50000 | X15: =AB15/Control!$D$84 -> 51355.272 | Y15: Panamax | Z15: Bayovar/Talara | AA15: =IF(Z15=V15,"",CONCATENATE(CONCATENATE(VLOOKUP(V15,Zones,2,FALSE),"/",VLOOKUP(Z15,Zones,2,FALSE)))) -> #N/A | AB15: 399000 | AC15: 1001 | AD15: 700000 | AE15: =IF(AC15>1000,IF(AD15=0,AC15,AD15)/AB15,((W15*T15*(IF(AD15=0,AC15,AD15)/100))+IF(X15<W15,0,(X15-W15)*T15*IF(AD15=0,AC15,AD15)/100*U15))/AB15) -> 1.754386 | AF15: 0 | AG15: =IF(INDEX(Index,MATCH(Z15,TVM_PortList,0),MATCH("Type",Control!$Q$3:$U$3,0))="BL",INDEX(Index,MATCH(Z15,TVM_PortList,0),MATCH("Payment",Control!$Q$3:$U$3,0))-INDEX(Index,MATCH(V15,TVM_PortList,0),MATCH("Payment",Control!$Q$3:$U$3,0)),BC15+INDEX(Index,MATCH(Z15,TVM_PortList,0),MATCH("Payment",Control!$Q$3:$U$3,0))-INDEX(Index,MATCH(V15,TVM_PortList,0),MATCH("Payment",Control!$Q$3:$U$3,0))) -> #N/A | AI15: =AF15*VLOOKUP($Y15,Control!$F$75:$H$79,3,FALSE)/$AB15 -> 0 | AJ15: =IF(AG15<0,0,$AG15*Control!$D$77) -> #N/A | AL15: =INDEX(Lightering,MATCH($V15,Control!$AB$3:$AB$29,0),MATCH(WTI!$Y15,Control!$AB$3:$AF$3,0))*($AB15/Control!$D$85)*Control!$H$90/$AB15 -> 0 | AM15: =IF(I15="Corpus Christi",Control!$D$76,0) -> 0 | AN15: 0 | AO15: =Control!$D$78 -> 0 | AP15: =Control!$D$79 -> 0.0673 | AQ15: =IF(INDEX(Control!$Q$3:$S$62,MATCH($Z15,Control!$Q$3:$Q$62,0),MATCH(AQ$9,Control!$Q$3:$S$3,0))=1,Control!$D$81*Control!$E$81,0) -> #N/A | AR15: =IF(INDEX(Control!$Q$3:$S$62,MATCH($Z15,Control!$Q$3:$Q$62,0),MATCH(AR$9,Control!$Q$3:$S$3,0))=1,Control!$D$82/$AB15,0) -> #N/A | AT15: =IF(AND(L15="Chiriqui Grande",V15="Puerto Armuelles"),Control!$G$93,0) -> 0 | AU15: =SUM(AI15:AT15) -> #N/A | AV15: =+R15+AE15+AU15 -> #N/A | AW15: =IF((MONTH(A15)=MONTH(BE15)),0,IF((MONTH(BE15)+12)-(MONTH(A15)+12)>1,VLOOKUP("Spreads",$BC$3:$BG$4,MATCH(EOMONTH(BE15,0),$BC$3:$BG$3,0),FALSE)+VLOOKUP("Spreads",$BC$3:$BG$4,MATCH(EOMONTH(BE15,-1),$BC$3:$BG$3,0),FALSE),VLOOKUP("Spreads",$BC$3:$BG$4,MATCH(EOMONTH(A15,0),$BC$3:$BG$3,0)))) -> #VALUE! | AX15: 0 | AZ15: =$Y$3+AV15+AW15+AX15 -> #N/A | BC15: =INDEX('[1]Transit Time'!$A:$DZ,MATCH(I15,'[1]Transit Time'!$A:$A,0),MATCH(L15,'[1]Transit Time'!$A$1:$DZ$1,0))+INDEX('[1]Transit Time'!$A:$DZ,MATCH(L15,'[1]Transit Time'!$A:$A,0),MATCH(V15,'[1]Transit Time'!$A$1:$DZ$1,0))+INDEX('[1]Transit Time'!$A:$DZ,MATCH(V15,'[1]Transit Time'!$A:$A,0),MATCH(Z15,'[1]Transit Time'!$A$1:$DZ$1,0)) -> #N/A | BD15: =IF(ISBLANK(A15),"",A15+$BC15) -> #N/A | BE15: =IFERROR(IF(ISBLANK(B15),"",B15+$BC15),"")
A16: =+$A$10 -> 46334 | B16: =IF(ISBLANK(A16),"",A16+2) -> 46336 | D16: =IF(AL16=0,0,VLOOKUP(Y16,Control!$G$41:$J$44,4,FALSE)) -> 0 | T16: =INDEX('[2]Flat Rates 2025'!$A:$DZ,MATCH(V16,'[2]Flat Rates 2025'!$A:$A,0),MATCH(Z16,'[2]Flat Rates 2025'!$A$1:$DZ$1,0)) -> #N/A | U16: =INDEX(Control!$E$17:$J$21,MATCH(Y16,Control!$E$17:$E$21,0),MATCH(V16,Control!$E$17:$J$17,0)) -> 0 | V16: Chiriqui Grande | W16: =INDEX(Vessel_Minimum_MT,MATCH(Y16,Control!$E$11:$E$15,0),MATCH(V16,Control!$E$11:$J$11,0)) -> 70000 | X16: =AB16/Control!$D$84 -> 64354.977 | Y16: Aframax | Z16: Mamonal | AA16: =IF(Z16=V16,"",CONCATENATE(CONCATENATE(VLOOKUP(V16,Zones,2,FALSE),"/",VLOOKUP(Z16,Zones,2,FALSE)))) -> CARIBS/CARIBS | AB16: 500000 | AC16: 180 | AD16: 325 | AE16: =IF(AC16>1000,IF(AD16=0,AC16,AD16)/AB16,((W16*T16*(IF(AD16=0,AC16,AD16)/100))+IF(X16<W16,0,(X16-W16)*T16*IF(AD16=0,AC16,AD16)/100*U16))/AB16) -> #N/A | AF16: 0 | AG16: =IF(INDEX(Index,MATCH(Z16,TVM_PortList,0),MATCH("Type",Control!$Q$3:$U$3,0))="BL",INDEX(Index,MATCH(Z16,TVM_PortList,0),MATCH("Payment",Control!$Q$3:$U$3,0))-INDEX(Index,MATCH(V16,TVM_PortList,0),MATCH("Payment",Control!$Q$3:$U$3,0)),BC16+INDEX(Index,MATCH(Z16,TVM_PortList,0),MATCH("Payment",Control!$Q$3:$U$3,0))-INDEX(Index,MATCH(V16,TVM_PortList,0),MATCH("Payment",Control!$Q$3:$U$3,0))) -> #N/A | AI16: =AF16*VLOOKUP($Y16,Control!$F$75:$H$79,3,FALSE)/$AB16 -> 0 | AJ16: =IF(AG16<0,0,$AG16*Control!$D$77) -> #N/A | AL16: =INDEX(Lightering,MATCH($V16,Control!$AB$3:$AB$29,0),MATCH(WTI!$Y16,Control!$AB$3:$AF$3,0))*($AB16/Control!$D$85)*Control!$H$90/$AB16 -> 0 | AM16: =IF(I16="Corpus Christi",Control!$D$76,0) -> 0 | AN16: 0 | AO16: =Control!$D$78 -> 0 | AP16: =Control!$D$79 -> 0.0673 | AQ16: =IF(INDEX(Control!$Q$3:$S$62,MATCH($Z16,Control!$Q$3:$Q$62,0),MATCH(AQ$9,Control!$Q$3:$S$3,0))=1,Control!$D$81*Control!$E$81,0) -> 0.2 | AR16: =IF(INDEX(Control!$Q$3:$S$62,MATCH($Z16,Control!$Q$3:$Q$62,0),MATCH(AR$9,Control!$Q$3:$S$3,0))=1,Control!$D$82/$AB16,0) -> 0 | AT16: =IF(AND(L16="Chiriqui Grande",V16="Puerto Armuelles"),Control!$G$93,0) -> 0 | AU16: =SUM(AI16:AT16) -> #N/A | AV16: =+R16+AE16+AU16 -> #N/A | AW16: =IF((MONTH(A16)=MONTH(BE16)),0,IF((MONTH(BE16)+12)-(MONTH(A16)+12)>1,VLOOKUP("Spreads",$BC$3:$BG$4,MATCH(EOMONTH(BE16,0),$BC$3:$BG$3,0),FALSE)+VLOOKUP("Spreads",$BC$3:$BG$4,MATCH(EOMONTH(BE16,-1),$BC$3:$BG$3,0),FALSE),VLOOKUP("Spreads",$BC$3:$BG$4,MATCH(EOMONTH(A16,0),$BC$3:$BG$3,0)))) -> #VALUE! | AX16: 0 | AZ16: =$Y$3+AV16+AW16+AX16 -> #N/A | BC16: =INDEX('[1]Transit Time'!$A:$DZ,MATCH(I16,'[1]Transit Time'!$A:$A,0),MATCH(L16,'[1]Transit Time'!$A$1:$DZ$1,0))+INDEX('[1]Transit Time'!$A:$DZ,MATCH(L16,'[1]Transit Time'!$A:$A,0),MATCH(V16,'[1]Transit Time'!$A$1:$DZ$1,0))+INDEX('[1]Transit Time'!$A:$DZ,MATCH(V16,'[1]Transit Time'!$A:$A,0),MATCH(Z16,'[1]Transit Time'!$A$1:$DZ$1,0)) -> #N/A | BD16: =IF(ISBLANK(A16),"",A16+$BC16) -> #N/A | BE16: =IFERROR(IF(ISBLANK(B16),"",B16+$BC16),"")
B17: =IF(ISBLANK(A17),"",A17+2) -> #VALUE! | D17: =IF(AL17=0,0,VLOOKUP(Y17,Control!$G$41:$J$44,4,FALSE)) -> 0 | E17: =AVERAGE(A17:B17)+D17 -> #VALUE! | T17: =INDEX('[2]Flat Rates 2025'!$A:$DZ,MATCH(V17,'[2]Flat Rates 2025'!$A:$A,0),MATCH(Z17,'[2]Flat Rates 2025'!$A$1:$DZ$1,0)) -> 0 | U17: =INDEX(Control!$E$17:$J$21,MATCH(Y17,Control!$E$17:$E$21,0),MATCH(V17,Control!$E$17:$J$17,0)) -> 0 | V17: Corpus Christi | W17: =INDEX(Vessel_Minimum_MT,MATCH(Y17,Control!$E$11:$E$15,0),MATCH(V17,Control!$E$11:$J$11,0)) -> 70000 | X17: =AB17/Control!$D$84 -> 96532.466 | Y17: Aframax | Z17: Quintero (MB) | AA17: =IF(Z17=V17,"",CONCATENATE(CONCATENATE(VLOOKUP(V17,Zones,2,FALSE),"/",VLOOKUP(Z17,Zones,2,FALSE)))) -> USGC/LATAM WEST | AB17: 750000 | AC17: 1001 | AD17: 1600000 | AE17: =IF(AC17>1000,IF(AD17=0,AC17,AD17)/AB17,((W17*T17*(IF(AD17=0,AC17,AD17)/100))+IF(X17<W17,0,(X17-W17)*T17*IF(AD17=0,AC17,AD17)/100*U17))/AB17) -> 2.1333333 | AF17: 3 | AG17: =IF(INDEX(Index,MATCH(Z17,TVM_PortList,0),MATCH("Type",Control!$Q$3:$U$3,0))="BL",INDEX(Index,MATCH(Z17,TVM_PortList,0),MATCH("Payment",Control!$Q$3:$U$3,0))-INDEX(Index,MATCH(V17,TVM_PortList,0),MATCH("Payment",Control!$Q$3:$U$3,0)),BC17+INDEX(Index,MATCH(Z17,TVM_PortList,0),MATCH("Payment",Control!$Q$3:$U$3,0))-INDEX(Index,MATCH(V17,TVM_PortList,0),MATCH("Payment",Control!$Q$3:$U$3,0))) -> 0 | AI17: =AF17*VLOOKUP($Y17,Control!$F$75:$H$79,3,FALSE)/$AB17 -> 0.32 | AJ17: =IF(AG17<0,0,$AG17*Control!$D$77) -> 0 | AL17: =INDEX(Lightering,MATCH($V17,Control!$AB$3:$AB$29,0),MATCH(WTI!$Y17,Control!$AB$3:$AF$3,0))*($AB17/Control!$D$85)*Control!$H$90/$AB17 -> 0 | AM17: =IF(I17="Corpus Christi",Control!$D$76,0) -> 0 | AN17: 0 | AO17: =Control!$D$78 -> 0 | AP17: =Control!$D$79 -> 0.0673 | AQ17: =IF(INDEX(Control!$Q$3:$S$62,MATCH($Z17,Control!$Q$3:$Q$62,0),MATCH(AQ$9,Control!$Q$3:$S$3,0))=1,Control!$D$81*Control!$E$81,0) -> 0 | AR17: =IF(INDEX(Control!$Q$3:$S$62,MATCH($Z17,Control!$Q$3:$Q$62,0),MATCH(AR$9,Control!$Q$3:$S$3,0))=1,Control!$D$82/$AB17,0) -> 0 | AT17: =IF(AND(L17="Chiriqui Grande",V17="Puerto Armuelles"),Control!$G$93,0) -> 0 | AU17: =SUM(AI17:AT17) -> 0.3873 | AV17: =+R17+AE17+AU17 -> 2.5206333 | AW17: =IF((MONTH(A17)=MONTH(BH17)),0,IF(((MONTH(BH17))-MONTH(A17))+12*YEAR(BG17)-YEAR(A17)>1,SUMIFS($BD$4:$BG$4,$BD$3:$BG$3,"<="&EOMONTH(BG17,-1),$BD$3:$BG$3,">="&EOMONTH(A17,0)),VLOOKUP("Spreads",$BC$3:$BG$4,MATCH(EOMONTH(A17,0),$BC$3:$BG$3,0)))) -> #VALUE! | AX17: =+IF($BC$3=1,HLOOKUP(EOMONTH(BE17,0),$BD$3:$BG$6,4,FALSE),IF($BC$3=2,-HLOOKUP(EOMONTH(BE17,0),$BD$3:$BG$6,3,FALSE),0)) -> #VALUE! | AZ17: =$Y$3+AV17+AW17+AX17 -> #VALUE! | BC17: =+INDEX('[1]Transit Time'!$A:$DZ,MATCH(V17,'[1]Transit Time'!$A:$A,0),MATCH(Z17,'[1]Transit Time'!$A$1:$DZ$1,0)) -> 18 | BD17: =IF(ISBLANK(A17),"",A17+$BC17+D17) -> #VALUE! | BE17: =IFERROR(IF(ISBLANK(B17),"",B17+$BC17),"") | BF17: =HLOOKUP($BC$3,$AV$3:$AX$3,2,FALSE) -> #N/A | BG17: =IF($BC$8=0,IF(BF17="ICE Brent",EOMONTH(BE17,2),EOMONTH(BE17,0)),IF(BF17="ICE Brent",EOMONTH(BE17,1),EOMONTH(BE17,-1))) -> #N/A | BH17: =IF($BC$8=1,EOMONTH(BE17,-1),EOMONTH(BE17,0)) -> #VALUE!
A18: =+$A$10 -> 46334 | B18: =IF(ISBLANK(A18),"",A18+2) -> 46336 | D18: =IF(AL18=0,0,VLOOKUP(Y18,Control!$G$41:$J$44,4,FALSE)) -> 0 | E18: =AVERAGE(A18:B18)+D18 -> 46335 | T18: =INDEX('[2]Flat Rates 2025'!$A:$DZ,MATCH(V18,'[2]Flat Rates 2025'!$A:$A,0),MATCH(Z18,'[2]Flat Rates 2025'!$A$1:$DZ$1,0)) -> 0 | U18: =INDEX(Control!$E$17:$J$21,MATCH(Y18,Control!$E$17:$E$21,0),MATCH(V18,Control!$E$17:$J$17,0)) -> 0 | V18: Corpus Christi | W18: =INDEX(Vessel_Minimum_MT,MATCH(Y18,Control!$E$11:$E$15,0),MATCH(V18,Control!$E$11:$J$11,0)) -> 70000 | X18: =AB18/Control!$D$84 -> 96532.466 | Y18: Aframax | Z18: Sao Sebastiao | AA18: =IF(Z18=V18,"",CONCATENATE(CONCATENATE(VLOOKUP(V18,Zones,2,FALSE),"/",VLOOKUP(Z18,Zones,2,FALSE)))) -> USGC/BAYOVAR+T | AB18: 750000 | AD18: 190 | AE18: =IF(AC18>1000,IF(AD18=0,AC18,AD18)/AB18,((W18*T18*(IF(AD18=0,AC18,AD18)/100))+IF(X18<W18,0,(X18-W18)*T18*IF(AD18=0,AC18,AD18)/100*U18))/AB18) -> 0 | AF18: 2 | AG18: =IF(INDEX(Index,MATCH(Z18,TVM_PortList,0),MATCH("Type",Control!$Q$3:$U$3,0))="BL",INDEX(Index,MATCH(Z18,TVM_PortList,0),MATCH("Payment",Control!$Q$3:$U$3,0))-INDEX(Index,MATCH(V18,TVM_PortList,0),MATCH("Payment",Control!$Q$3:$U$3,0)),BC18+INDEX(Index,MATCH(Z18,TVM_PortList,0),MATCH("Payment",Control!$Q$3:$U$3,0))-INDEX(Index,MATCH(V18,TVM_PortList,0),MATCH("Payment",Control!$Q$3:$U$3,0))) -> 2 | AI18: =AF18*VLOOKUP($Y18,Control!$F$75:$H$79,3,FALSE)/$AB18 -> 0.21333333 | AJ18: =IF(AG18<0,0,$AG18*Control!$D$77) -> 0.026072329 | AL18: =INDEX(Lightering,MATCH($V18,Control!$AB$3:$AB$29,0),MATCH(WTI!$Y18,Control!$AB$3:$AF$3,0))*($AB18/Control!$D$85)*Control!$H$90/$AB18 -> 0 | AM18: =IF(I18="Corpus Christi",Control!$D$76,0) -> 0 | AN18: 0.62666667 | AO18: =Control!$D$78 -> 0 | AP18: =Control!$D$79 -> 0.0673 | AQ18: =IF(INDEX(Control!$Q$3:$S$62,MATCH($Z18,Control!$Q$3:$Q$62,0),MATCH(AQ$9,Control!$Q$3:$S$3,0))=1,Control!$D$81*Control!$E$81,0) -> 0 | AR18: =IF(INDEX(Control!$Q$3:$S$62,MATCH($Z18,Control!$Q$3:$Q$62,0),MATCH(AR$9,Control!$Q$3:$S$3,0))=1,Control!$D$82/$AB18,0) -> 0 | AT18: =IF(AND(L18="Chiriqui Grande",V18="Puerto Armuelles"),Control!$G$93,0) -> 0 | AU18: =SUM(AI18:AT18) -> 0.93337233 | AV18: =+R18+AE18+AU18 -> 0.93337233 | AW18: =IF((MONTH(A18)=MONTH(BH18)),0,IF(((MONTH(BH18))-MONTH(A18))+12*YEAR(BG18)-YEAR(A18)>1,SUMIFS($BD$4:$BG$4,$BD$3:$BG$3,"<="&EOMONTH(BG18,-1),$BD$3:$BG$3,">="&EOMONTH(A18,0)),VLOOKUP("Spreads",$BC$3:$BG$4,MATCH(EOMONTH(A18,0),$BC$3:$BG$3,0)))) -> #N/A | AX18: =+IF($BC$3=1,HLOOKUP(EOMONTH(BE18,0),$BD$3:$BG$6,4,FALSE),IF($BC$3=2,-HLOOKUP(EOMONTH(BE18,0),$BD$3:$BG$6,3,FALSE),0)) -> -1.7 | AZ18: =$Y$3+AV18+AW18+AX18 -> #N/A | BC18: =+INDEX('[1]Transit Time'!$A:$DZ,MATCH(V18,'[1]Transit Time'!$A:$A,0),MATCH(Z18,'[1]Transit Time'!$A$1:$DZ$1,0)) -> 19 | BD18: =IF(ISBLANK(A18),"",A18+$BC18+D18) -> 46353 | BE18: =IFERROR(IF(ISBLANK(B18),"",B18+$BC18),"") -> 46355 | BF18: =HLOOKUP($BC$3,$AV$3:$AX$3,2,FALSE) -> #N/A | BG18: =IF($BC$8=0,IF(BF18="ICE Brent",EOMONTH(BE18,2),EOMONTH(BE18,0)),IF(BF18="ICE Brent",EOMONTH(BE18,1),EOMONTH(BE18,-1))) -> #N/A | BH18: =IF($BC$8=1,EOMONTH(BE18,-1),EOMONTH(BE18,0)) -> 46326
A19: =+$A$10 -> 46334 | B19: =IF(ISBLANK(A19),"",A19+2) -> 46336 | D19: =IF(AL19=0,0,VLOOKUP(Y19,Control!$G$41:$J$44,4,FALSE)) -> 0 | E19: =AVERAGE(A19:B19)+D19 -> 46335 | T19: =INDEX('[2]Flat Rates 2025'!$A:$DZ,MATCH(V19,'[2]Flat Rates 2025'!$A:$A,0),MATCH(Z19,'[2]Flat Rates 2025'!$A$1:$DZ$1,0)) -> 0 | U19: =INDEX(Control!$E$17:$J$21,MATCH(Y19,Control!$E$17:$E$21,0),MATCH(V19,Control!$E$17:$J$17,0)) -> 0.5 | V19: Corpus Christi | W19: =INDEX(Vessel_Minimum_MT,MATCH(Y19,Control!$E$11:$E$15,0),MATCH(V19,Control!$E$11:$J$11,0)) -> 145000 | X19: =AB19/Control!$D$84 -> 109403.46 | Y19: Suezmax | Z19: Sao Sebastiao | AA19: =IF(Z19=V19,"",CONCATENATE(CONCATENATE(VLOOKUP(V19,Zones,2,FALSE),"/",VLOOKUP(Z19,Zones,2,FALSE)))) -> USGC/BAYOVAR+T | AB19: 850000 | AD19: 90 | AE19: =IF(AC19>1000,IF(AD19=0,AC19,AD19)/AB19,((W19*T19*(IF(AD19=0,AC19,AD19)/100))+IF(X19<W19,0,(X19-W19)*T19*IF(AD19=0,AC19,AD19)/100*U19))/AB19) -> 0 | AF19: 2 | AG19: =IF(INDEX(Index,MATCH(Z19,TVM_PortList,0),MATCH("Type",Control!$Q$3:$U$3,0))="BL",INDEX(Index,MATCH(Z19,TVM_PortList,0),MATCH("Payment",Control!$Q$3:$U$3,0))-INDEX(Index,MATCH(V19,TVM_PortList,0),MATCH("Payment",Control!$Q$3:$U$3,0)),BC19+INDEX(Index,MATCH(Z19,TVM_PortList,0),MATCH("Payment",Control!$Q$3:$U$3,0))-INDEX(Index,MATCH(V19,TVM_PortList,0),MATCH("Payment",Control!$Q$3:$U$3,0))) -> 2 | AI19: =ABH364*VLOOKUP($Y19,Control!$F$75:$H$79,3,FALSE)/$AB19 -> 0 | AJ19: =IF(AG19<0,0,$AG19*Control!$D$77) -> 0.026072329 | AM19: =IF(I19="Corpus Christi",Control!$D$76,0) -> 0 | AN19: 0 | AO19: =Control!$D$78 -> 0 | AP19: =Control!$D$79 -> 0.0673 | AQ19: =IF(INDEX(Control!$Q$3:$S$62,MATCH($Z19,Control!$Q$3:$Q$62,0),MATCH(AQ$9,Control!$Q$3:$S$3,0))=1,Control!$D$81*Control!$E$81,0) -> 0 | AR19: =IF(INDEX(Control!$Q$3:$S$62,MATCH($Z19,Control!$Q$3:$Q$62,0),MATCH(AR$9,Control!$Q$3:$S$3,0))=1,Control!$D$82/$AB19,0) -> 0 | AT19: =IF(AND(L19="Chiriqui Grande",V19="Puerto Armuelles"),Control!$G$93,0) -> 0 | AU19: =SUM(AI19:AT19) -> 0.093372329 | AV19: =+R19+AE19+AU19 -> 0.093372329 | AW19: =IF((MONTH(A19)=MONTH(BH19)),0,IF(((MONTH(BH19))-MONTH(A19))+12*YEAR(BG19)-YEAR(A19)>1,SUMIFS($BD$4:$BH$4,$BD$3:$BH$3,"<="&EOMONTH(BG19,-1),$BD$3:$BH$3,">="&EOMONTH(A19,0)),VLOOKUP("Spreads",$BC$3:$BH$4,MATCH(EOMONTH(A19,0),$BC$3:$BH$3,0)))) -> 0 | AZ19: =$Y$3+AV19+AW19+AX19 -> -3.5066277 | BC19: =+INDEX('[1]Transit Time'!$A:$DZ,MATCH(V19,'[1]Transit Time'!$A:$A,0),MATCH(Z19,'[1]Transit Time'!$A$1:$DZ$1,0)) -> 19 | BD19: =IF(ISBLANK(A19),"",A19+$BC19+D19) -> 46353 | BE19: =BD19+2 -> 46355 | BF19: ICE Brent | BG19: =BH19 -> 46356 | BH19: =EOMONTH(BE19,0) -> 46356
A20: =+$A$10 -> 46334 | B20: =IF(ISBLANK(A20),"",A20+2) -> 46336 | D20: =IF(AL20=0,0,VLOOKUP(Y20,Control!$G$41:$J$44,4,FALSE)) -> 0 | E20: =AVERAGE(A20:B20)+D20 -> 46335 | T20: =INDEX('[2]Flat Rates 2025'!$A:$DZ,MATCH(V20,'[2]Flat Rates 2025'!$A:$A,0),MATCH(Z20,'[2]Flat Rates 2025'!$A$1:$DZ$1,0)) -> 0 | U20: =INDEX(Control!$E$17:$J$21,MATCH(Y20,Control!$E$17:$E$21,0),MATCH(V20,Control!$E$17:$J$17,0)) -> 0 | V20: Corpus Christi | W20: =INDEX(Vessel_Minimum_MT,MATCH(Y20,Control!$E$11:$E$15,0),MATCH(V20,Control!$E$11:$J$11,0)) -> 70000 | X20: =AB20/Control!$D$84 -> 90096.968 | Y20: Aframax | Z20: Saint John | AA20: =IF(Z20=V20,"",CONCATENATE(CONCATENATE(VLOOKUP(V20,Zones,2,FALSE),"/",VLOOKUP(Z20,Zones,2,FALSE)))) -> USGC/ECC | AB20: 700000 | AD20: =AD21 -> 927.5 | AE20: =IF(AC20>1000,IF(AD20=0,AC20,AD20)/AB20,((W20*T20*(IF(AD20=0,AC20,AD20)/100))+IF(X20<W20,0,(X20-W20)*T20*IF(AD20=0,AC20,AD20)/100*U20))/AB20) -> 0 | AF20: 1 | AG20: =IF(INDEX(Index,MATCH(Z20,TVM_PortList,0),MATCH("Type",Control!$Q$3:$U$3,0))="BL",INDEX(Index,MATCH(Z20,TVM_PortList,0),MATCH("Payment",Control!$Q$3:$U$3,0))-INDEX(Index,MATCH(V20,TVM_PortList,0),MATCH("Payment",Control!$Q$3:$U$3,0)),BC20+INDEX(Index,MATCH(Z20,TVM_PortList,0),MATCH("Payment",Control!$Q$3:$U$3,0))-INDEX(Index,MATCH(V20,TVM_PortList,0),MATCH("Payment",Control!$Q$3:$U$3,0))) -> 0 | AI20: =ABH365*VLOOKUP($Y20,Control!$F$75:$H$79,3,FALSE)/$AB20 -> 0 | AJ20: =IF(AG20<0,0,$AG20*Control!$D$77) -> 0 | AM20: =IF(I20="Corpus Christi",Control!$D$76,0) -> 0 | AN20: 0 | AO20: =Control!$D$78 -> 0 | AP20: =Control!$D$79 -> 0.0673 | AQ20: =IF(INDEX(Control!$Q$3:$S$62,MATCH($Z20,Control!$Q$3:$Q$62,0),MATCH(AQ$9,Control!$Q$3:$S$3,0))=1,Control!$D$81*Control!$E$81,0) -> 0 | AR20: =IF(INDEX(Control!$Q$3:$S$62,MATCH($Z20,Control!$Q$3:$Q$62,0),MATCH(AR$9,Control!$Q$3:$S$3,0))=1,Control!$D$82/$AB20,0) -> 0 | AT20: =IF(AND(L20="Chiriqui Grande",V20="Puerto Armuelles"),Control!$G$93,0) -> 0 | AU20: =SUM(AI20:AT20) -> 0.0673 | AV20: =+R20+AE20+AU20 -> 0.0673 | AW20: =IF((MONTH(A20)=MONTH(BH20)),0,IF(((MONTH(BH20))-MONTH(A20))+12*YEAR(BG20)-YEAR(A20)>1,SUMIFS($BD$4:$BH$4,$BD$3:$BH$3,"<="&EOMONTH(BG20,-1),$BD$3:$BH$3,">="&EOMONTH(A20,0)),VLOOKUP("Spreads",$BC$3:$BH$4,MATCH(EOMONTH(A20,0),$BC$3:$BH$3,0)))) -> 0 | AZ20: =$Y$3+AV20+AW20+AX20 -> -3.5327 | BC20: =+INDEX('[1]Transit Time'!$A:$DZ,MATCH(V20,'[1]Transit Time'!$A:$A,0),MATCH(Z20,'[1]Transit Time'!$A$1:$DZ$1,0)) -> 8 | BD20: =IF(ISBLANK(A20),"",A20+$BC20+D20) -> 46342 | BE20: =BD20+2 -> 46344 | BF20: ICE Brent | BG20: =BH20 -> 46356 | BH20: =EOMONTH(BE20,0) -> 46356
A21: =A9 -> 46334 | B21: =B9 -> 46336 | D21: =IF(AL21=0,0,VLOOKUP(Y21,Control!$G$41:$J$44,4,FALSE)) -> 0 | E21: =AVERAGE(A21:B21)+D21 -> 46335 | T21: =T22 -> 12.01 | U21: =INDEX(Control!$E$17:$J$21,MATCH(Y21,Control!$E$17:$E$21,0),MATCH(V21,Control!$E$17:$J$17,0)) -> 0 | V21: Corpus Christi | W21: =INDEX(Vessel_Minimum_MT,MATCH(Y21,Control!$E$11:$E$15,0),MATCH(V21,Control!$E$11:$J$11,0)) -> 70000 | X21: =AB21/Control!$D$84 -> 90096.968 | Y21: Aframax | Z21: Saint John | AA21: =IF(Z21=V21,"",CONCATENATE(CONCATENATE(VLOOKUP(V21,Zones,2,FALSE),"/",VLOOKUP(Z21,Zones,2,FALSE)))) -> USGC/ECC | AB21: 700000 | AC21: 70 | AD21: =AD52+7.5 -> 927.5 | AE21: =IF(AC21>1000,IF(AD21=0,AC21,AD21)/AB21,((W21*T21*(IF(AD21=0,AC21,AD21)/100))+IF(X21<W21,0,(X21-W21)*T21*IF(AD21=0,AC21,AD21)/100*U21))/AB21) -> 11.139275 | AF21: 0 | AG21: =AG52 -> -10 | AH21: =AH52 -> 0 | AI21: =AF21*VLOOKUP($Y21,Control!$F$75:$H$87,3,FALSE)/$AB21 -> 0 | AJ21: =IF($AK$3=1,$AG21*Control!$D$77,0) -> 0 | AK21: =IF($AK$4=1,$AH21*Control!$D$77,0) -> 0 | AQ21: =IF(INDEX(Control!$Q$3:$S$62,MATCH($Z21,Control!$Q$3:$Q$62,0),MATCH(AQ$9,Control!$Q$3:$S$3,0))=1,Control!$D$81*Control!$E$81,0) -> 0 | AR21: =IF(INDEX(Control!$Q$3:$S$62,MATCH($Z21,Control!$Q$3:$Q$62,0),MATCH(AR$9,Control!$Q$3:$S$3,0))=1,INDEX(Control!$AK$3:$AO$69,MATCH(WTI!Z21,Control!$AK$3:$AK$29,0),MATCH(WTI!Y21,Control!$AK$3:$AO$3,0))/AB21*1000,0) -> 0 | AS21: =52000/AB21 -> 0.074285714 | AU21: =SUM(AI21:AT21) -> 0.074285714 | AV21: =+R21+AE21+AU21 -> 11.213561 | AW21: =IF((MONTH(A21)=MONTH(BH21)),0,IF(((MONTH(BH21))-MONTH(A21))+12*YEAR(BG21)-YEAR(A21)>1,SUMIFS($BD$4:$BH$4,$BD$3:$BH$3,"<="&EOMONTH(BG21,-1),$BD$3:$BH$3,">="&EOMONTH(A21,0)),VLOOKUP("Spreads",$BC$3:$BH$4,MATCH(EOMONTH(A21,0),$BC$3:$BH$3,0)))) -> 0 | AZ21: =$Y$3+AV21+AW21+AX21 -> 7.6135607 | BC21: =+INDEX('[1]Transit Time'!$A:$DZ,MATCH(V21,'[1]Transit Time'!$A:$A,0),MATCH(Z21,'[1]Transit Time'!$A$1:$DZ$1,0)) -> 8 | BD21: =E21+BC21 -> 46343 | BE21: =BD21+2 -> 46345 | BF21: =BF22 -> ICE Brent | BG21: =EOMONTH(BE21,0) -> 46356 | BH21: =BG21 -> 46356 | BI21: =AE21*AB21 -> 7797492.5 | BK21: =AI21*AB21 -> 0 | BL21: =(AU21-AI21-AJ21)*AB21 -> 52000 | BM21: =AJ21*AB21 -> 0 | BP21: =(AV21-AJ21)*AB21 -> 7849492.5 | BQ21: =BP21-BM21 -> 7849492.5
A22: =+$A$10 -> 46334 | B22: =IF(ISBLANK(A22),"",A22+2) -> 46336 | D22: =IF(AL22=0,0,VLOOKUP(Y22,Control!$G$41:$J$44,4,FALSE)) -> 0 | E22: =AVERAGE(A22:B22)+D22 -> 46335 | T22: 12.01 | U22: =INDEX(Control!$E$17:$J$21,MATCH(Y22,Control!$E$17:$E$21,0),MATCH(V22,Control!$E$17:$J$17,0)) -> 0.5 | V22: Corpus Christi | W22: =INDEX(Vessel_Minimum_MT,MATCH(Y22,Control!$E$11:$E$15,0),MATCH(V22,Control!$E$11:$J$11,0)) -> 145000 | X22: =AB22/Control!$D$84 -> 94601.816 | Y22: Suezmax | Z22: Saint John | AA22: =IF(Z22=V22,"",CONCATENATE(CONCATENATE(VLOOKUP(V22,Zones,2,FALSE),"/",VLOOKUP(Z22,Zones,2,FALSE)))) -> USGC/ECC | AB22: 735000 | AD22: 72 | AE22: =IF(AC22>1000,IF(AD22=0,AC22,AD22)/AB22,((W22*T22*(IF(AD22=0,AC22,AD22)/100))+IF(X22<W22,0,(X22-W22)*T22*IF(AD22=0,AC22,AD22)/100*U22))/AB22) -> 1.7059102 | AF22: 0 | AG22: =AG21 -> -10 | AH22: =AH21 -> 0 | AI22: =ABH367*VLOOKUP($Y22,Control!$F$75:$H$79,3,FALSE)/$AB22 -> 0 | AJ22: =IF(AG22<0,0,$AG22*Control!$D$77) -> 0 | AM22: =IF(I22="Corpus Christi",Control!$D$76,0) -> 0 | AN22: 0 | AO22: =Control!$D$78 -> 0 | AQ22: =IF(INDEX(Control!$Q$3:$S$62,MATCH($Z22,Control!$Q$3:$Q$62,0),MATCH(AQ$9,Control!$Q$3:$S$3,0))=1,Control!$D$81*Control!$E$81,0) -> 0 | AR22: =IF(INDEX(Control!$Q$3:$S$62,MATCH($Z22,Control!$Q$3:$Q$62,0),MATCH(AR$9,Control!$Q$3:$S$3,0))=1,Control!$D$82/$AB22,0) -> 0 | AS22: =52000/AB22 -> 0.070748299 | AT22: =IF(AND(L22="Chiriqui Grande",V22="Puerto Armuelles"),Control!$G$93,0) -> 0 | AU22: =SUM(AI22:AT22) -> 0.070748299 | AV22: =+R22+AE22+AU22 -> 1.7766585 | AW22: =IF((MONTH(A22)=MONTH(BH22)),0,IF(((MONTH(BH22))-MONTH(A22))+12*YEAR(BG22)-YEAR(A22)>1,SUMIFS($BD$4:$BH$4,$BD$3:$BH$3,"<="&EOMONTH(BG22,-1),$BD$3:$BH$3,">="&EOMONTH(A22,0)),VLOOKUP("Spreads",$BC$3:$BH$4,MATCH(EOMONTH(A22,0),$BC$3:$BH$3,0)))) -> 0 | AZ22: =$Y$3+AV22+AW22+AX22 -> -1.8233415 | BC22: =+INDEX('[1]Transit Time'!$A:$DZ,MATCH(V22,'[1]Transit Time'!$A:$A,0),MATCH(Z22,'[1]Transit Time'!$A$1:$DZ$1,0)) -> 8 | BD22: =IF(ISBLANK(A22),"",A22+$BC22+D22) -> 46342 | BE22: =BD22+2 -> 46344 | BF22: ICE Brent | BG22: =BH22 -> 46356 | BH22: =EOMONTH(BE22,0) -> 46356
A23: Load Window | D23: =D9 -> STS Time | E23: =E9 -> Depart | T23: Flat | U23: =INDEX(Control!$E$17:$J$21,MATCH(Y23,Control!$E$17:$E$21,0),MATCH(V23,Control!$E$17:$J$17,0)) -> #N/A | V23: Loadport | W23: =$W$9 -> Vessel MT | X23: Actual MT | Y23: Vessel | Z23: Destination | AA23: Route | AB23: Volume | AC23: Current WS Rate | AD23: WS Rate Call | AE23: Freight | AF23: Demm. | AG23: ATA tvm | AH23: =AH9 -> Ext. TVM | AI23: Demm. $ | AJ23: =AG23 -> ATA tvm | AK23: =AH23 -> Ext. TVM | AL23: =AL9 -> STS | AM23: Wharfage | AN23: Panama Canal | AO23: Insurance | AP23: Inspection | AQ23: Outturn Losses | AR23: ECA costs | AS23: Corpus Dock Fee | AT23: Pipeline Fee | AU23: Total Secondary Costs | AV23: All In Cost | AW23: Structure | AX23: =AX9 -> Basis | AZ23: DES Price | BC23: Transit Time | BD23: Arrival Window | BF23: =BF9 -> Basis | BG23: =BG9 -> Pricing Month | BH23: =BH9 -> Delivery Month | BP23: with | BQ23: without | BS23: BL+30 | BT23: NOR+xx
A24: =A22 -> 46334 | B24: =B9 -> 46336 | E24: =AVERAGE(A24:B24)+D24 -> 46335 | T24: =INDEX('[2]Flat Rates 2025'!$A:$DZ,MATCH(V24,'[2]Flat Rates 2025'!$A:$A,0),MATCH(Z24,'[2]Flat Rates 2025'!$A$1:$DZ$1,0)) -> 0 | U24: =INDEX(Control!$E$17:$J$21,MATCH(Y24,Control!$E$17:$E$21,0),MATCH(V24,Control!$E$17:$J$17,0)) -> 0 | V24: Corpus Christi | W24: =INDEX(Vessel_Minimum_MT,MATCH(Y24,Control!$E$11:$E$15,0),MATCH(V24,Control!$E$11:$J$11,0)) -> 70000 | X24: =AB24/Control!$D$84 -> 96532.466 | Y24: Aframax | Z24: Daesan | AA24: =IF(Z24=V24,"",CONCATENATE(CONCATENATE(VLOOKUP(V24,Zones,2,FALSE),"/",VLOOKUP(Z24,Zones,2,FALSE)))) -> USGC/KOREA | AB24: 750000 | AC24: 1001 | AD24: 6700000 | AE24: =IF(AC24>1000,IF(AD24=0,AC24,AD24)/AB24,((W24*T24*(IF(AD24=0,AC24,AD24)/100))+IF(X24<W24,0,(X24-W24)*T24*IF(AD24=0,AC24,AD24)/100*U24))/AB24) -> 8.9333333 | AF24: 5 | AG24: =IF(INDEX(Index,MATCH(Z24,TVM_PortList,0),MATCH("Type",Control!$Q$3:$U$3,0))="BL",INDEX(Index,MATCH(Z24,TVM_PortList,0),MATCH("Payment",Control!$Q$3:$U$3,0))-INDEX(Index,MATCH(V24,TVM_PortList,0),MATCH("Payment",Control!$Q$3:$U$3,0)),BC24+INDEX(Index,MATCH(Z24,TVM_PortList,0),MATCH("Payment",Control!$Q$3:$U$3,0))-INDEX(Index,MATCH(V24,TVM_PortList,0),MATCH("Payment",Control!$Q$3:$U$3,0))) -> 19 | AI24: =AF24*VLOOKUP($Y24,Control!$F$75:$H$87,3,FALSE)/$AB24 -> 0.53333333 | AJ24: =$AG24*Control!$D$77 -> 0.24768712 | AL24: =IF(((AB24-VLOOKUP(Y24,Control!$J$76:$K$80,2,FALSE))/Control!$D$85)<=0,0,ROUNDUP(((AB24-VLOOKUP(Y24,Control!$J$76:$K$80,2,FALSE))/Control!$D$85),0)*Control!$H$90/AB24) -> 0 | AM24: =IF(I24="Corpus Christi",Control!$D$76,0) -> 0 | AN24: 0 | AO24: =Control!$D$78 -> 0 | AP24: =Control!$D$79 -> 0.0673 | AQ24: =IF(INDEX(Control!$Q$3:$S$62,MATCH($Z24,Control!$Q$3:$Q$62,0),MATCH(AQ$9,Control!$Q$3:$S$3,0))=1,Control!$D$81*Control!$E$81,0) -> 0.2 | AS24: =IF(AND(Y24="VLCC",Control!$K$79=1200000),Control!$D$83/AB24,0) -> 0 | AU24: =SUM(AI24:AT24) -> 1.0483205 | AV24: =+R24+AE24+AU24 -> 9.9816538 | AW24: =IF((MONTH(A24)=MONTH(BH24)),0,IF(((MONTH(BH24))-MONTH(A24))+12*YEAR(BG24)-YEAR(A24)>1,SUMIFS($BD$4:$BG$4,$BD$3:$BG$3,"<="&EOMONTH(BG24,-1),$BD$3:$BG$3,">="&EOMONTH(A24,0)),VLOOKUP("Spreads",$BC$3:$BG$4,MATCH(EOMONTH(A24,0),$BC$3:$BG$3,0)))) -> 0 | AX24: =+IF($BC$3=1,HLOOKUP(EOMONTH(BG24,0),$BD$3:$BH$6,4,FALSE),IF($BC$3=2,-HLOOKUP(EOMONTH(BG24,0),$BC$3:$BH$6,3,FALSE),0)) -> -1.7 | AZ24: =$Y$3+AV24+AW24+AX24 -> 4.6816538 | BC24: 39 | BD24: =IF(ISBLANK(A24),"",A24+$BC24+D24) -> 46373 | BE24: =BD24+2 -> 46375 | BF24: =HLOOKUP($BC$3,$AV$4:$AX$5,2,FALSE) -> Dubai | BG24: =IF($BC$8=0,IF(BF24="ICE Brent",EOMONTH(BE24,2),EOMONTH(BE24,0)),IF(BF24="ICE Brent",EOMONTH(BE24,1),EOMONTH(BE24,-1))) -> 46356 | BH24: =IF($BC$8=1,EOMONTH(BE24,-1),EOMONTH(BE24,0)) -> 46356
A25: =+$A$10 -> 46334 | B25: =IF(ISBLANK(A25),"",A25+2) -> 46336 | E25: =AVERAGE(A25:B25)+D25 -> 46335 | T25: =INDEX('[2]Flat Rates 2025'!$A:$DZ,MATCH(V25,'[2]Flat Rates 2025'!$A:$A,0),MATCH(Z25,'[2]Flat Rates 2025'!$A$1:$DZ$1,0)) -> 0 | U25: =INDEX(Control!$E$17:$J$21,MATCH(Y25,Control!$E$17:$E$21,0),MATCH(V25,Control!$E$17:$J$17,0)) -> 0.5 | V25: Corpus Christi | W25: =INDEX(Vessel_Minimum_MT,MATCH(Y25,Control!$E$11:$E$15,0),MATCH(V25,Control!$E$11:$J$11,0)) -> 145000 | X25: =AB25/Control!$D$84 -> 109403.46 | Y25: Suezmax | Z25: Daesan | AA25: =IF(Z25=V25,"",CONCATENATE(CONCATENATE(VLOOKUP(V25,Zones,2,FALSE),"/",VLOOKUP(Z25,Zones,2,FALSE)))) -> USGC/KOREA | AB25: 850000 | AC25: 1001 | AD25: 7500000 | AE25: =IF(AC25>1000,IF(AD25=0,AC25,AD25)/AB25,((W25*T25*(IF(AD25=0,AC25,AD25)/100))+IF(X25<W25,0,(X25-W25)*T25*IF(AD25=0,AC25,AD25)/100*U25))/AB25) -> 8.8235294 | AF25: 2 | AG25: =IF(INDEX(Index,MATCH(Z25,TVM_PortList,0),MATCH("Type",Control!$Q$3:$U$3,0))="BL",INDEX(Index,MATCH(Z25,TVM_PortList,0),MATCH("Payment",Control!$Q$3:$U$3,0))-INDEX(Index,MATCH(V25,TVM_PortList,0),MATCH("Payment",Control!$Q$3:$U$3,0)),BC25+INDEX(Index,MATCH(Z25,TVM_PortList,0),MATCH("Payment",Control!$Q$3:$U$3,0))-INDEX(Index,MATCH(V25,TVM_PortList,0),MATCH("Payment",Control!$Q$3:$U$3,0))) -> 21 | AI25: =AF25*VLOOKUP($Y25,Control!$F$75:$H$87,3,FALSE)/$AB25 -> 0.22352941 | AJ25: =$AG25*Control!$D$77 -> 0.27375945 | AL25: =IF(((AB25-VLOOKUP(Y25,Control!$J$76:$K$80,2,FALSE))/Control!$D$85)<=0,0,ROUNDUP(((AB25-VLOOKUP(Y25,Control!$J$76:$K$80,2,FALSE))/Control!$D$85),0)*Control!$H$90/AB25) -> 0 | AM25: =IF(I25="Corpus Christi",Control!$D$76,0) -> 0 | AN25: 0 | AO25: =Control!$D$78 -> 0 | AP25: =Control!$D$79 -> 0.0673 | AQ25: =IF(INDEX(Control!$Q$3:$S$62,MATCH($Z25,Control!$Q$3:$Q$62,0),MATCH(AQ$9,Control!$Q$3:$S$3,0))=1,Control!$D$81*Control!$E$81,0) -> 0.2 | AS25: =IF(AND(Y25="VLCC",Control!$K$79=1200000),Control!$D$83/AB25,0) -> 0 | AU25: =SUM(AI25:AT25) -> 0.76458886 | AV25: =+R25+AE25+AU25 -> 9.5881183 | AW25: =IF((MONTH(A25)=MONTH(BH25)),0,IF(((MONTH(BH25))-MONTH(A25))+12*YEAR(BG25)-YEAR(A25)>1,SUMIFS($BD$4:$BG$4,$BD$3:$BG$3,"<="&EOMONTH(BG25,-1),$BD$3:$BG$3,">="&EOMONTH(A25,0)),VLOOKUP("Spreads",$BC$3:$BG$4,MATCH(EOMONTH(A25,0),$BC$3:$BG$3,0)))) -> 0 | AX25: =+IF($BC$3=1,HLOOKUP(EOMONTH(BG25,0),$BD$3:$BH$6,4,FALSE),IF($BC$3=2,-HLOOKUP(EOMONTH(BG25,0),$BC$3:$BH$6,3,FALSE),0)) -> -1.7 | AZ25: =$Y$3+AV25+AW25+AX25 -> 4.2881183 | BC25: =BC24+AF25 -> 41 | BD25: =IF(ISBLANK(A25),"",A25+$BC25+D25) -> 46375 | BE25: =BD25+2 -> 46377 | BF25: =HLOOKUP($BC$3,$AV$4:$AX$5,2,FALSE) -> Dubai | BG25: =IF($BC$8=0,IF(BF25="ICE Brent",EOMONTH(BE25,2),EOMONTH(BE25,0)),IF(BF25="ICE Brent",EOMONTH(BE25,1),EOMONTH(BE25,-1))) -> 46356 | BH25: =IF($BC$8=1,EOMONTH(BE25,-1),EOMONTH(BE25,0)) -> 46356
Y26: MODA EIEC | BI26: Freight | BK26: Demurrage | BL26: STS | BM26: ATA TVM | BN26: Ext. TVM | BO26: Other
A27: =+$A$10 -> 46334 | B27: =IF(ISBLANK(A27),"",A27+2) -> 46336 | D27: =IF(AL27=0,0,VLOOKUP(Y27,Control!$G$41:$J$44,4,FALSE)) -> 3 | E27: =AVERAGE(A27:B27)+D27 -> 46338 | T27: 0 | U27: =INDEX(Control!$E$17:$J$21,MATCH(Y27,Control!$E$17:$E$21,0),MATCH(V27,Control!$E$17:$J$17,0)) -> #N/A | V27: Corpus Christi - MODA | W27: 270000 | X27: =AB27/Control!$D$84 -> 257419.91 | Y27: VLCC-MODA | Z27: Chiba | AA27: =AA38 -> 0 | AB27: 2000000 | AC27: 1001 | AD27: =AD28 -> 55000000 | AE27: =IF(AC27>1000,IF(AD27=0,AC27,AD27)/AB27,((W27*T27*(IF(AD27=0,AC27,AD27)/100))+IF(X27<W27,0,(X27-W27)*T27*IF(AD27=0,AC27,AD27)/100*U27))/AB27) -> 27.5 | AF27: 2 | AG27: =AG40 -> -9.5 | AH27: =INDEX(Control!$AS$36:$AY$118,MATCH(WTI!$Z27,Control!$AS$36:$AS$118,0),MATCH(WTI!AH$23,Control!$AS$36:$AY$36,0))-6 -> 30.5 | AI27: =AF27*VLOOKUP($Y27,Control!$F$75:$H$87,3,FALSE)/$AB27 -> 0.45 | AJ27: =IF($AK$3=1,$AG27*Control!$D$77,0) -> 0 | AK27: =IF($AK$4=1,$AH27*Control!$D$77,0) -> 0.39760301 | AL27: =IF(((AB27-VLOOKUP(Y27,Control!$J$76:$K$82,2,FALSE))/AN27)<=0,0,ROUNDUP(((AB27-VLOOKUP(Y27,Control!$J$76:$K$82,2,FALSE))/Control!$D$86),0)*IF(AN27=Control!$D$86,Control!$H$91,Control!$H$90)/AB27) -> 0.925 | AM27: =IF(I27="Corpus Christi",Control!$D$76,0) -> 0 | AN27: =IF(AND(Control!$D$85-ROUNDUP(((AB27-VLOOKUP(Y27,Control!$J$76:$K$82,2,FALSE))),0)>0,Control!$D$85-ROUNDUP(((AB27-VLOOKUP(Y27,Control!$J$76:$K$82,2,FALSE))),0)<Control!$D$86-ROUNDUP(((AB27-VLOOKUP(Y27,Control!$J$76:$K$82,2,FALSE))),0)),Control!$D$85,Control!$D$86) -> 750000 | AO27: =Control!$D$78 -> 0 | AP27: =Control!$D$79 -> 0.0673 | AQ27: =IF(INDEX(Control!$Q$3:$S$62,MATCH($Z27,Control!$Q$3:$Q$62,0),MATCH(AQ$9,Control!$Q$3:$S$3,0))=1,Control!$D$81*Control!$E$81,0) -> 0.2 | AS27: =Control!$D$83/AB27 -> 0.15 | AU27: =SUM(AI27:AM27,AO27:AT27) -> 2.189903 | AV27: =+R27+AE27+AU27 -> 29.689903 | AW27: =IF((MONTH(A27)=MONTH(BH27)),0,IF(((MONTH(BH27))-MONTH(A27))+12*YEAR(BG27)-YEAR(A27)>1,SUMIFS($BD$4:$BH$4,$BD$3:$BH$3,"<="&EOMONTH(BG27,-1),$BD$3:$BH$3,">="&EOMONTH(A27,0)),VLOOKUP("Spreads",$BC$3:$BH$4,MATCH(EOMONTH(A27,0),$BC$3:$BH$3,0)))) -> 0 | AX27: =+IF($BC$3=1,HLOOKUP(EOMONTH(BG27,0),$BD$3:$BH$6,4,FALSE),IF($BC$3=2,-HLOOKUP(EOMONTH(BG27,0),$BC$3:$BH$6,3,FALSE),0)) -> -1.7 | AZ27: =$Y$3+AV27+AW27+AX27 -> 24.389903 | BC27: =BC40 -> 40 | BD27: =IF(ISBLANK(A27),"",A27+$BC27+D27) -> 46377 | BE27: =BD27+2 -> 46379 | BF27: =HLOOKUP($BC$3,$AV$4:$AX$5,2,FALSE) -> Dubai | BG27: =IF($BC$8=0,IF(BF27="ICE Brent",EOMONTH(BE27,2),EOMONTH(BE27,0)),IF(BF27="ICE Brent",EOMONTH(BE27,1),EOMONTH(BE27,-1))) -> 46356 | BH27: =IF($BC$8=1,EOMONTH(BE27,-1),EOMONTH(BE27,0)) -> 46356 | BI27: =AE27*AB27 -> 55000000 | BK27: =AI27*AB27 -> 900000 | BL27: =AL27*AB27 -> 1850000 | BM27: =AJ27*AB27 -> 0 | BN27: =AK27*AB27 -> 795206.03 | BO27: =(AU27-AL27-AK27-AJ27-AI27)*AB27 -> 834600 | BP27: =SUM(BI27:BM27) -> 57750000 | BQ27: =BP27-BM27 -> 57750000
A28: =+$A$10 -> 46334 | B28: =IF(ISBLANK(A28),"",A28+2) -> 46336 | D28: =IF(AL28=0,0,VLOOKUP(Y28,Control!$G$41:$J$44,4,FALSE)) -> 3 | E28: =AVERAGE(A28:B28)+D28 -> 46338 | T28: 0 | U28: =INDEX(Control!$E$17:$J$21,MATCH(Y28,Control!$E$17:$E$21,0),MATCH(V28,Control!$E$17:$J$17,0)) -> #N/A | V28: Corpus Christi - MODA | W28: 270000 | X28: =AB28/Control!$D$84 -> 267073.16 | Y28: VLCC-MODA | Z28: Daesan | AA28: =AA43 -> USGC/KOREA | AB28: =AB43 -> 2075000 | AC28: 1001 | AD28: =AD43 -> 55000000 | AE28: =IF(AC28>1000,IF(AD28=0,AC28,AD28)/AB28,((W28*T28*(IF(AD28=0,AC28,AD28)/100))+IF(X28<W28,0,(X28-W28)*T28*IF(AD28=0,AC28,AD28)/100*U28))/AB28) -> 26.506024 | AF28: 2 | AG28: =AG43 -> -9.5 | AH28: =INDEX(Control!$AS$36:$AY$118,MATCH(WTI!$Z28,Control!$AS$36:$AS$118,0),MATCH(WTI!AH$23,Control!$AS$36:$AY$36,0))-6 -> 32.5 | AI28: =AF28*VLOOKUP($Y28,Control!$F$75:$H$87,3,FALSE)/$AB28 -> 0.43373494 | AJ28: =IF($AK$3=1,$AG28*Control!$D$77,0) -> 0 | AK28: =IF($AK$4=1,$AH28*Control!$D$77,0) -> 0.42367534 | AL28: =IF(((AB28-VLOOKUP(Y28,Control!$J$76:$K$82,2,FALSE))/AN28)<=0,0,ROUNDUP(((AB28-VLOOKUP(Y28,Control!$J$76:$K$82,2,FALSE))/Control!$D$86),0)*IF(AN28=Control!$D$86,Control!$H$91,Control!$H$90)/AB28) -> 0.89156627 | AM28: =IF(I28="Corpus Christi",Control!$D$76,0) -> 0 | AN28: =IF(AND(Control!$D$85-ROUNDUP(((AB28-VLOOKUP(Y28,Control!$J$76:$K$82,2,FALSE))),0)>0,Control!$D$85-ROUNDUP(((AB28-VLOOKUP(Y28,Control!$J$76:$K$82,2,FALSE))),0)<Control!$D$86-ROUNDUP(((AB28-VLOOKUP(Y28,Control!$J$76:$K$82,2,FALSE))),0)),Control!$D$85,Control!$D$86) -> 750000 | AO28: =Control!$D$78 -> 0 | AP28: =Control!$D$79 -> 0.0673 | AS28: =Control!$D$83/AB28 -> 0.14457831 | AU28: =SUM(AI28:AM28,AO28:AT28) -> 1.9608549 | AV28: =+R28+AE28+AU28 -> 28.466879 | AW28: =IF((MONTH(A28)=MONTH(BH28)),0,IF(((MONTH(BH28))-MONTH(A28))+12*YEAR(BG28)-YEAR(A28)>1,SUMIFS($BD$4:$BH$4,$BD$3:$BH$3,"<="&EOMONTH(BG28,-1),$BD$3:$BH$3,">="&EOMONTH(A28,0)),VLOOKUP("Spreads",$BC$3:$BH$4,MATCH(EOMONTH(A28,0),$BC$3:$BH$3,0)))) -> 2.9 | AX28: =+IF($BC$3=1,HLOOKUP(EOMONTH(BG28,0),$BD$3:$BH$6,4,FALSE),IF($BC$3=2,-HLOOKUP(EOMONTH(BG28,0),$BC$3:$BH$6,3,FALSE),0)) -> -0.9 | AZ28: =$Y$3+AV28+AW28+AX28 -> 26.866879 | BC28: =BC43 -> 52 | BD28: =IF(ISBLANK(A28),"",A28+$BC28+D28) -> 46389 | BE28: =BD28+2 -> 46391 | BF28: =HLOOKUP($BC$3,$AV$4:$AX$5,2,FALSE) -> Dubai | BG28: =IF($BC$8=0,IF(BF28="ICE Brent",EOMONTH(BE28,2),EOMONTH(BE28,0)),IF(BF28="ICE Brent",EOMONTH(BE28,1),EOMONTH(BE28,-1))) -> 46387 | BH28: =IF($BC$8=1,EOMONTH(BE28,-1),EOMONTH(BE28,0)) -> 46387 | BI28: =AE28*AB28 -> 55000000 | BK28: =AI28*AB28 -> 900000 | BL28: =AL28*AB28 -> 1850000 | BM28: =AJ28*AB28 -> 0 | BN28: =AK28*AB28 -> 879126.34 | BO28: =(AU28-AL28-AK28-AJ28-AI28)*AB28 -> 439647.5 | BP28: =SUM(BI28:BM28) -> 57750000 | BQ28: =BP28-BM28 -> 57750000 | BR28: =+BQ28/2100000 -> 27.5
A29: =+$A$10 -> 46334 | B29: =IF(ISBLANK(A29),"",A29+2) -> 46336 | D29: =IF(AL29=0,0,VLOOKUP(Y29,Control!$G$41:$J$44,4,FALSE)) -> 3 | E29: =AVERAGE(A29:B29)+D29 -> 46338 | T29: 0 | U29: =INDEX(Control!$E$17:$J$21,MATCH(Y29,Control!$E$17:$E$21,0),MATCH(V29,Control!$E$17:$J$17,0)) -> #N/A | V29: Corpus Christi - MODA | W29: 270000 | X29: =AB29/Control!$D$84 -> 267073.16 | Y29: VLCC-MODA | Z29: Singapore | AA29: =AA44 -> USGC/Singapore | AB29: =AB28 -> 2075000 | AC29: 1001 | AD29: =AD28-1000000 -> 54000000 | AE29: =IF(AC29>1000,IF(AD29=0,AC29,AD29)/AB29,((W29*T29*(IF(AD29=0,AC29,AD29)/100))+IF(X29<W29,0,(X29-W29)*T29*IF(AD29=0,AC29,AD29)/100*U29))/AB29) -> 26.024096 | AF29: 2 | AG29: =AG44 -> -9.5 | AH29: =INDEX(Control!$AS$36:$AY$118,MATCH(WTI!$Z29,Control!$AS$36:$AS$118,0),MATCH(WTI!AH$23,Control!$AS$36:$AY$36,0))-6 -> 22.5 | AI29: =AF29*VLOOKUP($Y29,Control!$F$75:$H$87,3,FALSE)/$AB29 -> 0.43373494 | AJ29: =IF($AK$3=1,$AG29*Control!$D$77,0) -> 0 | AK29: =IF($AK$4=1,$AH29*Control!$D$77,0) -> 0.2933137 | AL29: =IF(((AB29-VLOOKUP(Y29,Control!$J$76:$K$82,2,FALSE))/AN29)<=0,0,ROUNDUP(((AB29-VLOOKUP(Y29,Control!$J$76:$K$82,2,FALSE))/Control!$D$86),0)*IF(AN29=Control!$D$86,Control!$H$91,Control!$H$90)/AB29) -> 0.89156627 | AM29: =IF(I29="Corpus Christi",Control!$D$76,0) -> 0 | AN29: =IF(AND(Control!$D$85-ROUNDUP(((AB29-VLOOKUP(Y29,Control!$J$76:$K$82,2,FALSE))),0)>0,Control!$D$85-ROUNDUP(((AB29-VLOOKUP(Y29,Control!$J$76:$K$82,2,FALSE))),0)<Control!$D$86-ROUNDUP(((AB29-VLOOKUP(Y29,Control!$J$76:$K$82,2,FALSE))),0)),Control!$D$85,Control!$D$86) -> 750000 | AO29: =Control!$D$78 -> 0 | AP29: =Control!$D$79 -> 0.0673 | AQ29: =IF(INDEX(Control!$Q$3:$S$62,MATCH($Z29,Control!$Q$3:$Q$62,0),MATCH(AQ$9,Control!$Q$3:$S$3,0))=1,Control!$D$81*Control!$E$81,0) -> 0.2 | AS29: =Control!$D$83/AB29 -> 0.14457831 | AU29: =SUM(AI29:AM29,AO29:AT29) -> 2.0304932 | AV29: =+R29+AE29+AU29 -> 28.05459 | AW29: =IF((MONTH(A29)=MONTH(BH29)),0,IF(((MONTH(BH29))-MONTH(A29))+12*YEAR(BG29)-YEAR(A29)>1,SUMIFS($BD$4:$BH$4,$BD$3:$BH$3,"<="&EOMONTH(BG29,-1),$BD$3:$BH$3,">="&EOMONTH(A29,0)),VLOOKUP("Spreads",$BC$3:$BH$4,MATCH(EOMONTH(A29,0),$BC$3:$BH$3,0)))) -> 0 | AX29: =-HLOOKUP(EOMONTH(BG29,0),$BC$3:$BH$6,3,FALSE) -> -5.28 | AZ29: =$Y$3+AV29+AW29+AX29 -> 19.17459 | BC29: =BC44 -> 44 | BD29: =IF(ISBLANK(A29),"",A29+$BC29+D29) -> 46381 | BE29: =BD29+2 -> 46383 | BF29: Dated | BG29: =IF($BH$8=0,IF(BF29="ICE Brent",EOMONTH(BE29,2),EOMONTH(BE29,0)),IF(BF29="ICE Brent",EOMONTH(BE29,1),EOMONTH(BE29,-1))) -> 46356 | BH29: =BG29 -> 46356 | BI29: =AE29*AB29 -> 54000000 | BK29: =AI29*AB29 -> 900000 | BL29: =AL29*AB29 -> 1850000 | BM29: =AJ29*AB29 -> 0 | BN29: =AK29*AB29 -> 608625.92 | BO29: =(AU29-AL29-AK29-AJ29-AI29)*AB29 -> 854647.5 | BP29: =SUM(BI29:BM29) -> 56750000 | BQ29: =BP29-BM29 -> 56750000
A30: =+$A$10 -> 46334 | B30: =IF(ISBLANK(A30),"",A30+2) -> 46336 | D30: =IF(AL30=0,0,VLOOKUP(Y30,Control!$G$41:$J$44,4,FALSE)) -> 3 | E30: =AVERAGE(A30:B30)+D30 -> 46338 | T30: 0 | U30: =INDEX(Control!$E$17:$J$21,MATCH(Y30,Control!$E$17:$E$21,0),MATCH(V30,Control!$E$17:$J$17,0)) -> #N/A | V30: Corpus Christi - MODA | W30: 270000 | X30: =AB30/Control!$D$84 -> 267073.16 | Y30: VLCC-MODA | Z30: Jamnagar | AA30: =AA46 -> USGC/INDIA | AB30: =AB46 -> 2075000 | AC30: 1001 | AD30: =AD29 -> 54000000 | AE30: =IF(AC30>1000,IF(AD30=0,AC30,AD30)/AB30,((W30*T30*(IF(AD30=0,AC30,AD30)/100))+IF(X30<W30,0,(X30-W30)*T30*IF(AD30=0,AC30,AD30)/100*U30))/AB30) -> 26.024096 | AF30: 2 | AG30: =AG46 -> -9.5 | AH30: =INDEX(Control!$AS$36:$AY$118,MATCH(WTI!$Z30,Control!$AS$36:$AS$118,0),MATCH(WTI!AH$23,Control!$AS$36:$AY$36,0))-6 -> 19.5 | AI30: =AF30*VLOOKUP($Y30,Control!$F$75:$H$87,3,FALSE)/$AB30 -> 0.43373494 | AJ30: =IF($AK$3=1,$AG30*Control!$D$77,0) -> 0 | AK30: =IF($AK$4=1,$AH30*Control!$D$77,0) -> 0.25420521 | AL30: =IF(((AB30-VLOOKUP(Y30,Control!$J$76:$K$82,2,FALSE))/AN30)<=0,0,ROUNDUP(((AB30-VLOOKUP(Y30,Control!$J$76:$K$82,2,FALSE))/Control!$D$86),0)*IF(AN30=Control!$D$86,Control!$H$91,Control!$H$90)/AB30) -> 0.89156627 | AM30: =IF(I30="Corpus Christi",Control!$D$76,0) -> 0 | AN30: =IF(AND(Control!$D$85-ROUNDUP(((AB30-VLOOKUP(Y30,Control!$J$76:$K$82,2,FALSE))),0)>0,Control!$D$85-ROUNDUP(((AB30-VLOOKUP(Y30,Control!$J$76:$K$82,2,FALSE))),0)<Control!$D$86-ROUNDUP(((AB30-VLOOKUP(Y30,Control!$J$76:$K$82,2,FALSE))),0)),Control!$D$85,Control!$D$86) -> 750000 | AO30: =Control!$D$78 -> 0 | AP30: =Control!$D$79 -> 0.0673 | AQ30: =IF(INDEX(Control!$Q$3:$S$62,MATCH($Z30,Control!$Q$3:$Q$62,0),MATCH(AQ$9,Control!$Q$3:$S$3,0))=1,Control!$D$81*Control!$E$81,0) -> 0.2 | AS30: =Control!$D$83/AB30 -> 0.14457831 | AU30: =SUM(AI30:AM30,AO30:AT30) -> 1.9913847 | AV30: =+R30+AE30+AU30 -> 28.015481 | AW30: =IF((MONTH(A30)=MONTH(BH30)),0,IF(((MONTH(BH30))-MONTH(A30))+12*YEAR(BG30)-YEAR(A30)>1,SUMIFS($BD$4:$BH$4,$BD$3:$BH$3,"<="&EOMONTH(BG30,-1),$BD$3:$BH$3,">="&EOMONTH(A30,0)),VLOOKUP("Spreads",$BC$3:$BH$4,MATCH(EOMONTH(A30,0),$BC$3:$BH$3,0)))) -> 0 | AX30: =-HLOOKUP(EOMONTH(BG30,0),$BC$3:$BH$6,3,FALSE) -> -5.28 | AZ30: =$Y$3+AV30+AW30+AX30 -> 19.135481 | BC30: =BC46 -> 43 | BD30: =IF(ISBLANK(A30),"",A30+$BC30+D30) -> 46380 | BE30: =BD30+2 -> 46382 | BF30: Dated | BG30: =IF($BC$8=0,IF(BF30="ICE Brent",EOMONTH(BE30,2),EOMONTH(BE30,0)),IF(BF30="ICE Brent",EOMONTH(BE30,1),EOMONTH(BE30,-1))) -> 46356 | BH30: =IF($BC$8=1,EOMONTH(BE30,-1),EOMONTH(BE30,0)) -> 46356 | BI30: =AE30*AB30 -> 54000000 | BK30: =AI30*AB30 -> 900000 | BL30: =AL30*AB30 -> 1850000 | BM30: =AJ30*AB30 -> 0 | BN30: =AK30*AB30 -> 527475.8 | BO30: =(AU30-AL30-AK30-AJ30-AI30)*AB30 -> 854647.5 | BP30: =SUM(BI30:BM30) -> 56750000 | BQ30: =BP30-BM30 -> 56750000
A31: =+$A$10 -> 46334 | B31: =IF(ISBLANK(A31),"",A31+2) -> 46336 | D31: =IF(AL31=0,0,VLOOKUP(Y31,Control!$G$41:$J$44,4,FALSE)) -> 3 | E31: =AVERAGE(A31:B31)+D31 -> 46338 | T31: 0 | U31: =INDEX(Control!$E$17:$J$21,MATCH(Y31,Control!$E$17:$E$21,0),MATCH(V31,Control!$E$17:$J$17,0)) -> #N/A | V31: Corpus Christi - MODA | W31: 270000 | X31: =AB31/Control!$D$84 -> 267073.16 | Y31: VLCC-MODA | Z31: Taiwan | AA31: =AA43 -> USGC/KOREA | AB31: =AB37 -> 2075000 | AC31: 1001 | AD31: =AD47 -> 54650000 | AE31: =IF(AC31>1000,IF(AD31=0,AC31,AD31)/AB31,((W31*T31*(IF(AD31=0,AC31,AD31)/100))+IF(X31<W31,0,(X31-W31)*T31*IF(AD31=0,AC31,AD31)/100*U31))/AB31) -> 26.337349 | AF31: 2 | AG31: =AG47 -> -9.5 | AH31: =INDEX(Control!$AS$36:$AY$118,MATCH(WTI!$Z31,Control!$AS$36:$AS$118,0),MATCH(WTI!AH$23,Control!$AS$36:$AY$36,0))-6 -> 24.5 | AI31: =AF31*VLOOKUP($Y31,Control!$F$75:$H$87,3,FALSE)/$AB31 -> 0.43373494 | AJ31: =IF($AK$3=1,$AG31*Control!$D$77,0) -> 0 | AK31: =IF($AK$4=1,$AH31*Control!$D$77,0) -> 0.31938603 | AL31: =IF(((AB31-VLOOKUP(Y31,Control!$J$76:$K$82,2,FALSE))/AN31)<=0,0,ROUNDUP(((AB31-VLOOKUP(Y31,Control!$J$76:$K$82,2,FALSE))/Control!$D$86),0)*IF(AN31=Control!$D$86,Control!$H$91,Control!$H$90)/AB31) -> 0.89156627 | AM31: =IF(I31="Corpus Christi",Control!$D$76,0) -> 0 | AN31: =IF(AND(Control!$D$85-ROUNDUP(((AB31-VLOOKUP(Y31,Control!$J$76:$K$82,2,FALSE))),0)>0,Control!$D$85-ROUNDUP(((AB31-VLOOKUP(Y31,Control!$J$76:$K$82,2,FALSE))),0)<Control!$D$86-ROUNDUP(((AB31-VLOOKUP(Y31,Control!$J$76:$K$82,2,FALSE))),0)),Control!$D$85,Control!$D$86) -> 750000 | AO31: =Control!$D$78 -> 0 | AP31: =Control!$D$79 -> 0.0673 | AS31: =Control!$D$83/AB31 -> 0.14457831 | AU31: =SUM(AI31:AM31,AO31:AT31) -> 1.8565655 | AV31: =+R31+AE31+AU31 -> 28.193915 | AW31: =IF((MONTH(A31)=MONTH(BH31)),0,IF(((MONTH(BH31))-MONTH(A31))+12*YEAR(BG31)-YEAR(A31)>1,SUMIFS($BD$4:$BH$4,$BD$3:$BH$3,"<="&EOMONTH(BG31,-1),$BD$3:$BH$3,">="&EOMONTH(A31,0)),VLOOKUP("Spreads",$BC$3:$BH$4,MATCH(EOMONTH(A31,0),$BC$3:$BH$3,0)))) -> 2.9 | AX31: =-HLOOKUP(EOMONTH(BG31,0),$BC$3:$BH$6,3,FALSE) -> -3.98 | AZ31: =$Y$3+AV31+AW31+AX31 -> 23.513915 | BC31: 49 | BD31: =IF(ISBLANK(A31),"",A31+$BC31+D31) -> 46386 | BE31: =BD31+2 -> 46388 | BF31: Dated | BG31: =IF($BC$8=0,IF(BF31="ICE Brent",EOMONTH(BE31,2),EOMONTH(BE31,0)),IF(BF31="ICE Brent",EOMONTH(BE31,1),EOMONTH(BE31,-1))) -> 46387 | BH31: =IF($BC$8=1,EOMONTH(BE31,-1),EOMONTH(BE31,0)) -> 46387 | BI31: =AE31*AB31 -> 54650000 | BK31: =AI31*AB31 -> 900000 | BL31: =AL31*AB31 -> 1850000 | BM31: =AJ31*AB31 -> 0 | BN31: =AK31*AB31 -> 662726.01 | BO31: =(AU31-AL31-AK31-AJ31-AI31)*AB31 -> 439647.5 | BP31: =SUM(BI31:BM31) -> 57400000 | BQ31: =BP31-BM31 -> 57400000
Y32: V DOCK | BI32: Freight | BJ32: Freight (TD7) | BK32: Demurrage | BL32: STS | BM32: TVM | BN32: Other | BP32: =SUM(BI32:BM32) -> 0
A33: =+$A$10 -> 46334 | B33: =IF(ISBLANK(A33),"",A33+2) -> 46336 | D33: 3 | E33: =A33+2+D33 -> 46339 | T33: 0 | U33: =INDEX(Control!$E$17:$J$21,MATCH(Y33,Control!$E$17:$E$21,0),MATCH(V33,Control!$E$17:$J$17,0)) -> #N/A | V33: Corpus Christi - STG | W33: 270000 | X33: =AB33/Control!$D$84 -> 267073.16 | Y33: VLCC-MODA | Z33: Chiba | AA33: =AA44 -> USGC/Singapore | AB33: =AB34 -> 2075000 | AC33: 1001 | AD33: =AD34+200000 -> 55200000 | AE33: =IF(AC33>1000,IF(AD33=0,AC33,AD33)/AB33,((W33*T33*(IF(AD33=0,AC33,AD33)/100))+IF(X33<W33,0,(X33-W33)*T33*IF(AD33=0,AC33,AD33)/100*U33))/AB33) -> 26.60241 | AF33: 2 | AG33: =AG27 -> -9.5 | AH33: =AH34+1 -> 33.5 | AI33: =AF33*VLOOKUP($Y33,Control!$F$75:$H$87,3,FALSE)/$AB33 -> 0.43373494 | AK33: =IF($AK$4=1,$AH33*Control!$D$77,0) -> 0.43671151 | AL33: =IF(((AB33-VLOOKUP(Y33,Control!$J$76:$K$82,2,FALSE))/AN33)<=0,0,ROUNDUP(((AB33-VLOOKUP(Y33,Control!$J$76:$K$82,2,FALSE))/Control!$D$86),0)*IF(AN33=Control!$D$86,Control!$H$91,Control!$H$90)/AB33) -> 0.89156627 | AM33: =IF(I33="Corpus Christi",Control!$D$76,0) -> 0 | AN33: =IF(AND(Control!$D$85-ROUNDUP(((AB33-VLOOKUP(Y33,Control!$J$76:$K$82,2,FALSE))),0)>0,Control!$D$85-ROUNDUP(((AB33-VLOOKUP(Y33,Control!$J$76:$K$82,2,FALSE))),0)<Control!$D$86-ROUNDUP(((AB33-VLOOKUP(Y33,Control!$J$76:$K$82,2,FALSE))),0)),Control!$D$85,Control!$D$86) -> 750000 | AO33: =Control!$D$78 -> 0 | AP33: 0.07 | AQ33: =IF(INDEX(Control!$Q$3:$S$62,MATCH($Z33,Control!$Q$3:$Q$62,0),MATCH(AQ$9,Control!$Q$3:$S$3,0))=1,Control!$D$81*Control!$E$81,0) -> 0.2 | AS33: =Control!$D$83/AB33 -> 0.14457831 | AU33: =SUM(AI33:AM33,AO33:AT33) -> 2.176591 | AV33: =+R33+AE33+AU33 -> 28.779001 | AW33: =IF((MONTH(A33)=MONTH(BH33)),0,IF(((MONTH(BH33))-MONTH(A33))+12*YEAR(BG33)-YEAR(A33)>1,SUMIFS($BD$4:$BH$4,$BD$3:$BH$3,"<="&EOMONTH(BG33,-1),$BD$3:$BH$3,">="&EOMONTH(A33,0)),VLOOKUP("Spreads",$BC$3:$BH$4,MATCH(EOMONTH(A33,0),$BC$3:$BH$3,0)))) -> 2.9 | AX33: =+IF(BF33="Dated",-INDEX($BC$3:$BH$6,MATCH(BF33,$BC$3:$BC$6,0),MATCH(BG33,$BC$3:$BH$3,0)),INDEX($BC$3:$BH$6,MATCH(BF33,$BC$3:$BC$6,0),MATCH(BG33,$BC$3:$BH$3,0))) -> -0.9 | AY33: =1/INDEX($BC$3:$BH$7,MATCH("CMA",$BC$3:$BC$7,0),MATCH(BG33,$BC$3:$BH$3,0))*INDEX($BC$3:$BH$7,MATCH("Spreads",$BC$3:$BC$7,0),MATCH(BG33,$BC$3:$BH$3,0)) -> 0.097826087 | AZ33: =$Y$3+AV33+AW33+AX33+AY33 -> 27.276827 | BC33: =BC34+1 -> 53 | BD33: =IF(ISBLANK(A33),"",E33+$BC33) -> 46392 | BE33: =BD33+2 -> 46394 | BF33: =HLOOKUP($BC$3,$AV$4:$AX$5,2,FALSE) -> Dubai | BG33: =IF($BC$8=0,IF(BF33="ICE Brent",EOMONTH(BE33,2),EOMONTH(BE33,0)),IF(BF33="ICE Brent",EOMONTH(BE33,1),EOMONTH(BE33,-1))) -> 46387 | BH33: =IF($BC$8=1,EOMONTH(BE33,-1),EOMONTH(BE33,0)) -> 46387 | BI33: =(AE33*AB33)/1000 -> 55200 | BJ33: 0 | BK33: =AI33*AB33/1000 -> 900 | BL33: =AL33*AB33/1000 -> 1850 | BM33: =(AJ33+AK33)*AB33/1000 -> 906.17638 | BN33: =(AU33-AI33-AJ33-AK33-AL33)*AB33/1000 -> 860.25
A34: =+$A$10 -> 46334 | B34: =IF(ISBLANK(A34),"",A34+2) -> 46336 | D34: 3 | E34: =A34+2+D34 -> 46339 | T34: 0 | U34: =INDEX(Control!$E$17:$J$21,MATCH(Y34,Control!$E$17:$E$21,0),MATCH(V34,Control!$E$17:$J$17,0)) -> #N/A | V34: Corpus Christi - STG | W34: 270000 | X34: =AB34/Control!$D$84 -> 267073.16 | Y34: VLCC-STG | Z34: Daesan | AA34: =AA47 -> USGC/KOREA | AB34: 2075000 | AC34: 1001 | AD34: =AD43 -> 55000000 | AE34: =IF(AC34>1000,IF(AD34=0,AC34,AD34)/AB34,((W34*T34*(IF(AD34=0,AC34,AD34)/100))+IF(X34<W34,0,(X34-W34)*T34*IF(AD34=0,AC34,AD34)/100*U34))/AB34) -> 26.506024 | AF34: 2 | AG34: =AG28 -> -9.5 | AH34: =INDEX(Control!$AS$36:$AY$118,MATCH(WTI!$Z34,Control!$AS$36:$AS$118,0),MATCH(WTI!AH$23,Control!$AS$36:$AY$36,0))-6 -> 32.5 | AI34: =AF34*VLOOKUP($Y34,Control!$F$75:$H$87,3,FALSE)/$AB34 -> 0.43373494 | AJ34: =IF($AK$3=1,$AG34*Control!$D$77,0) -> 0 | AK34: =IF($AK$4=1,$AH34*Control!$D$77,0) -> 0.42367534 | AL34: =IF(((AB34-VLOOKUP(Y34,Control!$J$76:$K$82,2,FALSE))/AN34)<=0,0,ROUNDUP(((AB34-VLOOKUP(Y34,Control!$J$76:$K$82,2,FALSE))/Control!$D$86),0)*IF(AN34=Control!$D$86,Control!$H$91,Control!$H$90)/AB34) -> 0.89156627 | AM34: =IF(I34="Corpus Christi",Control!$D$76,0) -> 0 | AN34: =IF(AND(Control!$D$85-ROUNDUP(((AB34-VLOOKUP(Y34,Control!$J$76:$K$82,2,FALSE))),0)>0,Control!$D$85-ROUNDUP(((AB34-VLOOKUP(Y34,Control!$J$76:$K$82,2,FALSE))),0)<Control!$D$86-ROUNDUP(((AB34-VLOOKUP(Y34,Control!$J$76:$K$82,2,FALSE))),0)),Control!$D$85,Control!$D$86) -> 750000 | AO34: =Control!$D$78 -> 0 | AP34: 0.07 | AQ34: 0.09 | AS34: =Control!$D$83/AB34 -> 0.14457831 | AU34: =SUM(AI34:AM34,AO34:AT34) -> 2.0535549 | AV34: =+R34+AE34+AU34 -> 28.559579 | AW34: =IF((MONTH(A34)=MONTH(BH34)),0,IF(((MONTH(BH34))-MONTH(A34))+12*YEAR(BG34)-YEAR(A34)>1,SUMIFS($BD$4:$BH$4,$BD$3:$BH$3,"<="&EOMONTH(BG34,-1),$BD$3:$BH$3,">="&EOMONTH(A34,0)),VLOOKUP("Spreads",$BC$3:$BH$4,MATCH(EOMONTH(A34,0),$BC$3:$BH$3,0)))) -> 2.9 | AX34: =+IF(BF34="Dated",-INDEX($BC$3:$BH$6,MATCH(BF34,$BC$3:$BC$6,0),MATCH(BG34,$BC$3:$BH$3,0)),INDEX($BC$3:$BH$6,MATCH(BF34,$BC$3:$BC$6,0),MATCH(BG34,$BC$3:$BH$3,0))) -> -0.9 | AY34: =1/INDEX($BC$3:$BH$7,MATCH("CMA",$BC$3:$BC$7,0),MATCH(BG34,$BC$3:$BH$3,0))*INDEX($BC$3:$BH$7,MATCH("Spreads",$BC$3:$BC$7,0),MATCH(BG34,$BC$3:$BH$3,0)) -> 0.097826087 | AZ34: =$Y$3+AV34+AW34+AX34+AY34 -> 27.057405 | BC34: =BC43 -> 52 | BD34: =IF(ISBLANK(A34),"",$BC34+E34) -> 46391 | BE34: =BD34+2 -> 46393 | BF34: Dubai | BG34: =IF($BC$8=0,IF(BF34="ICE Brent",EOMONTH(BE34,2),EOMONTH(BE34,0)),IF(BF34="ICE Brent",EOMONTH(BE34,1),EOMONTH(BE34,-1))) -> 46387 | BH34: =IF($BC$8=1,EOMONTH(BE34,-1),EOMONTH(BE34,0)) -> 46387 | BI34: =(AE34*AB34)/1000 -> 55000 | BJ34: 0 | BK34: =AI34*AB34/1000 -> 900 | BL34: =AL34*AB34/1000 -> 1850 | BM34: =(AJ34+AK34)*AB34/1000 -> 879.12634 | BN34: =(AU34-AI34-AJ34-AK34-AL34)*AB34/1000 -> 632
A35: =+$A$10 -> 46334 | B35: =IF(ISBLANK(A35),"",A35+2) -> 46336 | D35: =D29 -> 3 | E35: =A35+2+D35 -> 46339 | T35: 0 | U35: =INDEX(Control!$E$17:$J$21,MATCH(Y35,Control!$E$17:$E$21,0),MATCH(V35,Control!$E$17:$J$17,0)) -> #N/A | V35: Corpus Christi - STG | W35: 270000 | X35: =AB35/Control!$D$84 -> 267073.16 | Y35: VLCC-STG | Z35: Singapore | AA35: =AA42 -> USGC/KOREA | AB35: =AB34 -> 2075000 | AC35: 1001 | AD35: =AD44 -> 54000000 | AE35: =IF(AC35>1000,IF(AD35=0,AC35,AD35)/AB35,((W35*T35*(IF(AD35=0,AC35,AD35)/100))+IF(X35<W35,0,(X35-W35)*T35*IF(AD35=0,AC35,AD35)/100*U35))/AB35) -> 26.024096 | AF35: 2 | AG35: =AG29 -> -9.5 | AH35: =INDEX(Control!$AS$36:$AY$118,MATCH(WTI!$Z35,Control!$AS$36:$AS$118,0),MATCH(WTI!AH$23,Control!$AS$36:$AY$36,0))-6 -> 22.5 | AI35: =AF35*VLOOKUP($Y35,Control!$F$75:$H$87,3,FALSE)/$AB35 -> 0.43373494 | AJ35: =IF($AK$3=1,$AG35*Control!$D$77,0) -> 0 | AK35: =IF($AK$4=1,$AH35*Control!$D$77,0) -> 0.2933137 | AL35: =IF(((AB35-VLOOKUP(Y35,Control!$J$76:$K$82,2,FALSE))/AN35)<=0,0,ROUNDUP(((AB35-VLOOKUP(Y35,Control!$J$76:$K$82,2,FALSE))/Control!$D$86),0)*IF(AN35=Control!$D$86,Control!$H$91,Control!$H$90)/AB35) -> 0.89156627 | AM35: =IF(I35="Corpus Christi",Control!$D$76,0) -> 0 | AN35: =IF(AND(Control!$D$85-ROUNDUP(((AB35-VLOOKUP(Y35,Control!$J$76:$K$82,2,FALSE))),0)>0,Control!$D$85-ROUNDUP(((AB35-VLOOKUP(Y35,Control!$J$76:$K$82,2,FALSE))),0)<Control!$D$86-ROUNDUP(((AB35-VLOOKUP(Y35,Control!$J$76:$K$82,2,FALSE))),0)),Control!$D$85,Control!$D$86) -> 750000 | AO35: =Control!$D$78 -> 0 | AP35: =Control!$D$79 -> 0.0673 | AQ35: =IF(INDEX(Control!$Q$3:$S$62,MATCH($Z35,Control!$Q$3:$Q$62,0),MATCH(AQ$9,Control!$Q$3:$S$3,0))=1,Control!$D$81*Control!$E$81,0) -> 0.2 | AS35: =Control!$D$83/AB35 -> 0.14457831 | AU35: =SUM(AI35:AM35,AO35:AT35) -> 2.0304932 | AV35: =+R35+AE35+AU35 -> 28.05459 | AW35: =IF((MONTH(A35)=MONTH(BH35)),0,IF(((MONTH(BH35))-MONTH(A35))+12*YEAR(BG35)-YEAR(A35)>1,SUMIFS($BD$4:$BH$4,$BD$3:$BH$3,"<="&EOMONTH(BG35,-1),$BD$3:$BH$3,">="&EOMONTH(A35,0)),VLOOKUP("Spreads",$BC$3:$BH$4,MATCH(EOMONTH(A35,0),$BC$3:$BH$3,0)))) -> 0 | AX35: =+IF(BF35="Dated",-INDEX($BC$3:$BH$6,MATCH(BF35,$BC$3:$BC$6,0),MATCH(BG35,$BC$3:$BH$3,0)),INDEX($BC$3:$BH$6,MATCH(BF35,$BC$3:$BC$6,0),MATCH(BG35,$BC$3:$BH$3,0))) -> -5.28 | AY35: =1/INDEX($BC$3:$BH$7,MATCH("CMA",$BC$3:$BC$7,0),MATCH(BG35,$BC$3:$BH$3,0))*INDEX($BC$3:$BH$7,MATCH("Spreads",$BC$3:$BC$7,0),MATCH(BG35,$BC$3:$BH$3,0)) -> 0.13181818 | AZ35: =$Y$3+AV35+AW35+AX35+AY35 -> 19.306408 | BC35: =BC44 -> 44 | BD35: =IF(ISBLANK(A35),"",$BC35+E35) -> 46383 | BE35: =BD35+2 -> 46385 | BF35: Dated | BG35: =IF($BH$8=0,IF(BF35="ICE Brent",EOMONTH(BE35,2),EOMONTH(BE35,0)),IF(BF35="ICE Brent",EOMONTH(BE35,1),EOMONTH(BE35,-1))) -> 46356 | BH35: =BG35 -> 46356 | BI35: =(AE35*AB35)/1000 -> 54000 | BJ35: 0 | BK35: =AI35*AB35/1000 -> 900 | BL35: =AL35*AB35/1000 -> 1850 | BM35: =(AJ35+AK35)*AB35/1000 -> 608.62592 | BN35: =(AU35-AI35-AJ35-AK35-AL35)*AB35/1000 -> 854.6475
A36: =+$A$10 -> 46334 | B36: =IF(ISBLANK(A36),"",A36+2) -> 46336 | D36: =D30 -> 3 | E36: =A36+2+D36 -> 46339 | T36: 0 | U36: =INDEX(Control!$E$17:$J$21,MATCH(Y36,Control!$E$17:$E$21,0),MATCH(V36,Control!$E$17:$J$17,0)) -> #N/A | V36: Corpus Christi - STG | W36: 270000 | X36: =AB36/Control!$D$84 -> 267073.16 | Y36: VLCC-STG | Z36: Jamnagar | AA36: =AA46 -> USGC/INDIA | AB36: =AB34 -> 2075000 | AC36: 1001 | AD36: =AD46 -> 54000000 | AE36: =IF(AC36>1000,IF(AD36=0,AC36,AD36)/AB36,((W36*T36*(IF(AD36=0,AC36,AD36)/100))+IF(X36<W36,0,(X36-W36)*T36*IF(AD36=0,AC36,AD36)/100*U36))/AB36) -> 26.024096 | AF36: 2 | AG36: =AG30 -> -9.5 | AH36: =INDEX(Control!$AS$36:$AY$118,MATCH(WTI!$Z36,Control!$AS$36:$AS$118,0),MATCH(WTI!AH$23,Control!$AS$36:$AY$36,0))-6 -> 19.5 | AI36: =AF36*VLOOKUP($Y36,Control!$F$75:$H$87,3,FALSE)/$AB36 -> 0.43373494 | AJ36: =IF($AK$3=1,$AG36*Control!$D$77,0) -> 0 | AK36: =IF($AK$4=1,$AH36*Control!$D$77,0) -> 0.25420521 | AL36: =IF(((AB36-VLOOKUP(Y36,Control!$J$76:$K$82,2,FALSE))/AN36)<=0,0,ROUNDUP(((AB36-VLOOKUP(Y36,Control!$J$76:$K$82,2,FALSE))/Control!$D$86),0)*IF(AN36=Control!$D$86,Control!$H$91,Control!$H$90)/AB36) -> 0.89156627 | AM36: =IF(I36="Corpus Christi",Control!$D$76,0) -> 0 | AN36: =IF(AND(Control!$D$85-ROUNDUP(((AB36-VLOOKUP(Y36,Control!$J$76:$K$82,2,FALSE))),0)>0,Control!$D$85-ROUNDUP(((AB36-VLOOKUP(Y36,Control!$J$76:$K$82,2,FALSE))),0)<Control!$D$86-ROUNDUP(((AB36-VLOOKUP(Y36,Control!$J$76:$K$82,2,FALSE))),0)),Control!$D$85,Control!$D$86) -> 750000 | AO36: =Control!$D$78 -> 0 | AP36: =Control!$D$79 -> 0.0673 | AQ36: =IF(INDEX(Control!$Q$3:$S$62,MATCH($Z36,Control!$Q$3:$Q$62,0),MATCH(AQ$9,Control!$Q$3:$S$3,0))=1,Control!$D$81*Control!$E$81,0) -> 0.2 | AS36: =Control!$D$83/AB36 -> 0.14457831 | AU36: =SUM(AI36:AM36,AO36:AT36) -> 1.9913847 | AV36: =+R36+AE36+AU36 -> 28.015481 | AW36: =IF((MONTH(A36)=MONTH(BH36)),0,IF(((MONTH(BH36))-MONTH(A36))+12*YEAR(BG36)-YEAR(A36)>1,SUMIFS($BD$4:$BH$4,$BD$3:$BH$3,"<="&EOMONTH(BG36,-1),$BD$3:$BH$3,">="&EOMONTH(A36,0)),VLOOKUP("Spreads",$BC$3:$BH$4,MATCH(EOMONTH(A36,0),$BC$3:$BH$3,0)))) -> 0 | AX36: =+IF(BF36="Dated",-INDEX($BC$3:$BH$6,MATCH(BF36,$BC$3:$BC$6,0),MATCH(BG36,$BC$3:$BH$3,0)),INDEX($BC$3:$BH$6,MATCH(BF36,$BC$3:$BC$6,0),MATCH(BG36,$BC$3:$BH$3,0))) -> -5.28 | AY36: =1/INDEX($BC$3:$BH$7,MATCH("CMA",$BC$3:$BC$7,0),MATCH(BG36,$BC$3:$BH$3,0))*INDEX($BC$3:$BH$7,MATCH("Spreads",$BC$3:$BC$7,0),MATCH(BG36,$BC$3:$BH$3,0)) -> 0.13181818 | AZ36: =$Y$3+AV36+AW36+AX36+AY36 -> 19.267299 | BC36: =BC46 -> 43 | BD36: =IF(ISBLANK(A36),"",$BC36+E36) -> 46382 | BE36: =BD36+2 -> 46384 | BF36: Dated | BG36: =IF($BC$8=0,IF(BF36="ICE Brent",EOMONTH(BE36,2),EOMONTH(BE36,0)),IF(BF36="ICE Brent",EOMONTH(BE36,1),EOMONTH(BE36,-1))) -> 46356 | BH36: =IF($BC$8=1,EOMONTH(BE36,-1),EOMONTH(BE36,0)) -> 46356 | BI36: =(AE36*AB36)/1000 -> 54000 | BJ36: 0 | BK36: =AI36*AB36/1000 -> 900 | BL36: =AL36*AB36/1000 -> 1850 | BM36: =(AJ36+AK36)*AB36/1000 -> 527.4758 | BN36: =(AU36-AI36-AJ36-AK36-AL36)*AB36/1000 -> 854.6475
A37: =+$A$10 -> 46334 | B37: =IF(ISBLANK(A37),"",A37+2) -> 46336 | D37: =D31 -> 3 | E37: =A37+2+D37 -> 46339 | T37: 0 | U37: =INDEX(Control!$E$17:$J$21,MATCH(Y37,Control!$E$17:$E$21,0),MATCH(V37,Control!$E$17:$J$17,0)) -> #N/A | V37: Corpus Christi - STG | W37: 270000 | X37: =AB37/Control!$D$84 -> 267073.16 | Y37: VLCC-STG | Z37: Taiwan | AA37: =AA47 -> USGC/KOREA | AB37: =AB34 -> 2075000 | AC37: 1001 | AD37: =AD34-350000 -> 54650000 | AE37: =IF(AC37>1000,IF(AD37=0,AC37,AD37)/AB37,((W37*T37*(IF(AD37=0,AC37,AD37)/100))+IF(X37<W37,0,(X37-W37)*T37*IF(AD37=0,AC37,AD37)/100*U37))/AB37) -> 26.337349 | AF37: 2 | AG37: =AG31 -> -9.5 | AH37: =INDEX(Control!$AS$36:$AY$118,MATCH(WTI!$Z37,Control!$AS$36:$AS$118,0),MATCH(WTI!AH$23,Control!$AS$36:$AY$36,0))-6 -> 24.5 | AI37: =AF37*VLOOKUP($Y37,Control!$F$75:$H$87,3,FALSE)/$AB37 -> 0.43373494 | AJ37: =IF($AK$3=1,$AG37*Control!$D$77,0) -> 0 | AK37: =IF($AK$4=1,$AH37*Control!$D$77,0) -> 0.31938603 | AL37: =IF(((AB37-VLOOKUP(Y37,Control!$J$76:$K$82,2,FALSE))/AN37)<=0,0,ROUNDUP(((AB37-VLOOKUP(Y37,Control!$J$76:$K$82,2,FALSE))/Control!$D$86),0)*IF(AN37=Control!$D$86,Control!$H$91,Control!$H$90)/AB37) -> 0.89156627 | AM37: =IF(I37="Corpus Christi",Control!$D$76,0) -> 0 | AN37: =IF(AND(Control!$D$85-ROUNDUP(((AB37-VLOOKUP(Y37,Control!$J$76:$K$82,2,FALSE))),0)>0,Control!$D$85-ROUNDUP(((AB37-VLOOKUP(Y37,Control!$J$76:$K$82,2,FALSE))),0)<Control!$D$86-ROUNDUP(((AB37-VLOOKUP(Y37,Control!$J$76:$K$82,2,FALSE))),0)),Control!$D$85,Control!$D$86) -> 750000 | AO37: =Control!$D$78 -> 0 | AP37: =Control!$D$79 -> 0.0673 | AS37: =Control!$D$83/AB37 -> 0.14457831 | AU37: =SUM(AI37:AM37,AO37:AT37) -> 1.8565655 | AV37: =+R37+AE37+AU37 -> 28.193915 | AW37: =IF((MONTH(A37)=MONTH(BH37)),0,IF(((MONTH(BH37))-MONTH(A37))+12*YEAR(BG37)-YEAR(A37)>1,SUMIFS($BD$4:$BH$4,$BD$3:$BH$3,"<="&EOMONTH(BG37,-1),$BD$3:$BH$3,">="&EOMONTH(A37,0)),VLOOKUP("Spreads",$BC$3:$BH$4,MATCH(EOMONTH(A37,0),$BC$3:$BH$3,0)))) -> 2.9 | AX37: =+IF(BF37="Dated",-INDEX($BC$3:$BH$6,MATCH(BF37,$BC$3:$BC$6,0),MATCH(BG37,$BC$3:$BH$3,0)),INDEX($BC$3:$BH$6,MATCH(BF37,$BC$3:$BC$6,0),MATCH(BG37,$BC$3:$BH$3,0))) -> -3.98 | AY37: =1/INDEX($BC$3:$BH$7,MATCH("CMA",$BC$3:$BC$7,0),MATCH(BG37,$BC$3:$BH$3,0))*INDEX($BC$3:$BH$7,MATCH("Spreads",$BC$3:$BC$7,0),MATCH(BG37,$BC$3:$BH$3,0)) -> 0.097826087 | AZ37: =$Y$3+AV37+AW37+AX37+AY37 -> 23.611741 | BC37: =BC47 -> 48 | BD37: =IF(ISBLANK(A37),"",$BC37+E37) -> 46387 | BE37: =BD37+2 -> 46389 | BF37: Dated | BG37: =IF($BC$8=0,IF(BF37="ICE Brent",EOMONTH(BE37,2),EOMONTH(BE37,0)),IF(BF37="ICE Brent",EOMONTH(BE37,1),EOMONTH(BE37,-1))) -> 46387 | BH37: =IF($BC$8=1,EOMONTH(BE37,-1),EOMONTH(BE37,0)) -> 46387 | BI37: =(AE37*AB37)/1000 -> 54650 | BJ37: 0 | BK37: =AI37*AB37/1000 -> 900 | BL37: =AL37*AB37/1000 -> 1850 | BM37: =(AJ37+AK37)*AB37/1000 -> 662.72601 | BN37: =(AU37-AI37-AJ37-AK37-AL37)*AB37/1000 -> 439.6475
A38: =+$A$10 -> 46334 | B38: =IF(ISBLANK(A38),"",A38+2) -> 46336 | D38: =D33 -> 3 | E38: =AVERAGE(A38:B38)+D38 -> 46338 | T38: 0 | U38: =INDEX(Control!$E$17:$J$21,MATCH(Y38,Control!$E$17:$E$21,0),MATCH(V38,Control!$E$17:$J$17,0)) -> #N/A | V38: Corpus Christi - STG | W38: 270000 | X38: =AB38/Control!$D$84 -> 267073.16 | Y38: VLCC-STG | Z38: Taiwan | AA38: =AA48 -> 0 | AB38: =AB35 -> 2075000 | AC38: 1001 | AD38: =AD33 -> 55200000 | AE38: =IF(AC38>1000,IF(AD38=0,AC38,AD38)/AB38,((W38*T38*(IF(AD38=0,AC38,AD38)/100))+IF(X38<W38,0,(X38-W38)*T38*IF(AD38=0,AC38,AD38)/100*U38))/AB38) -> 26.60241 | AF38: 2 | AG38: =AG33 -> -9.5 | AI38: =AF38*VLOOKUP($Y38,Control!$F$75:$H$87,3,FALSE)/$AB38 -> 0.43373494 | AJ38: =$AG38*Control!$D$77 -> -0.12384356 | AL38: =IF(((AB38-VLOOKUP(Y38,Control!$J$76:$K$82,2,FALSE))/AN38)<=0,0,ROUNDUP(((AB38-VLOOKUP(Y38,Control!$J$76:$K$82,2,FALSE))/Control!$D$86),0)*IF(AN38=Control!$D$86,Control!$H$91,Control!$H$90)/AB38) -> 0.89156627 | AM38: =IF(I38="Corpus Christi",Control!$D$76,0) -> 0 | AN38: =IF(AND(Control!$D$85-ROUNDUP(((AB38-VLOOKUP(Y38,Control!$J$76:$K$82,2,FALSE))),0)>0,Control!$D$85-ROUNDUP(((AB38-VLOOKUP(Y38,Control!$J$76:$K$82,2,FALSE))),0)<Control!$D$86-ROUNDUP(((AB38-VLOOKUP(Y38,Control!$J$76:$K$82,2,FALSE))),0)),Control!$D$85,Control!$D$86) -> 750000 | AO38: =Control!$D$78 -> 0 | AP38: =Control!$D$79 -> 0.0673 | AQ38: =AQ35 -> 0.2 | AS38: =Control!$D$83/AB38 -> 0.14457831 | AU38: =SUM(AI38:AM38,AO38:AT38) -> 1.613336 | AV38: =+R38+AE38+AU38 -> 28.215746 | AW38: =IF((MONTH(A38)=MONTH(BH38)),0,IF(((MONTH(BH38))-MONTH(A38))+12*YEAR(BG38)-YEAR(A38)>1,SUMIFS($BD$4:$BG$4,$BD$3:$BG$3,"<="&EOMONTH(BG38,-1),$BD$3:$BG$3,">="&EOMONTH(A38,0)),VLOOKUP("Spreads",$BC$3:$BG$4,MATCH(EOMONTH(A38,0),$BC$3:$BG$3,0)))) -> 2.9 | AX38: =+IF($BC$3=1,HLOOKUP(EOMONTH(BG38,0),$BD$3:$BH$6,4,FALSE),IF($BC$3=2,-HLOOKUP(EOMONTH(BG38,0),$BC$3:$BH$6,3,FALSE),0)) -> -0.9 | AZ38: =$Y$3+AV38+AW38+AX38 -> 26.615746 | BC38: =BC33 -> 53 | BD38: =IF(ISBLANK(A38),"",A38+$BC38+D38) -> 46390 | BE38: =BD38+2 -> 46392 | BF38: =HLOOKUP($BC$3,$AV$4:$AX$5,2,FALSE) -> Dubai | BG38: =IF($BC$8=0,IF(BF38="ICE Brent",EOMONTH(BE38,2),EOMONTH(BE38,0)),IF(BF38="ICE Brent",EOMONTH(BE38,1),EOMONTH(BE38,-1))) -> 46387 | BH38: =IF($BC$8=1,EOMONTH(BE38,-1),EOMONTH(BE38,0)) -> 46387 | BL38: =AL38*AB38 -> 1850000 | BM38: =AJ38*AB38 -> -256975.39 | BN38: =AK38*AB38 -> 0
Y39: 3X STS | BI39: Freight | BK39: Demurrage | BL39: STS | BM39: TVM | BN39: Other
A40: =+$A$10 -> 46334 | B40: =IF(ISBLANK(A40),"",A40+2) -> 46336 | D40: =IF(AL40=0,0,VLOOKUP(Y40,Control!$G$41:$J$44,4,FALSE)) -> 0 | E40: =A40+2+D40 -> 46336 | T40: =INDEX('[2]Flat Rates 2025'!$A:$DZ,MATCH(V40,'[2]Flat Rates 2025'!$A:$A,0),MATCH(Z40,'[2]Flat Rates 2025'!$A$1:$DZ$1,0)) -> 0 | U40: =INDEX(Control!$E$17:$J$21,MATCH(Y40,Control!$E$17:$E$21,0),MATCH(V40,Control!$E$17:$J$17,0)) -> 0 | V40: Corpus Christi | W40: =INDEX(Vessel_Minimum_MT,MATCH(Y40,Control!$E$11:$E$15,0),MATCH(V40,Control!$E$11:$J$11,0)) -> 70000 | X40: =AB40/Control!$D$84 -> 90096.968 | Y40: Aframax | Z40: Daesan | AA40: =IF(Z40=V40,"",CONCATENATE(CONCATENATE(VLOOKUP(V40,Zones,2,FALSE),"/",VLOOKUP(Z40,Zones,2,FALSE)))) -> USGC/KOREA | AB40: 700000 | AC40: 1001 | AD40: 13000000 | AE40: =IF(AC40>1000,IF(AD40=0,AC40,AD40)/AB40,((W40*T40*(IF(AD40=0,AC40,AD40)/100))+IF(X40<W40,0,(X40-W40)*T40*IF(AD40=0,AC40,AD40)/100*U40))/AB40) -> 18.571429 | AF40: 1 | AG40: =INDEX(Control!$AS$36:$AY$118,MATCH(WTI!$Z40,Control!$AS$36:$AS$118,0),MATCH(WTI!AG$23,Control!$AS$36:$AY$36,0)) -> -9.5 | AH40: =INDEX(Control!$AS$36:$AY$118,MATCH(WTI!$Z40,Control!$AS$36:$AS$118,0),MATCH(WTI!AH$23,Control!$AS$36:$AY$36,0))-(BC43-BC40) -> 26.5 | AI40: =AF40*VLOOKUP($Y40,Control!$F$75:$H$87,3,FALSE)/$AB40 -> 0.11428571 | AJ40: =IF($AK$3=1,$AG40*Control!$D$77,0) -> 0 | AK40: =IF($AK$4=1,$AH40*Control!$D$77,0) -> 0.34545836 | AL40: =IF(((AB40-VLOOKUP(Y40,Control!$J$76:$K$80,2,FALSE))/Control!$D$85)<=0,0,ROUNDUP(((AB40-VLOOKUP(Y40,Control!$J$76:$K$80,2,FALSE))/Control!$D$85),0)*Control!$H$90/AB40) -> 0 | AM40: =IF(I40="Corpus Christi",Control!$D$76,0) -> 0 | AN40: 0 | AO40: =Control!$D$78 -> 0 | AP40: =Control!$D$79 -> 0.0673 | AS40: =IF(AND(Y40="VLCC",Control!$K$79=1200000),Control!$D$83/AB40,0) -> 0 | AU40: =SUM(AI40:AT40) -> 0.52704407 | AV40: =+R40+AE40+AU40 -> 19.098473 | AW40: =IF((MONTH(A40)=MONTH(BH40)),0,IF(((MONTH(BH40))-MONTH(A40))+12*YEAR(BG40)-YEAR(A40)>1,SUMIFS($BD$4:$BH$4,$BD$3:$BH$3,"<="&EOMONTH(BG40,-1),$BD$3:$BH$3,">="&EOMONTH(A40,0)),VLOOKUP("Spreads",$BC$3:$BH$4,MATCH(EOMONTH(A40,0),$BC$3:$BH$3,0)))) -> 2.9 | AX40: =+IF(BF40="Dated",-INDEX($BC$3:$BH$6,MATCH(BF40,$BC$3:$BC$6,0),MATCH(BG40,$BC$3:$BH$3,0)),INDEX($BC$3:$BH$6,MATCH(BF40,$BC$3:$BC$6,0),MATCH(BG40,$BC$3:$BH$3,0))) -> -0.9 | AY40: =1/INDEX($BC$3:$BH$7,MATCH("CMA",$BC$3:$BC$7,0),MATCH(BG40,$BC$3:$BH$3,0))*INDEX($BC$3:$BH$7,MATCH("Spreads",$BC$3:$BC$7,0),MATCH(BG40,$BC$3:$BH$3,0)) -> 0.097826087 | AZ40: =$Y$3+AV40+AW40+AX40+AY40 -> 17.596299 | BC40: 40 | BD40: =IF(ISBLANK(A40),"",E40+$BC40) -> 46376 | BE40: =BD40+2 -> 46378 | BF40: Dubai | BG40: =BG43 -> 46387 | BH40: =BG40 -> 46387 | BI40: =(AE40*AB40)/1000 -> 13000 | BJ40: 0 | BK40: =AI40*AB40/1000 -> 80 | BL40: =AL40*AB40/1000 -> 0 | BM40: =(AJ40+AK40)*AB40/1000 -> 241.82085 | BN40: =(AU40-AI40-AJ40-AK40-AL40)*AB40/1000 -> 47.11
A41: =+$A$10 -> 46334 | B41: =IF(ISBLANK(A41),"",A41+2) -> 46336 | D41: =IF(AL41=0,0,VLOOKUP(Y41,Control!$G$41:$J$44,4,FALSE)) -> 0 | E41: =A41+2+D41 -> 46336 | T41: =INDEX('[2]Flat Rates 2025'!$A:$DZ,MATCH(V41,'[2]Flat Rates 2025'!$A:$A,0),MATCH(Z41,'[2]Flat Rates 2025'!$A$1:$DZ$1,0)) -> 0 | U41: =INDEX(Control!$E$17:$J$21,MATCH(Y41,Control!$E$17:$E$21,0),MATCH(V41,Control!$E$17:$J$17,0)) -> #N/A | V41: Corpus Christi | W41: =INDEX(Vessel_Minimum_MT,MATCH(Y41,Control!$E$11:$E$15,0),MATCH(V41,Control!$E$11:$J$11,0)) -> #N/A | X41: =AB41/Control!$D$84 -> 128709.95 | Y41: Suezmax-MODA | Z41: Daesan | AA41: =IF(Z41=V41,"",CONCATENATE(CONCATENATE(VLOOKUP(V41,Zones,2,FALSE),"/",VLOOKUP(Z41,Zones,2,FALSE)))) -> USGC/KOREA | AB41: 1000000 | AC41: 1001 | AD41: 13500000 | AE41: =IF(AC41>1000,IF(AD41=0,AC41,AD41)/AB41,((W41*T41*(IF(AD41=0,AC41,AD41)/100))+IF(X41<W41,0,(X41-W41)*T41*IF(AD41=0,AC41,AD41)/100*U41))/AB41) -> 13.5 | AF41: =$AF$38 -> 2 | AG41: =INDEX(Control!$AS$36:$AY$118,MATCH(WTI!$Z41,Control!$AS$36:$AS$118,0),MATCH(WTI!AG$23,Control!$AS$36:$AY$36,0)) -> -9.5 | AH41: =INDEX(Control!$AS$36:$AY$118,MATCH(WTI!$Z41,Control!$AS$36:$AS$118,0),MATCH(WTI!AH$23,Control!$AS$36:$AY$36,0))-6 -> 32.5 | AI41: =AF41*VLOOKUP($Y41,Control!$F$75:$H$87,3,FALSE)/$AB41 -> 0.19 | AJ41: =IF($AK$3=1,$AG41*Control!$D$77,0) -> 0 | AK41: =IF($AK$4=1,$AH41*Control!$D$77,0) -> 0.42367534 | AL41: =IF(((AB41-VLOOKUP(Y41,Control!$J$76:$K$82,2,FALSE))/Control!$D$85)<=0,0,ROUNDUP(((AB41-VLOOKUP(Y41,Control!$J$76:$K$82,2,FALSE))/Control!$D$85),0)*Control!$H$90/AB41) -> 0 | AM41: =IF(I41="Corpus Christi",Control!$D$76,0) -> 0 | AN41: 0 | AO41: =Control!$D$78 -> 0 | AP41: =Control!$D$79 -> 0.0673 | AQ41: =IF(INDEX(Control!$Q$3:$S$62,MATCH($Z41,Control!$Q$3:$Q$62,0),MATCH(AQ$9,Control!$Q$3:$S$3,0))=1,Control!$D$81*Control!$E$81,0) -> 0.2 | AS41: =IF(AND(Y41="VLCC",Control!$K$79=1200000),Control!$D$83/AB41,0) -> 0 | AU41: =SUM(AI41:AT41) -> 0.88097534 | AV41: =+R41+AE41+AU41 -> 14.380975 | AW41: =IF((MONTH(A41)=MONTH(BH41)),0,IF(((MONTH(BH41))-MONTH(A41))+12*YEAR(BG41)-YEAR(A41)>1,SUMIFS($BD$4:$BH$4,$BD$3:$BH$3,"<="&EOMONTH(BG41,-1),$BD$3:$BH$3,">="&EOMONTH(A41,0)),VLOOKUP("Spreads",$BC$3:$BH$4,MATCH(EOMONTH(A41,0),$BC$3:$BH$3,0)))) -> 2.9 | AX41: =+IF(BF41="Dated",-INDEX($BC$3:$BH$6,MATCH(BF41,$BC$3:$BC$6,0),MATCH(BG41,$BC$3:$BH$3,0)),INDEX($BC$3:$BH$6,MATCH(BF41,$BC$3:$BC$6,0),MATCH(BG41,$BC$3:$BH$3,0))) -> -0.9 | AY41: =1/INDEX($BC$3:$BH$7,MATCH("CMA",$BC$3:$BC$7,0),MATCH(BG41,$BC$3:$BH$3,0))*INDEX($BC$3:$BH$7,MATCH("Spreads",$BC$3:$BC$7,0),MATCH(BG41,$BC$3:$BH$3,0)) -> 0.097826087 | AZ41: =$Y$3+AV41+AW41+AX41+AY41 -> 12.878801 | BC41: =+INDEX('[1]Transit Time'!$A:$DZ,MATCH(V41,'[1]Transit Time'!$A:$A,0),MATCH(Z41,'[1]Transit Time'!$A$1:$DZ$1,0)) -> 54 | BD41: =IF(ISBLANK(A41),"",E41+$BC41) -> 46390 | BE41: =BD41+2 -> 46392 | BF41: Dubai | BG41: =IF($BC$8=0,IF(BF41="ICE Brent",EOMONTH(BE41,2),EOMONTH(BE41,0)),IF(BF41="ICE Brent",EOMONTH(BE41,1),EOMONTH(BE41,-1))) -> 46387 | BH41: =IF($BC$8=1,EOMONTH(BE41,-1),EOMONTH(BE41,0)) -> 46387 | BI41: =(AE41*AB41)/1000 -> 13500 | BJ41: 0 | BK41: =AI41*AB41/1000 -> 190 | BL41: =AL41*AB41/1000 -> 0 | BM41: =(AJ41+AK41)*AB41/1000 -> 423.67534 | BN41: =(AU41-AI41-AJ41-AK41-AL41)*AB41/1000 -> 267.3
A42: =+$A$10 -> 46334 | B42: =IF(ISBLANK(A42),"",A42+2) -> 46336 | D42: =IF(AL42=0,0,VLOOKUP(Y42,Control!$G$41:$J$44,4,FALSE)) -> 0 | E42: =A42+2+D42 -> 46336 | T42: =INDEX('[2]Flat Rates 2025'!$A:$DZ,MATCH(V42,'[2]Flat Rates 2025'!$A:$A,0),MATCH(Z42,'[2]Flat Rates 2025'!$A$1:$DZ$1,0)) -> 0 | U42: =INDEX(Control!$E$17:$J$21,MATCH(Y42,Control!$E$17:$E$21,0),MATCH(V42,Control!$E$17:$J$17,0)) -> #N/A | V42: Corpus Christi | W42: =INDEX(Vessel_Minimum_MT,MATCH(Y42,Control!$E$11:$E$15,0),MATCH(V42,Control!$E$11:$J$11,0)) -> #N/A | X42: =AB42/Control!$D$84 -> 128709.95 | Y42: Suezmax-MODA | Z42: Daesan | AA42: =IF(Z42=V42,"",CONCATENATE(CONCATENATE(VLOOKUP(V42,Zones,2,FALSE),"/",VLOOKUP(Z42,Zones,2,FALSE)))) -> USGC/KOREA | AB42: 1000000 | AC42: 1001 | AD42: =AD41+900000 -> 14400000 | AE42: =IF(AC42>1000,IF(AD42=0,AC42,AD42)/AB42,((W42*T42*(IF(AD42=0,AC42,AD42)/100))+IF(X42<W42,0,(X42-W42)*T42*IF(AD42=0,AC42,AD42)/100*U42))/AB42) -> 14.4 | AF42: =$AF$38 -> 2 | AG42: =INDEX(Control!$AS$36:$AY$118,MATCH(WTI!$Z42,Control!$AS$36:$AS$118,0),MATCH(WTI!AG$23,Control!$AS$36:$AY$36,0)) -> -9.5 | AH42: =INDEX(Control!$AS$36:$AY$118,MATCH(WTI!$Z42,Control!$AS$36:$AS$118,0),MATCH(WTI!AH$23,Control!$AS$36:$AY$36,0))-9 -> 29.5 | AI42: =AF42*VLOOKUP($Y42,Control!$F$75:$H$87,3,FALSE)/$AB42 -> 0.19 | AJ42: =IF($AK$3=1,$AG42*Control!$D$77,0) -> 0 | AK42: =IF($AK$4=1,$AH42*Control!$D$77,0) -> 0.38456685 | AL42: =AL60 -> 0 | AM42: =IF(I42="Corpus Christi",Control!$D$76,0) -> 0 | AN42: 0 | AO42: =Control!$D$78 -> 0 | AP42: =Control!$D$79 -> 0.0673 | AQ42: =IF(INDEX(Control!$Q$3:$S$62,MATCH($Z42,Control!$Q$3:$Q$62,0),MATCH(AQ$9,Control!$Q$3:$S$3,0))=1,Control!$D$81*Control!$E$81,0) -> 0.2 | AS42: =IF(AND(Y42="VLCC",Control!$K$79=1200000),Control!$D$83/AB42,0) -> 0 | AU42: =SUM(AI42:AT42) -> 0.84186685 | AV42: =+R42+AE42+AU42 -> 15.241867 | AW42: =IF((MONTH(A42)=MONTH(BH42)),0,IF(((MONTH(BH42))-MONTH(A42))+12*YEAR(BG42)-YEAR(A42)>1,SUMIFS($BD$4:$BH$4,$BD$3:$BH$3,"<="&EOMONTH(BG42,-1),$BD$3:$BH$3,">="&EOMONTH(A42,0)),VLOOKUP("Spreads",$BC$3:$BH$4,MATCH(EOMONTH(A42,0),$BC$3:$BH$3,0)))) -> 2.9 | AX42: =+IF(BF42="Dated",-INDEX($BC$3:$BH$6,MATCH(BF42,$BC$3:$BC$6,0),MATCH(BG42,$BC$3:$BH$3,0)),INDEX($BC$3:$BH$6,MATCH(BF42,$BC$3:$BC$6,0),MATCH(BG42,$BC$3:$BH$3,0))) -> -3.98 | AY42: =1/INDEX($BC$3:$BH$7,MATCH("CMA",$BC$3:$BC$7,0),MATCH(BG42,$BC$3:$BH$3,0))*INDEX($BC$3:$BH$7,MATCH("Spreads",$BC$3:$BC$7,0),MATCH(BG42,$BC$3:$BH$3,0)) -> 0.097826087 | AZ42: =$Y$3+AV42+AW42+AX42+AY42 -> 10.659693 | BC42: =+INDEX('[1]Transit Time'!$A:$DZ,MATCH(V42,'[1]Transit Time'!$A:$A,0),MATCH(Z42,'[1]Transit Time'!$A$1:$DZ$1,0)) -> 54 | BD42: =IF(ISBLANK(A42),"",E42+$BC42) -> 46390 | BE42: =BD42+2 -> 46392 | BF42: =BF46 -> Dated | BG42: =IF($BC$8=0,IF(BF42="ICE Brent",EOMONTH(BE42,2),EOMONTH(BE42,0)),IF(BF42="ICE Brent",EOMONTH(BE42,1),EOMONTH(BE42,-1))) -> 46387 | BH42: =IF($BC$8=1,EOMONTH(BE42,-1),EOMONTH(BE42,0)) -> 46387 | BI42: =(AE42*AB42)/1000 -> 14400 | BJ42: 0 | BK42: =AI42*AB42/1000 -> 190 | BL42: =AL42*AB42/1000 -> 0 | BM42: =(AJ42+AK42)*AB42/1000 -> 384.56685 | BN42: =(AU42-AI42-AJ42-AK42-AL42)*AB42/1000 -> 267.3
A43: =A42 -> 46334 | B43: =IF(ISBLANK(A43),"",A43+2) -> 46336 | D43: =IF(AL43=0,0,VLOOKUP(Y43,Control!$G$41:$J$44,4,FALSE)) -> 9 | E43: =A43+2+D43 -> 46345 | T43: =INDEX('[2]Flat Rates 2025'!$A:$DZ,MATCH(V43,'[2]Flat Rates 2025'!$A:$A,0),MATCH(Z43,'[2]Flat Rates 2025'!$A$1:$DZ$1,0)) -> 0 | U43: =INDEX(Control!$E$17:$J$21,MATCH(Y43,Control!$E$17:$E$21,0),MATCH(V43,Control!$E$17:$J$17,0)) -> 0.5 | V43: Corpus Christi | W43: =INDEX(Vessel_Minimum_MT,MATCH(Y43,Control!$E$11:$E$15,0),MATCH(V43,Control!$E$11:$J$11,0)) -> 270000 | X43: =AB43/Control!$D$84 -> 267073.16 | Y43: VLCC | Z43: Daesan | AA43: =IF(Z43=V43,"",CONCATENATE(CONCATENATE(VLOOKUP(V43,Zones,2,FALSE),"/",VLOOKUP(Z43,Zones,2,FALSE)))) -> USGC/KOREA | AB43: 2075000 | AC43: 1001 | AD43: 55000000 | AE43: =IF(AC43>1000,IF(AD43=0,AC43,AD43)/AB43,((W43*T43*(IF(AD43=0,AC43,AD43)/100))+IF(X43<W43,0,(X43-W43)*T43*IF(AD43=0,AC43,AD43)/100*U43))/AB43) -> 26.506024 | AF43: 5 | AG43: =INDEX(Control!$AS$36:$AY$118,MATCH(WTI!$Z43,Control!$AS$36:$AS$118,0),MATCH(WTI!AG$23,Control!$AS$36:$AY$36,0)) -> -9.5 | AH43: =INDEX(Control!$AS$36:$AY$118,MATCH(WTI!$Z43,Control!$AS$36:$AS$118,0),MATCH(WTI!AH$23,Control!$AS$36:$AY$36,0)) -> 38.5 | AI43: =AF43*VLOOKUP($Y43,Control!$F$75:$H$87,3,FALSE)/$AB43 -> 1.0843373 | AK43: =IF($AK$4=1,$AH43*Control!$D$77,0) -> 0.50189233 | AL43: =IF(((AB43-VLOOKUP(Y43,Control!$J$76:$K$80,2,FALSE))/Control!$D$85)<=0,0,ROUNDUP(((AB43-VLOOKUP(Y43,Control!$J$76:$K$80,2,FALSE))/Control!$D$85),0)*Control!$H$90/AB43) -> 2.6746988 | AM43: =IF(I43="Corpus Christi",Control!$D$76,0) -> 0 | AN43: 0 | AO43: =Control!$D$78 -> 0 | AP43: =Control!$D$79 -> 0.0673 | AQ43: =IF(INDEX(Control!$Q$3:$S$62,MATCH($Z43,Control!$Q$3:$Q$62,0),MATCH(AQ$9,Control!$Q$3:$S$3,0))=1,Control!$D$81*Control!$E$81,0) -> 0.2 | AS43: =IF(AND(Y43="VLCC",Control!$K$79=1200000),Control!$D$83/AB43,0) -> 0 | AU43: =SUM(AI43:AT43) -> 4.5282285 | AV43: =+R43+AE43+AU43 -> 31.034253 | AW43: =IF((MONTH(A43)=MONTH(BH43)),0,IF(((MONTH(BH43))-MONTH(A43))+12*YEAR(BG43)-YEAR(A43)>1,SUMIFS($BD$4:$BH$4,$BD$3:$BH$3,"<="&EOMONTH(BG43,-1),$BD$3:$BH$3,">="&EOMONTH(A43,0)),VLOOKUP("Spreads",$BC$3:$BH$4,MATCH(EOMONTH(A43,0),$BC$3:$BH$3,0)))) -> 2.9 | AX43: =+IF(BF43="Dated",-INDEX($BC$3:$BH$6,MATCH(BF43,$BC$3:$BC$6,0),MATCH(BG43,$BC$3:$BH$3,0)),INDEX($BC$3:$BH$6,MATCH(BF43,$BC$3:$BC$6,0),MATCH(BG43,$BC$3:$BH$3,0))) -> -0.9 | AY43: =1/INDEX($BC$3:$BH$7,MATCH("CMA",$BC$3:$BC$7,0),MATCH(BG43,$BC$3:$BH$3,0))*INDEX($BC$3:$BH$7,MATCH("Spreads",$BC$3:$BC$7,0),MATCH(BG43,$BC$3:$BH$3,0)) -> 0.097826087 | AZ43: =$Y$3+AV43+AW43+AX43+AY43 -> 29.532079 | BC43: 52 | BD43: =IF(ISBLANK(A43),"",E43+$BC43) -> 46397 | BE43: =BD43+2 -> 46399 | BF43: =HLOOKUP($BC$3,$AV$4:$AX$5,2,FALSE) -> Dubai | BG43: =BG34 -> 46387 | BH43: =IF($BC$8=1,EOMONTH(BE43,-1),EOMONTH(BE43,0)) -> 46387 | BI43: =(AE43*AB43)/1000 -> 55000 | BJ43: 0 | BK43: =AI43*AB43/1000 -> 2250 | BL43: =AL43*AB43/1000 -> 5550 | BM43: =(AJ43+AK43)*AB43/1000 -> #VALUE! | BN43: =(AU43-AI43-AJ43-AK43-AL43)*AB43/1000 -> #VALUE!
A44: =+$A$10 -> 46334 | B44: =IF(ISBLANK(A44),"",A44+2) -> 46336 | D44: =IF(AL44=0,0,VLOOKUP(Y44,Control!$G$41:$J$44,4,FALSE)) -> 9 | E44: =A44+2+D44 -> 46345 | T44: =INDEX('[2]Flat Rates 2025'!$A:$DZ,MATCH(V44,'[2]Flat Rates 2025'!$A:$A,0),MATCH(Z44,'[2]Flat Rates 2025'!$A$1:$DZ$1,0)) -> 0 | U44: =INDEX(Control!$E$17:$J$21,MATCH(Y44,Control!$E$17:$E$21,0),MATCH(V44,Control!$E$17:$J$17,0)) -> 0.5 | V44: Corpus Christi | W44: =INDEX(Vessel_Minimum_MT,MATCH(Y44,Control!$E$11:$E$15,0),MATCH(V44,Control!$E$11:$J$11,0)) -> 270000 | X44: =AB44/Control!$D$84 -> 267073.16 | Y44: VLCC | Z44: Singapore | AA44: =IF(Z44=V44,"",CONCATENATE(CONCATENATE(VLOOKUP(V44,Zones,2,FALSE),"/",VLOOKUP(Z44,Zones,2,FALSE)))) -> USGC/Singapore | AB44: =$AB$43 -> 2075000 | AC44: 1001 | AD44: =AD43-1000000 -> 54000000 | AE44: =IF(AC44>1000,IF(AD44=0,AC44,AD44)/AB44,((W44*T44*(IF(AD44=0,AC44,AD44)/100))+IF(X44<W44,0,(X44-W44)*T44*IF(AD44=0,AC44,AD44)/100*U44))/AB44) -> 26.024096 | AF44: =$AF$43 -> 5 | AG44: =INDEX(Control!$AS$36:$AY$118,MATCH(WTI!$Z44,Control!$AS$36:$AS$118,0),MATCH(WTI!AG$23,Control!$AS$36:$AY$36,0)) -> -9.5 | AH44: =INDEX(Control!$AS$36:$AY$118,MATCH(WTI!$Z44,Control!$AS$36:$AS$118,0),MATCH(WTI!AH$23,Control!$AS$36:$AY$36,0)) -> 28.5 | AI44: =AF44*VLOOKUP($Y44,Control!$F$75:$H$87,3,FALSE)/$AB44 -> 1.0843373 | AJ44: =IF($AK$3=1,$AG44*Control!$D$77,0) -> 0 | AK44: =IF($AK$4=1,$AH44*Control!$D$77,0) -> 0.37153068 | AL44: =IF(((AB44-VLOOKUP(Y44,Control!$J$76:$K$80,2,FALSE))/Control!$D$85)<=0,0,ROUNDUP(((AB44-VLOOKUP(Y44,Control!$J$76:$K$80,2,FALSE))/Control!$D$85),0)*Control!$H$90/AB44) -> 2.6746988 | AM44: =IF(I44="Corpus Christi",Control!$D$76,0) -> 0 | AN44: 0 | AO44: =Control!$D$78 -> 0 | AP44: =Control!$D$79 -> 0.0673 | AQ44: =IF(INDEX(Control!$Q$3:$S$62,MATCH($Z44,Control!$Q$3:$Q$62,0),MATCH(AQ$9,Control!$Q$3:$S$3,0))=1,Control!$D$81*Control!$E$81,0) -> 0.2 | AS44: =IF(AND(Y44="VLCC",Control!$K$79=1200000),Control!$D$83/AB44,0) -> 0 | AU44: =SUM(AI44:AT44) -> 4.3978668 | AV44: =+R44+AE44+AU44 -> 30.421963 | AW44: =IF((MONTH(A44)=MONTH(BH44)),0,IF(((MONTH(BH44))-MONTH(A44))+12*YEAR(BG44)-YEAR(A44)>1,SUMIFS($BD$4:$BH$4,$BD$3:$BH$3,"<="&EOMONTH(BG44,-1),$BD$3:$BH$3,">="&EOMONTH(A44,0)),VLOOKUP("Spreads",$BC$3:$BH$4,MATCH(EOMONTH(A44,0),$BC$3:$BH$3,0)))) -> 2.9 | AX44: =+IF(BF44="Dated",-INDEX($BC$3:$BH$6,MATCH(BF44,$BC$3:$BC$6,0),MATCH(BG44,$BC$3:$BH$3,0)),INDEX($BC$3:$BH$6,MATCH(BF44,$BC$3:$BC$6,0),MATCH(BG44,$BC$3:$BH$3,0))) -> -3.98 | AY44: =1/INDEX($BC$3:$BH$7,MATCH("CMA",$BC$3:$BC$7,0),MATCH(BG44,$BC$3:$BH$3,0))*INDEX($BC$3:$BH$7,MATCH("Spreads",$BC$3:$BC$7,0),MATCH(BG44,$BC$3:$BH$3,0)) -> 0.097826087 | AZ44: =$Y$3+AV44+AW44+AX44+AY44 -> 25.839789 | BC44: =+INDEX('[1]Transit Time'!$A:$DZ,MATCH(V44,'[1]Transit Time'!$A:$A,0),MATCH(Z44,'[1]Transit Time'!$A$1:$DZ$1,0)) -> 44 | BD44: =IF(ISBLANK(A44),"",E44+$BC44) -> 46389 | BE44: =BD44+2 -> 46391 | BF44: Dated | BG44: =IF($BH$8=0,IF(BF44="ICE Brent",EOMONTH(BE44,2),EOMONTH(BE44,0)),IF(BF44="ICE Brent",EOMONTH(BE44,1),EOMONTH(BE44,-1))) -> 46387 | BH44: =BG44 -> 46387 | BI44: =(AE44*AB44)/1000 -> 54000 | BJ44: 0 | BK44: =AI44*AB44/1000 -> 2250 | BL44: =AL44*AB44/1000 -> 5550 | BM44: =(AJ44+AK44)*AB44/1000 -> 770.92617 | BN44: =(AU44-AI44-AJ44-AK44-AL44)*AB44/1000 -> 554.6475
A45: =+$A$10 -> 46334 | B45: =IF(ISBLANK(A45),"",A45+2) -> 46336 | D45: =IF(AL45=0,0,VLOOKUP(Y45,Control!$G$41:$J$44,4,FALSE)) -> 9 | E45: =A45+2+D45 -> 46345 | T45: =INDEX('[2]Flat Rates 2025'!$A:$DZ,MATCH(V45,'[2]Flat Rates 2025'!$A:$A,0),MATCH(Z45,'[2]Flat Rates 2025'!$A$1:$DZ$1,0)) -> 0 | U45: =INDEX(Control!$E$17:$J$21,MATCH(Y45,Control!$E$17:$E$21,0),MATCH(V45,Control!$E$17:$J$17,0)) -> 0.5 | V45: Corpus Christi | W45: =INDEX(Vessel_Minimum_MT,MATCH(Y45,Control!$E$11:$E$15,0),MATCH(V45,Control!$E$11:$J$11,0)) -> 270000 | X45: =AB45/Control!$D$84 -> 267073.16 | Y45: VLCC | Z45: Singapore | AA45: =IF(Z45=V45,"",CONCATENATE(CONCATENATE(VLOOKUP(V45,Zones,2,FALSE),"/",VLOOKUP(Z45,Zones,2,FALSE)))) -> USGC/Singapore | AB45: =AB44 -> 2075000 | AC45: 1001 | AD45: =AD44 -> 54000000 | AE45: =IF(AC45>1000,IF(AD45=0,AC45,AD45)/AB45,((W45*T45*(IF(AD45=0,AC45,AD45)/100))+IF(X45<W45,0,(X45-W45)*T45*IF(AD45=0,AC45,AD45)/100*U45))/AB45) -> 26.024096 | AF45: 5 | AG45: =INDEX(Control!$AS$36:$AY$118,MATCH(WTI!$Z45,Control!$AS$36:$AS$118,0),MATCH(WTI!AG$23,Control!$AS$36:$AY$36,0)) -> -9.5 | AH45: =INDEX(Control!$AS$36:$AY$118,MATCH(WTI!$Z45,Control!$AS$36:$AS$118,0),MATCH(WTI!AH$23,Control!$AS$36:$AY$36,0))-6 -> 22.5 | AI45: =AF45*VLOOKUP($Y45,Control!$F$75:$H$87,3,FALSE)/$AB45 -> 1.0843373 | AJ45: =IF($AK$3=1,$AG45*Control!$D$77,0) -> 0 | AK45: =IF($AK$4=1,$AH45*Control!$D$77,0) -> 0.2933137 | AL45: =IF(((AB45-VLOOKUP(Y45,Control!$J$76:$K$82,2,FALSE))/Control!$D$85)<=0,0,ROUNDUP(((AB45-VLOOKUP(Y45,Control!$J$76:$K$82,2,FALSE))/Control!$D$85),0)*Control!$H$90/AB45) -> 2.6746988 | AM45: =IF(I45="Corpus Christi",Control!$D$76,0) -> 0 | AN45: 0 | AO45: =Control!$D$78 -> 0 | AP45: =Control!$D$79 -> 0.0673 | AQ45: =IF(INDEX(Control!$Q$3:$S$62,MATCH($Z45,Control!$Q$3:$Q$62,0),MATCH(AQ$9,Control!$Q$3:$S$3,0))=1,Control!$D$81*Control!$E$81,0) -> 0.2 | AS45: =IF(AND(Y45="VLCC",Control!$K$79=1200000),Control!$D$83/AB45,0) -> 0 | AU45: =SUM(AI45:AT45) -> 4.3196498 | AV45: =+R45+AE45+AU45 -> 30.343746 | AW45: =IF((MONTH(A45)=MONTH(BH45)),0,IF(((MONTH(BH45))-MONTH(A45))+12*YEAR(BG45)-YEAR(A45)>1,SUMIFS($BD$4:$BH$4,$BD$3:$BH$3,"<="&EOMONTH(BG45,-1),$BD$3:$BH$3,">="&EOMONTH(A45,0)),VLOOKUP("Spreads",$BC$3:$BH$4,MATCH(EOMONTH(A45,0),$BC$3:$BH$3,0)))) -> 2.9 | AX45: =+IF(BF45="Dated",-INDEX($BC$3:$BH$6,MATCH(BF45,$BC$3:$BC$6,0),MATCH(BG45,$BC$3:$BH$3,0)),INDEX($BC$3:$BH$6,MATCH(BF45,$BC$3:$BC$6,0),MATCH(BG45,$BC$3:$BH$3,0))) -> -0.9 | AY45: =1/INDEX($BC$3:$BH$7,MATCH("CMA",$BC$3:$BC$7,0),MATCH(BG45,$BC$3:$BH$3,0))*INDEX($BC$3:$BH$7,MATCH("Spreads",$BC$3:$BC$7,0),MATCH(BG45,$BC$3:$BH$3,0)) -> 0.097826087 | AZ45: =$Y$3+AV45+AW45+AX45+AY45 -> 28.841572 | BC45: =+INDEX('[1]Transit Time'!$A:$DZ,MATCH(V45,'[1]Transit Time'!$A:$A,0),MATCH(Z45,'[1]Transit Time'!$A$1:$DZ$1,0)) -> 44 | BD45: =IF(ISBLANK(A45),"",E45+$BC45) -> 46389 | BE45: =BD45+2 -> 46391 | BF45: =HLOOKUP($BC$3,$AV$4:$AX$5,2,FALSE) -> Dubai | BG45: =IF($BC$8=0,IF(BF45="ICE Brent",EOMONTH(BE45,2),EOMONTH(BE45,0)),IF(BF45="ICE Brent",EOMONTH(BE45,1),EOMONTH(BE45,-1))) -> 46387 | BH45: =IF($BC$8=1,EOMONTH(BE45,-1),EOMONTH(BE45,0)) -> 46387 | BI45: =(AE45*AB45)/1000 -> 54000 | BJ45: 0 | BK45: =AI45*AB45/1000 -> 2250 | BL45: =AL45*AB45/1000 -> 5550 | BM45: =(AJ45+AK45)*AB45/1000 -> 608.62592 | BN45: =(AU45-AI45-AJ45-AK45-AL45)*AB45/1000 -> 554.6475
A46: =+$A$10 -> 46334 | B46: =IF(ISBLANK(A46),"",A46+2) -> 46336 | D46: =IF(AL46=0,0,VLOOKUP(Y46,Control!$G$41:$J$44,4,FALSE)) -> 9 | E46: =A46+2+D46 -> 46345 | T46: =INDEX('[2]Flat Rates 2025'!$A:$DZ,MATCH(V46,'[2]Flat Rates 2025'!$A:$A,0),MATCH(Z46,'[2]Flat Rates 2025'!$A$1:$DZ$1,0)) -> 0 | U46: =INDEX(Control!$E$17:$J$21,MATCH(Y46,Control!$E$17:$E$21,0),MATCH(V46,Control!$E$17:$J$17,0)) -> 0.5 | V46: Corpus Christi | W46: =INDEX(Vessel_Minimum_MT,MATCH(Y46,Control!$E$11:$E$15,0),MATCH(V46,Control!$E$11:$J$11,0)) -> 270000 | X46: =AB46/Control!$D$84 -> 267073.16 | Y46: VLCC | Z46: Jamnagar | AA46: =IF(Z46=V46,"",CONCATENATE(CONCATENATE(VLOOKUP(V46,Zones,2,FALSE),"/",VLOOKUP(Z46,Zones,2,FALSE)))) -> USGC/INDIA | AB46: =$AB$43 -> 2075000 | AC46: 1001 | AD46: =AD44 -> 54000000 | AE46: =IF(AC46>1000,IF(AD46=0,AC46,AD46)/AB46,((W46*T46*(IF(AD46=0,AC46,AD46)/100))+IF(X46<W46,0,(X46-W46)*T46*IF(AD46=0,AC46,AD46)/100*U46))/AB46) -> 26.024096 | AF46: =$AF$43 -> 5 | AG46: =INDEX(Control!$AS$36:$AY$118,MATCH(WTI!$Z46,Control!$AS$36:$AS$118,0),MATCH(WTI!AG$23,Control!$AS$36:$AY$36,0)) -> -9.5 | AH46: =INDEX(Control!$AS$36:$AY$118,MATCH(WTI!$Z46,Control!$AS$36:$AS$118,0),MATCH(WTI!AH$23,Control!$AS$36:$AY$36,0)) -> 25.5 | AI46: =AF46*VLOOKUP($Y46,Control!$F$75:$H$87,3,FALSE)/$AB46 -> 1.0843373 | AJ46: =IF($AK$3=1,$AG46*Control!$D$77,0) -> 0 | AK46: =IF($AK$4=1,$AH46*Control!$D$77,0) -> 0.33242219 | AL46: =IF(((AB46-VLOOKUP(Y46,Control!$J$76:$K$80,2,FALSE))/Control!$D$85)<=0,0,ROUNDUP(((AB46-VLOOKUP(Y46,Control!$J$76:$K$80,2,FALSE))/Control!$D$85),0)*Control!$H$90/AB46) -> 2.6746988 | AM46: =IF(I46="Corpus Christi",Control!$D$76,0) -> 0 | AN46: 0 | AO46: =Control!$D$78 -> 0 | AP46: =Control!$D$79 -> 0.0673 | AQ46: =IF(INDEX(Control!$Q$3:$S$62,MATCH($Z46,Control!$Q$3:$Q$62,0),MATCH(AQ$9,Control!$Q$3:$S$3,0))=1,Control!$D$81*Control!$E$81,0) -> 0.2 | AS46: =IF(AND(Y46="VLCC",Control!$K$79=1200000),Control!$D$83/AB46,0) -> 0 | AU46: =SUM(AI46:AT46) -> 4.3587583 | AV46: =+R46+AE46+AU46 -> 30.382855 | AW46: =IF((MONTH(A46)=MONTH(BH46)),0,IF(((MONTH(BH46))-MONTH(A46))+12*YEAR(BG46)-YEAR(A46)>1,SUMIFS($BD$4:$BH$4,$BD$3:$BH$3,"<="&EOMONTH(BG46,-1),$BD$3:$BH$3,">="&EOMONTH(A46,0)),VLOOKUP("Spreads",$BC$3:$BH$4,MATCH(EOMONTH(A46,0),$BC$3:$BH$3,0)))) -> 2.9 | AX46: =+IF(BF46="Dated",-INDEX($BC$3:$BH$6,MATCH(BF46,$BC$3:$BC$6,0),MATCH(BG46,$BC$3:$BH$3,0)),INDEX($BC$3:$BH$6,MATCH(BF46,$BC$3:$BC$6,0),MATCH(BG46,$BC$3:$BH$3,0))) -> -3.98 | AY46: =1/INDEX($BC$3:$BH$7,MATCH("CMA",$BC$3:$BC$7,0),MATCH(BG46,$BC$3:$BH$3,0))*INDEX($BC$3:$BH$7,MATCH("Spreads",$BC$3:$BC$7,0),MATCH(BG46,$BC$3:$BH$3,0)) -> 0.097826087 | AZ46: =$Y$3+AV46+AW46+AX46+AY46 -> 25.800681 | BC46: =+INDEX('[1]Transit Time'!$A:$DZ,MATCH(V46,'[1]Transit Time'!$A:$A,0),MATCH(Z46,'[1]Transit Time'!$A$1:$DZ$1,0))+2 -> 43 | BD46: =IF(ISBLANK(A46),"",E46+$BC46) -> 46388 | BE46: =BD46+2 -> 46390 | BF46: Dated | BG46: =IF($BC$8=0,IF(BF46="ICE Brent",EOMONTH(BE46,2),EOMONTH(BE46,0)),IF(BF46="ICE Brent",EOMONTH(BE46,1),EOMONTH(BE46,-1))) -> 46387 | BH46: =IF($BC$8=1,EOMONTH(BE46,-1),EOMONTH(BE46,0)) -> 46387 | BI46: =(AE46*AB46)/1000 -> 54000 | BJ46: 0 | BK46: =AI46*AB46/1000 -> 2250 | BL46: =AL46*AB46/1000 -> 5550 | BM46: =(AJ46+AK46)*AB46/1000 -> 689.77605 | BN46: =(AU46-AI46-AJ46-AK46-AL46)*AB46/1000 -> 554.6475
A47: =+$A$10 -> 46334 | B47: =IF(ISBLANK(A47),"",A47+2) -> 46336 | D47: =IF(AL47=0,0,VLOOKUP(Y47,Control!$G$41:$J$44,4,FALSE)) -> 9 | E47: =A47+2+D47 -> 46345 | T47: =INDEX('[2]Flat Rates 2025'!$A:$DZ,MATCH(V47,'[2]Flat Rates 2025'!$A:$A,0),MATCH(Z47,'[2]Flat Rates 2025'!$A$1:$DZ$1,0)) -> #N/A | U47: =INDEX(Control!$E$17:$J$21,MATCH(Y47,Control!$E$17:$E$21,0),MATCH(V47,Control!$E$17:$J$17,0)) -> 0.5 | V47: Corpus Christi | W47: =INDEX(Vessel_Minimum_MT,MATCH(Y47,Control!$E$11:$E$15,0),MATCH(V47,Control!$E$11:$J$11,0)) -> 270000 | X47: =AB47/Control!$D$84 -> 267073.16 | Y47: VLCC | Z47: Taiwan | AA47: =AA43 -> USGC/KOREA | AB47: =+$AB$46 -> 2075000 | AC47: 1001 | AD47: =AD43-350000 -> 54650000 | AE47: =IF(AC47>1000,IF(AD47=0,AC47,AD47)/AB47,((W47*T47*(IF(AD47=0,AC47,AD47)/100))+IF(X47<W47,0,(X47-W47)*T47*IF(AD47=0,AC47,AD47)/100*U47))/AB47) -> 26.337349 | AF47: =$AF$43 -> 5 | AG47: =INDEX(Control!$AS$36:$AY$118,MATCH(WTI!$Z47,Control!$AS$36:$AS$118,0),MATCH(WTI!AG$23,Control!$AS$36:$AY$36,0)) -> -9.5 | AH47: =INDEX(Control!$AS$36:$AY$118,MATCH(WTI!$Z47,Control!$AS$36:$AS$118,0),MATCH(WTI!AH$23,Control!$AS$36:$AY$36,0)) -> 30.5 | AI47: =AF47*VLOOKUP($Y47,Control!$F$75:$H$87,3,FALSE)/$AB47 -> 1.0843373 | AJ47: =IF($AK$3=1,$AG47*Control!$D$77,0) -> 0 | AK47: =IF($AK$4=1,$AH47*Control!$D$77,0) -> 0.39760301 | AL47: =IF(((AB47-VLOOKUP(Y47,Control!$J$76:$K$80,2,FALSE))/Control!$D$85)<=0,0,ROUNDUP(((AB47-VLOOKUP(Y47,Control!$J$76:$K$80,2,FALSE))/Control!$D$85),0)*Control!$H$90/AB47) -> 2.6746988 | AM47: =IF(I47="Corpus Christi",Control!$D$76,0) -> 0 | AN47: 0 | AO47: =Control!$D$78 -> 0 | AP47: =Control!$D$79 -> 0.0673 | AS47: =IF(AND(Y47="VLCC",Control!$K$79=1200000),Control!$D$83/AB47,0) -> 0 | AU47: =SUM(AI47:AT47) -> 4.2239392 | AV47: =+R47+AE47+AU47 -> 30.561289 | AW47: =IF((MONTH(A47)=MONTH(BH47)),0,IF(((MONTH(BH47))-MONTH(A47))+12*YEAR(BG47)-YEAR(A47)>1,SUMIFS($BD$4:$BH$4,$BD$3:$BH$3,"<="&EOMONTH(BG47,-1),$BD$3:$BH$3,">="&EOMONTH(A47,0)),VLOOKUP("Spreads",$BC$3:$BH$4,MATCH(EOMONTH(A47,0),$BC$3:$BH$3,0)))) -> 2.9 | AX47: =+IF(BF47="Dated",-INDEX($BC$3:$BH$6,MATCH(BF47,$BC$3:$BC$6,0),MATCH(BG47,$BC$3:$BH$3,0)),INDEX($BC$3:$BH$6,MATCH(BF47,$BC$3:$BC$6,0),MATCH(BG47,$BC$3:$BH$3,0))) -> -3.98 | AY47: =1/INDEX($BC$3:$BH$7,MATCH("CMA",$BC$3:$BC$7,0),MATCH(BG47,$BC$3:$BH$3,0))*INDEX($BC$3:$BH$7,MATCH("Spreads",$BC$3:$BC$7,0),MATCH(BG47,$BC$3:$BH$3,0)) -> 0.097826087 | AZ47: =$Y$3+AV47+AW47+AX47+AY47 -> 25.979115 | BC47: 48 | BD47: =IF(ISBLANK(A47),"",E47+$BC47) -> 46393 | BE47: =BD47+2 -> 46395 | BF47: Dated | BG47: =IF($BC$8=0,IF(BF47="ICE Brent",EOMONTH(BE47,2),EOMONTH(BE47,0)),IF(BF47="ICE Brent",EOMONTH(BE47,1),EOMONTH(BE47,-1))) -> 46387 | BH47: =IF($BC$8=1,EOMONTH(BE47,-1),EOMONTH(BE47,0)) -> 46387 | BI47: =(AE47*AB47)/1000 -> 54650 | BJ47: 0 | BK47: =AI47*AB47/1000 -> 2250 | BL47: =AL47*AB47/1000 -> 5550 | BM47: =(AJ47+AK47)*AB47/1000 -> 825.02625 | BN47: =(AU47-AI47-AJ47-AK47-AL47)*AB47/1000 -> 139.6475
Y48: CORPUS-EUROPE
A49: Load Window | D49: =D23 -> STS Time | E49: =E23 -> Depart | T49: Flat | U49: Overages | V49: Loadport | W49: =$W$9 -> Vessel MT | X49: Actual MT | Y49: Vessel | Z49: Destination | AA49: Route | AB49: Volume | AC49: =$AC$9 -> Current WS Rate | AD49: WS Rate Call | AE49: Destination Freight | AF49: Demurrage | AG49: =AG9 -> ATA TVM | AH49: =AH9 -> Ext. TVM | AI49: Demurrage $ | AJ49: =AG49 -> ATA TVM | AK49: =AH49 -> Ext. TVM | AL49: =AL9 -> STS | AM49: Wharfage | AN49: Panama Canal | AO49: Insurance | AP49: Inspection | AQ49: Outturn Losses | AR49: EU TAX | AS49: Other costs | AT49: Pipeline Fee | AU49: Total Secondary Costs | AV49: All In Cost | AW49: Structure | AX49: =AX9 -> Basis | AZ49: DES Price | BC49: Transit Time | BD49: Arrival Window | BF49: =BF23 -> Basis | BG49: =BG9 -> Pricing Month | BH49: =BH9 -> Delivery Month | BI49: Freight | BK49: Demurrage | BL49: STS | BM49: TVM | BN49: Other
A50: =A38 -> 46334 | B50: =B38 -> 46336 | D50: =IF(AL50=0,0,VLOOKUP(Y50,Control!$G$41:$J$44,4,FALSE)) -> 0 | E50: =AVERAGE(A50:B50)+D50 -> 46335 | T50: =INDEX([2]Sheet1!$F$2:$AG$5,MATCH($V50,[2]Sheet1!$F$2:$F$5,0),MATCH(Z50,[2]Sheet1!$F$2:$AG$2,0)) -> 11.63 | U50: =INDEX(Control!$E$17:$J$21,MATCH(Y50,Control!$E$17:$E$21,0),MATCH(V50,Control!$E$17:$J$17,0)) -> 0 | V50: Corpus Christi | W50: =INDEX(Vessel_Minimum_MT,MATCH(Y50,Control!$E$11:$E$15,0),MATCH(V50,Control!$E$11:$J$11,0)) -> 70000 | X50: =AB50/Control!$D$84 -> 90096.968 | Y50: Aframax | Z50: Saint John | AA50: =IF(Z50=V50,"",CONCATENATE(CONCATENATE(VLOOKUP(V50,Zones,2,FALSE),"/",VLOOKUP(Z50,Zones,2,FALSE)))) -> USGC/ECC | AB50: 700000 | AC50: 70 | AD50: =AD52+10 -> 930 | AE50: =IF(AC50>1000,IF(AD50=0,AC50,AD50)/AB50,((W50*T50*(IF(AD50=0,AC50,AD50)/100))+IF(X50<W50,0,(X50-W50)*T50*IF(AD50=0,AC50,AD50)/100*U50))/AB50) -> 10.8159 | AF50: 0 | AG50: =AG52 -> -10 | AH50: =AH52 -> 0 | AI50: =AF50*VLOOKUP($Y50,Control!$F$75:$H$87,3,FALSE)/$AB50 -> 0 | AJ50: =IF($AK$3=1,$AG50*Control!$D$77,0) -> 0 | AK50: =IF($AK$4=1,$AH50*Control!$D$77,0) -> 0 | AQ50: =IF(INDEX(Control!$Q$3:$S$62,MATCH($Z50,Control!$Q$3:$Q$62,0),MATCH(AQ$9,Control!$Q$3:$S$3,0))=1,Control!$D$81*Control!$E$81,0) -> 0 | AR50: =IF(INDEX(Control!$Q$3:$S$62,MATCH($Z50,Control!$Q$3:$Q$62,0),MATCH(AR$9,Control!$Q$3:$S$3,0))=1,INDEX(Control!$AK$3:$AO$69,MATCH(WTI!Z50,Control!$AK$3:$AK$29,0),MATCH(WTI!Y50,Control!$AK$3:$AO$3,0))/AB50*1000,0) -> 0 | AS50: =52000/AB50 -> 0.074285714 | AU50: =SUM(AI50:AT50) -> 0.074285714 | AV50: =+R50+AE50+AU50 -> 10.890186 | AW50: =IF((MONTH(A50)=MONTH(BH50)),0,IF(((MONTH(BH50))-MONTH(A50))+12*YEAR(BG50)-YEAR(A50)>1,SUMIFS($BD$4:$BH$4,$BD$3:$BH$3,"<="&EOMONTH(BG50,-1),$BD$3:$BH$3,">="&EOMONTH(A50,0)),VLOOKUP("Spreads",$BC$3:$BH$4,MATCH(EOMONTH(A50,0),$BC$3:$BH$3,0)))) -> 0 | AZ50: =$Y$3+AV50+AW50+AX50 -> 7.2901857 | BC50: =+INDEX('[1]Transit Time'!$A:$DZ,MATCH(V50,'[1]Transit Time'!$A:$A,0),MATCH(Z50,'[1]Transit Time'!$A$1:$DZ$1,0)) -> 8 | BD50: =IF(ISBLANK(A50),"",$BC50+E50) -> 46343 | BE50: =BD50+2 -> 46345 | BF50: =BF51 -> ICE Brent | BG50: =EOMONTH(BE50,0) -> 46356 | BH50: =BG50 -> 46356 | BI50: =(AE50*AB50)/1000 -> 7571.13 | BJ50: 0 | BK50: =AI50*AB50/1000 -> 0 | BL50: =AL50*AB50/1000 -> 0 | BM50: =(AJ50+AK50)*AB50/1000 -> 0 | BN50: =(AU50-AI50-AJ50-AK50-AL50)*AB50/1000 -> 52
A51: =+$A$10 -> 46334 | B51: =IF(ISBLANK(A51),"",A51+2) -> 46336 | D51: =IF(AL51=0,0,VLOOKUP(Y51,Control!$G$41:$J$44,4,FALSE)) -> 0 | E51: =AVERAGE(A51:B51)+D51 -> 46335 | T51: =INDEX([2]Sheet1!$F$2:$AG$5,MATCH($V51,[2]Sheet1!$F$2:$F$5,0),MATCH(Z51,[2]Sheet1!$F$2:$AG$2,0)) -> 11.63 | U51: 0 | V51: Corpus Christi | W51: =INDEX(Vessel_Minimum_MT,MATCH(Y51,Control!$E$11:$E$15,0),MATCH(V51,Control!$E$11:$J$11,0)) -> 145000 | X51: =AB51/Control!$D$84 -> 128709.95 | Y51: Suezmax | Z51: Saint John | AA51: =IF(Z51=V51,"",CONCATENATE(CONCATENATE(VLOOKUP(V51,Zones,2,FALSE),"/",VLOOKUP(Z51,Zones,2,FALSE)))) -> USGC/ECC | AB51: 1000000 | AD51: =AD61+5 -> 555 | AE51: =IF(AC51>1000,IF(AD51=0,AC51,AD51)/AB51,((W51*T51*(IF(AD51=0,AC51,AD51)/100))+IF(X51<W51,0,(X51-W51)*T51*IF(AD51=0,AC51,AD51)/100*U51))/AB51) -> 9.3592425 | AF51: 0 | AG51: =AG50 -> -10 | AH51: =AH50 -> 0 | AI51: =ABH397*VLOOKUP($Y51,Control!$F$75:$H$79,3,FALSE)/$AB51 -> 0 | AJ51: =IF(AG51<0,0,$AG51*Control!$D$77) -> 0 | AM51: =IF(I51="Corpus Christi",Control!$D$76,0) -> 0 | AN51: 0 | AO51: =Control!$D$78 -> 0 | AQ51: =IF(INDEX(Control!$Q$3:$S$62,MATCH($Z51,Control!$Q$3:$Q$62,0),MATCH(AQ$9,Control!$Q$3:$S$3,0))=1,Control!$D$81*Control!$E$81,0) -> 0 | AR51: =IF(INDEX(Control!$Q$3:$S$62,MATCH($Z51,Control!$Q$3:$Q$62,0),MATCH(AR$9,Control!$Q$3:$S$3,0))=1,Control!$D$82/$AB51,0) -> 0 | AS51: =52000/AB51 -> 0.052 | AT51: =IF(AND(L51="Chiriqui Grande",V51="Puerto Armuelles"),Control!$G$93,0) -> 0 | AU51: =SUM(AI51:AT51) -> 0.052 | AV51: =+R51+AE51+AU51 -> 9.4112425 | AW51: =IF((MONTH(A51)=MONTH(BH51)),0,IF(((MONTH(BH51))-MONTH(A51))+12*YEAR(BG51)-YEAR(A51)>1,SUMIFS($BD$4:$BH$4,$BD$3:$BH$3,"<="&EOMONTH(BG51,-1),$BD$3:$BH$3,">="&EOMONTH(A51,0)),VLOOKUP("Spreads",$BC$3:$BH$4,MATCH(EOMONTH(A51,0),$BC$3:$BH$3,0)))) -> 0 | AZ51: =$Y$3+AV51+AW51+AX51 -> 5.8112425 | BC51: =+INDEX('[1]Transit Time'!$A:$DZ,MATCH(V51,'[1]Transit Time'!$A:$A,0),MATCH(Z51,'[1]Transit Time'!$A$1:$DZ$1,0)) -> 8 | BD51: =IF(ISBLANK(A51),"",$BC51+E51) -> 46343 | BE51: =BD51+2 -> 46345 | BF51: ICE Brent | BG51: =BH51 -> 46356 | BH51: =EOMONTH(BE51,0) -> 46356 | BI51: =(AE51*AB51)/1000 -> 9359.2425 | BJ51: 0 | BK51: =AI51*AB51/1000 -> 0 | BL51: =AL51*AB51/1000 -> 0 | BM51: =(AJ51+AK51)*AB51/1000 -> 0 | BN51: =(AU51-AI51-AJ51-AK51-AL51)*AB51/1000 -> 52
A52: =A9 -> 46334 | B52: =B9 -> 46336 | D52: =IF(AL52=0,0,VLOOKUP(Y52,Control!$G$41:$J$44,4,FALSE)) -> 0 | E52: =AVERAGE(A52:B52)+D52 -> 46335 | T52: =INDEX([2]Sheet1!$F$2:$AG$5,MATCH($V52,[2]Sheet1!$F$2:$F$5,0),MATCH(Z52,[2]Sheet1!$F$2:$AG$2,0)) -> 21.51 | U52: =INDEX(Control!$E$17:$J$21,MATCH(Y52,Control!$E$17:$E$21,0),MATCH(V52,Control!$E$17:$J$17,0)) -> 0 | V52: Corpus Christi | W52: =INDEX(Vessel_Minimum_MT,MATCH(Y52,Control!$E$11:$E$15,0),MATCH(V52,Control!$E$11:$J$11,0)) -> 70000 | X52: =AB52/Control!$D$84 -> 90096.968 | Y52: Aframax | Z52: Rotterdam | AA52: =IF(Z52=V52,"",CONCATENATE(CONCATENATE(VLOOKUP(V52,Zones,2,FALSE),"/",VLOOKUP(Z52,Zones,2,FALSE)))) -> USGC/Nsea | AB52: 700000 | AC52: 70 | AD52: 920 | AE52: =IF(AC52>1000,IF(AD52=0,AC52,AD52)/AB52,((W52*T52*(IF(AD52=0,AC52,AD52)/100))+IF(X52<W52,0,(X52-W52)*T52*IF(AD52=0,AC52,AD52)/100*U52))/AB52) -> 19.7892 | AG52: =INDEX(Control!$AS$36:$AY$118,MATCH(WTI!$Z52,Control!$AS$36:$AS$118,0),MATCH(WTI!AG$23,Control!$AS$36:$AY$36,0)) -> -10 | AH52: =INDEX(Control!$AS$36:$AY$118,MATCH(WTI!$Z52,Control!$AS$36:$AS$118,0),MATCH(WTI!AH$23,Control!$AS$36:$AY$36,0)) -> 0 | AI52: =AF52*VLOOKUP($Y52,Control!$F$75:$H$87,3,FALSE)/$AB52 -> 0 | AJ52: =IF($AK$3=1,$AG52*Control!$D$77,0) -> 0 | AK52: =IF($AK$4=1,$AH52*Control!$D$77,0) -> 0 | AP52: =Control!$D$79 -> 0.0673 | AQ52: =IF(INDEX(Control!$Q$3:$S$62,MATCH($Z52,Control!$Q$3:$Q$62,0),MATCH(AQ$9,Control!$Q$3:$S$3,0))=1,Control!$D$81*Control!$E$81,0) -> 0 | AR52: =IF(INDEX(Control!$Q$3:$S$62,MATCH($Z52,Control!$Q$3:$Q$62,0),MATCH(AR$9,Control!$Q$3:$S$3,0))=1,INDEX(Control!$AK$3:$AO$69,MATCH(WTI!Z52,Control!$AK$3:$AK$29,0),MATCH(WTI!Y52,Control!$AK$3:$AO$3,0))/AB52*1000,0) -> 0 | AS52: =93980/AB52 -> 0.13425714 | AU52: =SUM(AI52:AT52) -> 0.20155714 | AV52: =+R52+AE52+AU52 -> 19.990757 | AW52: =IF((MONTH(A52)=MONTH(BH52)),0,IF(((MONTH(BH52))-MONTH(A52))+12*YEAR(BG52)-YEAR(A52)>1,SUMIFS($BD$4:$BH$4,$BD$3:$BH$3,"<="&EOMONTH(BG52,-1),$BD$3:$BH$3,">="&EOMONTH(A52,0)),VLOOKUP("Spreads",$BC$3:$BH$4,MATCH(EOMONTH(A52,0),$BC$3:$BH$3,0)))) -> 0 | AX52: =+IF(BF52="Dated",-INDEX($BC$3:$BH$6,MATCH(BF52,$BC$3:$BC$6,0),MATCH(BG52,$BC$3:$BH$3,0)),INDEX($BC$3:$BH$6,MATCH(BF52,$BC$3:$BC$6,0),MATCH(BG52,$BC$3:$BH$3,0))) -> -5.28 | AY52: =1/INDEX($BC$3:$BH$7,MATCH("CMA",$BC$3:$BC$7,0),MATCH(BG52,$BC$3:$BH$3,0))*INDEX($BC$3:$BH$7,MATCH("Spreads",$BC$3:$BC$7,0),MATCH(BG52,$BC$3:$BH$3,0)) -> 0.13181818 | AZ52: =$Y$3+AV52+AW52+AX52+AY52 -> 11.242575 | BC52: =+INDEX('[1]Transit Time'!$A:$DZ,MATCH(V52,'[1]Transit Time'!$A:$A,0),MATCH(Z52,'[1]Transit Time'!$A$1:$DZ$1,0)) -> 17 | BD52: =IF(ISBLANK(A52),"",$BC52+E52) -> 46352 | BE52: =BD52+2 -> 46354 | BF52: Dated | BG52: =EOMONTH(BE52,0) -> 46356 | BH52: =BG52 -> 46356 | BI52: =(AE52*AB52)/1000 -> 13852.44 | BJ52: 0 | BK52: =AI52*AB52/1000 -> 0 | BL52: =AL52*AB52/1000 -> 0 | BM52: =(AJ52+AK52)*AB52/1000 -> 0 | BN52: =(AU52-AI52-AJ52-AK52-AL52)*AB52/1000 -> 141.09
A53: =+$A$10 -> 46334 | B53: =IF(ISBLANK(A53),"",A53+2) -> 46336 | D53: =IF(AL53=0,0,VLOOKUP(Y53,Control!$G$41:$J$44,4,FALSE)) -> 0 | E53: =AVERAGE(A53:B53)+D53 -> 46335 | T53: =INDEX([2]Sheet1!$F$2:$AG$5,MATCH($V53,[2]Sheet1!$F$2:$F$5,0),MATCH(Z53,[2]Sheet1!$F$2:$AG$2,0)) -> 20.65 | U53: =INDEX(Control!$E$17:$J$21,MATCH(Y53,Control!$E$17:$E$21,0),MATCH(V53,Control!$E$17:$J$17,0)) -> 0 | V53: Corpus Christi | W53: =INDEX(Vessel_Minimum_MT,MATCH(Y53,Control!$E$11:$E$15,0),MATCH(V53,Control!$E$11:$J$11,0)) -> 70000 | X53: =AB53/Control!$D$84 -> 90096.968 | Y53: Aframax | Z53: Tranmere | AA53: =IF(Z53=V53,"",CONCATENATE(CONCATENATE(VLOOKUP(V53,Zones,2,FALSE),"/",VLOOKUP(Z53,Zones,2,FALSE)))) -> USGC/Nsea | AB53: =AB52 -> 700000 | AC53: 70 | AD53: =AD52+5 -> 925 | AE53: =IF(AC53>1000,IF(AD53=0,AC53,AD53)/AB53,((W53*T53*(IF(AD53=0,AC53,AD53)/100))+IF(X53<W53,0,(X53-W53)*T53*IF(AD53=0,AC53,AD53)/100*U53))/AB53) -> 19.10125 | AF53: =$AF$52 -> 0 | AG53: =INDEX(Control!$AS$36:$AY$118,MATCH(WTI!$Z53,Control!$AS$36:$AS$118,0),MATCH(WTI!AG$23,Control!$AS$36:$AY$36,0)) -> -10 | AH53: =INDEX(Control!$AS$36:$AY$118,MATCH(WTI!$Z53,Control!$AS$36:$AS$118,0),MATCH(WTI!AH$23,Control!$AS$36:$AY$36,0)) -> 0 | AI53: =AF53*VLOOKUP($Y53,Control!$F$75:$H$87,3,FALSE)/$AB53 -> 0 | AJ53: =IF($AK$3=1,$AG53*Control!$D$77,0) -> 0 | AK53: =IF($AK$4=1,$AH53*Control!$D$77,0) -> 0 | AL53: =IF(((AB53-VLOOKUP(Y53,Control!$J$76:$K$80,2,FALSE))/Control!$D$85)<=0,0,ROUNDUP(((AB53-VLOOKUP(Y53,Control!$J$76:$K$80,2,FALSE))/Control!$D$85),0)*Control!$H$90/AB53) -> 0 | AM53: =IF(I53="Corpus Christi",Control!$D$76,0) -> 0 | AN53: 0 | AO53: =Control!$D$78 -> 0 | AP53: =Control!$D$79 -> 0.0673 | AQ53: =IF(INDEX(Control!$Q$3:$S$62,MATCH($Z53,Control!$Q$3:$Q$62,0),MATCH(AQ$9,Control!$Q$3:$S$3,0))=1,Control!$D$81*Control!$E$81,0) -> 0 | AR53: =IF(INDEX(Control!$Q$3:$S$62,MATCH($Z53,Control!$Q$3:$Q$62,0),MATCH(AR$9,Control!$Q$3:$S$3,0))=1,INDEX(Control!$AK$3:$AO$69,MATCH(WTI!Z53,Control!$AK$3:$AK$29,0),MATCH(WTI!Y53,Control!$AK$3:$AO$3,0))/AB53*1000,0) -> 0 | AS53: =IF(Z53="Rotterdam",0.114,"") | AU53: =SUM(AI53:AT53) -> 0.0673 | AV53: =+R53+AE53+AU53 -> 19.16855 | AW53: =IF((MONTH(A53)=MONTH(BH53)),0,IF(((MONTH(BH53))-MONTH(A53))+12*YEAR(BG53)-YEAR(A53)>1,SUMIFS($BD$4:$BH$4,$BD$3:$BH$3,"<="&EOMONTH(BG53,-1),$BD$3:$BH$3,">="&EOMONTH(A53,0)),VLOOKUP("Spreads",$BC$3:$BH$4,MATCH(EOMONTH(A53,0),$BC$3:$BH$3,0)))) -> 0 | AX53: =+IF(BF53="Dated",-INDEX($BC$3:$BH$6,MATCH(BF53,$BC$3:$BC$6,0),MATCH(BG53,$BC$3:$BH$3,0)),INDEX($BC$3:$BH$6,MATCH(BF53,$BC$3:$BC$6,0),MATCH(BG53,$BC$3:$BH$3,0))) -> -5.28 | AY53: =1/INDEX($BC$3:$BH$7,MATCH("CMA",$BC$3:$BC$7,0),MATCH(BG53,$BC$3:$BH$3,0))*INDEX($BC$3:$BH$7,MATCH("Spreads",$BC$3:$BC$7,0),MATCH(BG53,$BC$3:$BH$3,0)) -> 0.13181818 | AZ53: =$Y$3+AV53+AW53+AX53+AY53 -> 10.420368 | BC53: =+INDEX('[1]Transit Time'!$A:$DZ,MATCH(V53,'[1]Transit Time'!$A:$A,0),MATCH(Z53,'[1]Transit Time'!$A$1:$DZ$1,0)) -> 17 | BD53: =IF(ISBLANK(A53),"",$BC53+E53) -> 46352 | BE53: =BD53+2 -> 46354 | BF53: Dated | BG53: =EOMONTH(BE53,0) -> 46356 | BH53: =BG53 -> 46356 | BI53: =(AE53*AB53)/1000 -> 13370.875 | BJ53: 0 | BK53: =AI53*AB53/1000 -> 0 | BL53: =AL53*AB53/1000 -> 0 | BM53: =(AJ53+AK53)*AB53/1000 -> 0 | BN53: =(AU53-AI53-AJ53-AK53-AL53)*AB53/1000 -> 47.11
A54: =+$A$10 -> 46334 | B54: =IF(ISBLANK(A54),"",A54+2) -> 46336 | D54: =IF(AL54=0,0,VLOOKUP(Y54,Control!$G$41:$J$44,4,FALSE)) -> 0 | E54: =AVERAGE(A54:B54)+D54 -> 46335 | T54: =INDEX([2]Sheet1!$F$2:$AG$5,MATCH($V54,[2]Sheet1!$F$2:$F$5,0),MATCH(Z54,[2]Sheet1!$F$2:$AG$2,0)) -> 19.41 | U54: =INDEX(Control!$E$17:$J$21,MATCH(Y54,Control!$E$17:$E$21,0),MATCH(V54,Control!$E$17:$J$17,0)) -> 0 | V54: Corpus Christi | W54: =INDEX(Vessel_Minimum_MT,MATCH(Y54,Control!$E$11:$E$15,0),MATCH(V54,Control!$E$11:$J$11,0)) -> 70000 | X54: =AB54/Control!$D$84 -> 90096.968 | Y54: Aframax | Z54: Pembroke | AA54: =IF(Z54=V54,"",CONCATENATE(CONCATENATE(VLOOKUP(V54,Zones,2,FALSE),"/",VLOOKUP(Z54,Zones,2,FALSE)))) -> USGC/Nsea | AB54: =AB53 -> 700000 | AC54: 70 | AD54: =$AD$52 -> 920 | AE54: =IF(AC54>1000,IF(AD54=0,AC54,AD54)/AB54,((W54*T54*(IF(AD54=0,AC54,AD54)/100))+IF(X54<W54,0,(X54-W54)*T54*IF(AD54=0,AC54,AD54)/100*U54))/AB54) -> 17.8572 | AF54: =$AF$52 -> 0 | AG54: =INDEX(Control!$AS$36:$AY$118,MATCH(WTI!$Z54,Control!$AS$36:$AS$118,0),MATCH(WTI!AG$23,Control!$AS$36:$AY$36,0)) -> -10 | AH54: =INDEX(Control!$AS$36:$AY$118,MATCH(WTI!$Z54,Control!$AS$36:$AS$118,0),MATCH(WTI!AH$23,Control!$AS$36:$AY$36,0)) -> 0 | AI54: =AF54*VLOOKUP($Y54,Control!$F$75:$H$87,3,FALSE)/$AB54 -> 0 | AJ54: =IF($AK$3=1,$AG54*Control!$D$77,0) -> 0 | AK54: =IF($AK$4=1,$AH54*Control!$D$77,0) -> 0 | AL54: =IF(((AB54-VLOOKUP(Y54,Control!$J$76:$K$80,2,FALSE))/Control!$D$85)<=0,0,ROUNDUP(((AB54-VLOOKUP(Y54,Control!$J$76:$K$80,2,FALSE))/Control!$D$85),0)*Control!$H$90/AB54) -> 0 | AM54: =IF(I54="Corpus Christi",Control!$D$76,0) -> 0 | AN54: 0 | AO54: =Control!$D$78 -> 0 | AP54: =Control!$D$79 -> 0.0673 | AQ54: =IF(INDEX(Control!$Q$3:$S$62,MATCH($Z54,Control!$Q$3:$Q$62,0),MATCH(AQ$9,Control!$Q$3:$S$3,0))=1,Control!$D$81*Control!$E$81,0) -> 0 | AR54: =IF(INDEX(Control!$Q$3:$S$62,MATCH($Z54,Control!$Q$3:$Q$62,0),MATCH(AR$9,Control!$Q$3:$S$3,0))=1,INDEX(Control!$AK$3:$AO$69,MATCH(WTI!Z54,Control!$AK$3:$AK$29,0),MATCH(WTI!Y54,Control!$AK$3:$AO$3,0))/AB54*1000,0) -> 0 | AS54: =IF(Z54="Rotterdam",0.114,"") | AU54: =SUM(AI54:AT54) -> 0.0673 | AV54: =+R54+AE54+AU54 -> 17.9245 | AW54: =IF((MONTH(A54)=MONTH(BH54)),0,IF(((MONTH(BH54))-MONTH(A54))+12*YEAR(BG54)-YEAR(A54)>1,SUMIFS($BD$4:$BH$4,$BD$3:$BH$3,"<="&EOMONTH(BG54,-1),$BD$3:$BH$3,">="&EOMONTH(A54,0)),VLOOKUP("Spreads",$BC$3:$BH$4,MATCH(EOMONTH(A54,0),$BC$3:$BH$3,0)))) -> 0 | AX54: =+IF(BF54="Dated",-INDEX($BC$3:$BH$6,MATCH(BF54,$BC$3:$BC$6,0),MATCH(BG54,$BC$3:$BH$3,0)),INDEX($BC$3:$BH$6,MATCH(BF54,$BC$3:$BC$6,0),MATCH(BG54,$BC$3:$BH$3,0))) -> -5.28 | AY54: =1/INDEX($BC$3:$BH$7,MATCH("CMA",$BC$3:$BC$7,0),MATCH(BG54,$BC$3:$BH$3,0))*INDEX($BC$3:$BH$7,MATCH("Spreads",$BC$3:$BC$7,0),MATCH(BG54,$BC$3:$BH$3,0)) -> 0.13181818 | AZ54: =$Y$3+AV54+AW54+AX54+AY54 -> 9.1763182 | BC54: =+INDEX('[1]Transit Time'!$A:$DZ,MATCH(V54,'[1]Transit Time'!$A:$A,0),MATCH(Z54,'[1]Transit Time'!$A$1:$DZ$1,0)) -> 17 | BD54: =IF(ISBLANK(A54),"",$BC54+E54) -> 46352 | BE54: =BD54+2 -> 46354 | BF54: Dated | BG54: =EOMONTH(BE54,0) -> 46356 | BH54: =BG54 -> 46356 | BI54: =(AE54*AB54)/1000 -> 12500.04 | BJ54: 0 | BK54: =AI54*AB54/1000 -> 0 | BL54: =AL54*AB54/1000 -> 0 | BM54: =(AJ54+AK54)*AB54/1000 -> 0 | BN54: =(AU54-AI54-AJ54-AK54-AL54)*AB54/1000 -> 47.11
A55: =+$A$10 -> 46334 | B55: =IF(ISBLANK(A55),"",A55+2) -> 46336 | D55: =IF(AL55=0,0,VLOOKUP(Y55,Control!$G$41:$J$44,4,FALSE)) -> 0 | E55: =AVERAGE(A55:B55)+D55 -> 46335 | T55: =INDEX([2]Sheet1!$F$2:$AG$5,MATCH($V55,[2]Sheet1!$F$2:$F$5,0),MATCH(Z55,[2]Sheet1!$F$2:$AG$2,0)) -> 24.91 | U55: =INDEX(Control!$E$17:$J$21,MATCH(Y55,Control!$E$17:$E$21,0),MATCH(V55,Control!$E$17:$J$17,0)) -> 0 | V55: Corpus Christi | W55: =INDEX(Vessel_Minimum_MT,MATCH(Y55,Control!$E$11:$E$15,0),MATCH(V55,Control!$E$11:$J$11,0)) -> 70000 | X55: =AB55/Control!$D$84 -> 90096.968 | Y55: Aframax | Z55: Butinge | AA55: =IF(Z55=V55,"",CONCATENATE(CONCATENATE(VLOOKUP(V55,Zones,2,FALSE),"/",VLOOKUP(Z55,Zones,2,FALSE)))) -> USGC/Nsea | AB55: =AB54 -> 700000 | AC55: 70 | AD55: =$AD$52+10 -> 930 | AE55: =IF(AC55>1000,IF(AD55=0,AC55,AD55)/AB55,((W55*T55*(IF(AD55=0,AC55,AD55)/100))+IF(X55<W55,0,(X55-W55)*T55*IF(AD55=0,AC55,AD55)/100*U55))/AB55) -> 23.1663 | AF55: =$AF$52 -> 0 | AG55: =INDEX(Control!$AS$36:$AY$118,MATCH(WTI!$Z55,Control!$AS$36:$AS$118,0),MATCH(WTI!AG$23,Control!$AS$36:$AY$36,0)) -> -10 | AH55: =INDEX(Control!$AS$36:$AY$118,MATCH(WTI!$Z55,Control!$AS$36:$AS$118,0),MATCH(WTI!AH$23,Control!$AS$36:$AY$36,0)) -> 0 | AI55: =AF55*VLOOKUP($Y55,Control!$F$75:$H$87,3,FALSE)/$AB55 -> 0 | AJ55: =IF($AK$3=1,$AG55*Control!$D$77,0) -> 0 | AK55: =IF($AK$4=1,$AH55*Control!$D$77,0) -> 0 | AL55: =IF(((AB55-VLOOKUP(Y55,Control!$J$76:$K$80,2,FALSE))/Control!$D$85)<=0,0,ROUNDUP(((AB55-VLOOKUP(Y55,Control!$J$76:$K$80,2,FALSE))/Control!$D$85),0)*Control!$H$90/AB55) -> 0 | AM55: =IF(I55="Corpus Christi",Control!$D$76,0) -> 0 | AN55: 0 | AO55: =Control!$D$78 -> 0 | AP55: =Control!$D$79 -> 0.0673 | AQ55: =IF(INDEX(Control!$Q$3:$S$62,MATCH($Z55,Control!$Q$3:$Q$62,0),MATCH(AQ$9,Control!$Q$3:$S$3,0))=1,Control!$D$81*Control!$E$81,0) -> 0.2 | AR55: =IF(INDEX(Control!$Q$3:$S$62,MATCH($Z55,Control!$Q$3:$Q$62,0),MATCH(AR$9,Control!$Q$3:$S$3,0))=1,INDEX(Control!$AK$3:$AO$69,MATCH(WTI!Z55,Control!$AK$3:$AK$29,0),MATCH(WTI!Y55,Control!$AK$3:$AO$3,0))/AB55*1000,0) -> 0 | AS55: =IF(Z55="Rotterdam",0.114,"") | AU55: =SUM(AI55:AT55) -> 0.2673 | AV55: =+R55+AE55+AU55 -> 23.4336 | AW55: =IF((MONTH(A55)=MONTH(BH55)),0,IF(((MONTH(BH55))-MONTH(A55))+12*YEAR(BG55)-YEAR(A55)>1,SUMIFS($BD$4:$BH$4,$BD$3:$BH$3,"<="&EOMONTH(BG55,-1),$BD$3:$BH$3,">="&EOMONTH(A55,0)),VLOOKUP("Spreads",$BC$3:$BH$4,MATCH(EOMONTH(A55,0),$BC$3:$BH$3,0)))) -> 0 | AX55: =+IF(BF55="Dated",-INDEX($BC$3:$BH$6,MATCH(BF55,$BC$3:$BC$6,0),MATCH(BG55,$BC$3:$BH$3,0)),INDEX($BC$3:$BH$6,MATCH(BF55,$BC$3:$BC$6,0),MATCH(BG55,$BC$3:$BH$3,0))) -> -5.28 | AY55: =1/INDEX($BC$3:$BH$7,MATCH("CMA",$BC$3:$BC$7,0),MATCH(BG55,$BC$3:$BH$3,0))*INDEX($BC$3:$BH$7,MATCH("Spreads",$BC$3:$BC$7,0),MATCH(BG55,$BC$3:$BH$3,0)) -> 0.13181818 | AZ55: =$Y$3+AV55+AW55+AX55+AY55 -> 14.685418 | BC55: =+INDEX('[1]Transit Time'!$A:$DZ,MATCH(V55,'[1]Transit Time'!$A:$A,0),MATCH(Z55,'[1]Transit Time'!$A$1:$DZ$1,0)) -> 19 | BD55: =IF(ISBLANK(A55),"",$BC55+E55) -> 46354 | BE55: =BD55+2 -> 46356 | BF55: Dated | BG55: =EOMONTH(BE55,0) -> 46356 | BH55: =BG55 -> 46356 | BI55: =(AE55*AB55)/1000 -> 16216.41 | BJ55: 0 | BK55: =AI55*AB55/1000 -> 0 | BL55: =AL55*AB55/1000 -> 0 | BM55: =(AJ55+AK55)*AB55/1000 -> 0 | BN55: =(AU55-AI55-AJ55-AK55-AL55)*AB55/1000 -> 187.11
A56: =+$A$10 -> 46334 | B56: =IF(ISBLANK(A56),"",A56+2) -> 46336 | D56: =IF(AL56=0,0,VLOOKUP(Y56,Control!$G$41:$J$44,4,FALSE)) -> 0 | E56: =AVERAGE(A56:B56)+D56 -> 46335 | T56: =INDEX([2]Sheet1!$F$2:$AG$5,MATCH($V56,[2]Sheet1!$F$2:$F$5,0),MATCH(Z56,[2]Sheet1!$F$2:$AG$2,0)) -> 24.91 | U56: =INDEX(Control!$E$17:$J$21,MATCH(Y56,Control!$E$17:$E$21,0),MATCH(V56,Control!$E$17:$J$17,0)) -> 0 | V56: Corpus Christi | W56: =INDEX(Vessel_Minimum_MT,MATCH(Y56,Control!$E$11:$E$15,0),MATCH(V56,Control!$E$11:$J$11,0)) -> 70000 | X56: =AB56/Control!$D$84 -> 90096.968 | Y56: Aframax | Z56: Augusta | AA56: =IF(Z56=V56,"",CONCATENATE(CONCATENATE(VLOOKUP(V56,Zones,2,FALSE),"/",VLOOKUP(Z56,Zones,2,FALSE)))) -> USGC/Med | AB56: =AB55 -> 700000 | AC56: 70 | AD56: =$AD$52 -> 920 | AE56: =IF(AC56>1000,IF(AD56=0,AC56,AD56)/AB56,((W56*T56*(IF(AD56=0,AC56,AD56)/100))+IF(X56<W56,0,(X56-W56)*T56*IF(AD56=0,AC56,AD56)/100*U56))/AB56) -> 22.9172 | AF56: =$AF$52 -> 0 | AG56: =INDEX(Control!$AS$36:$AY$118,MATCH(WTI!$Z56,Control!$AS$36:$AS$118,0),MATCH(WTI!AG$23,Control!$AS$36:$AY$36,0)) -> -10 | AH56: =INDEX(Control!$AS$36:$AY$118,MATCH(WTI!$Z56,Control!$AS$36:$AS$118,0),MATCH(WTI!AH$23,Control!$AS$36:$AY$36,0)) -> 0 | AI56: =AF56*VLOOKUP($Y56,Control!$F$75:$H$87,3,FALSE)/$AB56 -> 0 | AJ56: =IF($AK$3=1,$AG56*Control!$D$77,0) -> 0 | AK56: =IF($AK$4=1,$AH56*Control!$D$77,0) -> 0 | AL56: =IF(((AB56-VLOOKUP(Y56,Control!$J$76:$K$80,2,FALSE))/Control!$D$85)<=0,0,ROUNDUP(((AB56-VLOOKUP(Y56,Control!$J$76:$K$80,2,FALSE))/Control!$D$85),0)*Control!$H$90/AB56) -> 0 | AM56: =IF(I56="Corpus Christi",Control!$D$76,0) -> 0 | AN56: 0 | AO56: =Control!$D$78 -> 0 | AP56: =Control!$D$79 -> 0.0673 | AQ56: =IF(INDEX(Control!$Q$3:$S$62,MATCH($Z56,Control!$Q$3:$Q$62,0),MATCH(AQ$9,Control!$Q$3:$S$3,0))=1,Control!$D$81*Control!$E$81,0) -> 0 | AR56: =IF(INDEX(Control!$Q$3:$S$62,MATCH($Z56,Control!$Q$3:$Q$62,0),MATCH(AR$9,Control!$Q$3:$S$3,0))=1,INDEX(Control!$AK$3:$AO$69,MATCH(WTI!Z56,Control!$AK$3:$AK$29,0),MATCH(WTI!Y56,Control!$AK$3:$AO$3,0))/AB56*1000,0) -> 0 | AS56: =IF(Z56="Rotterdam",0.114,"") | AU56: =SUM(AI56:AT56) -> 0.0673 | AV56: =+R56+AE56+AU56 -> 22.9845 | AW56: =IF((MONTH(A56)=MONTH(BH56)),0,IF(((MONTH(BH56))-MONTH(A56))+12*YEAR(BG56)-YEAR(A56)>1,SUMIFS($BD$4:$BH$4,$BD$3:$BH$3,"<="&EOMONTH(BG56,-1),$BD$3:$BH$3,">="&EOMONTH(A56,0)),VLOOKUP("Spreads",$BC$3:$BH$4,MATCH(EOMONTH(A56,0),$BC$3:$BH$3,0)))) -> 0 | AX56: =+IF(BF56="Dated",-INDEX($BC$3:$BH$6,MATCH(BF56,$BC$3:$BC$6,0),MATCH(BG56,$BC$3:$BH$3,0)),INDEX($BC$3:$BH$6,MATCH(BF56,$BC$3:$BC$6,0),MATCH(BG56,$BC$3:$BH$3,0))) -> -5.28 | AY56: =1/INDEX($BC$3:$BH$7,MATCH("CMA",$BC$3:$BC$7,0),MATCH(BG56,$BC$3:$BH$3,0))*INDEX($BC$3:$BH$7,MATCH("Spreads",$BC$3:$BC$7,0),MATCH(BG56,$BC$3:$BH$3,0)) -> 0.13181818 | AZ56: =$Y$3+AV56+AW56+AX56+AY56 -> 14.236318 | BC56: =+INDEX('[1]Transit Time'!$A:$DZ,MATCH(V56,'[1]Transit Time'!$A:$A,0),MATCH(Z56,'[1]Transit Time'!$A$1:$DZ$1,0)) -> 19.5 | BD56: =IF(ISBLANK(A56),"",$BC56+E56) -> 46354.5 | BE56: =BD56+2 -> 46356.5 | BF56: Dated | BG56: =EOMONTH(BE56,0) -> 46356 | BH56: =BG56 -> 46356 | BI56: =(AE56*AB56)/1000 -> 16042.04 | BJ56: 0 | BK56: =AI56*AB56/1000 -> 0 | BL56: =AL56*AB56/1000 -> 0 | BM56: =(AJ56+AK56)*AB56/1000 -> 0 | BN56: =(AU56-AI56-AJ56-AK56-AL56)*AB56/1000 -> 47.11
A57: =+$A$10 -> 46334 | B57: =IF(ISBLANK(A57),"",A57+2) -> 46336 | D57: =IF(AL57=0,0,VLOOKUP(Y57,Control!$G$41:$J$44,4,FALSE)) -> 0 | E57: =AVERAGE(A57:B57)+D57 -> 46335 | T57: =INDEX([2]Sheet1!$F$2:$AG$5,MATCH($V57,[2]Sheet1!$F$2:$F$5,0),MATCH(Z57,[2]Sheet1!$F$2:$AG$2,0)) -> 24.11 | U57: =INDEX(Control!$E$17:$J$21,MATCH(Y57,Control!$E$17:$E$21,0),MATCH(V57,Control!$E$17:$J$17,0)) -> 0 | V57: Corpus Christi | W57: =INDEX(Vessel_Minimum_MT,MATCH(Y57,Control!$E$11:$E$15,0),MATCH(V57,Control!$E$11:$J$11,0)) -> 70000 | X57: =AB57/Control!$D$84 -> 90096.968 | Y57: Aframax | Z57: Wilhelmshaven | AA57: =IF(Z57=V57,"",CONCATENATE(CONCATENATE(VLOOKUP(V57,Zones,2,FALSE),"/",VLOOKUP(Z57,Zones,2,FALSE)))) -> USGC/Nsea | AB57: =AB56 -> 700000 | AD57: =$AD$52 -> 920 | AE57: =IF(AC57>1000,IF(AD57=0,AC57,AD57)/AB57,((W57*T57*(IF(AD57=0,AC57,AD57)/100))+IF(X57<W57,0,(X57-W57)*T57*IF(AD57=0,AC57,AD57)/100*U57))/AB57) -> 22.1812 | AF57: =$AF$52 -> 0 | AG57: =INDEX(Control!$AS$36:$AY$118,MATCH(WTI!$Z57,Control!$AS$36:$AS$118,0),MATCH(WTI!AG$23,Control!$AS$36:$AY$36,0)) -> -10 | AH57: =INDEX(Control!$AS$36:$AY$118,MATCH(WTI!$Z57,Control!$AS$36:$AS$118,0),MATCH(WTI!AH$23,Control!$AS$36:$AY$36,0)) -> 0 | AI57: =AF57*VLOOKUP($Y57,Control!$F$75:$H$87,3,FALSE)/$AB57 -> 0 | AJ57: =IF($AK$3=1,$AG57*Control!$D$77,0) -> 0 | AK57: =IF($AK$4=1,$AH57*Control!$D$77,0) -> 0 | AL57: =IF(((AB57-VLOOKUP(Y57,Control!$J$76:$K$80,2,FALSE))/Control!$D$85)<=0,0,ROUNDUP(((AB57-VLOOKUP(Y57,Control!$J$76:$K$80,2,FALSE))/Control!$D$85),0)*Control!$H$90/AB57) -> 0 | AM57: =IF(I57="Corpus Christi",Control!$D$76,0) -> 0 | AN57: 0 | AO57: =Control!$D$78 -> 0 | AP57: =Control!$D$79 -> 0.0673 | AQ57: =IF(INDEX(Control!$Q$3:$S$62,MATCH($Z57,Control!$Q$3:$Q$62,0),MATCH(AQ$9,Control!$Q$3:$S$3,0))=1,Control!$D$81*Control!$E$81,0) -> 0 | AR57: =IF(INDEX(Control!$Q$3:$S$62,MATCH($Z57,Control!$Q$3:$Q$62,0),MATCH(AR$9,Control!$Q$3:$S$3,0))=1,INDEX(Control!$AK$3:$AO$69,MATCH(WTI!Z57,Control!$AK$3:$AK$29,0),MATCH(WTI!Y57,Control!$AK$3:$AO$3,0))/AB57*1000,0) -> 0 | AS57: =IF(Z57="Rotterdam",0.114,"") | AU57: =SUM(AI57:AT57) -> 0.0673 | AV57: =+R57+AE57+AU57 -> 22.2485 | AW57: =IF((MONTH(A57)=MONTH(BH57)),0,IF(((MONTH(BH57))-MONTH(A57))+12*YEAR(BG57)-YEAR(A57)>1,SUMIFS($BD$4:$BH$4,$BD$3:$BH$3,"<="&EOMONTH(BG57,-1),$BD$3:$BH$3,">="&EOMONTH(A57,0)),VLOOKUP("Spreads",$BC$3:$BH$4,MATCH(EOMONTH(A57,0),$BC$3:$BH$3,0)))) -> 0 | AX57: =+IF(BF57="Dated",-INDEX($BC$3:$BH$6,MATCH(BF57,$BC$3:$BC$6,0),MATCH(BG57,$BC$3:$BH$3,0)),INDEX($BC$3:$BH$6,MATCH(BF57,$BC$3:$BC$6,0),MATCH(BG57,$BC$3:$BH$3,0))) -> -5.28 | AY57: =1/INDEX($BC$3:$BH$7,MATCH("CMA",$BC$3:$BC$7,0),MATCH(BG57,$BC$3:$BH$3,0))*INDEX($BC$3:$BH$7,MATCH("Spreads",$BC$3:$BC$7,0),MATCH(BG57,$BC$3:$BH$3,0)) -> 0.13181818 | AZ57: =$Y$3+AV57+AW57+AX57+AY57 -> 13.500318 | BC57: =+INDEX('[1]Transit Time'!$A:$DZ,MATCH(V57,'[1]Transit Time'!$A:$A,0),MATCH(Z57,'[1]Transit Time'!$A$1:$DZ$1,0)) -> 18 | BD57: =IF(ISBLANK(A57),"",$BC57+E57) -> 46353 | BE57: =BD57+2 -> 46355 | BF57: Dated | BG57: =EOMONTH(BE57,0) -> 46356 | BH57: =BG57 -> 46356 | BI57: =(AE57*AB57)/1000 -> 15526.84 | BJ57: 0 | BK57: =AI57*AB57/1000 -> 0 | BL57: =AL57*AB57/1000 -> 0 | BM57: =(AJ57+AK57)*AB57/1000 -> 0 | BN57: =(AU57-AI57-AJ57-AK57-AL57)*AB57/1000 -> 47.11
A58: =+$A$10 -> 46334 | B58: =IF(ISBLANK(A58),"",A58+2) -> 46336 | D58: =IF(AL58=0,0,VLOOKUP(Y58,Control!$G$41:$J$44,4,FALSE)) -> 0 | E58: =AVERAGE(A58:B58)+D58 -> 46335 | T58: =INDEX([2]Sheet1!$F$2:$AG$5,MATCH($V58,[2]Sheet1!$F$2:$F$5,0),MATCH(Z58,[2]Sheet1!$F$2:$AG$2,0)) -> 19.61 | U58: =INDEX(Control!$E$17:$J$21,MATCH(Y58,Control!$E$17:$E$21,0),MATCH(V58,Control!$E$17:$J$17,0)) -> 0 | V58: Corpus Christi | W58: =INDEX(Vessel_Minimum_MT,MATCH(Y58,Control!$E$11:$E$15,0),MATCH(V58,Control!$E$11:$J$11,0)) -> 70000 | X58: =AB58/Control!$D$84 -> 90096.968 | Y58: Aframax | Z58: Sines | AA58: =$AA$57 -> USGC/Nsea | AB58: =AB57 -> 700000 | AC58: 70 | AD58: =$AD$52 -> 920 | AE58: =IF(AC58>1000,IF(AD58=0,AC58,AD58)/AB58,((W58*T58*(IF(AD58=0,AC58,AD58)/100))+IF(X58<W58,0,(X58-W58)*T58*IF(AD58=0,AC58,AD58)/100*U58))/AB58) -> 18.0412 | AF58: =$AF$52 -> 0 | AG58: =INDEX(Control!$AS$36:$AY$118,MATCH(WTI!$Z58,Control!$AS$36:$AS$118,0),MATCH(WTI!AG$23,Control!$AS$36:$AY$36,0)) -> -10 | AH58: =INDEX(Control!$AS$36:$AY$118,MATCH(WTI!$Z58,Control!$AS$36:$AS$118,0),MATCH(WTI!AH$23,Control!$AS$36:$AY$36,0)) -> 0 | AI58: =AF58*VLOOKUP($Y58,Control!$F$75:$H$87,3,FALSE)/$AB58 -> 0 | AJ58: =IF($AK$3=1,$AG58*Control!$D$77,0) -> 0 | AK58: =IF($AK$4=1,$AH58*Control!$D$77,0) -> 0 | AL58: =IF(((AB58-VLOOKUP(Y58,Control!$J$76:$K$80,2,FALSE))/Control!$D$85)<=0,0,ROUNDUP(((AB58-VLOOKUP(Y58,Control!$J$76:$K$80,2,FALSE))/Control!$D$85),0)*Control!$H$90/AB58) -> 0 | AM58: =IF(I58="Corpus Christi",Control!$D$76,0) -> 0 | AN58: 0 | AO58: =Control!$D$78 -> 0 | AP58: =Control!$D$79 -> 0.0673 | AQ58: =IF(INDEX(Control!$Q$3:$S$62,MATCH($Z58,Control!$Q$3:$Q$62,0),MATCH(AQ$9,Control!$Q$3:$S$3,0))=1,Control!$D$81*Control!$E$81,0) -> 0 | AR58: 0 | AS58: =IF(Z58="Rotterdam",0.114,"") | AU58: =SUM(AI58:AT58) -> 0.0673 | AV58: =+R58+AE58+AU58 -> 18.1085 | AW58: =IF((MONTH(A58)=MONTH(BH58)),0,IF(((MONTH(BH58))-MONTH(A58))+12*YEAR(BG58)-YEAR(A58)>1,SUMIFS($BD$4:$BH$4,$BD$3:$BH$3,"<="&EOMONTH(BG58,-1),$BD$3:$BH$3,">="&EOMONTH(A58,0)),VLOOKUP("Spreads",$BC$3:$BH$4,MATCH(EOMONTH(A58,0),$BC$3:$BH$3,0)))) -> 0 | AX58: =+IF(BF58="Dated",-INDEX($BC$3:$BH$6,MATCH(BF58,$BC$3:$BC$6,0),MATCH(BG58,$BC$3:$BH$3,0)),INDEX($BC$3:$BH$6,MATCH(BF58,$BC$3:$BC$6,0),MATCH(BG58,$BC$3:$BH$3,0))) -> -5.28 | AY58: =1/INDEX($BC$3:$BH$7,MATCH("CMA",$BC$3:$BC$7,0),MATCH(BG58,$BC$3:$BH$3,0))*INDEX($BC$3:$BH$7,MATCH("Spreads",$BC$3:$BC$7,0),MATCH(BG58,$BC$3:$BH$3,0)) -> 0.13181818 | AZ58: =$Y$3+AV58+AW58+AX58+AY58 -> 9.3603182 | BC58: =+INDEX('[1]Transit Time'!$A:$DZ,MATCH(V58,'[1]Transit Time'!$A:$A,0),MATCH(Z58,'[1]Transit Time'!$A$1:$DZ$1,0)) -> 16 | BD58: =IF(ISBLANK(A58),"",$BC58+E58) -> 46351 | BE58: =BD58+2 -> 46353 | BF58: Dated | BG58: =EOMONTH(BE58,0) -> 46356 | BH58: =BG58 -> 46356 | BI58: =(AE58*AB58)/1000 -> 12628.84 | BJ58: 0 | BK58: =AI58*AB58/1000 -> 0 | BL58: =AL58*AB58/1000 -> 0 | BM58: =(AJ58+AK58)*AB58/1000 -> 0 | BN58: =(AU58-AI58-AJ58-AK58-AL58)*AB58/1000 -> 47.11
A59: =+$A$10 -> 46334 | B59: =IF(ISBLANK(A59),"",A59+2) -> 46336 | D59: =IF(AL59=0,0,VLOOKUP(Y59,Control!$G$41:$J$44,4,FALSE)) -> 0 | E59: =AVERAGE(A59:B59)+D59 -> 46335 | T59: =INDEX([2]Sheet1!$F$2:$AG$5,MATCH($V59,[2]Sheet1!$F$2:$F$5,0),MATCH(Z59,[2]Sheet1!$F$2:$AG$2,0)) -> 23.89 | U59: =INDEX(Control!$E$17:$J$21,MATCH(Y59,Control!$E$17:$E$21,0),MATCH(V59,Control!$E$17:$J$17,0)) -> 0 | V59: Corpus Christi | W59: =INDEX(Vessel_Minimum_MT,MATCH(Y59,Control!$E$11:$E$15,0),MATCH(V59,Control!$E$11:$J$11,0)) -> 70000 | X59: =AB59/Control!$D$84 -> 90096.968 | Y59: Aframax | Z59: Kalundborg | AA59: =IF(Z59=V59,"",CONCATENATE(CONCATENATE(VLOOKUP(V59,Zones,2,FALSE),"/",VLOOKUP(Z59,Zones,2,FALSE)))) -> USGC/Nsea | AB59: =AB52 -> 700000 | AD59: =$AD$52+5 -> 925 | AE59: =IF(AC59>1000,IF(AD59=0,AC59,AD59)/AB59,((W59*T59*(IF(AD59=0,AC59,AD59)/100))+IF(X59<W59,0,(X59-W59)*T59*IF(AD59=0,AC59,AD59)/100*U59))/AB59) -> 22.09825 | AF59: 0 | AG59: =INDEX(Control!$AS$36:$AY$118,MATCH(WTI!$Z59,Control!$AS$36:$AS$118,0),MATCH(WTI!AG$23,Control!$AS$36:$AY$36,0)) -> -10 | AH59: =INDEX(Control!$AS$36:$AY$118,MATCH(WTI!$Z59,Control!$AS$36:$AS$118,0),MATCH(WTI!AH$23,Control!$AS$36:$AY$36,0)) -> 0 | AI59: =AF59*VLOOKUP($Y59,Control!$F$75:$H$87,3,FALSE)/$AB59 -> 0 | AJ59: =IF($AK$3=1,$AG59*Control!$D$77,0) -> 0 | AK59: =IF($AK$4=1,$AH59*Control!$D$77,0) -> 0 | AL59: =IF(((AB59-VLOOKUP(Y59,Control!$J$76:$K$80,2,FALSE))/Control!$D$85)<=0,0,ROUNDUP(((AB59-VLOOKUP(Y59,Control!$J$76:$K$80,2,FALSE))/Control!$D$85),0)*Control!$H$90/AB59) -> 0 | AM59: =IF(I59="Corpus Christi",Control!$D$76,0) -> 0 | AN59: 0 | AO59: =Control!$D$78 -> 0 | AP59: =Control!$D$79 -> 0.0673 | AQ59: =IF(INDEX(Control!$Q$3:$S$62,MATCH($Z59,Control!$Q$3:$Q$62,0),MATCH(AQ$9,Control!$Q$3:$S$3,0))=1,Control!$D$81*Control!$E$81,0) -> 0 | AR59: 0 | AS59: =IF(Z59="Rotterdam",0.114,"") | AU59: =SUM(AI59:AT59) -> 0.0673 | AV59: =+R59+AE59+AU59 -> 22.16555 | AW59: =IF((MONTH(A59)=MONTH(BH59)),0,IF(((MONTH(BH59))-MONTH(A59))+12*YEAR(BG59)-YEAR(A59)>1,SUMIFS($BD$4:$BH$4,$BD$3:$BH$3,"<="&EOMONTH(BG59,-1),$BD$3:$BH$3,">="&EOMONTH(A59,0)),VLOOKUP("Spreads",$BC$3:$BH$4,MATCH(EOMONTH(A59,0),$BC$3:$BH$3,0)))) -> 2.9 | AX59: =+IF(BF59="Dated",-INDEX($BC$3:$BH$6,MATCH(BF59,$BC$3:$BC$6,0),MATCH(BG59,$BC$3:$BH$3,0)),INDEX($BC$3:$BH$6,MATCH(BF59,$BC$3:$BC$6,0),MATCH(BG59,$BC$3:$BH$3,0))) -> -3.98 | AY59: =1/INDEX($BC$3:$BH$7,MATCH("CMA",$BC$3:$BC$7,0),MATCH(BG59,$BC$3:$BH$3,0))*INDEX($BC$3:$BH$7,MATCH("Spreads",$BC$3:$BC$7,0),MATCH(BG59,$BC$3:$BH$3,0)) -> 0.097826087 | AZ59: =$Y$3+AV59+AW59+AX59+AY59 -> 17.583376 | BC59: =+INDEX('[1]Transit Time'!$A:$DZ,MATCH(V59,'[1]Transit Time'!$A:$A,0),MATCH(Z59,'[1]Transit Time'!$A$1:$DZ$1,0))+3 -> 20 | BD59: =IF(ISBLANK(A59),"",$BC59+E59) -> 46355 | BE59: =BD59+2 -> 46357 | BF59: Dated | BG59: =EOMONTH(BE59,0) -> 46387 | BH59: =BG59 -> 46387 | BI59: =(AE59*AB59)/1000 -> 15468.775 | BJ59: 0 | BK59: =AI59*AB59/1000 -> 0 | BL59: =AL59*AB59/1000 -> 0 | BM59: =(AJ59+AK59)*AB59/1000 -> 0 | BN59: =(AU59-AI59-AJ59-AK59-AL59)*AB59/1000 -> 47.11
A60: =+$A$10 -> 46334 | B60: =IF(ISBLANK(A60),"",A60+2) -> 46336 | D60: =IF(AL60=0,0,VLOOKUP(Y60,Control!$G$41:$J$44,4,FALSE)) -> 0 | E60: =AVERAGE(A60:B60)+D60 -> 46335 | T60: =INDEX([2]Sheet1!$F$2:$AG$5,MATCH($V60,[2]Sheet1!$F$2:$F$5,0),MATCH(Z60,[2]Sheet1!$F$2:$AG$2,0)) -> 21.51 | U60: 0 | V60: Corpus Christi | W60: 145000 | X60: =AB60/Control!$D$84 -> 122274.46 | Y60: Suezmax-MODA | Z60: Rotterdam | AA60: =IF(Z60=V60,"",CONCATENATE(CONCATENATE(VLOOKUP(V60,Zones,2,FALSE),"/",VLOOKUP(Z60,Zones,2,FALSE)))) -> USGC/Nsea | AB60: 950000 | AC60: 70 | AD60: 550 | AE60: =IF(AC60>1000,IF(AD60=0,AC60,AD60)/AB60,((W60*T60*(IF(AD60=0,AC60,AD60)/100))+IF(X60<W60,0,(X60-W60)*T60*IF(AD60=0,AC60,AD60)/100*U60))/AB60) -> 18.057079 | AF60: =$AF$52 -> 0 | AG60: =INDEX(Control!$AS$36:$AY$118,MATCH(WTI!$Z60,Control!$AS$36:$AS$118,0),MATCH(WTI!AG$23,Control!$AS$36:$AY$36,0)) -> -10 | AH60: =INDEX(Control!$AS$36:$AY$118,MATCH(WTI!$Z60,Control!$AS$36:$AS$118,0),MATCH(WTI!AH$23,Control!$AS$36:$AY$36,0)) -> 0 | AI60: =AF60*VLOOKUP($Y60,Control!$F$75:$H$87,3,FALSE)/$AB60 -> 0 | AJ60: =IF($AK$3=1,$AG60*Control!$D$77,0) -> 0 | AK60: =IF($AK$4=1,$AH60*Control!$D$77,0) -> 0 | AL60: =IF(((AB60-VLOOKUP(Y60,Control!$J$76:$K$82,2,FALSE))/AN60)<=0,0,ROUNDUP(((AB60-VLOOKUP(Y60,Control!$J$76:$K$82,2,FALSE))/Control!$D$86),0)*IF(AN60=Control!$D$86,Control!$H$91,Control!$H$90)/AB60) -> 0 | AM60: =IF(I60="Corpus Christi",Control!$D$76,0) -> 0 | AN60: =IF(AND(Control!$D$85-ROUNDUP(((AB60-VLOOKUP(Y60,Control!$J$76:$K$82,2,FALSE))),0)>0,Control!$D$85-ROUNDUP(((AB60-VLOOKUP(Y60,Control!$J$76:$K$82,2,FALSE))),0)<Control!$D$86-ROUNDUP(((AB60-VLOOKUP(Y60,Control!$J$76:$K$82,2,FALSE))),0)),Control!$D$85,Control!$D$86) -> 750000 | AO60: =Control!$D$78 -> 0 | AP60: =Control!$D$79 -> 0.0673 | AQ60: =IF(INDEX(Control!$Q$3:$S$62,MATCH($Z60,Control!$Q$3:$Q$62,0),MATCH(AQ$9,Control!$Q$3:$S$3,0))=1,Control!$D$81*Control!$E$81,0) -> 0 | AR60: =AR52 -> 0 | AS60: =116490/AB60 -> 0.12262105 | AU60: =SUM(AI60:AM60,AO60:AT60) -> 0.18992105 | AV60: =+R60+AE60+AU60 -> 18.247 | AW60: =IF((MONTH(A60)=MONTH(BH60)),0,IF(((MONTH(BH60))-MONTH(A60))+12*YEAR(BG60)-YEAR(A60)>1,SUMIFS($BD$4:$BH$4,$BD$3:$BH$3,"<="&EOMONTH(BG60,-1),$BD$3:$BH$3,">="&EOMONTH(A60,0)),VLOOKUP("Spreads",$BC$3:$BH$4,MATCH(EOMONTH(A60,0),$BC$3:$BH$3,0)))) -> 0 | AX60: =+IF(BF60="Dated",-INDEX($BC$3:$BH$6,MATCH(BF60,$BC$3:$BC$6,0),MATCH(BG60,$BC$3:$BH$3,0)),INDEX($BC$3:$BH$6,MATCH(BF60,$BC$3:$BC$6,0),MATCH(BG60,$BC$3:$BH$3,0))) -> -5.28 | AY60: =1/INDEX($BC$3:$BH$7,MATCH("CMA",$BC$3:$BC$7,0),MATCH(BG60,$BC$3:$BH$3,0))*INDEX($BC$3:$BH$7,MATCH("Spreads",$BC$3:$BC$7,0),MATCH(BG60,$BC$3:$BH$3,0)) -> 0.13181818 | AZ60: =$Y$3+AV60+AW60+AX60+AY60 -> 9.4988182 | BC60: =$BC$52 -> 17 | BD60: =IF(ISBLANK(A60),"",$BC60+E60) -> 46352 | BE60: =BD60+2 -> 46354 | BF60: Dated | BG60: =EOMONTH(BE60,0) -> 46356 | BH60: =BG60 -> 46356 | BI60: =(AE60*AB60)/1000 -> 17154.225 | BJ60: 0 | BK60: =AI60*AB60/1000 -> 0 | BL60: =AL60*AB60/1000 -> 0 | BM60: =(AJ60+AK60)*AB60/1000 -> 0 | BN60: =(AU60-AI60-AJ60-AK60-AL60)*AB60/1000 -> 180.425
A61: =+$A$10 -> 46334 | B61: =IF(ISBLANK(A61),"",A61+2) -> 46336 | D61: =IF(AL61=0,0,VLOOKUP(Y61,Control!$G$41:$J$44,4,FALSE)) -> 0 | E61: =AVERAGE(A61:B61)+D61 -> 46335 | T61: =INDEX([2]Sheet1!$F$2:$AG$5,MATCH($V61,[2]Sheet1!$F$2:$F$5,0),MATCH(Z61,[2]Sheet1!$F$2:$AG$2,0)) -> 24.11 | U61: 0 | V61: Corpus Christi | W61: 145000 | X61: =AB61/Control!$D$84 -> 122274.46 | Y61: Suezmax-MODA | Z61: Wilhelmshaven | AA61: =IF(Z61=V61,"",CONCATENATE(CONCATENATE(VLOOKUP(V61,Zones,2,FALSE),"/",VLOOKUP(Z61,Zones,2,FALSE)))) -> USGC/Nsea | AB61: 950000 | AC61: 70 | AD61: =AD60 -> 550 | AE61: =IF(AC61>1000,IF(AD61=0,AC61,AD61)/AB61,((W61*T61*(IF(AD61=0,AC61,AD61)/100))+IF(X61<W61,0,(X61-W61)*T61*IF(AD61=0,AC61,AD61)/100*U61))/AB61) -> 20.239711 | AF61: =$AF$52 -> 0 | AG61: =INDEX(Control!$AS$36:$AY$118,MATCH(WTI!$Z61,Control!$AS$36:$AS$118,0),MATCH(WTI!AG$23,Control!$AS$36:$AY$36,0)) -> -10 | AH61: =INDEX(Control!$AS$36:$AY$118,MATCH(WTI!$Z61,Control!$AS$36:$AS$118,0),MATCH(WTI!AH$23,Control!$AS$36:$AY$36,0)) -> 0 | AI61: =AF61*VLOOKUP($Y61,Control!$F$75:$H$87,3,FALSE)/$AB61 -> 0 | AJ61: =IF($AK$3=1,$AG61*Control!$D$77,0) -> 0 | AK61: =IF($AK$4=1,$AH61*Control!$D$77,0) -> 0 | AL61: =IF(((AB61-VLOOKUP(Y61,Control!$J$76:$K$82,2,FALSE))/AN61)<=0,0,ROUNDUP(((AB61-VLOOKUP(Y61,Control!$J$76:$K$82,2,FALSE))/Control!$D$86),0)*IF(AN61=Control!$D$86,Control!$H$91,Control!$H$90)/AB61) -> 0 | AM61: =IF(I61="Corpus Christi",Control!$D$76,0) -> 0 | AN61: =IF(AND(Control!$D$85-ROUNDUP(((AB61-VLOOKUP(Y61,Control!$J$76:$K$82,2,FALSE))),0)>0,Control!$D$85-ROUNDUP(((AB61-VLOOKUP(Y61,Control!$J$76:$K$82,2,FALSE))),0)<Control!$D$86-ROUNDUP(((AB61-VLOOKUP(Y61,Control!$J$76:$K$82,2,FALSE))),0)),Control!$D$85,Control!$D$86) -> 750000 | AO61: =Control!$D$78 -> 0 | AP61: =Control!$D$79 -> 0.0673 | AQ61: =IF(INDEX(Control!$Q$3:$S$62,MATCH($Z61,Control!$Q$3:$Q$62,0),MATCH(AQ$9,Control!$Q$3:$S$3,0))=1,Control!$D$81*Control!$E$81,0) -> 0 | AR61: =AR53 -> 0 | AU61: =SUM(AI61:AM61,AO61:AT61) -> 0.0673 | AV61: =+R61+AE61+AU61 -> 20.307011 | AW61: =IF((MONTH(A61)=MONTH(BH61)),0,IF(((MONTH(BH61))-MONTH(A61))+12*YEAR(BG61)-YEAR(A61)>1,SUMIFS($BD$4:$BH$4,$BD$3:$BH$3,"<="&EOMONTH(BG61,-1),$BD$3:$BH$3,">="&EOMONTH(A61,0)),VLOOKUP("Spreads",$BC$3:$BH$4,MATCH(EOMONTH(A61,0),$BC$3:$BH$3,0)))) -> 0 | AX61: =+IF(BF61="Dated",-INDEX($BC$3:$BH$6,MATCH(BF61,$BC$3:$BC$6,0),MATCH(BG61,$BC$3:$BH$3,0)),INDEX($BC$3:$BH$6,MATCH(BF61,$BC$3:$BC$6,0),MATCH(BG61,$BC$3:$BH$3,0))) -> -5.28 | AY61: =1/INDEX($BC$3:$BH$7,MATCH("CMA",$BC$3:$BC$7,0),MATCH(BG61,$BC$3:$BH$3,0))*INDEX($BC$3:$BH$7,MATCH("Spreads",$BC$3:$BC$7,0),MATCH(BG61,$BC$3:$BH$3,0)) -> 0.13181818 | AZ61: =$Y$3+AV61+AW61+AX61+AY61 -> 11.558829 | BC61: =+INDEX('[1]Transit Time'!$A:$DZ,MATCH(V61,'[1]Transit Time'!$A:$A,0),MATCH(Z61,'[1]Transit Time'!$A$1:$DZ$1,0)) -> 18 | BD61: =IF(ISBLANK(A61),"",$BC61+E61) -> 46353 | BE61: =BD61+2 -> 46355 | BF61: Dated | BG61: =EOMONTH(BE61,0) -> 46356 | BH61: =BG61 -> 46356 | BI61: =(AE61*AB61)/1000 -> 19227.725 | BJ61: 0 | BK61: =AI61*AB61/1000 -> 0 | BL61: =AL61*AB61/1000 -> 0 | BM61: =(AJ61+AK61)*AB61/1000 -> 0 | BN61: =(AU61-AI61-AJ61-AK61-AL61)*AB61/1000 -> 63.935
A62: =+$A$10 -> 46334 | B62: =IF(ISBLANK(A62),"",A62+2) -> 46336 | D62: =IF(AL62=0,0,VLOOKUP(Y62,Control!$G$41:$J$44,4,FALSE)) -> 9 | E62: =AVERAGE(A62:B62)+D62 -> 46344 | T62: =INDEX([2]Sheet1!$F$2:$AG$5,MATCH($V62,[2]Sheet1!$F$2:$F$5,0),MATCH(Z62,[2]Sheet1!$F$2:$AG$2,0)) -> 21.51 | U62: =INDEX(Control!$E$17:$J$21,MATCH(Y62,Control!$E$17:$E$21,0),MATCH(V62,Control!$E$17:$J$17,0)) -> 0.5 | V62: Corpus Christi | W62: =INDEX(Vessel_Minimum_MT,MATCH(Y62,Control!$E$11:$E$15,0),MATCH(V62,Control!$E$11:$J$11,0)) -> 270000 | X62: =AB62/Control!$D$84 -> 267073.16 | Y62: VLCC | Z62: Rotterdam | AA62: =IF(Z62=V62,"",CONCATENATE(CONCATENATE(VLOOKUP(V62,Zones,2,FALSE),"/",VLOOKUP(Z62,Zones,2,FALSE)))) -> USGC/Nsea | AB62: 2075000 | AD62: 35000000 | AE62: =AD62/AB62 -> 16.86747 | AF62: 5 | AG62: =INDEX(Control!$AS$36:$AY$118,MATCH(WTI!$Z62,Control!$AS$36:$AS$118,0),MATCH(WTI!AG$23,Control!$AS$36:$AY$36,0)) -> -10 | AH62: =INDEX(Control!$AS$36:$AY$118,MATCH(WTI!$Z62,Control!$AS$36:$AS$118,0),MATCH(WTI!AH$23,Control!$AS$36:$AY$36,0)) -> 0 | AI62: =AF62*VLOOKUP($Y62,Control!$F$75:$H$87,3,FALSE)/$AB62 -> 1.0843373 | AJ62: =IF($AK$3=1,$AG62*Control!$D$77,0) -> 0 | AK62: =IF($AK$4=1,$AH62*Control!$D$77,0) -> 0 | AL62: =IF(((AB62-VLOOKUP(Y62,Control!$J$76:$K$80,2,FALSE))/Control!$D$85)<=0,0,ROUNDUP(((AB62-VLOOKUP(Y62,Control!$J$76:$K$80,2,FALSE))/Control!$D$85),0)*Control!$H$90/AB62) -> 2.6746988 | AM62: =IF(I62="Corpus Christi",Control!$D$76,0) -> 0 | AN62: 0 | AO62: =Control!$D$78 -> 0 | AP62: =Control!$D$79 -> 0.0673 | AQ62: =IF(INDEX(Control!$Q$3:$S$62,MATCH($Z62,Control!$Q$3:$Q$62,0),MATCH(AQ$9,Control!$Q$3:$S$3,0))=1,Control!$D$81*Control!$E$81,0) -> 0 | AR62: =IF(INDEX(Control!$Q$3:$S$62,MATCH($Z62,Control!$Q$3:$Q$62,0),MATCH(AR$9,Control!$Q$3:$S$3,0))=1,INDEX(Control!$AK$3:$AO$69,MATCH(WTI!Z62,Control!$AK$3:$AK$29,0),MATCH(WTI!Y62,Control!$AK$3:$AO$3,0))/AB62*1000,0) -> 0 | AS62: =116490/AB63+(Control!$D$83/AB36) -> 0.20071807 | AU62: =SUM(AI62:AM62,AO62:AT62) -> 4.0270542 | AV62: =+R62+AE62+AU62 -> 20.894524 | AW62: =IF((MONTH(A62)=MONTH(BH62)),0,IF(((MONTH(BH62))-MONTH(A62))+12*YEAR(BG62)-YEAR(A62)>1,SUMIFS($BD$4:$BH$4,$BD$3:$BH$3,"<="&EOMONTH(BG62,-1),$BD$3:$BH$3,">="&EOMONTH(A62,0)),VLOOKUP("Spreads",$BC$3:$BH$4,MATCH(EOMONTH(A62,0),$BC$3:$BH$3,0)))) -> 2.9 | AX62: =+IF(BF62="Dated",-INDEX($BC$3:$BH$6,MATCH(BF62,$BC$3:$BC$6,0),MATCH(BG62,$BC$3:$BH$3,0)),INDEX($BC$3:$BH$6,MATCH(BF62,$BC$3:$BC$6,0),MATCH(BG62,$BC$3:$BH$3,0))) -> -3.98 | AY62: =1/INDEX($BC$3:$BH$7,MATCH("CMA",$BC$3:$BC$7,0),MATCH(BG62,$BC$3:$BH$3,0))*INDEX($BC$3:$BH$7,MATCH("Spreads",$BC$3:$BC$7,0),MATCH(BG62,$BC$3:$BH$3,0)) -> 0.097826087 | AZ62: =$Y$3+AV62+AW62+AX62+AY62 -> 16.31235 | BC62: =+INDEX('[1]Transit Time'!$A:$DZ,MATCH(V62,'[1]Transit Time'!$A:$A,0),MATCH(Z62,'[1]Transit Time'!$A$1:$DZ$1,0)) -> 17 | BD62: =IF(ISBLANK(A62),"",$BC62+E62) -> 46361 | BE62: =BD62+2 -> 46363 | BF62: Dated | BG62: =BG63 -> 46387 | BH62: =BG62 -> 46387 | BI62: =(AE62*AB62)/1000 -> 35000 | BJ62: 0 | BK62: =AI62*AB62/1000 -> 2250 | BL62: =AL62*AB62/1000 -> 5550 | BM62: =(AJ62+AK62)*AB62/1000 -> 0 | BN62: =(AU62-AI62-AJ62-AK62-AL62)*AB62/1000 -> 556.1375
A63: =+$A$10 -> 46334 | B63: =IF(ISBLANK(A63),"",A63+2) -> 46336 | D63: 3 | E63: =AVERAGE(A63:B63)+D63 -> 46338 | T63: =INDEX([2]Sheet1!$F$2:$AG$5,MATCH($V63,[2]Sheet1!$F$2:$F$5,0),MATCH(Z63,[2]Sheet1!$F$2:$AG$2,0)) -> 21.51 | U63: 0.5 | V63: Corpus Christi | W63: =W62 -> 270000 | X63: =AB63/Control!$D$84 -> 267073.16 | Y63: VLCC-MODA | Z63: Rotterdam | AA63: =IF(Z63=V63,"",CONCATENATE(CONCATENATE(VLOOKUP(V63,Zones,2,FALSE),"/",VLOOKUP(Z63,Zones,2,FALSE)))) -> USGC/Nsea | AB63: =AB62 -> 2075000 | AC63: 70 | AD63: =$AD$62 -> 35000000 | AE63: =AD63/AB63 -> 16.86747 | AF63: 1 | AG63: =INDEX(Control!$AS$36:$AY$118,MATCH(WTI!$Z63,Control!$AS$36:$AS$118,0),MATCH(WTI!AG$23,Control!$AS$36:$AY$36,0)) -> -10 | AH63: =INDEX(Control!$AS$36:$AY$118,MATCH(WTI!$Z63,Control!$AS$36:$AS$118,0),MATCH(WTI!AH$23,Control!$AS$36:$AY$36,0)) -> 0 | AI63: =AF63*VLOOKUP($Y63,Control!$F$75:$H$87,3,FALSE)/$AB63 -> 0.21686747 | AJ63: =IF($AK$3=1,$AG63*Control!$D$77,0) -> 0 | AK63: =IF($AK$4=1,$AH63*Control!$D$77,0) -> 0 | AL63: =IF(((AB63-VLOOKUP(Y63,Control!$J$76:$K$82,2,FALSE))/AN63)<=0,0,ROUNDUP(((AB63-VLOOKUP(Y63,Control!$J$76:$K$82,2,FALSE))/Control!$D$86),0)*IF(AN63=Control!$D$86,Control!$H$91,Control!$H$90)/AB63) -> 0.89156627 | AM63: =IF(I63="Corpus Christi",Control!$D$76,0) -> 0 | AN63: =IF(AND(Control!$D$85-ROUNDUP(((AB63-VLOOKUP(Y63,Control!$J$76:$K$82,2,FALSE))),0)>0,Control!$D$85-ROUNDUP(((AB63-VLOOKUP(Y63,Control!$J$76:$K$82,2,FALSE))),0)<Control!$D$86-ROUNDUP(((AB63-VLOOKUP(Y63,Control!$J$76:$K$82,2,FALSE))),0)),Control!$D$85,Control!$D$86) -> 750000 | AO63: =Control!$D$78 -> 0 | AP63: =Control!$D$79 -> 0.0673 | AQ63: =IF(INDEX(Control!$Q$3:$S$62,MATCH($Z63,Control!$Q$3:$Q$62,0),MATCH(AQ$9,Control!$Q$3:$S$3,0))=1,Control!$D$81*Control!$E$81,0) -> 0 | AR63: =AR62 -> 0 | AS63: =116490/AB64+(Control!$D$83/AB37) -> 0.20071807 | AU63: =SUM(AI63:AM63,AO63:AT63) -> 1.3764518 | AV63: =+R63+AE63+AU63 -> 18.243922 | AW63: =IF((MONTH(A63)=MONTH(BH63)),0,IF(((MONTH(BH63))-MONTH(A63))+12*YEAR(BG63)-YEAR(A63)>1,SUMIFS($BD$4:$BH$4,$BD$3:$BH$3,"<="&EOMONTH(BG63,-1),$BD$3:$BH$3,">="&EOMONTH(A63,0)),VLOOKUP("Spreads",$BC$3:$BH$4,MATCH(EOMONTH(A63,0),$BC$3:$BH$3,0)))) -> 2.9 | AX63: =+IF(BF63="Dated",-INDEX($BC$3:$BH$6,MATCH(BF63,$BC$3:$BC$6,0),MATCH(BG63,$BC$3:$BH$3,0)),INDEX($BC$3:$BH$6,MATCH(BF63,$BC$3:$BC$6,0),MATCH(BG63,$BC$3:$BH$3,0))) -> -3.98 | AY63: =1/INDEX($BC$3:$BH$7,MATCH("CMA",$BC$3:$BC$7,0),MATCH(BG63,$BC$3:$BH$3,0))*INDEX($BC$3:$BH$7,MATCH("Spreads",$BC$3:$BC$7,0),MATCH(BG63,$BC$3:$BH$3,0)) -> 0.097826087 | AZ63: =$Y$3+AV63+AW63+AX63+AY63 -> 13.661748 | BC63: =+INDEX('[1]Transit Time'!$A:$DZ,MATCH(V63,'[1]Transit Time'!$A:$A,0),MATCH(Z63,'[1]Transit Time'!$A$1:$DZ$1,0)) -> 17 | BD63: =IF(ISBLANK(A63),"",$BC63+E63) -> 46355 | BE63: =BD63+2 -> 46357 | BF63: Dated | BG63: =EOMONTH(BE63,0) -> 46387 | BH63: =BG63 -> 46387 | BI63: =(AE63*AB63)/1000 -> 35000 | BJ63: 0 | BK63: =AI63*AB63/1000 -> 450 | BL63: =AL63*AB63/1000 -> 1850 | BM63: =(AJ63+AK63)*AB63/1000 -> 0 | BN63: =(AU63-AI63-AJ63-AK63-AL63)*AB63/1000 -> 556.1375
A64: =+$A$10 -> 46334 | B64: =IF(ISBLANK(A64),"",A64+2) -> 46336 | D64: 3 | E64: =AVERAGE(A64:B64)+D64 -> 46338 | T64: =INDEX([2]Sheet1!$F$2:$AG$5,MATCH($V64,[2]Sheet1!$F$2:$F$5,0),MATCH(Z64,[2]Sheet1!$F$2:$AG$2,0)) -> 21.51 | U64: 0.5 | V64: Corpus Christi | W64: =W63 -> 270000 | X64: =AB64/Control!$D$84 -> 267073.16 | Y64: VLCC-STG | Z64: Rotterdam | AA64: =IF(Z64=V64,"",CONCATENATE(CONCATENATE(VLOOKUP(V64,Zones,2,FALSE),"/",VLOOKUP(Z64,Zones,2,FALSE)))) -> USGC/Nsea | AB64: =AB62 -> 2075000 | AC64: 70 | AD64: =$AD$62 -> 35000000 | AE64: =AD64/AB64 -> 16.86747 | AF64: 1 | AG64: =INDEX(Control!$AS$36:$AY$118,MATCH(WTI!$Z64,Control!$AS$36:$AS$118,0),MATCH(WTI!AG$23,Control!$AS$36:$AY$36,0)) -> -10 | AH64: =INDEX(Control!$AS$36:$AY$118,MATCH(WTI!$Z64,Control!$AS$36:$AS$118,0),MATCH(WTI!AH$23,Control!$AS$36:$AY$36,0)) -> 0 | AI64: =AF64*VLOOKUP($Y64,Control!$F$75:$H$87,3,FALSE)/$AB64 -> 0.21686747 | AJ64: =IF($AK$3=1,$AG64*Control!$D$77,0) -> 0 | AK64: =IF($AK$4=1,$AH64*Control!$D$77,0) -> 0 | AL64: =IF(((AB64-VLOOKUP(Y64,Control!$J$76:$K$82,2,FALSE))/AN64)<=0,0,ROUNDUP(((AB64-VLOOKUP(Y64,Control!$J$76:$K$82,2,FALSE))/Control!$D$86),0)*IF(AN64=Control!$D$86,Control!$H$91,Control!$H$90)/AB64) -> 0.89156627 | AM64: =IF(I64="Corpus Christi",Control!$D$76,0) -> 0 | AN64: =IF(AND(Control!$D$85-ROUNDUP(((AB64-VLOOKUP(Y64,Control!$J$76:$K$82,2,FALSE))),0)>0,Control!$D$85-ROUNDUP(((AB64-VLOOKUP(Y64,Control!$J$76:$K$82,2,FALSE))),0)<Control!$D$86-ROUNDUP(((AB64-VLOOKUP(Y64,Control!$J$76:$K$82,2,FALSE))),0)),Control!$D$85,Control!$D$86) -> 750000 | AO64: =Control!$D$78 -> 0 | AP64: =Control!$D$79 -> 0.0673 | AQ64: =IF(INDEX(Control!$Q$3:$S$62,MATCH($Z64,Control!$Q$3:$Q$62,0),MATCH(AQ$9,Control!$Q$3:$S$3,0))=1,Control!$D$81*Control!$E$81,0) -> 0 | AR64: =AR63 -> 0 | AS64: =116490/AB65+(Control!$D$83/AB38) -> 0.20071807 | AU64: =SUM(AI64:AM64,AO64:AT64) -> 1.3764518 | AV64: =+R64+AE64+AU64 -> 18.243922 | AW64: =IF((MONTH(A64)=MONTH(BH64)),0,IF(((MONTH(BH64))-MONTH(A64))+12*YEAR(BG64)-YEAR(A64)>1,SUMIFS($BD$4:$BH$4,$BD$3:$BH$3,"<="&EOMONTH(BG64,-1),$BD$3:$BH$3,">="&EOMONTH(A64,0)),VLOOKUP("Spreads",$BC$3:$BH$4,MATCH(EOMONTH(A64,0),$BC$3:$BH$3,0)))) -> 2.9 | AX64: =+IF(BF64="Dated",-INDEX($BC$3:$BH$6,MATCH(BF64,$BC$3:$BC$6,0),MATCH(BG64,$BC$3:$BH$3,0)),INDEX($BC$3:$BH$6,MATCH(BF64,$BC$3:$BC$6,0),MATCH(BG64,$BC$3:$BH$3,0))) -> -3.98 | AY64: =1/INDEX($BC$3:$BH$7,MATCH("CMA",$BC$3:$BC$7,0),MATCH(BG64,$BC$3:$BH$3,0))*INDEX($BC$3:$BH$7,MATCH("Spreads",$BC$3:$BC$7,0),MATCH(BG64,$BC$3:$BH$3,0)) -> 0.097826087 | AZ64: =$Y$3+AV64+AW64+AX64+AY64 -> 13.661748 | BC64: =+INDEX('[1]Transit Time'!$A:$DZ,MATCH(V64,'[1]Transit Time'!$A:$A,0),MATCH(Z64,'[1]Transit Time'!$A$1:$DZ$1,0)) -> 17 | BD64: =IF(ISBLANK(A64),"",$BC64+E64) -> 46355 | BE64: =BD64+2 -> 46357 | BF64: Dated | BG64: =EOMONTH(BE64,0) -> 46387 | BH64: =BG64 -> 46387 | BI64: =(AE64*AB64)/1000 -> 35000 | BJ64: 0 | BK64: =AI64*AB64/1000 -> 450 | BL64: =AL64*AB64/1000 -> 1850 | BM64: =(AJ64+AK64)*AB64/1000 -> 0 | BN64: =(AU64-AI64-AJ64-AK64-AL64)*AB64/1000 -> 556.1375
A65: =+$A$10 -> 46334 | B65: =IF(ISBLANK(A65),"",A65+2) -> 46336 | D65: =IF(AL65=0,0,VLOOKUP(Y65,Control!$G$41:$J$44,4,FALSE)) -> 9 | E65: =AVERAGE(A65:B65)+D65 -> 46344 | U65: =INDEX(Control!$E$17:$J$21,MATCH(Y65,Control!$E$17:$E$21,0),MATCH(V65,Control!$E$17:$J$17,0)) -> 0.5 | V65: Corpus Christi | W65: =INDEX(Vessel_Minimum_MT,MATCH(Y65,Control!$E$11:$E$15,0),MATCH(V65,Control!$E$11:$J$11,0)) -> 270000 | X65: =AB65/Control!$D$84 -> 267073.16 | Y65: VLCC | Z65: Lagos | AA65: USGC/Nsea | AB65: =AB62 -> 2075000 | AD65: =$AD$62+150000 -> 35150000 | AE65: =AD65/AB65 -> 16.939759 | AF65: 5 | AG65: =INDEX(Control!$AS$36:$AY$118,MATCH(WTI!$Z65,Control!$AS$36:$AS$118,0),MATCH(WTI!AG$23,Control!$AS$36:$AY$36,0)) -> -10 | AH65: =INDEX(Control!$AS$36:$AY$118,MATCH(WTI!$Z65,Control!$AS$36:$AS$118,0),MATCH(WTI!AH$23,Control!$AS$36:$AY$36,0)) -> 0 | AI65: =AF65*VLOOKUP($Y65,Control!$F$75:$H$87,3,FALSE)/$AB65 -> 1.0843373 | AJ65: =IF($AK$3=1,$AG65*Control!$D$77,0) -> 0 | AK65: =IF($AK$4=1,$AH65*Control!$D$77,0) -> 0 | AL65: =IF(((AB65-VLOOKUP(Y65,Control!$J$76:$K$80,2,FALSE))/Control!$D$85)<=0,0,ROUNDUP(((AB65-VLOOKUP(Y65,Control!$J$76:$K$80,2,FALSE))/Control!$D$85),0)*Control!$H$90/AB65) -> 2.6746988 | AM65: =IF(I65="Corpus Christi",Control!$D$76,0) -> 0 | AN65: 0 | AO65: =Control!$D$78 -> 0 | AP65: =Control!$D$79 -> 0.0673 | AQ65: =IF(INDEX(Control!$Q$3:$S$62,MATCH($Z65,Control!$Q$3:$Q$62,0),MATCH(AQ$9,Control!$Q$3:$S$3,0))=1,Control!$D$81*Control!$E$81,0) -> 0 | AR65: =IF(INDEX(Control!$Q$3:$S$62,MATCH($Z65,Control!$Q$3:$Q$62,0),MATCH(AR$9,Control!$Q$3:$S$3,0))=1,INDEX(Control!$AK$3:$AO$69,MATCH(WTI!Z65,Control!$AK$3:$AK$29,0),MATCH(WTI!Y65,Control!$AK$3:$AO$3,0))/AB65*1000,0) -> 0 | AS65: =650000/AB65+(116490/AB65)+(Control!$D$83/AB38) -> 0.51397108 | AU65: =SUM(AI65:AT65) -> 4.3403072 | AV65: =+R65+AE65+AU65 -> 21.280066 | AW65: =IF((MONTH(A65)=MONTH(BH65)),0,IF(((MONTH(BH65))-MONTH(A65))+12*YEAR(BG65)-YEAR(A65)>1,SUMIFS($BD$4:$BH$4,$BD$3:$BH$3,"<="&EOMONTH(BG65,-1),$BD$3:$BH$3,">="&EOMONTH(A65,0)),VLOOKUP("Spreads",$BC$3:$BH$4,MATCH(EOMONTH(A65,0),$BC$3:$BH$3,0)))) -> 2.9 | AX65: =+IF(BF65="Dated",-INDEX($BC$3:$BH$6,MATCH(BF65,$BC$3:$BC$6,0),MATCH(BG65,$BC$3:$BH$3,0)),INDEX($BC$3:$BH$6,MATCH(BF65,$BC$3:$BC$6,0),MATCH(BG65,$BC$3:$BH$3,0))) -> -3.98 | AY65: =1/INDEX($BC$3:$BH$7,MATCH("CMA",$BC$3:$BC$7,0),MATCH(BG65,$BC$3:$BH$3,0))*INDEX($BC$3:$BH$7,MATCH("Spreads",$BC$3:$BC$7,0),MATCH(BG65,$BC$3:$BH$3,0)) -> 0.097826087 | AZ65: =$Y$3+AV65+AW65+AX65+AY65 -> 16.697892 | BC65: 21 | BD65: =IF(ISBLANK(A65),"",$BC65+E65) -> 46365 | BE65: =BD65+2 -> 46367 | BF65: Dated | BG65: =EOMONTH(BD65,0) -> 46387 | BH65: =BG65 -> 46387 | BI65: =(AE65*AB65)/1000 -> 35150 | BJ65: 0 | BK65: =AI65*AB65/1000 -> 2250 | BL65: =AL65*AB65/1000 -> 5550 | BM65: =(AJ65+AK65)*AB65/1000 -> 0 | BN65: =(AU65-AI65-AJ65-AK65-AL65)*AB65/1000 -> 1206.1375
A66: =+$A$10 -> 46334 | B66: =IF(ISBLANK(A66),"",A66+2) -> 46336 | D66: =IF(AL66=0,0,VLOOKUP(Y66,Control!$G$41:$J$44,4,FALSE)) -> 3 | E66: =AVERAGE(A66:B66)+D66 -> 46338 | U66: 0.5 | V66: Corpus Christi | W66: =W65 -> 270000 | X66: =AB66/Control!$D$84 -> 267073.16 | Y66: VLCC-MODA | Z66: Lagos | AA66: USGC/Nsea | AB66: =AB65 -> 2075000 | AC66: 70 | AD66: =AD65 -> 35150000 | AE66: =AD66/AB66 -> 16.939759 | AG66: =INDEX(Control!$AS$36:$AY$118,MATCH(WTI!$Z66,Control!$AS$36:$AS$118,0),MATCH(WTI!AG$23,Control!$AS$36:$AY$36,0)) -> -10 | AH66: =INDEX(Control!$AS$36:$AY$118,MATCH(WTI!$Z66,Control!$AS$36:$AS$118,0),MATCH(WTI!AH$23,Control!$AS$36:$AY$36,0)) -> 0 | AI66: =AF66*VLOOKUP($Y66,Control!$F$75:$H$87,3,FALSE)/$AB66 -> 0 | AJ66: =IF($AK$3=1,$AG66*Control!$D$77,0) -> 0 | AK66: =IF($AK$4=1,$AH66*Control!$D$77,0) -> 0 | AL66: =IF(((AB66-VLOOKUP(Y66,Control!$J$76:$K$80,2,FALSE))/Control!$D$85)<=0,0,ROUNDUP(((AB66-VLOOKUP(Y66,Control!$J$76:$K$80,2,FALSE))/Control!$D$85),0)*Control!$H$90/AB66) -> 0.89156627 | AM66: =IF(I66="Corpus Christi",Control!$D$76,0) -> 0 | AN66: =IF(AND(Control!$D$85-ROUNDUP(((AB66-VLOOKUP(Y66,Control!$J$76:$K$82,2,FALSE))),0)>0,Control!$D$85-ROUNDUP(((AB66-VLOOKUP(Y66,Control!$J$76:$K$82,2,FALSE))),0)<Control!$D$86-ROUNDUP(((AB66-VLOOKUP(Y66,Control!$J$76:$K$82,2,FALSE))),0)),Control!$D$85,Control!$D$86) -> 750000 | AO66: =Control!$D$78 -> 0 | AP66: =Control!$D$79 -> 0.0673 | AQ66: =IF(INDEX(Control!$Q$3:$S$62,MATCH($Z66,Control!$Q$3:$Q$62,0),MATCH(AQ$9,Control!$Q$3:$S$3,0))=1,Control!$D$81*Control!$E$81,0) -> 0 | AR66: =AR65 -> 0 | AS66: =AS65 -> 0.51397108 | AU66: =SUM(AI66:AM66,AO66:AT66) -> 1.4728373 | AV66: =+R66+AE66+AU66 -> 18.412596 | AW66: =IF((MONTH(A66)=MONTH(BH66)),0,IF(((MONTH(BH66))-MONTH(A66))+12*YEAR(BG66)-YEAR(A66)>1,SUMIFS($BD$4:$BH$4,$BD$3:$BH$3,"<="&EOMONTH(BG66,-1),$BD$3:$BH$3,">="&EOMONTH(A66,0)),VLOOKUP("Spreads",$BC$3:$BH$4,MATCH(EOMONTH(A66,0),$BC$3:$BH$3,0)))) -> 2.9 | AX66: =+IF(BF66="Dated",-INDEX($BC$3:$BH$6,MATCH(BF66,$BC$3:$BC$6,0),MATCH(BG66,$BC$3:$BH$3,0)),INDEX($BC$3:$BH$6,MATCH(BF66,$BC$3:$BC$6,0),MATCH(BG66,$BC$3:$BH$3,0))) -> -3.98 | AY66: =1/INDEX($BC$3:$BH$7,MATCH("CMA",$BC$3:$BC$7,0),MATCH(BG66,$BC$3:$BH$3,0))*INDEX($BC$3:$BH$7,MATCH("Spreads",$BC$3:$BC$7,0),MATCH(BG66,$BC$3:$BH$3,0)) -> 0.097826087 | AZ66: =$Y$3+AV66+AW66+AX66+AY66 -> 13.830422 | BC66: 21 | BD66: =IF(ISBLANK(A66),"",$BC66+E66) -> 46359 | BE66: =BD66+2 -> 46361 | BF66: Dated | BG66: =EOMONTH(BE66,0) -> 46387 | BH66: =BG66 -> 46387 | BI66: =(AE66*AB66)/1000 -> 35150 | BJ66: 0 | BK66: =AI66*AB66/1000 -> 0 | BL66: =AL66*AB66/1000 -> 1850 | BM66: =(AJ66+AK66)*AB66/1000 -> 0 | BN66: =(AU66-AI66-AJ66-AK66-AL66)*AB66/1000 -> 1206.1375
Y67: Corpus- CASH BFOETM | BD67: =AZ59-AZ52 -> 6.3408008 | BE67: =BD67+2 -> 8.3408008 | BG67: =EOMONTH(BE67,0) -> 31 | BH67: =BG67 -> 31 | BL67: =(AU67-AI67-AJ67)*AB67 -> 0 | BM67: =AJ67*AB67 -> 0
A68: Load Window | D68: =D49 -> STS Time | E68: =E49 -> Depart | T68: Flat | U68: Overages | V68: Loadport | W68: =$W$9 -> Vessel MT | X68: Actual MT | Y68: Vessel | Z68: Destination | AA68: Route | AB68: Volume | AC68: =$AC$9 -> Current WS Rate | AD68: WS Rate Call | AE68: Destination Freight | AF68: Demurrage | AG68: =AG23 -> ATA tvm | AH68: =AH23 -> Ext. TVM | AI68: Demurrage $ | AJ68: =AG68 -> ATA tvm | AK68: =AH68 -> Ext. TVM | AL68: =AL23 -> STS | AM68: Wharfage | AN68: Panama Canal | AO68: Insurance | AP68: Inspection | AQ68: Outturn Losses | AR68: ECA costs | AS68: Other costs | AT68: Pipeline Fee | AU68: Total Secondary Costs | AV68: All In Cost | AW68: Structure | AX68: =AX49 -> Basis | AZ68: DES Price | BC68: Transit Time | BD68: Arrival Window | BF68: =BF9 -> Basis | BG68: =BG49 -> Pricing Month | BH68: =BH49 -> Delivery Month
A69: =+$A$10 -> 46334 | B69: =IF(ISBLANK(A69),"",A69+2) -> 46336 | D69: =IF(AL69=0,0,VLOOKUP(Y69,Control!$G$41:$J$44,4,FALSE)) -> 0 | E69: =AVERAGE(A69:B69)+D69 -> 46335 | T69: =$T$52 -> 21.51 | U69: =INDEX(Control!$E$17:$J$21,MATCH(Y69,Control!$E$17:$E$21,0),MATCH(V69,Control!$E$17:$J$17,0)) -> 0 | V69: Corpus Christi | W69: =INDEX(Vessel_Minimum_MT,MATCH(Y69,Control!$E$11:$E$15,0),MATCH(V69,Control!$E$11:$J$11,0)) -> 70000 | X69: =AB69/Control!$D$84 -> 90096.968 | Y69: Aframax | Z69: Rotterdam-CASH | AA69: =AA52 -> USGC/Nsea | AB69: 700000 | AC69: 70 | AD69: 180 | AE69: =IF(AC69>1000,IF(AD69=0,AC69,AD69)/AB69,((W69*T69*(IF(AD69=0,AC69,AD69)/100))+IF(X69<W69,0,(X69-W69)*T69*IF(AD69=0,AC69,AD69)/100*U69))/AB69) -> 3.8718 | AF69: 0 | AG69: =INDEX(Control!$AS$36:$AY$118,MATCH(WTI!$Z69,Control!$AS$36:$AS$118,0),MATCH(WTI!AG$23,Control!$AS$36:$AY$36,0)) -> -10 | AH69: 16 | AI69: =AF69*VLOOKUP($Y69,Control!$F$75:$H$87,3,FALSE)/$AB69 -> 0 | AJ69: =IF(AND($AK$3=1,$AG69*Control!$D$77<0),$AG69*Control!$D$77,0) -> 0 | AK69: =IF($AK$4=1,$AH69*Control!$D$77,0) -> 0.20857863 | AL69: =IF(((AB69-VLOOKUP(Y69,Control!$J$76:$K$80,2,FALSE))/Control!$D$85)<=0,0,ROUNDUP(((AB69-VLOOKUP(Y69,Control!$J$76:$K$80,2,FALSE))/Control!$D$85),0)*Control!$H$90/AB69) -> 0 | AM69: =IF(I69="Corpus Christi",Control!$D$76,0) -> 0 | AN69: 0 | AO69: =Control!$D$78 -> 0 | AS69: =AS52 -> 0.13425714 | AT69: =IF(AND(L69="Chiriqui Grande",V69="Puerto Armuelles"),Control!$G$93,0) -> 0 | AU69: =SUM(AI69:AT69) -> 0.34283577 | AV69: =+R69+AE69+AU69 -> 4.2146358 | AW69: =IF((MONTH(A69)=MONTH(BH69)),0,IF(((MONTH(BH69))-MONTH(A69))+12*YEAR(BG69)-YEAR(A69)>1,SUMIFS($BD$4:$BG$4,$BD$3:$BG$3,"<="&EOMONTH(BG69,-1),$BD$3:$BG$3,">="&EOMONTH(A69,0)),VLOOKUP("Spreads",$BC$3:$BG$4,MATCH(EOMONTH(A69,0),$BC$3:$BG$3,0)))) -> 0 | AX69: -1.9 | AZ69: =$Y$3+AV69+AW69+AX69 -> -1.2853642 | BC69: 19 | BD69: =IF(ISBLANK(E69),"",E69+$BC69+D69) -> 46354 | BE69: =BD69+2 -> 46356 | BF69: Dated | BG69: =EOMONTH(BE69,0) -> 46356 | BH69: =BG69 -> 46356 | BI69: =AE69*AB69 -> 2710260 | BK69: =AI69*AB69 -> 0 | BL69: =(AU69-AI69-AJ69)*AB69 -> 239985.04 | BM69: =AJ69*AB69 -> 0
BL70: =(AU70-AI70-AJ70)*AB70 -> 0 | BM70: =AJ70*AB70 -> 0
Y71: -5.65 | AW71: MEH Arb Open? | AZ71: =AZ73-AZ72 -> 1.6259678
A72: =A9 -> 46334 | B72: =IF(ISBLANK(A72),"",A72+2) -> 46336 | D72: 0 | E72: =A72 -> 46334 | T72: =T69 -> 21.51 | U72: =INDEX(Control!$E$17:$J$21,MATCH(Y72,Control!$E$17:$E$21,0),MATCH(V72,Control!$E$17:$J$17,0)) -> 0 | V72: Corpus Christi | W72: =INDEX(Vessel_Minimum_MT,MATCH(Y72,Control!$E$11:$E$15,0),MATCH(V72,Control!$E$11:$J$11,0)) -> 70000 | X72: =AB72/Control!$D$84 -> 90096.968 | Y72: Aframax | Z72: Rotterdam-CASH | AA72: =AA53 -> USGC/Nsea | AB72: 700000 | AC72: 70 | AD72: 240 | AE72: =IF(AC72>1000,IF(AD72=0,AC72,AD72)/AB72,((W72*T72*(IF(AD72=0,AC72,AD72)/100))+IF(X72<W72,0,(X72-W72)*T72*IF(AD72=0,AC72,AD72)/100*U72))/AB72) -> 5.1624 | AF72: 0 | AG72: =INDEX(Control!$AS$36:$AY$118,MATCH(WTI!$Z72,Control!$AS$36:$AS$118,0),MATCH(WTI!AG$23,Control!$AS$36:$AY$36,0)) -> -10 | AH72: =AH69 -> 16 | AI72: =AF72*VLOOKUP($Y72,Control!$F$75:$H$87,3,FALSE)/$AB72 -> 0 | AJ72: =IF(AND($AK$3=1,$AG72*Control!$D$77<0),$AG72*Control!$D$77,0) -> 0 | AK72: =IF($AK$4=1,$AH72*Control!$D$77,0) -> 0.20857863 | AL72: =IF(((AB72-VLOOKUP(Y72,Control!$J$76:$K$80,2,FALSE))/Control!$D$85)<=0,0,ROUNDUP(((AB72-VLOOKUP(Y72,Control!$J$76:$K$80,2,FALSE))/Control!$D$85),0)*Control!$H$90/AB72) -> 0 | AM72: =IF(I72="Corpus Christi",Control!$D$76,0) -> 0 | AN72: 0 | AO72: =Control!$D$78 -> 0 | AR72: 0.13 | AT72: =IF(AND(L72="Chiriqui Grande",V72="Puerto Armuelles"),Control!$G$93,0) -> 0 | AU72: =SUM(AI72:AT72) -> 0.33857863 | AV72: =+R72+AE72+AU72 -> 5.5009786 | AZ72: =$Y$71+AV72+AW72+AX72 -> -0.14902137 | BC72: 19 | BD72: =IF(ISBLANK(E72),"",E72+$BC72+D72) -> 46353 | BE72: =BD72+2 -> 46355 | BF72: Dated | BG72: =EOMONTH(BD72,0) -> 46356 | BH72: =BG72 -> 46356 | BI72: =AE72*AB72 -> 3613680 | BK72: =AI72*AB72 -> 0 | BL72: =(AU72-AI72-AJ72)*AB72 -> 237005.04 | BM72: =AJ72*AB72 -> 0
A73: =BD72 -> 46353 | B73: =IF(ISBLANK(A73),"",A73+2) -> 46355 | D73: =IF(AL73=0,0,VLOOKUP(Y73,Control!$G$41:$J$44,4,FALSE)) -> 0 | E73: =A73 -> 46353 | T73: 7.25 | U73: =INDEX(Control!$E$17:$J$21,MATCH(Y73,Control!$E$17:$E$21,0),MATCH(V73,Control!$E$17:$J$17,0)) -> 0 | V73: Corpus Christi | W73: 86700 | X73: =AB73/Control!$D$84 -> 90096.968 | Y73: Aframax | Z73: Rotterdam-CASH | AA73: =AA54 -> USGC/Nsea | AB73: 700000 | AC73: 70 | AD73: 150 | AE73: =IF(AC73>1000,IF(AD73=0,AC73,AD73)/AB73,((W73*T73*(IF(AD73=0,AC73,AD73)/100))+IF(X73<W73,0,(X73-W73)*T73*IF(AD73=0,AC73,AD73)/100*U73))/AB73) -> 1.3469464 | AF73: 0 | AG73: 0 | AI73: =AF73*VLOOKUP($Y73,Control!$F$75:$H$87,3,FALSE)/$AB73 -> 0 | AJ73: =$AG73*Control!$D$77 -> 0 | AL73: =IF(((AB73-VLOOKUP(Y73,Control!$J$76:$K$80,2,FALSE))/Control!$D$85)<=0,0,ROUNDUP(((AB73-VLOOKUP(Y73,Control!$J$76:$K$80,2,FALSE))/Control!$D$85),0)*Control!$H$90/AB73) -> 0 | AM73: =IF(I73="Corpus Christi",Control!$D$76,0) -> 0 | AN73: 0 | AO73: =Control!$D$78 -> 0 | AR73: 0.13 | AT73: =IF(AND(L73="Chiriqui Grande",V73="Puerto Armuelles"),Control!$G$93,0) -> 0 | AU73: =SUM(AI73:AT73) -> 0.13 | AV73: =+R73+AE73+AU73 -> 1.4769464 | AZ73: =$Y$5+AV73+AW73+AX73 -> 1.4769464 | BC73: 0 | BD73: =IF(ISBLANK(E73),"",E73+$BC73+D73) -> 46353 | BE73: =BD73+2 -> 46355 | BF73: Dated | BG73: =EOMONTH(BD73,0) -> 46356 | BH73: =BG73 -> 46356 | BI73: =AE73*AB73 -> 942862.5 | BK73: =AI73*AB73 -> 0 | BL73: =(AU73-AI73-AJ73)*AB73 -> 91000 | BM73: =AJ73*AB73 -> 0
Y74: RDAM STS-EUROPE | BI74: =BI72-BI73 -> 2670817.5 | BK74: =BK72-BK73 -> 0 | BL74: =BL72-BL73 -> 146005.04 | BM74: =BM72-BM73 -> 0
A75: =A9 -> 46334 | B75: =A75+2 -> 46336 | D75: =IF(AL75=0,0,VLOOKUP(Y75,Control!$G$41:$J$44,4,FALSE)) -> 3 | E75: =AVERAGE(A75:B75)+D75 -> 46338 | T75: 0 | U75: 0 | V75: Corpus Christi | W75: =INDEX(Vessel_Minimum_MT,MATCH(Y75,Control!$E$11:$E$15,0),MATCH(V75,Control!$E$11:$J$11,0)) -> #N/A | X75: =AB75/Control!$D$84 -> 267073.16 | Y75: VLCC-MODA | Z75: Rotterdam | AA75: =IF(Z75=V75,"",CONCATENATE(CONCATENATE(VLOOKUP(V75,Zones,2,FALSE),"/",VLOOKUP(Z75,Zones,2,FALSE)))) -> USGC/Nsea | AB75: =2075000 -> 2075000 | AD75: =AD62 -> 35000000 | AE75: =AD75/AB75 -> 16.86747 | AF75: 7 | AG75: =IF(AND($BC$48=1,VLOOKUP(Z75,Control!$AS$37:$AV$68,4,FALSE)<0),0,VLOOKUP(Z75,Control!$AS$37:$AV$68,4,FALSE)) -> -8 | AI75: =AF75*VLOOKUP($Y75,Control!$F$75:$H$87,3,FALSE)/$AB75 -> 1.5180723 | AL75: =IF(((AB75-VLOOKUP(Y75,Control!$J$76:$K$80,2,FALSE))/Control!$D$85)<=0,0,ROUNDUP(((AB75-VLOOKUP(Y75,Control!$J$76:$K$80,2,FALSE))/Control!$D$85),0)*Control!$H$90/AB75) -> 0.89156627 | AM75: =IF(I75="Corpus Christi",Control!$D$76,0) -> 0 | AN75: 0 | AO75: =Control!$D$78 -> 0 | AP75: =Control!$D$79 -> 0.0673 | AQ75: =IF(INDEX(Control!$Q$3:$S$62,MATCH($Z75,Control!$Q$3:$Q$62,0),MATCH(AQ$9,Control!$Q$3:$S$3,0))=1,Control!$D$81*Control!$E$81,0) -> 0 | AR75: =IF(INDEX(Control!$Q$3:$S$62,MATCH($Z75,Control!$Q$3:$Q$62,0),MATCH(AR$9,Control!$Q$3:$S$3,0))=1,INDEX(Control!$AK$3:$AO$69,MATCH(WTI!Z75,Control!$AK$3:$AK$29,0),MATCH(WTI!Y75,Control!$AK$3:$AO$3,0))/AB75*1000,0) -> 0 | AS75: =116490/AB75 -> 0.056139759 | AU75: =SUM(AI75:AT75) -> 2.5330783 | AV75: =+R75+AE75+AU75 -> 19.400548 | AW75: =IF((MONTH(A75)=MONTH(BH75)),0,IF(((MONTH(BH75))-MONTH(A75))+12*YEAR(BG75)-YEAR(A75)>1,SUMIFS($BD$4:$BH$4,$BD$3:$BH$3,"<="&EOMONTH(BG75,-1),$BD$3:$BH$3,">="&EOMONTH(A75,0)),VLOOKUP("Spreads",$BC$3:$BH$4,MATCH(EOMONTH(A75,0),$BC$3:$BH$3,0)))) -> 0 | AX75: =-HLOOKUP(EOMONTH(BG75,0),$BD$3:$BG$6,3,FALSE) -> -5.28 | AZ75: =$Y$3+AV75+AW75+AX75 -> 10.520548 | BC75: =+INDEX('[1]Transit Time'!$A:$DZ,MATCH(V75,'[1]Transit Time'!$A:$A,0),MATCH(Z75,'[1]Transit Time'!$A$1:$DZ$1,0)) -> 17 | BD75: =IF(ISBLANK(A75),"",A75+$BC75+D75) -> 46354 | BE75: =BD75+2 -> 46356 | BF75: Dated | BG75: =EOMONTH(BE75,0) -> 46356 | BH75: =BG75 -> 46356
A77: =BD75+1 -> 46355 | B77: =A77+2 -> 46357 | D77: =IF(AL77=0,0,VLOOKUP(Y77,Control!$G$41:$J$44,4,FALSE)) -> 0 | E77: =AVERAGE(A77:B77)+D77 -> 46356 | T77: 0 | U77: 0 | V77: Rotterdam-STS | W77: =INDEX(Vessel_Minimum_MT,MATCH(Y77,Control!$E$11:$E$15,0),MATCH(V77,Control!$E$11:$O$11,0)) -> 80000 | X77: =AB77/Control!$D$84 -> 90096.968 | Y77: Aframax | Z77: Rotterdam | AA77: =IF(Z77=V77,"",CONCATENATE(CONCATENATE(VLOOKUP(V77,Zones,2,FALSE),"/",VLOOKUP(Z77,Zones,2,FALSE)))) -> Nsea/Nsea | AB77: 700000 | AC77: 70 | AD77: =AD73 -> 150 | AE77: =IF(AC77>1000,IF(AD77=0,AC77,AD77)/AB77,((W77*T77*(IF(AD77=0,AC77,AD77)/100))+IF(X77<W77,0,(X77-W77)*T77*IF(AD77=0,AC77,AD77)/100*U77))/AB77) -> 0 | AG77: =IF(AND($BC$48=1,VLOOKUP(Z77,Control!$AS$37:$AV$68,4,FALSE)<0),0,VLOOKUP(Z77,Control!$AS$37:$AV$68,4,FALSE))-$AG$75+2 -> 2 | AI77: =AF77*VLOOKUP($Y77,Control!$F$75:$H$87,3,FALSE)/$AB77 -> 0 | AJ77: =$AG77*Control!$D$77 -> 0.026072329 | AL77: =Control!$I$90/WTI!AB77 -> 0.10714286 | AM77: =IF(I77="Corpus Christi",Control!$D$76,0) -> 0 | AN77: 0 | AO77: =Control!$D$78 -> 0 | AP77: =Control!$D$79 -> 0.0673 | AQ77: =IF(INDEX(Control!$Q$3:$S$62,MATCH($Z77,Control!$Q$3:$Q$62,0),MATCH(AQ$9,Control!$Q$3:$S$3,0))=1,Control!$D$81*Control!$E$81,0) -> 0 | AR77: =IF(INDEX(Control!$Q$3:$S$62,MATCH($Z77,Control!$Q$3:$Q$62,0),MATCH(AR$9,Control!$Q$3:$S$3,0))=1,INDEX(Control!$AK$3:$AO$69,MATCH(WTI!Z77,Control!$AK$3:$AK$29,0),MATCH(WTI!Y77,Control!$AK$3:$AO$3,0))/AB77*1000,0) -> 0 | AS77: =93980/AB77 -> 0.13425714 | AU77: =SUM(AI77:AT77) -> 0.33477233 | AV77: =+R77+AE77+AU77 -> 0.33477233 | AW77: =IF((MONTH(A77)=MONTH(BH77)),0,IF(((MONTH(BH77))-MONTH(A77))+12*YEAR(BG77)-YEAR(A77)>1,SUMIFS($BD$4:$BH$4,$BD$3:$BH$3,"<="&EOMONTH(BG77,-1),$BD$3:$BH$3,">="&EOMONTH(A77,0)),VLOOKUP("Spreads",$BC$3:$BH$4,MATCH(EOMONTH(A77,0),$BC$3:$BH$3,0)))) -> 2.9 | AX77: 0 | AZ77: =$AZ$75+AV77+AW77+AX77 -> 13.755321 | BC77: 4 | BD77: =IF(ISBLANK(E77),"",E77+$BC77+D77) -> 46360 | BE77: =BD77+2 -> 46362 | BF77: Dated | BG77: =EOMONTH(BE77,0) -> 46387 | BH77: =BG77 -> 46387
A78: =A77 -> 46355 | B78: =B77 -> 46357 | D78: =IF(AL78=0,0,VLOOKUP(Y78,Control!$G$41:$J$44,4,FALSE)) -> 0 | E78: =AVERAGE(A78:B78)+D78 -> 46356 | T78: =INDEX([2]Sheet1!$F$2:$AG$5,MATCH($V78,[2]Sheet1!$F$2:$F$5,0),MATCH(Z78,[2]Sheet1!$F$2:$AG$2,0)) -> 7.84 | U78: 0 | V78: Rotterdam-STS | W78: =INDEX(Vessel_Minimum_MT,MATCH(Y78,Control!$E$11:$E$15,0),MATCH(V78,Control!$E$11:$O$11,0)) -> 80000 | X78: =AB78/Control!$D$84 -> 90096.968 | Y78: Aframax | Z78: Tranmere | AA78: =IF(Z78=V78,"",CONCATENATE(CONCATENATE(VLOOKUP(V78,Zones,2,FALSE),"/",VLOOKUP(Z78,Zones,2,FALSE)))) -> Nsea/Nsea | AB78: =AB77 -> 700000 | AC78: 70 | AD78: =$AD$77 -> 150 | AE78: =IF(AC78>1000,IF(AD78=0,AC78,AD78)/AB78,((W78*T78*(IF(AD78=0,AC78,AD78)/100))+IF(X78<W78,0,(X78-W78)*T78*IF(AD78=0,AC78,AD78)/100*U78))/AB78) -> 1.344 | AF78: =$AF$52 -> 0 | AG78: =IF(AND($BC$48=1,VLOOKUP(Z78,Control!$AS$37:$AV$68,4,FALSE)<0),0,VLOOKUP(Z78,Control!$AS$37:$AV$68,4,FALSE))-$AG$75+2 -> 2 | AI78: =AF78*VLOOKUP($Y78,Control!$F$75:$H$87,3,FALSE)/$AB78 -> 0 | AJ78: =$AG78*Control!$D$77 -> 0.026072329 | AL78: =Control!$I$90/WTI!AB78 -> 0.10714286 | AM78: =IF(I78="Corpus Christi",Control!$D$76,0) -> 0 | AN78: 0 | AO78: =Control!$D$78 -> 0 | AP78: =Control!$D$79 -> 0.0673 | AQ78: =IF(INDEX(Control!$Q$3:$S$62,MATCH($Z78,Control!$Q$3:$Q$62,0),MATCH(AQ$9,Control!$Q$3:$S$3,0))=1,Control!$D$81*Control!$E$81,0) -> 0 | AR78: =IF(INDEX(Control!$Q$3:$S$62,MATCH($Z78,Control!$Q$3:$Q$62,0),MATCH(AR$9,Control!$Q$3:$S$3,0))=1,INDEX(Control!$AK$3:$AO$69,MATCH(WTI!Z78,Control!$AK$3:$AK$29,0),MATCH(WTI!Y78,Control!$AK$3:$AO$3,0))/AB78*1000,0) -> 0 | AS78: =IF(Z78="Rotterdam",0.114,"") | AU78: =SUM(AI78:AT78) -> 0.20051519 | AV78: =+R78+AE78+AU78 -> 1.5445152 | AW78: =IF((MONTH(A78)=MONTH(BH78)),0,IF(((MONTH(BH78))-MONTH(A78))+12*YEAR(BG78)-YEAR(A78)>1,SUMIFS($BD$4:$BH$4,$BD$3:$BH$3,"<="&EOMONTH(BG78,-1),$BD$3:$BH$3,">="&EOMONTH(A78,0)),VLOOKUP("Spreads",$BC$3:$BH$4,MATCH(EOMONTH(A78,0),$BC$3:$BH$3,0)))) -> 2.9 | AX78: 0 | AZ78: =$AZ$75+AV78+AW78+AX78 -> 14.965063 | BC78: 4 | BD78: =IF(ISBLANK(E78),"",E78+$BC78+D78) -> 46360 | BE78: =BD78+2 -> 46362 | BF78: Dated | BG78: =EOMONTH(BE78,0) -> 46387 | BH78: =BG78 -> 46387
A79: =A78 -> 46355 | B79: =B78 -> 46357 | D79: =IF(AL79=0,0,VLOOKUP(Y79,Control!$G$41:$J$44,4,FALSE)) -> 0 | E79: =AVERAGE(A79:B79)+D79 -> 46356 | T79: =INDEX([2]Sheet1!$F$2:$AG$5,MATCH($V79,[2]Sheet1!$F$2:$F$5,0),MATCH(Z79,[2]Sheet1!$F$2:$AG$2,0)) -> 6.37 | U79: 0 | V79: Rotterdam-STS | W79: =INDEX(Vessel_Minimum_MT,MATCH(Y79,Control!$E$11:$E$15,0),MATCH(V79,Control!$E$11:$O$11,0)) -> 80000 | X79: =AB79/Control!$D$84 -> 90096.968 | Y79: Aframax | Z79: Pembroke | AA79: =IF(Z79=V79,"",CONCATENATE(CONCATENATE(VLOOKUP(V79,Zones,2,FALSE),"/",VLOOKUP(Z79,Zones,2,FALSE)))) -> Nsea/Nsea | AB79: =AB78 -> 700000 | AC79: 70 | AD79: =$AD$77 -> 150 | AE79: =IF(AC79>1000,IF(AD79=0,AC79,AD79)/AB79,((W79*T79*(IF(AD79=0,AC79,AD79)/100))+IF(X79<W79,0,(X79-W79)*T79*IF(AD79=0,AC79,AD79)/100*U79))/AB79) -> 1.092 | AF79: =$AF$52 -> 0 | AG79: =IF(AND($BC$48=1,VLOOKUP(Z79,Control!$AS$37:$AV$68,4,FALSE)<0),0,VLOOKUP(Z79,Control!$AS$37:$AV$68,4,FALSE))-$AG$75+2 -> 2 | AI79: =AF79*VLOOKUP($Y79,Control!$F$75:$H$87,3,FALSE)/$AB79 -> 0 | AJ79: =$AG79*Control!$D$77 -> 0.026072329 | AL79: =Control!$I$90/WTI!AB79 -> 0.10714286 | AM79: =IF(I79="Corpus Christi",Control!$D$76,0) -> 0 | AN79: 0 | AO79: =Control!$D$78 -> 0 | AP79: =Control!$D$79 -> 0.0673 | AQ79: =IF(INDEX(Control!$Q$3:$S$62,MATCH($Z79,Control!$Q$3:$Q$62,0),MATCH(AQ$9,Control!$Q$3:$S$3,0))=1,Control!$D$81*Control!$E$81,0) -> 0 | AR79: =IF(INDEX(Control!$Q$3:$S$62,MATCH($Z79,Control!$Q$3:$Q$62,0),MATCH(AR$9,Control!$Q$3:$S$3,0))=1,INDEX(Control!$AK$3:$AO$69,MATCH(WTI!Z79,Control!$AK$3:$AK$29,0),MATCH(WTI!Y79,Control!$AK$3:$AO$3,0))/AB79*1000,0) -> 0 | AS79: =IF(Z79="Rotterdam",0.114,"") | AU79: =SUM(AI79:AT79) -> 0.20051519 | AV79: =+R79+AE79+AU79 -> 1.2925152 | AW79: =IF((MONTH(A79)=MONTH(BH79)),0,IF(((MONTH(BH79))-MONTH(A79))+12*YEAR(BG79)-YEAR(A79)>1,SUMIFS($BD$4:$BH$4,$BD$3:$BH$3,"<="&EOMONTH(BG79,-1),$BD$3:$BH$3,">="&EOMONTH(A79,0)),VLOOKUP("Spreads",$BC$3:$BH$4,MATCH(EOMONTH(A79,0),$BC$3:$BH$3,0)))) -> 2.9 | AX79: 0 | AZ79: =$AZ$75+AV79+AW79+AX79 -> 14.713063 | BC79: 4 | BD79: =IF(ISBLANK(E79),"",E79+$BC79+D79) -> 46360 | BE79: =BD79+2 -> 46362 | BF79: Dated | BG79: =EOMONTH(BE79,0) -> 46387 | BH79: =BG79 -> 46387
